Workbook

Sheet Main
A1: Apple | D1: Price | E1: 309
D2: Share | E2: 14598.18 | F2: Q326
D3: MC | E3: =+E2*E1 -> 4510837.6
D4: Cash | E4: 62399 | F4: Q326
D5: Debt | E5: =+11007+71340 -> 82347 | F5: Q326
D6: EV | E6: =+E3-E4+E5 -> 4530785.6
A9: P/FCF | B9: =+E3/SUM(Model!I126:L126) -> 26.657434 | D9: BETA | E9: 1.09 | G9: WACC | H9: =+(E3/(E3+E5))*E10+(E5/(E3+E5))*F11*(1-Model!Z52) -> 0.10300751 | J9: mu | K9: 0.0007926
A10: EV/EBITDA | B10: =+E6/SUM(Model!I70:L70) -> 26.975545 | D10: CAPM | E10: =+'[1]Zero-rate curve US'!J3+E9*(0.1-'[1]Zero-rate curve US'!J3) -> 0.10434567 | J10: sigma
A11: EV/FCF | B11: =+E6/SUM(Model!I126:L126) -> 26.775319 | D11: Cost of Debt | E11: =+'[1]Zero-rate curve US'!I3+(E12/100) -> 0.053294304 | F11: 0.0352
A12: Inc. Margin | D12: Cr. Spread | E12: =+'[1]Credit Spread US'!J6 -> 0.79478261
A13: P/E | B13: =+E1/SUM(Model!I42:L42) -> 35.422428 | D13: Rating | E13: AAA | F13: Aaa
A14: Leverage | B14: =+(E5-E4)/SUM(Model!I70:L70) -> 0.11876708 | E14: S&P | F14: Moody’s
A17: Products
A18: iPhone | B18: Smartphone and iOS perating system
B19: Types
B20: Pro
B21: Air
B22: Normal
B23: e
A25: Mac | B25: PC based on MacOS
B26: Macbook Air
B27: Macbook Pro
B28: Macbook Neo
B29: iMac
B30: Mac Mini
B31: Mac Studio
B32: Mac Pro | C32: ?
A34: iPad | B34: tabet based on iPadOS
B35: iPad Pro
B36: iPad Aid
B37: iPad
B38: iPad mini
A40: Wearables | B40: smartwatches, headphones, “Spatial computers”
B41: Apple Watch
B42: AirPods and Beats
B43: Apple Vision Pro (spatial computer based on VisionOS)
A44: Home
B45: Apple TV (based on tvOS)
B46: HomePod
A48: Services
B49: Advertising, Apple Care, Cloud Services (iCloud), App Store (games, music, video, …)
B50: Apple Arcade, Apple Fitness+, Apple Music, Apple News+, Apple TV
B51: Payment Services, Apple Card and Apple Pay

Sheet Model
A1: Main
A2: in Million | B2: Q124 | C2: Q224 | D2: Q324 | E2: Q424 | F2: Q125 | G2: Q225 | H2: Q325 | I2: Q425 | J2: Q126 | K2: Q226 | L2: Q326 | M2: Q426 | Q2: 2016 | R2: =+Q2+1 -> 2017 | S2: =+R2+1 -> 2018 | T2: =+S2+1 -> 2019 | U2: =+T2+1 -> 2020 | V2: =+U2+1 -> 2021 | W2: =+V2+1 -> 2022 | X2: =+W2+1 -> 2023 | Y2: =+X2+1 -> 2024 | ... AE2: =+AD2+1 -> 2030
A4: iPhone | B4: 69702 | C4: 45963 | D4: 39296 | E4: 46222 | F4: 69138 | G4: 46841 | H4: 44582 | I4: 49025 | J4: 85269 | K4: 56994 | L4: 54252 | Q4: 86613 | R4: 96600 | S4: 166699 | T4: 142381 | U4: 137781 | V4: 191973 | W4: 205489 | X4: 200583 | Y4: 201183 | Z4: 209586
A5: Y/Y | F5: =+F4/B4-1 -> -0.0080915899 | G5: =+G4/C4-1 -> 0.019102321 | H5: =+H4/D4-1 -> 0.13451751 | I5: =+I4/E4-1 -> 0.060642118 | J5: =+J4/F4-1 -> 0.23331598 | K5: =+K4/G4-1 -> 0.21675455 | L5: =+L4/H4-1 -> 0.21690368 | R5: =+R4/Q4-1 -> 0.11530602 | S5: =+S4/R4-1 -> 0.72566253 | T5: =+T4/S4-1 -> -0.1458797 | U5: =+U4/T4-1 -> -0.032307682 | V5: =+V4/U4-1 -> 0.39331983 | W5: =+W4/V4-1 -> 0.070405734 | X5: =+X4/W4-1 -> -0.023874757 | Y5: =+Y4/X4-1 -> 0.0029912804 | Z5: =+Z4/Y4-1 -> 0.041767943
A6: Mac | B6: 7780 | C6: 7451 | D6: 7009 | E6: 7744 | F6: 8987 | G6: 7949 | H6: 8046 | I6: 8726 | J6: 8386 | K6: 8399 | L6: 10352 | Q6: 49952 | R6: 54938 | S6: 18805 | T6: 25740 | U6: 28622 | V6: 35190 | W6: 40177 | X6: 29357 | Y6: 29984 | Z6: 33708
A7: Y/Y | F7: =+F6/B6-1 -> 0.15514139 | G7: =+G6/C6-1 -> 0.066836666 | H7: =+H6/D6-1 -> 0.14795263 | I7: =+I6/E6-1 -> 0.12680785 | J7: =+J6/F6-1 -> -0.066874374 | K7: =+K6/G6-1 -> 0.056610894 | L7: =+L6/H6-1 -> 0.28660204 | R7: =+R6/Q6-1 -> 0.099815823 | S7: =+S6/R6-1 -> -0.65770505 | T7: =+T6/S6-1 -> 0.3687849 | U7: =+U6/T6-1 -> 0.11196581 | V7: =+V6/U6-1 -> 0.22947383 | W7: =+W6/V6-1 -> 0.1417164 | X7: =+X6/W6-1 -> -0.26930831 | Y7: =+Y6/X6-1 -> 0.021357768 | Z7: =+Z6/Y6-1 -> 0.12419957
A8: iPad | B8: 7023 | C8: 5559 | D8: 7162 | E8: 6950 | F8: 8088 | G8: 6402 | H8: 6581 | I8: 6952 | J8: 8595 | K8: 6914 | L8: 6191 | Q8: 48492 | R8: 44764 | S8: 25484 | T8: 21280 | U8: 23724 | V8: 31862 | W8: 29292 | X8: 28300 | Y8: 26694 | Z8: 28023
A9: Y/Y | F9: =+F8/B8-1 -> 0.1516446 | G9: =+G8/C8-1 -> 0.15164598 | H9: =+H8/D8-1 -> -0.081122591 | I9: =+I8/E8-1 -> 0.00028776978 | J9: =+J8/F8-1 -> 0.06268546 | K9: =+K8/G8-1 -> 0.079975008 | L9: =+L8/H8-1 -> -0.05926151 | R9: =+R8/Q8-1 -> -0.07687866 | S9: =+S8/R8-1 -> -0.43070324 | T9: =+T8/S8-1 -> -0.16496625 | U9: =+U8/T8-1 -> 0.11484962 | V9: =+V8/U8-1 -> 0.34302816 | W9: =+W8/V8-1 -> -0.080660348 | X9: =+X8/W8-1 -> -0.033865902 | Y9: =+Y8/X8-1 -> -0.056749117 | Z9: =+Z8/Y8-1 -> 0.049786469
A10: Wearable | B10: 11953 | C10: 7913 | D10: 8097 | E10: 9042 | F10: 11747 | G10: 7522 | H10: 7404 | I10: 9013 | J10: 11493 | K10: 7901 | L10: 7883 | Q10: 16928 | R10: 17733 | S10: 37190 | T10: 24482 | U10: 30620 | V10: 38367 | W10: 41241 | X10: 39845 | Y10: 37005 | Z10: 35686
A11: Y/Y | F11: =+F10/B10-1 -> -0.017234167 | G11: =+G10/C10-1 -> -0.049412359 | H11: =+H10/D10-1 -> -0.085587255 | I11: =+I10/E10-1 -> -0.003207255 | J11: =+J10/F10-1 -> -0.021622542 | K11: =+K10/G10-1 -> 0.050385536 | L11: =+L10/H10-1 -> 0.06469476 | R11: =+R10/Q10-1 -> 0.047554348 | S11: =+S10/R10-1 -> 1.0972199 | T11: =+T10/S10-1 -> -0.34170476 | U11: =+U10/T10-1 -> 0.25071481 | V11: =+V10/U10-1 -> 0.25300457 | W11: =+W10/V10-1 -> 0.074908124 | X11: =+X10/W10-1 -> -0.03384981 | Y11: =+Y10/X10-1 -> -0.071276195 | Z11: =+Z10/Y10-1 -> -0.035643832
A12: Products | B12: =+B10+B8+B6+B4 -> 96458 | C12: =+C10+C8+C6+C4 -> 66886 | D12: =+D10+D8+D6+D4 -> 61564 | E12: =+E10+E8+E6+E4 -> 69958 | F12: =+F10+F8+F6+F4 -> 97960 | G12: =+G10+G8+G6+G4 -> 68714 | H12: =+H10+H8+H6+H4 -> 66613 | I12: =+I10+I8+I6+I4 -> 73716 | ... L12: =+L10+L8+L6+L4 -> 78678 | Q12: =+Q10+Q8+Q6+Q4 -> 201985 | R12: =+R10+R8+R6+R4 -> 214035 | S12: =+S10+S8+S6+S4 -> 248178 | T12: =+T10+T8+T6+T4 -> 213883 | U12: =+U10+U8+U6+U4 -> 220747 | V12: =+V10+V8+V6+V4 -> 297392 | W12: =+W10+W8+W6+W4 -> 316199 | X12: =+X10+X8+X6+X4 -> 298085 | ... Z12: =+Z10+Z8+Z6+Z4 -> 307003
A13: Y/Y | F13: =+F12/B12-1 -> 0.015571544 | G13: =+G12/C12-1 -> 0.027330084 | H13: =+H12/D12-1 -> 0.082012215 | I13: =+I12/E12-1 -> 0.053717945 | J13: =+J12/F12-1 -> 0.16111678 | K13: =+K12/G12-1 -> 0.16727304 | L13: =+L12/H12-1 -> 0.1811208 | R13: =+R12/Q12-1 -> 0.059657895 | S13: =+S12/R12-1 -> 0.15952064 | T13: =+T12/S12-1 -> -0.13818711 | U13: =+U12/T12-1 -> 0.032092312 | V13: =+V12/U12-1 -> 0.34720744 | W13: =+W12/V12-1 -> 0.063239764 | X13: =+X12/W12-1 -> -0.057286709 | Y13: =+Y12/X12-1 -> -0.010798933 | Z13: =+Z12/Y12-1 -> 0.04116107
A14: Services | B14: 23117 | C14: 23867 | D14: 24213 | E14: 24972 | F14: 26340 | G14: 26645 | H14: 27423 | I14: 28750 | J14: 30013 | K14: 30976 | L14: 30739 | Q14: 11132 | R14: 12863 | S14: 17417 | T14: 46291 | U14: 53768 | V14: 68425 | W14: 78129 | X14: 85200 | Y14: 96169 | Z14: 109158
A15: Y/Y | F15: =+F14/B14-1 -> 0.13942121 | G15: =+G14/C14-1 -> 0.11639502 | H15: =+H14/D14-1 -> 0.13257341 | I15: =+I14/E14-1 -> 0.15128944 | J15: =+J14/F14-1 -> 0.13944571 | K15: =+K14/G14-1 -> 0.16254457 | L15: =+L14/H14-1 -> 0.1209204 | R15: =+R14/Q14-1 -> 0.15549766 | S15: =+S14/R14-1 -> 0.35403872 | T15: =+T14/S14-1 -> 1.6578056 | U15: =+U14/T14-1 -> 0.16152168 | V15: =+V14/U14-1 -> 0.27259708 | W15: =+W14/V14-1 -> 0.14181951 | X15: =+X14/W14-1 -> 0.090504166 | Y15: =+Y14/X14-1 -> 0.12874413 | Z15: =+Z14/Y14-1 -> 0.13506431
A16: Revenue | B16: =+B14+B12 -> 119575 | C16: =+C14+C12 -> 90753 | D16: =+D14+D12 -> 85777 | E16: =+E14+E12 -> 94930 | F16: =+F14+F12 -> 124300 | G16: =+G14+G12 -> 95359 | H16: =+H14+H12 -> 94036 | I16: =+I14+I12 -> 102466 | ... L16: =+L14+L12 -> 109417 | Q16: =+Q14+Q12 -> 213117 | R16: =+R14+R12 -> 226898 | S16: =+S14+S12 -> 265595 | T16: =+T14+T12 -> 260174 | U16: =+U14+U12 -> 274515 | V16: =+V14+V12 -> 365817 | W16: =+W14+W12 -> 394328 | X16: =+X14+X12 -> 383285 | ... Z16: =+Z14+Z12 -> 416161 | AA16: =+Z16*1.08 -> 449453.88 | AB16: =+AA16*1.06 -> 476421.11 | AC16: =+AB16*1.06 -> 505006.38 | AD16: =+AC16*1.06 -> 535306.76 | AE16: =+AD16*1.06 -> 567425.17
A17: Y/Y | F17: =+F16/B16-1 -> 0.039514949 | G17: =+G16/C16-1 -> 0.050753143 | H17: =+H16/D16-1 -> 0.096284552 | I17: =+I16/E16-1 -> 0.07938481 | J17: =+J16/F16-1 -> 0.15652454 | K17: =+K16/G16-1 -> 0.16595182 | L17: =+L16/H16-1 -> 0.16356502 | R17: =+R16/Q16-1 -> 0.064664011 | S17: =+S16/R16-1 -> 0.170548 | T17: =+T16/S16-1 -> -0.020410776 | U17: =+U16/T16-1 -> 0.055120804 | V17: =+V16/U16-1 -> 0.33259385 | W17: =+W16/V16-1 -> 0.077937876 | X17: =+X16/W16-1 -> -0.028004605 | Y17: =+Y16/X16-1 -> 0.020219941 | ... AE17: =+AE16/AD16-1 -> 0.06
A18: Products COGS | B18: 58440 | C18: 42424 | D18: 39803 | E18: 44566 | F18: 59447 | G18: 44030 | H18: 43620 | I18: 47019 | J18: 67478 | K18: 49179 | L18: 47153 | T18: 144996 | U18: 151286 | V18: 192266 | W18: 201471 | X18: 189282 | Y18: 185233 | Z18: 194116
A19: % COGS | B19: =+B18/B22 -> 0.90296663 | C19: =+C18/C22 -> 0.87504641 | D19: =+D18/D22 -> 0.86342437 | E19: =+E18/E22 -> 0.87297017 | F19: =+F18/F22 -> 0.90037107 | G19: =+G18/G22 -> 0.87201933 | H19: =+H18/H22 -> 0.8668866 | I19: =+I18/I22 -> 0.86871132 | ... L19: =+L18/L22 -> 0.8628653 | Q19: =+Q18/Q22 -> 0 | R19: =+R18/R22 -> 0 | S19: =+S18/S22 -> 0 | T19: =+T18/T22 -> 0.89624309 | U19: =+U18/U22 -> 0.8922322 | V19: =+V18/V22 -> 0.9027378 | W19: =+W18/W22 -> 0.90125075 | X19: =+X18/X22 -> 0.88392945 | ... Z19: =+Z18/Z22 -> 0.87851195
A20: Services COGS | B20: 6280 | C20: 6058 | D20: 6296 | E20: 6485 | F20: 6578 | G20: 6462 | H20: 6698 | I20: 7106 | J20: 7047 | K20: 7224 | L20: 7494 | T20: 16786 | U20: 18273 | V20: 20715 | W20: 22075 | X20: 24855 | Y20: 25119 | Z20: 26844
A21: % COGS | B21: =+B20/B22 -> 0.097033375 | C21: =+C20/C22 -> 0.12495359 | D21: =+D20/D22 -> 0.13657563 | E21: =+E20/E22 -> 0.12702983 | F21: =+F20/F22 -> 0.099628928 | G21: =+G20/G22 -> 0.12798067 | H21: =+H20/H22 -> 0.1331134 | I21: =+I20/I22 -> 0.13128868 | ... L21: =+L20/L22 -> 0.1371347 | Q21: =+Q20/Q24 -> 0 | R21: =+R20/R24 -> 0 | S21: =+S20/S24 -> 0 | T21: =+T20/T24 -> 0.1706033 | U21: =+U20/U24 -> 0.17410153 | V21: =+V20/V24 -> 0.13553744 | W21: =+W20/W24 -> 0.12925835 | X21: =+X20/X24 -> 0.14694232 | ... Z21: =+Z20/Z24 -> 0.13751979
A22: COGS | B22: =+B20+B18 -> 64720 | C22: =+C20+C18 -> 48482 | D22: =+D20+D18 -> 46099 | E22: =+E20+E18 -> 51051 | F22: =+F20+F18 -> 66025 | G22: =+G20+G18 -> 50492 | H22: =+H20+H18 -> 50318 | I22: =+I20+I18 -> 54125 | ... L22: =+L20+L18 -> 54647 | Q22: 131376 | R22: 141048 | S22: 163756 | T22: =+T20+T18 -> 161782 | U22: =+U20+U18 -> 169559 | V22: =+V20+V18 -> 212981 | W22: =+W20+W18 -> 223546 | X22: =+X20+X18 -> 214137 | Y22: =+Y20+Y18 -> 210352 | Z22: =+Z20+Z18 -> 220960 | AA22: =+AA16-AA24 -> 238210.56 | AB22: =+AB16-AB24 -> 250121.08 | AC22: =+AC16-AC24 -> 262603.32 | AD22: =+AD16-AD24 -> 275682.98 | AE22: =+AE16-AE24 -> 289386.84
A23: % Rev | B23: =+B22/B$16 -> 0.54125026 | C23: =+C22/C$16 -> 0.53421925 | D23: =+D22/D$16 -> 0.53742845 | E23: =+E22/E$16 -> 0.5377752 | F23: =+F22/F$16 -> 0.53117458 | G23: =+G22/G$16 -> 0.52949381 | H23: =+H22/H$16 -> 0.53509294 | I23: =+I22/I$16 -> 0.528224 | ... L23: =+L22/L$16 -> 0.49943793 | Q23: =+Q22/Q$16 -> 0.61645012 | R23: =+R22/R$16 -> 0.62163615 | S23: =+S22/S$16 -> 0.61656281 | T23: =+T22/T$16 -> 0.62182232 | U23: =+U22/U$16 -> 0.61766752 | V23: =+V22/V$16 -> 0.5822064 | W23: =+W22/W$16 -> 0.56690369 | X23: =+X22/X$16 -> 0.5586887 | ... AE23: =+AE22/AE$16 -> 0.51
A24: Gross Profit | B24: =+B16-B22 -> 54855 | C24: =+C16-C22 -> 42271 | D24: =+D16-D22 -> 39678 | E24: =+E16-E22 -> 43879 | F24: =+F16-F22 -> 58275 | G24: =+G16-G22 -> 44867 | H24: =+H16-H22 -> 43718 | I24: =+I16-I22 -> 48341 | ... L24: =+L16-L22 -> 54770 | Q24: =+Q16-Q22 -> 81741 | R24: =+R16-R22 -> 85850 | S24: =+S16-S22 -> 101839 | T24: =+T16-T22 -> 98392 | U24: =+U16-U22 -> 104956 | V24: =+V16-V22 -> 152836 | W24: =+W16-W22 -> 170782 | X24: =+X16-X22 -> 169148 | ... Z24: =+Z16-Z22 -> 195201 | AA24: =+AA16*0.47 -> 211243.32 | AB24: =+AB16*0.475 -> 226300.03 | AC24: =+AC16*0.48 -> 242403.06 | AD24: =+AD16*0.485 -> 259623.78 | AE24: =+AE16*0.49 -> 278038.33
A25: % Rev | B25: =+B24/B$16 -> 0.45874974 | C25: =+C24/C$16 -> 0.46578075 | D25: =+D24/D$16 -> 0.46257155 | E25: =+E24/E$16 -> 0.4622248 | F25: =+F24/F$16 -> 0.46882542 | G25: =+G24/G$16 -> 0.47050619 | H25: =+H24/H$16 -> 0.46490706 | I25: =+I24/I$16 -> 0.471776 | ... L25: =+L24/L$16 -> 0.50056207 | Q25: =+Q24/Q$16 -> 0.38354988 | R25: =+R24/R$16 -> 0.37836385 | S25: =+S24/S$16 -> 0.38343719 | T25: =+T24/T$16 -> 0.37817768 | U25: =+U24/U$16 -> 0.38233248 | V25: =+V24/V$16 -> 0.4177936 | W25: =+W24/W$16 -> 0.43309631 | X25: =+X24/X$16 -> 0.4413113 | ... AE25: =+AE24/AE$16 -> 0.49
A26: R&D | B26: 7696 | C26: 7903 | D26: 8006 | E26: 7765 | F26: 8268 | G26: 8550 | H26: 8866 | I26: 8866 | J26: 10887 | K26: 11419 | L26: 11729 | Q26: 10045 | R26: 11581 | S26: 14236 | T26: 16217 | U26: 18752 | V26: 21914 | W26: 26251 | X26: 29915 | Y26: 31370 | Z26: 34550 | AA26: =+AA16*0.08 -> 35956.31 | AB26: =+AB16*0.08 -> 38113.689 | AC26: =+AC16*0.076 -> 38380.485 | AD26: =+AD16*0.076 -> 40683.314 | AE26: =+AE16*0.076 -> 43124.313
A27: % Rev | B27: =+B26/B$16 -> 0.06436128 | C27: =+C26/C$16 -> 0.087082521 | D27: =+D26/D$16 -> 0.093335043 | E27: =+E26/E$16 -> 0.081797114 | F27: =+F26/F$16 -> 0.066516492 | G27: =+G26/G$16 -> 0.089661175 | H27: =+H26/H$16 -> 0.094283041 | I27: =+I26/I$16 -> 0.086526262 | ... L27: =+L26/L$16 -> 0.10719541 | Q27: =+Q26/Q$16 -> 0.047133734 | R27: =+R26/R$16 -> 0.051040556 | S27: =+S26/S$16 -> 0.053600407 | T27: =+T26/T$16 -> 0.062331363 | U27: =+U26/U$16 -> 0.068309564 | V27: =+V26/V$16 -> 0.059904269 | W27: =+W26/W$16 -> 0.066571484 | X27: =+X26/X$16 -> 0.078048971 | ... AE27: =+AE26/AE$16 -> 0.076
A28: SG&A | B28: 6786 | C28: 6468 | D28: 6320 | E28: 6523 | F28: 7175 | G28: 6728 | H28: 6650 | I28: 7048 | J28: 7492 | K28: 7477 | L28: 7346 | Q28: 14194 | R28: 15261 | S28: 16705 | T28: 18245 | U28: 19916 | V28: 21973 | W28: 25094 | X28: 24932 | Y28: 26097 | Z28: 27601 | AA28: =+AA16*0.065 -> 29214.502 | AB28: =+AB16*0.065 -> 30967.372 | AC28: =+AC16*0.063 -> 31815.402 | AD28: =+AD16*0.063 -> 33724.326 | AE28: =+AE16*0.063 -> 35747.786
A29: % Rev | B29: =+B28/B$16 -> 0.056750993 | C29: =+C28/C$16 -> 0.071270371 | D29: =+D28/D$16 -> 0.073679425 | E29: =+E28/E$16 -> 0.068713789 | F29: =+F28/F$16 -> 0.05772325 | G29: =+G28/G$16 -> 0.070554431 | H29: =+H28/H$16 -> 0.070717598 | I29: =+I28/I$16 -> 0.068783792 | ... L29: =+L28/L$16 -> 0.067137648 | Q29: =+Q28/Q$16 -> 0.066601914 | R29: =+R28/R$16 -> 0.067259297 | S29: =+S28/S$16 -> 0.062896515 | T29: =+T28/T$16 -> 0.070126146 | U29: =+U28/U$16 -> 0.07254977 | V29: =+V28/V$16 -> 0.060065552 | W29: =+W28/W$16 -> 0.063637378 | X29: =+X28/X$16 -> 0.065048202 | ... AE29: =+AE28/AE$16 -> 0.063
A30: OP Exp. | B30: =+B28+B26 -> 14482 | C30: =+C28+C26 -> 14371 | D30: =+D28+D26 -> 14326 | E30: =+E28+E26 -> 14288 | F30: =+F28+F26 -> 15443 | G30: =+G28+G26 -> 15278 | H30: =+H28+H26 -> 15516 | I30: =+I28+I26 -> 15914 | ... L30: =+L28+L26 -> 19075 | Q30: =+Q28+Q26 -> 24239 | R30: =+R28+R26 -> 26842 | S30: =+S28+S26 -> 30941 | T30: =+T28+T26 -> 34462 | U30: =+U28+U26 -> 38668 | V30: =+V28+V26 -> 43887 | W30: =+W28+W26 -> 51345 | X30: =+X28+X26 -> 54847 | ... Z30: =+Z28+Z26 -> 62151 | AA30: =+AA16*0.14 -> 62923.543 | AB30: =+AB16*0.14 -> 66698.956 | AC30: =+AC16*0.135 -> 68175.861 | AD30: =+AD16*0.135 -> 72266.413 | AE30: =+AE16*0.135 -> 76602.398
A31: % Rev | B31: =+B30/B$16 -> 0.12111227 | C31: =+C30/C$16 -> 0.15835289 | D31: =+D30/D$16 -> 0.16701447 | E31: =+E30/E$16 -> 0.1505109 | F31: =+F30/F$16 -> 0.12423974 | G31: =+G30/G$16 -> 0.16021561 | H31: =+H30/H$16 -> 0.16500064 | I31: =+I30/I$16 -> 0.15531005 | ... L31: =+L30/L$16 -> 0.17433306 | Q31: =+Q30/Q$16 -> 0.11373565 | R31: =+R30/R$16 -> 0.11829985 | S31: =+S30/S$16 -> 0.11649692 | T31: =+T30/T$16 -> 0.13245751 | U31: =+U30/U$16 -> 0.14085933 | V31: =+V30/V$16 -> 0.11996982 | W31: =+W30/W$16 -> 0.13020886 | X31: =+X30/X$16 -> 0.14309717 | ... AE31: =+AE30/AE$16 -> 0.135
A32: EBIT | B32: =+B24-B30 -> 40373 | C32: =+C24-C30 -> 27900 | D32: =+D24-D30 -> 25352 | E32: =+E24-E30 -> 29591 | F32: =+F24-F30 -> 42832 | G32: =+G24-G30 -> 29589 | H32: =+H24-H30 -> 28202 | I32: =+I24-I30 -> 32427 | ... L32: =+L24-L30 -> 35695 | Q32: =+Q24-Q30 -> 57502 | R32: =+R24-R30 -> 59008 | S32: =+S24-S30 -> 70898 | T32: =+T24-T30 -> 63930 | U32: =+U24-U30 -> 66288 | V32: =+V24-V30 -> 108949 | W32: =+W24-W30 -> 119437 | X32: =+X24-X30 -> 114301 | ... AE32: =+AE24-AE30 -> 201435.93
A33: % Rev | B33: =+B32/B$16 -> 0.33763747 | C33: =+C32/C$16 -> 0.30742785 | D33: =+D32/D$16 -> 0.29555708 | E33: =+E32/E$16 -> 0.31171389 | F33: =+F32/F$16 -> 0.34458568 | G33: =+G32/G$16 -> 0.31029059 | H33: =+H32/H$16 -> 0.29990642 | I33: =+I32/I$16 -> 0.31646595 | ... L33: =+L32/L$16 -> 0.32622901 | Q33: =+Q32/Q$16 -> 0.26981423 | R33: =+R32/R$16 -> 0.26006399 | S33: =+S32/S$16 -> 0.26694027 | T33: =+T32/T$16 -> 0.24572017 | U33: =+U32/U$16 -> 0.24147314 | V33: =+V32/V$16 -> 0.29782378 | W33: =+W32/W$16 -> 0.30288744 | X33: =+X32/X$16 -> 0.29821412 | ... AE33: =+AE32/AE$16 -> 0.355
A34: Other Income | B34: -50 | C34: 158 | D34: 142 | E34: 19 | F34: -248 | G34: -279 | H34: -171 | I34: 377 | J34: 150 | K34: -52 | L34: 572 | Q34: 1348 | R34: 2745 | S34: 2005 | T34: 1807 | U34: 803 | V34: 258 | W34: -334 | X34: -565 | Y34: 269 | Z34: -321 | AA34: 200 | AB34: 200 | AC34: 200 | AD34: 200 | AE34: 200
A35: % Rev | B35: =+B34/B$16 -> -0.00041814761 | C35: =+C34/C$16 -> 0.0017409893 | D35: =+D34/D$16 -> 0.0016554554 | E35: =+E34/E$16 -> 0.00020014748 | F35: =+F34/F$16 -> -0.001995173 | G35: =+G34/G$16 -> -0.0029257857 | H35: =+H34/H$16 -> -0.0018184525 | I35: =+I34/I$16 -> 0.0036792692 | ... L35: =+L34/L$16 -> 0.0052277068 | Q35: =+Q34/Q$16 -> 0.0063251641 | R35: =+R34/R$16 -> 0.012097947 | S35: =+S34/S$16 -> 0.0075490879 | T35: =+T34/T$16 -> 0.006945352 | U35: =+U34/U$16 -> 0.0029251589 | V35: =+V34/V$16 -> 0.00070527067 | W35: =+W34/W$16 -> -0.00084701061 | X35: =+X34/X$16 -> -0.0014740989 | ... AE35: =+AE34/AE$16 -> 0.00035246938
A36: EBT | B36: =+B32+B34 -> 40323 | C36: =+C32+C34 -> 28058 | D36: =+D32+D34 -> 25494 | E36: =+E32+E34 -> 29610 | F36: =+F32+F34 -> 42584 | G36: =+G32+G34 -> 29310 | H36: =+H32+H34 -> 28031 | I36: =+I32+I34 -> 32804 | ... L36: =+L32+L34 -> 36267 | Q36: =+Q32+Q34 -> 58850 | R36: =+R32+R34 -> 61753 | S36: =+S32+S34 -> 72903 | T36: =+T32+T34 -> 65737 | U36: =+U32+U34 -> 67091 | V36: =+V32+V34 -> 109207 | W36: =+W32+W34 -> 119103 | X36: =+X32+X34 -> 113736 | ... AE36: =+AE32+AE34 -> 201635.93
A37: % Rev | B37: =+B36/B$16 -> 0.33721932 | C37: =+C36/C$16 -> 0.30916884 | D37: =+D36/D$16 -> 0.29721254 | E37: =+E36/E$16 -> 0.31191404 | F37: =+F36/F$16 -> 0.34259051 | G37: =+G36/G$16 -> 0.3073648 | H37: =+H36/H$16 -> 0.29808797 | I37: =+I36/I$16 -> 0.32014522 | ... L37: =+L36/L$16 -> 0.33145672 | Q37: =+Q36/Q$16 -> 0.2761394 | R37: =+R36/R$16 -> 0.27216194 | S37: =+S36/S$16 -> 0.27448935 | T37: =+T36/T$16 -> 0.25266552 | U37: =+U36/U$16 -> 0.2443983 | V37: =+V36/V$16 -> 0.29852905 | W37: =+W36/W$16 -> 0.30204043 | X37: =+X36/X$16 -> 0.29674002 | ... AE37: =+AE36/AE$16 -> 0.35535247
A38: Taxes | B38: 6407 | C38: 4422 | D38: 4046 | E38: 14874 | F38: 6254 | G38: 4530 | H38: 4597 | I38: 5338 | J38: 8905 | K38: 6255 | L38: 6478 | Q38: 15685 | R38: 15738 | S38: 13372 | T38: 10481 | U38: 9680 | V38: 14527 | W38: 19300 | X38: 16741 | Y38: 29749 | Z38: 20719 | AA38: =+AA36*0.15 -> 22277.967 | AB38: =+AB36*0.15 -> 23970.161 | AC38: =+AC36*0.15 -> 26164.08 | AD38: =+AD36*0.15 -> 28133.605 | AE38: =+AE36*0.15 -> 30245.39
A39: % Rev | B39: =+B38/B$16 -> 0.053581434 | C39: =+C38/C$16 -> 0.048725662 | D39: =+D38/D$16 -> 0.047168821 | E39: =+E38/E$16 -> 0.15668387 | F39: =+F38/F$16 -> 0.050313757 | G39: =+G38/G$16 -> 0.047504693 | H39: =+H38/H$16 -> 0.048885533 | I39: =+I38/I$16 -> 0.052095329 | ... L39: =+L38/L$16 -> 0.059204694 | Q39: =+Q38/Q$16 -> 0.073598071 | R39: =+R38/R$16 -> 0.069361563 | S39: =+S38/S$16 -> 0.050347333 | T39: =+T38/T$16 -> 0.040284579 | U39: =+U38/U$16 -> 0.03526219 | V39: =+V38/V$16 -> 0.039711112 | W39: =+W38/W$16 -> 0.048944026 | X39: =+X38/X$16 -> 0.043677681 | ... AE39: =+AE38/AE$16 -> 0.05330287
A40: Net Income | B40: =+B36-B38 -> 33916 | C40: =+C36-C38 -> 23636 | D40: =+D36-D38 -> 21448 | E40: =+E36-E38 -> 14736 | F40: =+F36-F38 -> 36330 | G40: =+G36-G38 -> 24780 | H40: =+H36-H38 -> 23434 | I40: =+I36-I38 -> 27466 | ... L40: =+L36-L38 -> 29789 | Q40: =+Q36-Q38 -> 43165 | R40: =+R36-R38 -> 46015 | S40: =+S36-S38 -> 59531 | T40: =+T36-T38 -> 55256 | U40: =+U36-U38 -> 57411 | V40: =+V36-V38 -> 94680 | W40: =+W36-W38 -> 99803 | X40: =+X36-X38 -> 96995 | ... AE40: =+AE36-AE38 -> 171390.54
A41: % Rev | B41: =+B40/B$16 -> 0.28363788 | C41: =+C40/C$16 -> 0.26044318 | D41: =+D40/D$16 -> 0.25004372 | E41: =+E40/E$16 -> 0.15523017 | F41: =+F40/F$16 -> 0.29227675 | G41: =+G40/G$16 -> 0.25986011 | H41: =+H40/H$16 -> 0.24920243 | I41: =+I40/I$16 -> 0.26804989 | ... L41: =+L40/L$16 -> 0.27225203 | Q41: =+Q40/Q$16 -> 0.20254133 | R41: =+R40/R$16 -> 0.20280038 | S41: =+S40/S$16 -> 0.22414202 | T41: =+T40/T$16 -> 0.21238095 | U41: =+U40/U$16 -> 0.20913611 | V41: =+V40/V$16 -> 0.25881793 | W41: =+W40/W$16 -> 0.25309641 | X41: =+X40/X$16 -> 0.25306234 | ... AE41: =+AE40/AE$16 -> 0.3020496
A42: EPS | B42: =+B40/B44 -> 2.1773629 | C42: =+C40/C44 -> 1.5283831 | D42: =+D40/D44 -> 1.39743 | E42: =+E40/E44 -> 0.96674815 | F42: =+F40/F44 -> 2.3978829 | G42: =+G40/G44 -> 1.6458409 | H42: =+H40/H44 -> 1.5676826 | I42: =+I40/I44 -> 1.8478688 | ... L42: =+L40/L44 -> 2.0244414 | Q42: =+Q40/Q44 -> 7.8477809 | R42: =+R40/R44 -> 8.7619381 | S42: =+S40/S44 -> 11.90594 | T42: =+T40/T44 -> 2.9714475 | U42: =+U40/U44 -> 3.275348 | V42: =+V40/V44 -> 5.6140204 | W42: =+W40/W44 -> 6.1132002 | X42: =+X40/X44 -> 6.1340529 | ... AE42: =+AE40/AE44 -> 12.636571
F43: =+F42/B42-1 -> 0.10127848 | G43: =+G42/C42-1 -> 0.076851037 | H43: =+H42/D42-1 -> 0.12183265 | I43: =+I42/E42-1 -> 0.91142733 | J43: =+J42/F42-1 -> 0.18538023 | K43: =+K42/G42-1 -> 0.22039352 | L43: =+L42/H42-1 -> 0.29135927 | R43: =+R42/Q42-1 -> 0.11648607 | S43: =+S42/R42-1 -> 0.358825 | T43: =+T42/S42-1 -> -0.75042312 | U43: =+U42/T42-1 -> 0.10227356 | V43: =+V42/U42-1 -> 0.7140226 | W43: =+W42/V42-1 -> 0.088916627 | X43: =+X42/W42-1 -> 0.0034110959 | Y43: =+Y42/X42-1 -> -0.0082323196 | ... AE43: =+AE42/AD42-1 -> 0.097002785
A44: Shares | B44: 15576.641 | C44: 15464.709 | D44: 15348.175 | E44: 15242.853 | F44: 15150.865 | G44: 15056.133 | H44: 14948.179 | I44: 14863.609 | J44: 14810.356 | K44: 14725.873 | L44: 14714.676 | Q44: 5500.281 | R44: 5251.692 | S44: 5000.109 | T44: 18595.651 | U44: 17528.214 | V44: 16864.919 | W44: 16325.819 | X44: 15812.547 | Y44: 15408.095 | Z44: 15004.697 | AA44: =+Z44*0.98 -> 14704.603 | AB44: =+AA44*0.98 -> 14410.511 | AC44: =+AB44*0.98 -> 14122.301 | AD44: =+AC44*0.98 -> 13839.855 | AE44: =+AD44*0.98 -> 13563.058
C45: =+C44/B44-1 -> -0.0071858882 | D45: =+D44/C44-1 -> -0.0075354797 | E45: =+E44/D44-1 -> -0.0068621839 | F45: =+F44/E44-1 -> -0.0060348283 | G45: =+G44/F44-1 -> -0.0062525803 | H45: =+H44/G44-1 -> -0.0071701014 | I45: =+I44/H44-1 -> -0.0056575453 | J45: =+J44/I44-1 -> -0.0035827772 | ... L45: =+L44/K44-1 -> -0.00076036239 | R45: =+R44/Q44-1 -> -0.045195691 | S45: =+S44/R44-1 -> -0.047905132 | T45: =+T44/S44-1 -> 2.7190491 | U45: =+U44/T44-1 -> -0.057402508 | V45: =+V44/U44-1 -> -0.037841562 | W45: =+W44/V44-1 -> -0.031965763 | X45: =+X44/W44-1 -> -0.03143928 | Y45: =+Y44/X44-1 -> -0.025577916 | ... AE45: =+AE44/AD44-1 -> -0.02
A48: Revenue | F48: =+F16/B16-1 -> 0.039514949 | G48: =+G16/C16-1 -> 0.050753143 | H48: =+H16/D16-1 -> 0.096284552 | I48: =+I16/E16-1 -> 0.07938481 | J48: =+J16/F16-1 -> 0.15652454 | K48: =+K16/G16-1 -> 0.16595182 | L48: =+L16/H16-1 -> 0.16356502 | R48: =+R16/Q16-1 -> 0.064664011 | S48: =+S16/R16-1 -> 0.170548 | T48: =+T16/S16-1 -> -0.020410776 | U48: =+U16/T16-1 -> 0.055120804 | V48: =+V16/U16-1 -> 0.33259385 | W48: =+W16/V16-1 -> 0.077937876 | X48: =+X16/W16-1 -> -0.028004605 | Y48: =+Y16/X16-1 -> 0.020219941 | ... AE48: =+AE16/AD16-1 -> 0.06
A49: Gross Margin | B49: =+B24/B16 -> 0.45874974 | C49: =+C24/C16 -> 0.46578075 | D49: =+D24/D16 -> 0.46257155 | E49: =+E24/E16 -> 0.4622248 | F49: =+F24/F16 -> 0.46882542 | G49: =+G24/G16 -> 0.47050619 | H49: =+H24/H16 -> 0.46490706 | I49: =+I24/I16 -> 0.471776 | ... L49: =+L24/L16 -> 0.50056207 | Q49: =+Q24/Q16 -> 0.38354988 | R49: =+R24/R16 -> 0.37836385 | S49: =+S24/S16 -> 0.38343719 | T49: =+T24/T16 -> 0.37817768 | U49: =+U24/U16 -> 0.38233248 | V49: =+V24/V16 -> 0.4177936 | W49: =+W24/W16 -> 0.43309631 | X49: =+X24/X16 -> 0.4413113 | ... AE49: =+AE24/AE16 -> 0.49
A50: OP Margin | B50: =+B32/B16 -> 0.33763747 | C50: =+C32/C16 -> 0.30742785 | D50: =+D32/D16 -> 0.29555708 | E50: =+E32/E16 -> 0.31171389 | F50: =+F32/F16 -> 0.34458568 | G50: =+G32/G16 -> 0.31029059 | H50: =+H32/H16 -> 0.29990642 | I50: =+I32/I16 -> 0.31646595 | ... L50: =+L32/L16 -> 0.32622901 | Q50: =+Q32/Q16 -> 0.26981423 | R50: =+R32/R16 -> 0.26006399 | S50: =+S32/S16 -> 0.26694027 | T50: =+T32/T16 -> 0.24572017 | U50: =+U32/U16 -> 0.24147314 | V50: =+V32/V16 -> 0.29782378 | W50: =+W32/W16 -> 0.30288744 | X50: =+X32/X16 -> 0.29821412 | ... AE50: =+AE32/AE16 -> 0.355
A51: NI Margin | B51: =+B40/B16 -> 0.28363788 | C51: =+C40/C16 -> 0.26044318 | D51: =+D40/D16 -> 0.25004372 | E51: =+E40/E16 -> 0.15523017 | F51: =+F40/F16 -> 0.29227675 | G51: =+G40/G16 -> 0.25986011 | H51: =+H40/H16 -> 0.24920243 | I51: =+I40/I16 -> 0.26804989 | ... L51: =+L40/L16 -> 0.27225203 | Q51: =+Q40/Q16 -> 0.20254133 | R51: =+R40/R16 -> 0.20280038 | S51: =+S40/S16 -> 0.22414202 | T51: =+T40/T16 -> 0.21238095 | U51: =+U40/U16 -> 0.20913611 | V51: =+V40/V16 -> 0.25881793 | W51: =+W40/W16 -> 0.25309641 | X51: =+X40/X16 -> 0.25306234 | ... AE51: =+AE40/AE16 -> 0.3020496
A52: Tax Rate | B52: =+B38/B36 -> 0.15889195 | C52: =+C38/C36 -> 0.15760211 | D52: =+D38/D36 -> 0.15870401 | E52: =+E38/E36 -> 0.50233029 | F52: =+F38/F36 -> 0.14686267 | G52: =+G38/G36 -> 0.15455476 | H52: =+H38/H36 -> 0.163997 | I52: =+I38/I36 -> 0.16272406 | ... L52: =+L38/L36 -> 0.17861968 | Q52: =+Q38/Q36 -> 0.26652506 | R52: =+R38/R36 -> 0.25485402 | S52: =+S38/S36 -> 0.18342181 | T52: =+T38/T36 -> 0.15943837 | U52: =+U38/U36 -> 0.14428165 | V52: =+V38/V36 -> 0.13302261 | W52: =+W38/W36 -> 0.16204462 | X52: =+X38/X36 -> 0.14719174 | ... AE52: =+AE38/AE36 -> 0.15
A54: Inc Margin | I54: =+(SUM(F32:I32)-SUM(B32:E32))/(SUM(F16:I16)-SUM(B16:E16)) -> 0.39138741 | J54: =+(SUM(G32:J32)-SUM(C32:F32))/(SUM(G16:J16)-SUM(C16:F16)) -> 0.38625586 | K54: =+(SUM(H32:K32)-SUM(D32:G32))/(SUM(H16:K16)-SUM(D16:G16)) -> 0.3916125 | L54: =+(SUM(I32:L32)-SUM(E32:H32))/(SUM(I16:L16)-SUM(E16:H16)) -> 0.42346816 | R54: =+(R32-Q32)/(R16-Q16) -> 0.10928089 | S54: =+(S32-R32)/(S16-R16) -> 0.30725896 | T54: =+(T32-S32)/(T16-S16) -> 1.2853717 | U54: =+(U32-T32)/(U16-T16) -> 0.16442368 | V54: =+(V32-U32)/(V16-U16) -> 0.46725154 | W54: =+(W32-V32)/(W16-V16) -> 0.36785802 | X54: =+(X32-W32)/(X16-W16) -> 0.46509101 | Y54: =+(Y32-X32)/(Y16-X16) -> 1.1503226 | ... AE54: =+(AE32-AD32)/(AE16-AD16) -> 0.43833333
AL55: GGM
A56: iPhone % Rev | B56: =+B4/B$16 -> 0.58291449 | C56: =+C4/C$16 -> 0.5064626 | D56: =+D4/D$16 -> 0.45811814 | E56: =+E4/E$16 -> 0.48690614 | F56: =+F4/F$16 -> 0.55621883 | G56: =+G4/G$16 -> 0.49120691 | H56: =+H4/H$16 -> 0.47409503 | I56: =+I4/I$16 -> 0.47845139 | ... L56: =+L4/L$16 -> 0.49582789 | Q56: =+Q4/Q$16 -> 0.40641056 | R56: =+R4/R$16 -> 0.42574196 | S56: =+S4/S$16 -> 0.62764359 | T56: =+T4/T$16 -> 0.54725299 | U56: =+U4/U$16 -> 0.501907 | V56: =+V4/V$16 -> 0.52477878 | W56: =+W4/W$16 -> 0.52111187 | X56: =+X4/X$16 -> 0.52332598 | ... Z56: =+Z4/Z$16 -> 0.50361759 | AL56: Net Payout | AM56: =+SUM(I147:L147)/SUM(I40:L40) -> 0.75906306
A57: Mac % Rev | B57: =+B6/B$16 -> 0.065063768 | C57: =+C6/C$16 -> 0.082101969 | D57: =+D6/D$16 -> 0.081711881 | E57: =+E6/E$16 -> 0.081575898 | F57: =+F6/F$16 -> 0.072300885 | G57: =+G6/G$16 -> 0.083358676 | H57: =+H6/H$16 -> 0.085562976 | I57: =+I6/I$16 -> 0.085159955 | ... L57: =+L6/L$16 -> 0.094610527 | Q57: =+Q6/Q$16 -> 0.23438768 | R57: =+R6/R$16 -> 0.24212642 | S57: =+S6/S$16 -> 0.070803291 | T57: =+T6/T$16 -> 0.09893379 | U57: =+U6/U$16 -> 0.10426388 | V57: =+V6/V$16 -> 0.096195639 | W57: =+W6/W$16 -> 0.10188726 | X57: =+X6/X$16 -> 0.076593136 | ... Z57: =+Z6/Z$16 -> 0.080997499 | AL57: Sustained Growth | AM57: =+(1-AM56)*L64 -> 0.26829539
A58: iPad & Rev | B58: =+B8/B$16 -> 0.058733013 | C58: =+C8/C$16 -> 0.061254173 | D58: =+D8/D$16 -> 0.083495576 | E58: =+E8/E$16 -> 0.07321184 | F58: =+F8/F$16 -> 0.065068383 | G58: =+G8/G$16 -> 0.067135771 | H58: =+H8/H$16 -> 0.069983836 | I58: =+I8/I$16 -> 0.067846896 | ... L58: =+L8/L$16 -> 0.056581701 | Q58: =+Q8/Q$16 -> 0.22753699 | R58: =+R8/R$16 -> 0.19728689 | S58: =+S8/S$16 -> 0.095950601 | T58: =+T8/T$16 -> 0.081791417 | U58: =+U8/U$16 -> 0.086421507 | V58: =+V8/V$16 -> 0.087098194 | W58: =+W8/W$16 -> 0.074283338 | X58: =+X8/X$16 -> 0.073835397 | ... Z58: =+Z8/Z$16 -> 0.06733692 | AL58: Equity Value | AM58: =+(SUM(I147:L147)*(1+0.07))/(Main!H9-0.07) -> 3172508.6
A59: Wearable % Rev | B59: =+B10/B$16 -> 0.099962367 | C59: =+C10/C$16 -> 0.08719271 | D59: =+D10/D$16 -> 0.094395934 | E59: =+E10/E$16 -> 0.095249131 | F59: =+F10/F$16 -> 0.094505229 | G59: =+G10/G$16 -> 0.078880861 | H59: =+H10/H$16 -> 0.078735803 | I59: =+I10/I$16 -> 0.087960885 | ... L59: =+L10/L$16 -> 0.072045477 | Q59: =+Q10/Q$16 -> 0.079430548 | R59: =+R10/R$16 -> 0.07815406 | S59: =+S10/S$16 -> 0.14002523 | T59: =+T10/T$16 -> 0.094098565 | U59: =+U10/U$16 -> 0.11154217 | V59: =+V10/V$16 -> 0.10488031 | W59: =+W10/W$16 -> 0.10458552 | X59: =+X10/X$16 -> 0.10395659 | ... Z59: =+Z10/Z$16 -> 0.085750467 | AL59: Just P/E | AM59: =+(AM56*(1+0.07))/(Main!H9-0.07) -> 24.606442
A60: Services % Rev | B60: =+B14/B$16 -> 0.19332636 | C60: =+C14/C$16 -> 0.26298855 | D60: =+D14/D$16 -> 0.28227847 | E60: =+E14/E$16 -> 0.26305699 | F60: =+F14/F$16 -> 0.21190668 | G60: =+G14/G$16 -> 0.27941778 | H60: =+H14/H$16 -> 0.29162236 | I60: =+I14/I$16 -> 0.28058088 | ... L60: =+L14/L$16 -> 0.28093441 | Q60: =+Q14/Q$16 -> 0.052234219 | R60: =+R14/R$16 -> 0.056690672 | S60: =+S14/S$16 -> 0.065577289 | T60: =+T14/T$16 -> 0.17792324 | U60: =+U14/U$16 -> 0.19586544 | V60: =+V14/V$16 -> 0.18704708 | W60: =+W14/W$16 -> 0.19813201 | X60: =+X14/X$16 -> 0.2222889 | ... Z60: =+Z14/Z$16 -> 0.26229752
A63: ROA | C63: =+(C40*4)/AVERAGE(B92:C92) -> #DIV/0! | D63: =+(D40*4)/AVERAGE(C92:D92) -> #DIV/0! | E63: =+(E40*4)/AVERAGE(D92:E92) -> 0.32299852 | F63: =+(F40*4)/AVERAGE(E92:F92) -> 0.40987571 | G63: =+(G40*4)/AVERAGE(F92:G92) -> 0.29353842 | H63: =+(H40*4)/AVERAGE(G92:H92) -> 0.28287925 | I63: =+(I40*4)/AVERAGE(H92:I92) -> 0.31810706 | J63: =+(J40*4)/AVERAGE(I92:J92) -> 0.45600362 | ... L63: =+(L40*4)/AVERAGE(K92:L92) -> 0.31591785 | R63: =+R40/AVERAGE(Q92:R92) -> 0.13203636 | S63: =+S40/AVERAGE(R92:S92) -> 0.16066792 | T63: =+T40/AVERAGE(S92:T92) -> 0.15692355 | U63: =+U40/AVERAGE(T92:U92) -> 0.17334134 | V63: =+V40/AVERAGE(U92:V92) -> 0.28057906 | W63: =+W40/AVERAGE(V92:W92) -> 0.28362915 | X63: =+X40/AVERAGE(W92:X92) -> 0.27503126 | Y63: =+Y40/AVERAGE(X92:Y92) -> 0.26126208 | Z63: =+Z40/AVERAGE(Y92:Z92) -> 0.30932547
A64: ROE | C64: =+(C40*4)/AVERAGE(B106:C106) -> #DIV/0! | D64: =+(D40*4)/AVERAGE(C106:D106) -> #DIV/0! | E64: =+(E40*4)/AVERAGE(D106:E106) -> 2.0700263 | F64: =+(F40*4)/AVERAGE(E106:F106) -> 2.3494034 | G64: =+(G40*4)/AVERAGE(F106:G106) -> 1.4843434 | H64: =+(H40*4)/AVERAGE(G106:H106) -> 1.4135388 | I64: =+(I40*4)/AVERAGE(H106:I106) -> 1.5744001 | J64: =+(J40*4)/AVERAGE(I106:J106) -> 2.0798528 | ... L64: =+(L40*4)/AVERAGE(K106:L106) -> 1.1135502 | R64: =+R40/AVERAGE(Q106:R106) -> 0.35086315 | S64: =+S40/AVERAGE(R106:S106) -> 0.49363583 | T64: =+T40/AVERAGE(S106:T106) -> 0.55917221 | U64: =+U40/AVERAGE(T106:U106) -> 0.73685562 | V64: =+V40/AVERAGE(U106:V106) -> 1.4744333 | W64: =+W40/AVERAGE(V106:W106) -> 1.7545929 | X64: =+X40/AVERAGE(W106:X106) -> 1.7194951 | Y64: =+Y40/AVERAGE(X106:Y106) -> 1.5741251 | Z64: =+Z40/AVERAGE(Y106:Z106) -> 1.7142245
A65: A. Turnover | C65: =+(C16*4)/AVERAGE(B92:C92) -> #DIV/0! | D65: =+(D16*4)/AVERAGE(C92:D92) -> #DIV/0! | E65: =+(E16*4)/AVERAGE(D92:E92) -> 2.0807715 | F65: =+(F16*4)/AVERAGE(E92:F92) -> 1.4023548 | G65: =+(G16*4)/AVERAGE(F92:G92) -> 1.1296017 | H65: =+(H16*4)/AVERAGE(G92:H92) -> 1.1351384 | I65: =+(I16*4)/AVERAGE(H92:I92) -> 1.1867457 | J65: =+(J16*4)/AVERAGE(I92:J92) -> 1.5571954 | ... L65: =+(L16*4)/AVERAGE(K92:L92) -> 1.1603875 | R65: =+R16/AVERAGE(Q92:R92) -> 0.65106563 | S65: =+S16/AVERAGE(R92:S92) -> 0.71681304 | T65: =+T16/AVERAGE(S92:T92) -> 0.73887774 | U65: =+U16/AVERAGE(T92:U92) -> 0.82884463 | V65: =+V16/AVERAGE(U92:V92) -> 1.0840789 | W65: =+W16/AVERAGE(V92:W92) -> 1.1206368 | X65: =+X16/AVERAGE(W92:X92) -> 1.0868123 | Y65: =+Y16/AVERAGE(X92:Y92) -> 1.0898973 | Z65: =+Z16/AVERAGE(Y92:Z92) -> 1.1492652
A66: Financial Leverage | C66: =+AVERAGE(B92:C92)/AVERAGE(B106:C106) -> #DIV/0! | D66: =+AVERAGE(C92:D92)/AVERAGE(C106:D106) -> #DIV/0! | E66: =+AVERAGE(D92:E92)/AVERAGE(D106:E106) -> 6.4087796 | F66: =+AVERAGE(E92:F92)/AVERAGE(E106:F106) -> 5.7319898 | G66: =+AVERAGE(F92:G92)/AVERAGE(F106:G106) -> 5.0567261 | H66: =+AVERAGE(G92:H92)/AVERAGE(G106:H106) -> 4.9969689 | I66: =+AVERAGE(H92:I92)/AVERAGE(H106:I106) -> 4.9492774 | J66: =+AVERAGE(I92:J92)/AVERAGE(I106:J106) -> 4.5610444 | ... L66: =+AVERAGE(K92:L92)/AVERAGE(K106:L106) -> 3.5248095 | R66: =+AVERAGE(Q92:R92)/AVERAGE(Q106:R106) -> 2.6573223 | S66: =+AVERAGE(R92:S92)/AVERAGE(R106:S106) -> 3.0723982 | T66: =+AVERAGE(S92:T92)/AVERAGE(S106:T106) -> 3.5633415 | U66: =+AVERAGE(T92:U92)/AVERAGE(T106:U106) -> 4.2508936 | V66: =+AVERAGE(U92:V92)/AVERAGE(U106:V106) -> 5.2549658 | W66: =+AVERAGE(V92:W92)/AVERAGE(V106:W106) -> 6.1862221 | X66: =+AVERAGE(W92:X92)/AVERAGE(W106:X106) -> 6.2519988 | Y66: =+AVERAGE(X92:Y92)/AVERAGE(X106:Y106) -> 6.0250806 | Z66: =+AVERAGE(Y92:Z92)/AVERAGE(Y106:Z106) -> 5.5418149
A67: Financial Leverage % | C67: =+C64-C63 -> #DIV/0! | D67: =+D64-D63 -> #DIV/0! | E67: =+E64-E63 -> 1.7470278 | F67: =+F64-F63 -> 1.9395277 | G67: =+G64-G63 -> 1.190805 | H67: =+H64-H63 -> 1.1306596 | I67: =+I64-I63 -> 1.256293 | J67: =+J64-J63 -> 1.6238492 | ... L67: =+L64-L63 -> 0.79763239 | R67: =+R64-R63 -> 0.21882679 | S67: =+S64-S63 -> 0.33296791 | T67: =+T64-T63 -> 0.40224866 | U67: =+U64-U63 -> 0.56351427 | V67: =+V64-V63 -> 1.1938543 | W67: =+W64-W63 -> 1.4709638 | X67: =+X64-X63 -> 1.4444639 | Y67: =+Y64-Y63 -> 1.312863 | Z67: =+Z64-Z63 -> 1.404899
A70: EBITDA | B70: =+B32+B112 -> 40373 | C70: =+C32+C112 -> 33584 | D70: =+D32+D112 -> 28202 | E70: =+E32+E112 -> 32502 | F70: =+F32+F112 -> 45912 | G70: =+G32+G112 -> 32250 | H70: =+H32+H112 -> 31032 | I70: =+I32+I112 -> 35554 | ... L70: =+L32+L112 -> 39015 | Q70: =+Q32+Q112 -> 68007 | R70: =+R32+R112 -> 69165 | S70: =+S32+S112 -> 81801 | T70: =+T32+T112 -> 76477 | U70: =+U32+U112 -> 77344 | V70: =+V32+V112 -> 120233 | W70: =+W32+W112 -> 130541 | X70: =+X32+X112 -> 125820 | ... AE70: =+AE32+AE112 -> 218458.69
AL71: EV | AM71: =+AI74 -> 2082861.5
A72: NOPAT | B72: =+B32*(1-B52) -> 33958.055 | C72: =+C32*(1-C52) -> 23502.901 | D72: =+D32*(1-D52) -> 21328.536 | E72: =+E32*(1-E52) -> 14726.544 | F72: =+F32*(1-F52) -> 36541.578 | G72: =+G32*(1-G52) -> 25015.879 | H72: =+H32*(1-H52) -> 23576.957 | I72: =+I32*(1-I52) -> 27150.347 | ... L72: =+L32*(1-L52) -> 29319.17 | Q72: =+Q32*(1-Q52) -> 42176.276 | R72: =+R32*(1-R52) -> 43969.574 | S72: =+S32*(1-S52) -> 57893.761 | T72: =+T32*(1-T52) -> 53737.105 | U72: =+U32*(1-U52) -> 56723.858 | V72: =+V32*(1-V52) -> 94456.32 | W72: =+W32*(1-W52) -> 100082.88 | X72: =+X32*(1-X52) -> 97476.837 | ... AE72: =+AE32*(1-AE52) -> 171220.54 | AH72: Terminal | AI72: 0.03 | AL72: Debt | AM72: =+Main!E5 -> 82347
A73: NWC | B73: =+B82+B83+B85+B86-B95-B96 -> 0 | C73: =+C82+C83+C85+C86-C95-C96 -> 0 | D73: =+D82+D83+D85+D86-D95-D96 -> 0 | E73: =+E82+E83+E85+E86-E95-E96 -> -59448 | F73: =+F82+F83+F85+F86-F95-F96 -> -43568 | G73: =+G82+G83+G85+G86-G95-G96 -> -45796 | H73: =+H82+H83+H85+H86-H95-H96 -> -45754 | I73: =+I82+I83+I85+I86-I95-I96 -> -42987 | ... L73: =+L82+L83+L85+L86-L95-L96 -> -39365 | Q73: =+Q82+Q83+Q85+Q86-Q95-Q96 -> -19607 | R73: =+R82+R83+R85+R86-R95-R96 -> -20329 | S73: =+S82+S83+S85+S86-S95-S96 -> -23537 | T73: =+T82+T83+T85+T86-T95-T96 -> -21694 | U73: =+U82+U83+U85+U86-U95-U96 -> -32210 | V73: =+V82+V83+V85+V86-V95-V96 -> -30059 | W73: =+W82+W83+W85+W86-W95-W96 -> -37859 | X73: =+X82+X83+X85+X86-X95-X96 -> -39429 | ... AE73: =+AE82+AE83+AE85+AE86-AE95-AE96 -> -64033.741 | AH73: Discount | AI73: =+Main!H9 -> 0.10300751 | AL73: Cash | AM73: =+Main!E4 -> 62399
A74: Inv. Capital | AH74: EV | AI74: =+NPV(AI73,AA75:AD75,AE75+AI75) -> 2082861.5 | AL74: Equity Value | AM74: =+AM71-AM72+AM73 -> 2062913.5
A75: UFCF | R75: =+R72+R112-R124-(R73-Q73) -> 42397.574 | S75: =+S72+S112-S124-(S73-R73) -> 58691.761 | T75: =+T72+T112-T124-(T73-S73) -> 53946.105 | U75: =+U72+U112-U124-(U73-T73) -> 70986.858 | V75: =+V72+V112-V124-(V73-U73) -> 92504.32 | W75: =+W72+W112-W124-(W73-V73) -> 108278.88 | X75: =+X72+X112-X124-(X73-W73) -> 99606.837 | Y75: =+Y72+Y112-Y124-(Y73-X73) -> 115548.81 | ... AE75: =+AE72+AE112-AE124-(AE73-AD73) -> 175714.66 | AH75: TV | AI75: =+AE75*(1+AI72)/(AI73-AI72) -> 2479006.6 | AJ75: =+AE70*16 -> 3495339 | AL75: Shares | AM75: =+Main!E2 -> 14598.18
A76: ROIC | AH76: Diff | AI76: =+AI74/Main!E6-1 -> -0.54028691 | AJ76: =+AE70*14 -> 3058421.7 | AL76: Price | AM76: =+AM74/AM75 -> 141.31306
A78: Net Cash | B78: =+B80+B81-B100 -> 0 | C78: =+C80+C81-C100 -> 0 | D78: =+D80+D81-D100 -> 0 | E78: =+E80+E81-E100 -> -31491 | F78: =+F80+F81-F100 -> -41029 | G78: =+G80+G81-G100 -> -43706 | H78: =+H80+H81-H100 -> -36403 | I78: =+I80+I81-I100 -> -35981 | ... L78: =+L80+L81-L100 -> -19948 | Q78: =+Q80+Q81-Q100 -> -11772 | R78: =+R80+R81-R100 -> -69522 | S78: =+S80+S81-S100 -> -36218 | T78: =+T80+T81-T100 -> -1510 | U78: =+U80+U81-U100 -> -16497 | V78: =+V80+V81-V100 -> -56080 | W78: =+W80+W81-W100 -> -61783 | X78: =+X80+X81-X100 -> -43548 | ... Z78: =+Z80+Z81-Z100 -> -35981
A80: Cash | E80: 29943 | F80: 30299 | G80: 28162 | H80: 36269 | I80: 35934 | J80: 45317 | K80: 45572 | L80: 39544 | Q80: 20484 | R80: 20289 | S80: 25913 | T80: 48844 | U80: 38016 | V80: 34940 | W80: 23646 | X80: 29965 | Y80: 29943 | Z80: 35934
A81: Mrk. Securities | E81: 35228 | F81: 23476 | G81: 20336 | H81: 19103 | I81: 18763 | J81: 21590 | K81: 22935 | L81: 22855 | Q81: 46671 | R81: 53892 | S81: 40388 | T81: 51713 | U81: 52927 | V81: 27699 | W81: 24658 | X81: 31590 | Y81: 35228 | Z81: 18763
A82: A/R | E82: 33410 | F82: 29667 | G82: 26136 | H82: 27557 | I82: 39777 | J82: 39921 | K82: 30339 | L82: 31398 | Q82: 15754 | R82: 17874 | S82: 23186 | T82: 22926 | U82: 16120 | V82: 26278 | W82: 28184 | X82: 29508 | Y82: 33410 | Z82: 39777 | AA82: =+(AA129/365)*AA16 -> 38905.29 | AB82: =+(AB129/365)*AB16 -> 40586.975 | AC82: =+(AC129/365)*AC16 -> 42330.404 | AD82: =+(AD129/365)*AD16 -> 44136.932 | AE82: =+(AE129/365)*AE16 -> 46007.853
A83: Vend. Non-trade /R | E83: 32833 | F83: 29667 | G83: 23662 | H83: 19278 | I83: 33180 | J83: 30399 | K83: 23172 | L83: 27509 | Q83: 13545 | R83: 17799 | S83: 25809 | T83: 22878 | U83: 21325 | V83: 25228 | W83: 32748 | X83: 31477 | Y83: 32833 | Z83: 33180 | AA83: =+AA$16*0.08 -> 35956.31 | AB83: =+AB$16*0.08 -> 38113.689 | AC83: =+AC$16*0.08 -> 40400.51 | AD83: =+AD$16*0.08 -> 42824.541 | AE83: =+AE$16*0.08 -> 45394.013
B84: =+B83/B$16 -> 0 | C84: =+C83/C$16 -> 0 | D84: =+D83/D$16 -> 0 | E84: =+E83/E$16 -> 0.34586537 | F84: =+F83/F$16 -> 0.23867257 | G84: =+G83/G$16 -> 0.24813599 | H84: =+H83/H$16 -> 0.20500659 | I84: =+I83/I$16 -> 0.32381473 | ... L84: =+L83/L$16 -> 0.25141431 | Q84: =+Q83/Q$16 -> 0.063556638 | R84: =+R83/R$16 -> 0.07844494 | S84: =+S83/S$16 -> 0.097174269 | T84: =+T83/T$16 -> 0.08793346 | U84: =+U83/U$16 -> 0.077682458 | V84: =+V83/V$16 -> 0.068963443 | W84: =+W83/W$16 -> 0.083047615 | X84: =+X83/X$16 -> 0.082124268 | ... AE84: =+AE83/AE$16 -> 0.08
A85: Inventories | E85: 7286 | F85: 6911 | G85: 6269 | H85: 5925 | I85: 5718 | J85: 5875 | K85: 6747 | L85: 11092 | Q85: 2132 | R85: 4855 | S85: 3956 | T85: 4106 | U85: 4061 | V85: 6580 | W85: 4946 | X85: 6331 | Y85: 7286 | Z85: 5718 | AA85: =+AA130/365*AA22 -> 6846.4594 | AB85: =+AB130/365*AB22 -> 7017.4665 | AC85: =+AC130/365*AC22 -> 7187.8062 | AD85: =+AD130/365*AD22 -> 7356.9903 | AE85: =+AE130/365*AE22 -> 7524.4869
A86: Other , curr | E86: 14287 | F86: 13248 | G86: 14109 | H86: 14359 | I86: 14585 | J86: 15002 | K86: 15349 | L86: 17420 | Q86: 8283 | R86: 13936 | S86: 12087 | T86: 12352 | U86: 11264 | V86: 14111 | W86: 21223 | X86: 14695 | Y86: 14287 | Z86: 14585 | AA86: =+AA$16*0.03 -> 13483.616 | AB86: =+AB$16*0.03 -> 14292.633 | AC86: =+AC$16*0.03 -> 15150.191 | AD86: =+AD$16*0.03 -> 16059.203 | AE86: =+AE$16*0.03 -> 17022.755
B87: =+B86/B$16 -> 0 | C87: =+C86/C$16 -> 0 | D87: =+D86/D$16 -> 0 | E87: =+E86/E$16 -> 0.15050037 | F87: =+F86/F$16 -> 0.10658085 | G87: =+G86/G$16 -> 0.14795667 | H87: =+H86/H$16 -> 0.15269684 | I87: =+I86/I$16 -> 0.1423399 | ... L87: =+L86/L$16 -> 0.15920744 | Q87: =+Q86/Q$16 -> 0.038865975 | R87: =+R86/R$16 -> 0.061419669 | S87: =+S86/S$16 -> 0.04550914 | T87: =+T86/T$16 -> 0.04747592 | U87: =+U86/U$16 -> 0.041032366 | V87: =+V86/V$16 -> 0.038573932 | W87: =+W86/W$16 -> 0.053820677 | X87: =+X86/X$16 -> 0.038339617 | ... AE87: =+AE86/AE$16 -> 0.03
A88: Mark. Sec | E88: 91479 | F88: 87593 | G88: 84424 | H88: 77614 | I88: 77723 | J88: 77888 | K88: 78088 | L88: 84118 | Q88: 170430 | R88: 194714 | S88: 170799 | T88: 105341 | U88: 100887 | V88: 127877 | W88: 120805 | X88: 100544 | Y88: 91479 | Z88: 77723
A89: PP&E | E89: 45680 | F89: 46069 | G89: 46876 | H89: 48508 | I89: 49834 | J89: 50159 | K89: 50116 | L89: 51431 | Q89: 27010 | R89: 33783 | S89: 41304 | T89: 37378 | U89: 36766 | V89: 39440 | W89: 42117 | X89: 43715 | Y89: 45680 | Z89: 49834
A90: Intangible | B90: 0 | C90: 0 | D90: 0 | E90: 0 | F90: 0 | G90: 0 | H90: 0 | I90: 11093 | J90: 0 | K90: 21334 | L90: 20342 | Q90: 0 | R90: 0 | S90: 0 | T90: 0 | U90: 0 | V90: 0 | W90: 0 | X90: 0 | Y90: 0 | Z90: 11093
A91: Other, non curr | E91: 74834 | F91: 77183 | G91: 81259 | H91: 82882 | I91: 72634 | J91: 93146 | K91: 77430 | L91: 77557 | Q91: =+8757+3206+5414 -> 17377 | R91: 18177 | S91: 22283 | T91: 32978 | U91: 42522 | V91: 48849 | W91: 54428 | X91: 64758 | Y91: 74834 | Z91: 72634
A92: A | B92: =+SUM(B80:B91)-B87-B84 -> 0 | C92: =+SUM(C80:C91)-C87-C84 -> 0 | D92: =+SUM(D80:D91)-D87-D84 -> 0 | E92: =+SUM(E80:E91)-E87-E84 -> 364980 | F92: =+SUM(F80:F91)-F87-F84 -> 344113 | G92: =+SUM(G80:G91)-G87-G84 -> 331233 | H92: =+SUM(H80:H91)-H87-H84 -> 331495 | I92: =+SUM(I80:I91)-I87-I84 -> 359241 | ... L92: =+SUM(L80:L91)-L87-L84 -> 383266 | Q92: =+SUM(Q80:Q91)-Q87-Q84 -> 321686 | R92: =+SUM(R80:R91)-R87-R84 -> 375319 | S92: =+SUM(S80:S91)-S87-S84 -> 365725 | T92: =+SUM(T80:T91)-T87-T84 -> 338516 | U92: =+SUM(U80:U91)-U87-U84 -> 323888 | V92: =+SUM(V80:V91)-V87-V84 -> 351002 | W92: =+SUM(W80:W91)-W87-W84 -> 352755 | X92: =+SUM(X80:X91)-X87-X84 -> 352583 | ... Z92: =+SUM(Z80:Z91)-Z87-Z84 -> 359241
A95: A/P | E95: 68960 | F95: 61910 | G95: 54126 | H95: 50374 | I95: 69860 | J95: 70587 | K95: 57349 | L95: 64525 | Q95: 37294 | R95: 44242 | S95: 55888 | T95: 46236 | U95: 42296 | V95: 54763 | W95: 64115 | X95: 62611 | Y95: 68960 | Z95: 69860 | AA95: =+AA131/365*AA22 -> 75481.536 | AB95: =+AB131/365*AB22 -> 79940.876 | AC95: =+AC131/365*AC22 -> 84649.768 | AD95: =+AD131/365*AD22 -> 89621.273 | AE95: =+AE131/365*AE22 -> 94869.074
A96: Other, curr | E96: 78304 | F96: 61151 | G96: 61846 | H96: 62499 | I96: 66387 | J96: 68543 | K96: 57654 | L96: 62259 | Q96: 22027 | R96: 30551 | S96: 32687 | T96: 37720 | U96: 42684 | V96: 47493 | W96: 60845 | X96: 58829 | Y96: 78304 | Z96: 66387 | AA96: =+AA$16*0.15 -> 67418.082 | AB96: =+AB$16*0.15 -> 71463.167 | AC96: =+AC$16*0.15 -> 75750.957 | AD96: =+AD$16*0.15 -> 80296.014 | AE96: =+AE$16*0.15 -> 85113.775
B97: =+B96/B$16 -> 0 | C97: =+C96/C$16 -> 0 | D97: =+D96/D$16 -> 0 | E97: =+E96/E$16 -> 0.82486042 | F97: =+F96/F$16 -> 0.49196299 | G97: =+G96/G$16 -> 0.64855965 | H97: =+H96/H$16 -> 0.66462844 | I97: =+I96/I$16 -> 0.64789296 | ... L97: =+L96/L$16 -> 0.56900664 | Q97: =+Q96/Q$16 -> 0.10335637 | R97: =+R96/R$16 -> 0.1346464 | S97: =+S96/S$16 -> 0.12307084 | T97: =+T96/T$16 -> 0.1449799 | U97: =+U96/U$16 -> 0.15548877 | V97: =+V96/V$16 -> 0.12982721 | W97: =+W96/W$16 -> 0.15430048 | X97: =+X96/X$16 -> 0.15348631 | ... AE97: =+AE96/AE$16 -> 0.15
A98: D/R | E98: 8249 | F98: 8461 | G98: 8976 | H98: 8979 | I98: 9055 | J98: 9413 | K98: 9331 | L98: 9538 | Q98: =+8080+2930 -> 11010 | R98: =+7548+2836 -> 10384 | S98: =+7543+2797 -> 10340 | T98: 5522 | U98: 6643 | V98: 7612 | W98: 7912 | X98: 8061 | Y98: 8249 | Z98: 9055
A99: Comm. Paper | E99: 9967 | F99: 1995 | G99: 5982 | H99: 9923 | I99: 7979 | J99: 1997 | K99: 1997 | L99: 1997 | Q99: 8105 | R99: 11977 | S99: 11964 | T99: 5980 | U99: 4996 | V99: 6000 | W99: 9982 | X99: 5985 | Y99: 9967 | Z99: 7979
A100: Debt | E100: =+10912+85750 -> 96662 | F100: =+10848+83956 -> 94804 | G100: =+13638+78566 -> 92204 | H100: =+9345+82430 -> 91775 | I100: =+12350+78328 -> 90678 | J100: =+11827+76685 -> 88512 | K100: =+8310+74404 -> 82714 | L100: =+11007+71340 -> 82347 | Q100: =+3500+75427 -> 78927 | R100: =+46496+97207 -> 143703 | S100: =+8784+93735 -> 102519 | T100: =+10260+91807 -> 102067 | U100: =+8773+98667 -> 107440 | V100: =+9613+109106 -> 118719 | W100: =+11128+98959 -> 110087 | X100: =+9822+95281 -> 105103 | Y100: =+10912+85750 -> 96662 | Z100: =+12350+78328 -> 90678
A101: Other, non curr | E101: 45888 | F101: 49006 | G101: 41300 | H101: 42115 | I101: 41549 | J101: 52055 | K101: 55546 | L101: 55080 | Q101: 36074 | R101: 40415 | S101: 45180 | T101: 50503 | U101: 54490 | V101: 53325 | W101: 49142 | X101: 49848 | Y101: 45888 | Z101: 41549
A102: L | B102: =+SUM(B95:B101)-B97 -> 0 | C102: =+SUM(C95:C101)-C97 -> 0 | D102: =+SUM(D95:D101)-D97 -> 0 | E102: =+SUM(E95:E101)-E97 -> 308030 | F102: =+SUM(F95:F101)-F97 -> 277327 | G102: =+SUM(G95:G101)-G97 -> 264434 | H102: =+SUM(H95:H101)-H97 -> 265665 | I102: =+SUM(I95:I101)-I97 -> 285508 | ... L102: =+SUM(L95:L101)-L97 -> 275746 | Q102: =+SUM(Q95:Q101)-Q97 -> 193437 | R102: =+SUM(R95:R101)-R97 -> 281272 | S102: =+SUM(S95:S101)-S97 -> 258578 | T102: =+SUM(T95:T101)-T97 -> 248028 | U102: =+SUM(U95:U101)-U97 -> 258549 | V102: =+SUM(V95:V101)-V97 -> 287912 | W102: =+SUM(W95:W101)-W97 -> 302083 | X102: =+SUM(X95:X101)-X97 -> 290437 | ... Z102: =+SUM(Z95:Z101)-Z97 -> 285508
A103: Stocks | E103: 83276 | F103: 84768 | G103: 88711 | H103: 89806 | I103: 93568 | J103: 95221 | K103: 99507 | L103: 100702 | Q103: 31251 | R103: 35867 | S103: 40201 | T103: 45174 | U103: 50779 | V103: 57365 | W103: 64849 | X103: 73812 | Y103: 83276 | Z103: 93568
A104: Retained Earnings | E104: -19154 | F104: -11221 | G104: -15552 | H104: -17607 | I104: -14264 | J104: -2177 | K104: 12359 | L104: 11326 | Q104: 96364 | R104: 98330 | S104: 70400 | T104: 45898 | U104: 14966 | V104: 5562 | W104: -3068 | X104: -214 | Y104: -19154 | Z104: -14264
A105: AOCI | E105: -7172 | F105: -6789 | G105: -6363 | H105: -6369 | I105: -5571 | J105: -4854 | K105: -5375 | L105: -4508 | Q105: 634 | R105: -150 | S105: -3454 | T105: -584 | U105: -406 | V105: 163 | W105: -11109 | X105: -11452 | Y105: -7172 | Z105: -5571
A106: SE | B106: =+SUM(B103:B105) -> 0 | C106: =+SUM(C103:C105) -> 0 | D106: =+SUM(D103:D105) -> 0 | E106: =+SUM(E103:E105) -> 56950 | F106: =+SUM(F103:F105) -> 66758 | G106: =+SUM(G103:G105) -> 66796 | H106: =+SUM(H103:H105) -> 65830 | I106: =+SUM(I103:I105) -> 73733 | ... L106: =+SUM(L103:L105) -> 107520 | Q106: =+SUM(Q103:Q105) -> 128249 | R106: =+SUM(R103:R105) -> 134047 | S106: =+SUM(S103:S105) -> 107147 | T106: =+SUM(T103:T105) -> 90488 | U106: =+SUM(U103:U105) -> 65339 | V106: =+SUM(V103:V105) -> 63090 | W106: =+SUM(W103:W105) -> 50672 | X106: =+SUM(X103:X105) -> 62146 | ... Z106: =+SUM(Z103:Z105) -> 73733
A107: L+SE | B107: =+B106+B102 -> 0 | C107: =+C106+C102 -> 0 | D107: =+D106+D102 -> 0 | E107: =+E106+E102 -> 364980 | F107: =+F106+F102 -> 344085 | G107: =+G106+G102 -> 331230 | H107: =+H106+H102 -> 331495 | I107: =+I106+I102 -> 359241 | ... L107: =+L106+L102 -> 383266 | Q107: =+Q106+Q102 -> 321686 | R107: =+R106+R102 -> 415319 | S107: =+S106+S102 -> 365725 | T107: =+T106+T102 -> 338516 | U107: =+U106+U102 -> 323888 | V107: =+V106+V102 -> 351002 | W107: =+W106+W102 -> 352755 | X107: =+X106+X102 -> 352583 | ... Z107: =+Z106+Z102 -> 359241
A110: Model NI | B110: =+B40 -> 33916 | C110: =+C40 -> 23636 | D110: =+D40 -> 21448 | E110: =+E40 -> 14736 | F110: =+F40 -> 36330 | G110: =+G40 -> 24780 | H110: =+H40 -> 23434 | I110: =+I40 -> 27466 | ... L110: =+L40 -> 29789 | Q110: =+Q40 -> 43165 | R110: =+R40 -> 46015 | S110: =+S40 -> 59531 | T110: =+T40 -> 55256 | U110: =+U40 -> 57411 | V110: =+V40 -> 94680 | W110: =+W40 -> 99803 | X110: =+X40 -> 96995 | ... Z110: =+Z40 -> 112010
A111: Net Income | C111: =+57552-B111 -> 57552 | D111: =+79000-C111-B111 -> 21448 | E111: =+93736-D111-C111-B111 -> 14736 | F111: 36330 | G111: =+61110-F111 -> 24780 | H111: =+84544-G111-F111 -> 23434 | I111: =+112010-H111-G111-F111 -> 27466 | J111: 42097 | K111: =+71675-J111 -> 29578 | L111: =+101464-K111-J111 -> 29789 | Q111: 45687 | R111: 48351 | S111: 58531 | T111: 55256 | U111: 57411 | V111: 94680 | W111: 99803 | X111: 96995 | Y111: 93736 | Z111: 112010
A112: D&A | C112: =+5684-B112 -> 5684 | D112: =+8534-C112-B112 -> 2850 | E112: =+11445-D112-C112-B112 -> 2911 | F112: 3080 | G112: =+5741-F112 -> 2661 | H112: =+8571-G112-F112 -> 2830 | I112: =+11698-H112-G112-F112 -> 3127 | J112: 3214 | K112: =+6653-J112 -> 3439 | L112: =+9973-K112-J112 -> 3320 | Q112: 10505 | R112: 10157 | S112: 10903 | T112: 12547 | U112: 11056 | V112: 11284 | W112: 11104 | X112: 11519 | Y112: 11445 | Z112: 11698 | AA112: =+AA$16*0.03 -> 13483.616 | AB112: =+AB$16*0.03 -> 14292.633 | AC112: =+AC$16*0.03 -> 15150.191 | AD112: =+AD$16*0.03 -> 16059.203 | AE112: =+AE$16*0.03 -> 17022.755
B113: =+B112/B$16 -> 0 | C113: =+C112/C$16 -> 0.062631538 | D113: =+D112/D$16 -> 0.03322569 | E113: =+E112/E$16 -> 0.0306647 | F113: =+F112/F$16 -> 0.024778761 | G113: =+G112/G$16 -> 0.027905075 | H113: =+H112/H$16 -> 0.030094857 | I113: =+I112/I$16 -> 0.03051744 | ... L113: =+L112/L$16 -> 0.030342634 | Q113: =+Q112/Q$16 -> 0.049292173 | R113: =+R112/R$16 -> 0.044764608 | S113: =+S112/S$16 -> 0.041051225 | T113: =+T112/T$16 -> 0.048225418 | U113: =+U112/U$16 -> 0.040274666 | V113: =+V112/V$16 -> 0.030846024 | W113: =+W112/W$16 -> 0.028159299 | X113: =+X112/X$16 -> 0.030053355 | ... AE113: =+AE112/AE$16 -> 0.03
A114: SBC | C114: =+5961-B114 -> 5961 | D114: =+8830-C114-B114 -> 2869 | E114: =+11688-D114-C114-B114 -> 2858 | F114: 3286 | G114: =+6512-F114 -> 3226 | H114: =+9680-G114-F114 -> 3168 | I114: =+12863-H114-G114-F114 -> 3183 | J114: 3594 | K114: =+7122-J114 -> 3528 | L114: =+10523-K114-J114 -> 3401 | Q114: 4210 | R114: 4840 | S114: 5340 | T114: 6068 | U114: 6829 | V114: 7906 | W114: 9038 | X114: 10833 | Y114: 11688 | Z114: 12863
...

Sheet Bond
A1: Main
B3: ISIN | C3: Bond Type | D3: Immediate Issuer | E3: Coupon (%) | F3: Maturity Date | G3: Callable | H3: Currency | I3: Seniority Level | J3: Yield To Worst
B4: US037833DN70 | C4: - | D4: Apple Inc. | E4: 2050 | F4: Sep 11, 2026 | G4: Yes | H4: USD | I4: Senior | J4: 3.68
B5: XS1135337498 | C5: - | D5: Apple Inc. | E5: 1625 | F5: Nov 10, 2026 | G5: Yes | H5: EUR | I5: Senior | J5: -
B6: US037833CJ77 | C6: - | D6: Apple Inc. | E6: 3350 | F6: Feb 09, 2027 | G6: Yes | H6: USD | I6: Senior | J6: 4.142
B7: US037833CR93 | C7: - | D7: Apple Inc. | E7: 3200 | F7: May 11, 2027 | G7: Yes | H7: USD | I7: Senior | J7: 4.1
B8: US037833CX61 | C8: Green | D8: Apple Inc. | E8: 3000 | F8: Jun 20, 2027 | G8: Yes | H8: USD | I8: Senior | J8: 4.145
B9: US037833DB33 | C9: - | D9: Apple Inc. | E9: 2900 | F9: Sep 12, 2027 | G9: Yes | H9: USD | I9: Senior | J9: 4.202
B10: XS1292389415 | C10: - | D10: Apple Inc. | E10: 2000 | F10: Sep 17, 2027 | G10: Yes | H10: EUR | I10: Senior | J10: -
B11: US037833DK32 | C11: - | D11: Apple Inc. | E11: 3000 | F11: Nov 13, 2027 | G11: Yes | H11: USD | I11: Senior | J11: 4.268
B12: US037833EC07 | C12: - | D12: Apple Inc. | E12: 1200 | F12: Feb 08, 2028 | G12: Yes | H12: USD | I12: Senior | J12: 4.387
B13: US037833ET32 | C13: - | D13: Apple Inc. | E13: 4000 | F13: May 10, 2028 | G13: Yes | H13: USD | I13: Senior | J13: 4.367
B14: US037833EY27 | C14: - | D14: Apple Inc. | E14: 4000 | F14: May 12, 2028 | G14: Yes | H14: USD | I14: Senior | J14: 4.416
B15: US037833EH93 | C15: - | D15: Apple Inc. | E15: 1400 | F15: Aug 05, 2028 | G15: Yes | H15: USD | I15: Senior | J15: 4.393
B16: XS1619312686 | C16: - | D16: Apple Inc. | E16: 1375 | F16: May 24, 2029 | G16: Yes | H16: EUR | I16: Senior | J16: -
B17: XS1269175466 | C17: - | D17: Apple Inc. | E17: 3050 | F17: Jul 31, 2029 | G17: Yes | H17: GBP | I17: Senior | J17: -
B18: US037833EN61 | C18: - | D18: Apple Inc. | E18: 3250 | F18: Aug 08, 2029 | G18: Yes | H18: USD | I18: Senior | J18: 4.472
B19: US037833DP29 | C19: - | D19: Apple Inc. | E19: 2200 | F19: Sep 11, 2029 | G19: Yes | H19: USD | I19: Senior | J19: 4.491
B20: CH0271171693 | C20: - | D20: Apple Inc. | E20: 750 | F20: Feb 25, 2030 | G20: -- | H20: CHF | I20: Senior | J20: -
B21: US037833EU05 | C21: - | D21: Apple Inc. | E21: 4150 | F21: May 10, 2030 | G21: Yes | H21: USD | I21: Senior | J21: 4.632
B22: US037833DU14 | C22: - | D22: Apple Inc. | E22: 1650 | F22: May 11, 2030 | G22: Yes | H22: USD | I22: Senior | J22: 4.703
B23: US037833EZ91 | C23: - | D23: Apple Inc. | E23: 4200 | F23: May 12, 2030 | G23: Yes | H23: USD | I23: Senior | J23: 4.588
B24: US037833DY36 | C24: - | D24: Apple Inc. | E24: 1250 | F24: Aug 20, 2030 | G24: Yes | H24: USD | I24: Senior | J24: 4.692
B25: US037833ED89 | C25: - | D25: Apple Inc. | E25: 1650 | F25: Feb 08, 2031 | G25: Yes | H25: USD | I25: Senior | J25: 4.675
B26: US037833EJ59 | C26: - | D26: Apple Inc. | E26: 1700 | F26: Aug 05, 2031 | G26: Yes | H26: USD | I26: Senior | J26: 4.747
B27: XS2079716937 | C27: Green | D27: Apple Inc. | E27: 500 | F27: Nov 15, 2031 | G27: Yes | H27: EUR | I27: Senior | J27: -
B28: US037833FA32 | C28: - | D28: Apple Inc. | E28: 4500 | F28: May 12, 2032 | G28: Yes | H28: USD | I28: Senior | J28: 4.704
B29: US037833EP10 | C29: - | D29: Apple Inc. | E29: 3350 | F29: Aug 08, 2032 | G29: Yes | H29: USD | I29: Senior | J29: 4.746
B30: US037833EV87 | C30: - | D30: Apple Inc. | E30: 4300 | F30: May 10, 2033 | G30: Yes | H30: USD | I30: Senior | J30: 4.747
B31: US037833FB15 | C31: - | D31: Apple Inc. | E31: 4750 | F31: May 12, 2035 | G31: Yes | H31: USD | I31: Senior | J31: 4.96
B32: US037833BW97 | C32: - | D32: Apple Inc. | E32: 4500 | F32: Feb 23, 2036 | G32: Yes | H32: USD | I32: Senior | J32: 4.965
B33: US037833EE62 | C33: - | D33: Apple Inc. | E33: 2375 | F33: Feb 08, 2041 | G33: Yes | H33: USD | I33: Senior | J33: 5.589
B34: XS1269176191 | C34: - | D34: Apple Inc. | E34: 3600 | F34: Jul 31, 2042 | G34: Yes | H34: GBP | I34: Senior | J34: -
B35: US037833AL42 | C35: - | D35: Apple Inc. | E35: 3850 | F35: May 04, 2043 | G35: Yes | H35: USD | I35: Senior | J35: 5.772
B36: US037833AT77 | C36: - | D36: Apple Inc. | E36: 4450 | F36: May 06, 2044 | G36: Yes | H36: USD | I36: Senior | J36: 5.797
B37: US037833BA77 | C37: - | D37: Apple Inc. | E37: 3450 | F37: Feb 09, 2045 | G37: Yes | H37: USD | I37: Senior | J37: 5.882
B38: US037833BH21 | C38: - | D38: Apple Inc. | E38: 4375 | F38: May 13, 2045 | G38: Yes | H38: USD | I38: Senior | J38: 5.88
B39: US037833BX70 | C39: - | D39: Apple Inc. | E39: 4650 | F39: Feb 23, 2046 | G39: Yes | H39: USD | I39: Senior | J39: 5.848
B40: US037833CD08 | C40: - | D40: Apple Inc. | E40: 3850 | F40: Aug 04, 2046 | G40: Yes | H40: USD | I40: Senior | J40: 5.924
B41: US037833CH12 | C41: - | D41: Apple Inc. | E41: 4250 | F41: Feb 09, 2047 | G41: Yes | H41: USD | I41: Senior | J41: 5.925
B42: US037833DD98 | C42: - | D42: Apple Inc. | E42: 3750 | F42: Sep 12, 2047 | G42: Yes | H42: USD | I42: Senior | J42: 5.962
B43: US037833DG20 | C43: - | D43: Apple Inc. | E43: 3750 | F43: Nov 13, 2047 | G43: Yes | H43: USD | I43: Senior | J43: 5.946
B44: US037833DQ02 | C44: - | D44: Apple Inc. | E44: 2950 | F44: Sep 11, 2049 | G44: Yes | H44: USD | I44: Senior | J44: 5.98
B45: US037833DW79 | C45: - | D45: Apple Inc. | E45: 2650 | F45: May 11, 2050 | G45: Yes | H45: USD | I45: Senior | J45: 5.983
B46: US037833DZ01 | C46: - | D46: Apple Inc. | E46: 2400 | F46: Aug 20, 2050 | G46: Yes | H46: USD | I46: Senior | J46: 5.966
... B54: US037833ER75 | C54: - | D54: Apple Inc. | E54: 4100 | F54: Aug 08, 2062 | G54: Yes | H54: USD | I54: Senior | J54: 6.005
E55: =+AVERAGE(E4:E54) -> 3051.9608
E56: =+MEDIAN(E4:E54) -> 3050
