Workbook

Sheet Main
A1: Adobe Inc. | E1: Price | F1: 277
E2: Share | F2: 397.5 | G2: Q226
E3: MC | F3: =+F2*F1 -> 110107.5
E4: Cash | F4: 5626 | G4: Q226
E5: Debt | F5: 6645 | G5: Q226
E6: EV | F6: =+F3-F4+F5 -> 111126.5
A10: P/FCF | B10: =+F3/SUM(Model!P139:S139) -> 10.71132 | D10: BETA | E10: 1.42 | G10: WACC | H10: =+(F3/(F3+F5))*E11+(F5/(F3+F5))*E12*(1-Model!AF68) -> 0.12633021
A11: EV/EBITDA | B11: =+F6/SUM(Model!P85:S85) -> 11.229436 | D11: CAPM | E11: =+0.0495+E10*(0.1-0.045) -> 0.1276
A12: EV/FCF | B12: =+F6/SUM(Model!P139:S139) -> 10.810448 | D12: Cost of Debt | E12: =+0.0495 + (E13/10) -> 0.12897826
A13: Inc. Margin | B13: =+(SUM(Model!P45:S45)-SUM(Model!L45:O45))/(SUM(Model!P23:S23)-SUM(Model!L23:O23)) -> 0.33461687 | D13: Cr. Spread | E13: =+'[1]Credit Spread US'!J6 -> 0.79478261
A14: P/E | B14: =+F1/SUM(Model!P59:S59) -> 15.842243 | D14: Rating | E14: A+ | F14: A1
A15: Leverage | B15: =+(F5-F4)/SUM(Model!P85:S85) -> 0.1029709 | E15: S&P | F15: Moody’s
A22: -> | B22: Subscription, fees charged for subscriptions, services and subscription-based consulting services
A23: -> | B23: Product, fees related to licences for on-premise software
A24: -> | B24: Services and Other, fees for project-based consulting and training and mantainance for ceertain licences
A26: Segments
A27: -> | B27: Digital Media, products to create (Creative Cloud)
A28: -> | B28: Digital experience, platform and set of products to optimize customer experience and data management (A Experience, Journey Optimiser, GenStudio, …)
A29: -> | B29: Publishing and Advertising, eLearning solutions, technial documentation, web conferences, PDF standard, …
A31: Total Adobe ARR | B31: annual value of subscriptions contracts in the creative & marketing and Business Professional & Consumers customer groups
A35: Geography division
B36: 2020 | C36: =+B36+1 -> 2021 | D36: =+C36+1 -> 2022 | E36: =+D36+1 -> 2023 | F36: =+E36+1 -> 2024 | G36: =+F36+1 -> 2025
A37: America | B37: 7454 | C37: 8996 | D37: 10251 | E37: 11654 | F37: 12891 | G37: 14120
C38: =+C37/B37-1 -> 0.2068688 | D38: =+D37/C37-1 -> 0.13950645 | E38: =+E37/D37-1 -> 0.1368647 | F38: =+F37/E37-1 -> 0.10614381 | G38: =+G37/F37-1 -> 0.095337833
A39: EMEA | B39: 3400 | C39: 4252 | D39: 4593 | E39: 4881 | F39: 5554 | G39: 6289
C40: =+C39/B39-1 -> 0.25058824 | D40: =+D39/C39-1 -> 0.080197554 | E40: =+E39/D39-1 -> 0.062704115 | F40: =+F39/E39-1 -> 0.13788158 | G40: =+G39/F39-1 -> 0.13233705
A41: APAC | B41: 2014 | C41: 2537 | D41: 2762 | E41: 2874 | F41: 3060 | G41: 3360
C42: =+C41/B41-1 -> 0.25968222 | D42: =+D41/C41-1 -> 0.088687426 | E42: =+E41/D41-1 -> 0.040550326 | F42: =+F41/E41-1 -> 0.064718163 | G42: =+G41/F41-1 -> 0.098039216
B46: -> | C46: Business Professionals and Customers
C47: Acrobat Suite (PDF reader enhanced with AI features)
D48: Acrobad Studio, AI vertical tool to use PDFs
D49: Adobe Acrobat, PDF reader tool
D50: Adobe Acrobat Reader, free PDF tool
D51: Adobe Express, all-in-one AI app for videmaking, marketing and social content
B53: -> | C53: Creative and Marketing Professionals
D54: Adobe Creative Cloud Pro, subscription based ecosystem. It includes Adobe Firefly models
E55: Photography
E56: Adobe Photoshop – Lightroom, PS – imaging and design app. LR – edit, organise, store photoes app.
E57: Adobe PS Express, non specialist PS
E58: Lightroom Classic and Web, both alternatives for non specialist
E60: Design and UI
E61: Adobe Illustrator, vector graphics app (used for prints, books, media)
E62: Adobe XD, UI for websites vector based
E63: Adobe InDesign, used for long documents and managing large amount of text)ù
E64: Adobe InCopy, together with InDesign (for page design) while InCopy (editorial work)
E65: Adobe Express, non specialist alternative to PS, Illustrator, InDesign
E67: Drawing and Painting
E68: Adobe Fresco, PS and Illustartor but optimised for drawing on a tablet
... E93: Adobe Experience Platform, platform for data management about known and unknown customers (Palantir Foundry)
D95: Creative Cloud Services
E96: Frame.io, cloud workspace to upload and organise the team
E97: Behance, online platform to find opportunities, publish works, …
E98: Adobe Portfolio, website builder for portfolio sites
E99: Adobe Fonts, library of fonts
E100: Adobe Color, generates colour palette and colour tool
E101: Creative Cloud Libraries, saves fonts, colors, logos to be reused
E102: Mixamo, web based 3D character animation
B105: Operations
B106: -> | C106: Marketing and Sales
C107: They sell their products as pey-per-use of with the SaaS model through their website adobe.com
B109: -> | C109: Service and Support
C110: -> | D110: Consulting Services
D111: they have a team that designs and implements solutions for their largest customers (throguth subscription)
C113: -> | D113: Customer Success Account Management
D114: they have a team that helps customers to understand their current and future needs (through subscription)
C116: -> | D116: Technical Support
D117: classic customer care
C119: -> | D119: Digital Learning Solutions
D120: Fee-based learning programs and learning.adobe.com
B123: -> | C123: Can issue up to 3B$ of unsecured Commercial Paper with maturity up to 397 days
B124: -> | C124: Revenue recognised as the sale takes place

Sheet Model
A1: Main | B1: 02/22 | C1: 05/22 | D1: 08/22 | E1: 11/22 | F1: 02/23 | G1: 05/23 | H1: 08/23 | I1: 11/23 | J1: 02/24 | K1: 05/24 | L1: 08/24 | M1: 11/24 | N1: 02/25 | O1: 05/25 | P1: 08/25 | Q1: 11/25 | R1: 02/26 | S1: 05/26 | T1: 08/26 | U1: 11/26 | AA1: 11/20 | AB1: 11/21 | AC1: 11/22 | AD1: 11/23 | AE1: 11/24 | AF1: 11/25 | AG1: 11/26 | AH1: 11/27 | AI1: 11/28 | AJ1: 11/29 | AK1: 11/30 | AL1: 11/31 | AM1: 11/32 | AN1: 11/33 | AO1: 11/34 | AP1: 11/35 | AQ1: 11/36
A2: in Millions | B2: Q122 | C2: Q222 | D2: Q322 | E2: Q422 | F2: Q123 | G2: Q223 | H2: Q323 | I2: Q423 | J2: Q124 | K2: Q224 | L2: Q324 | M2: Q424 | N2: Q125 | O2: Q225 | P2: Q325 | Q2: Q425 | R2: Q126 | S2: Q226 | T2: Q326 | U2: Q426 | AA2: 2020 | AB2: =+AA2+1 -> 2021 | AC2: =+AB2+1 -> 2022 | AD2: =+AC2+1 -> 2023 | AE2: =+AD2+1 -> 2024 | AF2: =+AE2+1 -> 2025 | AG2: =+AF2+1 -> 2026 | AH2: =+AG2+1 -> 2027 | AI2: =+AH2+1 -> 2028 | ... AQ2: =+AP2+1 -> 2036
A3: Total Adobe ARR | AE3: 22610 | AF3: 25200
A5: Creative & Marketing Pro | AD5: 13425 | AE5: 14749 | AF5: 16303
AE6: =+AE5/AD5-1 -> 0.098621974 | AF6: =+AF5/AE5-1 -> 0.10536308
A7: Business Pro & Consumers | AD7: 4744 | AE7: 5662 | AF7: 6495
AE8: =+AE7/AD7-1 -> 0.19350759 | AF8: =+AF7/AE7-1 -> 0.14712116
A11: Digital Media | B11: 2995 | C11: 3079 | D11: 3116 | E11: =+AC11-D11-C11-B11 -> 3195 | F11: 3301 | G11: 3418 | H11: 3506 | I11: =+AD11-H11-G11-F11 -> 3613 | J11: 3725 | K11: 3828 | L11: 3921 | M11: =+AE11-L11-K11-J11 -> 4073 | N11: 4159 | O11: 4280 | P11: 4397 | Q11: =+AF11-P11-O11-N11 -> 4553 | AA11: 8813 | AB11: 11048 | AC11: 12385 | AD11: 13838 | AE11: 15547 | AF11: 17389
A12: % | F12: =+F11/B11-1 -> 0.10217028 | G12: =+G11/C11-1 -> 0.11010068 | H12: =+H11/D11-1 -> 0.12516046 | I12: =+I11/E11-1 -> 0.13082942 | J12: =+J11/F11-1 -> 0.12844593 | K12: =+K11/G11-1 -> 0.11995319 | L12: =+L11/H11-1 -> 0.11836851 | M12: =+M11/I11-1 -> 0.12731802 | ... Q12: =+Q11/M11-1 -> 0.11784925 | AB12: =+AB11/AA11-1 -> 0.25360263 | AC12: =+AC11/AB11-1 -> 0.12101738 | AD12: =+AD11/AC11-1 -> 0.11731934 | AE12: =+AE11/AD11-1 -> 0.12350051 | AF12: =+AF11/AE11-1 -> 0.11847945
A13: Digital Experience | B13: 932 | C13: 961 | D13: 981 | E13: =+AC13-D13-C13-B13 -> 1006 | F13: 1042 | G13: 1070 | H13: 1096 | I13: =+AD13-H13-G13-F13 -> 1123 | J13: 1164 | K13: 1204 | L13: 1231 | M13: =+AE13-L13-K13-J13 -> 1265 | N13: 1297 | O13: 1334 | P13: 1368 | Q13: =+AF13-P13-O13-N13 -> 1410 | AA13: 2660 | AB13: 3379 | AC13: 3880 | AD13: 4331 | AE13: 4864 | AF13: 5409
A14: % | F14: =+F13/B13-1 -> 0.11802575 | G14: =+G13/C13-1 -> 0.11342352 | H14: =+H13/D13-1 -> 0.11722732 | I14: =+I13/E13-1 -> 0.11630219 | J14: =+J13/F13-1 -> 0.11708253 | K14: =+K13/G13-1 -> 0.12523364 | L14: =+L13/H13-1 -> 0.12317518 | M14: =+M13/I13-1 -> 0.12644702 | ... Q14: =+Q13/M13-1 -> 0.11462451 | AB14: =+AB13/AA13-1 -> 0.27030075 | AC14: =+AC13/AB13-1 -> 0.14826872 | AD14: =+AD13/AC13-1 -> 0.11623711 | AE14: =+AE13/AD13-1 -> 0.12306627 | AF14: =+AF13/AE13-1 -> 0.1120477
A15: Publishing and ADV | B15: 31 | C15: 30 | D15: 31 | E15: =+AC15-D15-C15-B15 -> 31 | F15: 30 | G15: 29 | H15: 29 | I15: =+AD15-H15-G15-F15 -> 27 | J15: 27 | K15: 28 | L15: 28 | M15: =+AE15-L15-K15-J15 -> 27 | N15: 27 | O15: 27 | P15: 26 | Q15: =+AF15-P15-O15-N15 -> 26 | AA15: 153 | AB15: 146 | AC15: 123 | AD15: 115 | AE15: 110 | AF15: 106
A16: % | F16: =+F15/B15-1 -> -0.032258065 | G16: =+G15/C15-1 -> -0.033333333 | H16: =+H15/D15-1 -> -0.064516129 | I16: =+I15/E15-1 -> -0.12903226 | J16: =+J15/F15-1 -> -0.1 | K16: =+K15/G15-1 -> -0.034482759 | L16: =+L15/H15-1 -> -0.034482759 | M16: =+M15/I15-1 -> 0 | ... Q16: =+Q15/M15-1 -> -0.037037037 | AB16: =+AB15/AA15-1 -> -0.045751634 | AC16: =+AC15/AB15-1 -> -0.15753425 | AD16: =+AD15/AC15-1 -> -0.06504065 | AE16: =+AE15/AD15-1 -> -0.043478261 | AF16: =+AF15/AE15-1 -> -0.036363636
A17: Subscription | B17: =+B15+B13+B11 -> 3958 | C17: =+C15+C13+C11 -> 4070 | D17: =+D15+D13+D11 -> 4128 | E17: =+E15+E13+E11 -> 4232 | F17: =+F15+F13+F11 -> 4373 | G17: =+G15+G13+G11 -> 4517 | H17: =+H15+H13+H11 -> 4631 | I17: =+I15+I13+I11 -> 4763 | ... Q17: =+Q15+Q13+Q11 -> 5989 | R17: 6198 | S17: 6416 | AA17: =+AA15+AA13+AA11 -> 11626 | AB17: =+AB15+AB13+AB11 -> 14573 | AC17: =+AC15+AC13+AC11 -> 16388 | AD17: =+AD15+AD13+AD11 -> 18284 | AE17: =+AE15+AE13+AE11 -> 20521 | AF17: =+AF15+AF13+AF11 -> 22904
A18: % | F18: =+F17/B17-1 -> 0.10485093 | G18: =+G17/C17-1 -> 0.10982801 | H18: =+H17/D17-1 -> 0.12185078 | I18: =+I17/E17-1 -> 0.12547259 | J18: =+J17/F17-1 -> 0.12417105 | K18: =+K17/G17-1 -> 0.12021253 | L18: =+L17/H17-1 -> 0.11854891 | M18: =+M17/I17-1 -> 0.12639093 | ... S18: =+S17/O17-1 -> 0.13738699 | AA18: =+AA17/AA$23 -> 0.9034815 | AB18: =+AB17/AB$23 -> 0.92321825 | AC18: =+AC17/AC$23 -> 0.93081904 | AD18: =+AD17/AD$23 -> 0.9420372 | AE18: =+AE17/AE$23 -> 0.9542432 | AF18: =+AF17/AF$23 -> 0.96360806
A19: Product | B19: 145 | C19: 146 | D19: 126 | E19: 115 | F19: 120 | G19: 130 | H19: 96 | I19: 114 | J19: 119 | K19: 104 | L19: 82 | M19: 81 | N19: 95 | O19: 88 | P19: 68 | Q19: 74 | R19: 90 | S19: 89 | AA19: 507 | AB19: 555 | AC19: 532 | AD19: 460 | AE19: 386 | AF19: 325
A20: % | F20: =+F19/B19-1 -> -0.17241379 | G20: =+G19/C19-1 -> -0.10958904 | H20: =+H19/D19-1 -> -0.23809524 | I20: =+I19/E19-1 -> -0.0086956522 | J20: =+J19/F19-1 -> -0.0083333333 | K20: =+K19/G19-1 -> -0.2 | L20: =+L19/H19-1 -> -0.14583333 | M20: =+M19/I19-1 -> -0.28947368 | ... S20: =+S19/O19-1 -> 0.011363636 | AA20: =+AA19/AA$23 -> 0.039400062 | AB20: =+AB19/AB$23 -> 0.035159962 | AC20: =+AC19/AC$23 -> 0.030216971 | AD20: =+AD19/AD$23 -> 0.023700345 | AE20: =+AE19/AE$23 -> 0.017949314 | AF20: =+AF19/AF$23 -> 0.013673272
A21: Services | B21: 159 | C21: 170 | D21: 179 | E21: 178 | F21: 162 | G21: 169 | H21: 163 | I21: 171 | J21: 147 | K21: 145 | L21: 146 | M21: 160 | N21: 136 | O21: 144 | P21: 129 | Q21: 131 | R21: 110 | S21: 113 | AA21: 735 | AB21: 657 | AC21: 686 | AD21: 665 | AE21: 598 | AF21: 540
A22: % | F22: =+F21/B21-1 -> 0.018867925 | G22: =+G21/C21-1 -> -0.0058823529 | H22: =+H21/D21-1 -> -0.089385475 | I22: =+I21/E21-1 -> -0.039325843 | J22: =+J21/F21-1 -> -0.092592593 | K22: =+K21/G21-1 -> -0.14201183 | L22: =+L21/H21-1 -> -0.10429448 | M22: =+M21/I21-1 -> -0.064327485 | ... S22: =+S21/O21-1 -> -0.21527778 | AA22: =+AA21/AA$23 -> 0.057118433 | AB22: =+AB21/AB$23 -> 0.041621793 | AC22: =+AC21/AC$23 -> 0.03896399 | AD22: =+AD21/AD$23 -> 0.034262456 | AE22: =+AE21/AE$23 -> 0.027807487 | AF22: =+AF21/AF$23 -> 0.022718667
A23: Revenues | B23: =+B21+B19+B17 -> 4262 | C23: =+C21+C19+C17 -> 4386 | D23: =+D21+D19+D17 -> 4433 | E23: =+E21+E19+E17 -> 4525 | F23: =+F21+F19+F17 -> 4655 | G23: =+G21+G19+G17 -> 4816 | H23: =+H21+H19+H17 -> 4890 | I23: =+I21+I19+I17 -> 5048 | ... S23: =+S21+S19+S17 -> 6618 | T23: =+P23*1.11 -> 6646.68 | U23: =+Q23*1.11 -> 6875.34 | AA23: =+AA21+AA19+AA17 -> 12868 | AB23: =+AB21+AB19+AB17 -> 15785 | AC23: =+AC21+AC19+AC17 -> 17606 | AD23: =+AD21+AD19+AD17 -> 19409 | AE23: =+AE21+AE19+AE17 -> 21505 | AF23: =+AF21+AF19+AF17 -> 23769 | AG23: =+AF23*1.115 -> 26502.435 | AH23: =+AG23*1.105 -> 29285.191 | AI23: =+AH23*1.095 -> 32067.284 | AJ23: =+AI23*1.09 -> 34953.339 | AK23: =+AJ23*1.08 -> 37749.606 | AL23: =+AK23*1.07 -> 40392.079 | AM23: =+AL23*1.06 -> 42815.604 | AN23: =+AM23*1.05 -> 44956.384 | AO23: =+AN23*1.04 -> 46754.639 | AP23: =+AO23*1.03 -> 48157.278 | AQ23: =+AP23*1.02 -> 49120.424
A24: % | F24: =+F23/B23-1 -> 0.09221023 | G24: =+G23/C23-1 -> 0.098039216 | H24: =+H23/D23-1 -> 0.10309046 | I24: =+I23/E23-1 -> 0.11558011 | J24: =+J23/F23-1 -> 0.1132116 | K24: =+K23/G23-1 -> 0.10236711 | L24: =+L23/H23-1 -> 0.10593047 | M24: =+M23/I23-1 -> 0.11053883 | ... U24: =+U23/Q23-1 -> 0.11 | AB24: =+AB23/AA23-1 -> 0.22668635 | AC24: =+AC23/AB23-1 -> 0.11536269 | AD24: =+AD23/AC23-1 -> 0.10240827 | AE24: =+AE23/AD23-1 -> 0.10799114 | AF24: =+AF23/AE23-1 -> 0.10527784 | AG24: =+AG23/AF23-1 -> 0.115 | AH24: =+AH23/AG23-1 -> 0.105 | AI24: =+AI23/AH23-1 -> 0.095 | ... AQ24: =+AQ23/AP23-1 -> 0.02
A25: Subscription | B25: 393 | C25: 410 | D25: 413 | E25: 430 | F25: 434 | G25: 436 | H25: 447 | I25: 505 | J25: 455 | K25: 456 | L25: 413 | M25: 475 | N25: 490 | O25: 505 | P25: 510 | Q25: 522 | R25: 540 | S25: 586 | AA25: 1108 | AB25: 1374 | AC25: 1646 | AD25: 1822 | AE25: 1799 | AF25: 2027
A26: % | F26: =+F25/B25-1 -> 0.1043257 | G26: =+G25/C25-1 -> 0.063414634 | H26: =+H25/D25-1 -> 0.082324455 | I26: =+I25/E25-1 -> 0.1744186 | J26: =+J25/F25-1 -> 0.048387097 | K26: =+K25/G25-1 -> 0.04587156 | L26: =+L25/H25-1 -> -0.07606264 | M26: =+M25/I25-1 -> -0.059405941 | ... U26: =+U25/Q25-1 -> -1 | AB26: =+AB25/AA25-1 -> 0.2400722 | AC26: =+AC25/AB25-1 -> 0.19796215 | AD26: =+AD25/AC25-1 -> 0.10692588 | AE26: =+AE25/AD25-1 -> -0.012623491 | AF26: =+AF25/AE25-1 -> 0.12673708
A27: Product | B27: 10 | C27: 9 | D27: 8 | E27: 8 | F27: 8 | G27: 8 | H27: 7 | I27: 6 | J27: 5 | K27: 8 | L27: 6 | M27: 6 | N27: 6 | O27: 6 | P27: 5 | Q27: 6 | R27: 6 | S27: 5 | AA27: 36 | AB27: 41 | AC27: 35 | AD27: 29 | AE27: 25 | AF27: 23
A28: % | F28: =+F27/B27-1 -> -0.2 | G28: =+G27/C27-1 -> -0.11111111 | H28: =+H27/D27-1 -> -0.125 | I28: =+I27/E27-1 -> -0.25 | J28: =+J27/F27-1 -> -0.375 | K28: =+K27/G27-1 -> 0 | L28: =+L27/H27-1 -> -0.14285714 | M28: =+M27/I27-1 -> 0 | ... U28: =+U27/Q27-1 -> -1 | AB28: =+AB27/AA27-1 -> 0.13888889 | AC28: =+AC27/AB27-1 -> -0.14634146 | AD28: =+AD27/AC27-1 -> -0.17142857 | AE28: =+AE27/AD27-1 -> -0.13793103 | AF28: =+AF27/AE27-1 -> -0.08
A29: Services | B29: 109 | C29: 120 | D29: 125 | E29: 130 | F29: 126 | G29: 128 | H29: 126 | I29: 123 | J29: 130 | K29: 134 | L29: 135 | M29: 135 | N29: 126 | O29: 127 | P29: 127 | Q29: 121 | R29: 118 | S29: 124 | AA29: 578 | AB29: 450 | AC29: 484 | AD29: 503 | AE29: 534 | AF29: 501
A30: % | F30: =+F29/B29-1 -> 0.1559633 | G30: =+G29/C29-1 -> 0.066666667 | H30: =+H29/D29-1 -> 0.008 | I30: =+I29/E29-1 -> -0.053846154 | J30: =+J29/F29-1 -> 0.031746032 | K30: =+K29/G29-1 -> 0.046875 | L30: =+L29/H29-1 -> 0.071428571 | M30: =+M29/I29-1 -> 0.097560976 | ... U30: =+U29/Q29-1 -> -1 | AB30: =+AB29/AA29-1 -> -0.22145329 | AC30: =+AC29/AB29-1 -> 0.075555556 | AD30: =+AD29/AC29-1 -> 0.039256198 | AE30: =+AE29/AD29-1 -> 0.061630219 | AF30: =+AF29/AE29-1 -> -0.061797753
A31: COGS | B31: =+B29+B27+B25+42 -> 554 | C31: =+C29+C27+C25+42 -> 581 | D31: =+D29+D27+D25+43 -> 589 | E31: =+E29+E27+E25+42 -> 610 | F31: =+F29+F27+F25+42 -> 610 | G31: =+G29+G27+G25+42 -> 614 | H31: =+H29+H27+H25+42 -> 622 | I31: =+I29+I27+I25+42 -> 676 | J31: =+J29+J27+J25+42 -> 632 | K31: =+K29+K27+K25+42 -> 640 | L31: =+L29+L27+L25+43 -> 597 | M31: =+M29+M27+M25+42 -> 658 | N31: =+N29+N27+N25+41 -> 663 | O31: =+O29+O27+O25+41 -> 679 | P31: =+P29+P27+P25+38 -> 680 | Q31: =+Q29+Q27+Q25+37 -> 686 | R31: =+R29+R27+R25+35 -> 699 | S31: =+S29+S27+S25+37 -> 752 | T31: =+T23-T33 -> 731.1348 | U31: =+U23-U33 -> 756.2874 | AA31: =SUM(AA25:AA29)+162 -> 1884 | AB31: =SUM(AB25:AB29)+172 -> 2037.379 | AC31: =SUM(AC25:AC29)+169 -> 2334.0516 | AD31: =SUM(AD25:AD29)+168 -> 2521.9355 | AE31: =SUM(AE25:AE29)+169 -> 2526.8494 | AF31: =SUM(AF25:AF29)+157 -> 2708.0467 | AG31: =+AG23-AG33 -> 2955.0215 | AH31: =+AH23-AH33 -> 3221.371 | AI31: =+AI23-AI33 -> 3367.0648 | AJ31: =+AJ23-AJ33 -> 3495.3339 | AK31: =+AK23-AK33 -> 3586.2126 | AL31: =+AL23-AL33 -> 3635.2871 | AM31: =+AM23-AM33 -> 3639.3263 | AN31: =+AN23-AN33 -> 3596.5107 | ... AQ31: =+AQ23-AQ33 -> 3192.8276
A32: % | B32: =+B31/B$23 -> 0.12998592 | C32: =+C31/C$23 -> 0.13246694 | D32: =+D31/D$23 -> 0.13286713 | E32: =+E31/E$23 -> 0.13480663 | F32: =+F31/F$23 -> 0.13104189 | G32: =+G31/G$23 -> 0.12749169 | H32: =+H31/H$23 -> 0.12719836 | I32: =+I31/I$23 -> 0.13391442 | ... U32: =+U31/U$23 -> 0.11 | AA32: =+AA31/AA$23 -> 0.1464097 | AB32: =+AB31/AB$23 -> 0.12907057 | AC32: =+AC31/AC$23 -> 0.13257137 | AD32: =+AD31/AD$23 -> 0.1299364 | AE32: =+AE31/AE$23 -> 0.11750056 | AF32: =+AF31/AF$23 -> 0.11393188 | AG32: =+AG31/AG$23 -> 0.1115 | AH32: =+AH31/AH$23 -> 0.11 | ... AQ32: =+AQ31/AQ$23 -> 0.065
A33: Gross Margin | B33: =+B23-B31 -> 3708 | C33: =+C23-C31 -> 3805 | D33: =+D23-D31 -> 3844 | E33: =+E23-E31 -> 3915 | F33: =+F23-F31 -> 4045 | G33: =+G23-G31 -> 4202 | H33: =+H23-H31 -> 4268 | I33: =+I23-I31 -> 4372 | ... S33: =+S23-S31 -> 5866 | T33: =+T23*0.89 -> 5915.5452 | U33: =+U23*0.89 -> 6119.0526 | AA33: =+AA23-AA31 -> 10984 | AB33: =+AB23-AB31 -> 13747.621 | AC33: =+AC23-AC31 -> 15271.948 | AD33: =+AD23-AD31 -> 16887.065 | AE33: =+AE23-AE31 -> 18978.151 | AF33: =+AF23-AF31 -> 21060.953 | AG33: =+AG23*0.8885 -> 23547.413 | AH33: =+AH23*0.89 -> 26063.82 | AI33: =+AI23*0.895 -> 28700.219 | AJ33: =+AJ23*0.9 -> 31458.005 | AK33: =+AK23*0.905 -> 34163.394 | AL33: =+AL23*0.91 -> 36756.792 | AM33: =+AM23*0.915 -> 39176.277 | AN33: =+AN23*0.92 -> 41359.873 | AO33: =+AO23*0.925 -> 43248.041 | AP33: =+AP23*0.93 -> 44786.269 | AQ33: =+AQ23*0.935 -> 45927.596
A34: % | B34: =+B33/B$23 -> 0.87001408 | C34: =+C33/C$23 -> 0.86753306 | D34: =+D33/D$23 -> 0.86713287 | E34: =+E33/E$23 -> 0.86519337 | F34: =+F33/F$23 -> 0.86895811 | G34: =+G33/G$23 -> 0.87250831 | H34: =+H33/H$23 -> 0.87280164 | I34: =+I33/I$23 -> 0.86608558 | ... U34: =+U33/U$23 -> 0.89 | AA34: =+AA33/AA$23 -> 0.8535903 | AB34: =+AB33/AB$23 -> 0.87092943 | AC34: =+AC33/AC$23 -> 0.86742863 | AD34: =+AD33/AD$23 -> 0.8700636 | AE34: =+AE33/AE$23 -> 0.88249944 | AF34: =+AF33/AF$23 -> 0.88606812 | AG34: =+AG33/AG$23 -> 0.8885 | AH34: =+AH33/AH$23 -> 0.89 | ... AQ34: =+AQ33/AQ$23 -> 0.935
A35: R&D | B35: 701 | C35: 738 | D35: 775 | E35: 773 | F35: 827 | G35: 876 | H35: 881 | I35: 889 | J35: 939 | K35: 984 | L35: 1022 | M35: 999 | N35: 1026 | O35: 1082 | P35: 1088 | Q35: 1098 | R35: 1110 | S35: 1198 | T35: =+P35*1.1 -> 1196.8 | U35: =+Q35*1.1 -> 1207.8 | AA35: 2188 | AB35: 2540 | AC35: 2987 | AD35: 3473 | AE35: 3944 | AF35: 4294 | AG35: =+AG23*0.17 -> 4505.414 | AH35: =+AH23*0.17 -> 4978.4824 | AI35: =+AI23*0.17 -> 5451.4382 | AJ35: =+AJ23*0.15 -> 5243.0009 | AK35: =+AK23*0.15 -> 5662.441 | AL35: =+AL23*0.15 -> 6058.8118 | AM35: =+AM23*0.15 -> 6422.3405 | AN35: =+AN23*0.15 -> 6743.4576 | AO35: =+AO23*0.15 -> 7013.1959 | AP35: =+AP23*0.15 -> 7223.5918 | AQ35: =+AQ23*0.15 -> 7368.0636
A36: % | B36: =+B35/B$23 -> 0.16447677 | C36: =+C35/C$23 -> 0.16826265 | D36: =+D35/D$23 -> 0.17482517 | E36: =+E35/E$23 -> 0.17082873 | F36: =+F35/F$23 -> 0.17765843 | G36: =+G35/G$23 -> 0.18189369 | H36: =+H35/H$23 -> 0.1801636 | I36: =+I35/I$23 -> 0.17610935 | ... U36: =+U35/U$23 -> 0.17567131 | AA36: =+AA35/AA$23 -> 0.17003419 | AB36: =+AB35/AB$23 -> 0.16091226 | AC36: =+AC35/AC$23 -> 0.16965807 | AD36: =+AD35/AD$23 -> 0.17893761 | AE36: =+AE35/AE$23 -> 0.18339921 | AF36: =+AF35/AF$23 -> 0.18065548 | AG36: =+AG35/AG$23 -> 0.17 | AH36: =+AH35/AH$23 -> 0.17 | ... AQ36: =+AQ35/AQ$23 -> 0.15
A37: S&M | B37: 1158 | C37: 1247 | D37: 1266 | E37: 1297 | F37: 1301 | G37: 1345 | H37: 1337 | I37: 1368 | J37: 1352 | K37: 1445 | L37: 1431 | M37: 1536 | N37: 1495 | O37: 1626 | P37: 1639 | Q37: 1728 | R37: 1708 | S37: 1884 | T37: =+P37*1.1 -> 1802.9 | U37: =+Q37*1.1 -> 1900.8 | AA37: 3591 | AB37: 4321 | AC37: 4968 | AD37: 5351 | AE37: 5764 | AF37: 6488 | AG37: =+AG23*0.27 -> 7155.6574 | AH37: =+AH23*0.27 -> 7907.0015 | AI37: =+AI23*0.25 -> 8016.8209 | AJ37: =+AJ23*0.25 -> 8738.3348 | AK37: =+AK23*0.25 -> 9437.4016 | AL37: =+AL23*0.25 -> 10098.02 | AM37: =+AM23*0.2 -> 8563.1207 | AN37: =+AN23*0.2 -> 8991.2768 | AO37: =+AO23*0.2 -> 9350.9278 | AP37: =+AP23*0.2 -> 9631.4557 | AQ37: =+AQ23*0.2 -> 9824.0848
A38: % | B38: =+B37/B$23 -> 0.27170343 | C38: =+C37/C$23 -> 0.28431373 | D38: =+D37/D$23 -> 0.28558538 | E38: =+E37/E$23 -> 0.28662983 | F38: =+F37/F$23 -> 0.27948443 | G38: =+G37/G$23 -> 0.27927741 | H38: =+H37/H$23 -> 0.27341513 | I38: =+I37/I$23 -> 0.27099842 | ... U38: =+U37/U$23 -> 0.27646633 | AA38: =+AA37/AA$23 -> 0.27906435 | AB38: =+AB37/AB$23 -> 0.27374089 | AC38: =+AC37/AC$23 -> 0.28217653 | AD38: =+AD37/AD$23 -> 0.27569684 | AE38: =+AE37/AE$23 -> 0.26803069 | AF38: =+AF37/AF$23 -> 0.27296058 | AG38: =+AG37/AG$23 -> 0.27 | AH38: =+AH37/AH$23 -> 0.27 | ... AQ38: =+AQ37/AQ$23 -> 0.2
A39: G&A | B39: 269 | C39: 291 | D39: 319 | E39: 340 | F39: 331 | G39: 357 | H39: 353 | I39: 372 | J39: 352 | K39: 355 | L39: 366 | M39: 456 | N39: 367 | O39: 377 | P39: 408 | Q39: 421 | R39: 463 | S39: 546 | T39: =+P39*1.1 -> 448.8 | U39: =+Q39*1.1 -> 463.1 | AA39: 968 | AB39: 1085 | AC39: 1219 | AD39: 1413 | AE39: 1529 | AF39: 1573 | AG39: =+AF39*1.06 -> 1667.38 | AH39: =+AG39*1.06 -> 1767.4228 | AI39: =+AH39*1.06 -> 1873.4682 | AJ39: =+AI39*1.06 -> 1985.8763 | AK39: =+AJ39*1.055 -> 2095.0995 | AL39: =+AK39*1.054 -> 2208.2348 | AM39: =+AL39*1.05 -> 2318.6466 | AN39: =+AM39*1.05 -> 2434.5789 | AO39: =+AN39*1.05 -> 2556.3078 | AP39: =+AO39*1.05 -> 2684.1232 | AQ39: =+AP39*1.05 -> 2818.3294
A40: % | B40: =+B39/B$23 -> 0.063115908 | C40: =+C39/C$23 -> 0.066347469 | D40: =+D39/D$23 -> 0.071960298 | E40: =+E39/E$23 -> 0.075138122 | F40: =+F39/F$23 -> 0.071106337 | G40: =+G39/G$23 -> 0.074127907 | H40: =+H39/H$23 -> 0.072188139 | I40: =+I39/I$23 -> 0.073692552 | ... U40: =+U39/U$23 -> 0.067356669 | AA40: =+AA39/AA$23 -> 0.075225365 | AB40: =+AB39/AB$23 -> 0.068736142 | AC40: =+AC39/AC$23 -> 0.06923776 | AD40: =+AD39/AD$23 -> 0.072801278 | AE40: =+AE39/AE$23 -> 0.071099744 | AF40: =+AF39/AF$23 -> 0.066178636 | AG40: =+AG39/AG$23 -> 0.062914219 | AH40: =+AH39/AH$23 -> 0.060352101 | ... AQ40: =+AQ39/AQ$23 -> 0.057375917
A41: Acquisition fee | B41: 0 | C41: 0 | D41: 0 | E41: 0 | F41: 0 | G41: 0 | H41: 0 | I41: 0 | J41: 1000 | K41: 0 | L41: 0 | M41: 0 | N41: 0 | O41: 0 | P41: 0 | Q41: 0 | R41: 0 | S41: 0 | T41: 0 | U41: 0 | AA41: 0 | AB41: 0 | AC41: 0 | AD41: 0 | AE41: 1000 | AF41: 0 | AG41: =+AF41*1.1 -> 0 | AH41: =+AG41*1.1 -> 0 | AI41: =+AH41*1.1 -> 0 | AJ41: =+AI41*1.1 -> 0 | AK41: =+AJ41*1.1 -> 0 | AL41: =+AK41*1.1 -> 0 | AM41: =+AL41*1.1 -> 0 | AN41: =+AM41*1.1 -> 0 | ... AQ41: =+AP41*1.1 -> 0
A42: % | F42: N.M. | G42: N.M. | H42: N.M. | I42: N.M. | J42: N.M. | K42: N.M. | L42: N.M. | M42: N.M. | N42: N.M. | O42: N.M. | P42: N.M. | Q42: N.M. | R42: N.M. | S42: N.M. | T42: N.M. | U42: N.M. | AB42: N.M. | AC42: N.M. | AD42: N.M. | AE42: N.M. | AF42: N.M. | AG42: N.M. | AH42: N.M. | AI42: N.M. | AJ42: N.M. | AK42: N.M. | AL42: N.M. | AM42: N.M. | AN42: N.M. | AO42: N.M. | AP42: N.M. | AQ42: N.M.
A43: Op Exp | B43: =+B35+B37+B39+B41 -> 2128 | C43: =+C35+C37+C39+C41 -> 2276 | D43: =+D35+D37+D39+D41 -> 2360 | E43: =+E35+E37+E39+E41 -> 2410 | F43: =+F35+F37+F39+F41 -> 2459 | G43: =+G35+G37+G39+G41 -> 2578 | H43: =+H35+H37+H39+H41 -> 2571 | I43: =+I35+I37+I39+I41 -> 2629 | ... U43: =+U35+U37+U39+U41 -> 3571.7 | AA43: =SUM(AA35:AA41) -> 6747.5243 | AB43: =SUM(AB35:AB41) -> 7946.5034 | AC43: =SUM(AC35:AC41) -> 9174.5211 | AD43: =SUM(AD35:AD41) -> 10237.527 | AE43: =SUM(AE35:AE41) -> 12237.523 | AF43: =SUM(AF35:AF41) -> 12355.52 | AG43: =SUM(AG35:AG41) -> 13328.954 | AH43: =SUM(AH35:AH41) -> 14653.407 | ... AQ43: =SUM(AQ35:AQ41) -> 20010.885
A44: % | B44: =+B43/B$23 -> 0.49929611 | C44: =+C43/C$23 -> 0.51892385 | D44: =+D43/D$23 -> 0.53237085 | E44: =+E43/E$23 -> 0.53259669 | F44: =+F43/F$23 -> 0.52824919 | G44: =+G43/G$23 -> 0.535299 | H44: =+H43/H$23 -> 0.52576687 | I44: =+I43/I$23 -> 0.52080032 | ... U44: =+U43/U$23 -> 0.51949431 | AA44: =+AA43/AA$23 -> 0.52436465 | AB44: =+AB43/AB$23 -> 0.50342118 | AC44: =+AC43/AC$23 -> 0.52110196 | AD44: =+AD43/AD$23 -> 0.5274629 | AE44: =+AE43/AE$23 -> 0.56905476 | AF44: =+AF43/AF$23 -> 0.51981656 | AG44: =+AG43/AG$23 -> 0.5029332 | AH44: =+AH43/AH$23 -> 0.50036919 | ... AQ44: =+AQ43/AQ$23 -> 0.40738421
A45: Op Inc / EBIT | B45: =+B33-B43 -> 1580 | C45: =+C33-C43 -> 1529 | D45: =+D33-D43 -> 1484 | E45: =+E33-E43 -> 1505 | F45: =+F33-F43 -> 1586 | G45: =+G33-G43 -> 1624 | H45: =+H33-H43 -> 1697 | I45: =+I33-I43 -> 1743 | ... U45: =+U33-U43 -> 2547.3526 | AA45: =+AA33-AA43 -> 4236.4757 | AB45: =+AB33-AB43 -> 5801.1176 | AC45: =+AC33-AC43 -> 6097.4273 | AD45: =+AD33-AD43 -> 6649.5371 | AE45: =+AE33-AE43 -> 6740.628 | AF45: =+AF33-AF43 -> 8705.4335 | AG45: =+AG33-AG43 -> 10218.459 | AH45: =+AH33-AH43 -> 11410.413 | ... AQ45: =+AQ33-AQ43 -> 25916.711
A46: % | B46: =+B45/B$23 -> 0.37071797 | C46: =+C45/C$23 -> 0.34860921 | D46: =+D45/D$23 -> 0.33476201 | E46: =+E45/E$23 -> 0.33259669 | F46: =+F45/F$23 -> 0.34070892 | G46: =+G45/G$23 -> 0.3372093 | H46: =+H45/H$23 -> 0.34703476 | I46: =+I45/I$23 -> 0.34528526 | ... U46: =+U45/U$23 -> 0.37050569 | AA46: =+AA45/AA$23 -> 0.32922565 | AB46: =+AB45/AB$23 -> 0.36750825 | AC46: =+AC45/AC$23 -> 0.34632667 | AD46: =+AD45/AD$23 -> 0.3426007 | AE46: =+AE45/AE$23 -> 0.31344469 | AF46: =+AF45/AF$23 -> 0.36625157 | AG46: =+AG45/AG$23 -> 0.3855668 | AH46: =+AH45/AH$23 -> 0.38963081 | ... AQ46: =+AQ45/AQ$23 -> 0.52761579
A47: Interest Exp | B47: -28 | C47: -28 | D47: -28 | E47: -28 | F47: -32 | G47: -26 | H47: -27 | I47: -28 | J47: -27 | K47: -41 | L47: -51 | M47: -50 | N47: -62 | O47: -68 | P47: -67 | Q47: -66 | R47: -63 | S47: -65 | T47: -62 | U47: -60 | AA47: -116 | AB47: -113 | AC47: -112 | AD47: -113 | AE47: -169 | AF47: -263 | AG47: =+AF90*$AU$66-($AF$109+$AF$110)*(Bond!$C$12/100) -> -256.61313 | AH47: =+AG90*$AU$66-($AF$109+$AF$110)*(Bond!$C$12/100) -> -91.863588 | AI47: =+AH90*$AU$66-($AF$109+$AF$110)*(Bond!$C$12/100) -> 95.153197 | AJ47: =+AI90*$AU$66-($AF$109+$AF$110)*(Bond!$C$12/100) -> 317.27532 | AK47: =+AJ90*$AU$66-($AF$109+$AF$110)*(Bond!$C$12/100) -> 580.62253 | AL47: =+AK90*$AU$66-($AF$109+$AF$110)*(Bond!$C$12/100) -> 876.0394 | AM47: =+AL90*$AU$66-($AF$109+$AF$110)*(Bond!$C$12/100) -> 1203.682 | AN47: =+AM90*$AU$66-($AF$109+$AF$110)*(Bond!$C$12/100) -> 1597.4971 | ... AQ47: =+AP90*$AU$66-($AF$109+$AF$110)*(Bond!$C$12/100) -> 2973.1897
A48: % | B48: =+B47/B$23 -> -0.0065696856 | C48: =+C47/C$23 -> -0.0063839489 | D48: =+D47/D$23 -> -0.0063162644 | E48: =+E47/E$23 -> -0.0061878453 | F48: =+F47/F$23 -> -0.0068743287 | G48: =+G47/G$23 -> -0.0053986711 | H48: =+H47/H$23 -> -0.0055214724 | I48: =+I47/I$23 -> -0.0055467512 | ... U48: =+U47/U$23 -> -0.0087268411 | AA48: =+AA47/AA$23 -> -0.0090146099 | AB48: =+AB47/AB$23 -> -0.007158695 | AC48: =+AC47/AC$23 -> -0.0063614677 | AD48: =+AD47/AD$23 -> -0.0058220413 | AE48: =+AE47/AE$23 -> -0.0078586375 | AF48: =+AF47/AF$23 -> -0.011064832 | AG48: =+AG47/AG$23 -> -0.0096826244 | AH48: =+AH47/AH$23 -> -0.0031368615 | ... AQ48: =+AQ47/AQ$23 -> 0.060528584
A49: Investemnt gain | B49: -9 | C49: -8 | D49: -6 | E49: 4 | F49: 1 | G49: 5 | H49: 6 | I49: 4 | J49: 18 | K49: 4 | L49: 12 | M49: 14 | N49: 6 | O49: 2 | P49: 23 | Q49: 12 | R49: 5 | S49: 18 | T49: 6 | U49: 6 | AA49: 13 | AB49: 16 | AC49: -19 | AD49: 16 | AE49: 48 | AF49: 43 | AG49: 35 | AH49: 70 | AI49: 70 | AJ49: 70 | AK49: 70 | AL49: 70 | AM49: 70 | AN49: 70 | AO49: 70 | AP49: 70 | AQ49: 70
A50: % | B50: =+B49/B$23 -> -0.0021116847 | C50: =+C49/C$23 -> -0.0018239854 | D50: =+D49/D$23 -> -0.0013534852 | E50: =+E49/E$23 -> 0.0008839779 | F50: =+F49/F$23 -> 0.00021482277 | G50: =+G49/G$23 -> 0.001038206 | H50: =+H49/H$23 -> 0.0012269939 | I50: =+I49/I$23 -> 0.00079239303 | ... U50: =+U49/U$23 -> 0.00087268411 | AA50: =+AA49/AA$23 -> 0.001010258 | AB50: =+AB49/AB$23 -> 0.0010136205 | AC50: =+AC49/AC$23 -> -0.0010791776 | AD50: =+AD49/AD$23 -> 0.00082435983 | AE50: =+AE49/AE$23 -> 0.0022320391 | AF50: =+AF49/AF$23 -> 0.0018090791 | AG50: =+AG49/AG$23 -> 0.0013206334 | AH50: =+AH49/AH$23 -> 0.0023902866 | ... AQ50: =+AQ49/AQ$23 -> 0.0014250691
A51: Other Income | B51: 0 | C51: -1 | D51: 6 | E51: 36 | F51: 43 | G51: 47 | H51: 67 | I51: 89 | J51: 70 | K51: 82 | L51: 89 | M51: 70 | N51: 75 | O51: 58 | P51: 58 | Q51: 57 | R51: 62 | S51: 47 | T51: 50 | U51: 50 | AA51: 42 | AB51: 0 | AC51: 41 | AD51: 246 | AE51: 311 | AF51: 248 | AG51: 300 | AH51: 300 | AI51: =+AH90*$AU$66 -> 359.46632 | AJ51: =+AI90*$AU$66 -> 581.58845 | AK51: =+AJ90*$AU$66 -> 844.93565 | AL51: =+AK90*$AU$66 -> 1140.3525 | AM51: =+AL90*$AU$66 -> 1467.9951 | AN51: =+AM90*$AU$66 -> 1861.8102 | AO51: =+AN90*$AU$66 -> 2289.3216 | AP51: =+AO90*$AU$66 -> 2748.7062 | AQ51: =+AP90*$AU$66 -> 3237.5028
A52: % | B52: =+B51/B$23 -> 0 | C52: =+C51/C$23 -> -0.00022799818 | D52: =+D51/D$23 -> 0.0013534852 | E52: =+E51/E$23 -> 0.0079558011 | F52: =+F51/F$23 -> 0.0092373792 | G52: =+G51/G$23 -> 0.0097591362 | H52: =+H51/H$23 -> 0.013701431 | I52: =+I51/I$23 -> 0.017630745 | ... U52: =+U51/U$23 -> 0.0072723676 | AA52: =+AA51/AA$23 -> 0.0032639105 | AB52: =+AB51/AB$23 -> 0 | AC52: =+AC51/AC$23 -> 0.0023287516 | AD52: =+AD51/AD$23 -> 0.012674532 | AE52: =+AE51/AE$23 -> 0.014461753 | AF52: =+AF51/AF$23 -> 0.010433758 | AG52: =+AG51/AG$23 -> 0.011319715 | AH52: =+AH51/AH$23 -> 0.010244086 | ... AQ52: =+AQ51/AQ$23 -> 0.065909505
A53: Pretax | B53: =+B45+B47+B49+B51 -> 1543 | C53: =+C45+C47+C49+C51 -> 1492 | D53: =+D45+D47+D49+D51 -> 1456 | E53: =+E45+E47+E49+E51 -> 1517 | F53: =+F45+F47+F49+F51 -> 1598 | G53: =+G45+G47+G49+G51 -> 1650 | H53: =+H45+H47+H49+H51 -> 1743 | I53: =+I45+I47+I49+I51 -> 1808 | ... U53: =+U45+U47+U49+U51 -> 2543.3526 | AA53: =+AA45+AA47+AA49+AA51 -> 4175.4757 | AB53: =+AB45+AB47+AB49+AB51 -> 5704.1176 | AC53: =+AC45+AC47+AC49+AC51 -> 6007.4273 | AD53: =+AD45+AD47+AD49+AD51 -> 6798.5371 | AE53: =+AE45+AE47+AE49+AE51 -> 6930.628 | AF53: =+AF45+AF47+AF49+AF51 -> 8733.4335 | AG53: =+AG45+AG47+AG49+AG51 -> 10296.846 | AH53: =+AH45+AH47+AH49+AH51 -> 11688.549 | ... AQ53: =+AQ45+AQ47+AQ49+AQ51 -> 32197.404
A54: % | B54: =+B53/B$23 -> 0.3620366 | C54: =+C53/C$23 -> 0.34017328 | D54: =+D53/D$23 -> 0.32844575 | E54: =+E53/E$23 -> 0.33524862 | F54: =+F53/F$23 -> 0.34328679 | G54: =+G53/G$23 -> 0.34260797 | H54: =+H53/H$23 -> 0.35644172 | I54: =+I53/I$23 -> 0.35816165 | ... U54: =+U53/U$23 -> 0.3699239 | AA54: =+AA53/AA$23 -> 0.32448521 | AB54: =+AB53/AB$23 -> 0.36136317 | AC54: =+AC53/AC$23 -> 0.34121477 | AD54: =+AD53/AD$23 -> 0.35027756 | AE54: =+AE53/AE$23 -> 0.32227984 | AF54: =+AF53/AF$23 -> 0.36742957 | AG54: =+AG53/AG$23 -> 0.38852453 | AH54: =+AH53/AH$23 -> 0.39912832 | ... AQ54: =+AQ53/AQ$23 -> 0.65547895
A55: Taxes | B55: 277 | C55: 314 | D55: 320 | E55: 341 | F55: 351 | G55: 355 | H55: 340 | I55: 325 | J55: 348 | K55: 357 | L55: 358 | M55: 308 | N55: 371 | O55: 410 | P55: 415 | Q55: 408 | R55: 533 | S55: 526 | T55: =+T53*0.22 -> 541.42994 | U55: =+U53*0.22 -> 559.53757 | AA55: -1084 | AB55: 883 | AC55: 1252 | AD55: 1371 | AE55: 1371 | AF55: 1604 | AG55: =+AG53*0.2 -> 2059.3692 | AH55: =+AH53*0.2 -> 2337.7098 | AI55: =+AI53*0.2 -> 2776.5265 | AJ55: =+AJ53*0.2 -> 3291.8401 | AK55: =+AK53*0.2 -> 3692.7109 | AL55: =+AL53*0.2 -> 4095.5325 | AM55: =+AM53*0.2 -> 4922.6885 | AN55: =+AN53*0.2 -> 5343.8926 | ... AQ55: =+AQ53*0.2 -> 6439.4808
A56: % | B56: =+B55/B$23 -> 0.064992961 | C56: =+C55/C$23 -> 0.071591427 | D56: =+D55/D$23 -> 0.072185879 | E56: =+E55/E$23 -> 0.075359116 | F56: =+F55/F$23 -> 0.075402793 | G56: =+G55/G$23 -> 0.073712625 | H56: =+H55/H$23 -> 0.069529652 | I56: =+I55/I$23 -> 0.064381933 | ... U56: =+U55/U$23 -> 0.081383258 | AA56: =+AA55/AA$23 -> -0.084239975 | AB56: =+AB55/AB$23 -> 0.055939183 | AC56: =+AC55/AC$23 -> 0.071112121 | AD56: =+AD55/AD$23 -> 0.070637333 | AE56: =+AE55/AE$23 -> 0.063752616 | AF56: =+AF55/AF$23 -> 0.067482856 | AG56: =+AG55/AG$23 -> 0.077704906 | AH56: =+AH55/AH$23 -> 0.079825665 | ... AQ56: =+AQ55/AQ$23 -> 0.13109579
A57: Net Inc | B57: =+B53-B55 -> 1266 | C57: =+C53-C55 -> 1178 | D57: =+D53-D55 -> 1136 | E57: =+E53-E55 -> 1176 | F57: =+F53-F55 -> 1247 | G57: =+G53-G55 -> 1295 | H57: =+H53-H55 -> 1403 | I57: =+I53-I55 -> 1483 | ... U57: =+U53-U55 -> 1983.815 | AA57: =+AA53-AA55 -> 5259.4757 | AB57: =+AB53-AB55 -> 4821.1176 | AC57: =+AC53-AC55 -> 4755.4273 | AD57: =+AD53-AD55 -> 5427.5371 | AE57: =+AE53-AE55 -> 5559.628 | AF57: =+AF53-AF55 -> 7129.4335 | AG57: =+AG53-AG55 -> 8237.4768 | AH57: =+AH53-AH55 -> 9350.8393 | ... AQ57: =+AQ53-AQ55 -> 25757.923 | AR57: =+AQ57*(1+$AU$64) -> 25500.344 | AS57: =+AR57*(1+$AU$64) -> 25245.34 | AT57: =+AS57*(1+$AU$64) -> 24992.887 | AU57: =+AT57*(1+$AU$64) -> 24742.958 | AV57: =+AU57*(1+$AU$64) -> 24495.529 | AW57: =+AV57*(1+$AU$64) -> 24250.573 | AX57: =+AW57*(1+$AU$64) -> 24008.068 | AY57: =+AX57*(1+$AU$64) -> 23767.987 | ... DZ57: =+DY57*(1+$AU$64) -> 10744.168
A58: % | B58: =+B57/B$23 -> 0.29704364 | C58: =+C57/C$23 -> 0.26858185 | D58: =+D57/D$23 -> 0.25625987 | E58: =+E57/E$23 -> 0.2598895 | F58: =+F57/F$23 -> 0.267884 | G58: =+G57/G$23 -> 0.26889535 | H58: =+H57/H$23 -> 0.28691207 | I58: =+I57/I$23 -> 0.29377971 | ... U58: =+U57/U$23 -> 0.28854064 | AA58: =+AA57/AA$23 -> 0.40872518 | AB58: =+AB57/AB$23 -> 0.30542399 | AC58: =+AC57/AC$23 -> 0.27010265 | AD58: =+AD57/AD$23 -> 0.27964022 | AE58: =+AE57/AE$23 -> 0.25852723 | AF58: =+AF57/AF$23 -> 0.29994671 | AG58: =+AG57/AG$23 -> 0.31081962 | AH58: =+AH57/AH$23 -> 0.31930266 | ... AQ58: =+AQ57/AQ$23 -> 0.52438316
A59: EPS | B59: =+B57/B61 -> 2.6652632 | C59: =+C57/C61 -> 2.4904863 | D59: =+D57/D61 -> 2.4221748 | E59: =+E57/E61 -> 2.5236052 | F59: =+F57/F61 -> 2.7108696 | G59: =+G57/G61 -> 2.8213508 | H59: =+H57/H61 -> 3.0566449 | I59: =+I57/I61 -> 3.2309368 | ... U59: =+U57/U61 -> 5.035061 | AA59: =+AA57/AA61 -> 10.84428 | AB59: =+AB57/AB61 -> 10.023114 | AC59: =+AC57/AC61 -> 10.096449 | AD59: =+AD57/AD61 -> 11.824699 | AE59: =+AE57/AE61 -> 12.354729 | AF59: =+AF57/AF61 -> 16.696565 | AG59: =+AG57/AG61 -> 19.685219 | AH59: =+AH57/AH61 -> 22.801875 | ... AQ59: =+AQ57/AQ61 -> 75.334886
A60: % | F60: =+F59/B59-1 -> 0.017111409 | G60: =+G59/C59-1 -> 0.13285137 | H60: =+H59/D59-1 -> 0.2619423 | I60: =+I59/E59-1 -> 0.28028619 | J60: =+J59/F59-1 -> -0.49844539 | K60: =+K59/G59-1 -> 0.2362181 | L60: =+L59/H59-1 -> 0.22975639 | M60: =+M59/I59-1 -> 0.17585 | ... U60: =+U59/Q59-1 -> 0.131261 | AB60: =+AB59/AA59-1 -> -0.075723436 | AC60: =+AC59/AB59-1 -> 0.0073165905 | AD60: =+AD59/AC59-1 -> 0.17117413 | AE60: =+AE59/AD59-1 -> 0.044823926 | AF60: =+AF59/AE59-1 -> 0.35143115 | AG60: =+AG59/AF59-1 -> 0.17899811 | AH60: =+AH59/AG59-1 -> 0.15832468 | AI60: =+AI59/AH59-1 -> 0.21195126 | ... AQ60: =+AQ59/AP59-1 -> 0.07544084
A61: Shares | B61: 475 | C61: 473 | D61: 469 | E61: 466 | F61: 460 | G61: 459 | H61: 459 | I61: 459 | J61: 456 | K61: 451 | L61: 448 | M61: 443 | N61: 438 | O61: 429 | P61: 424 | Q61: 417 | R61: 411 | S61: 402 | T61: =+S61*0.99 -> 397.98 | U61: =+T61*0.99 -> 394.0002 | AA61: 485 | AB61: 481 | AC61: 471 | AD61: 459 | AE61: 450 | AF61: 427 | AG61: =+AF61*0.98 -> 418.46 | AH61: =+AG61*0.98 -> 410.0908 | AI61: =+AH61*0.98 -> 401.88898 | AJ61: =+AI61*0.98 -> 393.8512 | AK61: =+AJ61*0.98 -> 385.97418 | AL61: =+AK61*0.98 -> 378.2547 | AM61: =+AL61*0.98 -> 370.6896 | AN61: =+AM61*0.98 -> 363.27581 | ... AQ61: =+AP61*0.98 -> 341.91229
A62: % | F62: =+F61/B61-1 -> -0.031578947 | G62: =+G61/C61-1 -> -0.029598309 | H62: =+H61/D61-1 -> -0.021321962 | I62: =+I61/E61-1 -> -0.015021459 | J62: =+J61/F61-1 -> -0.0086956522 | K62: =+K61/G61-1 -> -0.017429194 | L62: =+L61/H61-1 -> -0.023965142 | M62: =+M61/I61-1 -> -0.034858388 | ... U62: =+U61/Q61-1 -> -0.055155396 | AB62: =+AB61/AA61-1 -> -0.0082474227 | AC62: =+AC61/AB61-1 -> -0.020790021 | AD62: =+AD61/AC61-1 -> -0.025477707 | AE62: =+AE61/AD61-1 -> -0.019607843 | AF62: =+AF61/AE61-1 -> -0.051111111 | AG62: =+AG61/AF61-1 -> -0.02 | AH62: =+AH61/AG61-1 -> -0.02 | AI62: =+AI61/AH61-1 -> -0.02 | ... AQ62: =+AQ61/AP61-1 -> -0.02
AW63: Gordon Growth Model
A64: Revenue q/q | C64: =+C23/B23-1 -> 0.029094322 | D64: =+D23/C23-1 -> 0.010715914 | E64: =+E23/D23-1 -> 0.02075344 | F64: =+F23/E23-1 -> 0.028729282 | G64: =+G23/F23-1 -> 0.034586466 | H64: =+H23/G23-1 -> 0.015365449 | I64: =+I23/H23-1 -> 0.032310838 | J64: =+J23/I23-1 -> 0.026545166 | ... U64: =+U23/T23-1 -> 0.034402138 | AT64: Terminal | AU64: -0.01 | AW64: Payout Ratio | AX64: =+SUM(P166:S166)/SUM(P57:S57) -> 1.2151058
A65: Gross Margin | B65: =+B33/B23 -> 0.87001408 | C65: =+C33/C23 -> 0.86753306 | D65: =+D33/D23 -> 0.86713287 | E65: =+E33/E23 -> 0.86519337 | F65: =+F33/F23 -> 0.86895811 | G65: =+G33/G23 -> 0.87250831 | H65: =+H33/H23 -> 0.87280164 | I65: =+I33/I23 -> 0.86608558 | ... U65: =+U33/U23 -> 0.89 | AA65: =+AA33/AA23 -> 0.8535903 | AB65: =+AB33/AB23 -> 0.87092943 | AC65: =+AC33/AC23 -> 0.86742863 | AD65: =+AD33/AD23 -> 0.8700636 | AE65: =+AE33/AE23 -> 0.88249944 | AF65: =+AF33/AF23 -> 0.88606812 | AG65: =+AG33/AG23 -> 0.8885 | AH65: =+AH33/AH23 -> 0.89 | ... AQ65: =+AQ33/AQ23 -> 0.935 | AT65: Discount | AU65: =+Main!H10 -> 0.12633021 | AW65: Sustained Growth
A66: Op Margin | B66: =+B45/B23 -> 0.37071797 | C66: =+C45/C23 -> 0.34860921 | D66: =+D45/D23 -> 0.33476201 | E66: =+E45/E23 -> 0.33259669 | F66: =+F45/F23 -> 0.34070892 | G66: =+G45/G23 -> 0.3372093 | H66: =+H45/H23 -> 0.34703476 | I66: =+I45/I23 -> 0.34528526 | ... U66: =+U45/U23 -> 0.37050569 | AA66: =+AA45/AA23 -> 0.32922565 | AB66: =+AB45/AB23 -> 0.36750825 | AC66: =+AC45/AC23 -> 0.34632667 | AD66: =+AD45/AD23 -> 0.3426007 | AE66: =+AE45/AE23 -> 0.31344469 | AF66: =+AF45/AF23 -> 0.36625157 | AG66: =+AG45/AG23 -> 0.3855668 | AH66: =+AH45/AH23 -> 0.38963081 | ... AQ66: =+AQ45/AQ23 -> 0.52761579 | AT66: ROIC | AU66: 0.02 | AW66: Equity Value
A67: NI Margin | B67: =+B57/B23 -> 0.29704364 | C67: =+C57/C23 -> 0.26858185 | D67: =+D57/D23 -> 0.25625987 | E67: =+E57/E23 -> 0.2598895 | F67: =+F57/F23 -> 0.267884 | G67: =+G57/G23 -> 0.26889535 | H67: =+H57/H23 -> 0.28691207 | I67: =+I57/I23 -> 0.29377971 | ... U67: =+U57/U23 -> 0.28854064 | AA67: =+AA57/AA23 -> 0.40872518 | AB67: =+AB57/AB23 -> 0.30542399 | AC67: =+AC57/AC23 -> 0.27010265 | AD67: =+AD57/AD23 -> 0.27964022 | AE67: =+AE57/AE23 -> 0.25852723 | AF67: =+AF57/AF23 -> 0.29994671 | AG67: =+AG57/AG23 -> 0.31081962 | AH67: =+AH57/AH23 -> 0.31930266 | ... AQ67: =+AQ57/AQ23 -> 0.52438316 | AT67: NPV | AU67: =NPV(AU65,AG57:DZ57) -> 136435.38 | AW67: Just. P/E
A68: Tax Rate | B68: =+B55/B53 -> 0.17952041 | C68: =+C55/C53 -> 0.21045576 | D68: =+D55/D53 -> 0.21978022 | E68: =+E55/E53 -> 0.22478576 | F68: =+F55/F53 -> 0.21964956 | G68: =+G55/G53 -> 0.21515152 | H68: =+H55/H53 -> 0.19506598 | I68: =+I55/I53 -> 0.17975664 | ... U68: =+U55/U53 -> 0.22 | AA68: =+AA55/AA53 -> -0.25961114 | AB68: =+AB55/AB53 -> 0.15480045 | AC68: =+AC55/AC53 -> 0.20840868 | AD68: =+AD55/AD53 -> 0.20166103 | AE68: =+AE55/AE53 -> 0.19781757 | AF68: =+AF55/AF53 -> 0.18366202 | AG68: =+AG55/AG53 -> 0.2 | AH68: =+AH55/AH53 -> 0.2 | ... AQ68: =+AQ55/AQ53 -> 0.2 | AT68: Share | AU68: =+AU67/Main!F1 -> 492.54651
A69: Rule of 40 | F69: =+F66+F24 -> 0.43291915 | G69: =+G66+G24 -> 0.43524852 | H69: =+H66+H24 -> 0.45012522 | I69: =+I66+I24 -> 0.46086537 | J69: =+J66+J24 -> 0.28824055 | K69: =+K66+K24 -> 0.45742456 | L69: =+L66+L24 -> 0.47427367 | M69: =+M66+M24 -> 0.45962909 | ... U69: =+U66+U24 -> 0.48050569 | AA69: =+AA66+AA24 -> 0.32922565 | AB69: =+AB66+AB24 -> 0.5941946 | AC69: =+AC66+AC24 -> 0.46168935 | AD69: =+AD66+AD24 -> 0.44500897 | AE69: =+AE66+AE24 -> 0.42143583 | AF69: =+AF66+AF24 -> 0.47152941 | AG69: =+AG66+AG24 -> 0.5005668 | AH69: =+AH66+AH24 -> 0.49463081 | ... AQ69: =+AQ66+AQ24 -> 0.54761579 | AT69: Diff | AU69: =+AU68/Main!F1-1 -> 0.77814625 | AW69: Dividend Payout | AX69: 0
A70: Incr. Margin | F70: =(F45-B45)/(F23-B23) -> 0.015267176 | G70: =(G45-C45)/(G23-C23) -> 0.22093023 | H70: =(H45-D45)/(H23-D23) -> 0.46608315 | I70: =(I45-E45)/(I23-E23) -> 0.45506692 | J70: =(J45-F45)/(J23-F23) -> -1.288425 | K70: =(K45-G45)/(K23-G23) -> 0.52941176 | L70: =(L45-H45)/(L23-H23) -> 0.56949807 | M70: =(M45-I45)/(M23-I23) -> 0.38351254 | ... S70: =(S45-O45)/(S23-O23) -> 0.17315436 | AB70: =+(AB45-AA45)/(AB23-AA23) -> 0.53638738 | AC70: =+(AC45-AB45)/(AC23-AB23) -> 0.1627181 | AD70: =+(AD45-AC45)/(AD23-AC23) -> 0.30621728 | AE70: =+(AE45-AD45)/(AE23-AD23) -> 0.043459426 | AF70: =+(AF45-AE45)/(AF23-AE23) -> 0.86784693 | AG70: =+(AG45-AF45)/(AG23-AF23) -> 0.5535254 | AH70: =+(AH45-AG45)/(AH23-AG23) -> 0.42833565 | AI70: =+(AI45-AH45)/(AI23-AH23) -> 0.70004866 | ... AQ70: =+(AQ45-AP45)/(AQ23-AP23) -> 0.69565678 | AW70: Debt-to-EBITDA | AX70: =+(-S92+S109+S110) -> 1726
A72: Subscription % Rev | B72: =+B17/B$23 -> 0.92867198 | C72: =+C17/C$23 -> 0.92795258 | D72: =+D17/D$23 -> 0.93119783 | E72: =+E17/E$23 -> 0.93524862 | F72: =+F17/F$23 -> 0.93941998 | G72: =+G17/G$23 -> 0.93791528 | H72: =+H17/H$23 -> 0.94703476 | I72: =+I17/I$23 -> 0.943542 | ... S72: =+S17/S$23 -> 0.96947718 | AA72: =+AA17/AA$23 -> 0.9034815 | AB72: =+AB17/AB$23 -> 0.92321825 | AC72: =+AC17/AC$23 -> 0.93081904 | AD72: =+AD17/AD$23 -> 0.9420372 | AE72: =+AE17/AE$23 -> 0.9542432 | AF72: =+AF17/AF$23 -> 0.96360806 | AG72: =+AG17/AG$23 -> 0 | AH72: =+AH17/AH$23 -> 0
A73: Product % Rev | B73: =+B19/B$23 -> 0.034021586 | C73: =+C19/C$23 -> 0.033287734 | D73: =+D19/D$23 -> 0.02842319 | E73: =+E19/E$23 -> 0.025414365 | F73: =+F19/F$23 -> 0.025778733 | G73: =+G19/G$23 -> 0.026993355 | H73: =+H19/H$23 -> 0.019631902 | I73: =+I19/I$23 -> 0.022583201 | ... S73: =+S19/S$23 -> 0.013448172 | AA73: =+AA19/AA$23 -> 0.039400062 | AB73: =+AB19/AB$23 -> 0.035159962 | AC73: =+AC19/AC$23 -> 0.030216971 | AD73: =+AD19/AD$23 -> 0.023700345 | AE73: =+AE19/AE$23 -> 0.017949314 | AF73: =+AF19/AF$23 -> 0.013673272 | AG73: =+AG19/AG$23 -> 0 | AH73: =+AH19/AH$23 -> 0
A74: Services % Rev | B74: =+B21/B$23 -> 0.037306429 | C74: =+C21/C$23 -> 0.03875969 | D74: =+D21/D$23 -> 0.040378976 | E74: =+E21/E$23 -> 0.039337017 | F74: =+F21/F$23 -> 0.034801289 | G74: =+G21/G$23 -> 0.035091362 | H74: =+H21/H$23 -> 0.033333333 | I74: =+I21/I$23 -> 0.033874802 | ... S74: =+S21/S$23 -> 0.017074645 | AA74: =+AA21/AA$23 -> 0.057118433 | AB74: =+AB21/AB$23 -> 0.041621793 | AC74: =+AC21/AC$23 -> 0.03896399 | AD74: =+AD21/AD$23 -> 0.034262456 | AE74: =+AE21/AE$23 -> 0.027807487 | AF74: =+AF21/AF$23 -> 0.022718667 | AG74: =+AG21/AG$23 -> 0 | AH74: =+AH21/AH$23 -> 0
AW75: EV | AX75: =+AU78 -> 125707.45
AT76: Terminal | AU76: -0.01 | AW76: Debt (-) | AX76: =+Main!F5 -> 6645
A77: ROA | C77: =+C57/AVERAGE(B103:C103) -> 0.045045658 | D77: =+D57/AVERAGE(C103:D103) -> 0.042811011 | E77: =+E57/AVERAGE(D103:E103) -> 0.043628746 | F77: =+F57/AVERAGE(E103:F103) -> 0.046328998 | G77: =+G57/AVERAGE(F103:G103) -> 0.047518231 | H77: =+H57/AVERAGE(G103:H103) -> 0.049289969 | I77: =+I57/AVERAGE(H103:I103) -> 0.050382699 | J77: =+J57/AVERAGE(I103:J103) -> 0.021185565 | ... S77: =+S57/AVERAGE(R103:S103) -> 0.057413599 | AB77: =+AB57/AVERAGE(AA103:AB103) -> 0.18713658 | AC77: =+AC57/AVERAGE(AB103:AC103) -> 0.17481225 | AD77: =+AD57/AVERAGE(AC103:AD103) -> 0.19062685 | AE77: =+AE57/AVERAGE(AD103:AE103) -> 0.1852928 | AF77: =+AF57/AVERAGE(AE103:AF103) -> 0.23873758 | AT77: Discount | AU77: =+Main!H10 -> 0.12633021 | AW77: Cash (+) | AX77: =+Main!F4 -> 5626
A78: ROE | C78: =+C57/AVERAGE(B122:C122) -> 0.084870317 | D78: =+D57/AVERAGE(C122:D122) -> 0.080118485 | E78: =+E57/AVERAGE(D122:E122) -> 0.082746974 | F78: =+F57/AVERAGE(E122:F122) -> 0.088748132 | G78: =+G57/AVERAGE(F122:G122) -> 0.089653501 | H78: =+H57/AVERAGE(G122:H122) -> 0.091657412 | I78: =+I57/AVERAGE(H122:I122) -> 0.091843686 | J78: =+J57/AVERAGE(I122:J122) -> 0.038776659 | ... S78: =+S57/AVERAGE(R122:S122) -> 0.1491874 | AB78: =+AB57/AVERAGE(AA122:AB122) -> 0.34361695 | AC78: =+AC57/AVERAGE(AB122:AC122) -> 0.32968853 | AD78: =+AD57/AVERAGE(AC122:AD122) -> 0.35510073 | AE78: =+AE57/AVERAGE(AD122:AE122) -> 0.36310146 | AF78: =+AF57/AVERAGE(AE122:AF122) -> 0.55421591 | AT78: EV | AU78: =+NPV(AU77,AG87:AP87,AQ87+AU79) -> 125707.45 | AW78: Equity Value | AX78: =+AX75-AX76+AX77 -> 124688.45
A79: A. Turnover | C79: =+C23/AVERAGE(B103:C103) -> 0.16771669 | D79: =+D23/AVERAGE(C103:D103) -> 0.16706093 | E79: =+E23/AVERAGE(D103:E103) -> 0.16787422 | F79: =+F23/AVERAGE(E103:F103) -> 0.17294425 | G79: =+G23/AVERAGE(F103:G103) -> 0.17671645 | H79: =+H23/AVERAGE(G103:H103) -> 0.17179469 | I79: =+I23/AVERAGE(H103:I103) -> 0.17149822 | J79: =+J23/AVERAGE(I103:J103) -> 0.17707032 | ... S79: =+S23/AVERAGE(R103:S103) -> 0.22194112 | AB79: =+AB23/AVERAGE(AA103:AB103) -> 0.61271083 | AC79: =+AC23/AVERAGE(AB103:AC103) -> 0.64720672 | AD79: =+AD23/AVERAGE(AC103:AD103) -> 0.68168608 | AE79: =+AE23/AVERAGE(AD103:AE103) -> 0.71672449 | AF79: =+AF23/AVERAGE(AE103:AF103) -> 0.79593329 | AT79: TV | AU79: =+AQ87*(1+AU76)/(AU77-AU76) -> 161022.41 | AW79: Shares | AX79: =+Main!F2 -> 397.5
A80: Financial Leverage | C80: =+AVERAGE(B115:C115)/AVERAGE(B122:C122) -> 0.88410234 | D80: =+AVERAGE(C115:D115)/AVERAGE(C122:D122) -> 0.87145552 | E80: =+AVERAGE(D115:E115)/AVERAGE(D122:E122) -> 0.89662831 | F80: =+AVERAGE(E115:F115)/AVERAGE(E122:F122) -> 0.93334211 | G80: =+AVERAGE(F115:G115)/AVERAGE(F122:G122) -> 0.90396882 | H80: =+AVERAGE(G115:H115)/AVERAGE(G122:H122) -> 0.85956495 | I80: =+AVERAGE(H115:I115)/AVERAGE(H122:I122) -> 0.82293105 | J80: =+AVERAGE(I115:J115)/AVERAGE(I122:J122) -> 0.83034234 | ... S80: =+AVERAGE(R115:S115)/AVERAGE(R122:S122) -> 1.5984804 | AB80: =+AVERAGE(AA115:AB115)/AVERAGE(AA122:AB122) -> 0.83618618 | AC80: =+AVERAGE(AB115:AC115)/AVERAGE(AB122:AC122) -> 0.8859613 | AD80: =+AVERAGE(AC115:AD115)/AVERAGE(AC122:AD122) -> 0.86280878 | AE80: =+AVERAGE(AD115:AE115)/AVERAGE(AD122:AE122) -> 0.95961234 | AF80: =+AVERAGE(AE115:AF115)/AVERAGE(AE122:AF122) -> 1.3214482 | AT80: Diff | AU80: =+AU78/Main!F6-1 -> 0.13121037 | AW80: Price | AX80: =+AX78/AX79 -> 313.68163
A81: Financial Leverage % | C81: =+C78-C77 -> 0.039824659 | D81: =+D78-D77 -> 0.037307474 | E81: =+E78-E77 -> 0.039118228 | F81: =+F78-F77 -> 0.042419134 | G81: =+G78-G77 -> 0.04213527 | H81: =+H78-H77 -> 0.042367442 | I81: =+I78-I77 -> 0.041460987 | J81: =+J78-J77 -> 0.017591094 | ... S81: =+S78-S77 -> 0.0917738 | AB81: =+AB78-AB77 -> 0.15648037 | AC81: =+AC78-AC77 -> 0.15487628 | AD81: =+AD78-AD77 -> 0.16447388 | AE81: =+AE78-AE77 -> 0.17780867 | AF81: =+AF78-AF77 -> 0.31547833 | AX81: =+AX80/Main!F1-1 -> 0.13242466
A83: NWC | B83: =+B93+B94+B95-(B106+B107-B109) -> 3608 | C83: =+C93+C94+C95-(C106+C107-C109) -> 3061 | D83: =+D93+D94+D95-(D106+D107-D109) -> 3174 | E83: =+E93+E94+E95-(E106+E107-E109) -> 3091 | F83: =+F93+F94+F95-(F106+F107-F109) -> 2601 | G83: =+G93+G94+G95-(G106+G107-G109) -> 1686 | H83: =+H93+H94+H95-(H106+H107-H109) -> 1781 | I83: =+I93+I94+I95-(I106+I107-I109) -> 1687 | ... S83: =+S93+S94+S95-(S106+S107-S109) -> 3038 | AA83: =+AA94+AA95-(AA106+AA107+AA112) -> -166 | AB83: =+AB94+AB95-(AB106+AB107+AB112) -> 235 | AC83: =+AC94+AC95-(AC106+AC107+AC112) -> 126 | AD83: =+AD94+AD95-(AD106+AD107+AD112) -> 387 | AE83: =+AE94+AE95-(AE106+AE107+AE112) -> -18 | AF83: =+AF94+AF95-(AF106+AF107+AF112) -> -119 | AG83: =+AG94+AG95-(AG106+AG107) -> 631.61596 | AH83: =+AH94+AH95-(AH106+AH107) -> 703.05433 | AI83: =+AI94+AI95-(AI106+AI107) -> 696.67432 | AJ83: =+AJ94+AJ95-(AJ106+AJ107) -> 1125.8731 | AK83: =+AK94+AK95-(AK106+AK107) -> 1131.8755 | AL83: =+AL94+AL95-(AL106+AL107) -> 1232.9245 | AM83: =+AM94+AM95-(AM106+AM107) -> 1213.8967 | AN83: =+AN94+AN95-(AN106+AN107) -> 1750.9018 | ... AQ83: =+AQ94+AQ95-(AQ106+AQ107) -> 1739.6704
A84: NOPAT | B84: =+B45*(1-B68) -> 1296.3577 | C84: =+C45*(1-C68) -> 1207.2131 | D84: =+D45*(1-D68) -> 1157.8462 | E84: =+E45*(1-E68) -> 1166.6974 | F84: =+F45*(1-F68) -> 1237.6358 | G84: =+G45*(1-G68) -> 1274.5939 | H84: =+H45*(1-H68) -> 1365.973 | I84: =+I45*(1-I68) -> 1429.6842 | ... S84: =+S45*(1-S68) -> 1712 | AA84: =+AA45*(1-AA68) -> 5336.312 | AB84: =+AB45*(1-AB68) -> 4903.102 | AC84: =+AC45*(1-AC68) -> 4826.6705 | AD84: =+AD45*(1-AD68) -> 5308.5846 | AE84: =+AE45*(1-AE68) -> 5407.2134 | AF84: =+AF45*(1-AF68) -> 7106.576 | AG84: =+AG45*(1-AG68) -> 8174.7673 | AH84: =+AH45*(1-AH68) -> 9128.3301 | ... AQ84: =+AQ45*(1-AQ68) -> 20733.369
A85: EBITDA | B85: =+B45+B128+B131+B132 -> 1963 | C85: =+C45+C128+C131+C132 -> 1839 | D85: =+D45+D128+D131+D132 -> 1818 | E85: =+E45+E128+E131+E132 -> 1784 | F85: =+F45+F128+F131+F132 -> 1768 | G85: =+G45+G128+G131+G132 -> 1737 | H85: =+H45+H128+H131+H132 -> 1823 | I85: =+I45+I128+I131+I132 -> 1833 | ... S85: =+S45+S128+S131+S132 -> 2578 | AA85: =+AA45+AA128+AA131+AA132 -> 3608.4757 | AB85: =+AB45+AB128+AB131+AB132 -> 6848.1176 | AC85: =+AC45+AC128+AC131+AC132 -> 7403.4273 | AD85: =+AD45+AD128+AD131+AD132 -> 7160.5371 | AE85: =+AE45+AE128+AE131+AE132 -> 7259.628 | AF85: =+AF45+AF128+AF131+AF132 -> 9060.4335
A86: % | F86: =+F85/B85-1 -> -0.099337748 | G86: =+G85/C85-1 -> -0.055464927 | H86: =+H85/D85-1 -> 0.002750275 | I86: =+I85/E85-1 -> 0.027466368 | J86: =+J85/F85-1 -> -0.42929864 | K86: =+K85/G85-1 -> 0.15141048 | L86: =+L85/H85-1 -> 0.15962699 | M86: =+M85/I85-1 -> 0.16584834 | ... S86: =+S85/O85-1 -> 0.16283266 | AB86: =+AB85/AA85-1 -> 0.89778684 | AC86: =+AC85/AB85-1 -> 0.081089386 | AD86: =+AD85/AC85-1 -> -0.03280781 | AE86: =+AE85/AD85-1 -> 0.013838481 | AF86: =+AF85/AE85-1 -> 0.24805754
A87: UFCF | AB87: =+AB84+AB128-AB137-(AB83-AA83) -> 4942.102 | AC87: =+AC84+AC128-AC137-(AC83-AB83) -> 5349.6705 | AD87: =+AD84+AD128-AD137-(AD83-AC83) -> 5559.5846 | AE87: =+AE84+AE128-AE137-(AE83-AD83) -> 6486.2134 | AF87: =+AF84+AF128-AF137-(AF83-AE83) -> 7846.576 | AG87: =+AG84+AG128-AG137-(AG83-AF83) -> 8166.2196 | AH87: =+AH84+AH128-AH137-(AH83-AG83) -> 9876.8771 | AI87: =+AI84+AI128-AI137-(AI83-AH83) -> 11590.675 | ... AQ87: =+AQ84+AQ128-AQ137-(AQ83-AP83) -> 22173.959
A90: Net Cash | B90: =+B92+B93-B109-B110 -> 576 | C90: =+C92+C93-C109-C110 -> 1173 | D90: =+D92+D93-D109-D110 -> 1637 | E90: =+E92+E93-E109-E110 -> 1967 | F90: =+F92+F93-F109-F110 -> 1524 | G90: =+G92+G93-G109-G110 -> 2970 | H90: =+H92+H93-H109-H110 -> 3883 | I90: =+I92+I93-I109-I110 -> 4208 | ... U90: =+U92+U93-U109-U110 -> 0 | AA90: =+AA92+AA93-AA109-AA110 -> 1875 | AB90: =+AB92+AB93-AB109-AB110 -> 1675 | AC90: =+AC92+AC93-AC109-AC110 -> 1967 | AD90: =+AD92+AD93-AD109-AD110 -> 4208 | AE90: =+AE92+AE93-AE109-AE110 -> 2258 | AF90: =+AF92+AF93-AF109-AF110 -> 385 | AG90: =+AF90+AG57 -> 8622.4768 | AH90: =+AG90+AH57 -> 17973.316 | AI90: =+AH90+AI57 -> 29079.422 | AJ90: =+AI90+AJ57 -> 42246.783 | AK90: =+AJ90+AK57 -> 57017.626 | AL90: =+AK90+AL57 -> 73399.756 | AM90: =+AL90+AM57 -> 93090.51 | AN90: =+AM90+AN57 -> 114466.08 | ... AQ90: =+AP90+AQ57 -> 187633.07
A92: Cash | B92: 2739 | C92: 3365 | D92: 3870 | E92: 4236 | F92: 4072 | G92: 5456 | H92: 6601 | I92: 7141 | J92: 6254 | K92: 7613 | L92: 7193 | M92: 7613 | N92: 6758 | O92: 4931 | P92: 4982 | Q92: 5431 | R92: 6332 | S92: 4919 | AA92: 4478 | AB92: 3844 | AC92: 4236 | AD92: 7141 | AE92: 7613 | AF92: 5431
A93: Short-term investment | B93: 1962 | C93: 1934 | D93: 1894 | E93: 1860 | F93: 1581 | G93: 1145 | H93: 915 | I93: 701 | J93: 566 | K93: 273 | L93: 322 | M93: 273 | N93: 677 | O93: 782 | P93: 958 | Q93: 1164 | R93: 558 | S93: 707 | AA93: 1514 | AB93: 1954 | AC93: 1860 | AD93: 701 | AE93: 273 | AF93: 1164
A94: A/R | B94: 1685 | C94: 1588 | D94: 1723 | E94: 2065 | F94: 1801 | G94: 1685 | H94: 1851 | I94: 2224 | J94: 2057 | K94: 2072 | L94: 1802 | M94: 2072 | N94: 1973 | O94: 1735 | P94: 2093 | Q94: 2344 | R94: 2092 | S94: 1993 | AA94: 1398 | AB94: 1878 | AC94: 2065 | AD94: 2224 | AE94: 2072 | AF94: 2344 | AG94: =+(AG148/365)*AG23 -> 2389.3106 | AH94: =+(AH148/365)*AH23 -> 2647.7022 | AI94: =+(AI148/365)*AI23 -> 2811.3783 | AJ94: =+(AJ148/365)*AJ23 -> 3064.4024 | AK94: =+(AK148/365)*AK23 -> 3206.131 | AL94: =+(AL148/365)*AL23 -> 3430.5601 | AM94: =+(AM148/365)*AM23 -> 3519.0907 | AN94: =+(AN148/365)*AN23 -> 3695.0452 | ... AQ94: =+(AQ148/365)*AQ23 -> 3768.1421
A95: Prepaid exp | B95: 1090 | C95: 1021 | D95: 1002 | E95: 835 | F95: 888 | G95: 988 | H95: 1043 | I95: 1018 | J95: 1131 | K95: 1274 | L95: 1399 | M95: 1274 | N95: 1447 | O95: 1530 | P95: 1379 | Q95: 1224 | R95: 1404 | S95: 1449 | AA95: 756 | AB95: 993 | AC95: 835 | AD95: 1018 | AE95: 1274 | AF95: 1224 | AG95: =+AG23*0.05 -> 1325.1218 | AH95: =+AH23*0.05 -> 1464.2595 | AI95: =+AI23*0.05 -> 1603.3642 | AJ95: =+AJ23*0.05 -> 1747.667 | AK95: =+AK23*0.05 -> 1887.4803 | AL95: =+AL23*0.05 -> 2019.6039 | AM95: =+AM23*0.05 -> 2140.7802 | AN95: =+AN23*0.05 -> 2247.8192 | ... AQ95: =+AQ23*0.05 -> 2456.0212
B96: =+B95/B$23 -> 0.25574847 | C96: =+C95/C$23 -> 0.23278614 | D96: =+D95/D$23 -> 0.22603203 | E96: =+E95/E$23 -> 0.18453039 | F96: =+F95/F$23 -> 0.19076262 | G96: =+G95/G$23 -> 0.2051495 | H96: =+H95/H$23 -> 0.21329243 | I96: =+I95/I$23 -> 0.20166403 | ... S96: =+S95/S$23 -> 0.21894832 | AA96: =+AA95/AA$23 -> 0.058750389 | AB96: =+AB95/AB$23 -> 0.062907824 | AC96: =+AC95/AC$23 -> 0.047427014 | AD96: =+AD95/AD$23 -> 0.052449894 | AE96: =+AE95/AE$23 -> 0.059242037 | AF96: =+AF95/AF$23 -> 0.051495646 | AG96: =+AG95/AG$23 -> 0.05 | AH96: =+AH95/AH$23 -> 0.05 | ... AQ96: =+AQ95/AQ$23 -> 0.05
A97: PP&E | B97: 1703 | C97: 1790 | D97: 1858 | E97: 1908 | F97: 1967 | G97: 2032 | H97: 2036 | I97: 2030 | J97: 1988 | K97: 1936 | L97: 1969 | M97: 1936 | N97: 1893 | O97: 1890 | P97: 1908 | Q97: 1873 | R97: 1852 | S97: 1870 | AA97: 1517 | AB97: 1673 | AC97: 1908 | AD97: 2030 | AE97: 1936 | AF97: 1873
A98: Op lease ROU | B98: 435 | C98: 430 | D98: 414 | E98: 407 | F98: 402 | G98: 389 | H98: 373 | I98: 358 | J98: 366 | K98: 281 | L98: 368 | M98: 281 | N98: 266 | O98: 259 | P98: 307 | Q98: 312 | R98: 305 | S98: 299 | AA98: 487 | AB98: 443 | AC98: 407 | AD98: 358 | AE98: 281 | AF98: 312
A99: Goodwill | B99: 12795 | C99: 12801 | D99: 12756 | E99: 12787 | F99: 12792 | G99: 12796 | H99: 12800 | I99: 12805 | J99: 12803 | K99: 12788 | L99: 12814 | M99: 12788 | N99: 12777 | O99: 12830 | P99: 12862 | Q99: 12857 | R99: 12869 | S99: 14041 | AA99: 10742 | AB99: 12668 | AC99: 12787 | AD99: 12805 | AE99: 12788 | AF99: 12857
A100: Other intangible | B100: 1743 | C100: 1650 | D100: 1548 | E100: 1449 | F100: 1354 | G100: 1258 | H100: 1167 | I100: 1088 | J100: 1011 | K100: 782 | L100: 858 | M100: 782 | N100: 706 | O100: 631 | P100: 555 | Q100: 495 | R100: 454 | S100: 1012 | AA100: 1359 | AB100: 1820 | AC100: 1449 | AD100: 1088 | AE100: 782 | AF100: 495
A101: D/T | B101: 950 | C101: 882 | D101: 799 | E101: 777 | F101: 826 | G101: 964 | H101: 1065 | I101: 1191 | J101: 1310 | K101: 1657 | L101: 1548 | M101: 1657 | N101: 1820 | O101: 1984 | P101: 2092 | Q101: 2186 | R101: 2138 | S101: 1998 | AA101: 1370 | AB101: 1085 | AC101: 777 | AD101: 1191 | AE101: 1657 | AF101: 2186
A102: Other Assets | B102: 874 | C102: 865 | D102: 880 | E102: 841 | F102: 984 | G102: 1125 | H102: 1239 | I102: 1223 | J102: 1265 | K102: 1554 | L102: 1557 | M102: 1554 | N102: 1638 | O102: 1535 | P102: 1618 | Q102: 1610 | R102: 1700 | S102: 1645 | AA102: 663 | AB102: 883 | AC102: 841 | AD102: 1223 | AE102: 1554 | AF102: 1610
A103: A | B103: =SUM(B92:B102) -> 25976.256 | C103: =SUM(C92:C102) -> 26326.233 | D103: =SUM(D92:D102) -> 26744.226 | E103: =SUM(E92:E102) -> 27165.185 | F103: =SUM(F92:F102) -> 26667.191 | G103: =SUM(G92:G102) -> 27838.205 | H103: =SUM(H92:H102) -> 29090.213 | I103: =SUM(I92:I102) -> 29779.202 | ... U103: =SUM(U92:U102) -> 0 | AA103: =SUM(AA92:AA102) -> 24284.059 | AB103: =SUM(AB92:AB102) -> 27241.063 | AC103: =SUM(AC92:AC102) -> 27165.047 | AD103: =SUM(AD92:AD102) -> 29779.052 | AE103: =SUM(AE92:AE102) -> 30230.059 | AF103: =SUM(AF92:AF102) -> 29496.051
A106: A/P | B106: 295 | C106: 366 | D106: 316 | E106: 379 | F106: 379 | G106: 346 | H106: 314 | I106: 314 | J106: 300 | K106: 361 | L106: 318 | M106: 361 | N106: 326 | O106: 360 | P106: 337 | Q106: 417 | R106: 419 | S106: 499 | AA106: 306 | AB106: 312 | AC106: 379 | AD106: 314 | AE106: 361 | AF106: 417 | AG106: =+(AG149/365)*AG31 -> 432.57288 | AH106: =+(AH149/365)*AH31 -> 480.38831 | AI106: =+(AI149/365)*AI31 -> 511.33979 | AJ106: =+(AJ149/365)*AJ31 -> 540.39566 | AK106: =+(AK149/365)*AK31 -> 564.27119 | AL106: =+(AL149/365)*AL31 -> 581.95249 | AM106: =+(AM149/365)*AM31 -> 592.56986 | AN106: =+(AN149/365)*AN31 -> 595.4519 | ... AQ106: =+(AQ149/365)*AQ31 -> 554.85901
A107: Accr. Exp | B107: 1333 | C107: 1615 | D107: 1629 | E107: 1790 | F107: 1790 | G107: 1786 | H107: 1714 | I107: 1942 | J107: 1569 | K107: 2336 | L107: 1848 | M107: 2336 | N107: 1951 | O107: 2256 | P107: 2289 | Q107: 2648 | R107: 2257 | S107: 2455 | AA107: 1422 | AB107: 1736 | AC107: 1790 | AD107: 1942 | AE107: 2336 | AF107: 2648 | AG107: =+AG23*0.1 -> 2650.2435 | AH107: =+AH23*0.1 -> 2928.5191 | AI107: =+AI23*0.1 -> 3206.7284 | AJ107: =+AJ23*0.09 -> 3145.8005 | AK107: =+AK23*0.09 -> 3397.4646 | AL107: =+AL23*0.09 -> 3635.2871 | AM107: =+AM23*0.09 -> 3853.4043 | AN107: =+AN23*0.08 -> 3596.5107 | AO107: =+AO23*0.08 -> 3740.3711 | AP107: =+AP23*0.08 -> 3852.5823 | AQ107: =+AQ23*0.08 -> 3929.6339
B108: =+B107/B$23 -> 0.31276396 | C108: =+C107/C$23 -> 0.36821705 | D108: =+D107/D$23 -> 0.36747124 | E108: =+E107/E$23 -> 0.39558011 | F108: =+F107/F$23 -> 0.38453276 | G108: =+G107/G$23 -> 0.37084718 | H108: =+H107/H$23 -> 0.35051125 | I108: =+I107/I$23 -> 0.38470681 | ... S108: =+S107/S$23 -> 0.37095799 | AA108: =+AA107/AA$23 -> 0.11050668 | AB108: =+AB107/AB$23 -> 0.10997783 | AC108: =+AC107/AC$23 -> 0.10166989 | AD108: =+AD107/AD$23 -> 0.10005667 | AE108: =+AE107/AE$23 -> 0.1086259 | AF108: =+AF107/AF$23 -> 0.11140561 | AG108: =+AG107/AG$23 -> 0.1 | AH108: =+AH107/AH$23 -> 0.1 | ... AQ108: =+AQ107/AQ$23 -> 0.08
A109: Debt | B109: =+499 -> 499 | C109: =+499 -> 499 | D109: =+500 -> 500 | E109: =+500 -> 500 | F109: =+500 -> 500 | G109: =+0 -> 0 | H109: =+0 -> 0 | I109: =+0 -> 0 | J109: =+1497 -> 1497 | K109: =+1499 -> 1499 | L109: =+1499 -> 1499 | M109: =+1499 -> 1499 | N109: 0 | O109: 0 | P109: 0 | Q109: 0 | R109: =+849 -> 849 | S109: =+1843 -> 1843 | AA109: 0 | AB109: 0 | AC109: =+500 -> 500 | AD109: =+0 -> 0 | AE109: =+1499 -> 1499 | AF109: 0
A110: Debt (Non Curr.) | B110: 3626 | C110: 3627 | D110: 3627 | E110: 3629 | F110: 3629 | G110: 3631 | H110: 3633 | I110: 3634 | J110: 2138 | K110: 4129 | L110: 4128 | M110: 4129 | N110: 6155 | O110: 6166 | P110: 6200 | Q110: 6210 | R110: 5379 | S110: 4802 | AA110: 4117 | AB110: 4123 | AC110: 3629 | AD110: 3634 | AE110: 4129 | AF110: 6210
...

Sheet Bond
A1: Main
B3: ISIN | C3: Coupon (%) | D3: Maturity Date
B4: US00724PAC32 | C4: 2.15 | D4: Feb 01, 2027
B5: US00724PAE97 | C5: 4.85 | D5: Apr 04, 2027
B6: US00724PAH29 | C6: 4.75 | D6: Jan 17, 2028
B7: US00724PAF62 | C7: 4.8 | D7: Apr 04, 2029
B8: US00724PAJ84 | C8: 4.95 | D8: Jan 17, 2030
B9: US00724PAD15 | C9: 2.3 | D9: Feb 01, 2030
B10: US00724PAG46 | C10: 4.95 | D10: Apr 04, 2034
B11: US00724PAK57 | C11: 5.3 | D11: Jan 17, 2035
C12: =+AVERAGE(C4:C11) -> 4.25625

Sheet Board
A1: Main | E1: Auditor | F1: KPMG
