Workbook

Sheet Main
A1: Autodesk Inc. | E1: Price | F1: 230
E2: Share | F2: 209 | G2: Q227
E3: MC | F3: =+F2*F1 -> 48070
E4: Cash | F4: 4357 | G4: Q227
E5: Debt | F5: =+994+499+1985 -> 3478 | G5: Q227
E6: EV | F6: =+F3-F4+F5 -> 47191
A10: BETA | B10: 1.31 | D10: WACC | E10: =+(F3/(F3+F5))*B11+(F5/(F3+F5))*B12*(1-0.17) -> 0.11095369 | G10: EV/EBITDA | H10: =+F6/SUM(Model!L77:O77) -> 16.23916
A11: CAPM | B11: =+0.05+B10*(0.1-0.05) -> 0.1155 | G11: EV/FCF | H11: =+F6/SUM(Model!L151:O151) -> 16.622402
A12: Cost of Debt | B12: =+0.05+(B13/100) -> 0.057973913 | D12: P/E | E12: =+F1/SUM(Model!L63:O63) -> 29.793612 | G12: P/EBITDA | H12: =+F3/SUM(Model!L77:O77) -> 16.541638
A13: Cr. Spread | B13: =+'[1]Credit Spread US'!J6 -> 0.7973913 | D13: FP/E | G13: P/FCF | H13: =+F3/SUM(Model!L151:O151) -> 16.932018
A14: Rating | B14: AA- | C14: A3 | G14: Inc. Margin | H14: =+(SUM(Model!L53:O53)-SUM(Model!H53:K53))/(SUM(Model!L29:O29)-SUM(Model!H29:K29)) -> 0.55021097
B15: S&P | C15: Moody’s
A21: AECO, Architecture, Engineering, Contruction and Operations
A22: AutoCAD and AutoCAD LT
A23: MFG, Manufacturing
A24: M&E, Media and Entertainment
A25: Other

Sheet Model
A1: Main | B1: 04/23 | C1: 07/23 | D1: 09/23 | E1: 12/23 | F1: 04/24 | G1: 07/24 | H1: 09/24 | I1: 12/24 | J1: 04/25 | K1: 07/25 | L1: 09/25 | M1: 12/25 | N1: 04/26 | O1: 07/26 | P1: 09/26 | Q1: 12/26 | U1: 01/16 | V1: 01/17 | W1: 01/18 | X1: 01/19 | Y1: 01/20 | Z1: 01/21 | AA1: 01/22 | AB1: 01/23 | AC1: 01/24 | AD1: 01/25 | AE1: 01/26
A2: in Millions | B2: Q124 | C2: Q224 | D2: Q324 | E2: Q424 | F2: Q125 | G2: Q225 | H2: Q325 | I2: Q425 | J2: Q126 | K2: Q226 | L2: Q326 | M2: Q426 | N2: Q127 | O2: Q227 | P2: Q327 | Q2: Q427 | U2: 2016 | V2: =+U2+1 -> 2017 | W2: =+V2+1 -> 2018 | X2: =+W2+1 -> 2019 | Y2: =+X2+1 -> 2020 | Z2: =+Y2+1 -> 2021 | AA2: =+Z2+1 -> 2022 | AB2: =+AA2+1 -> 2023 | AC2: =+AB2+1 -> 2024 | ... AJ2: =+AI2+1 -> 2031
A4: Total Subs (‘000) | U4: 2578.2 | V4: 3107 | W4: 3715.7 | X4: 4330
A6: ARR | U6: 1376.4 | V6: 1599.9 | W6: 2.0541 | X6: 2.7494
A8: ARPS | U8: 534 | V8: 515 | W8: =+W4/W6 -> 1808.9187 | X8: =+X4/X6 -> 1574.8891
A12: AECO | B12: 582 | C12: 627 | D12: 675 | E12: 696 | F12: 674 | G12: 713 | H12: 751 | I12: 799 | J12: 809 | K12: 878 | L12: 921 | M12: 975 | N12: 970 | O12: 1029 | U12: 949.1 | V12: 880.9 | W12: 949.1 | Y12: 1377.1 | Z12: 1648.6 | AA12: 1969 | AB12: 2278 | AC12: 2580 | AD12: 2937 | AE12: 3583
B13: =+B12/B$29 -> 0.45862884 | C13: =+C12/C$29 -> 0.466171 | D13: =+D12/D$29 -> 0.47736917 | E13: =+E12/E$29 -> 0.4737917 | F13: =+F12/F$29 -> 0.47565279 | G13: =+G12/G$29 -> 0.47375415 | H13: =+H12/H$29 -> 0.47834395 | I13: =+I12/I$29 -> 0.48749237 | ... O13: =+O12/O$29 -> 0.50293255 | Y13: =+Y12/Y$29 -> 0.42057844 | Z13: =+Z12/Z$29 -> 0.43498681 | AA13: =+AA12/AA$29 -> 0.44892841 | AB13: =+AB12/AB$29 -> 0.45514486 | AC13: =+AC12/AC$29 -> 0.46934692 | AD13: =+AD12/AD$29 -> 0.47904094 | AE13: =+AE12/AE$29 -> 0.49722454
A14: AutoCAD and AutoCAD LT | B14: 349 | C14: 364 | D14: 372 | E14: 377 | F14: 376 | G14: 389 | H14: 398 | I14: 409 | J14: 411 | K14: 440 | L14: 458 | M14: 478 | N14: 474 | O14: 500 | U14: 594.8 | V14: 326.7 | W14: 594.8 | Y14: 948.2 | Z14: 1099.4 | AA14: 1244 | AB14: 1387 | AC14: 1462 | AD14: 1572 | AE14: 1787
B15: =+B14/B$29 -> 0.2750197 | C15: =+C14/C$29 -> 0.27063197 | D15: =+D14/D$29 -> 0.26308345 | E15: =+E14/E$29 -> 0.25663717 | F15: =+F14/F$29 -> 0.26534933 | G15: =+G14/G$29 -> 0.25847176 | H15: =+H14/H$29 -> 0.25350318 | I15: =+I14/I$29 -> 0.2495424 | ... O15: =+O14/O$29 -> 0.24437928 | Y15: =+Y14/Y$29 -> 0.28958861 | Z15: =+Z14/Z$29 -> 0.29007916 | AA15: =+AA14/AA$29 -> 0.28362973 | AB15: =+AB14/AB$29 -> 0.27712288 | AC15: =+AC14/AC$29 -> 0.26596325 | AD15: =+AD14/AD$29 -> 0.25640189 | AE15: =+AE14/AE$29 -> 0.24798779
A16: MFG | B16: 246 | C16: 256 | D16: 269 | E16: 292 | F16: 268 | G16: 296 | H16: 307 | I16: 318 | J16: 309 | K16: 334 | L16: 355 | M16: 381 | N16: 367 | O16: 385 | U16: 724.6 | V16: 625.8 | W16: 724.6 | Y16: 726.1 | Z16: 798.6 | AA16: 876 | AB16: 978 | AC16: 1063 | AD16: 1189 | AE16: 1379
B17: =+B16/B$29 -> 0.19385343 | C17: =+C16/C$29 -> 0.19033457 | D17: =+D16/D$29 -> 0.19024045 | E17: =+E16/E$29 -> 0.19877468 | F17: =+F16/F$29 -> 0.18913197 | G17: =+G16/G$29 -> 0.19667774 | H17: =+H16/H$29 -> 0.1955414 | I17: =+I16/I$29 -> 0.19402074 | ... O17: =+O16/O$29 -> 0.18817204 | Y17: =+Y16/Y$29 -> 0.22175732 | Z17: =+Z16/Z$29 -> 0.2107124 | AA17: =+AA16/AA$29 -> 0.1997264 | AB17: =+AB16/AB$29 -> 0.1954046 | AC17: =+AC16/AC$29 -> 0.19337821 | AD17: =+AD16/AD$29 -> 0.19393247 | AE17: =+AE16/AE$29 -> 0.1913683
A18: M&E | B18: 71 | C18: 74 | D18: 73 | E18: 77 | F18: 71 | G18: 77 | H18: 83 | I18: 84 | J18: 76 | K18: 80 | L18: 86 | M18: 90 | N18: 86 | O18: 92 | U18: 160 | V18: 138.9 | W18: 160 | Y18: 199.2 | Z18: 219.4 | AA18: 259 | AB18: 291 | AC18: 295 | AD18: 315 | AE18: 332
B19: =+B18/B$29 -> 0.055949567 | C19: =+C18/C$29 -> 0.055018587 | D19: =+D18/D$29 -> 0.051626591 | E19: =+E18/E$29 -> 0.05241661 | F19: =+F18/F$29 -> 0.050105857 | G19: =+G18/G$29 -> 0.051162791 | H19: =+H18/H$29 -> 0.052866242 | I19: =+I18/I$29 -> 0.051250763 | ... O19: =+O18/O$29 -> 0.044965787 | Y19: =+Y18/Y$29 -> 0.060837431 | Z19: =+Z18/Z$29 -> 0.057889182 | AA19: =+AA18/AA$29 -> 0.059051528 | AB19: =+AB18/AB$29 -> 0.058141858 | AC19: =+AC18/AC$29 -> 0.053665636 | AD19: =+AD18/AD$29 -> 0.051378242 | AE19: =+AE18/AE$29 -> 0.046072717
A20: Other | B20: 21 | C20: 24 | D20: 25 | E20: 27 | F20: 28 | G20: 30 | H20: 31 | I20: 29 | J20: 28 | K20: 31 | L20: 33 | M20: 33 | N20: 37 | O20: 40 | U20: 75.6 | V20: 58.7 | W20: 75.6 | Y20: 23.7 | Z20: 24.4 | AA20: 38 | AB20: 71 | AC20: 97 | AD20: 118 | AE20: 125
B21: =+B20/B$29 -> 0.016548463 | C21: =+C20/C$29 -> 0.017843866 | D21: =+D20/D$29 -> 0.017680339 | E21: =+E20/E$29 -> 0.01837985 | F21: =+F20/F$29 -> 0.019760056 | G21: =+G20/G$29 -> 0.019933555 | H21: =+H20/H$29 -> 0.019745223 | I21: =+I20/I$29 -> 0.017693716 | ... O21: =+O20/O$29 -> 0.019550342 | Y21: =+Y20/Y$29 -> 0.0072381883 | Z21: =+Z20/Z$29 -> 0.0064379947 | AA21: =+AA20/AA$29 -> 0.0086639307 | AB21: =+AB20/AB$29 -> 0.014185814 | AC21: =+AC20/AC$29 -> 0.017645989 | AD21: =+AD20/AD$29 -> 0.019246452 | AE21: =+AE20/AE$29 -> 0.017346656
A25: Subscriptions | B25: 1193 | C25: 1270 | D25: 1314 | E25: 1339 | F25: 1330 | G25: 1408 | H25: 1457 | I25: 1522 | J25: 1540 | K25: 1667 | L25: 1734 | M25: 1819 | N25: 1836 | O25: 1952 | U25: 228.1 | V25: 443.1 | W25: 894.3 | X25: 1802.3 | Y25: 2751.9 | Z25: 3381 | AA25: 4060 | AB25: 4651 | AC25: 5116 | AD25: 5717 | AE25: 6743
B26: =+B25/B$29 -> 0.94011032 | C26: =+C25/C$29 -> 0.94423792 | D26: =+D25/D$29 -> 0.92927864 | E26: =+E25/E$29 -> 0.91150442 | F26: =+F25/F$29 -> 0.93860268 | G26: =+G25/G$29 -> 0.93554817 | H26: =+H25/H$29 -> 0.92802548 | I26: =+I25/I$29 -> 0.92861501 | ... O26: =+O25/O$29 -> 0.9540567 | U26: =+U25/U$29 -> 0.091090611 | V26: =+V25/V$29 -> 0.21816839 | W26: =+W25/W$29 -> 0.43484392 | X26: =+X25/X$29 -> 0.70133863 | Y26: =+Y25/Y$29 -> 0.84045445 | Z26: =+Z25/Z$29 -> 0.89208443 | AA26: =+AA25/AA$29 -> 0.92567259 | AB26: =+AB25/AB$29 -> 0.92927073 | ... AE26: =+AE25/AE$29 -> 0.93574799
A27: Other | B27: =+14+62 -> 76 | C27: =+14+61 -> 75 | D27: =+12+88 -> 100 | E27: =+14+116 -> 130 | F27: =+11+76 -> 87 | G27: =+11+86 -> 97 | H27: =+9+104 -> 113 | I27: =+10+107 -> 117 | J27: 93 | K27: 96 | L27: =+8+111 -> 119 | M27: =+8+130 -> 138 | N27: 98 | O27: 94 | U27: =+1123.5+1152.5 -> 2276 | V27: =+1103.1+484.8 -> 1587.9 | W27: =+989.6+172.7 -> 1162.3 | X27: =+635.1+132.4 -> 767.5 | Y27: =+386.6+135.8 -> 522.4 | Z27: =+183+226 -> 409 | AA27: =+76+250 -> 326 | AB27: =+65+289 -> 354 | AC27: =+54+327 -> 381 | AD27: =+41+373 -> 414 | AE27: =+430+33 -> 463
B28: =+B27/B$29 -> 0.059889677 | C28: =+C27/C$29 -> 0.055762082 | D28: =+D27/D$29 -> 0.070721358 | E28: =+E27/E$29 -> 0.088495575 | F28: =+F27/F$29 -> 0.061397318 | G28: =+G27/G$29 -> 0.064451827 | H28: =+H27/H$29 -> 0.071974522 | I28: =+I27/I$29 -> 0.071384991 | ... O28: =+O27/O$29 -> 0.045943304 | U28: =+U27/U$29 -> 0.90890939 | V28: =+V27/V$29 -> 0.78183161 | W28: =+W27/W$29 -> 0.56515608 | X28: =+X27/X$29 -> 0.29866137 | Y28: =+Y27/Y$29 -> 0.15954555 | Z28: =+Z27/Z$29 -> 0.10791557 | AA28: =+AA27/AA$29 -> 0.074327405 | AB28: =+AB27/AB$29 -> 0.070729271 | ... AE28: =+AE27/AE$29 -> 0.064252012
A29: Revenue | B29: =+B27+B25 -> 1269 | C29: =+C27+C25 -> 1345 | D29: =+D27+D25 -> 1414 | E29: =+E27+E25 -> 1469 | F29: =+F27+F25 -> 1417 | G29: =+G27+G25 -> 1505 | H29: =+H27+H25 -> 1570 | I29: =+I27+I25 -> 1639 | ... Q29: =+Q27+Q25 -> 0 | U29: =+U27+U25 -> 2504.1 | V29: =+V27+V25 -> 2031 | W29: =+W27+W25 -> 2056.6 | X29: =+X27+X25 -> 2569.8 | Y29: =+Y27+Y25 -> 3274.3 | Z29: =+Z27+Z25 -> 3790 | AA29: =+AA27+AA25 -> 4386 | AB29: =+AB27+AB25 -> 5005 | ... AE29: =+AE27+AE25 -> 7206 | AF29: =+AE29*1.15 -> 8286.9 | AG29: =+AF29*1.14 -> 9447.066 | AH29: =+AG29*1.13 -> 10675.185 | AI29: =+AH29*1.12 -> 11956.207 | AJ29: =+AI29*1.11 -> 13271.389
F30: =+F29/B29-1 -> 0.11662727 | G30: =+G29/C29-1 -> 0.11895911 | H30: =+H29/D29-1 -> 0.11032532 | I30: =+I29/E29-1 -> 0.11572498 | J30: =+J29/F29-1 -> 0.15243472 | K30: =+K29/G29-1 -> 0.17142857 | L30: =+L29/H29-1 -> 0.18025478 | M30: =+M29/I29-1 -> 0.19402074 | ... O30: =+O29/K29-1 -> 0.16052184 | V30: =+V29/U29-1 -> -0.18893015 | W30: =+W29/V29-1 -> 0.012604628 | X30: =+X29/W29-1 -> 0.24953807 | Y30: =+Y29/X29-1 -> 0.27414585 | Z30: =+Z29/Y29-1 -> 0.15749931 | AA30: =+AA29/Z29-1 -> 0.15725594 | AB30: =+AB29/AA29-1 -> 0.14113087 | AC30: =+AC29/AB29-1 -> 0.098301698 | ... AJ30: =+AJ29/AI29-1 -> 0.11
A31: Cost of Subs | B31: 96 | C31: 95 | D31: 94 | E31: 96 | F31: 100 | G31: 100 | H31: 105 | I31: 108 | J31: 111 | K31: 114 | L31: 118 | M31: 120 | N31: 129 | O31: 130 | U31: 162.3 | V31: 191.7 | W31: 214.4 | X31: 216 | Y31: 223.9 | Z31: 242 | AA31: 299 | AB31: 343 | AC31: 381 | AD31: 413 | AE31: 463
B32: =+B31/B$29 -> 0.075650118 | C32: =+C31/C$29 -> 0.07063197 | D32: =+D31/D$29 -> 0.066478076 | E32: =+E31/E$29 -> 0.065350579 | F32: =+F31/F$29 -> 0.07057163 | G32: =+G31/G$29 -> 0.066445183 | H32: =+H31/H$29 -> 0.066878981 | I32: =+I31/I$29 -> 0.065893838 | ... O32: =+O31/O$29 -> 0.063538612 | U32: =+U31/U$29 -> 0.064813706 | V32: =+V31/V$29 -> 0.094387001 | W32: =+W31/W$29 -> 0.10424973 | X32: =+X31/X$29 -> 0.084053234 | Y32: =+Y31/Y$29 -> 0.068381028 | Z32: =+Z31/Z$29 -> 0.063852243 | AA32: =+AA31/AA$29 -> 0.068171455 | AB32: =+AB31/AB$29 -> 0.068531469 | ... AE32: =+AE31/AE$29 -> 0.064252012
A33: Cost of Other | B33: 20 | C33: 21 | D33: 21 | E33: 20 | F33: 20 | G33: 18 | H33: 19 | I33: 23 | J33: 24 | K33: 22 | L33: 22 | M33: 22 | N33: 21 | O33: 22 | U33: 159.4 | V33: 110.2 | W33: 72.6 | X33: 54.4 | Y33: 66.5 | Z33: 64 | AA33: 67 | AB33: 79 | AC33: 82 | AD33: 80 | AE33: 90
B34: =+B33/B$29 -> 0.015760441 | C34: =+C33/C$29 -> 0.015613383 | D34: =+D33/D$29 -> 0.014851485 | E34: =+E33/E$29 -> 0.013614704 | F34: =+F33/F$29 -> 0.014114326 | G34: =+G33/G$29 -> 0.011960133 | H34: =+H33/H$29 -> 0.012101911 | I34: =+I33/I$29 -> 0.014032947 | ... O34: =+O33/O$29 -> 0.010752688 | U34: =+U33/U$29 -> 0.063655605 | V34: =+V33/V$29 -> 0.054258986 | W34: =+W33/W$29 -> 0.035300982 | X34: =+X33/X$29 -> 0.021168963 | Y34: =+Y33/Y$29 -> 0.020309685 | Z34: =+Z33/Z$29 -> 0.016886544 | AA34: =+AA33/AA$29 -> 0.015275878 | AB34: =+AB33/AB$29 -> 0.015784216 | ... AE34: =+AE33/AE$29 -> 0.012489592
A35: D&A | B35: 11 | C35: 11 | D35: 12 | E35: 14 | F35: 17 | G35: 22 | H35: 23 | I35: 23 | J35: 25 | K35: 23 | L35: 25 | M35: 24 | N35: 25 | O35: 24 | U35: 49 | V35: 40 | W35: 16.4 | X35: 15.5 | Y35: 34.5 | Z35: 31 | AA35: 52 | AB35: 58 | AC35: 48 | AD35: 85 | AE35: 97
B36: =+B35/B$29 -> 0.0086682427 | C36: =+C35/C$29 -> 0.0081784387 | D36: =+D35/D$29 -> 0.0084865629 | E36: =+E35/E$29 -> 0.0095302927 | F36: =+F35/F$29 -> 0.011997177 | G36: =+G35/G$29 -> 0.01461794 | H36: =+H35/H$29 -> 0.014649682 | I36: =+I35/I$29 -> 0.014032947 | ... O36: =+O35/O$29 -> 0.011730205 | U36: =+U35/U$29 -> 0.019567909 | V36: =+V35/V$29 -> 0.019694732 | W36: =+W35/W$29 -> 0.0079743266 | X36: =+X35/X$29 -> 0.0060315978 | Y36: =+Y35/Y$29 -> 0.010536603 | Z36: =+Z35/Z$29 -> 0.0081794195 | AA36: =+AA35/AA$29 -> 0.011855905 | AB36: =+AB35/AB$29 -> 0.011588412 | ... AE36: =+AE35/AE$29 -> 0.013461005
A37: COGS | B37: =+B35+B33+B31 -> 127 | C37: =+C35+C33+C31 -> 127 | D37: =+D35+D33+D31 -> 127 | E37: =+E35+E33+E31 -> 130 | F37: =+F35+F33+F31 -> 137 | G37: =+G35+G33+G31 -> 140 | H37: =+H35+H33+H31 -> 147 | I37: =+I35+I33+I31 -> 154 | ... Q37: =+Q35+Q33+Q31 -> 0 | U37: =+U35+U33+U31 -> 370.7 | V37: =+V35+V33+V31 -> 341.9 | W37: =+W35+W33+W31 -> 303.4 | X37: =+X35+X33+X31 -> 285.9 | Y37: =+Y35+Y33+Y31 -> 324.9 | Z37: =+Z35+Z33+Z31 -> 337 | AA37: =+AA35+AA33+AA31 -> 418 | AB37: =+AB35+AB33+AB31 -> 480 | ... AE37: =+AE35+AE33+AE31 -> 650 | AF37: =+AF29-AF39 -> 745.821 | AG37: =+AG29-AG39 -> 850.23594 | AH37: =+AH29-AH39 -> 960.76661 | AI37: =+AI29-AI39 -> 1076.0586 | AJ37: =+AJ29-AJ39 -> 1194.4251
B38: =+B37/B$29 -> 0.1000788 | C38: =+C37/C$29 -> 0.094423792 | D38: =+D37/D$29 -> 0.089816124 | E38: =+E37/E$29 -> 0.088495575 | F38: =+F37/F$29 -> 0.096683133 | G38: =+G37/G$29 -> 0.093023256 | H38: =+H37/H$29 -> 0.093630573 | I38: =+I37/I$29 -> 0.093959732 | ... O38: =+O37/O$29 -> 0.086021505 | U38: =+U37/U$29 -> 0.14803722 | V38: =+V37/V$29 -> 0.16834072 | W38: =+W37/W$29 -> 0.14752504 | X38: =+X37/X$29 -> 0.11125379 | Y38: =+Y37/Y$29 -> 0.099227316 | Z38: =+Z37/Z$29 -> 0.088918206 | AA38: =+AA37/AA$29 -> 0.095303238 | AB38: =+AB37/AB$29 -> 0.095904096 | ... AJ38: =+AJ37/AJ$29 -> 0.09
A39: Gross Profit | B39: =+B29-B37 -> 1142 | C39: =+C29-C37 -> 1218 | D39: =+D29-D37 -> 1287 | E39: =+E29-E37 -> 1339 | F39: =+F29-F37 -> 1280 | G39: =+G29-G37 -> 1365 | H39: =+H29-H37 -> 1423 | I39: =+I29-I37 -> 1485 | ... Q39: =+Q29-Q37 -> 0 | U39: =+U29-U37 -> 2133.4 | V39: =+V29-V37 -> 1689.1 | W39: =+W29-W37 -> 1753.2 | X39: =+X29-X37 -> 2283.9 | Y39: =+Y29-Y37 -> 2949.4 | Z39: =+Z29-Z37 -> 3453 | AA39: =+AA29-AA37 -> 3968 | AB39: =+AB29-AB37 -> 4525 | ... AE39: =+AE29-AE37 -> 6556 | AF39: =+AF29*0.91 -> 7541.079 | AG39: =+AG29*0.91 -> 8596.8301 | AH39: =+AH29*0.91 -> 9714.418 | AI39: =+AI29*0.91 -> 10880.148 | AJ39: =+AJ29*0.91 -> 12076.964
B40: =+B39/B$29 -> 0.8999212 | C40: =+C39/C$29 -> 0.90557621 | D40: =+D39/D$29 -> 0.91018388 | E40: =+E39/E$29 -> 0.91150442 | F40: =+F39/F$29 -> 0.90331687 | G40: =+G39/G$29 -> 0.90697674 | H40: =+H39/H$29 -> 0.90636943 | I40: =+I39/I$29 -> 0.90604027 | ... O40: =+O39/O$29 -> 0.91397849 | U40: =+U39/U$29 -> 0.85196278 | V40: =+V39/V$29 -> 0.83165928 | W40: =+W39/W$29 -> 0.85247496 | X40: =+X39/X$29 -> 0.88874621 | Y40: =+Y39/Y$29 -> 0.90077268 | Z40: =+Z39/Z$29 -> 0.91108179 | AA40: =+AA39/AA$29 -> 0.90469676 | AB40: =+AB39/AB$29 -> 0.9040959 | ... AJ40: =+AJ39/AJ$29 -> 0.91
A41: M&S | B41: 456 | C41: 449 | D41: 439 | E41: 479 | F41: 469 | G41: 480 | H41: 525 | I41: 526 | J41: 566 | K41: 559 | L41: 612 | M41: 636 | N41: 593 | O41: 616 | U41: 1015.5 | V41: 1022.5 | W41: 1087.3 | X41: 1183.9 | Y41: 1310.3 | Z41: 1440 | AA41: 1623 | AB41: 1745 | AC41: 1823 | AD41: 2000 | AE41: 2373 | AF41: =+AF29*0.32 -> 2651.808 | AG41: =+AG29*0.32 -> 3023.0611 | AH41: =+AH29*0.3 -> 3202.5554 | AI41: =+AI29*0.3 -> 3586.862 | AJ41: =+AJ29*0.3 -> 3981.4168
B42: =+B41/B$29 -> 0.35933806 | C42: =+C41/C$29 -> 0.333829 | D42: =+D41/D$29 -> 0.31046676 | E42: =+E41/E$29 -> 0.32607216 | F42: =+F41/F$29 -> 0.33098095 | G42: =+G41/G$29 -> 0.31893688 | H42: =+H41/H$29 -> 0.3343949 | I42: =+I41/I$29 -> 0.32092739 | ... O42: =+O41/O$29 -> 0.30107527 | U42: =+U41/U$29 -> 0.40553492 | V42: =+V41/V$29 -> 0.50344658 | W42: =+W41/W$29 -> 0.52868813 | X42: =+X41/X$29 -> 0.46069733 | Y42: =+Y41/Y$29 -> 0.40017714 | Z42: =+Z41/Z$29 -> 0.37994723 | AA42: =+AA41/AA$29 -> 0.37004104 | AB42: =+AB41/AB$29 -> 0.34865135 | ... AJ42: =+AJ41/AJ$29 -> 0.3
A43: R&D | B43: 327 | C43: 355 | D43: 339 | E43: 352 | F43: 346 | G43: 368 | H43: 378 | I43: 393 | J43: 394 | K43: 413 | L43: 416 | M43: 420 | N43: 421 | O43: 464 | U43: 790 | V43: 766.1 | W43: 755.5 | X43: 725 | Y43: 851.1 | Z43: 932 | AA43: 1115 | AB43: 1219 | AC43: 1373 | AD43: 1485 | AE43: 1643 | AF43: =+AF29*0.24 -> 1988.856 | AG43: =+AG29*0.22 -> 2078.3545 | AH43: =+AH29*0.22 -> 2348.5406 | AI43: =+AI29*0.2 -> 2391.2413 | AJ43: =+AJ29*0.2 -> 2654.2779
B44: =+B43/B$29 -> 0.25768322 | C44: =+C43/C$29 -> 0.26394052 | D44: =+D43/D$29 -> 0.2397454 | E44: =+E43/E$29 -> 0.23961879 | F44: =+F43/F$29 -> 0.24417784 | G44: =+G43/G$29 -> 0.24451827 | H44: =+H43/H$29 -> 0.24076433 | I44: =+I43/I$29 -> 0.23978035 | ... O44: =+O43/O$29 -> 0.22678397 | U44: =+U43/U$29 -> 0.31548261 | V44: =+V43/V$29 -> 0.37720335 | W44: =+W43/W$29 -> 0.36735389 | X44: =+X43/X$29 -> 0.28212312 | Y44: =+Y43/Y$29 -> 0.25993342 | Z44: =+Z43/Z$29 -> 0.24591029 | AA44: =+AA43/AA$29 -> 0.25421797 | AB44: =+AB43/AB$29 -> 0.24355644 | ... AJ44: =+AJ43/AJ$29 -> 0.2
A45: G&A | B45: 132 | C45: 141 | D45: 165 | E45: 182 | F45: 155 | G45: 161 | H45: 161 | I45: 173 | J45: 162 | K45: 168 | L45: 172 | M45: 191 | N45: 162 | O45: 179 | U45: 293.4 | V45: 287.8 | W45: 305.2 | X45: 340.1 | Y45: 405.6 | Z45: 414 | AA45: 572 | AB45: 532 | AC45: 620 | AD45: 650 | AE45: 693 | AF45: =+AF29*0.1 -> 828.69 | AG45: =+AG29*0.095 -> 897.47127 | AH45: =+AH29*0.095 -> 1014.1425 | AI45: =+AI29*0.09 -> 1076.0586 | AJ45: =+AJ29*0.09 -> 1194.4251
B46: =+B45/B$29 -> 0.10401891 | C46: =+C45/C$29 -> 0.10483271 | D46: =+D45/D$29 -> 0.11669024 | E46: =+E45/E$29 -> 0.12389381 | F46: =+F45/F$29 -> 0.10938603 | G46: =+G45/G$29 -> 0.10697674 | H46: =+H45/H$29 -> 0.10254777 | I46: =+I45/I$29 -> 0.10555217 | ... O46: =+O45/O$29 -> 0.087487781 | U46: =+U45/U$29 -> 0.11716784 | V46: =+V45/V$29 -> 0.14170359 | W46: =+W45/W$29 -> 0.14840027 | X46: =+X45/X$29 -> 0.13234493 | Y46: =+Y45/Y$29 -> 0.12387381 | Z46: =+Z45/Z$29 -> 0.10923483 | AA46: =+AA45/AA$29 -> 0.13041496 | AB46: =+AB45/AB$29 -> 0.10629371 | ... AJ46: =+AJ45/AJ$29 -> 0.09
A47: Amortisation purchase | B47: 10 | C47: 11 | D47: 10 | E47: 11 | F47: 11 | G47: 13 | H47: 13 | I47: 12 | J47: 13 | K47: 14 | L47: 13 | M47: 13 | N47: 12 | O47: 13 | U47: 33.2 | V47: 31.8 | W47: 20.2 | X47: 18 | Y47: 38.9 | Z47: 38 | AA47: 40 | AB47: 40 | AC47: 42 | AD47: 49 | AE47: 53 | AF47: =+AF29*0.008 -> 66.2952 | AG47: =+AG29*0.008 -> 75.576528 | AH47: =+AH29*0.008 -> 85.401477 | AI47: =+AI29*0.008 -> 95.649654 | AJ47: =+AJ29*0.008 -> 106.17112
B48: =+B47/B$29 -> 0.0078802206 | C48: =+C47/C$29 -> 0.0081784387 | D48: =+D47/D$29 -> 0.0070721358 | E48: =+E47/E$29 -> 0.0074880871 | F48: =+F47/F$29 -> 0.0077628793 | G48: =+G47/G$29 -> 0.0086378738 | H48: =+H47/H$29 -> 0.0082802548 | I48: =+I47/I$29 -> 0.0073215375 | ... O48: =+O47/O$29 -> 0.0063538612 | U48: =+U47/U$29 -> 0.013258256 | V48: =+V47/V$29 -> 0.015657312 | W48: =+W47/W$29 -> 0.0098220364 | X48: =+X47/X$29 -> 0.0070044361 | Y48: =+Y47/Y$29 -> 0.011880402 | Z48: =+Z47/Z$29 -> 0.010026385 | AA48: =+AA47/AA$29 -> 0.009119927 | AB48: =+AB47/AB$29 -> 0.007992008 | ... AJ48: =+AJ47/AJ$29 -> 0.008
A49: Restructuring | B49: 0 | C49: 0 | D49: 0 | E49: 0 | F49: 0 | G49: 0 | H49: 0 | I49: 15 | J49: 105 | K49: 6 | L49: 5 | M49: 100 | N49: 30 | O49: -1 | U49: 0 | V49: 80.5 | W49: 94.1 | X49: 41.9 | Y49: 0.5 | Z49: 0 | AA49: 0 | AB49: 0 | AC49: 0 | AD49: 15 | AE49: 216 | AF49: 0 | AG49: 0 | AH49: 0 | AI49: 0 | AJ49: 0
B50: =+B49/B$29 -> 0 | C50: =+C49/C$29 -> 0 | D50: =+D49/D$29 -> 0 | E50: =+E49/E$29 -> 0 | F50: =+F49/F$29 -> 0 | G50: =+G49/G$29 -> 0 | H50: =+H49/H$29 -> 0 | I50: =+I49/I$29 -> 0.0091519219 | ... O50: =+O49/O$29 -> -0.00048875855 | U50: =+U49/U$29 -> 0 | V50: =+V49/V$29 -> 0.039635647 | W50: =+W49/W$29 -> 0.04575513 | X50: =+X49/X$29 -> 0.016304771 | Y50: =+Y49/Y$29 -> 0.00015270439 | Z50: =+Z49/Z$29 -> 0 | AA50: =+AA49/AA$29 -> 0 | AB50: =+AB49/AB$29 -> 0 | ... AJ50: =+AJ49/AJ$29 -> 0
A51: Op Ex. | B51: =+B49+B47+B45+B43+B41 -> 925 | C51: =+C49+C47+C45+C43+C41 -> 956 | D51: =+D49+D47+D45+D43+D41 -> 953 | E51: =+E49+E47+E45+E43+E41 -> 1024 | F51: =+F49+F47+F45+F43+F41 -> 981 | G51: =+G49+G47+G45+G43+G41 -> 1022 | H51: =+H49+H47+H45+H43+H41 -> 1077 | I51: =+I49+I47+I45+I43+I41 -> 1119 | ... Q51: =+Q49+Q47+Q45+Q43+Q41 -> 0 | U51: =+U49+U47+U45+U43+U41 -> 2132.1 | V51: =+V49+V47+V45+V43+V41 -> 2188.7 | W51: =+W49+W47+W45+W43+W41 -> 2262.3 | X51: =+X49+X47+X45+X43+X41 -> 2308.9 | Y51: =+Y49+Y47+Y45+Y43+Y41 -> 2606.4 | Z51: =+Z49+Z47+Z45+Z43+Z41 -> 2824 | AA51: =+AA49+AA47+AA45+AA43+AA41 -> 3350 | AB51: =+AB49+AB47+AB45+AB43+AB41 -> 3536 | ... AJ51: =+AJ49+AJ47+AJ45+AJ43+AJ41 -> 7936.2909
B52: =+B51/B$29 -> 0.72892041 | C52: =+C51/C$29 -> 0.71078067 | D52: =+D51/D$29 -> 0.67397454 | E52: =+E51/E$29 -> 0.69707284 | F52: =+F51/F$29 -> 0.69230769 | G52: =+G51/G$29 -> 0.67906977 | H52: =+H51/H$29 -> 0.68598726 | I52: =+I51/I$29 -> 0.68273337 | ... O52: =+O51/O$29 -> 0.62121212 | U52: =+U51/U$29 -> 0.85144363 | V52: =+V51/V$29 -> 1.0776465 | W52: =+W51/W$29 -> 1.1000194 | X52: =+X51/X$29 -> 0.89847459 | Y52: =+Y51/Y$29 -> 0.79601747 | Z52: =+Z51/Z$29 -> 0.74511873 | AA52: =+AA51/AA$29 -> 0.76379389 | AB52: =+AB51/AB$29 -> 0.70649351 | ... AJ52: =+AJ51/AJ$29 -> 0.598
A53: EBIT | B53: =+B39-B51 -> 217 | C53: =+C39-C51 -> 262 | D53: =+D39-D51 -> 334 | E53: =+E39-E51 -> 315 | F53: =+F39-F51 -> 299 | G53: =+G39-G51 -> 343 | H53: =+H39-H51 -> 346 | I53: =+I39-I51 -> 366 | ... Q53: =+Q39-Q51 -> 0 | U53: =+U39-U51 -> 1.3 | V53: =+V39-V51 -> -499.6 | W53: =+W39-W51 -> -509.1 | X53: =+X39-X51 -> -25 | Y53: =+Y39-Y51 -> 343 | Z53: =+Z39-Z51 -> 629 | AA53: =+AA39-AA51 -> 618 | AB53: =+AB39-AB51 -> 989 | ... AJ53: =+AJ39-AJ51 -> 4140.6735
B54: =+B53/B$29 -> 0.17100079 | C54: =+C53/C$29 -> 0.19479554 | D54: =+D53/D$29 -> 0.23620934 | E54: =+E53/E$29 -> 0.21443159 | F54: =+F53/F$29 -> 0.21100917 | G54: =+G53/G$29 -> 0.22790698 | H54: =+H53/H$29 -> 0.22038217 | I54: =+I53/I$29 -> 0.22330689 | ... O54: =+O53/O$29 -> 0.29276637 | U54: =+U53/U$29 -> 0.0005191486 | V54: =+V53/V$29 -> -0.2459872 | W54: =+W53/W$29 -> -0.24754449 | X54: =+X53/X$29 -> -0.0097283835 | Y54: =+Y53/Y$29 -> 0.10475521 | Z54: =+Z53/Z$29 -> 0.16596306 | AA54: =+AA53/AA$29 -> 0.14090287 | AB54: =+AB53/AB$29 -> 0.1976024 | ... AJ54: =+AJ53/AJ$29 -> 0.312
A55: Interest | B55: 4 | C55: -4 | D55: -14 | E55: 22 | F55: 10 | G55: 9 | H55: 5 | I55: 6 | J55: 1 | K55: 12 | L55: -2 | M55: 14 | N55: 58 | O55: -6 | U55: -21.6 | V55: -24.2 | W55: -48.2 | X55: -17.7 | Y55: -48.2 | Z55: -82 | AA55: -53 | AB55: -43 | AC55: 8 | AD55: 30 | AE55: 25 | AF55: =+AF29*0.003 -> 24.8607 | AG55: =+AG29*0.003 -> 28.341198 | AH55: =+AH29*0.003 -> 32.025554 | AI55: =+AI29*0.003 -> 35.86862 | AJ55: =+AJ29*0.003 -> 39.814168
B56: =+B55/B$29 -> 0.0031520883 | C56: =+C55/C$29 -> -0.0029739777 | D56: =+D55/D$29 -> -0.0099009901 | E56: =+E55/E$29 -> 0.014976174 | F56: =+F55/F$29 -> 0.007057163 | G56: =+G55/G$29 -> 0.0059800664 | H56: =+H55/H$29 -> 0.0031847134 | I56: =+I55/I$29 -> 0.0036607688 | ... O56: =+O55/O$29 -> -0.0029325513 | U56: =+U55/U$29 -> -0.0086258536 | V56: =+V55/V$29 -> -0.011915313 | W56: =+W55/W$29 -> -0.02343674 | X56: =+X55/X$29 -> -0.0068876955 | Y56: =+Y55/Y$29 -> -0.014720704 | Z56: =+Z55/Z$29 -> -0.021635884 | AA56: =+AA55/AA$29 -> -0.012083903 | AB56: =+AB55/AB$29 -> -0.0085914086 | ... AJ56: =+AJ55/AJ$29 -> 0.003
A57: EBT | B57: =+B55+B53 -> 221 | C57: =+C55+C53 -> 258 | D57: =+D55+D53 -> 320 | E57: =+E55+E53 -> 337 | F57: =+F55+F53 -> 309 | G57: =+G55+G53 -> 352 | H57: =+H55+H53 -> 351 | I57: =+I55+I53 -> 372 | ... Q57: =+Q55+Q53 -> 0 | U57: =+U55+U53 -> -20.3 | V57: =+V55+V53 -> -523.8 | W57: =+W55+W53 -> -557.3 | X57: =+X55+X53 -> -42.7 | Y57: =+Y55+Y53 -> 294.8 | Z57: =+Z55+Z53 -> 547 | AA57: =+AA55+AA53 -> 565 | AB57: =+AB55+AB53 -> 946 | ... AJ57: =+AJ55+AJ53 -> 4180.4877
B58: =+B57/B$29 -> 0.17415288 | C58: =+C57/C$29 -> 0.19182156 | D58: =+D57/D$29 -> 0.22630835 | E58: =+E57/E$29 -> 0.22940776 | F58: =+F57/F$29 -> 0.21806634 | G58: =+G57/G$29 -> 0.23388704 | H58: =+H57/H$29 -> 0.22356688 | I58: =+I57/I$29 -> 0.22696766 | ... O58: =+O57/O$29 -> 0.28983382 | U58: =+U57/U$29 -> -0.008106705 | V58: =+V57/V$29 -> -0.25790251 | W58: =+W57/W$29 -> -0.27098123 | X58: =+X57/X$29 -> -0.016616079 | Y58: =+Y57/Y$29 -> 0.090034511 | Z58: =+Z57/Z$29 -> 0.14432718 | AA58: =+AA57/AA$29 -> 0.12881897 | AB58: =+AB57/AB$29 -> 0.18901099 | ... AJ58: =+AJ57/AJ$29 -> 0.315
A59: Taxes | B59: 60 | C59: 36 | D59: 79 | E59: 55 | F59: 57 | G59: 70 | H59: 76 | I59: 69 | J59: 82 | K59: 143 | L59: 125 | M59: 129 | N59: 108 | O59: 101 | U59: 310.5 | V59: 58.3 | W59: 9.6 | X59: 38.1 | Y59: 80.3 | Z59: -661 | AA59: 68 | AB59: 123 | AC59: 230 | AD59: 272 | AE59: 479 | AF59: =+AF57*0.2 -> 406.0581 | AG59: =+AG57*0.2 -> 510.14156 | AH59: =+AH57*0.2 -> 619.16071 | AI59: =+AI57*0.2 -> 753.24102 | AJ59: =+AJ57*0.2 -> 836.09754
B60: =+B59/B$29 -> 0.047281324 | C60: =+C59/C$29 -> 0.026765799 | D60: =+D59/D$29 -> 0.055869873 | E60: =+E59/E$29 -> 0.037440436 | F60: =+F59/F$29 -> 0.040225829 | G60: =+G59/G$29 -> 0.046511628 | H60: =+H59/H$29 -> 0.048407643 | I60: =+I59/I$29 -> 0.042098841 | ... O60: =+O59/O$29 -> 0.049364614 | U60: =+U59/U$29 -> 0.12399665 | V60: =+V59/V$29 -> 0.028705071 | W60: =+W59/W$29 -> 0.0046678985 | X60: =+X59/X$29 -> 0.014826057 | Y60: =+Y59/Y$29 -> 0.024524326 | Z60: =+Z59/Z$29 -> -0.17440633 | AA60: =+AA59/AA$29 -> 0.015503876 | AB60: =+AB59/AB$29 -> 0.024575425 | ... AJ60: =+AJ59/AJ$29 -> 0.063
A61: Net Income | B61: =+B57-B59 -> 161 | C61: =+C57-C59 -> 222 | D61: =+D57-D59 -> 241 | E61: =+E57-E59 -> 282 | F61: =+F57-F59 -> 252 | G61: =+G57-G59 -> 282 | H61: =+H57-H59 -> 275 | I61: =+I57-I59 -> 303 | ... Q61: =+Q57-Q59 -> 0 | U61: =+U57-U59 -> -330.8 | V61: =+V57-V59 -> -582.1 | W61: =+W57-W59 -> -566.9 | X61: =+X57-X59 -> -80.8 | Y61: =+Y57-Y59 -> 214.5 | Z61: =+Z57-Z59 -> 1208 | AA61: =+AA57-AA59 -> 497 | AB61: =+AB57-AB59 -> 823 | ... AJ61: =+AJ57-AJ59 -> 3344.3901
B62: =+B61/B$29 -> 0.12687155 | C62: =+C61/C$29 -> 0.16505576 | D62: =+D61/D$29 -> 0.17043847 | E62: =+E61/E$29 -> 0.19196732 | F62: =+F61/F$29 -> 0.17784051 | G62: =+G61/G$29 -> 0.18737542 | H62: =+H61/H$29 -> 0.17515924 | I62: =+I61/I$29 -> 0.18486882 | ... O62: =+O61/O$29 -> 0.24046921 | U62: =+U61/U$29 -> -0.13210335 | V62: =+V61/V$29 -> -0.28660758 | W62: =+W61/W$29 -> -0.27564913 | X62: =+X61/X$29 -> -0.031442136 | Y62: =+Y61/Y$29 -> 0.065510185 | Z62: =+Z61/Z$29 -> 0.31873351 | AA62: =+AA61/AA$29 -> 0.11331509 | AB62: =+AB61/AB$29 -> 0.16443556 | ... AJ62: =+AJ61/AJ$29 -> 0.252
A63: EPS | B63: =+B61/B65 -> 0.74537037 | C63: =+C61/C65 -> 1.0325581 | D63: =+D61/D65 -> 1.1157407 | E63: =+E61/E65 -> 1.3055556 | F63: =+F61/F65 -> 1.1612903 | G63: =+G61/G65 -> 1.2995392 | H63: =+H61/H65 -> 1.2672811 | I63: =+I61/I65 -> 1.3963134 | ... Q63: =+Q61/Q65 -> #DIV/0! | U63: =+U61/U65 -> -1.4637168 | V63: =+V61/V65 -> -2.6138303 | W63: =+W61/W65 -> -2.5826879 | X63: =+X61/X65 -> -0.36911832 | Y63: =+Y61/Y65 -> 0.96404494 | Z63: =+Z61/Z65 -> 5.4389914 | AA63: =+AA61/AA65 -> 2.2387387 | AB63: =+AB61/AB65 -> 3.7752294 | ... AJ63: =+AJ61/AJ65 -> 16.192978
F64: =+F63/B63-1 -> 0.55800441 | G64: =+G63/C63-1 -> 0.25856271 | H64: =+H63/D63-1 -> 0.13582041 | I64: =+I63/E63-1 -> 0.069516619 | J64: =+J63/F63-1 -> -0.39403292 | K64: =+K63/G63-1 -> 0.120254 | L64: =+L63/H63-1 -> 0.25887526 | M64: =+M63/I63-1 -> 0.057524444 | ... O64: =+O63/K63-1 -> 0.60168375 | V64: =+V63/U63-1 -> 0.78574861 | W64: =+W63/V63-1 -> -0.011914445 | X64: =+X63/W63-1 -> -0.85707978 | Y64: =+Y63/X63-1 -> -3.6117505 | Z64: =+Z63/Y63-1 -> 4.6418443 | AA64: =+AA63/Z63-1 -> -0.58839083 | AB64: =+AB63/AA63-1 -> 0.68631975 | AC64: =+AC63/AB63-1 -> 0.11104361 | ... AJ64: =+AJ63/AI63-1 -> 0.12121212
A65: Shares | B65: 216 | C65: 215 | D65: 216 | E65: 216 | F65: 217 | G65: 217 | H65: 217 | I65: 217 | J65: 216 | K65: 215 | L65: 215 | M65: 214 | N65: 212 | O65: 211 | U65: 226 | V65: 222.7 | W65: 219.5 | X65: 218.9 | Y65: 222.5 | Z65: 222.1 | AA65: 222 | AB65: 218 | AC65: 216 | AD65: 217 | AE65: 215 | AF65: =+AE65*0.995 -> 213.925 | AG65: =+AF65*0.995 -> 212.85538 | AH65: =+AG65*0.99 -> 210.72682 | AI65: =+AH65*0.99 -> 208.61955 | AJ65: =+AI65*0.99 -> 206.53336
C66: =+C65/B65-1 -> -0.0046296296 | D66: =+D65/C65-1 -> 0.0046511628 | E66: =+E65/D65-1 -> 0 | F66: =+F65/E65-1 -> 0.0046296296 | G66: =+G65/F65-1 -> 0 | H66: =+H65/G65-1 -> 0 | I66: =+I65/H65-1 -> 0 | J66: =+J65/I65-1 -> -0.0046082949 | ... O66: =+O65/N65-1 -> -0.0047169811 | V66: =+V65/U65-1 -> -0.01460177 | W66: =+W65/V65-1 -> -0.014369106 | X66: =+X65/W65-1 -> -0.0027334852 | Y66: =+Y65/X65-1 -> 0.016445866 | Z66: =+Z65/Y65-1 -> -0.0017977528 | AA66: =+AA65/Z65-1 -> -0.00045024764 | AB66: =+AB65/AA65-1 -> -0.018018018 | AC66: =+AC65/AB65-1 -> -0.0091743119 | ... AJ66: =+AJ65/AI65-1 -> -0.01
A68: Revenue | F68: =+F29/B29-1 -> 0.11662727 | G68: =+G29/C29-1 -> 0.11895911 | H68: =+H29/D29-1 -> 0.11032532 | I68: =+I29/E29-1 -> 0.11572498 | J68: =+J29/F29-1 -> 0.15243472 | K68: =+K29/G29-1 -> 0.17142857 | L68: =+L29/H29-1 -> 0.18025478 | M68: =+M29/I29-1 -> 0.19402074 | ... O68: =+O29/K29-1 -> 0.16052184 | V68: =+V29/U29-1 -> -0.18893015 | W68: =+W29/V29-1 -> 0.012604628 | X68: =+X29/W29-1 -> 0.24953807 | Y68: =+Y29/X29-1 -> 0.27414585 | Z68: =+Z29/Y29-1 -> 0.15749931 | AA68: =+AA29/Z29-1 -> 0.15725594 | AB68: =+AB29/AA29-1 -> 0.14113087 | AC68: =+AC29/AB29-1 -> 0.098301698 | ... AJ68: =+AJ29/AI29-1 -> 0.11
A69: Gross Margin | B69: =+B39/B29 -> 0.8999212 | C69: =+C39/C29 -> 0.90557621 | D69: =+D39/D29 -> 0.91018388 | E69: =+E39/E29 -> 0.91150442 | F69: =+F39/F29 -> 0.90331687 | G69: =+G39/G29 -> 0.90697674 | H69: =+H39/H29 -> 0.90636943 | I69: =+I39/I29 -> 0.90604027 | ... O69: =+O39/O29 -> 0.91397849 | U69: =+U39/U29 -> 0.85196278 | V69: =+V39/V29 -> 0.83165928 | W69: =+W39/W29 -> 0.85247496 | X69: =+X39/X29 -> 0.88874621 | Y69: =+Y39/Y29 -> 0.90077268 | Z69: =+Z39/Z29 -> 0.91108179 | AA69: =+AA39/AA29 -> 0.90469676 | AB69: =+AB39/AB29 -> 0.9040959 | ... AJ69: =+AJ39/AJ29 -> 0.91
A70: OP Margin | B70: =+B53/B29 -> 0.17100079 | C70: =+C53/C29 -> 0.19479554 | D70: =+D53/D29 -> 0.23620934 | E70: =+E53/E29 -> 0.21443159 | F70: =+F53/F29 -> 0.21100917 | G70: =+G53/G29 -> 0.22790698 | H70: =+H53/H29 -> 0.22038217 | I70: =+I53/I29 -> 0.22330689 | ... O70: =+O53/O29 -> 0.29276637 | U70: =+U53/U29 -> 0.0005191486 | V70: =+V53/V29 -> -0.2459872 | W70: =+W53/W29 -> -0.24754449 | X70: =+X53/X29 -> -0.0097283835 | Y70: =+Y53/Y29 -> 0.10475521 | Z70: =+Z53/Z29 -> 0.16596306 | AA70: =+AA53/AA29 -> 0.14090287 | AB70: =+AB53/AB29 -> 0.1976024 | ... AJ70: =+AJ53/AJ29 -> 0.312
A71: NI Margin | B71: =+B61/B29 -> 0.12687155 | C71: =+C61/C29 -> 0.16505576 | D71: =+D61/D29 -> 0.17043847 | E71: =+E61/E29 -> 0.19196732 | F71: =+F61/F29 -> 0.17784051 | G71: =+G61/G29 -> 0.18737542 | H71: =+H61/H29 -> 0.17515924 | I71: =+I61/I29 -> 0.18486882 | ... O71: =+O61/O29 -> 0.24046921 | U71: =+U61/U29 -> -0.13210335 | V71: =+V61/V29 -> -0.28660758 | W71: =+W61/W29 -> -0.27564913 | X71: =+X61/X29 -> -0.031442136 | Y71: =+Y61/Y29 -> 0.065510185 | Z71: =+Z61/Z29 -> 0.31873351 | AA71: =+AA61/AA29 -> 0.11331509 | AB71: =+AB61/AB29 -> 0.16443556 | ... AJ71: =+AJ61/AJ29 -> 0.252
A72: Tax Rate | B72: =+B59/B57 -> 0.27149321 | C72: =+C59/C57 -> 0.13953488 | D72: =+D59/D57 -> 0.246875 | E72: =+E59/E57 -> 0.16320475 | F72: =+F59/F57 -> 0.18446602 | G72: =+G59/G57 -> 0.19886364 | H72: =+H59/H57 -> 0.21652422 | I72: =+I59/I57 -> 0.18548387 | ... O72: =+O59/O57 -> 0.1703204 | U72: =+U59/U57 -> -15.295567 | V72: =+V59/V57 -> -0.11130202 | W72: =+W59/W57 -> -0.017225911 | X72: =+X59/X57 -> -0.89227166 | Y72: =+Y59/Y57 -> 0.27238806 | Z72: =+Z59/Z57 -> -1.2084095 | AA72: =+AA59/AA57 -> 0.12035398 | AB72: =+AB59/AB57 -> 0.13002114 | ... AJ72: =+AJ59/AJ57 -> 0.2
A73: Inc. Margin | I73: =+(SUM(F53:I53)-SUM(B53:E53))/(SUM(F29:I29)-SUM(B29:E29)) -> 0.35646688 | J73: =+(SUM(G53:J53)-SUM(C53:F53))/(SUM(G29:J29)-SUM(C29:F29)) -> 0.11111111 | K73: =+(SUM(H53:K53)-SUM(D53:G53))/(SUM(H29:K29)-SUM(D29:G29)) -> 0.1225 | L73: =+(SUM(I53:L53)-SUM(E53:H53))/(SUM(I29:L29)-SUM(E29:H29)) -> 0.22653722 | M73: =+(SUM(J53:M53)-SUM(F53:I53))/(SUM(J29:M29)-SUM(F29:I29)) -> 0.20837209 | N73: =+(SUM(K53:N53)-SUM(G53:J53))/(SUM(K29:N29)-SUM(G29:J29)) -> 0.51551724 | O73: =+(SUM(L53:O53)-SUM(H53:K53))/(SUM(L29:O29)-SUM(H29:K29)) -> 0.55021097 | V73: =+(V53-U53)/(V29-U29) -> 1.0587614 | W73: =+(W53-V53)/(W29-V29) -> -0.37109375 | X73: =+(X53-W53)/(X29-W29) -> 0.94329696 | Y73: =+(Y53-X53)/(Y29-X29) -> 0.52235628 | Z73: =+(Z53-Y53)/(Z29-Y29) -> 0.554586 | AA73: =+(AA53-Z53)/(AA29-Z29) -> -0.018456376 | AB73: =+(AB53-AA53)/(AB29-AA29) -> 0.5993538 | AC73: =+(AC53-AB53)/(AC29-AB29) -> 0.28252033 | ... AJ73: =+(AJ53-AI53)/(AJ29-AI29) -> 0.312
A74: Rule of 40 | V74: =+V68+V70 -> -0.43491735 | W74: =+W68+W70 -> -0.23493986 | X74: =+X68+X70 -> 0.23980969 | Y74: =+Y68+Y70 -> 0.37890106 | Z74: =+Z68+Z70 -> 0.32346237 | AA74: =+AA68+AA70 -> 0.29815881 | AB74: =+AB68+AB70 -> 0.33873327 | AC74: =+AC68+AC70 -> 0.30350454 | ... AJ74: =+AJ68+AJ70 -> 0.422
A77: EBITDA | B77: =+B53+B136 -> 280 | C77: =+C53+C136 -> 328 | D77: =+D53+D136 -> 404 | E77: =+E53+E136 -> 395 | F77: =+F53+F136 -> 380 | G77: =+G53+G136 -> 433 | H77: =+H53+H136 -> 445 | I77: =+I53+I136 -> 488 | ... O77: =+O53+O136 -> 824 | U77: =+U53+U136 -> 147.1 | V77: =+V53+V136 -> -360.4 | W77: =+W53+W136 -> -400.7 | X77: =+X53+X136 -> 70.2 | Y77: =+Y53+Y136 -> 470.3 | Z77: =+Z53+Z136 -> 753 | AA77: =+AA53+AA136 -> 766 | AB77: =+AB53+AB136 -> 1139 | ... AJ77: =+AJ53+AJ136 -> 5467.8125
A78: Adj. EBITDA | B78: =+B77+B139+B140+B141 -> 239 | C78: =+C77+C139+C140+C141 -> 278 | D78: =+D77+D139+D140+D141 -> 371 | E78: =+E77+E139+E140+E141 -> 395 | F78: =+F77+F139+F140+F141 -> 373 | G78: =+G77+G139+G140+G141 -> 395 | H78: =+H77+H139+H140+H141 -> 423 | I78: =+I77+I139+I140+I141 -> 433 | ... O78: =+O77+O139+O140+O141 -> 841 | U78: =+U77+U139+U140+U141 -> 358 | V78: =+V77+V139+V140+V141 -> -326.4 | W78: =+W77+W139+W140+W141 -> -338.4 | X78: =+X77+X139+X140+X141 -> 97.3 | Y78: =+Y77+Y139+Y140+Y141 -> 469.2 | Z78: =+Z77+Z139+Z140+Z141 -> 13 | AA78: =+AA77+AA139+AA140+AA141 -> 880 | AB78: =+AB77+AB139+AB140+AB141 -> 888 | ... AE78: =+AE77+AE139+AE140+AE141 -> 2619
AL79: Discount | AM79: =+Main!E10 -> 0.11095369 | AP79: EV | AQ79: =+AM81 -> 50297.398
A80: NOPAT | U80: =+U53*(1-U72) -> 21.184236 | V80: =+V53*(1-V72) -> -555.20649 | W80: =+W53*(1-W72) -> -517.86971 | X80: =+X53*(1-X72) -> -47.306792 | Y80: =+Y53*(1-Y72) -> 249.5709 | Z80: =+Z53*(1-Z72) -> 1389.0896 | AA80: =+AA53*(1-AA72) -> 543.62124 | AB80: =+AB53*(1-AB72) -> 860.40909 | ... AJ80: =+AJ53*(1-AJ72) -> 3312.5388 | AL80: Terminal | AM80: 0.02 | AP80: Cash | AQ80: =+Main!F4 -> 4357
A81: NWC | U81: =+U93+U94-(U105+U114+U112+U109+U106) -> -819.4 | V81: =+V93+V94-(V105+V114+V112+V109+V106) -> -1176 | W81: =+W93+W94-(W105+W114+W112+W109+W106) -> -1540.5 | X81: =+X93+X94-(X105+X114+X112+X109+X106) -> -1621.6 | Y81: =+Y93+Y94-(Y105+Y114+Y112+Y109+Y106) -> -1932.7 | Z81: =+Z93+Z94-(Z105+Z114+Z112+Z109+Z106) -> -3805.4 | AA81: =+AA93+AA94-(AA105+AA114+AA112+AA109+AA106) -> -2629 | AB81: =+AB93+AB94-(AB105+AB114+AB112+AB109+AB106) -> -2698 | ... AJ81: =+AJ93+AJ94-(AJ105+AJ114+AJ112+AJ109+AJ106) -> -6810.6139 | AL81: EV | AM81: =+NPV(AM79,AF82:AI82,AJ82+AN82) -> 50297.398 | AP81: Debt | AQ81: =+Main!F5 -> 3478
A82: UFCF | X82: =+X80+X136-X149-(X81-W81) -> 61.993208 | Y82: =+Y80+Y136-Y149-(Y81-X81) -> 634.7709 | Z82: =+Z80+Z136-Z149-(Z81-Y81) -> 3294.7896 | AA82: =+AA80+AA136-AA149-(AA81-Z81) -> -540.77876 | AB82: =+AB80+AB136-AB149-(AB81-AA81) -> 1039.4091 | AC82: =+AC80+AC136-AC149-(AC81-AB81) -> 1431.6197 | AD82: =+AD80+AD136-AD149-(AD81-AC81) -> 1650.896 | AE82: =+AE80+AE136-AE149-(AE81-AD81) -> 2010.4704 | ... AJ82: =+AJ80+AJ136-AJ149-(AJ81-AI81) -> 5197.7913 | AL82: TV | AM82: =+AJ82*(1+AM80)/(AM79-AM80) -> 58290.624 | AN82: =+AJ77*11 -> 60145.937 | AP82: Equity Value | AQ82: =+AQ79+AQ80-AQ81 -> 51176.398
AL83: Diff | AM83: =+AM81/Main!F6-1 -> 0.065826068 | AN83: =+AJ77*30 -> 164034.37 | AP83: Shares | AQ83: =+Main!F2 -> 209
AP84: Price | AQ84: =+AQ82/AQ83 -> 244.86315
AQ85: =+AQ84/Main!F1-1 -> 0.064622384
A91: Cash | E91: 1892 | F91: 1681 | G91: 1513 | H91: 1437 | I91: 1599 | J91: 1816 | K91: 2003 | L91: 1989 | M91: 2249 | N91: 2671 | O91: 4098 | U91: 1353 | V91: 1213.1 | W91: 1078 | X91: 886 | Y91: 1774.7 | Z91: 1772.2 | AA91: 1528 | AB91: 1947 | AC91: 1892 | AD91: 1599 | AE91: 2249
A92: Mrk. Sec | E92: =+354+234 -> 588 | F92: =+308+238 -> 546 | G92: =+365+231 -> 596 | H92: =+276+264 -> 540 | I92: =+287+267 -> 554 | J92: =+224+261 -> 485 | K92: =+233+282 -> 515 | L92: =+300+302 -> 602 | M92: =+348+376 -> 724 | N92: =+253+385 -> 638 | O92: =+57+202 -> 259 | U92: 897.9 | V92: =+686.8+306.2 -> 993 | W92: =+245.2+190.8 -> 436 | X92: =+67.6+0 -> 67.6 | Y92: =+69+0 -> 69 | Z92: =+4+0 -> 4 | AA92: =+236+45 -> 281 | AB92: =+125+102 -> 227 | AC92: =+354+234 -> 588 | AD92: =+287+267 -> 554 | AE92: =+348+376 -> 724
A93: A/R | E93: 876 | F93: 353 | G93: 402 | H93: 702 | I93: 1008 | J93: 494 | K93: 532 | L93: 806 | M93: 1439 | N93: 579 | O93: 684 | U93: 653.6 | V93: 452.3 | W93: 438.2 | X93: 474.3 | Y93: 652.3 | Z93: 643.1 | AA93: 716 | AB93: 961 | AC93: 876 | AD93: 1008 | AE93: 1439 | AF93: =+AF191*AF29/365 -> 1429.7288 | AG93: =+AG191*AG29/365 -> 1655.7732 | AH93: =+AH191*AH29/365 -> 1900.2708 | AI93: =+AI191*AI29/365 -> 2161.0601 | AJ93: =+AJ191*AJ29/365 -> 2435.1367
A94: Prepaid Exp | E94: 457 | F94: 468 | G94: 478 | H94: 484 | I94: 588 | J94: 681 | K94: 721 | L94: 800 | M94: 906 | N94: 871 | O94: 831 | U94: 88.6 | V94: 108.4 | W94: 116.5 | X94: 192.1 | Y94: 163.3 | Z94: 206.2 | AA94: 284 | AB94: 308 | AC94: 457 | AD94: 588 | AE94: 906 | AF94: =+AF29*0.1 -> 828.69 | AG94: =+AG29*0.1 -> 944.7066 | AH94: =+AH29*0.1 -> 1067.5185 | AI94: =+AI29*0.1 -> 1195.6207 | AJ94: =+AJ29*0.1 -> 1327.1389
B95: =+B94/B29 -> 0 | C95: =+C94/C29 -> 0 | D95: =+D94/D29 -> 0 | E95: =+E94/E29 -> 0.31109598 | F95: =+F94/F29 -> 0.33027523 | G95: =+G94/G29 -> 0.31760797 | H95: =+H94/H29 -> 0.30828025 | I95: =+I94/I29 -> 0.35875534 | ... O95: =+O94/O29 -> 0.40615836 | U95: =+U94/U29 -> 0.035381974 | V95: =+V94/V29 -> 0.053372723 | W95: =+W94/W29 -> 0.056646893 | X95: =+X94/X29 -> 0.074752899 | Y95: =+Y94/Y29 -> 0.049873255 | Z95: =+Z94/Z29 -> 0.054406332 | AA95: =+AA94/AA29 -> 0.064751482 | AB95: =+AB94/AB29 -> 0.061538462 | AC95: =+AC94/AC29 -> 0.083136256 | AD95: =+AD94/AD$29 -> 0.095906051 | AE95: =+AE94/AE$29 -> 0.12572856 | AF95: =+AF94/AF$29 -> 0.1 | AG95: =+AG94/AG$29 -> 0.1 | AH95: =+AH94/AH$29 -> 0.1 | AI95: =+AI94/AI$29 -> 0.1 | AJ95: =+AJ94/AJ$29 -> 0.1
A96: Computer Equip. | E96: 121 | F96: 117 | G96: 116 | H96: 116 | I96: 117 | J96: 111 | K96: 109 | L96: 118 | M96: 121 | N96: 122 | O96: 124 | U96: 169.3 | V96: 158.6 | W96: 145 | X96: 149.7 | Y96: 161.7 | Z96: 192.8 | AA96: 162 | AB96: 144 | AC96: 121 | AD96: 117 | AE96: 121
A97: OP Lease ROU | E97: 224 | F97: 214 | G97: 205 | H97: 184 | I97: 169 | J97: 147 | K97: 149 | L97: 152 | M97: 157 | N97: 152 | O97: 145 | U97: 70.8 | V97: 45.7 | W97: 27.1 | X97: 0 | Y97: 438.8 | Z97: 416.7 | AA97: 305 | AB97: 245 | AC97: 224 | AD97: 169 | AE97: 157
A98: Intangible | E98: 406 | F98: 572 | G98: 609 | H98: 594 | I98: 574 | J98: 549 | K98: 521 | L98: 493 | M98: 467 | N98: 453 | O98: 423 | U98: 0 | V98: 0 | W98: 0 | X98: 0 | Y98: 70.9 | Z98: 199.3 | AA98: 494 | AB98: 407 | AC98: 406 | AD98: 574 | AE98: 467
A99: Goodwill | E99: 3653 | F99: 4133 | G99: 4253 | H99: 4256 | I99: 4242 | J99: 4275 | K99: 4275 | L99: 4278 | M99: 4295 | N99: 4337 | O99: 4331 | U99: 1535 | V99: 1561.1 | W99: 1620.2 | X99: 2450.8 | Y99: 2445 | Z99: 2706.5 | AA99: 3604 | AB99: 3625 | AC99: 3653 | AD99: 4242 | AE99: 4295
A100: D/T | E100: 1093 | F100: 1126 | G100: 1129 | H100: 1150 | I100: 1205 | J100: 1128 | K100: 1053 | L100: 936 | M100: 842 | N100: 813 | O100: 808 | U100: 9.2 | V100: 63.9 | W100: 81.7 | X100: 65.3 | Y100: 56.4 | Z100: 763.1 | AA100: 741 | AB100: 1014 | AC100: 1093 | AD100: 1205 | AE100: 842
A101: Other A | E101: 602 | F101: 620 | G101: 659 | H101: 670 | I101: 777 | J101: 899 | K101: 978 | L101: 1024 | M101: 1267 | N101: 1296 | O101: 1280 | U101: 205.6 | V101: 202 | W101: 170.9 | X101: =+337.8+105.6 -> 443.4 | Y101: 347.2 | Z101: 375.9 | AA101: 492 | AB101: 560 | AC101: 602 | AD101: 777 | AE101: 1267
A102: A | B102: =+SUM(B91:B101)-B95 -> 0 | C102: =+SUM(C91:C101)-C95 -> 0 | D102: =+SUM(D91:D101)-D95 -> 0 | E102: =+SUM(E91:E101)-E95 -> 9912 | F102: =+SUM(F91:F101)-F95 -> 9830 | G102: =+SUM(G91:G101)-G95 -> 9960 | H102: =+SUM(H91:H101)-H95 -> 10133 | I102: =+SUM(I91:I101)-I95 -> 10833 | ... Q102: =+SUM(Q91:Q101)-Q95 -> 0 | U102: =+SUM(U91:U101)-U95 -> 4983 | V102: =+SUM(V91:V101)-V95 -> 4798.1 | W102: =+SUM(W91:W101)-W95 -> 4113.6 | X102: =+SUM(X91:X101)-X95 -> 4729.2 | Y102: =+SUM(Y91:Y101)-Y95 -> 6179.3 | Z102: =+SUM(Z91:Z101)-Z95 -> 7279.8 | AA102: =+SUM(AA91:AA101)-AA95 -> 8607 | AB102: =+SUM(AB91:AB101)-AB95 -> 9438 | ... AE102: =+SUM(AE91:AE101)-AE95 -> 12467
A105: A/P | E105: 100 | F105: 163 | G105: 174 | H105: 217 | I105: 242 | J105: 277 | K105: 324 | L105: 384 | M105: 422 | N105: 403 | O105: 457 | U105: 119.9 | V105: 93.5 | W105: 94.7 | X105: 101.6 | Y105: 83.7 | Z105: 122.5 | AA105: 121 | AB105: 102 | AC105: 100 | AD105: 242 | AE105: 422 | AF105: =+AF193/365*AF37 -> 387.07245 | AG105: =+AG193/365*AG37 -> 448.25084 | AH105: =+AH193/365*AH37 -> 514.42016 | AI105: =+AI193/365*AI37 -> 584.9949 | AJ105: =+AJ193/365*AJ37 -> 659.16153
A106: Acc. Comp | E106: 476 | F106: 326 | G106: 361 | H106: 394 | I106: 506 | J106: 399 | K106: 388 | L106: 442 | M106: 659 | N106: 360 | O106: 354 | U106: 243.3 | V106: 238.2 | W106: 250.9 | X106: 280.8 | Y106: 272.1 | Z106: 322.6 | AA106: 341 | AB106: 358 | AC106: 476 | AD106: 506 | AE106: 659 | AF106: =+AF29*0.08 -> 662.952 | AG106: =+AG29*0.085 -> 803.00061 | AH106: =+AH29*0.09 -> 960.76661 | AI106: =+AI29*0.09 -> 1076.0586 | AJ106: =+AJ29*0.09 -> 1194.4251
U107: =+U106/U$29 -> 0.097160657 | V107: =+V106/V$29 -> 0.11728213 | W107: =+W106/W$29 -> 0.12199747 | X107: =+X106/X$29 -> 0.1092692 | Y107: =+Y106/Y$29 -> 0.083101732 | Z107: =+Z106/Z$29 -> 0.085118734 | AA107: =+AA106/AA$29 -> 0.077747378 | AB107: =+AB106/AB$29 -> 0.071528472 | ... AJ107: =+AJ106/AJ$29 -> 0.09
A108: Accr. Income Taxes | E108: 36 | F108: 59 | G108: 48 | H108: 73 | I108: 62 | J108: 84 | K108: 60 | L108: 98 | M108: 54 | N108: 75 | O108: 63 | U108: 29.4 | V108: 50 | W108: 28 | X108: 13.2 | Y108: 21.2 | Z108: 42.6 | AA108: 30 | AB108: 33 | AC108: 36 | AD108: 62 | AE108: 54
A109: D/R | E109: 3500 | F109: 3362 | G109: 3228 | H109: 3277 | I109: 3787 | J109: 3620 | K109: 3550 | L109: 3577 | M109: 4406 | N109: 4210 | O109: 4036 | U109: 1068.9 | V109: 1270.1 | W109: 1551.6 | X109: 1763.3 | Y109: 2176.1 | Z109: 2500.9 | AA109: 2863 | AB109: 3203 | AC109: 3500 | AD109: 3787 | AE109: 4406 | AF109: =+AF29*0.62 -> 5137.878 | AG109: =+AG29*0.62 -> 5857.1809 | AH109: =+AH29*0.62 -> 6618.6144 | AI109: =+AI29*0.62 -> 7412.8482 | AJ109: =+AJ29*0.62 -> 8228.2615
U110: =+U109/U$29 -> 0.42685995 | V110: =+V109/V$29 -> 0.62535697 | W110: =+W109/W$29 -> 0.75444909 | X110: =+X109/X$29 -> 0.68616235 | Y110: =+Y109/Y$29 -> 0.66460007 | Z110: =+Z109/Z$29 -> 0.65986807 | AA110: =+AA109/AA$29 -> 0.65275878 | AB110: =+AB109/AB$29 -> 0.63996004 | ... AJ110: =+AJ109/AJ$29 -> 0.62
A111: Debt | E111: =+0+2284 -> 2284 | F111: 2285 | G111: =+300+1986 -> 2286 | H111: =+300+1986 -> 2286 | I111: =+300+1987 -> 2287 | J111: =+300+1988 -> 2288 | K111: =+56+2481 -> 2537 | L111: =+57+2482 -> 2539 | M111: 2483 | N111: 2484 | O111: =+994+499+1985 -> 3478 | U111: =+0+1487.7 -> 1487.7 | V111: =+398.7+1092 -> 1490.7 | W111: 1586 | X111: 2087.7 | Y111: =+449.7+1635.1 -> 2084.8 | AA111: =+350+2278 -> 2628 | AB111: =+0+2281 -> 2281 | AC111: =+0+2284 -> 2284 | AD111: =+300+1987 -> 2287 | AE111: 2483
A112: OP Lease L | E112: 67 | F112: 66 | G112: 67 | H112: 60 | I112: 58 | J112: 57 | K112: 0 | L112: 0 | M112: 52 | N112: 53 | O112: 52 | U112: 0 | V112: 0 | W112: 0 | X112: 0 | Y112: 48.1 | Z112: 71.5 | AA112: 87 | AB112: 85 | AC112: 67 | AD112: 58 | AE112: 52 | AF112: =+AF29*0.007 -> 58.0083 | AG112: =+AG29*0.007 -> 66.129462 | AH112: =+AH29*0.007 -> 74.726292 | AI112: =+AI29*0.007 -> 83.693447 | AJ112: =+AJ29*0.007 -> 92.899726
U113: =+U112/U$29 -> 0 | V113: =+V112/V$29 -> 0 | W113: =+W112/W$29 -> 0 | X113: =+X112/X$29 -> 0 | Y113: =+Y112/Y$29 -> 0.014690163 | Z113: =+Z112/Z$29 -> 0.018865435 | AA113: =+AA112/AA$29 -> 0.019835841 | AB113: =+AB112/AB$29 -> 0.016983017 | ... AJ113: =+AJ112/AJ$29 -> 0.007
A114: Other, curr | E114: 172 | F114: 121 | G114: 159 | H114: 147 | I114: 196 | J114: 182 | K114: 188 | L114: 177 | M114: 215 | N114: 139 | O114: 173 | U114: 129.5 | V114: 134.9 | W114: 198 | X114: 142.3 | Y114: 168.3 | Z114: =+0+1637.2 -> 1637.2 | AA114: 217 | AB114: 219 | AC114: 172 | AD114: 196 | AE114: 215 | AF114: =+AF29*0.03 -> 248.607 | AG114: =+AG29*0.03 -> 283.41198 | AH114: =+AH29*0.03 -> 320.25554 | AI114: =+AI29*0.03 -> 358.6862 | AJ114: =+AJ29*0.03 -> 398.14168
B115: =+B114/B$29 -> 0 | C115: =+C114/C$29 -> 0 | D115: =+D114/D$29 -> 0 | E115: =+E114/E$29 -> 0.11708645 | F115: =+F114/F$29 -> 0.085391673 | G115: =+G114/G$29 -> 0.10564784 | H115: =+H114/H$29 -> 0.093630573 | I115: =+I114/I$29 -> 0.11958511 | ... O115: =+O114/O$29 -> 0.08455523 | U115: =+U114/U$29 -> 0.051715187 | V115: =+V114/V$29 -> 0.066420483 | W115: =+W114/W$29 -> 0.096275406 | X115: =+X114/X$29 -> 0.055373959 | Y115: =+Y114/Y$29 -> 0.051400299 | Z115: =+Z114/Z$29 -> 0.43197889 | AA115: =+AA114/AA$29 -> 0.049475604 | AB115: =+AB114/AB$29 -> 0.043756244 | ... AJ115: =+AJ114/AJ$29 -> 0.03
A116: D/R, non curr | E116: 764 | F116: 600 | G116: 464 | H116: 381 | I116: 341 | J116: 309 | K116: 294 | L116: 269 | M116: 287 | N116: 247 | O116: 222 | U116: 450.3 | V116: 517.9 | W116: 403.5 | X116: 328.1 | Y116: 831 | Z116: 859.3 | AA116: 927 | AB116: 1377 | AC116: 764 | AD116: 341 | AE116: 287
A117: OP Lease, non curr | E117: 275 | F117: 263 | G117: 250 | H117: 232 | I117: 214 | J117: 199 | K117: 197 | L117: 195 | M117: 199 | N117: 187 | O117: 175 | U117: 0 | V117: 0 | W117: 0 | X117: 0 | Y117: 411.7 | Z117: 396 | AA117: 346 | AB117: 300 | AC117: 275 | AD117: 214 | AE117: 199
A118: D/ Income/P, non curr | E118: 168 | F118: 178 | G118: 183 | H118: 192 | I118: 200 | J118: 206 | K118: 210 | L118: 216 | M118: 181 | N118: 186 | O118: 203 | U118: 67.7 | V118: 91.5 | W118: 66.6 | X118: 79.8 | Y118: 19.1 | Z118: 15.9 | AA118: 20 | AB118: 164 | AC118: 168 | AD118: 200 | AE118: 181
A119: D/ Income taxes, non curr | E119: 25 | F119: 42 | G119: 36 | H119: 35 | I119: 32 | J119: 31 | K119: 30 | L119: 27 | M119: 40 | N119: 45 | O119: 53 | U119: 161.4 | V119: 39.3 | W119: 41.6 | X119: 21.5 | Y119: 82.5 | Z119: 11.4 | AA119: 29 | AB119: 32 | AC119: 25 | AD119: 1987 | AE119: 40
...
