Workbook

Sheet Main
A1: Amazon.com | D1: Price | E1: 259 | J1: -> | K1: Q126 began testing robotaxis in Miami and Austin, expanded service in SF and Las Vegas.
D2: Share | E2: 10786.314 | F2: Q226 | K2: Driven 2 million miles and carried 350,000+ rides
D3: MC | E3: =+E2*E1 -> 2793655.2
D4: Cash | E4: 122988 | F4: Q226
D5: Debt | E5: 128894 | F5: Q226
D6: EV | E6: =+E3-E4+E5 -> 2799561.2
A8: CAPM | B8: =+0.05+B10*(0.1-0.05) -> 0.123 | D8: WACC | E8: =+(E3/(E3+E5))*B8+(E5/(E5+E3))*B9*(1-0.2) -> 0.11961632
A9: Cost of Debt | B9: =+0.05+(B19/100) -> 0.057847826
A10: BETA | B10: 1.46 | D10: FPE | E10: =+E1/SUM(Model!Q49:T49) -> 20.684523
A11: P/FCF | B11: =+E3/SUM(Model!P125:S125) -> -239.58051
A12: P/E | B12: =+E1/SUM(Model!P49:S49) -> 20.832267
A13: EV/EBITDA | B13: =+E6/SUM(Model!P74:S74) -> 16.574081 | D13: NTM | E13: =+E6/Model!AL74 -> 13.2917
A14: EV/FCF | B14: =+E6/SUM(Model!P125:S125) -> -240.087
A15: Inc Margin | B15: =+((Model!S33+Model!R33+Model!Q33+Model!P33)-(Model!O33+Model!N33+Model!M33+Model!L33))/((Model!S15+Model!R15+Model!Q15+Model!P15)-(Model!O15+Model!N15+Model!M15+Model!L15)) -> 0.16586206
A19: Cr. Spread | B19: =+'[1]Credit Spread US'!J6 -> 0.78478261
A20: Rating | B20: AA | C20: Aa2
B21: S&P | C21: Moody’s
A25: Manufacture products
B26: Kindle
B27: Fire Tablet
B28: Fire TV
B29: Echo
B30: Ring
B31: Blink
B32: Eero
B33: Amazon Leo (Satellite)
B34: -> | C34: AMZN to acquire GSAT to aff direct to devide (D2D) services.
B35: -> | C35: Partnership with AAPL to use satellites to iPhone and Apple Watches SOS call
A37: Services
B38: AWS (Amazon Web Service)
B39: -> | C39: Lambda (data centers)
B40: -> | C40: Annapurna Labs (acquired in 2015), it is AWS’ in house silicon-design organization
C41: responsible for the design of Trainium, Inferentia, Nitro (EC2 virtualisation/security infrastructure), Graviton (general CPU)
C42: This allows AWS to vertically integrate Chip Design / Networking Design / Build Data Centers / Offer EC2 / Offer SageMaker/Bedrock / Sell AI compute
C43: -> | D43: Annapurna projects the AI accelletarors together with Marvell
C44: -> | D44: TSMC is later in charge of materially manifactures the chips
C45: -> | D45: Marvell is in charge of the packaging, silicon engineering, connectivity, interfaces, …
B46: -> | C46: EC2 (Elastic Compute Cloud – Virtual servers)
C47: This service allows firms to rent compute, choosing RAM, CPU, storage, …
C48: EBS, is the persistent memory that survives the virtual machine.
B49: -> | C49: S3 (Simple Storage Service – Storage)
C50: Storage that is lent to companies (like google drive but for software to upload files at enormous dimension)
B51: -> | C51: RDS/Aurora (Relational Database Service - databases)
C52: RDS, stores tables that have all one element (column) in common → the elements are related by one element
C53: Amazon Aurora, this is Amazon’s own database engine (compatible with MySQL and PostgreSQL).
B54: -> | C54: Bedrock (GenAI)
C55: Software used by customers to use LLMs, add RAG (own data), fine tune, customise models, create agents, …
C56: -> | D56: Trainium (training accelerator), use the Neutron ecosystem for ML applications
C57: -> | D57: Inferentia (Inference accellerator), now Inf2 (second generation) with throughtput 4x inf1,
D58: -> | E58: Project Rainier, AI computing cluster (EC2 ultra cluster) with circa 500,000 Trn2 to expand Anthropic’s training workspace
C59: -> | D59: Amazon Nova, Amazon own AI model
D60: -> | E60: Amazon Nova forge, platform where amazon allows clients to access Nova’s training checkpoints to develop their own LLMs
C61: -> | D61: Amazon Bio Discovery (AI), Platform to design and test antibodies
D62: Give the system a target → the model proposes an antibody → the model ranks the candidates →
D63: → the labs manufactures and test them → the experiments are run on Bio Discovery → the model uses the results to loop the research
B64: -> | C64: DynamoDB (database)
B65: -> | C65: SageMaker (building, training and deploying LLMs)
B66: -> | C66: Amazon Transform, AWS’ migration and modernisation service. It modernises the IT of firms and automates certain tasks
C67: Ofc leads everything to AWS’ services
B69: Develope and produce Media content (Amazon Prime)
B70: Twitch
B71: Advertisement
B72: Sellers parnetship (they earn a per-unit fee)
A75: COGS | B75: purchase of consumer products,shipping costs,digital media
A76: Technology Infrastructure | B76: AWS costs / R&D
A77: Fulfillment | B77: Cost of operating the delivery that processes the order (payment costs, packing costs, storing,…)
A81: Seasonality on Q4 due to holidays (Christmas)
A84: Revenues
B85: Retail Sales | C85: sales to direct consumers
B86: Third Party services | C86: People using amazon parcel and amazon’s warehouses
B87: Subscriptions
B88: AWS | C88: Lease storage, computing, databases
B89: Other | C89: healthcare services, credit card agreements, …

Sheet Model
A1: Main | B1: 03/22 | C1: 06/22 | D1: 09/22 | E1: 12/22 | F1: 03/23 | G1: 06/23 | H1: 09/23 | I1: 12/23 | J1: 03/24 | K1: 06/24 | L1: 09/24 | M1: 12/24 | N1: 03/25 | O1: 06/25 | P1: 09/25 | Q1: 12/25 | R1: 03/26 | S1: 06/26 | T1: 09/26 | U1: 12/26 | AE1: 12/19 | AF1: 12/20 | AG1: 12/21 | AH1: 12/22 | AI1: 12/23 | AJ1: 12/24 | AK1: 12/25 | AL1: 12/26 | AM1: 12/27 | AN1: 12/28 | AO1: 12/29 | AP1: 12/30
A2: in Millions | B2: Q122 | C2: Q222 | D2: Q322 | E2: Q422 | F2: Q123 | G2: Q223 | H2: Q323 | I2: Q423 | J2: Q124 | K2: Q224 | L2: Q324 | M2: Q424 | N2: Q125 | O2: Q225 | P2: Q325 | Q2: Q425 | R2: Q126 | S2: Q226 | T2: Q326 | U2: Q426 | AA2: =+AB2-1 -> 2015 | AB2: =+AC2-1 -> 2016 | AC2: =+AD2-1 -> 2017 | AD2: =+AE2-1 -> 2018 | AE2: 2019 | AF2: 2020 | AG2: =AF2+1 -> 2021 | AH2: =AG2+1 -> 2022 | AI2: =AH2+1 -> 2023 | AJ2: =AI2+1 -> 2024 | AK2: =AJ2+1 -> 2025 | AL2: =AK2+1 -> 2026 | AM2: =AL2+1 -> 2027 | AN2: =AM2+1 -> 2028 | ... AP2: =AO2+1 -> 2030
A3: Microsoft Azure
A5: Google Cloud | B5: 5821 | C5: 6276 | D5: 6868 | E5: 7315 | F5: 7454 | G5: 8031 | H5: 8411 | I5: 9192 | J5: 9574 | K5: 10347 | L5: 11353 | M5: 11955 | N5: 12260 | O5: 13624 | P5: 15157 | Q5: 17664 | R5: 20028 | S5: =+O5*1.35 -> 18392.4 | T5: =+P5*1.35 -> 20461.95 | U5: =+Q5*1.35 -> 23846.4 | AF5: 13059 | AG5: 19206 | AH5: =+SUM(B5:E5) -> 26280 | AI5: =+SUM(F5:I5) -> 33088 | AJ5: =+SUM(J5:M5) -> 43229 | AK5: =+SUM(N5:Q5) -> 58705
F6: =+F5/B5-1 -> 0.28053599 | G6: =+G5/C5-1 -> 0.27963671 | H6: =+H5/D5-1 -> 0.22466511 | I6: =+I5/E5-1 -> 0.25659604 | J6: =+J5/F5-1 -> 0.28441105 | K6: =+K5/G5-1 -> 0.28838252 | L6: =+L5/H5-1 -> 0.34978005 | M6: =+M5/I5-1 -> 0.30058747 | ... S6: =+S5/O5-1 -> 0.35 | AG6: =+AG5/AF5-1 -> 0.47070986 | AH6: =+AH5/AG5-1 -> 0.3683224 | AI6: =+AI5/AH5-1 -> 0.25905632 | AJ6: =+AJ5/AI5-1 -> 0.30648574 | AK6: =+AK5/AJ5-1 -> 0.35800042
A7: AWS | B7: 18441 | C7: 19739 | D7: 20538 | E7: 21378 | F7: 21354 | G7: 22140 | H7: 23059 | I7: 24204 | J7: 25037 | K7: 26281 | L7: 27452 | M7: 28786 | N7: 29267 | O7: 30873 | P7: 33006 | Q7: 35579 | R7: 37587 | S7: 42232 | AA7: 7880 | AB7: 12219 | AC7: 17459 | AD7: 25655 | AE7: 35026 | AF7: 45370 | AG7: 62202 | AH7: 80096 | AI7: 90757 | AJ7: 107556 | AK7: 128725
B8: =+B7/B15 -> 0.15836797 | C8: =+C7/C15 -> 0.16281736 | D8: =+D7/D15 -> 0.16158803 | E8: =+E7/E15 -> 0.14328034 | F8: =+F7/F15 -> 0.16766909 | G8: =+G7/G15 -> 0.16475298 | H8: =+H7/H15 -> 0.16115821 | I8: =+I7/I15 -> 0.14240914 | ... S8: =+S7/S15 -> 0.21052212 | AA8: =+AA7/AA15 -> 0.07364073 | AB8: =+AB7/AB15 -> 0.089854177 | AC8: =+AC7/AC15 -> 0.098158164 | AD8: =+AD7/AD15 -> 0.11016072 | AE8: =+AE7/AE15 -> 0.12486008 | AF8: =+AF7/AF15 -> 0.11751938 | AG8: =+AG7/AG15 -> 0.13239482 | AH8: =+AH7/AH15 -> 0.15583395 | ... AK8: =+AK7/AK15 -> 0.17955181
A9: Y/Y | F9: =+F7/B7-1 -> 0.15796323 | G9: =+G7/C7-1 -> 0.12163737 | H9: =+H7/D7-1 -> 0.12274808 | I9: =+I7/E7-1 -> 0.13219197 | J9: =+J7/F7-1 -> 0.17247354 | K9: =+K7/G7-1 -> 0.18703704 | L9: =+L7/H7-1 -> 0.1905113 | M9: =+M7/I7-1 -> 0.18930755 | ... S9: =+S7/O7-1 -> 0.36792667 | AB9: =+AB7/AA7-1 -> 0.55063452 | AC9: =+AC7/AB7-1 -> 0.42884033 | AD9: =+AD7/AC7-1 -> 0.46944269 | AE9: =+AE7/AD7-1 -> 0.36526993 | AF9: =+AF7/AE7-1 -> 0.29532347 | AG9: =+AG7/AF7-1 -> 0.37099405 | AH9: =+AH7/AG7-1 -> 0.28767564 | AI9: =+AI7/AH7-1 -> 0.13310278 | ... AK9: =+AK7/AJ7-1 -> 0.1968184
A11: Product Sales | B11: 56455 | C11: 56575 | D11: 59340 | E11: 70531 | F11: 56981 | G11: 59032 | H11: 63171 | I11: 76703 | J11: 60915 | K11: 61569 | L11: 67601 | M11: 82226 | N11: 63970 | O11: 68246 | P11: 74058 | Q11: 89992 | R11: 71304 | S11: 77602 | AA11: 79268 | AB11: 94665 | AC11: 118573 | AD11: 141915 | AE11: 160408 | AF11: 215915 | AG11: 241787 | AH11: 242901 | AI11: 255887 | AJ11: 272311 | AK11: 296266
F12: =+F11/B11-1 -> 0.0093171553 | G12: =+G11/C11-1 -> 0.043429076 | H12: =+H11/D11-1 -> 0.064560162 | I12: =+I11/E11-1 -> 0.087507621 | J12: =+J11/F11-1 -> 0.069040557 | K12: =+K11/G11-1 -> 0.042976691 | L12: =+L11/H11-1 -> 0.070127115 | M12: =+M11/I11-1 -> 0.072005006 | ... S12: =+S11/O11-1 -> 0.13709228 | AF12: =+AF11/AE11-1 -> 0.34603636 | AG12: =+AG11/AF11-1 -> 0.11982493 | AH12: =+AH11/AG11-1 -> 0.004607361 | AI12: =+AI11/AH11-1 -> 0.05346211 | AJ12: =+AJ11/AI11-1 -> 0.064184581 | AK12: =+AK11/AJ11-1 -> 0.08796927
A13: Service Sales | B13: 59989 | C13: 64659 | D13: 67761 | E13: 78673 | F13: 70377 | G13: 75351 | H13: 79912 | I13: 93258 | J13: 82398 | K13: 86408 | L13: 91276 | M13: 105566 | N13: 91697 | O13: 99456 | P13: 106111 | Q13: 123394 | R13: 110215 | S13: 123004 | AA13: 27738 | AB13: 41322 | AC13: 59293 | AD13: 90972 | AE13: 120114 | AF13: 170149 | AG13: 228035 | AH13: 271082 | AI13: 318898 | AJ13: 365648 | AK13: 420658
F14: =+F13/B13-1 -> 0.17316508 | G14: =+G13/C13-1 -> 0.16535981 | H14: =+H13/D13-1 -> 0.17932144 | I14: =+I13/E13-1 -> 0.18538762 | J14: =+J13/F13-1 -> 0.17080864 | K14: =+K13/G13-1 -> 0.14673992 | L14: =+L13/H13-1 -> 0.14220643 | M14: =+M13/I13-1 -> 0.13197795 | ... S14: =+S13/O13-1 -> 0.23676802 | AF14: =+AF13/AE13-1 -> 0.4165626 | AG14: =+AG13/AF13-1 -> 0.3402077 | AH14: =+AH13/AG13-1 -> 0.18877365 | AI14: =+AI13/AH13-1 -> 0.17638943 | AJ14: =+AJ13/AI13-1 -> 0.1465986 | AK14: =+AK13/AJ13-1 -> 0.15044524
A15: Revenue | B15: =+B13+B11 -> 116444 | C15: =+C13+C11 -> 121234 | D15: =+D13+D11 -> 127101 | E15: =+E13+E11 -> 149204 | F15: =+F13+F11 -> 127358 | G15: =+G13+G11 -> 134383 | H15: =+H13+H11 -> 143083 | I15: =+I13+I11 -> 169961 | ... S15: =+S13+S11 -> 200606 | T15: =+P15*1.12 -> 201789.28 | U15: =+Q15*1.165 -> 248594.69 | AA15: =+AA13+AA11 -> 107006 | AB15: =+AB13+AB11 -> 135987 | AC15: =+AC13+AC11 -> 177866 | AD15: =+AD13+AD11 -> 232887 | AE15: =+AE13+AE11 -> 280522 | AF15: =+AF13+AF11 -> 386064 | AG15: =+AG13+AG11 -> 469822 | AH15: =+AH13+AH11 -> 513983 | ... AK15: =+AK13+AK11 -> 716924 | AL15: =+SUM(R15:U15) -> 832508.97 | AM15: =+AL15*1.15 -> 957385.32 | AN15: =+AM15*1.14 -> 1091419.3 | AO15: =+AN15*1.13 -> 1233303.8 | AP15: =+AO15*1.12 -> 1381300.2
F16: =+F15/B15-1 -> 0.093727457 | G16: =+G15/C15-1 -> 0.10845967 | H16: =+H15/D15-1 -> 0.12574252 | I16: =+I15/E15-1 -> 0.13911825 | J16: =+J15/F15-1 -> 0.12527678 | K16: =+K15/G15-1 -> 0.10115863 | L16: =+L15/H15-1 -> 0.11038348 | M16: =+M15/I15-1 -> 0.1049123 | ... U16: =+U15/Q15-1 -> 0.165 | AF16: =+AF15/AE15-1 -> 0.37623431 | AG16: =+AG15/AF15-1 -> 0.21695367 | AH16: =+AH15/AG15-1 -> 0.093995173 | AI16: =+AI15/AH15-1 -> 0.11829574 | AJ16: =+AJ15/AI15-1 -> 0.10990892 | AK16: =+AK15/AJ15-1 -> 0.12377755 | AL16: =+AL15/AK15-1 -> 0.16122346 | AM16: =+AM15/AL15-1 -> 0.15 | ... AP16: =+AP15/AO15-1 -> 0.12
A17: COGS | B17: 66499 | C17: 66424 | D17: 70268 | E17: 85640 | F17: 67791 | G17: 69373 | H17: 75022 | I17: 92553 | J17: 72633 | K17: 73785 | L17: 80977 | M17: 98893 | N17: 76976 | O17: 80809 | P17: 88670 | Q17: 109959 | R17: 87463 | S17: 95778 | T17: =+T15-T19 -> 98876.747 | U17: =+U15-U19 -> 121811.4 | AA17: 71651 | AB17: 88265 | AC17: 111934 | AD17: 139156 | AE17: 165536 | AF17: 233307 | AG17: 272344 | AH17: 288831 | AI17: 304739 | AJ17: 326288 | AK17: 356414 | AL17: =+AL15-AL19 -> 407929.4 | AM17: =+AM15-AM19 -> 459544.95 | AN17: =+AN15-AN19 -> 512967.05 | AO17: =+AO15-AO19 -> 567319.73 | AP17: =+AP15-AP19 -> 635398.1
B18: =+B17/B$15 -> 0.57108138 | C18: =+C17/C$15 -> 0.5478991 | D18: =+D17/D$15 -> 0.55285167 | E18: =+E17/E$15 -> 0.57397925 | F18: =+F17/F$15 -> 0.53228694 | G18: =+G17/G$15 -> 0.51623345 | H18: =+H17/H$15 -> 0.52432504 | I18: =+I17/I$15 -> 0.54455434 | ... U18: =+U17/U$15 -> 0.49 | AE18: =+AE17/AE$15 -> 0.59009989 | AF18: =+AF17/AF$15 -> 0.60432208 | AG18: =+AG17/AG$15 -> 0.57967486 | AH18: =+AH17/AH$15 -> 0.5619466 | AI18: =+AI17/AI$15 -> 0.53017911 | AJ18: =+AJ17/AJ$15 -> 0.51145607 | AK18: =+AK17/AK$15 -> 0.49714335 | AL18: =+AL17/AL$15 -> 0.49 | ... AP18: =+AP17/AP$15 -> 0.46
A19: Gross Margin | B19: =+B15-B17 -> 49945 | C19: =+C15-C17 -> 54810 | D19: =+D15-D17 -> 56833 | E19: =+E15-E17 -> 63564 | F19: =+F15-F17 -> 59567 | G19: =+G15-G17 -> 65010 | H19: =+H15-H17 -> 68061 | I19: =+I15-I17 -> 77408 | ... S19: =+S15-S17 -> 104828 | T19: =+T15*0.51 -> 102912.53 | U19: =+U15*0.51 -> 126783.29 | AA19: =+AA15-AA17 -> 35355 | AB19: =+AB15-AB17 -> 47722 | AC19: =+AC15-AC17 -> 65932 | AD19: =+AD15-AD17 -> 93731 | AE19: =+AE15-AE17 -> 114986 | AF19: =+AF15-AF17 -> 152757 | AG19: =+AG15-AG17 -> 197478 | AH19: =+AH15-AH17 -> 225152 | ... AK19: =+AK15-AK17 -> 360510 | AL19: =+AL15*0.51 -> 424579.57 | AM19: =+AM15*0.52 -> 497840.36 | AN19: =+AN15*0.53 -> 578452.21 | AO19: =+AO15*0.54 -> 665984.03 | AP19: =+AP15*0.54 -> 745902.12
B20: =+B19/B$15 -> 0.42891862 | C20: =+C19/C$15 -> 0.4521009 | D20: =+D19/D$15 -> 0.44714833 | E20: =+E19/E$15 -> 0.42602075 | F20: =+F19/F$15 -> 0.46771306 | G20: =+G19/G$15 -> 0.48376655 | H20: =+H19/H$15 -> 0.47567496 | I20: =+I19/I$15 -> 0.45544566 | ... U20: =+U19/U$15 -> 0.51 | AE20: =+AE19/AE$15 -> 0.40990011 | AF20: =+AF19/AF$15 -> 0.39567792 | AG20: =+AG19/AG$15 -> 0.42032514 | AH20: =+AH19/AH$15 -> 0.4380534 | AI20: =+AI19/AI$15 -> 0.46982089 | AJ20: =+AJ19/AJ$15 -> 0.48854393 | AK20: =+AK19/AK$15 -> 0.50285665 | AL20: =+AL19/AL$15 -> 0.51 | ... AP20: =+AP19/AP$15 -> 0.54
A21: Fulfillment | B21: 20271 | C21: 20342 | D21: 20583 | E21: 23103 | F21: 20905 | G21: 21305 | H21: 22314 | I21: 26095 | J21: 22317 | K21: 23566 | L21: 24660 | M21: 27962 | N21: 24593 | O21: 25976 | P21: 27679 | Q21: 30826 | R21: 27289 | S21: 29633 | T21: =+P21*1.1 -> 30446.9 | U21: =+Q21*1.1 -> 33908.6 | AA21: 13410 | AB21: 17619 | AC21: 25249 | AD21: 34027 | AE21: 40232 | AF21: 58517 | AG21: 75111 | AH21: 84299 | AI21: 90619 | AJ21: 98505 | AK21: 109074 | AL21: =+AL15*0.14 -> 116551.26 | AM21: =+AM15*0.14 -> 134033.94 | AN21: =+AN15*0.13 -> 141884.5 | AO21: =+AO15*0.13 -> 160329.49 | AP21: =+AP15*0.13 -> 179569.03
B22: =+B21/B$15 -> 0.17408368 | C22: =+C21/C$15 -> 0.16779121 | D22: =+D21/D$15 -> 0.16194208 | E22: =+E21/E$15 -> 0.15484169 | F22: =+F21/F$15 -> 0.1641436 | G22: =+G21/G$15 -> 0.1585394 | H22: =+H21/H$15 -> 0.15595144 | I22: =+I21/I$15 -> 0.15353522 | ... U22: =+U21/U$15 -> 0.13640114 | AE22: =+AE21/AE$15 -> 0.14341834 | AF22: =+AF21/AF$15 -> 0.15157331 | AG22: =+AG21/AG$15 -> 0.15987119 | AH22: =+AH21/AH$15 -> 0.16401126 | AI22: =+AI21/AI$15 -> 0.15765721 | AJ22: =+AJ21/AJ$15 -> 0.15440647 | AK22: =+AK21/AK$15 -> 0.15214165 | AL22: =+AL21/AL$15 -> 0.14 | ... AP22: =+AP21/AP$15 -> 0.13
A23: R&D | B23: 14842 | C23: 18072 | D23: 19485 | E23: 20814 | F23: 20450 | G23: 21931 | H23: 21203 | I23: 22038 | J23: 20424 | K23: 22304 | L23: 22245 | M23: 23571 | N23: 22994 | O23: 27166 | P23: 28962 | Q23: 29399 | R23: 29567 | S23: 33158 | T23: =+T15*0.165 -> 33295.231 | U23: =+U15*0.165 -> 41018.124 | AA23: 5254 | AB23: 7233 | AC23: 10069 | AD23: 13814 | AE23: 35931 | AF23: 42740 | AG23: 56052 | AH23: 73213 | AI23: 85622 | AJ23: 88544 | AK23: 108521 | AL23: =+AL15*0.14 -> 116551.26 | AM23: =+AM15*0.14 -> 134033.94 | AN23: =+AN15*0.14 -> 152798.7 | AO23: =+AO15*0.13 -> 160329.49 | AP23: =+AP15*0.13 -> 179569.03
B24: =+B23/B$15 -> 0.12746041 | C24: =+C23/C$15 -> 0.14906709 | D24: =+D23/D$15 -> 0.15330328 | E24: =+E23/E$15 -> 0.13950028 | F24: =+F23/F$15 -> 0.16057099 | G24: =+G23/G$15 -> 0.16319773 | H24: =+H23/H$15 -> 0.14818672 | I24: =+I23/I$15 -> 0.12966504 | ... U24: =+U23/U$15 -> 0.165 | AE24: =+AE23/AE$15 -> 0.12808621 | AF24: =+AF23/AF$15 -> 0.11070703 | AG24: =+AG23/AG$15 -> 0.11930476 | AH24: =+AH23/AH$15 -> 0.14244245 | AI24: =+AI23/AI$15 -> 0.14896353 | AJ24: =+AJ23/AJ$15 -> 0.13879262 | AK24: =+AK23/AK$15 -> 0.1513703 | AL24: =+AL23/AL$15 -> 0.14 | ... AP24: =+AP23/AP$15 -> 0.13
A25: S&M | B25: 8320 | C25: 10086 | D25: 11014 | E25: 12818 | F25: 10172 | G25: 10745 | H25: 10551 | I25: 12902 | J25: 9662 | K25: 10512 | L25: 10609 | M25: 13124 | N25: 9763 | O25: 11416 | P25: 11686 | Q25: 14264 | R25: 10314 | S25: 11698 | T25: =+T15*0.058 -> 11703.778 | U25: =+U15*0.058 -> 14418.492 | AA25: 12540 | AB25: 16085 | AC25: 22620 | AD25: 28837 | AE25: 18878 | AF25: 22008 | AG25: 32551 | AH25: 42238 | AI25: 44370 | AJ25: 43907 | AK25: 47129 | AL25: =+AL15*0.05 -> 41625.448 | AM25: =+AM15*0.05 -> 47869.266 | AN25: =+AN15*0.05 -> 54570.963 | AO25: =+AO15*0.05 -> 61665.188 | AP25: =+AP15*0.04 -> 55252.009
B26: =+B25/B$15 -> 0.071450654 | C26: =+C25/C$15 -> 0.083194483 | D26: =+D25/D$15 -> 0.086655494 | E26: =+E25/E$15 -> 0.085909225 | F26: =+F25/F$15 -> 0.079869345 | G26: =+G25/G$15 -> 0.07995803 | H26: =+H25/H$15 -> 0.073740416 | I26: =+I25/I$15 -> 0.075911533 | ... U26: =+U25/U$15 -> 0.058 | AE26: =+AE25/AE$15 -> 0.06729597 | AF26: =+AF25/AF$15 -> 0.057006092 | AG26: =+AG25/AG$15 -> 0.069283686 | AH26: =+AH25/AH$15 -> 0.082177815 | AI26: =+AI25/AI$15 -> 0.077194081 | AJ26: =+AJ25/AJ$15 -> 0.068824172 | AK26: =+AK25/AK$15 -> 0.065737791 | AL26: =+AL25/AL$15 -> 0.05 | ... AP26: =+AP25/AP$15 -> 0.04
A27: G&A | B27: 2594 | C27: 2903 | D27: 3061 | E27: 3333 | F27: 3043 | G27: 3202 | H27: 2561 | I27: 3010 | J27: 2742 | K27: 3041 | L27: 2713 | M27: 2863 | N27: 2628 | O27: 2965 | P27: 2875 | Q27: 2704 | R27: 2587 | S27: 2788 | T27: =+P27*1 -> 2875 | U27: =+Q27*1 -> 2704 | AA27: 1747 | AB27: 2432 | AC27: 3674 | AD27: 4336 | AE27: 5203 | AF27: 6668 | AG27: 8823 | AH27: 11891 | AI27: 11816 | AJ27: 11359 | AK27: 11172 | AL27: =+AL15*0.015 -> 12487.635 | AM27: =+AM15*0.015 -> 14360.78 | AN27: =+AN15*0.01 -> 10914.193 | AO27: =+AO15*0.01 -> 12333.038 | AP27: =+AP15*0.01 -> 13813.002
B28: =+B27/B$15 -> 0.022276803 | C28: =+C27/C$15 -> 0.023945428 | D28: =+D27/D$15 -> 0.024083209 | E28: =+E27/E$15 -> 0.022338543 | F28: =+F27/F$15 -> 0.023893277 | G28: =+G27/G$15 -> 0.023827419 | H28: =+H27/H$15 -> 0.017898702 | I28: =+I27/I$15 -> 0.017709945 | ... U28: =+U27/U$15 -> 0.010877143 | AE28: =+AE27/AE$15 -> 0.018547565 | AF28: =+AF27/AF$15 -> 0.017271748 | AG28: =+AG27/AG$15 -> 0.018779453 | AH28: =+AH27/AH$15 -> 0.023135006 | AI28: =+AI27/AI$15 -> 0.020557252 | AJ28: =+AJ27/AJ$15 -> 0.017805219 | AK28: =+AK27/AK$15 -> 0.015583242 | AL28: =+AL27/AL$15 -> 0.015 | ... AP28: =+AP27/AP$15 -> 0.01
A29: Other expense | B29: 249 | C29: 90 | D29: 165 | E29: 759 | F29: 223 | G29: 146 | H29: 244 | I29: 154 | J29: 228 | K29: 97 | L29: 262 | M29: 176 | N29: 308 | O29: 199 | P29: 2875 | Q29: 1257 | R29: 447 | S29: 90 | T29: 100 | U29: 100 | AA29: 171 | AB29: 167 | AC29: 214 | AD29: 296 | AE29: 201 | AF29: -75 | AG29: 62 | AH29: 1263 | AI29: 767 | AJ29: 763 | AK29: 4639 | AL29: =+AL15*0.006 -> 4995.0538 | AM29: =+AM15*0.006 -> 5744.3119 | AN29: =+AN15*0.006 -> 6548.5156 | AO29: =+AO15*0.006 -> 7399.8226 | AP29: =+AP15*0.006 -> 8287.8013
B30: =+B29/B$15 -> 0.0021383669 | C30: =+C29/C$15 -> 0.000742366 | D30: =+D29/D$15 -> 0.0012981802 | E30: =+E29/E$15 -> 0.005086995 | F30: =+F29/F$15 -> 0.0017509697 | G30: =+G29/G$15 -> 0.0010864469 | H30: =+H29/H$15 -> 0.0017053039 | I30: =+I29/I$15 -> 0.00090609022 | ... U30: =+U29/U$15 -> 0.00040226121 | AE30: =+AE29/AE$15 -> 0.00071652134 | AF30: =+AF29/AF$15 -> -0.00019426831 | AG30: =+AG29/AG$15 -> 0.00013196487 | AH30: =+AH29/AH$15 -> 0.0024572797 | AI30: =+AI29/AI$15 -> 0.001334412 | AJ30: =+AJ29/AJ$15 -> 0.0011960016 | AK30: =+AK29/AK$15 -> 0.0064706998 | AL30: =+AL29/AL$15 -> 0.006 | ... AP30: =+AP29/AP$15 -> 0.006
A31: Op Ex. | B31: =+B21+B23+B25+B27+B29 -> 46276 | C31: =+C21+C23+C25+C27+C29 -> 51493 | D31: =+D21+D23+D25+D27+D29 -> 54308 | E31: =+E21+E23+E25+E27+E29 -> 60827 | F31: =+F21+F23+F25+F27+F29 -> 54793 | G31: =+G21+G23+G25+G27+G29 -> 57329 | H31: =+H21+H23+H25+H27+H29 -> 56873 | I31: =+I21+I23+I25+I27+I29 -> 64199 | ... U31: =+U21+U23+U25+U27+U29 -> 92149.216 | AA31: =+AA21+AA23+AA25+AA27+AA29 -> 33122 | AB31: =+AB21+AB23+AB25+AB27+AB29 -> 43536 | AC31: =+AC21+AC23+AC25+AC27+AC29 -> 61826 | AD31: =+AD21+AD23+AD25+AD27+AD29 -> 81310 | AE31: =+AE21+AE23+AE25+AE27+AE29 -> 100445 | AF31: =+AF21+AF23+AF25+AF27+AF29 -> 129858 | AG31: =+AG21+AG23+AG25+AG27+AG29 -> 172599 | AH31: =+AH21+AH23+AH25+AH27+AH29 -> 212904 | ... AP31: =+AP21+AP23+AP25+AP27+AP29 -> 436490.87
B32: =+B31/B$15 -> 0.39740991 | C32: =+C31/C$15 -> 0.42474058 | D32: =+D31/D$15 -> 0.42728224 | E32: =+E31/E$15 -> 0.40767674 | F32: =+F31/F$15 -> 0.43022818 | G32: =+G31/G$15 -> 0.42660902 | H32: =+H31/H$15 -> 0.39748258 | I32: =+I31/I$15 -> 0.37772783 | ... U32: =+U31/U$15 -> 0.37068055 | AE32: =+AE31/AE$15 -> 0.35806461 | AF32: =+AF31/AF$15 -> 0.33636392 | AG32: =+AG31/AG$15 -> 0.36737105 | AH32: =+AH31/AH$15 -> 0.41422382 | AI32: =+AI31/AI$15 -> 0.40570648 | AJ32: =+AJ31/AJ$15 -> 0.38102449 | AK32: =+AK31/AK$15 -> 0.39130368 | AL32: =+AL31/AL$15 -> 0.351 | ... AP32: =+AP31/AP$15 -> 0.316
A33: EBIT | B33: =+B19-B31 -> 3669 | C33: =+C19-C31 -> 3317 | D33: =+D19-D31 -> 2525 | E33: =+E19-E31 -> 2737 | F33: =+F19-F31 -> 4774 | G33: =+G19-G31 -> 7681 | H33: =+H19-H31 -> 11188 | I33: =+I19-I31 -> 13209 | ... U33: =+U19-U31 -> 34634.076 | AA33: =+AA19-AA31 -> 2233 | AB33: =+AB19-AB31 -> 4186 | AC33: =+AC19-AC31 -> 4106 | AD33: =+AD19-AD31 -> 12421 | AE33: =+AE19-AE31 -> 14541 | AF33: =+AF19-AF31 -> 22899 | AG33: =+AG19-AG31 -> 24879 | AH33: =+AH19-AH31 -> 12248 | ... AP33: =+AP19-AP31 -> 309411.25
B34: =+B33/B$15 -> 0.031508708 | C34: =+C33/C$15 -> 0.027360311 | D34: =+D33/D$15 -> 0.019866091 | E34: =+E33/E$15 -> 0.018344012 | F34: =+F33/F$15 -> 0.037484885 | G34: =+G33/G$15 -> 0.057157527 | H34: =+H33/H$15 -> 0.078192378 | I34: =+I33/I$15 -> 0.077717829 | ... U34: =+U33/U$15 -> 0.13931945 | AE34: =+AE33/AE$15 -> 0.051835507 | AF34: =+AF33/AF$15 -> 0.059314 | AG34: =+AG33/AG$15 -> 0.052954098 | AH34: =+AH33/AH$15 -> 0.023829582 | AI34: =+AI33/AI$15 -> 0.064114408 | AJ34: =+AJ33/AJ$15 -> 0.10751945 | AK34: =+AK33/AK$15 -> 0.11155297 | AL34: =+AL33/AL$15 -> 0.159 | ... AP34: =+AP33/AP$15 -> 0.224
A35: Interest Income | B35: 108 | C35: 159 | D35: 277 | E35: 445 | F35: 611 | G35: 661 | H35: 776 | I35: 901 | J35: 993 | K35: 1180 | L35: 1256 | M35: 1248 | N35: 1066 | O35: 1085 | P35: 1100 | Q35: 1130 | R35: 1135 | S35: 1295 | T35: =+$AK$77*(0.05/4) -> 1085.125 | U35: =+$AK$77*(0.05/4) -> 1085.125 | AA35: 50 | AB35: 100 | AC35: 202 | AD35: 440 | AE35: 832 | AF35: 555 | AG35: 448 | AH35: 989 | AI35: 2949 | AJ35: 4677 | AK35: 4381 | AL35: =+$AK$77*0.05 -> 4340.5 | AM35: =+$AK$77*0.05 -> 4340.5 | AN35: =+$AK$77*0.05 -> 4340.5 | AO35: =+$AK$77*0.05 -> 4340.5 | AP35: =+$AK$77*0.05 -> 4340.5
B36: =+B35/B$15 -> 0.00092748446 | C36: =+C35/C$15 -> 0.0013115133 | D36: =+D35/D$15 -> 0.0021793692 | E36: =+E35/E$15 -> 0.0029824938 | F36: =+F35/F$15 -> 0.0047975 | G36: =+G35/G$15 -> 0.0049187769 | H36: =+H35/H$15 -> 0.0054234256 | I36: =+I35/I$15 -> 0.0053012162 | ... U36: =+U35/U$15 -> 0.0043650369 | AE36: =+AE35/AE$15 -> 0.0029658993 | AF36: =+AF35/AF$15 -> 0.0014375855 | AG36: =+AG35/AG$15 -> 0.00095355262 | AH36: =+AH35/AH$15 -> 0.0019241882 | AI36: =+AI35/AI$15 -> 0.0051306141 | AJ36: =+AJ35/AJ$15 -> 0.0073311921 | AK36: =+AK35/AK$15 -> 0.006110829 | AL36: =+AL35/AL$15 -> 0.0052137576 | ... AP36: =+AP35/AP$15 -> 0.0031423292
A37: Interest Expense | B37: -472 | C37: -584 | D37: -617 | E37: -694 | F37: -823 | G37: -840 | H37: -806 | I37: -713 | J37: -644 | K37: -589 | L37: -603 | M37: -570 | N37: -541 | O37: -516 | P37: -538 | Q37: -679 | R37: -800 | S37: -1314 | T37: =-($AK$95*(0.05/4)) -> -820.6 | U37: =-($AK$95*(0.05/4)) -> -820.6 | AA37: -459 | AB37: -484 | AC37: -848 | AD37: -1417 | AE37: -1600 | AF37: -1647 | AG37: -1809 | AH37: -2367 | AI37: -3182 | AJ37: -2406 | AK37: -2274 | AL37: =-($AK$95*0.05) -> -3282.4 | AM37: =-($AK$95*0.05) -> -3282.4 | AN37: =-($AK$95*0.05) -> -3282.4 | AO37: =-($AK$95*0.05) -> -3282.4 | AP37: =-($AK$95*0.05) -> -3282.4
B38: =+B37/B$15 -> -0.0040534506 | C38: =+C37/C$15 -> -0.0048171305 | D38: =+D37/D$15 -> -0.0048544071 | E38: =+E37/E$15 -> -0.0046513498 | F38: =+F37/F$15 -> -0.006462099 | G38: =+G37/G$15 -> -0.0062507907 | H38: =+H37/H$15 -> -0.0056330941 | I38: =+I37/I$15 -> -0.00419508 | ... U38: =+U37/U$15 -> -0.0033009555 | AE38: =+AE37/AE$15 -> -0.0057036525 | AF38: =+AF37/AF$15 -> -0.004266132 | AG38: =+AG37/AG$15 -> -0.0038503944 | AH38: =+AH37/AH$15 -> -0.0046052107 | AI38: =+AI37/AI$15 -> -0.005535983 | AJ38: =+AJ37/AJ$15 -> -0.0037714022 | AK38: =+AK37/AK$15 -> -0.0031718843 | AL38: =+AL37/AL$15 -> -0.0039427803 | ... AP38: =+AP37/AP$15 -> -0.0023763118
A39: Other Income | B39: -8570 | C39: -5545 | D39: 759 | E39: -3450 | F39: -443 | G39: 61 | H39: 1031 | I39: 289 | J39: -2673 | K39: -18 | L39: -27 | M39: 468 | N39: 2749 | O39: 1117 | P39: 10186 | Q39: 1177 | R39: 15647 | S39: 53415 | T39: 7000 | U39: 7000 | AA39: -256 | AB39: 90 | AC39: 346 | AD39: -183 | AE39: 203 | AF39: 2371 | AG39: 14633 | AH39: -16806 | AI39: 938 | AJ39: -2250 | AK39: 15229 | AL39: =+SUM(R39:U39) -> 83062 | AM39: =+AL75*$AS$56 -> 6772.2732 | AN39: =+AM75*$AS$56 -> 10726.58 | AO39: =+AN75*$AS$56 -> 15941.948 | AP39: =+AO75*$AS$56 -> 22500.641
B40: =+B39/B$15 -> -0.073597609 | C40: =+C39/C$15 -> -0.045737994 | D40: =+D39/D$15 -> 0.0059716289 | E40: =+E39/E$15 -> -0.023122704 | F40: =+F39/F$15 -> -0.0034783838 | G40: =+G39/G$15 -> 0.00045392646 | H40: =+H39/H$15 -> 0.0072056079 | I40: =+I39/I$15 -> 0.0017003901 | ... U40: =+U39/U$15 -> 0.028158284 | AE40: =+AE39/AE$15 -> 0.00072365091 | AF40: =+AF39/AF$15 -> 0.0061414688 | AG40: =+AG39/AG$15 -> 0.031145838 | AH40: =+AH39/AH$15 -> -0.032697579 | AI40: =+AI39/AI$15 -> 0.0016319145 | AJ40: =+AJ39/AJ$15 -> -0.0035268724 | AK40: =+AK39/AK$15 -> 0.02124214 | AL40: =+AL39/AL$15 -> 0.099773099 | ... AP40: =+AP39/AP$15 -> 0.016289465
A41: EBT | B41: =+B39+B37+B35+B33 -> -5265 | C41: =+C39+C37+C35+C33 -> -2653 | D41: =+D39+D37+D35+D33 -> 2944 | E41: =+E39+E37+E35+E33 -> -962 | F41: =+F39+F37+F35+F33 -> 4119 | G41: =+G39+G37+G35+G33 -> 7563 | H41: =+H39+H37+H35+H33 -> 12189 | I41: =+I39+I37+I35+I33 -> 13686 | ... U41: =+U39+U37+U35+U33 -> 41898.601 | AA41: =+AA39+AA37+AA35+AA33 -> 1568 | AB41: =+AB39+AB37+AB35+AB33 -> 3892 | AC41: =+AC39+AC37+AC35+AC33 -> 3806 | AD41: =+AD39+AD37+AD35+AD33 -> 11261 | AE41: =+AE39+AE37+AE35+AE33 -> 13976 | AF41: =+AF39+AF37+AF35+AF33 -> 24178 | AG41: =+AG39+AG37+AG35+AG33 -> 38151 | AH41: =+AH39+AH37+AH35+AH33 -> -5936 | ... AP41: =+AP39+AP37+AP35+AP33 -> 332969.99
B42: =+B41/B$15 -> -0.045214867 | C42: =+C41/C$15 -> -0.0218833 | D42: =+D41/D$15 -> 0.023162682 | E42: =+E41/E$15 -> -0.0064475483 | F42: =+F41/F$15 -> 0.032341902 | G42: =+G41/G$15 -> 0.05627944 | H42: =+H41/H$15 -> 0.085188317 | I42: =+I41/I$15 -> 0.080524356 | ... U42: =+U41/U$15 -> 0.16854182 | AE42: =+AE41/AE$15 -> 0.049821404 | AF42: =+AF41/AF$15 -> 0.062626922 | AG42: =+AG41/AG$15 -> 0.081203094 | AH42: =+AH41/AH$15 -> -0.01154902 | AI42: =+AI41/AI$15 -> 0.065340954 | AJ42: =+AJ41/AJ$15 -> 0.10755237 | AK42: =+AK41/AK$15 -> 0.13573405 | AL42: =+AL41/AL$15 -> 0.26004408 | ... AP42: =+AP41/AP$15 -> 0.24105548
A43: Taxes | B43: -1422 | C43: -637 | D43: 69 | E43: -1227 | F43: 948 | G43: 804 | H43: 2306 | I43: 3062 | J43: 2467 | K43: 1767 | L43: 2706 | M43: 2325 | N43: 4553 | O43: 2678 | P43: 6910 | Q43: 4946 | R43: 9560 | S43: 18199 | T43: =+T41*0.3 -> 9526.8445 | U43: =+U41*0.3 -> 12569.58 | AA43: 950 | AB43: 1425 | AC43: 769 | AD43: 1197 | AE43: 2374 | AF43: 2863 | AG43: 4791 | AH43: -3217 | AI43: 7120 | AJ43: 9265 | AK43: 19087 | AL43: =+AL41*0.22 -> 47627.586 | AM43: =+AM41*0.22 -> 37318.268 | AN43: =+AN41*0.22 -> 49174.404 | AO43: =+AO41*0.22 -> 61803.952 | AP43: =+AP41*0.22 -> 73253.398
B44: =+B43/B$15 -> -0.012211879 | C44: =+C43/C$15 -> -0.0052543016 | D44: =+D43/D$15 -> 0.00054287535 | E44: =+E43/E$15 -> -0.0082236401 | F44: =+F43/F$15 -> 0.0074435842 | G44: =+G43/G$15 -> 0.0059828996 | H44: =+H43/H$15 -> 0.01611652 | I44: =+I43/I$15 -> 0.018015898 | ... U44: =+U43/U$15 -> 0.050562545 | AE44: =+AE43/AE$15 -> 0.0084627944 | AF44: =+AF43/AF$15 -> 0.0074158689 | AG44: =+AG43/AG$15 -> 0.010197479 | AH44: =+AH43/AH$15 -> -0.0062589619 | AI44: =+AI43/AI$15 -> 0.01238724 | AJ44: =+AJ43/AJ$15 -> 0.014522877 | AK44: =+AK43/AK$15 -> 0.026623464 | AL44: =+AL43/AL$15 -> 0.057209697 | ... AP44: =+AP43/AP$15 -> 0.053032206
A45: Equity-method investment | B45: -1 | C45: -12 | D45: -3 | E45: 13 | F45: 1 | G45: -9 | H45: -4 | I45: 0 | J45: -85 | K45: 7 | L45: -3 | M45: -20 | N45: 1 | O45: -15 | P45: -73 | Q45: -467 | R45: -19 | S45: -11 | T45: -20 | U45: -20 | AA45: -22 | AB45: -96 | AC45: -4 | AD45: 9 | AE45: -14 | AF45: 16 | AG45: 4 | AH45: -3 | AI45: -12 | AJ45: -101 | AK45: -554 | AL45: -500 | AM45: -500 | AN45: -500 | AO45: -500 | AP45: -500
B46: =+B45/B$15 -> -8.587819e-06 | C46: =+C45/C$15 -> -9.8982134e-05 | D46: =+D45/D$15 -> -2.3603276e-05 | E46: =+E45/E$15 -> 8.7129031e-05 | F46: =+F45/F$15 -> 7.8518821e-06 | G46: =+G45/G$15 -> -6.6972757e-05 | H46: =+H45/H$15 -> -2.7955802e-05 | I46: =+I45/I$15 -> 0 | ... U46: =+U45/U$15 -> -8.0452241e-05 | AE46: =+AE45/AE$15 -> -4.9906959e-05 | AF46: =+AF45/AF$15 -> 4.1443906e-05 | AG46: =+AG45/AG$15 -> 8.5138627e-06 | AH46: =+AH45/AH$15 -> -5.8367689e-06 | AI46: =+AI45/AI$15 -> -2.0877372e-05 | AJ46: =+AJ45/AJ$15 -> -0.00015831738 | AK46: =+AK45/AK$15 -> -0.00077274579 | AL46: =+AL45/AL$15 -> -0.00060059413 | ... AP46: =+AP45/AP$15 -> -0.00036197779
A47: Net Income | B47: =+B41-B43+B45 -> -3844 | C47: =+C41-C43+C45 -> -2028 | D47: =+D41-D43+D45 -> 2872 | E47: =+E41-E43+E45 -> 278 | F47: =+F41-F43+F45 -> 3172 | G47: =+G41-G43+G45 -> 6750 | H47: =+H41-H43+H45 -> 9879 | I47: =+I41-I43+I45 -> 10624 | ... U47: =+U41-U43+U45 -> 29309.021 | AA47: =+AA41-AA43+AA45 -> 596 | AB47: =+AB41-AB43+AB45 -> 2371 | AC47: =+AC41-AC43+AC45 -> 3033 | AD47: =+AD41-AD43+AD45 -> 10073 | AE47: =+AE41-AE43+AE45 -> 11588 | AF47: =+AF41-AF43+AF45 -> 21331 | AG47: =+AG41-AG43+AG45 -> 33364 | AH47: =+AH41-AH43+AH45 -> -2722 | ... AP47: =+AP41-AP43+AP45 -> 259216.59 | AQ47: =+AP47*(1+$AS$54) -> 264400.92 | AR47: =+AQ47*(1+$AS$54) -> 269688.94 | AS47: =+AR47*(1+$AS$54) -> 275082.72 | AT47: =+AS47*(1+$AS$54) -> 280584.38 | AU47: =+AT47*(1+$AS$54) -> 286196.06 | AV47: =+AU47*(1+$AS$54) -> 291919.98 | AW47: =+AV47*(1+$AS$54) -> 297758.38 | AX47: =+AW47*(1+$AS$54) -> 303713.55 | ... DL47: =+DK47*(1+$AS$54) -> 1122213.5
B48: =+B47/B$15 -> -0.033011576 | C48: =+C47/C$15 -> -0.016727981 | D48: =+D47/D$15 -> 0.022596203 | E48: =+E47/E$15 -> 0.0018632208 | F48: =+F47/F$15 -> 0.02490617 | G48: =+G47/G$15 -> 0.050229568 | H48: =+H47/H$15 -> 0.069043842 | I48: =+I47/I$15 -> 0.062508458 | ... U48: =+U47/U$15 -> 0.11789882 | AE48: =+AE47/AE$15 -> 0.041308703 | AF48: =+AF47/AF$15 -> 0.055252497 | AG48: =+AG47/AG$15 -> 0.071014129 | AH48: =+AH47/AH$15 -> -0.005295895 | AI48: =+AI47/AI$15 -> 0.052932836 | AJ48: =+AJ47/AJ$15 -> 0.092871172 | AK48: =+AK47/AK$15 -> 0.10833784 | AL48: =+AL47/AL$15 -> 0.20223379 | ... AP48: =+AP47/AP$15 -> 0.1876613
A49: EPS | B49: =+B47/B51 -> -7.5520629 | C49: =+C47/C51 -> -0.19931204 | D49: =+D47/D51 -> 0.27799826 | E49: =+E47/E51 -> 0.026969344 | F49: =+F47/F51 -> 0.30656229 | G49: =+G47/G51 -> 0.64599483 | H49: =+H47/H51 -> 0.95708196 | I49: =+I47/I51 -> 1.0013195 | ... U49: =+U47/U51 -> 2.6953302 | AA49: =+AA47/AA51 -> 1.2494759 | AB49: =+AB47/AB51 -> 4.8987603 | AC49: =+AC47/AC51 -> 6.1521298 | AD49: =+AD47/AD51 -> 20.146 | AE49: =+AE47/AE51 -> 22.992063 | AF49: =+AF47/AF51 -> 41.82549 | AG49: =+AG47/AG51 -> 3.2404817 | AH49: =+AH47/AH51 -> -0.26715085 | ... AP49: =+AP47/AP51 -> 25.175534
F50: =+F49/B49-1 -> -1.0405932 | G50: =+G49/C49-1 -> -4.241123 | H50: =+H49/D49-1 -> 2.4427624 | I50: =+I49/E49-1 -> 36.128063 | J50: =+J49/F49-1 -> 2.1889139 | K50: =+K49/G49-1 -> 0.94945648 | L50: =+L49/H49-1 -> 0.49188144 | M50: =+M49/I49-1 -> 0.8547618 | ... U50: =+U49/Q49-1 -> 0.38162382 | AF50: =+AF49/AE49-1 -> 0.81912729 | AG50: =+AG49/AF49-1 -> -0.92252376 | AH50: =+AH49/AG49-1 -> -1.0824417 | AI50: =+AI49/AH49-1 -> -11.854648 | AJ50: =+AJ49/AI49-1 -> 0.90575073 | AK50: =+AK49/AJ49-1 -> 0.29809587 | AL50: =+AL49/AK49-1 -> 1.1895463 | AM50: =+AM49/AL49-1 -> -0.20919161 | ... AP50: =+AP49/AO49-1 -> 0.1976545
A51: Shares | B51: 509 | C51: 10175 | D51: 10331 | E51: 10308 | F51: 10347 | G51: 10449 | H51: 10322 | I51: 10610 | J51: 10670 | K51: 10708 | L51: 10735 | M51: 10771 | N51: 10793 | O51: 10806 | P51: 10845 | Q51: 10863 | R51: 10874 | S51: 10903 | T51: 10874 | U51: 10874 | AA51: 477 | AB51: 484 | AC51: 493 | AD51: 500 | AE51: 504 | AF51: 510 | AG51: 10296 | AH51: 10189 | AI51: 10492 | AJ51: 10721 | AK51: 10827 | AL51: =+AK51*0.99 -> 10718.73 | AM51: =+AL51*0.99 -> 10611.543 | AN51: =+AM51*0.99 -> 10505.427 | AO51: =+AN51*0.99 -> 10400.373 | AP51: =+AO51*0.99 -> 10296.369
C52: =+C51/B51-1 -> 18.990177 | D52: =+D51/C51-1 -> 0.015331695 | E52: =+E51/D51-1 -> -0.0022263092 | F52: =+F51/E51-1 -> 0.0037834692 | G52: =+G51/F51-1 -> 0.0098579298 | H52: =+H51/G51-1 -> -0.012154273 | I52: =+I51/H51-1 -> 0.027901569 | J52: =+J51/I51-1 -> 0.0056550424 | ... U52: =+U51/T51-1 -> 0 | AF52: =+AF51/AE51-1 -> 0.011904762 | AG52: =+AG51/AF51-1 -> 19.188235 | AH52: =+AH51/AG51-1 -> -0.010392385 | AI52: =+AI51/AH51-1 -> 0.029737953 | AJ52: =+AJ51/AI51-1 -> 0.021826153 | AK52: =+AK51/AJ51-1 -> 0.0098871374 | AL52: =+AL51/AK51-1 -> -0.01 | AM52: =+AM51/AL51-1 -> -0.01 | ... AP52: =+AP51/AO51-1 -> -0.01
AU53: Gordon Growth Model
A54: Gross Margin | B54: =+B19/B15 -> 0.42891862 | C54: =+C19/C15 -> 0.4521009 | D54: =+D19/D15 -> 0.44714833 | E54: =+E19/E15 -> 0.42602075 | F54: =+F19/F15 -> 0.46771306 | G54: =+G19/G15 -> 0.48376655 | H54: =+H19/H15 -> 0.47567496 | I54: =+I19/I15 -> 0.45544566 | ... U54: =+U19/U15 -> 0.51 | AA54: =+AA19/AA15 -> 0.33040203 | AB54: =+AB19/AB15 -> 0.3509306 | AC54: =+AC19/AC15 -> 0.37068355 | AD54: =+AD19/AD15 -> 0.40247416 | AE54: =+AE19/AE15 -> 0.40990011 | AF54: =+AF19/AF15 -> 0.39567792 | AG54: =+AG19/AG15 -> 0.42032514 | AH54: =+AH19/AH15 -> 0.4380534 | ... AP54: =+AP19/AP15 -> 0.54 | AR54: Terminal | AS54: 0.02 | AU54: Payout rate
A55: Op Margin | B55: =+B33/B15 -> 0.031508708 | C55: =+C33/C15 -> 0.027360311 | D55: =+D33/D15 -> 0.019866091 | E55: =+E33/E15 -> 0.018344012 | F55: =+F33/F15 -> 0.037484885 | G55: =+G33/G15 -> 0.057157527 | H55: =+H33/H15 -> 0.078192378 | I55: =+I33/I15 -> 0.077717829 | ... U55: =+U33/U15 -> 0.13931945 | AA55: =+AA33/AA15 -> 0.020867989 | AB55: =+AB33/AB15 -> 0.030782354 | AC55: =+AC33/AC15 -> 0.023084794 | AD55: =+AD33/AD15 -> 0.053334879 | AE55: =+AE33/AE15 -> 0.051835507 | AF55: =+AF33/AF15 -> 0.059314 | AG55: =+AG33/AG15 -> 0.052954098 | AH55: =+AH33/AH15 -> 0.023829582 | ... AP55: =+AP33/AP15 -> 0.224 | AR55: Discount | AS55: =+Main!$E$8 -> 0.11961632 | AU55: Sustainable growth
A56: NI Margin | B56: =+B47/B15 -> -0.033011576 | C56: =+C47/C15 -> -0.016727981 | D56: =+D47/D15 -> 0.022596203 | E56: =+E47/E15 -> 0.0018632208 | F56: =+F47/F15 -> 0.02490617 | G56: =+G47/G15 -> 0.050229568 | H56: =+H47/H15 -> 0.069043842 | I56: =+I47/I15 -> 0.062508458 | ... U56: =+U47/U15 -> 0.11789882 | AA56: =+AA47/AA15 -> 0.0055697811 | AB56: =+AB47/AB15 -> 0.01743549 | AC56: =+AC47/AC15 -> 0.017052163 | AD56: =+AD47/AD15 -> 0.043252736 | AE56: =+AE47/AE15 -> 0.041308703 | AF56: =+AF47/AF15 -> 0.055252497 | AG56: =+AG47/AG15 -> 0.071014129 | AH56: =+AH47/AH15 -> -0.005295895 | ... AP56: =+AP47/AP15 -> 0.1876613 | AR56: ROIC | AS56: 0.03 | AU56: Equity Value
A57: Tax Rate | B57: =+B43/B41 -> 0.27008547 | C57: =+C43/C41 -> 0.24010554 | D57: =+D43/D41 -> 0.0234375 | E57: =+E43/E41 -> 1.2754678 | F57: =+F43/F41 -> 0.23015295 | G57: =+G43/G41 -> 0.10630702 | H57: =+H43/H41 -> 0.18918697 | I57: =+I43/I41 -> 0.22373228 | ... U57: =+U43/U41 -> 0.3 | AA57: =+AA43/AA41 -> 0.60586735 | AB57: =+AB43/AB41 -> 0.36613566 | AC57: =+AC43/AC41 -> 0.2020494 | AD57: =+AD43/AD41 -> 0.10629607 | AE57: =+AE43/AE41 -> 0.16986262 | AF57: =+AF43/AF41 -> 0.11841343 | AG57: =+AG43/AG41 -> 0.12557993 | AH57: =+AH43/AH41 -> 0.54194744 | ... AP57: =+AP43/AP41 -> 0.22 | AR57: NPV | AS57: =+NPV(AS55,AL47:DL47)+Main!E4-Main!E5 -> 2167069.3 | AU57: Just. P/E
AR58: Share | AS58: =+AS57/Main!E2 -> 200.90917
A59: ROA | C59: =+C47/AVERAGE(B87:C87) -> -0.0048838343 | D59: =+D47/AVERAGE(C87:D87) -> 0.0067768055 | E59: =+E47/AVERAGE(D87:E87) -> 0.00062433748 | F59: =+F47/AVERAGE(E87:F87) -> 0.0068431902 | G59: =+G47/AVERAGE(F87:G87) -> 0.014331438 | H59: =+H47/AVERAGE(G87:H87) -> 0.020485438 | I59: =+I47/AVERAGE(H87:I87) -> 0.020939416 | J59: =+J47/AVERAGE(I87:J87) -> 0.01970301 | ... S59: =+S47/AVERAGE(R87:S87) -> 0.062263488 | AB59: =+AB47/AVERAGE(AA87:AB87) -> 0.032008316 | AC59: =+AC47/AVERAGE(AB87:AC87) -> 0.028251798 | AD59: =+AD47/AVERAGE(AC87:AD87) -> 0.0685336 | AE59: =+AE47/AVERAGE(AD87:AE87) -> 0.059747974 | AF59: =+AF47/AVERAGE(AE87:AF87) -> 0.078072187 | AG59: =+AG47/AVERAGE(AF87:AG87) -> 0.089960957 | AH59: =+AH47/AVERAGE(AG87:AH87) -> -0.0061637818 | AI59: =+AI47/AVERAGE(AH87:AI87) -> 0.061431821 | ... AK59: =+AK47/AVERAGE(AJ87:AK87) -> 0.1076555 | AR59: Diff | AS59: =+AS58/Main!E1-1 -> -0.22428891 | AU59: Dividend Yield
A60: ROE | C60: =+C47/AVERAGE(B104:C104) -> -0.01528242 | D60: =+D47/AVERAGE(C104:D104) -> 0.021361816 | E60: =+E47/AVERAGE(D104:E104) -> 0.0019609779 | F60: =+F47/AVERAGE(E104:F104) -> 0.021106634 | G60: =+G47/AVERAGE(F104:G104) -> 0.041779109 | H60: =+H47/AVERAGE(G104:H104) -> 0.05620429 | I60: =+I47/AVERAGE(H104:I104) -> 0.055216573 | J60: =+J47/AVERAGE(I104:J104) -> 0.049845175 | ... S60: =+S47/AVERAGE(R104:S104) -> 0.12610942 | AB60: =+AB47/AVERAGE(AA104:AB104) -> 0.1451529 | AC60: =+AC47/AVERAGE(AB104:AC104) -> 0.12908031 | AD60: =+AD47/AVERAGE(AC104:AD104) -> 0.28271913 | AE60: =+AE47/AVERAGE(AD104:AE104) -> 0.21945099 | AF60: =+AF47/AVERAGE(AE104:AF104) -> 0.27441723 | AG60: =+AG47/AVERAGE(AF104:AG104) -> 0.2880565 | AH60: =+AH47/AVERAGE(AG104:AH104) -> -0.019149595 | AI60: =+AI47/AVERAGE(AH104:AI104) -> 0.17489753 | ... AK60: =+AK47/AVERAGE(AJ104:AK104) -> 0.22285825 | AU60: Debt-to-EBITDA
A61: A. Turnover | C61: =+C15/AVERAGE(B87:C87) -> 0.291956 | D61: =+D15/AVERAGE(C87:D87) -> 0.29990904 | E61: =+E15/AVERAGE(D87:E87) -> 0.33508507 | F61: =+F15/AVERAGE(E87:F87) -> 0.27475883 | G61: =+G15/AVERAGE(F87:G87) -> 0.28531877 | H61: =+H15/AVERAGE(G87:H87) -> 0.29670188 | I61: =+I15/AVERAGE(H87:I87) -> 0.33498532 | J61: =+J15/AVERAGE(I87:J87) -> 0.27070247 | ... S61: =+S15/AVERAGE(R87:S87) -> 0.19937793 | AB61: =+AB15/AVERAGE(AA87:AB87) -> 1.8358139 | AC61: =+AC15/AVERAGE(AB87:AC87) -> 1.6567868 | AD61: =+AD15/AVERAGE(AC87:AD87) -> 1.5844917 | AE61: =+AE15/AVERAGE(AD87:AE87) -> 1.4463774 | AF61: =+AF15/AVERAGE(AE87:AF87) -> 1.4130074 | AG61: =+AG15/AVERAGE(AF87:AG87) -> 1.2668036 | AH61: =+AH15/AVERAGE(AG87:AH87) -> 1.1638792 | AI61: =+AI15/AVERAGE(AH87:AI87) -> 1.1605617 | ... AK61: =+AK15/AVERAGE(AJ87:AK87) -> 0.99370173
A62: Financial Leverage | C62: =+AVERAGE(B87:C87)/AVERAGE(B104:C104) -> 3.1291847 | D62: =+AVERAGE(C87:D87)/AVERAGE(C104:D104) -> 3.1521955 | E62: =+AVERAGE(D87:E87)/AVERAGE(D104:E104) -> 3.1408941 | F62: =+AVERAGE(E87:F87)/AVERAGE(E104:F104) -> 3.0843267 | G62: =+AVERAGE(F87:G87)/AVERAGE(F104:G104) -> 2.915207 | H62: =+AVERAGE(G87:H87)/AVERAGE(G104:H104) -> 2.7436216 | I62: =+AVERAGE(H87:I87)/AVERAGE(H104:I104) -> 2.6369682 | J62: =+AVERAGE(I87:J87)/AVERAGE(I104:J104) -> 2.5298254 | ... S62: =+AVERAGE(R87:S87)/AVERAGE(R104:S104) -> 2.0254153 | AB62: =+AVERAGE(AA87:AB87)/AVERAGE(AA104:AB104) -> 4.5348496 | AC62: =+AVERAGE(AB87:AC87)/AVERAGE(AB104:AC104) -> 4.5689237 | AD62: =+AVERAGE(AC87:AD87)/AVERAGE(AC104:AD104) -> 4.1252631 | AE62: =+AVERAGE(AD87:AE87)/AVERAGE(AD104:AE104) -> 3.6729445 | AF62: =+AVERAGE(AE87:AF87)/AVERAGE(AE104:AF104) -> 3.5149166 | AG62: =+AVERAGE(AF87:AG87)/AVERAGE(AF104:AG104) -> 3.2020168 | AH62: =+AVERAGE(AG87:AH87)/AVERAGE(AG104:AH104) -> 3.1067931 | AI62: =+AVERAGE(AH87:AI87)/AVERAGE(AH104:AI104) -> 2.8470186 | ... AK62: =+AVERAGE(AJ87:AK87)/AVERAGE(AJ104:AK104) -> 2.0701055
A63: Financial Leverage % | C63: =+C60-C59 -> -0.010398585 | D63: =+D60-D59 -> 0.01458501 | E63: =+E60-E59 -> 0.0013366405 | F63: =+F60-F59 -> 0.014263444 | G63: =+G60-G59 -> 0.027447671 | H63: =+H60-H59 -> 0.035718852 | I63: =+I60-I59 -> 0.034277157 | J63: =+J60-J59 -> 0.030142165 | ... S63: =+S60-S59 -> 0.063845935 | AB63: =+AB60-AB59 -> 0.11314458 | AC63: =+AC60-AC59 -> 0.10082851 | AD63: =+AD60-AD59 -> 0.21418553 | AE63: =+AE60-AE59 -> 0.15970302 | AF63: =+AF60-AF59 -> 0.19634504 | AG63: =+AG60-AG59 -> 0.19809554 | AH63: =+AH60-AH59 -> -0.012985813 | AI63: =+AI60-AI59 -> 0.11346571 | ... AK63: =+AK60-AK59 -> 0.11520275
AU64: EV | AV64: =+AS67 -> 2286954.8
A65: NWC | B65: =+SUM(B79,B80)-SUM(B89,B90,B92) -> -72017 | C65: =+SUM(C79,C80)-SUM(C89,C90,C92) -> -67334 | D65: =+SUM(D79,D80)-SUM(D89,D90,D92) -> -68055 | E65: =+SUM(E79,E80)-SUM(E89,E90,E92) -> -78628 | F65: =+SUM(F79,F80)-SUM(F89,F90,F92) -> -75754 | G65: =+SUM(G79,G80)-SUM(G89,G90,G92) -> -71726 | H65: =+SUM(H79,H80)-SUM(H89,H90,H92) -> -66388 | I65: =+SUM(I79,I80)-SUM(I89,I90,I92) -> -79346 | ... S65: =+SUM(S79,S80)-SUM(S89,S90,S92) -> -114998 | AA65: =+SUM(AA79,AA80)-SUM(AA89,AA90,AA92) -> -17990 | AB65: =+SUM(AB79,AB80)-SUM(AB89,AB90,AB92) -> -24016 | AC65: =+SUM(AC79,AC80)-SUM(AC89,AC90,AC92) -> -28672 | AD65: =+SUM(AD79,AD80)-SUM(AD89,AD90,AD92) -> -34540 | AE65: =+SUM(AE79,AE80)-SUM(AE89,AE90,AE92) -> -46499 | AF65: =+SUM(AF79,AF80)-SUM(AF89,AF90,AF92) -> -78048 | AG65: =+SUM(AG79,AG80)-SUM(AG89,AG90,AG92) -> -76735 | AH65: =+SUM(AH79,AH80)-SUM(AH89,AH90,AH92) -> -78628 | ... AP65: =+SUM(AP79,AP80)-SUM(AP89,AP90,AP92) -> -205866.57 | AR65: Terminal | AS65: 0.02 | AU65: Debt (-) | AV65: =+Main!E5 -> 128894
A66: NOPAT | B66: =+B33*(1-B57) -> 2678.0564 | C66: =+C33*(1-C57) -> 2520.5699 | D66: =+D33*(1-D57) -> 2465.8203 | E66: =+E33*(1-E57) -> -753.9553 | F66: =+F33*(1-F57) -> 3675.2498 | G66: =+G33*(1-G57) -> 6864.4558 | H66: =+H33*(1-H57) -> 9071.3762 | I66: =+I33*(1-I57) -> 10253.72 | ... S66: =+S33*(1-S57) -> 21280.178 | AA66: =+AA33*(1-AA57) -> 880.09821 | AB66: =+AB33*(1-AB57) -> 2653.3561 | AC66: =+AC33*(1-AC57) -> 3276.3852 | AD66: =+AD33*(1-AD57) -> 11100.697 | AE66: =+AE33*(1-AE57) -> 12071.028 | AF66: =+AF33*(1-AF57) -> 20187.451 | AG66: =+AG33*(1-AG57) -> 21754.697 | AH66: =+AH33*(1-AH57) -> 5610.2278 | ... AP66: =+AP33*(1-AP57) -> 241340.77 | AR66: Discount | AS66: =+Main!$E$8 -> 0.11961632 | AU66: Cash (+) | AV66: =+Main!E4 -> 122988
A67: UFCF | AB67: =+AB66+AB110-AB123-(AB65-AA65) -> 10058.356 | AC67: =+AC66+AC110-AC123-(AC65-AB65) -> 17513.385 | AD67: =+AD66+AD110-AD123-(AD65-AC65) -> 30205.697 | AE67: =+AE66+AE110-AE123-(AE65-AD65) -> 28958.028 | AF67: =+AF66+AF110-AF123-(AF65-AE65) -> 36847.451 | AG67: =+AG66+AG110-AG123-(AG65-AF65) -> -6178.3031 | AH67: =+AH66+AH110-AH123-(AH65-AG65) -> -14220.772 | AI67: =+AI66+AI110-AI123-(AI65-AH65) -> 26517.653 | ... AP67: =+AP66+AP110-AP123-(AP65-AO65) -> 305478.91 | AR67: EV | AS67: =+NPV(AS66,AL67:AP67,AP67+AS68) -> 2286954.8 | AU67: Equity Value | AV67: =+AV64-AV65+AV66 -> 2281048.8
AR68: TV | AS68: =+AP67*(1+AS65)/(AS66-AS65) -> 3127885.9 | AU68: Share | AV68: =+Main!E2 -> 10786.314
AR69: Diff | AS69: =+AS67/Main!E6-1 -> -0.18310243 | AU69: Price | AV69: =+AV67/AV68 -> 211.47621
AV70: =+AV69/Main!E1-1 -> -0.18348952
A72: Intventory to Sales | AA72: =+AA79/AA15 -> 0.095723604 | AB72: =+AB79/AB15 -> 0.084280115 | AC72: =+AC79/AC15 -> 0.090219604 | AD72: =+AD79/AD15 -> 0.073743919 | AE72: =+AE79/AE15 -> 0.073067353 | AF72: =+AF79/AF15 -> 0.061634858 | AG72: =+AG79/AG15 -> 0.06947312 | AH72: =+AH79/AH15 -> 0.066938012 | ... AK72: =+AK79/AK15 -> 0.053457549
A74: EBITDA | B74: =+B33+B110 -> 12647 | C74: =+C33+C110 -> 12911 | D74: =+D33+D110 -> 12729 | E74: =+E33+E110 -> 15422 | F74: =+F33+F110 -> 15897 | G74: =+G33+G110 -> 19270 | H74: =+H33+H110 -> 23309 | I74: =+I33+I110 -> 27029 | ... S74: =+S33+S110 -> 47449 | AA74: =+AA33+AA110 -> 8514 | AB74: =+AB33+AB110 -> 12302 | AC74: =+AC33+AC110 -> 15584 | AD74: =+AD33+AD110 -> 27762 | AE74: =+AE33+AE110 -> 36330 | AF74: =+AF33+AF110 -> 48150 | AG74: =+AG33+AG110 -> 59312 | AH74: =+AH33+AH110 -> 54169 | ... AP74: =+AP33+AP110 -> 488980.28
A75: Net Cash | B75: =+B77+B78-B95 -> 18829 | C75: =+C77+C78-C95 -> 2657 | D75: =+D77+D78-D95 -> -257 | E75: =+E77+E78-E95 -> 2876 | F75: =+F77+F78-F95 -> -2679 | G75: =+G77+G78-G95 -> 878 | H75: =+H77+H78-H95 -> 3071 | I75: =+I77+I78-I95 -> 28466 | ... S75: =+S77+S78-S95 -> -5906 | AA75: =+AA77+AA78-AA95 -> 11581 | AB75: =+AB77+AB78-AB95 -> 18287 | AC75: =+AC77+AC78-AC95 -> 6243 | AD75: =+AD77+AD78-AD95 -> 17755 | AE75: =+AE77+AE78-AE95 -> 31607 | AF75: =+AF77+AF78-AF95 -> 52580 | AG75: =+AG77+AG78-AG95 -> 47305 | AH75: =+AH77+AH78-AH95 -> 2876 | ... AK75: =+AK77+AK78-AK95 -> 57381 | AL75: =+AK75+AL47 -> 225742.44 | AM75: =+AL75+AM47 -> 357552.66 | AN75: =+AM75+AN47 -> 531398.28 | AO75: =+AN75+AO47 -> 750021.38 | AP75: =+AO75+AP47 -> 1009238
A77: Cash | B77: 36393 | C77: 37478 | D77: 34947 | E77: 53888 | F77: 49343 | G77: 49529 | H77: 49605 | I77: 73387 | J77: 72852 | K77: 71178 | L77: 75091 | M77: 78779 | N77: 66207 | O77: 57741 | P77: 66922 | Q77: 86810 | R77: 101816 | S77: 78213 | AA77: 15890 | AB77: 19334 | AC77: 20522 | AD77: 31750 | AE77: 36092 | AF77: 42122 | AG77: 36220 | AH77: 53888 | AI77: 73387 | AJ77: 78779 | AK77: 86810
A78: Mrk. Securities | B78: 29992 | C78: 23232 | D78: 23715 | E78: 16138 | F78: 15062 | G78: 14441 | H78: 14564 | I78: 13393 | J78: 12222 | K78: 17914 | L78: 12960 | M78: 22423 | N78: 28358 | O78: 35439 | P78: 27275 | Q78: 36219 | R78: 41273 | S78: 44775 | AA78: 3918 | AB78: 6647 | AC78: 10464 | AD78: 9500 | AE78: 18929 | AF78: 42274 | AG78: 59829 | AH78: 16138 | AI78: 13393 | AJ78: 22423 | AK78: 36219
A79: Inventories | B79: 34987 | C79: 38153 | D79: 36154 | E79: 34405 | F79: 34170 | G79: 36587 | H79: 35406 | I79: 33318 | J79: 31147 | K79: 34109 | L79: 36103 | M79: 34214 | N79: 35864 | O79: 40825 | P79: 41494 | Q79: 38325 | R79: 36534 | S79: 38184 | AA79: 10243 | AB79: 11461 | AC79: 16047 | AD79: 17174 | AE79: 20497 | AF79: 23795 | AG79: 32640 | AH79: 34405 | AI79: 33318 | AJ79: 34214 | AK79: 38325 | AL79: =+(AL130/365)*AL17 -> 42070.631 | AM79: =+(AM130/365)*AM17 -> 48023.368 | AN79: =+(AN130/365)*AN17 -> 54308.779 | AO79: =+(AO130/365)*AO17 -> 60840.349 | AP79: =+(AP130/365)*AP17 -> 67270.782
A80: A/R | B80: 32504 | C80: 34804 | D80: 36154 | E80: 42360 | F80: 37646 | G80: 39925 | H80: 43420 | I80: 52253 | J80: 47768 | K80: 50106 | L80: 51638 | M80: 55451 | N80: 54216 | O80: 57415 | P80: 61175 | Q80: 67729 | R80: 75532 | S80: 88092 | AA80: 5654 | AB80: 8339 | AC80: 13164 | AD80: 16677 | AE80: 20816 | AF80: 24542 | AG80: 32891 | AH80: 42360 | AI80: 52253 | AJ80: 55451 | AK80: 67729 | AL80: =+(AL129/365)*AL15 -> 60478.942 | AM80: =+(AM129/365)*AM15 -> 70862.27 | AN80: =+(AN129/365)*AN15 -> 82278.083 | AO80: =+(AO129/365)*AO15 -> 94663.691 | AP80: =+(AP129/365)*AP15 -> 107915.53
A81: A/R + V/R | AG81: =+20200+5300 -> 25500 | AH81: =+26600+6900 -> 33500 | AI81: =+34100+8500 -> 42600 | AJ81: =+34300+11600 -> 45900 | AK81: =+40400+15900 -> 56300
A82: Other | AG82: =+1000 -> 1000 | AH82: =+1300+3100+4500 -> 8900 | AI82: =+1000+3300+5400 -> 9700 | AJ82: =+3400+6300 -> 9700 | AK82: =+4500+6900 -> 11400
A83: PP&E | B83: 168468 | C83: 173706 | D83: 177195 | E83: 186715 | F83: 190754 | G83: 193784 | H83: 196468 | I83: 204177 | J83: 209950 | K83: 220717 | L83: 237917 | M83: 252665 | N83: 272781 | O83: 297616 | P83: 324435 | Q83: 357025 | R83: 397458 | S83: 446046 | AA83: 21838 | AB83: 29114 | AC83: 48866 | AD83: 61797 | AE83: 72705 | AF83: 113114 | AG83: 160281 | AH83: 186715 | AI83: 204177 | AJ83: 252665 | AK83: 357025
A84: Op Lease | B84: 56161 | C84: 58430 | D84: 62033 | E84: 66123 | F84: 68262 | G84: 70332 | H84: 70758 | I84: 72513 | J84: 73313 | K84: 74575 | L84: 76527 | M84: 76141 | N84: 78495 | O84: 82125 | P84: 83456 | Q84: 86054 | R84: 88741 | S84: 92743 | AC84: 0 | AD84: 0 | AE84: 25141 | AF84: 37553 | AG84: 56082 | AH84: 66123 | AI84: 72513 | AJ84: 76141 | AK84: 86054
A85: Good will | B85: 20229 | C85: 20195 | D85: 20168 | E85: 20288 | F85: 22749 | G85: 22785 | H85: 22749 | I85: 22789 | J85: 22770 | K85: 22879 | L85: 23081 | M85: 23074 | N85: 23089 | O85: 23155 | P85: 23260 | Q85: 23273 | R85: 23449 | S85: 23504 | AA85: 3759 | AB85: 3784 | AC85: 13350 | AD85: 14548 | AE85: 14754 | AF85: 15017 | AG85: 15371 | AH85: 20288 | AI85: 22789 | AJ85: 23074 | AK85: 23273
A86: Other Assets | B86: 32033 | C86: 33730 | D86: 37503 | E86: 42758 | F86: 46392 | G86: 50224 | H86: 53913 | I86: 56024 | J86: 60947 | K86: 63340 | L86: 71309 | M86: 82147 | N86: 84246 | O86: 87854 | P86: 99904 | Q86: 122607 | R86: 151827 | S86: 284132 | AA86: 3445 | AB86: 4723 | AC86: 8897 | AD86: 11202 | AE86: 16314 | AF86: 22778 | AG86: 27235 | AH86: 42758 | AI86: 56024 | AJ86: 82147 | AK86: 122607
A87: A | B87: =+SUM(B77:B86) -> 410767 | C87: =+SUM(C77:C86) -> 419728 | D87: =+SUM(D77:D86) -> 427869 | E87: =+SUM(E77:E86) -> 462675 | F87: =+SUM(F77:F86) -> 464378 | G87: =+SUM(G77:G86) -> 477607 | H87: =+SUM(H77:H86) -> 486883 | I87: =+SUM(I77:I86) -> 527854 | ... U87: =+SUM(U77:U86) -> 0 | AA87: =+SUM(AA77:AA86)-AA81-AA82 -> 64747 | AB87: =+SUM(AB77:AB86)-AB81-AB82 -> 83402 | AC87: =+SUM(AC77:AC86)-AC81-AC82 -> 131310 | AD87: =+SUM(AD77:AD86)-AD81-AD82 -> 162648 | AE87: =+SUM(AE77:AE86)-AE81-AE82 -> 225248 | AF87: =+SUM(AF77:AF86)-AF81-AF82 -> 321195 | AG87: =+SUM(AG77:AG86)-AG81-AG82 -> 420549 | AH87: =+SUM(AH77:AH86)-AH81-AH82 -> 462675 | ... AK87: =+SUM(AK77:AK86)-AK81-AK82 -> 818042
A89: A/P | B89: 68547 | C89: 71219 | D89: 67760 | E89: 79600 | F89: 66907 | G89: 69481 | H89: 72004 | I89: 84981 | J89: 73068 | K89: 81817 | L89: 84570 | M89: 94363 | N89: 89241 | O89: 98285 | P89: 106032 | Q89: 121909 | R89: 124749 | S89: 147440 | AA89: 20397 | AB89: 25309 | AC89: 34616 | AD89: 38192 | AE89: 47183 | AF89: 72539 | AG89: 78664 | AH89: 79600 | AI89: 84981 | AJ89: 94363 | AK89: 121909 | AL89: =+(AL131/365)*AL17 -> 124883.38 | AM89: =+(AM131/365)*AM17 -> 141943.98 | AN89: =+(AN131/365)*AN17 -> 159850.36 | AO89: =+(AO131/365)*AO17 -> 178342 | AP89: =+(AP131/365)*AP17 -> 201483.85
A90: Accr. Expense | B90: 58141 | C90: 56254 | D90: 59974 | E90: 62566 | F90: 66382 | G90: 64235 | H90: 58812 | I90: 64709 | J90: 63970 | K90: 60351 | L90: 60602 | M90: 66965 | N90: 66331 | O90: 66974 | P90: 68051 | Q90: 75520 | R90: 71120 | S90: 73406 | AA90: 10372 | AB90: 13739 | AC90: 18170 | AD90: 23663 | AE90: 32439 | AF90: 44138 | AG90: 51775 | AH90: 62566 | AI90: 64709 | AJ90: 66965 | AK90: 75520 | AL90: =+AL15*0.1 -> 83250.897 | AM90: =+AM15*0.1 -> 95738.532 | AN90: =+AN15*0.1 -> 109141.93 | AO90: =+AO15*0.1 -> 123330.38 | AP90: =+AP15*0.1 -> 138130.02
B91: =+B90/B$15 -> 0.49930439 | C91: =+C90/C$15 -> 0.46401175 | D91: =+D90/D$15 -> 0.47186096 | E91: =+E90/E$15 -> 0.41933192 | F91: =+F90/F$15 -> 0.52122364 | G91: =+G90/G$15 -> 0.47799945 | H91: =+H90/H$15 -> 0.41103416 | I91: =+I90/I$15 -> 0.38072852 | ... U91: =+U90/U$15 -> 0 | AA91: =+AA90/AA$15 -> 0.096929144 | AB91: =+AB90/AB$15 -> 0.10103172 | AC91: =+AC90/AC$15 -> 0.10215556 | AD91: =+AD90/AD$15 -> 0.10160722 | AE91: =+AE90/AE$15 -> 0.11563799 | AF91: =+AF90/AF$15 -> 0.11432819 | AG91: =+AG90/AG$15 -> 0.11020131 | AH91: =+AH90/AH$15 -> 0.12172776 | ... AP91: =+AP90/AP$15 -> 0.1
A92: Unr. Revenue | B92: 12820 | C92: 12818 | D92: 12629 | E92: 13227 | F92: 14281 | G92: 14522 | H92: 14398 | I92: 15227 | J92: 15927 | K92: 16004 | L92: 16305 | M92: 18103 | N92: 20599 | O92: 21662 | P92: 21113 | Q92: 20576 | R92: 20887 | S92: 20428 | AA92: 3118 | AB92: 4768 | AC92: 5097 | AD92: 6536 | AE92: 8190 | AF92: 9708 | AG92: 11827 | AH92: 13227 | AI92: 15227 | AJ92: 18103 | AK92: 20576 | AL92: =+AL15*0.03 -> 24975.269 | AM92: =+AM15*0.03 -> 28721.559 | AN92: =+AN15*0.03 -> 32742.578 | AO92: =+AO15*0.03 -> 36999.113 | AP92: =+AP15*0.03 -> 41439.006
C93: =+C92/B92-1 -> -0.00015600624 | D93: =+D92/C92-1 -> -0.01474489 | E93: =+E92/D92-1 -> 0.047351334 | F93: =+F92/E92-1 -> 0.079685492 | G93: =+G92/F92-1 -> 0.016875569 | H93: =+H92/G92-1 -> -0.0085387688 | I93: =+I92/H92-1 -> 0.057577441 | J93: =+J92/I92-1 -> 0.045970973 | ... S93: =+S92/R92-1 -> -0.021975391 | AA93: =+AA92/AA$15 -> 0.029138553 | AB93: =+AB92/AB$15 -> 0.035062175 | AC93: =+AC92/AC$15 -> 0.028656404 | AD93: =+AD92/AD$15 -> 0.028065113 | AE93: =+AE92/AE$15 -> 0.029195571 | AF93: =+AF92/AF$15 -> 0.02514609 | AG93: =+AG92/AG$15 -> 0.025173364 | AH93: =+AH92/AH$15 -> 0.025734314 | ... AP93: =+AP92/AP$15 -> 0.03
A94: Lease Liab | B94: 65731 | C94: 66524 | D94: 69332 | E94: 72968 | F94: 74267 | G94: 75822 | H94: 75891 | I94: 77297 | J94: 77052 | K94: 78084 | L94: 79802 | M94: 78277 | N94: 79871 | O94: 83221 | P94: 84677 | Q94: 87339 | R94: 90814 | S94: 94338 | AA94: 0 | AB94: 0 | AC94: 0 | AD94: 0 | AE94: 39791 | AF94: 52573 | AG94: 67651 | AH94: 72968 | AI94: 77297 | AJ94: 78277 | AK94: 87339
A95: Debt | B95: 47556 | C95: 58053 | D95: 58919 | E95: 67150 | F95: 67084 | G95: 63092 | H95: 61098 | I95: 58314 | J95: 57634 | K95: 54889 | L95: 54890 | M95: 52623 | N95: 53374 | O95: 50718 | P95: 50742 | Q95: 65648 | R95: 119074 | S95: 128894 | AA95: 8227 | AB95: 7694 | AC95: 24743 | AD95: 23495 | AE95: 23414 | AF95: 31816 | AG95: 48744 | AH95: 67150 | AI95: 58314 | AJ95: 52623 | AK95: 65648
A96: Other Liab | B96: 23971 | C96: 23458 | D96: 22259 | E96: 21121 | F96: 20931 | G96: 21853 | H96: 21707 | I96: 25451 | J96: 26657 | K96: 27226 | L96: 29306 | M96: 28593 | N96: 27973 | O96: 27535 | P96: 27675 | Q96: 35985 | R96: 48072 | S96: 79563 | AA96: 9249 | AB96: 12607 | AC96: 20975 | AD96: 27213 | AE96: 12171 | AF96: 17017 | AG96: 23643 | AH96: 21121 | AI96: 25451 | AJ96: 28593 | AK96: 35985
A97: L | B97: =+SUM(B89:B96)-B93-B91 -> 276766 | C97: =+SUM(C89:C96)-C93-C91 -> 288326 | D97: =+SUM(D89:D96)-D93-D91 -> 290873 | E97: =+SUM(E89:E96)-E93-E91 -> 316632 | F97: =+SUM(F89:F96)-F93-F91 -> 309852 | G97: =+SUM(G89:G96)-G93-G91 -> 309005 | H97: =+SUM(H89:H96)-H93-H91 -> 303910 | I97: =+SUM(I89:I96)-I93-I91 -> 325979 | ... U97: =+SUM(U89:U96)-U93-U91 -> 0 | AA97: =+SUM(AA89:AA96)-AA93-AA91 -> 51363 | AB97: =+SUM(AB89:AB96)-AB93-AB91 -> 64117 | AC97: =+SUM(AC89:AC96)-AC93-AC91 -> 103601 | AD97: =+SUM(AD89:AD96)-AD93-AD91 -> 119099 | AE97: =+SUM(AE89:AE96)-AE93-AE91 -> 163188 | AF97: =+SUM(AF89:AF96)-AF93-AF91 -> 227791 | AG97: =+SUM(AG89:AG96)-AG93-AG91 -> 282304 | AH97: =+SUM(AH89:AH96)-AH93-AH91 -> 316632 | ... AK97: =+SUM(AK89:AK96)-AK93-AK91 -> 406977
A98: Preferred Stock | B98: 0 | C98: 0 | D98: 0 | E98: 0 | F98: 0 | G98: 0 | H98: 0 | I98: 0 | J98: 0 | K98: 0 | L98: 0 | M98: 0 | N98: 0 | O98: 0 | P98: 0 | Q98: 0 | R98: 0 | S98: 0 | AA98: 0 | AB98: 0 | AC98: 0 | AD98: 0 | AE98: 0 | AF98: 0 | AG98: 0 | AH98: 0 | AI98: 0 | AJ98: 0 | AK98: 0
A99: Stock | B99: 5 | C99: 107 | D99: 107 | E99: 108 | F99: 108 | G99: 108 | H99: 108 | I99: 109 | J99: 109 | K99: 110 | L99: 110 | M99: 111 | N99: 111 | O99: 112 | P99: 112 | Q99: 112 | R99: 113 | S99: 113 | AA99: 5 | AB99: 5 | AC99: 5 | AD99: 5 | AE99: 5 | AF99: 5 | AG99: 106 | AH99: 108 | AI99: 109 | AJ99: 111 | AK99: 112
A100: Treasury Stock | B100: -4503 | C100: -7837 | D100: -7837 | E100: -7837 | F100: -7837 | G100: -7837 | H100: -7873 | I100: -7837 | J100: -7837 | K100: -7837 | L100: -7837 | M100: -7837 | N100: -7837 | O100: -7837 | P100: -7837 | Q100: -7837 | R100: -7837 | S100: -7837 | AA100: -1837 | AB100: -1837 | AC100: -1837 | AD100: -1837 | AE100: -1837 | AF100: -1837 | AG100: -1837 | AH100: -7837 | AI100: -7837 | AJ100: -7837 | AK100: -7837
A101: APIC | B101: 58793 | C101: 63871 | D101: 69419 | E101: 75066 | F101: 79863 | G101: 86896 | H101: 92711 | I101: 99025 | J101: 103938 | K101: 110633 | L101: 115934 | M101: 120864 | N101: 124514 | O101: 130923 | P101: 135679 | Q101: 140024 | R101: 143979 | S101: 149619 | AA101: 13394 | AB101: 17186 | AC101: 21389 | AD101: 26791 | AE101: 33658 | AF101: 42865 | AG101: 55437 | AH101: 75066 | AI101: 99025 | AJ101: 120864 | AK101: 140024
A102: Acc. Income | B102: -2365 | C102: -4782 | D102: -7115 | E102: -4487 | F102: -3973 | G102: -3680 | H102: -5003 | I102: -3040 | J102: -3598 | K102: -3993 | L102: -1918 | M102: -34 | N102: -914 | O102: 2420 | P102: 12333 | Q102: 28230 | R102: 24868 | S102: 66287 | AA102: -723 | AB102: -985 | AC102: -484 | AD102: -1035 | AE102: -986 | AF102: -180 | AG102: -1376 | AH102: -4487 | AI102: -3040 | AJ102: -34 | AK102: 28230
A103: Retained Earn. | B103: 82071 | C103: 80043 | D103: 82915 | E103: 83193 | F103: 86365 | G103: 93115 | H103: 102994 | I103: 113618 | J103: 124049 | K103: 137534 | L103: 152862 | M103: 172866 | N103: 189993 | O103: 208157 | P103: 229344 | Q103: 250536 | R103: 280791 | S103: 343438 | AA103: 2545 | AB103: 4916 | AC103: 8636 | AD103: 19625 | AE103: 31220 | AF103: 52551 | AG103: 85915 | AH103: 83193 | AI103: 113618 | AJ103: 172866 | AK103: 250536
A104: SE | B104: =+SUM(B98:B103) -> 134001 | C104: =+SUM(C98:C103) -> 131402 | D104: =+SUM(D98:D103) -> 137489 | E104: =+SUM(E98:E103) -> 146043 | F104: =+SUM(F98:F103) -> 154526 | G104: =+SUM(G98:G103) -> 168602 | H104: =+SUM(H98:H103) -> 182937 | I104: =+SUM(I98:I103) -> 201875 | ... U104: =+SUM(U98:U103) -> 0 | AA104: =+SUM(AA98:AA103) -> 13384 | AB104: =+SUM(AB98:AB103) -> 19285 | AC104: =+SUM(AC98:AC103) -> 27709 | AD104: =+SUM(AD98:AD103) -> 43549 | AE104: =+SUM(AE98:AE103) -> 62060 | AF104: =+SUM(AF98:AF103) -> 93404 | AG104: =+SUM(AG98:AG103) -> 138245 | AH104: =+SUM(AH98:AH103) -> 146043 | ... AK104: =+SUM(AK98:AK103) -> 411065
A105: L+SE | B105: =+B104+B97 -> 410767 | C105: =+C104+C97 -> 419728 | D105: =+D104+D97 -> 428362 | E105: =+E104+E97 -> 462675 | F105: =+F104+F97 -> 464378 | G105: =+G104+G97 -> 477607 | H105: =+H104+H97 -> 486847 | I105: =+I104+I97 -> 527854 | ... U105: =+U104+U97 -> 0 | AA105: =+AA104+AA97 -> 64747 | AB105: =+AB104+AB97 -> 83402 | AC105: =+AC104+AC97 -> 131310 | AD105: =+AD104+AD97 -> 162648 | AE105: =+AE104+AE97 -> 225248 | AF105: =+AF104+AF97 -> 321195 | AG105: =+AG104+AG97 -> 420549 | AH105: =+AH104+AH97 -> 462675 | ... AK105: =+AK104+AK97 -> 818042
A108: Model NI | B108: =+B47 -> -3844 | C108: =+C47 -> -2028 | D108: =+D47 -> 2872 | E108: =+E47 -> 278 | F108: =+F47 -> 3172 | G108: =+G47 -> 6750 | H108: =+H47 -> 9879 | I108: =+I47 -> 10624 | ... U108: =+U47 -> 29309.021 | AA108: =+AA47 -> 596 | AB108: =+AB47 -> 2371 | AC108: =+AC47 -> 3033 | AD108: =+AD47 -> 10073 | AE108: =+AE47 -> 11588 | AF108: =+AF47 -> 21331 | AG108: =+AG47 -> 33364 | AH108: =+AH47 -> -2722 | ... AP108: =+AP47 -> 259216.59
...

Sheet Bond
A1: Main
B3: isin | C3: bondType | D3: immediateIssuer | E3: coupon | F3: couponType | G3: maturityDate | H3: callable | I3: currency | J3: seniorityLevel | K3: liquidityScore
B4: US023135BX34 | C4: — | D4: Amazon.com, Inc. | E4: 1000 | F4: Fixed Listing | G4: 12/05/2026 | H4: Y | I4: USD | J4: Senior | K4: — | O4: Axio is a firm that Amazon acquired in 2024
B5: INE491W08251 | C5: — | D5: Axio | E5: 13000 | F5: Fixed Listing | G5: 12/06/2026 | H5: N | I5: INR | J5: Senior | K5: —
B6: INE1FMW07013 | C6: — | D6: Axio Digital Private Limited | E6: 12500 | F6: Fixed Listing | G6: 24/07/2026 | H6: N | I6: INR | J6: Senior | K6: —
B7: INE491W08426 | C7: — | D7: Axio | E7: 13000 | F7: Fixed Listing | G7: 31/08/2026 | H7: N | I7: INR | J7: Senior | K7: —
B8: INE1FMW07070 | C8: — | D8: Axio Digital Private Limited | E8: 12500 | F8: Fixed Listing | G8: 07/09/2026 | H8: N | I8: INR | J8: Senior | K8: —
B9: INE491W07535 | C9: — | D9: Axio | E9: 13500 | F9: Fixed Listing | G9: 28/09/2026 | H9: N | I9: INR | J9: Senior | K9: —
B10: INE1FMW07088 | C10: — | D10: Axio Digital Private Limited | E10: 12500 | F10: Fixed Listing | G10: 09/11/2026 | H10: N | I10: INR | J10: Senior | K10: —
B11: INE1FMW07104 | C11: — | D11: Axio Digital Private Limited | E11: 12500 | F11: Fixed Listing | G11: 13/12/2026 | H11: N | I11: INR | J11: Senior | K11: —
B12: US023135CF19 | C12: — | D12: Amazon.com, Inc. | E12: 3300 | F12: Fixed Listing | G12: 13/04/2027 | H12: Y | I12: USD | J12: Senior | K12: —
B13: US023135BR65 | C13: — | D13: Amazon.com, Inc. | E13: 1200 | F13: Fixed Listing | G13: 03/06/2027 | H13: Y | I13: USD | J13: Senior | K13: —
B14: US023135BC96 | C14: — | D14: Amazon.com, Inc. | E14: 3150 | F14: Fixed Listing | G14: 22/08/2027 | H14: Y | I14: USD | J14: Senior | K14: —
B15: US023135CP90 | C15: — | D15: Amazon.com, Inc. | E15: 4550 | F15: Fixed Listing | G15: 01/12/2027 | H15: Y | I15: USD | J15: Senior | K15: —
B16: INE491W08277 | C16: — | D16: Axio | E16: 13000 | F16: Fixed Listing | G16: 04/01/2028 | H16: N | I16: INR | J16: Senior | K16: —
... B63: US023135DK94 | C63: — | D63: Amazon.com, Inc. | E63: 6050 | F63: Fixed Listing | G63: 13/03/2076 | H63: Y | I63: USD | J63: Senior | K63: —
E64: =+AVERAGE(E4:E63) -> 5314.1167

Sheet Board
A1: Main | E1: auditor | F1: E&Y
