Workbook

Sheet Main
A1: Alphabeth Inc. | D1: Share A | E1: 344
D2: Share B | E2: 0 | I2: -> | J2: Increasing growth of Google cloud
D3: Share C | E3: 340 | I3: -> | J3: +74% CapEx in AI (?)
D4: Shares A | E4: 5868 | F4: Q226 | I4: -> | J4: Waymo more than 500.000 drives a week
D5: Shares B | E5: 835 | F5: Q226 | I5: -> | J5: 350 M paid users between Google One and YT Premium
D6: Shares C | E6: 5527 | F6: Q226
D7: MC | E7: =+E4*E1+E6*E3 -> 3897772
D8: Cash | E8: 242474 | F8: Q226
D9: Debt | E9: 98165 | F9: Q226
D10: Preferred | E10: 18023 | F10: Q226
D11: Ev | E11: =+E7-E8+E9+E10 -> 3771486
D13: IPO | E13: 2004
A15: HQ | B15: 1600 Amphitheatre Parkway, Mountain View, CA 94043, US
A16: CEO | B16: Sundar Pichai
A18: P/FCF | B18: =+E7/SUM(Model!P139:S139) -> 73.165994 | D18: WACC | E18: =+(E7/(E7+E9+E10))*B24+(E10/(E10+E9+E7))*B25*(1-Model!AH59) -> 0.10946049
A19: P/E | B19: =+E7/SUM(Model!P41:S41) -> 15.961065
A20: EV/EBITDA | B20: =+E11/SUM(Model!P71:S71) -> 17.708502
A21: EV/FCF | B21: =+E11/SUM(Model!O139:R139) -> 58.537087
A22: Inc Margin | B22: =+((Model!S33+Model!R33+Model!Q33+Model!P33)-(Model!O33+Model!N33+Model!M33+Model!L33))/((Model!S19+Model!R19+Model!Q19+Model!P19)-(Model!O19+Model!N19+Model!M19+Model!L19)) -> 0.35261257
A23: BETA | B23: 1.25
A24: CAPM | B24: =+0.05+B23*(0.1-0.05) -> 0.1125
A25: Cost of Debt | B25: =+0.05+(B26/100) -> 0.058052174 | C25: =+Bond!D50/100000 -> 0.036967174
A26: Cr. Spread | B26: =+'[1]Credit Spread US'!J6 -> 0.80521739
A27: Rating | B27: AA+ | C27: AA1
B28: S&P | C28: Moody’s
A30: Google Search and Other
B31: Google Search Advertising
B32: Revenues from properties like Gmail, Maps and Google Play
A34: YT Ads
B35: Advertising on Youtube
B36: -> | C36: Long form video
B37: -> | C37: Short form video
B38: -> | C38: Connected-TV / living room viewers
B39: -> | C39: Music
B40: -> | C40: Live Streams
A42: Google Network
B43: Google’s revenue on third party websites
B44: -> | C44: AdSense
B45: -> | C45: AdMob
B46: -> | C46: Google Ad Manager
A49: Google Subscriptions, Platforms & Devices
B50: Subscriptions
B51: -> | C51: YT Premium/Music (consumer target)
B52: -> | C52: YT TV (live TV market)
B53: -> | C53: NFL Sunday Ticket (sport subscription)
B54: -> | C54: Google One (storage and AI related)
B55: -> | C55: Google Play Pass (consumer target)
B57: Platforms
B58: -> | C58: Google Play (marketplace fee)
B60: Devices
B61: -> | C61: Pixel Phone family
A64: Google Cloud (enterprise IT target)
B65: Cloud Infrastructure
B66: -> | C66: Compute
C67: GOOGL is a huge Nvidia customer serving (A100, H100, B200, …)
C68: GOOGL also deploys their inhouse made TPUs (AI accellerators)
C69: -> | D69: TPU v7 (Ironwood) with a high-speed domain (single superpod) of up to 9,216 TPUs
C70: -> | D70: TPU 8t (mainly for training) with a single superpod up to 9,600 TPUs
C71: -> | D71: TPR 8i (mainly for inference) single superpod up to 1,152 TPUs with much more efficient token generation
B75: -> | C75: Storage
B76: -> | C76: Databases
B77: -> | C77: Networking
B78: -> | C78: Data Analytics
B79: -> | C79: Cybersecurity
B80: -> | C80: AI Infrastructure
B81: -> | C81: Vertex AI
B82: -> | C82: Gemini Enterprise
B83: Workspace (all with enterprise feature)
B84: -> | C84: Gmail
B85: -> | C85: Docs
B86: -> | C86: Drive
B87: -> | C87: …
B88: AI services
B89: -> | C89: Gemini Enterprise
A91: Hedging Gains
B92: FX hedge accounting
A96: Other Bets
B97: Waymo (AV)
B98: Google Fiber (High Speed Internet)
B99: Verily (health tech company)
B100: Wing (drone delivery)
B101: Intrinsic (Robotic Company) – after selling Boston Dynamics
B102: Isomorphic Labs (AI drug discovery)
B103: Moonshot Factory (general R&D, no major revenue provider)

Sheet Model
A1: Main | B1: 03/22 | C1: 06/22 | D1: 09/22 | E1: 12/22 | F1: 03/23 | G1: 06/23 | H1: 09/23 | I1: 12/23 | J1: 03/24 | K1: 06/24 | L1: 09/24 | M1: 12/24 | N1: 03/25 | O1: 06/25 | P1: 09/25 | Q1: 12/25 | R1: 03/26 | S1: 06/26 | T1: 09/26 | U1: 12/26 | AC1: 12/20 | AD1: 12/21 | AE1: 12/22 | AF1: 12/23 | AG1: 12/24 | AH1: 12/25 | AI1: 12/26 | AJ1: 12/27 | AK1: 12/28 | AL1: 12/29 | AM1: 12/30
A2: in Millions | B2: Q122 | C2: Q222 | D2: Q322 | E2: Q422 | F2: Q123 | G2: Q223 | H2: Q323 | I2: Q423 | J2: Q124 | K2: Q224 | L2: Q324 | M2: Q424 | N2: Q125 | O2: Q225 | P2: Q325 | Q2: Q425 | R2: Q126 | S2: Q226 | T2: Q326 | U2: Q426 | AC2: 2020 | AD2: =+AC2+1 -> 2021 | AE2: =+AD2+1 -> 2022 | AF2: =+AE2+1 -> 2023 | AG2: =+AF2+1 -> 2024 | AH2: =+AG2+1 -> 2025 | AI2: =+AH2+1 -> 2026 | AJ2: =+AI2+1 -> 2027 | AK2: =+AJ2+1 -> 2028 | ... AM2: =+AL2+1 -> 2030
A3: Google Search & Other | B3: 39618 | C3: 40689 | D3: 39539 | E3: 42604 | F3: 40359 | G3: 42628 | H3: 44026 | I3: 48020 | J3: 46156 | K3: 48509 | L3: 49385 | M3: 54034 | N3: 50702 | O3: 54190 | P3: 56567 | Q3: 63073 | R3: 60399 | S3: 63271 | T3: =+P3*1.13 -> 63920.71 | U3: =+Q3*1.13 -> 71272.49 | AC3: 104062 | AD3: 148951 | AE3: =SUM(B3:E3) -> 162450 | AF3: =SUM(F3:I3) -> 175033 | AG3: =SUM(J3:M3) -> 198084 | AH3: =SUM(N3:Q3) -> 224532
F4: =F3/B3-1 -> 0.01870362 | G4: =G3/C3-1 -> 0.047654157 | H4: =H3/D3-1 -> 0.11348289 | I4: =I3/E3-1 -> 0.12712421 | J4: =J3/F3-1 -> 0.14363587 | K4: =K3/G3-1 -> 0.13796096 | L4: =L3/H3-1 -> 0.12172353 | M4: =M3/I3-1 -> 0.12523948 | ... U4: =U3/Q3-1 -> 0.13 | AD4: =+AD3/AC3-1 -> 0.43136784 | AE4: =+AE3/AD3-1 -> 0.090627119 | AF4: =+AF3/AE3-1 -> 0.077457679 | AG4: =+AG3/AF3-1 -> 0.13169517 | AH4: =+AH3/AG3-1 -> 0.13351911
A5: YT Ads | B5: 6869 | C5: 7340 | D5: 7071 | E5: 7963 | F5: 6693 | G5: 7665 | H5: 7952 | I5: 9200 | J5: 8090 | K5: 8663 | L5: 8921 | M5: 10473 | N5: 8927 | O5: 9796 | P5: 10261 | Q5: 11383 | R5: 9883 | S5: 11055 | T5: =+P5*1.1 -> 11287.1 | U5: =+Q5*1.1 -> 12521.3 | AC5: 19772 | AD5: 28845 | AE5: =SUM(B5:E5) -> 29243 | AF5: =SUM(F5:I5) -> 31510 | AG5: =SUM(J5:M5) -> 36147 | AH5: =SUM(N5:Q5) -> 40367
F6: =F5/B5-1 -> -0.025622361 | G6: =G5/C5-1 -> 0.044277929 | H6: =H5/D5-1 -> 0.12459341 | I6: =I5/E5-1 -> 0.15534346 | J6: =J5/F5-1 -> 0.20872553 | K6: =K5/G5-1 -> 0.13020222 | L6: =L5/H5-1 -> 0.12185614 | M6: =M5/I5-1 -> 0.13836957 | ... U6: =U5/Q5-1 -> 0.1 | AD6: =+AD5/AC5-1 -> 0.45888125 | AE6: =+AE5/AD5-1 -> 0.013797885 | AF6: =+AF5/AE5-1 -> 0.077522826 | AG6: =+AG5/AF5-1 -> 0.14715963 | AH6: =+AH5/AG5-1 -> 0.11674551
A7: Google Network | B7: 8174 | C7: 8259 | D7: 7872 | E7: 8475 | F7: 7496 | G7: 7850 | H7: 7669 | I7: 8297 | J7: 7413 | K7: 7444 | L7: 7548 | M7: 7954 | N7: 7256 | O7: 7354 | P7: 7354 | Q7: 7828 | R7: 6971 | S7: 7303 | T7: =+S7*0.99 -> 7229.97 | U7: =+T7*0.99 -> 7157.6703 | AC7: 23090 | AD7: 31701 | AE7: =SUM(B7:E7) -> 32780 | AF7: =SUM(F7:I7) -> 31312 | AG7: =SUM(J7:M7) -> 30359 | AH7: =SUM(N7:Q7) -> 29792
F8: =F7/B7-1 -> -0.082945926 | G8: =G7/C7-1 -> -0.049521734 | H8: =H7/D7-1 -> -0.025787602 | I8: =I7/E7-1 -> -0.02100295 | J8: =J7/F7-1 -> -0.011072572 | K8: =K7/G7-1 -> -0.051719745 | L8: =L7/H7-1 -> -0.015777807 | M8: =M7/I7-1 -> -0.041340243 | ... U8: =U7/Q7-1 -> -0.085632307 | AD8: =+AD7/AC7-1 -> 0.37293201 | AE8: =+AE7/AD7-1 -> 0.034036781 | AF8: =+AF7/AE7-1 -> -0.044783405 | AG8: =+AG7/AF7-1 -> -0.030435616 | AH8: =+AH7/AG7-1 -> -0.018676504
A9: Google Subscriptions | B9: 6811 | C9: 6553 | D9: 6895 | E9: 8796 | F9: 7413 | G9: 8142 | H9: 8339 | I9: 10794 | J9: 8739 | K9: 9312 | L9: 10656 | M9: 11633 | N9: 10379 | O9: 11203 | P9: 12870 | Q9: 13578 | R9: 12384 | S9: 12911 | T9: =+P9*1.15 -> 14800.5 | U9: =+Q9*1.15 -> 15614.7 | AC9: 21711 | AD9: 28032 | AE9: =SUM(B9:E9) -> 29055 | AF9: =SUM(F9:I9) -> 34688 | AG9: =SUM(J9:M9) -> 40340 | AH9: =SUM(N9:Q9) -> 48030
F10: =F9/B9-1 -> 0.088386434 | G10: =G9/C9-1 -> 0.24248436 | H10: =H9/D9-1 -> 0.20942712 | I10: =I9/E9-1 -> 0.2271487 | J10: =J9/F9-1 -> 0.17887495 | K10: =K9/G9-1 -> 0.14369934 | L10: =L9/H9-1 -> 0.27785106 | M10: =M9/I9-1 -> 0.077728368 | ... U10: =U9/Q9-1 -> 0.15 | AD10: =+AD9/AC9-1 -> 0.29114274 | AE10: =+AE9/AD9-1 -> 0.036494007 | AF10: =+AF9/AE9-1 -> 0.19387369 | AG10: =+AG9/AF9-1 -> 0.16293819 | AH10: =+AH9/AG9-1 -> 0.19062965
A11: Total Google Services | B11: =+B9+B7+B5+B3 -> 61472 | C11: =+C9+C7+C5+C3 -> 62841 | D11: =+D9+D7+D5+D3 -> 61377 | E11: =+E9+E7+E5+E3 -> 67838 | F11: =+F9+F7+F5+F3 -> 61961 | G11: =+G9+G7+G5+G3 -> 66285 | H11: =+H9+H7+H5+H3 -> 67986 | I11: =+I9+I7+I5+I3 -> 76311 | ... U11: =+U9+U7+U5+U3 -> 106566.16 | AC11: =+AC9+AC7+AC5+AC3 -> 168635 | AD11: =+AD9+AD7+AD5+AD3 -> 237529 | AE11: =+AE9+AE7+AE5+AE3 -> 253528 | AF11: =+AF9+AF7+AF5+AF3 -> 272543 | AG11: =+AG9+AG7+AG5+AG3 -> 304930 | AH11: =+AH9+AH7+AH5+AH3 -> 342721
F12: =F11/B11-1 -> 0.0079548412 | G12: =G11/C11-1 -> 0.054804984 | H12: =H11/D11-1 -> 0.10767877 | I12: =I11/E11-1 -> 0.1249005 | J12: =J11/F11-1 -> 0.1361663 | K12: =K11/G11-1 -> 0.11530512 | L12: =L11/H11-1 -> 0.12537875 | M12: =M11/I11-1 -> 0.10199054 | ... U12: =U11/Q11-1 -> 0.11166218 | AD12: =+AD11/AC11-1 -> 0.40853915 | AE12: =+AE11/AD11-1 -> 0.067355986 | AF12: =+AF11/AE11-1 -> 0.075001578 | AG12: =+AG11/AF11-1 -> 0.11883262 | AH12: =+AH11/AG11-1 -> 0.12393336
A13: Google Cloud | B13: 5821 | C13: 6276 | D13: 6868 | E13: 7315 | F13: 7454 | G13: 8031 | H13: 8411 | I13: 9192 | J13: 9574 | K13: 10347 | L13: 11353 | M13: 11955 | N13: 12260 | O13: 13624 | P13: 15157 | Q13: 17664 | R13: 20028 | S13: 24768 | T13: =+P13*1.35 -> 20461.95 | U13: =+Q13*1.35 -> 23846.4 | AC13: 13059 | AD13: 19206 | AE13: =SUM(B13:E13) -> 26280 | AF13: =SUM(F13:I13) -> 33088 | AG13: =SUM(J13:M13) -> 43229 | AH13: =SUM(N13:Q13) -> 58705
F14: =F13/B13-1 -> 0.28053599 | G14: =G13/C13-1 -> 0.27963671 | H14: =H13/D13-1 -> 0.22466511 | I14: =I13/E13-1 -> 0.25659604 | J14: =J13/F13-1 -> 0.28441105 | K14: =K13/G13-1 -> 0.28838252 | L14: =L13/H13-1 -> 0.34978005 | M14: =M13/I13-1 -> 0.30058747 | ... U14: =U13/Q13-1 -> 0.35 | AD14: =+AD13/AC13-1 -> 0.47070986 | AE14: =+AE13/AD13-1 -> 0.3683224 | AF14: =+AF13/AE13-1 -> 0.25905632 | AG14: =+AG13/AF13-1 -> 0.30648574 | AH14: =+AH13/AG13-1 -> 0.35800042
A15: Other Bets | B15: 440 | C15: 193 | D15: 209 | E15: 226 | F15: 288 | G15: 285 | H15: 297 | I15: 657 | J15: 495 | K15: 365 | L15: 388 | M15: 400 | N15: 450 | O15: 373 | P15: 344 | Q15: 370 | R15: 411 | S15: 382 | T15: =+P15*0.93 -> 319.92 | U15: =+Q15*0.93 -> 344.1 | AC15: 657 | AD15: 753 | AE15: =SUM(B15:E15) -> 1068 | AF15: =SUM(F15:I15) -> 1527 | AG15: =SUM(J15:M15) -> 1648 | AH15: =SUM(N15:Q15) -> 1537
F16: =F15/B15-1 -> -0.34545455 | G16: =G15/C15-1 -> 0.47668394 | H16: =H15/D15-1 -> 0.42105263 | I16: =I15/E15-1 -> 1.9070796 | J16: =J15/F15-1 -> 0.71875 | K16: =K15/G15-1 -> 0.28070175 | L16: =L15/H15-1 -> 0.30639731 | M16: =M15/I15-1 -> -0.39117199 | ... U16: =U15/Q15-1 -> -0.07 | AD16: =+AD15/AC15-1 -> 0.14611872 | AE16: =+AE15/AD15-1 -> 0.41832669 | AF16: =+AF15/AE15-1 -> 0.42977528 | AG16: =+AG15/AF15-1 -> 0.079240341 | AH16: =+AH15/AG15-1 -> -0.067354369
A17: Hedging gains | B17: 278 | C17: 375 | D17: 638 | E17: 669 | F17: 84 | G17: 3 | H17: -1 | I17: 150 | J17: 72 | K17: 102 | L17: 17 | M17: 20 | N17: 260 | O17: -112 | P17: -207 | Q17: -68 | R17: -180 | S17: 106 | T17: -100 | U17: -100 | AC17: 176 | AD17: 149 | AE17: =SUM(B17:E17) -> 1960 | AF17: =SUM(F17:I17) -> 236 | AG17: =SUM(J17:M17) -> 211 | AH17: =SUM(N17:Q17) -> -127
F18: =F17/B17-1 -> -0.69784173 | G18: =G17/C17-1 -> -0.992 | H18: =H17/D17-1 -> -1.0015674 | I18: =I17/E17-1 -> -0.77578475 | J18: =J17/F17-1 -> -0.14285714 | K18: =K17/G17-1 -> 33 | L18: =L17/H17-1 -> -18 | M18: =M17/I17-1 -> -0.86666667 | ... U18: =U17/Q17-1 -> 0.47058824 | AD18: =+AD17/AC17-1 -> -0.15340909 | AE18: =+AE17/AD17-1 -> 12.154362 | AF18: =+AF17/AE17-1 -> -0.87959184 | AG18: =+AG17/AF17-1 -> -0.1059322 | AH18: =+AH17/AG17-1 -> -1.6018957
A19: Revenues | B19: =+B17+B15+B13+B11 -> 68011 | C19: =+C17+C15+C13+C11 -> 69685 | D19: =+D17+D15+D13+D11 -> 69092 | E19: =+E17+E15+E13+E11 -> 76048 | F19: =+F17+F15+F13+F11 -> 69787 | G19: =+G17+G15+G13+G11 -> 74604 | H19: =+H17+H15+H13+H11 -> 76693 | I19: =+I17+I15+I13+I11 -> 86310 | ... S19: =+S17+S15+S13+S11 -> 119796 | T19: =+P19*1.17 -> 119744.82 | U19: =+Q19*1.16 -> 132040.48 | AC19: =+AC17+AC15+AC13+AC11 -> 182527 | AD19: =+AD17+AD15+AD13+AD11 -> 257637 | AE19: =+AE17+AE15+AE13+AE11 -> 282836 | AF19: =+AF17+AF15+AF13+AF11 -> 307394 | AG19: =+AG17+AG15+AG13+AG11 -> 350018 | AH19: =+AH17+AH15+AH13+AH11 -> 402836 | AI19: =+AH19*1.2 -> 483403.2 | AJ19: =+AI19*1.18 -> 570415.78 | AK19: =+AJ19*1.16 -> 661682.3 | AL19: =+AK19*1.15 -> 760934.65 | AM19: =+AL19*1.14 -> 867465.5
AD20: =+AD19/AC19-1 -> 0.41150076 | AE20: =+AE19/AD19-1 -> 0.097808156 | AF20: =+AF19/AE19-1 -> 0.086827702 | AG20: =+AG19/AF19-1 -> 0.13866243 | AH20: =+AH19/AG19-1 -> 0.15090081 | AI20: =+AI19/AH19-1 -> 0.2 | AJ20: =+AJ19/AI19-1 -> 0.18 | AK20: =+AK19/AJ19-1 -> 0.16 | ... AM20: =+AM19/AL19-1 -> 0.14
A21: COGS | B21: 29599 | C21: 30104 | D21: 31158 | E21: 35342 | F21: 30612 | G21: 31916 | H21: 33229 | I21: 37575 | J21: 33712 | K21: 35507 | L21: 36474 | M21: 40613 | N21: 36361 | O21: 39039 | P21: 41369 | Q21: 45766 | R21: 41271 | S21: 45943 | T21: =+T19-T23 -> 46700.48 | U21: =+U19-U23 -> 51495.787 | AC21: 84732 | AD21: 110939 | AE21: =SUM(B21:E21) -> 126203 | AF21: =SUM(F21:I21) -> 133332 | AG21: =SUM(J21:M21) -> 146306 | AH21: =SUM(N21:Q21) -> 162535 | AI21: =+AI19-AI23 -> 188527.25 | AJ21: =+AJ19-AJ23 -> 219610.07 | AK21: =+AK19-AK23 -> 251439.27 | AL21: =+AL19-AL23 -> 285350.49 | AM21: =+AM19-AM23 -> 320962.23
B22: =+B21/B$19 -> 0.43520901 | C22: =+C21/C$19 -> 0.43200115 | D22: =+D21/D$19 -> 0.45096393 | E22: =+E21/E$19 -> 0.4647328 | F22: =+F21/F$19 -> 0.43864903 | G22: =+G21/G$19 -> 0.42780548 | H22: =+H21/H$19 -> 0.43327292 | I22: =+I21/I$19 -> 0.43534932 | ... U22: =+U21/U$19 -> 0.39 | AC22: =+AC21/AC$19 -> 0.46421625 | AD22: =+AD21/AD$19 -> 0.43060197 | AE22: =+AE21/AE$19 -> 0.44620557 | AF22: =+AF21/AF$19 -> 0.43374952 | AG22: =+AG21/AG$19 -> 0.41799565 | AH22: =+AH21/AH$19 -> 0.40347685 | AI22: =+AI21/AI$19 -> 0.39 | AJ22: =+AJ21/AJ$19 -> 0.385 | ... AM22: =+AM21/AM$19 -> 0.37
A23: Gross Margin | B23: =+B19-B21 -> 38412 | C23: =+C19-C21 -> 39581 | D23: =+D19-D21 -> 37934 | E23: =+E19-E21 -> 40706 | F23: =+F19-F21 -> 39175 | G23: =+G19-G21 -> 42688 | H23: =+H19-H21 -> 43464 | I23: =+I19-I21 -> 48735 | ... S23: =+S19-S21 -> 73853 | T23: =+T19*0.61 -> 73044.34 | U23: =+U19*0.61 -> 80544.693 | AC23: =+AC19-AC21 -> 97795 | AD23: =+AD19-AD21 -> 146698 | AE23: =+AE19-AE21 -> 156633 | AF23: =+AF19-AF21 -> 174062 | AG23: =+AG19-AG21 -> 203712 | AH23: =+AH19-AH21 -> 240301 | AI23: =+AI19*0.61 -> 294875.95 | AJ23: =+AJ19*0.615 -> 350805.7 | AK23: =+AK19*0.62 -> 410243.03 | AL23: =+AL19*0.625 -> 475584.15 | AM23: =+AM19*0.63 -> 546503.26
B24: =+B23/B$19 -> 0.56479099 | C24: =+C23/C$19 -> 0.56799885 | D24: =+D23/D$19 -> 0.54903607 | E24: =+E23/E$19 -> 0.5352672 | F24: =+F23/F$19 -> 0.56135097 | G24: =+G23/G$19 -> 0.57219452 | H24: =+H23/H$19 -> 0.56672708 | I24: =+I23/I$19 -> 0.56465068 | ... U24: =+U23/U$19 -> 0.61 | AC24: =+AC23/AC$19 -> 0.53578375 | AD24: =+AD23/AD$19 -> 0.56939803 | AE24: =+AE23/AE$19 -> 0.55379443 | AF24: =+AF23/AF$19 -> 0.56625048 | AG24: =+AG23/AG$19 -> 0.58200435 | AH24: =+AH23/AH$19 -> 0.59652315 | AI24: =+AI23/AI$19 -> 0.61 | AJ24: =+AJ23/AJ$19 -> 0.615 | ... AM24: =+AM23/AM$19 -> 0.63
A25: R&D | B25: 9119 | C25: 9841 | D25: 10273 | E25: 10267 | F25: 11468 | G25: 10588 | H25: 11258 | I25: 12113 | J25: 11903 | K25: 11860 | L25: 12447 | M25: 13116 | N25: 13556 | O25: 13808 | P25: 15151 | Q25: 18572 | R25: 17032 | S25: 18219 | T25: =+S25*1.1 -> 20040.9 | U25: =+T25*1.1 -> 22044.99 | AC25: 27573 | AD25: 31562 | AE25: =SUM(B25:E25) -> 39500 | AF25: =SUM(F25:I25) -> 45427 | AG25: =SUM(J25:M25) -> 49326 | AH25: =SUM(N25:Q25) -> 61087 | AI25: =+AH25*1.12 -> 68417.44 | AJ25: =+AI25*1.12 -> 76627.533 | AK25: =+AJ25*1.12 -> 85822.837 | AL25: =+AK25*1.12 -> 96121.577 | AM25: =+AL25*1.12 -> 107656.17
B26: =+B25/B$19 -> 0.13408125 | C26: =+C25/C$19 -> 0.14122121 | D26: =+D25/D$19 -> 0.14868581 | E26: =+E25/E$19 -> 0.13500684 | F26: =+F25/F$19 -> 0.1643286 | G26: =+G25/G$19 -> 0.14192269 | H26: =+H25/H$19 -> 0.14679306 | I26: =+I25/I$19 -> 0.14034295 | ... U26: =+U25/U$19 -> 0.1669563 | AC26: =+AC25/AC$19 -> 0.15106258 | AD26: =+AD25/AD$19 -> 0.1225057 | AE26: =+AE25/AE$19 -> 0.1396569 | AF26: =+AF25/AF$19 -> 0.14778102 | AG26: =+AG25/AG$19 -> 0.14092418 | AH26: =+AH25/AH$19 -> 0.15164236 | AI26: =+AI25/AI$19 -> 0.14153287 | AJ26: =+AJ25/AJ$19 -> 0.13433628 | ... AM26: =+AM25/AM$19 -> 0.12410426
A27: S&M | B27: 5825 | C27: 6630 | D27: 6929 | E27: 7183 | F27: 6533 | G27: 6781 | H27: 6884 | I27: 7719 | J27: 6426 | K27: 6792 | L27: 7227 | M27: 7363 | N27: 6172 | O27: 7101 | P27: 7205 | Q27: 8215 | R27: 7606 | S27: 8403 | T27: =+S27*1.1 -> 9243.3 | U27: =+T27*1.1 -> 10167.63 | AC27: 17946 | AD27: 22912 | AE27: =SUM(B27:E27) -> 26567 | AF27: =SUM(F27:I27) -> 27917 | AG27: =SUM(J27:M27) -> 27808 | AH27: =SUM(N27:Q27) -> 28693 | AI27: =+AH27*1.12 -> 32136.16 | AJ27: =+AI27*1.12 -> 35992.499 | AK27: =+AJ27*1.12 -> 40311.599 | AL27: =+AK27*1.12 -> 45148.991 | AM27: =+AL27*1.12 -> 50566.87
B28: =+B27/B$19 -> 0.08564791 | C28: =+C27/C$19 -> 0.095142427 | D28: =+D27/D$19 -> 0.10028657 | E28: =+E27/E$19 -> 0.094453503 | F28: =+F27/F$19 -> 0.093613424 | G28: =+G27/G$19 -> 0.09089325 | H28: =+H27/H$19 -> 0.089760474 | I28: =+I27/I$19 -> 0.089433438 | ... U28: =+U27/U$19 -> 0.077003885 | AC28: =+AC27/AC$19 -> 0.098319701 | AD28: =+AD27/AD$19 -> 0.088931326 | AE28: =+AE27/AE$19 -> 0.093930758 | AF28: =+AF27/AF$19 -> 0.090818298 | AG28: =+AG27/AG$19 -> 0.079447343 | AH28: =+AH27/AH$19 -> 0.071227497 | AI28: =+AI27/AI$19 -> 0.066478997 | AJ28: =+AJ27/AJ$19 -> 0.063098709 | ... AM28: =+AM27/AM$19 -> 0.058292659
A29: G&A | B29: 3374 | C29: 3657 | D29: 3597 | E29: 5096 | F29: 3759 | G29: 3481 | H29: 3979 | I29: 5206 | J29: 3026 | K29: 3158 | L29: 3599 | M29: 4405 | N29: 3539 | O29: 5209 | P29: 7393 | Q29: 5341 | R29: 4291 | S29: 6461 | T29: =+S29*1.1 -> 7107.1 | U29: =+T29*1.1 -> 7817.81 | AC29: 11052 | AD29: 13510 | AE29: =SUM(B29:E29) -> 15724 | AF29: =SUM(F29:I29) -> 16425 | AG29: =SUM(J29:M29) -> 14188 | AH29: =SUM(N29:Q29) -> 21482 | AI29: =+AH29*1.12 -> 24059.84 | AJ29: =+AI29*1.12 -> 26947.021 | AK29: =+AJ29*1.12 -> 30180.663 | AL29: =+AK29*1.12 -> 33802.343 | AM29: =+AL29*1.12 -> 37858.624
B30: =+B29/B$19 -> 0.049609622 | C30: =+C29/C$19 -> 0.052479013 | D30: =+D29/D$19 -> 0.05206102 | E30: =+E29/E$19 -> 0.067010309 | F30: =+F29/F$19 -> 0.0538639 | G30: =+G29/G$19 -> 0.046659697 | H30: =+H29/H$19 -> 0.05188218 | I30: =+I29/I$19 -> 0.06031746 | ... U30: =+U29/U$19 -> 0.059207676 | AC30: =+AC29/AC$19 -> 0.060549946 | AD30: =+AD29/AD$19 -> 0.05243812 | AE30: =+AE29/AE$19 -> 0.055594055 | AF30: =+AF29/AF$19 -> 0.053433053 | AG30: =+AG29/AG$19 -> 0.040535058 | AH30: =+AH29/AH$19 -> 0.053326912 | AI30: =+AI29/AI$19 -> 0.049771785 | AJ30: =+AJ29/AJ$19 -> 0.047241016 | ... AM30: =+AM29/AM$19 -> 0.043642801
A31: Op Exp | B31: =+B29+B27+B25 -> 18318 | C31: =+C29+C27+C25 -> 20128 | D31: =+D29+D27+D25 -> 20799 | E31: =+E29+E27+E25 -> 22546 | F31: =+F29+F27+F25 -> 21760 | G31: =+G29+G27+G25 -> 20850 | H31: =+H29+H27+H25 -> 22121 | I31: =+I29+I27+I25 -> 25038 | ... U31: =+U29+U27+U25 -> 40030.43 | AC31: =+AC29+AC27+AC25 -> 56571 | AD31: =+AD29+AD27+AD25 -> 67984 | AE31: =+AE29+AE27+AE25 -> 81791 | AF31: =+AF29+AF27+AF25 -> 89769 | AG31: =+AG29+AG27+AG25 -> 91322 | AH31: =+AH29+AH27+AH25 -> 111262 | AI31: =+AI29+AI27+AI25 -> 124613.44 | AJ31: =+AJ29+AJ27+AJ25 -> 139567.05 | ... AM31: =+AM29+AM27+AM25 -> 196081.66
B32: =+B31/B$19 -> 0.26933878 | C32: =+C31/C$19 -> 0.28884265 | D32: =+D31/D$19 -> 0.3010334 | E32: =+E31/E$19 -> 0.29647065 | F32: =+F31/F$19 -> 0.31180592 | G32: =+G31/G$19 -> 0.27947563 | H32: =+H31/H$19 -> 0.28843571 | I32: =+I31/I$19 -> 0.29009385 | ... U32: =+U31/U$19 -> 0.30316786 | AC32: =+AC31/AC$19 -> 0.30993223 | AD32: =+AD31/AD$19 -> 0.26387514 | AE32: =+AE31/AE$19 -> 0.28918172 | AF32: =+AF31/AF$19 -> 0.29203238 | AG32: =+AG31/AG$19 -> 0.26090658 | AH32: =+AH31/AH$19 -> 0.27619676 | AI32: =+AI31/AI$19 -> 0.25778365 | AJ32: =+AJ31/AJ$19 -> 0.244676 | ... AM32: =+AM31/AM$19 -> 0.22603972
A33: EBIT | B33: =+B23-B31 -> 20094 | C33: =+C23-C31 -> 19453 | D33: =+D23-D31 -> 17135 | E33: =+E23-E31 -> 18160 | F33: =+F23-F31 -> 17415 | G33: =+G23-G31 -> 21838 | H33: =+H23-H31 -> 21343 | I33: =+I23-I31 -> 23697 | ... U33: =+U23-U31 -> 40514.263 | AC33: =+AC23-AC31 -> 41224 | AD33: =+AD23-AD31 -> 78714 | AE33: =+AE23-AE31 -> 74842 | AF33: =+AF23-AF31 -> 84293 | AG33: =+AG23-AG31 -> 112390 | AH33: =+AH23-AH31 -> 129039 | AI33: =+AI23-AI31 -> 170262.51 | AJ33: =+AJ23-AJ31 -> 211238.65 | ... AM33: =+AM23-AM31 -> 350421.6
B34: =+B33/B$19 -> 0.29545221 | C34: =+C33/C$19 -> 0.2791562 | D34: =+D33/D$19 -> 0.24800266 | E34: =+E33/E$19 -> 0.23879655 | F34: =+F33/F$19 -> 0.24954504 | G34: =+G33/G$19 -> 0.29271889 | H34: =+H33/H$19 -> 0.27829137 | I34: =+I33/I$19 -> 0.27455683 | ... U34: =+U33/U$19 -> 0.30683214 | AC34: =+AC33/AC$19 -> 0.22585152 | AD34: =+AD33/AD$19 -> 0.30552289 | AE34: =+AE33/AE$19 -> 0.26461271 | AF34: =+AF33/AF$19 -> 0.2742181 | AG34: =+AG33/AG$19 -> 0.32109777 | AH34: =+AH33/AH$19 -> 0.32032639 | AI34: =+AI33/AI$19 -> 0.35221635 | AJ34: =+AJ33/AJ$19 -> 0.370324 | ... AM34: =+AM33/AM$19 -> 0.40396028
A35: Other Income | B35: -1160 | C35: -439 | D35: -902 | E35: -1013 | F35: 790 | G35: 65 | H35: -146 | I35: 715 | J35: 2843 | K35: 126 | L35: 3185 | M35: 1271 | N35: 11183 | O35: 2662 | P35: 12759 | Q35: 3183 | R35: 37716 | S35: 97983 | T35: 3000 | U35: 3000 | AC35: 6858 | AD35: 12020 | AE35: =SUM(B35:E35) -> -3514 | AF35: =SUM(F35:I35) -> 1424 | AG35: =SUM(J35:M35) -> 7425 | AH35: =SUM(N35:Q35) -> 29787 | AI35: =+AH86*$AQ$59 -> 1605.92 | AJ35: =+AI86*$AQ$59 -> 4527.6833 | AK35: =+AJ86*$AQ$59 -> 8195.711 | AL35: =+AK86*$AQ$59 -> 12651.813 | AM35: =+AL86*$AQ$59 -> 17975.585
B36: =+B35/B$19 -> -0.017056064 | C36: =+C35/C$19 -> -0.0062997776 | D36: =+D35/D$19 -> -0.013055057 | E36: =+E35/E$19 -> -0.013320534 | F36: =+F35/F$19 -> 0.01132016 | G36: =+G35/G$19 -> 0.00087126696 | H36: =+H35/H$19 -> -0.0019036939 | I36: =+I35/I$19 -> 0.0082840922 | ... U36: =+U35/U$19 -> 0.022720305 | AC36: =+AC35/AC$19 -> 0.037572524 | AD36: =+AD35/AD$19 -> 0.046654789 | AE36: =+AE35/AE$19 -> -0.012424161 | AF36: =+AF35/AF$19 -> 0.0046324912 | AG36: =+AG35/AG$19 -> 0.021213195 | AH36: =+AH35/AH$19 -> 0.073943242 | AI36: =+AI35/AI$19 -> 0.0033221129 | AJ36: =+AJ35/AJ$19 -> 0.0079375142 | ... AM36: =+AM35/AM$19 -> 0.020721959
A37: EBT | B37: =+B33+B35 -> 18934 | C37: =+C33+C35 -> 19014 | D37: =+D33+D35 -> 16233 | E37: =+E33+E35 -> 17147 | F37: =+F33+F35 -> 18205 | G37: =+G33+G35 -> 21903 | H37: =+H33+H35 -> 21197 | I37: =+I33+I35 -> 24412 | ... U37: =+U33+U35 -> 43514.263 | AC37: =+AC33+AC35 -> 48082 | AD37: =+AD33+AD35 -> 90734 | AE37: =+AE33+AE35 -> 71328 | AF37: =+AF33+AF35 -> 85717 | AG37: =+AG33+AG35 -> 119815 | AH37: =+AH33+AH35 -> 158826 | AI37: =+AI33+AI35 -> 171868.43 | AJ37: =+AJ33+AJ35 -> 215766.33 | ... AM37: =+AM33+AM35 -> 368397.19
B38: =+B37/B$19 -> 0.27839614 | C38: =+C37/C$19 -> 0.27285643 | D38: =+D37/D$19 -> 0.23494761 | E38: =+E37/E$19 -> 0.22547602 | F38: =+F37/F$19 -> 0.2608652 | G38: =+G37/G$19 -> 0.29359016 | H38: =+H37/H$19 -> 0.27638768 | I38: =+I37/I$19 -> 0.28284092 | ... U38: =+U37/U$19 -> 0.32955244 | AC38: =+AC37/AC$19 -> 0.26342404 | AD38: =+AD37/AD$19 -> 0.35217768 | AE38: =+AE37/AE$19 -> 0.25218855 | AF38: =+AF37/AF$19 -> 0.2788506 | AG38: =+AG37/AG$19 -> 0.34231097 | AH38: =+AH37/AH$19 -> 0.39426963 | AI38: =+AI37/AI$19 -> 0.35553847 | AJ38: =+AJ37/AJ$19 -> 0.37826151 | ... AM38: =+AM37/AM$19 -> 0.42468224
A39: Taxes | B39: 2498 | C39: 3012 | D39: 2323 | E39: 3523 | F39: 3154 | G39: 3535 | H39: 1508 | I39: 3725 | J39: 4653 | K39: 3932 | L39: 5405 | M39: 5707 | N39: 7249 | O39: 5737 | P39: 9008 | Q39: 4662 | R39: 14834 | S39: 26560 | T39: =+T37*P59 -> 8120.458 | U39: =+U37*Q59 -> 5186.0698 | AC39: 7813 | AD39: 14701 | AE39: =SUM(B39:E39) -> 11356 | AF39: =SUM(F39:I39) -> 11922 | AG39: =SUM(J39:M39) -> 19697 | AH39: =SUM(N39:Q39) -> 26656 | AI39: =+AI37*0.15 -> 25780.265 | AJ39: =+AJ37*0.15 -> 32364.95 | AK39: =+AK37*0.15 -> 39318.546 | AL39: =+AL37*0.15 -> 46974.458 | AM39: =+AM37*0.15 -> 55259.578
B40: =+B39/B$19 -> 0.036729353 | C40: =+C39/C$19 -> 0.043223075 | D40: =+D39/D$19 -> 0.033621838 | E40: =+E39/E$19 -> 0.046326005 | F40: =+F39/F$19 -> 0.045194664 | G40: =+G39/G$19 -> 0.047383518 | H40: =+H39/H$19 -> 0.019662811 | I40: =+I39/I$19 -> 0.043158383 | ... U40: =+U39/U$19 -> 0.039276363 | AC40: =+AC39/AC$19 -> 0.042804626 | AD40: =+AD39/AD$19 -> 0.057060904 | AE40: =+AE39/AE$19 -> 0.040150476 | AF40: =+AF39/AF$19 -> 0.038784101 | AG40: =+AG39/AG$19 -> 0.056274249 | AH40: =+AH39/AH$19 -> 0.066170849 | AI40: =+AI39/AI$19 -> 0.05333077 | AJ40: =+AJ39/AJ$19 -> 0.056739227 | ... AM40: =+AM39/AM$19 -> 0.063702335
A41: Net Income | B41: =+B37-B39 -> 16436 | C41: =+C37-C39 -> 16002 | D41: =+D37-D39 -> 13910 | E41: =+E37-E39 -> 13624 | F41: =+F37-F39 -> 15051 | G41: =+G37-G39 -> 18368 | H41: =+H37-H39 -> 19689 | I41: =+I37-I39 -> 20687 | ... U41: =+U37-U39 -> 38328.193 | AC41: =+AC37-AC39 -> 40269 | AD41: =+AD37-AD39 -> 76033 | AE41: =+AE37-AE39 -> 59972 | AF41: =+AF37-AF39 -> 73795 | AG41: =+AG37-AG39 -> 100118 | AH41: =+AH37-AH39 -> 132170 | AI41: =+AI37-AI39 -> 146088.17 | AJ41: =+AJ37-AJ39 -> 183401.38 | ... AM41: =+AM37-AM39 -> 313137.61 | AN41: =+AM41*(1+$AQ$57) -> 319400.36 | AO41: =+AN41*(1+$AQ$57) -> 325788.37 | AP41: =+AO41*(1+$AQ$57) -> 332304.14 | AQ41: =+AP41*(1+$AQ$57) -> 338950.22 | AR41: =+AQ41*(1+$AQ$57) -> 345729.22 | AS41: =+AR41*(1+$AQ$57) -> 352643.81 | AT41: =+AS41*(1+$AQ$57) -> 359696.68 | AU41: =+AT41*(1+$AQ$57) -> 366890.62 | ... DH41: =+DG41*(1+$AQ$57) -> 1329069.7
B42: =+B41/B$19 -> 0.24166679 | C42: =+C41/C$19 -> 0.22963335 | D42: =+D41/D$19 -> 0.20132577 | E42: =+E41/E$19 -> 0.17915001 | F42: =+F41/F$19 -> 0.21567054 | G42: =+G41/G$19 -> 0.24620664 | H42: =+H41/H$19 -> 0.25672486 | I42: =+I41/I$19 -> 0.23968254 | ... U42: =+U41/U$19 -> 0.29027608 | AC42: =+AC41/AC$19 -> 0.22061942 | AD42: =+AD41/AD$19 -> 0.29511677 | AE42: =+AE41/AE$19 -> 0.21203807 | AF42: =+AF41/AF$19 -> 0.24006649 | AG42: =+AG41/AG$19 -> 0.28603672 | AH42: =+AH41/AH$19 -> 0.32809878 | AI42: =+AI41/AI$19 -> 0.3022077 | AJ42: =+AJ41/AJ$19 -> 0.32152228 | ... AM42: =+AM41/AM$19 -> 0.3609799
A43: Preferred Stock Dividend | B43: 0 | C43: 0 | D43: 0 | E43: 0 | F43: 0 | G43: 0 | H43: 0 | I43: 0 | J43: 0 | K43: 0 | L43: 0 | M43: 0 | N43: 0 | O43: 0 | P43: 0 | Q43: 0 | R43: 0 | S43: 86 | AC43: 0 | AD43: 0 | AE43: 0 | AF43: 0 | AG43: 0 | AH43: 0
A45: NI Common Shareholder | B45: =+B41-B43 -> 16436 | C45: =+C41-C43 -> 16002 | D45: =+D41-D43 -> 13910 | E45: =+E41-E43 -> 13624 | F45: =+F41-F43 -> 15051 | G45: =+G41-G43 -> 18368 | H45: =+H41-H43 -> 19689 | I45: =+I41-I43 -> 20687 | ... U45: =+U41-U43 -> 38328.193 | AC45: =+AC41-AC43 -> 40269 | AD45: =+AD41-AD43 -> 76033 | AE45: =+AE41-AE43 -> 59972 | AF45: =+AF41-AF43 -> 73795 | AG45: =+AG41-AG43 -> 100118 | AH45: =+AH41-AH43 -> 132170 | AI45: =+AI41-AI43 -> 146088.17 | AJ45: =+AJ41-AJ43 -> 183401.38 | ... AM45: =+AM41-AM43 -> 313137.61
F46: =F45/B45-1 -> -0.084266245 | G46: =G45/C45-1 -> 0.14785652 | H46: =H45/D45-1 -> 0.41545651 | I46: =I45/E45-1 -> 0.51842337 | J46: =J45/F45-1 -> 0.57212145 | K46: =K45/G45-1 -> 0.28587761 | L46: =L45/H45-1 -> 0.33582203 | M46: =M45/I45-1 -> 0.28273795 | ... U46: =U45/Q45-1 -> 0.11241309
A47: EPS | B47: =B41/B49 -> 1.2310688 | C47: =C41/C49 -> 1.2087016 | D47: =D41/D49 -> 1.0620753 | E47: =E41/E49 -> 1.0522901 | F47: =F41/F49 -> 1.1737503 | G47: =G41/G49 -> 1.4390473 | H47: =H41/H49 -> 1.5508034 | I47: =I41/I49 -> 1.6415648 | ... U47: =U41/U49 -> 3.1344613 | AC47: =AC41/AC49 -> 58.613332 | AD47: =AD41/AD49 -> 112.19702 | AE47: =AE41/AE49 -> 4.5576623 | AF47: =AF41/AF49 -> 5.8009237 | AG47: =AG41/AG49 -> 8.0433831 | AH47: =AH41/AH49 -> 10.807032 | AI47: =AI41/AI49 -> 12.065724 | AJ47: =AJ41/AJ49 -> 15.300505 | ... AM47: =AM41/AM49 -> 26.92358
F48: =F47/B47-1 -> -0.046559981 | G48: =G47/C47-1 -> 0.1905729 | H48: =H47/D47-1 -> 0.46016335 | I48: =I47/E47-1 -> 0.55999265 | J48: =J47/F47-1 -> 0.60926905 | K48: =K47/G47-1 -> 0.31356077 | L48: =L47/H47-1 -> 0.36561692 | M48: =M47/I47-1 -> 0.30912404 | ... U48: =U47/Q47-1 -> 0.11241309 | AD48: =+AD47/AC47-1 -> 0.91418935 | AE48: =+AE47/AD47-1 -> -0.95937804 | AF48: =+AF47/AE47-1 -> 0.27278486 | AG48: =+AG47/AF47-1 -> 0.38656937 | AH48: =+AH47/AG47-1 -> 0.34359284 | AI48: =+AI47/AH47-1 -> 0.11646974 | AJ48: =+AJ47/AI47-1 -> 0.2680967 | AK48: =+AK47/AJ47-1 -> 0.22712078 | ... AM48: =+AM47/AL47-1 -> 0.18825757
A49: Shares | B49: 13351 | C49: 13239 | D49: 13097 | E49: 12947 | F49: 12823 | G49: 12764 | H49: 12696 | I49: 12602 | J49: 12527 | K49: 12495 | L49: 12419 | M49: 12348 | N49: 12291 | O49: 12198 | P49: 12203 | Q49: 12228 | R49: 12238 | S49: 12309 | T49: 12228 | U49: 12228 | AC49: 687.028 | AD49: 677.674 | AE49: =AVERAGE(B49:E49) -> 13158.5 | AF49: =AVERAGE(F49:I49) -> 12721.25 | AG49: =AVERAGE(J49:M49) -> 12447.25 | AH49: =AVERAGE(N49:Q49) -> 12230 | AI49: =+AH49*0.99 -> 12107.7 | AJ49: =+AI49*0.99 -> 11986.623 | AK49: =+AJ49*0.99 -> 11866.757 | AL49: =+AK49*0.99 -> 11748.089 | AM49: =+AL49*0.99 -> 11630.608
F50: =F49/B49-1 -> -0.039547599 | G50: =G49/C49-1 -> -0.035878843 | H50: =H49/D49-1 -> -0.030617699 | I50: =I49/E49-1 -> -0.0266471 | J50: =J49/F49-1 -> -0.023083522 | K50: =K49/G49-1 -> -0.021074898 | L50: =L49/H49-1 -> -0.021817895 | M50: =M49/I49-1 -> -0.020155531 | ... U50: =U49/Q49-1 -> 0 | AD50: =+AD49/AC49-1 -> -0.013615166 | AE50: =+AE49/AD49-1 -> 18.417153 | AF50: =+AF49/AE49-1 -> -0.033229471 | AG50: =+AG49/AF49-1 -> -0.021538764 | AH50: =+AH49/AG49-1 -> -0.017453654 | AI50: =+AI49/AH49-1 -> -0.01 | AJ50: =+AJ49/AI49-1 -> -0.01 | AK50: =+AK49/AJ49-1 -> -0.01 | ... AM50: =+AM49/AL49-1 -> -0.01
A52: Preferred Dividends | S52: =+S43/835 -> 0.10299401
A55: Revenue Y/Y | F55: =+F19/B19-1 -> 0.026113423 | G55: =+G19/C19-1 -> 0.070589079 | H55: =+H19/D19-1 -> 0.11001274 | I55: =+I19/E19-1 -> 0.13494109 | J55: =+J19/F19-1 -> 0.15406881 | K55: =+K19/G19-1 -> 0.13589084 | L55: =+L19/H19-1 -> 0.15092642 | M55: =+M19/I19-1 -> 0.11770363 | ... U55: =+U19/Q19-1 -> 0.16 | AD55: =+AD19/AC19-1 -> 0.41150076 | AE55: =+AE19/AD19-1 -> 0.097808156 | AF55: =+AF19/AE19-1 -> 0.086827702 | AG55: =+AG19/AF19-1 -> 0.13866243 | AH55: =+AH19/AG19-1 -> 0.15090081 | AI55: =+AI19/AH19-1 -> 0.2 | AJ55: =+AJ19/AI19-1 -> 0.18 | AK55: =+AK19/AJ19-1 -> 0.16 | ... AM55: =+AM19/AL19-1 -> 0.14
A56: Gross Margin | B56: =+B23/B19 -> 0.56479099 | C56: =+C23/C19 -> 0.56799885 | D56: =+D23/D19 -> 0.54903607 | E56: =+E23/E19 -> 0.5352672 | F56: =+F23/F19 -> 0.56135097 | G56: =+G23/G19 -> 0.57219452 | H56: =+H23/H19 -> 0.56672708 | I56: =+I23/I19 -> 0.56465068 | ... U56: =+U23/U19 -> 0.61 | AC56: =AC23/AC19 -> 0.53578375 | AD56: =AD23/AD19 -> 0.56939803 | AE56: =AE23/AE19 -> 0.55379443 | AF56: =AF23/AF19 -> 0.56625048 | AG56: =AG23/AG19 -> 0.58200435 | AH56: =AH23/AH19 -> 0.59652315 | AI56: =AI23/AI19 -> 0.61 | AJ56: =AJ23/AJ19 -> 0.615 | ... AM56: =AM23/AM19 -> 0.63
A57: Op Margin | B57: =+B33/B19 -> 0.29545221 | C57: =+C33/C19 -> 0.2791562 | D57: =+D33/D19 -> 0.24800266 | E57: =+E33/E19 -> 0.23879655 | F57: =+F33/F19 -> 0.24954504 | G57: =+G33/G19 -> 0.29271889 | H57: =+H33/H19 -> 0.27829137 | I57: =+I33/I19 -> 0.27455683 | ... U57: =+U33/U19 -> 0.30683214 | AC57: =+AC33/AC19 -> 0.22585152 | AD57: =+AD33/AD19 -> 0.30552289 | AE57: =+AE33/AE19 -> 0.26461271 | AF57: =+AF33/AF19 -> 0.2742181 | AG57: =+AG33/AG19 -> 0.32109777 | AH57: =+AH33/AH19 -> 0.32032639 | AI57: =+AI33/AI19 -> 0.35221635 | AJ57: =+AJ33/AJ19 -> 0.370324 | ... AM57: =+AM33/AM19 -> 0.40396028 | AP57: Terminal | AQ57: 0.02
A58: NI Margin | B58: =+B41/B19 -> 0.24166679 | C58: =+C41/C19 -> 0.22963335 | D58: =+D41/D19 -> 0.20132577 | E58: =+E41/E19 -> 0.17915001 | F58: =+F41/F19 -> 0.21567054 | G58: =+G41/G19 -> 0.24620664 | H58: =+H41/H19 -> 0.25672486 | I58: =+I41/I19 -> 0.23968254 | ... U58: =+U41/U19 -> 0.29027608 | AC58: =+AC41/AC19 -> 0.22061942 | AD58: =+AD41/AD19 -> 0.29511677 | AE58: =+AE41/AE19 -> 0.21203807 | AF58: =+AF41/AF19 -> 0.24006649 | AG58: =+AG41/AG19 -> 0.28603672 | AH58: =+AH41/AH19 -> 0.32809878 | AI58: =+AI41/AI19 -> 0.3022077 | AJ58: =+AJ41/AJ19 -> 0.32152228 | ... AM58: =+AM41/AM19 -> 0.3609799 | AP58: Discount | AQ58: =+Main!E18 -> 0.10946049
A59: Tax Margin | B59: =B39/B37 -> 0.13193197 | C59: =C39/C37 -> 0.15840959 | D59: =D39/D37 -> 0.14310355 | E59: =E39/E37 -> 0.20545868 | F59: =F39/F37 -> 0.17324911 | G59: =G39/G37 -> 0.16139342 | H59: =H39/H37 -> 0.071142143 | I59: =I39/I37 -> 0.15258889 | ... U59: =U39/U37 -> 0.11918092 | AC59: =AC39/AC37 -> 0.16249324 | AD59: =AD39/AD37 -> 0.16202306 | AE59: =AE39/AE37 -> 0.15920817 | AF59: =AF39/AF37 -> 0.1390856 | AG59: =AG39/AG37 -> 0.16439511 | AH59: =AH39/AH37 -> 0.16783146 | AI59: =AI39/AI37 -> 0.15 | AJ59: =AJ39/AJ37 -> 0.15 | ... AM59: =AM39/AM37 -> 0.15 | AP59: ROIC | AQ59: 0.02
A60: Rule of 40 | F60: =+F20+F57 -> 0.24954504 | G60: =+G20+G57 -> 0.29271889 | H60: =+H20+H57 -> 0.27829137 | I60: =+I20+I57 -> 0.27455683 | J60: =+J20+J57 -> 0.31626914 | K60: =+K20+K57 -> 0.32362937 | L60: =+L20+L57 -> 0.32311823 | M60: =+M20+M57 -> 0.32105651 | ... U60: =+U20+U57 -> 0.30683214 | AD60: =+AD20+AD57 -> 0.71702365 | AE60: =+AE20+AE57 -> 0.36242086 | AF60: =+AF20+AF57 -> 0.36104581 | AG60: =+AG20+AG57 -> 0.45976021 | AH60: =+AH20+AH57 -> 0.4712272 | AI60: =+AI20+AI57 -> 0.55221635 | AJ60: =+AJ20+AJ57 -> 0.550324 | AK60: =+AK20+AK57 -> 0.5437611 | ... AM60: =+AM20+AM57 -> 0.54396028 | AP60: NPV | AQ60: =+NPV(AQ58,AI41:DH41) -> 2925158.9
A61: CFFO Margin | B61: =+B135/B19 -> 0.36914617 | C61: =+C135/C19 -> 0.27871134 | D61: =+D135/D19 -> 0.33799861 | E61: =+E135/E19 -> 0.31051441 | F61: =+F135/F19 -> 0.3368679 | G61: =+G135/G19 -> 0.38424213 | H61: =+H135/H19 -> 0.39972357 | I61: =+I135/I19 -> 0.21915189 | ... S61: =+S135/S19 -> 0.32612942 | AC61: =+AC135/AC19 -> 0.35679105 | AD61: =+AD135/AD19 -> 0.35574083 | AE61: =+AE135/AE19 -> 0.32349135 | AF61: =+AF135/AF19 -> 0.3309954 | AG61: =+AG135/AG19 -> 0.35797873 | AH61: =+AH135/AH19 -> 0.40888352 | AP61: Shares | AQ61: =AQ60/AH49 -> 239.17898
A62: Inc. Margin | AD62: =+(AD33-AC33)/(AD25-AC25) -> 9.3983454 | AE62: =+(AE33-AD33)/(AE25-AD25) -> -0.4877803 | AF62: =+(AF33-AE33)/(AF25-AE25) -> 1.5945672 | AG62: =+(AG33-AF33)/(AG25-AF25) -> 7.2062067 | AH62: =+(AH33-AG33)/(AH25-AG25) -> 1.4156109 | AI62: =+(AI33-AH33)/(AI25-AH25) -> 5.6236068 | AJ62: =+(AJ33-AI33)/(AJ25-AI25) -> 4.9909469 | AK62: =+(AK33-AJ33)/(AK25-AJ25) -> 4.6425086 | ... AM62: =+(AM33-AL33)/(AM25-AL25) -> 4.3270166 | AP62: Diff | AQ62: =+AQ61/Main!E1-1 -> -0.30471227
A64: ROA | C64: =+C41/AVERAGE(B97:C97) -> 0.044931705 | D64: =+D41/AVERAGE(C97:D97) -> 0.038994169 | E64: =+E41/AVERAGE(D97:E97) -> 0.037660379 | F64: =+F41/AVERAGE(E97:F97) -> 0.040968758 | G64: =+G41/AVERAGE(F97:G97) -> 0.048816334 | H64: =+H41/AVERAGE(G97:H97) -> 0.050500478 | I64: =+I41/AVERAGE(H97:I97) -> 0.051787348 | J64: =+J41/AVERAGE(I97:J97) -> 0.058456445 | ... S64: =+S41/AVERAGE(R97:S97) -> 0.13800709 | AD64: =+AD41/AVERAGE(AC97:AD97) -> 0.22399408 | AE64: =+AE41/AVERAGE(AD97:AE97) -> 0.16554686 | AF64: =+AF41/AVERAGE(AE97:AF97) -> 0.19230619 | AG64: =+AG41/AVERAGE(AF97:AG97) -> 0.23489031 | AH64: =+AH41/AVERAGE(AG97:AH97) -> 0.25282702
A65: ROE | C65: =+C41/AVERAGE(B117:C117) -> 0.062824019 | D65: =+D41/AVERAGE(C117:D117) -> 0.054651357 | E65: =+E41/AVERAGE(D117:E117) -> 0.053451557 | F65: =+F41/AVERAGE(E117:F117) -> 0.058220092 | G65: =+G41/AVERAGE(F117:G117) -> 0.069571146 | H65: =+H41/AVERAGE(G117:H117) -> 0.072875933 | I65: =+I41/AVERAGE(H117:I117) -> 0.074335991 | J65: =+J41/AVERAGE(I117:J117) -> 0.082127926 | ... S65: =+S41/AVERAGE(R117:S117) -> 0.20048319 | AD65: =+AD41/AVERAGE(AC117:AD117) -> 0.32069324 | AE65: =+AE41/AVERAGE(AD117:AE117) -> 0.236213 | AF65: =+AF41/AVERAGE(AE117:AF117) -> 0.27355646 | AG65: =+AG41/AVERAGE(AF117:AG117) -> 0.32908492 | AH65: =+AH41/AVERAGE(AG117:AH117) -> 0.35704782
A66: A. Turnover | C66: =+C19/AVERAGE(B97:C97) -> 0.19566716 | D66: =+D19/AVERAGE(C97:D97) -> 0.19368693 | E66: =+E19/AVERAGE(D97:E97) -> 0.21021701 | F66: =+F19/AVERAGE(E97:F97) -> 0.18995992 | G66: =+G19/AVERAGE(F97:G97) -> 0.19827383 | H66: =+H19/AVERAGE(G97:H97) -> 0.19671051 | I66: =+I19/AVERAGE(H97:I97) -> 0.21606642 | J66: =+J19/AVERAGE(I97:J97) -> 0.19896981 | ... S66: =+S19/AVERAGE(R97:S97) -> 0.14735943 | AD66: =+AD19/AVERAGE(AC97:AD97) -> 0.75900154 | AE66: =+AE19/AVERAGE(AD97:AE97) -> 0.78074122 | AF66: =+AF19/AVERAGE(AE97:AF97) -> 0.80105385 | AG66: =+AG19/AVERAGE(AF97:AG97) -> 0.82118935 | AH66: =+AH19/AVERAGE(AG97:AH97) -> 0.77058201
A67: Financial Leverage | C67: =+AVERAGE(B97:C97)/AVERAGE(B117:C117) -> 1.3982113 | D67: =+AVERAGE(C97:D97)/AVERAGE(C117:D117) -> 1.4015264 | E67: =+AVERAGE(D97:E97)/AVERAGE(D117:E117) -> 1.4193048 | F67: =+AVERAGE(E97:F97)/AVERAGE(E117:F117) -> 1.4210851 | G67: =+AVERAGE(F97:G97)/AVERAGE(F117:G117) -> 1.4251612 | H67: =+AVERAGE(G97:H97)/AVERAGE(G117:H117) -> 1.4430741 | I67: =+AVERAGE(H97:I97)/AVERAGE(H117:I117) -> 1.4354083 | J67: =+AVERAGE(I97:J97)/AVERAGE(I117:J117) -> 1.4049422 | ... S67: =+AVERAGE(R97:S97)/AVERAGE(R117:S117) -> 1.4527021 | AD67: =+AVERAGE(AC97:AD97)/AVERAGE(AC117:AD117) -> 1.4317041 | AE67: =+AVERAGE(AD97:AE97)/AVERAGE(AD117:AE117) -> 1.4268648 | AF67: =+AVERAGE(AE97:AF97)/AVERAGE(AE117:AF117) -> 1.4225047 | AG67: =+AVERAGE(AF97:AG97)/AVERAGE(AF117:AG117) -> 1.4010153 | AH67: =+AVERAGE(AG97:AH97)/AVERAGE(AG117:AH117) -> 1.4122218
A68: Financial Leverage % | C68: =+C65-C64 -> 0.017892313 | D68: =+D65-D64 -> 0.015657188 | E68: =+E65-E64 -> 0.015791177 | F68: =+F65-F64 -> 0.017251334 | G68: =+G65-G64 -> 0.020754812 | H68: =+H65-H64 -> 0.022375455 | I68: =+I65-I64 -> 0.022548642 | J68: =+J65-J64 -> 0.023671481 | ... S68: =+S65-S64 -> 0.062476103 | AD68: =+AD65-AD64 -> 0.096699156 | AE68: =+AE65-AE64 -> 0.070666135 | AF68: =+AF65-AF64 -> 0.081250267 | AG68: =+AG65-AG64 -> 0.094194617 | AH68: =+AH65-AH64 -> 0.10422081
A70: EBITDA | AC70: =+AC33+AC122 -> 54921 | AD70: =+AD33+AD122 -> 91155 | AE70: =+AE33+AE122 -> 90171 | AF70: =+AF33+AF122 -> 96812 | AG70: =+AG33+AG122 -> 127701 | AH70: =+AH33+AH122 -> 150175 | AI70: =+AI33+AI122 -> 194568.91 | AJ70: =+AJ33+AJ122 -> 239191.01 | ... AM70: =+AM33+AM122 -> 392933.65
A71: Adj. EBITDA | B71: =+B37+B122+B125+B126 -> 22063 | C71: =+C37+C122+C125+C126 -> 21807 | D71: =+D37+D122+D125+D126 -> 19737 | E71: =+E37+E122+E125+E126 -> 20488 | F71: =+F37+F122+F125+F126 -> 18902 | G71: =+G37+G122+G125+G126 -> 23394 | H71: =+H37+H122+H125+H126 -> 23413 | I71: =+I37+I122+I125+I126 -> 25587 | ... S71: =+S37+S122+S125+S126 -> 67476 | AC71: =+AC37+AC122+AC125+AC126 -> 56852 | AD71: =+AD37+AD122+AD125+AD126 -> 92713 | AE71: =+AE37+AE122+AE125+AE126 -> 84095 | AF71: =+AF37+AF122+AF125+AF126 -> 91296 | AG71: =+AG37+AG122+AG125+AG126 -> 127198 | AH71: =+AH37+AH122+AH125+AH126 -> 163690
AD72: =+AD71/AC71-1 -> 0.63077816 | AE72: =+AE71/AD71-1 -> -0.092953523 | AF72: =+AF71/AE71-1 -> 0.085629348 | AG72: =+AG71/AF71-1 -> 0.39324834 | AH72: =+AH71/AG71-1 -> 0.2868913
A74: Backlog (B) | B74: 50.5 | C74: 51.2 | D74: 52.4 | E74: 59.3 | F74: 61.7 | G74: 60.6 | H74: 64.9 | I74: 74.1 | J74: 72.5 | K74: 78.8 | L74: 86.8 | M74: 93.2 | N74: 92.4 | O74: 108.2 | P74: 155 | Q74: 240 | R74: 460 | S74: 519.5 | AD74: 51 | AE74: 64.3 | AF74: 74.1 | AG74: 93.2 | AH74: 242.8
A75: Y/Y | F75: =+F74/B74-1 -> 0.22178218 | G75: =+G74/C74-1 -> 0.18359375 | H75: =+H74/D74-1 -> 0.23854962 | I75: =+I74/E74-1 -> 0.24957841 | J75: =+J74/F74-1 -> 0.17504052 | K75: =+K74/G74-1 -> 0.30033003 | L75: =+L74/H74-1 -> 0.33744222 | M75: =+M74/I74-1 -> 0.25775978 | ... S75: =+S74/O74-1 -> 3.8012939 | AE75: =+AE74/AD74-1 -> 0.26078431 | AF75: =+AF74/AE74-1 -> 0.15241058 | AG75: =+AG74/AF74-1 -> 0.25775978 | AH75: =+AH74/AG74-1 -> 1.6051502
A76: q/q | C76: =+C74/B74-1 -> 0.013861386 | D76: =+D74/C74-1 -> 0.0234375 | E76: =+E74/D74-1 -> 0.13167939 | F76: =+F74/E74-1 -> 0.040472175 | G76: =+G74/F74-1 -> -0.017828201 | H76: =+H74/G74-1 -> 0.070957096 | I76: =+I74/H74-1 -> 0.14175655 | J76: =+J74/I74-1 -> -0.021592443 | ... S76: =+S74/R74-1 -> 0.12934783
A78: TAC | B78: 11990 | C78: 12214 | D78: 11826 | E78: 12925 | F78: 11721 | G78: 12537 | H78: 12642 | I78: 13986 | J78: 12946 | K78: 13387 | L78: 13719 | M78: 14848 | N78: 13748 | O78: 14705 | P78: 14876 | Q78: 16597 | R78: 15228 | S78: 16179 | AC78: 32778 | AD78: 45566 | AE78: =SUM(B78:E78) -> 48955 | AF78: =SUM(F78:I78) -> 50886 | AG78: =SUM(J78:M78) -> 54900 | AH78: =SUM(N78:Q78) -> 59926
F79: =+F78/B78-1 -> -0.022435363 | G79: =+G78/C78-1 -> 0.026445063 | H79: =+H78/D78-1 -> 0.069000507 | I79: =+I78/E78-1 -> 0.082088975 | J79: =+J78/F78-1 -> 0.10451327 | K79: =+K78/G78-1 -> 0.067799314 | L79: =+L78/H78-1 -> 0.085192216 | M79: =+M78/I78-1 -> 0.061633062 | ... S79: =+S78/O78-1 -> 0.10023801 | AD79: =+AD78/AC78-1 -> 0.39013973 | AE79: =+AE78/AD78-1 -> 0.074375631 | AF79: =+AF78/AE78-1 -> 0.039444388 | AG79: =+AG78/AF78-1 -> 0.078882207 | AH79: =+AH78/AG78-1 -> 0.09154827
AS80: EV | AT80: =+AQ83 -> 4102251.1
A81: NOPAT | B81: =+B33*(1-B59) -> 17442.959 | C81: =+C33*(1-C59) -> 16371.458 | D81: =+D33*(1-D59) -> 14682.921 | E81: =+E33*(1-E59) -> 14428.87 | F81: =+F33*(1-F59) -> 14397.867 | G81: =+G33*(1-G59) -> 18313.491 | H81: =+H33*(1-H59) -> 19824.613 | I81: =+I33*(1-I59) -> 20081.101 | ... S81: =+S33*(1-S59) -> 32965.836 | AC81: =+AC33*(1-AC59) -> 34525.379 | AD81: =+AD33*(1-AD59) -> 65960.517 | AE81: =+AE33*(1-AE59) -> 62926.543 | AF81: =+AF33*(1-AF59) -> 72569.058 | AG81: =+AG33*(1-AG59) -> 93913.634 | AH81: =+AH33*(1-AH59) -> 107382.2 | AI81: =+AI33*(1-AI59) -> 144723.14 | AJ81: =+AJ33*(1-AJ59) -> 179552.85 | ... AM81: =+AM33*(1-AM59) -> 297858.36 | AP81: Terminal | AQ81: 0.02 | AS81: Cash | AT81: =+Main!E8 -> 242474
A82: NWC | AC82: =+AC90-(AC99+AC100+AC102+AC104+AC106) -> -24900 | AD82: =+AD90-(AD99+AD100+AD102+AD104+AD106) -> -24677 | AE82: =+AE90-(AE99+AE100+AE102+AE104+AE106) -> -29042 | AF82: =+AF90-(AF99+AF100+AF102+AF104+AF106) -> -33850 | AG82: =+AG90-(AG99+AG100+AG102+AG104+AG106) -> -36782 | AH82: =+AH90-(AH99+AH100+AH102+AH104+AH106) -> 10141 | AI82: =+AI90-(AI99+AI100+AI102+AI104+AI106) -> 11161.202 | AJ82: =+AJ90-(AJ99+AJ100+AJ102+AJ104+AJ106) -> 15130.082 | ... AM82: =+AM90-(AM99+AM100+AM102+AM104+AM106) -> 27305.328 | AP82: Discount | AQ82: =+Main!E18 -> 0.10946049 | AS82: Debt | AT82: =+Main!E9 -> 98165
A83: UFCF | AE83: =+AE81+AE122-AE137-(AE82-AD82) -> 51135.543 | AF83: =+AF81+AF122-AF137-(AF82-AE82) -> 57645.058 | AG83: =+AG81+AG122-AG137-(AG82-AF82) -> 59621.634 | AH83: =+AH81+AH122-AH137-(AH82-AG82) -> -9851.8042 | AI83: =+AI81+AI122-AI137-(AI82-AH82) -> -14884.667 | AJ83: =+AJ81+AJ122-AJ137-(AJ82-AI82) -> 20642.333 | AK83: =+AK81+AK122-AK137-(AK82-AJ82) -> 134196.63 | AL83: =+AL81+AL122-AL137-(AL82-AK82) -> 189510.5 | AM83: =+AM81+AM122-AM137-(AM82-AL82) -> 227735.33 | AP83: EV | AQ83: =+NPV(AQ82,AI83:AL83,AM83+AR84) -> 4102251.1 | AS83: Pr. Shares | AT83: =+Main!E10 -> 18023
AP84: TV | AQ84: =+AM83*(1+AQ81)/(AQ82-AQ81) -> 2596565.7 | AR84: =+AM70*16 -> 6286938.4 | AS84: Equity Value | AT84: =+AT80+AT81-AT82-AT83 -> 4228537.1
AP85: Diff | AQ85: =+AQ83/Main!E11-1 -> 0.087701531 | AR85: =+AM70*29 -> 11395076 | AS85: Shares | AT85: =+SUM(Main!E4:E6) -> 12230
A86: Net Cash | B86: =+B88+B89-B108 -> 119179 | C86: =+C88+C89-C108 -> 110263 | D86: =+D88+D89-D108 -> 101606 | E86: =+E88+E89-E108 -> 99061 | F86: =+F88+F89-F108 -> 101405 | G86: =+G88+G89-G108 -> 104627 | H86: =+H88+H89-H108 -> 106154 | I86: =+I88+I89-I108 -> 98864 | ... T86: =+T88+T89-T108 -> 0 | AC86: =+AC88+AC89-AC108 -> 122762 | AD86: =+AD88+AD89-AD108 -> 124832 | AE86: =+AE88+AE89-AE108 -> 99061 | AF86: =+AF88+AF89-AF108 -> 98864 | AG86: =+AG88+AG89-AG108 -> 84774 | AH86: =+AH88+AH89-AH108 -> 80296 | AI86: =+AH86+AI41 -> 226384.17 | AJ86: =+AI86+AJ41 -> 409785.55 | AK86: =+AJ86+AK41 -> 632590.64 | AL86: =+AK86+AL41 -> 898779.24 | AM86: =+AL86+AM41 -> 1211916.8 | AS86: Price | AT86: =+AT84/AT85 -> 345.75119
AT87: =+AT86/Main!E1-1 -> 0.0050906785
A88: Cash | B88: 20886 | C88: 17936 | D88: 21984 | E88: 21879 | F88: 25924 | G88: 25929 | H88: 30702 | I88: 24048 | J88: 24493 | K88: 27225 | L88: 19959 | M88: 23466 | N88: 23264 | O88: 21036 | P88: 23090 | Q88: 30708 | R88: 38063 | S88: 55911 | AC88: 26465 | AD88: 20945 | AE88: 21879 | AF88: 24048 | AG88: 23466 | AH88: 30708
A89: Mrk. Securities | B89: 113084 | C89: 107061 | D89: 94275 | E89: 91883 | F89: 89178 | G89: 92403 | H89: 89233 | I89: 86686 | J89: 83597 | K89: 73500 | L89: 73271 | M89: 72191 | N89: 72064 | O89: 74112 | P89: 75406 | Q89: 96135 | R89: 88777 | S89: 186563 | AC89: 110229 | AD89: 118704 | AE89: 91883 | AF89: 86686 | AG89: 72191 | AH89: 96135
A90: A/R | B90: 34703 | C90: 35707 | D90: 34697 | E90: 40258 | F90: 36036 | G90: 38804 | H90: 41020 | I90: 47964 | J90: 44552 | K90: 47087 | L90: 49104 | M90: 52340 | N90: 51000 | O90: 55048 | P90: 57148 | Q90: 62886 | R90: 62999 | S90: 69175 | AC90: 30930 | AD90: 39304 | AE90: 40258 | AF90: 47964 | AG90: 52340 | AH90: 62886 | AI90: =+(AI143*AI19)/365 -> 69797.796 | AJ90: =+(AJ143*AJ19)/365 -> 83142.791 | AK90: =+(AK143*AK19)/365 -> 97352.052 | AL90: =+(AL143*AL19)/365 -> 112997.24 | AM90: =+(AM143*AM19)/365 -> 130005.16
A91: Non Mrk. Sec. | B91: 30544 | C91: 30665 | D91: 30419 | E91: 30492 | F91: 31213 | G91: 31224 | H91: 30907 | I91: 31008 | J91: 33994 | K91: 34172 | L91: 36177 | M91: 37982 | N91: 51029 | O91: 52574 | P91: 63800 | Q91: 68687 | R91: 106946 | S91: 131461 | AC91: 20703 | AD91: 29549 | AE91: 30492 | AF91: 31008 | AG91: 37982 | AH91: 68687
A92: D/T | B92: 0 | C92: 0 | D92: 0 | E92: 5261 | F92: 6885 | G92: 9357 | H92: 10983 | I92: 12169 | J92: 0 | K92: 14958 | L92: 15915 | M92: 17180 | N92: 18386 | O92: 19289 | P92: 10331 | Q92: 9113 | R92: 1995 | S92: 1448 | AC92: 0 | AD92: 0 | AE92: 5261 | AF92: 12169 | AG92: 17180 | AH92: 9113
A93: PP&E | B93: 104218 | C93: 106223 | D93: 108363 | E93: 112668 | F93: 117560 | G93: 121208 | H93: 125705 | I93: 134345 | J93: 143182 | K93: 151155 | L93: 161270 | M93: 171036 | N93: 185062 | O93: 203231 | P93: 223787 | Q93: 246597 | R93: 281020 | S93: 321212 | AC93: 84749 | AD93: 97599 | AE93: 112668 | AF93: 134345 | AG93: 171036 | AH93: 246597
A94: Op Lease | B94: 12992 | C94: 13398 | D94: 13677 | E94: 14381 | F94: 14447 | G94: 14469 | H94: 14199 | I94: 14091 | J94: 13768 | K94: 13606 | L94: 13561 | M94: 13588 | N94: 13722 | O94: 14255 | P94: 14524 | Q94: 15221 | R94: 15509 | S94: 17694 | AC94: 12211 | AD94: 12959 | AE94: 14381 | AF94: 14091 | AG94: 13588 | AH94: 15221
A95: Goodwill and Int | B95: 23010 | C95: 23949 | D95: 28834 | E95: 28960 | F95: 28994 | G95: 29210 | H95: 29146 | I95: 29198 | J95: 29183 | K95: 29185 | L95: 31935 | M95: 31885 | N95: 32173 | O95: 32885 | P95: 33269 | Q95: 33380 | R95: =+57774+9444 -> 67218 | S95: =+57828+9105 -> 66933 | AC95: 21175 | AD95: 22956 | AE95: 28960 | AF95: 29198 | AG95: 31885 | AH95: 33380
A96: Other Assets | B96: =+5778+1388+1369+6892+919+1313 -> 17659 | C96: =+5712+1377+8321+1980+1366+1490 -> 20246 | D96: =+5670+2192+2991+10518+3156+1479 -> 26006 | E96: =+8707+10775 -> 19482 | F96: =+6439+1968+2315+8532 -> 19254 | G96: =+6822+1966+9421+2231 -> 20440 | H96: =+7628+1833+12398+2957 -> 24816 | I96: =+10051+12650 -> 22701 | J96: =+10065+12829+11687 -> 34581 | K96: =+9699+14183 -> 23882 | L96: =+13867+15207 -> 29074 | M96: =+14874+15714 -> 30588 | N96: =+15724+12950 -> 28674 | O96: =+16020+14153 -> 30173 | P96: =+16811+18303 -> 35114 | Q96: =+16245+16309 -> 32554 | R96: =+17478+23914 -> 41392 | S96: =+39711+21884+9991 -> 71586 | AC96: =+3953+1445+1084+5490+728+454 -> 13154 | AD96: =+5361+1417+1284+7054+1170+966 -> 17252 | AE96: =+8707+10775 -> 19482 | AF96: =+10051+12650 -> 22701 | AG96: =+14874+15714 -> 30588 | AH96: =+16245+16309 -> 32554
A97: A | B97: =SUM(B88:B96) -> 357096 | C97: =SUM(C88:C96) -> 355185 | D97: =SUM(D88:D96) -> 358255 | E97: =SUM(E88:E96) -> 365264 | F97: =SUM(F88:F96) -> 369491 | G97: =SUM(G88:G96) -> 383044 | H97: =SUM(H88:H96) -> 396711 | I97: =SUM(I88:I96) -> 402210 | ... T97: =SUM(T88:T96) -> 0 | AC97: =SUM(AC88:AC96) -> 319616 | AD97: =SUM(AD88:AD96) -> 359268 | AE97: =SUM(AE88:AE96) -> 365264 | AF97: =SUM(AF88:AF96) -> 402210 | AG97: =SUM(AG88:AG96) -> 450256 | AH97: =SUM(AH88:AH96) -> 595281
A99: A/P | B99: 3436 | C99: 4409 | D99: 6303 | E99: 5128 | F99: 4184 | G99: 5313 | H99: 5803 | I99: 7493 | J99: 6198 | K99: 6092 | L99: 7049 | M99: 7987 | N99: 8497 | O99: 8347 | P99: 10546 | Q99: 12200 | R99: 16852 | S99: 20258 | AC99: 5589 | AD99: 6037 | AE99: 5128 | AF99: 7493 | AG99: 7987 | AH99: 12200 | AI99: =+(AI144*AI21)/365 -> 12224.144 | AJ99: =+(AJ144*AJ21)/365 -> 14841.232 | AK99: =+(AK144*AK21)/365 -> 17681.121 | AL99: =+(AL144*AL21)/365 -> 20847.529 | AM99: =+(AM144*AM21)/365 -> 24328.649
A100: Accr. Compensations | B100: 9803 | C100: 10852 | D100: 12366 | E100: 14028 | F100: 9954 | G100: 11260 | H100: 12562 | I100: 15140 | J100: 9703 | K100: 11373 | L100: 12908 | M100: 15069 | N100: 9984 | O100: 12168 | P100: 13944 | Q100: 17546 | R100: 13947 | S100: 15086 | AC100: 11086 | AD100: 13889 | AE100: 14028 | AF100: 15140 | AG100: 15069 | AH100: 17546 | AI100: =+AH100*1.15 -> 20177.9 | AJ100: =+AI100*1.15 -> 23204.585 | AK100: =+AJ100*1.15 -> 26685.273 | AL100: =+AK100*1.15 -> 30688.064 | AM100: =+AL100*1.15 -> 35291.273
F101: =+F100/B100-1 -> 0.015403448 | G101: =+G100/C100-1 -> 0.037596756 | H101: =+H100/D100-1 -> 0.015849911 | I101: =+I100/E100-1 -> 0.079270031 | J101: =+J100/F100-1 -> -0.025215994 | K101: =+K100/G100-1 -> 0.010035524 | L101: =+L100/H100-1 -> 0.027543385 | M101: =+M100/I100-1 -> -0.0046895641 | ... S101: =+S100/O100-1 -> 0.23980934 | AD101: =AD100/AC100-1 -> 0.25284142 | AE101: =AE100/AD100-1 -> 0.01000792 | AF101: =AF100/AE100-1 -> 0.079270031 | AG101: =AG100/AF100-1 -> -0.0046895641 | AH101: =AH100/AG100-1 -> 0.1643772 | AI101: =AI100/AH100-1 -> 0.15 | AJ101: =AJ100/AI100-1 -> 0.15 | AK101: =AK100/AJ100-1 -> 0.15 | ... AM101: =AM100/AL100-1 -> 0.15
A102: Accr. Exp | B102: 33051 | C102: 32976 | D102: 35038 | E102: 37866 | F102: 43185 | G102: 49300 | H102: 55602 | I102: 46168 | J102: 48603 | K102: 47298 | L102: 46585 | M102: 51228 | N102: 58300 | O102: 52039 | P102: 59437 | Q102: 5557 | R102: 63019 | S102: 73014 | AC102: 28631 | AD102: 31236 | AE102: 37866 | AF102: 46168 | AG102: 51228 | AH102: 5557 | AI102: =+AH102*1.15 -> 6390.55 | AJ102: =+AI102*1.15 -> 7349.1325 | AK102: =+AJ102*1.15 -> 8451.5024 | AL102: =+AK102*1.15 -> 9719.2277 | AM102: =+AL102*1.15 -> 11177.112
F103: =+F102/B102-1 -> 0.30661705 | G103: =+G102/C102-1 -> 0.49502669 | H103: =+H102/D102-1 -> 0.58690565 | I103: =+I102/E102-1 -> 0.21924682 | J103: =+J102/F102-1 -> 0.12546023 | K103: =+K102/G102-1 -> -0.040608519 | L103: =+L102/H102-1 -> -0.16217043 | M103: =+M102/I102-1 -> 0.10959972 | ... S103: =+S102/O102-1 -> 0.40306309 | AD103: =AD102/AC102-1 -> 0.090985296 | AE103: =AE102/AD102-1 -> 0.21225509 | AF103: =AF102/AE102-1 -> 0.21924682 | AG103: =AG102/AF102-1 -> 0.10959972 | AH103: =AH102/AG102-1 -> -0.89152417 | AI103: =AI102/AH102-1 -> 0.15 | AJ103: =AJ102/AI102-1 -> 0.15 | AK103: =AK102/AJ102-1 -> 0.15 | ... AM103: =AM102/AL102-1 -> 0.15
A104: Accr. Revenue share | B104: 8116 | C104: 7889 | D104: 7662 | E104: 8370 | F104: 7816 | G104: 7990 | H104: 8025 | I104: 8876 | J104: 8520 | K104: 8899 | L104: 9365 | M104: 9802 | N104: 9965 | O104: 9787 | P104: 10081 | Q104: 10864 | R104: 10208 | S104: 10599 | AC104: 7500 | AD104: 8996 | AE104: 8370 | AF104: 8876 | AG104: 9802 | AH104: 10864 | AI104: =+AH104*1.1 -> 11950.4 | AJ104: =+AI104*1.1 -> 13145.44 | AK104: =+AJ104*1.1 -> 14459.984 | AL104: =+AK104*1.1 -> 15905.982 | AM104: =+AL104*1.1 -> 17496.581
F105: =+F104/B104-1 -> -0.036964022 | G105: =+G104/C104-1 -> 0.012802637 | H105: =+H104/D104-1 -> 0.047376664 | I105: =+I104/E104-1 -> 0.060454002 | J105: =+J104/F104-1 -> 0.090071648 | K105: =+K104/G104-1 -> 0.11376721 | L105: =+L104/H104-1 -> 0.16697819 | M105: =+M104/I104-1 -> 0.10432627 | ... S105: =+S104/O104-1 -> 0.082967201 | AD105: =AD104/AC104-1 -> 0.19946667 | AE105: =AE104/AD104-1 -> -0.069586483 | AF105: =AF104/AE104-1 -> 0.060454002 | AG105: =AG104/AF104-1 -> 0.10432627 | AH105: =AH104/AG104-1 -> 0.10834524 | AI105: =AI104/AH104-1 -> 0.1 | AJ105: =AJ104/AI104-1 -> 0.1 | AK105: =AK104/AJ104-1 -> 0.1 | ... AM105: =AM104/AL104-1 -> 0.1
A106: D/R | B106: =+499+3198 -> 3697 | C106: =+472+3272 -> 3744 | D106: =+594+3585 -> 4179 | E106: 3908 | F106: 3715 | G106: 3846 | H106: 4303 | I106: 4137 | J106: 3973 | K106: 4251 | L106: =+1015+4896 -> 5911 | M106: 5036 | N106: 4908 | O106: 4969 | P106: 5542 | Q106: 6578 | R106: 7162 | S106: 7154 | AC106: =+481+2543 -> 3024 | AD106: =+535+3288 -> 3823 | AE106: 3908 | AF106: 4137 | AG106: 5036 | AH106: 6578 | AI106: =+AH106*1.2 -> 7893.6 | AJ106: =+AI106*1.2 -> 9472.32 | AK106: =+AJ106*1.15 -> 10893.168 | AL106: =+AK106*1.15 -> 12527.143 | AM106: =+AL106*1.15 -> 14406.215
F107: =+F106/B106-1 -> 0.0048688126 | G107: =+G106/C106-1 -> 0.02724359 | H107: =+H106/D106-1 -> 0.02967217 | I107: =+I106/E106-1 -> 0.058597748 | J107: =+J106/F106-1 -> 0.069448183 | K107: =+K106/G106-1 -> 0.10530421 | L107: =+L106/H106-1 -> 0.37369277 | M107: =+M106/I106-1 -> 0.21730723 | ... S107: =+S106/O106-1 -> 0.4397263 | AD107: =AD106/AC106-1 -> 0.26421958 | AE107: =AE106/AD106-1 -> 0.022233848 | AF107: =AF106/AE106-1 -> 0.058597748 | AG107: =AG106/AF106-1 -> 0.21730723 | AH107: =AH106/AG106-1 -> 0.30619539 | AI107: =AI106/AH106-1 -> 0.2 | AJ107: =AJ106/AI106-1 -> 0.2 | AK107: =AK106/AJ106-1 -> 0.15 | ... AM107: =AM106/AL106-1 -> 0.15
A108: Debt | B108: 14791 | C108: 14734 | D108: 14653 | E108: 14701 | F108: 13697 | G108: 13705 | H108: 13781 | I108: 11870 | J108: 13228 | K108: 13238 | L108: 12297 | M108: 10883 | N108: 10886 | O108: 23607 | P108: 21607 | Q108: 46547 | R108: 77501 | S108: 98165 | AC108: 13932 | AD108: 14817 | AE108: 14701 | AF108: 11870 | AG108: 10883 | AH108: 46547
A109: Income taxes payable | B109: 9406 | C109: =+1956+8163 -> 10119 | D109: =+8572+1025 -> 9597 | E109: 9258 | F109: 9722 | G109: 8753 | H109: 8038 | I109: 8474 | J109: 9234 | K109: 7703 | L109: 8219 | M109: 8782 | N109: 9773 | O109: 10027 | P109: 10072 | Q109: 9531 | R109: 12457 | S109: 11306 | AC109: =+8849+1485 -> 10334 | AD109: =+808+9176 -> 9984 | AE109: 9258 | AF109: 8474 | AG109: 8782 | AH109: 9531
...

Sheet Bond
A1: Main
B3: isin | C3: bondType | D3: coupon | E3: couponType | F3: maturityDate | G3: callable | H3: currency | I3: seniorityLevel
B4: US02079KAC18 | C4: — | D4: 1998 | E4: Fixed Listing | F4: 15/08/2026 | G4: Y | H4: USD | I4: Senior
B5: US02079KAJ60 | C5: — | D5: 800 | E5: Fixed Listing | F5: 15/08/2027 | G5: Y | H5: USD | I5: Senior
B6: XS3226478918 | C6: — | D6: 2375 | E6: Fixed Listing | F6: 06/11/2028 | G6: Y | H6: EUR | I6: Senior
B7: US02079KAU16 | C7: — | D7: 4181 | E7: Floating Rate | F7: 15/11/2028 | G7: Y | H7: USD | I7: Senior
B8: US02079KAV98 | C8: — | D8: 3875 | E8: Fixed Listing | F8: 15/11/2028 | G8: Y | H8: USD | I8: Senior
B9: XS3285554096 | C9: — | D9: 4125 | E9: Fixed Listing | F9: 13/02/2029 | G9: Y | H9: GBP | I9: Senior
B10: US02079KBJ51 | C10: — | D10: 3700 | E10: Fixed Listing | F10: 15/02/2029 | G10: Y | H10: USD | I10: Senior
B11: CH1504033700 | C11: — | D11: 427 | E11: Fixed Listing | F11: 01/03/2029 | G11: Y | H11: CHF | I11: Senior
B12: XS3064418687 | C12: — | D12: 2500 | E12: Fixed Listing | F12: 06/05/2029 | G12: Y | H12: EUR | I12: Senior
B13: US02079KAK34 | C13: — | D13: 4000 | E13: Fixed Listing | F13: 15/05/2030 | G13: Y | H13: USD | I13: Senior
B14: US02079KAD90 | C14: Sustainable | D14: 1100 | E14: Fixed Listing | F14: 15/08/2030 | G14: Y | H14: USD | I14: Senior
B15: US02079KAW71 | C15: — | D15: 4100 | E15: Fixed Listing | F15: 15/11/2030 | G15: Y | H15: USD | I15: Senior
... B49: XS3285675040 | C49: — | D49: 6125 | E49: Fixed Listing | F49: 13/02/2126 | G49: Y | H49: GBP | I49: Senior
D50: =+AVERAGE(D4:D49) -> 3696.7174

Sheet Board
A1: Main
