Workbook

Sheet Main
A1: META | E1: Share A | F1: 2205.1285 | G1: Q226 | L1: -> | M1: 2026 Focus on AI, Reels, Youth Platform (?), Platform Support, Infrastucture Capacity (AI)
E2: Share B | F2: 342.37772 | G2: Q226
E3: Price | F3: 644 | L3: -> | M3: Dependant on the ADV market, a decrease in spending whould mean a decrease in the core business of META
E4: MC | F4: =+F3*(F2+F1) -> 1640594 | L4: -> | M4: Testing a shopping feature with their chatbot Llama. Increase In monetization
E5: Cash | F5: 90260 | G5: Q226 | M5: possible monetization of where to buy the product?
E6: Debt | F6: 83664 | G6: Q226 | L6: -> | M6: Server and Network depreciation from 3 to 5 years minimum
E7: EV | F7: =F4-F5+F6 -> 1633998 | L7: -> | M7: Dismissed the METAverse project
M8: -> | N8: Mark Zuckerberg (and the board) is willing to transform the whole business to pursue a risky project that may pay off
L9: -> | M9: California alligations agains META and GOOGL that the companies have to pay for the mental problems of those that use their platforms
M10: I wouldn’t consider this a real therat since it is not illegal to maximise the engagement of the platform’s users
M11: META and GOOGL will appeal to the sentence
A12: P/FCF | B12: =+F4/SUM(Model!P148:S148) -> 43.318989 | D12: WACC | E12: =+(F4/(F4+F6))*B17+(F6/(F4+F6))*B18*(1-0.11) -> 0.10915439 | H12: mu | I12: 0.0008 | L12: -> | M12: Mark Zuckerberg is locked in
A13: P/E | B13: =+F3/SUM(Model!P54:S54) -> 19.640087 | H13: sigma | I13: 0.0248 | M13: -> | N13: Mark has the majority of the voting power
A14: EV/EBITDA | B14: =+F7/SUM(Model!P90:S90) -> 12.403109 | D14: PEG | E14: =+B13/11.37 -> 1.7273603 | L14: -> | M14: META experimenting a subscription model on Instagram in order to have certain “premium” feature
A15: EV/FCF | B15: =+F7/SUM(Model!P148:S148) -> 43.144825 | L15: -> | M15: META to expand their partnership with broadcom from the production of meta’s MTIA
A16: Inc. Margin | B16: =+((Model!S44+Model!R44+Model!Q44+Model!P44)-(Model!O44+Model!N44+Model!M44+Model!L44))/((Model!S30+Model!R30+Model!Q30+Model!P30)-(Model!O30+Model!N30+Model!M30+Model!L30)) -> 0.16617115 | D16: FPE | E16: =+F3/Model!AO54 -> 19.150959 | M16: MTIA (Meta Training and Inference Accellerator) is e purpose-built silicon-chip in order to make training and inference (usage of ML models) of ML cheaper, faster and energy efficient.
A17: CAPM | B17: =+0.0495+1.24*(0.1-0.0495) -> 0.11212 | M17: commitment that exceeds 1GW (30B$ ca. Per GW) → Hock Tan (Broadcom CEO) to become META’s advisor in META’s BoD
A18: Cost of Debt | B18: =+0.0495 + (B19/100) -> 0.057304348 | L18: -> | M18: META to monetise MetaAI by introducing a subscription model in order to access enhanced capabilities of the AI
A19: Cr. Spread | B19: =+'[1]Credit Spread US'!J6 -> 0.78043478 | L19: -> | M19: META shifting from AI buyer to AI provider with news disclosing their intentions to become a neocloud
A20: Rating | B20: AA- | C20: Aa3 | M20: BofA disclosed memo shows that META’s CapEx spends 22B$ per GW instead of the 40B$ consensus and 30B$ my guess
B21: S&P | C21: Moody’s | L21: -> | M21: Committing from 9-25 years to purchase clean and renewable energy
A22: EV/Sales | B22: =+F7/SUM(Model!P30:S30) -> 7.1589025 | L22: -> | M22: META agreed to settle the 1.4T (200B) fine with up to 17B fine paying it in 9 years
A23: EV/DAU | B23: =+F7/Model!S16 -> 453.88834 | M23: This is an outstanding win because accounting for an 8% cost of capital it is closer to a 9B fine
M24: Secondly they passed the ball to TikTok and YouTube saying that if they do not agree META will pay only up to 70% of the fine
M25: META positions itself as proactive to child care (also given everything that they are doing for children) and now TikTok and YT will fight against this ruling
A26: Seasonality | B26: Demand historically strong during fourth quarter due to holidays demand | M26: On top of that META bought for 9B$ the legislative safety for at least 9 years for their algoroithm
A28: Family of Apps (FoA)
B29: Facebook | E29: IPO | F29: 41030
B30: Facebook Dating (?)
B31: Facebook Marketplace
B32: Instagram
B33: Messanger
B34: Whatsapp
B35: Meta AI
B36: Threads | C36: -> | D36: Fastest organic growth among all kind of ages
B37: Aveola (?) | C37: -> | D37: “Live video chat”
B38: Meta Pay
B39: -> | C39: Advertisement
B40: -> | C40: paid messaging from Whatsapp, Verified on Instagram (and further Instagram paid feature), fees from developers, …
A43: Reality Labs Products
B44: Meta Quest
B45: Software in the Meta Horizon Store
B46: Ray-Ban Meta
B47: Oakley Meta
B48: Ray-Ban Meta Display (with the wristband to control the AI)
B49: -> | C49: Selling of hardware (Ai glasses and Meta Quest)
B50: -> | C50: Selling of Software (mainly for Meta Quest)
A54: DAU | B54: (Daily Active People in META’s filings) contains only the FoA users, user that uses at least one of the FoA
A55: ARPU | B55: (Average Revenue Per Person in META’s filings) only FoA users
A58: AI Infrastructure | B58: Datacenters, 33 (28 in the USA, 3 in Europe, 1 in Asia, 1 in Canada and 1 leased in India)
A72: Revenue | B72: Q423 | C72: Q124 | D72: Q224 | E72: Q324 | F72: Q424 | G72: Q125 | H72: Q225 | I72: Q325 | J72: Q425 | K72: Q126 | L72: Q226 | M72: Q326 | N72: Q426 | P72: ADV Revenue | Q72: Q423 | R72: Q124 | S72: Q224 | T72: Q324 | U72: Q424 | V72: Q125 | W72: Q225 | X72: Q325 | Y72: Q425 | Z72: Q126
A73: US Canada | B73: 18585 | C73: 15824 | D73: 16847 | E73: 17609 | F73: 21783 | G73: 18605 | H73: 20371 | I73: 21751 | J73: 26472 | K73: 24079 | L73: 23863 | P73: US Canada | Q73: 17784 | R73: 15451 | S73: 16593 | T73: 17389 | U73: 20982 | V73: 18259 | W73: 20045 | X73: 21331 | Y73: 25643 | Z73: 23667
A74: Europe | B74: 9441 | C74: 8483 | D74: 9300 | E74: 9492 | F74: 11503 | G74: 9680 | H74: 11532 | I74: 12268 | J74: 14480 | K74: 13500 | L74: 14009 | P74: Europe | Q74: 9159 | R74: 8327 | S74: 9135 | T74: 9358 | U74: 11154 | V74: 9527 | W74: 11366 | X74: 12072 | Y74: 14198 | Z74: 13296
A75: Asia Pacific | B75: 7512 | C75: 7481 | D75: 7888 | E75: 8220 | F75: 9245 | G75: 8439 | H75: 9366 | I75: 10272 | J75: 11182 | K75: 10914 | L75: 16073 | P75: Asia Pacific | Q75: 7316 | R75: 7338 | S75: 7721 | T75: 8050 | U75: 9012 | V75: 8224 | W75: 9148 | X75: 10020 | Y75: 10893 | Z75: 10631
A76: Rest of the World | B76: 4573 | C76: 4667 | D76: 5036 | E76: 5268 | F76: 5854 | G76: 5590 | H76: 6247 | I76: 6951 | J76: 7759 | K76: 7818 | L76: 6856 | P76: Rest of the World | Q76: 4447 | R76: 4519 | S76: 4880 | T76: 5088 | U76: 5635 | V76: 5382 | W76: 6004 | X76: 6659 | Y76: 7403 | Z76: 7430
B106: -> | C106: Meta Segment Anything Model (SAM)

Sheet Model
A1: Main | B1: 03/22 | C1: 06/22 | D1: 09/22 | E1: 12/22 | F1: 03/23 | G1: 06/23 | H1: 09/23 | I1: 12/23 | J1: 03/24 | K1: 06/24 | L1: 09/24 | M1: 12/24 | N1: 03/25 | O1: 06/25 | P1: 09/25 | Q1: 12/25 | R1: 03/26 | S1: 06/26 | T1: 09/26 | U1: 12/26 | Z1: 12/10 | AA1: 12/11 | AB1: 12/12 | AC1: 12/13 | AD1: 12/14 | AE1: 12/15 | AF1: 12/16 | AG1: 12/17 | AH1: 12/18 | AI1: 12/20 | AJ1: 12/21 | AK1: 12/22 | AL1: 12/23 | AM1: 12/24 | AN1: 12/25 | AO1: 12/26 | AP1: 12/27 | AQ1: 12/28 | AR1: 12/29 | AS1: 12/30 | AT1: 12/31
A2: in Millions | B2: Q122 | C2: Q222 | D2: Q322 | E2: Q422 | F2: Q123 | G2: Q223 | H2: Q323 | I2: Q423 | J2: Q124 | K2: Q224 | L2: Q324 | M2: Q424 | N2: Q125 | O2: Q225 | P2: Q325 | Q2: Q425 | R2: Q126 | S2: Q226 | T2: Q326 | U2: Q426 | Z2: =+AA2-1 -> 2011 | AA2: =+AB2-1 -> 2012 | AB2: =+AC2-1 -> 2013 | AC2: =+AD2-1 -> 2014 | AD2: =+AE2-1 -> 2015 | AE2: =+AF2-1 -> 2016 | AF2: =+AG2-1 -> 2017 | AG2: =+AH2-1 -> 2018 | AH2: =+AI2-1 -> 2019 | AI2: 2020 | AJ2: =+AI2+1 -> 2021 | AK2: =+AJ2+1 -> 2022 | AL2: =+AK2+1 -> 2023 | AM2: =+AL2+1 -> 2024 | AN2: =+AM2+1 -> 2025 | AO2: =+AN2+1 -> 2026 | AP2: =+AO2+1 -> 2027 | AQ2: =+AP2+1 -> 2028 | ... AT2: =+AS2+1 -> 2031 | AV2: CAGR ‘26 – ‘36
A3: SNAP DAU | B3: 332 | C3: 347 | D3: 363 | E3: 375 | F3: 383 | G3: 397 | H3: 406 | I3: 414 | J3: 422 | K3: 432 | L3: 443 | M3: 453 | N3: 460 | O3: 469 | P3: 477 | Q3: 474 | R3: 483 | S3: 493 | Z3: NA | AA3: NA | AB3: NA | AC3: 71 | AD3: 107 | AE3: 158 | AF3: 187 | AG3: 186 | AH3: 218 | AI3: 265 | AJ3: 319 | AK3: 374 | AL3: 414 | AM3: 453 | AN3: 474
A4: Y/Y % | F4: =+F3/B3-1 -> 0.15361446 | G4: =+G3/C3-1 -> 0.14409222 | H4: =+H3/D3-1 -> 0.1184573 | I4: =+I3/E3-1 -> 0.104 | J4: =+J3/F3-1 -> 0.10182768 | K4: =+K3/G3-1 -> 0.088161209 | L4: =+L3/H3-1 -> 0.091133005 | M4: =+M3/I3-1 -> 0.094202899 | ... S4: =+S3/O3-1 -> 0.051172708 | AD4: =+AD3/AC3-1 -> 0.50704225 | AE4: =+AE3/AD3-1 -> 0.47663551 | AF4: =+AF3/AE3-1 -> 0.1835443 | AG4: =+AG3/AF3-1 -> -0.0053475936 | AH4: =+AH3/AG3-1 -> 0.17204301 | AI4: =+AI3/AH3-1 -> 0.21559633 | AJ4: =+AJ3/AI3-1 -> 0.20377358 | AK4: =+AK3/AJ3-1 -> 0.17241379 | ... AN4: =+AN3/AM3-1 -> 0.046357616
A5: SNAP ARPU | B5: 3.2 | C5: 3.2 | D5: 3.11 | E5: 3.47 | F5: 2.58 | G5: 2.69 | H5: 2.93 | I5: 3.29 | J5: 2.83 | K5: 2.86 | L5: 3.1 | M5: 3.44 | N5: 2.96 | O5: 2.87 | P5: 3.16 | Q5: 3.62 | R5: 3.17 | S5: 3.25 | Z5: NA | AA5: NA | AB5: NA | AC5: NA | AD5: NA | AE5: =+0.32+0.5+0.84+1.05 -> 2.71 | AF5: =+0.9+1.05+1.17+1.53 -> 4.65 | AG5: =+1.21+1.4+1.6+2.09 -> 6.3 | AH5: =+1.68+1.91+2.12+2.58 -> 8.29 | AI5: =+2.02+1.91+2.73+3.44 -> 10.1 | AJ5: 13.65 | AK5: 12.98 | AL5: 11.49 | AM5: 12.23 | AN5: 12.61
A6: Y/Y % | F6: =+F5/B5-1 -> -0.19375 | G6: =+G5/C5-1 -> -0.159375 | H6: =+H5/D5-1 -> -0.057877814 | I6: =+I5/E5-1 -> -0.051873199 | J6: =+J5/F5-1 -> 0.096899225 | K6: =+K5/G5-1 -> 0.063197026 | L6: =+L5/H5-1 -> 0.058020478 | M6: =+M5/I5-1 -> 0.045592705 | ... S6: =+S5/O5-1 -> 0.13240418 | AF6: =+AF5/AE5-1 -> 0.71586716 | AG6: =+AG5/AF5-1 -> 0.35483871 | AH6: =+AH5/AG5-1 -> 0.31587302 | AI6: =+AI5/AH5-1 -> 0.21833534 | AJ6: =+AJ5/AI5-1 -> 0.35148515 | AK6: =+AK5/AJ5-1 -> -0.049084249 | AL6: =+AL5/AK5-1 -> -0.11479199 | AM6: =+AM5/AL5-1 -> 0.064403829 | AN6: =+AN5/AM5-1 -> 0.031071137
A7: RDDT DAU | B7: NA | C7: NA | D7: NA | E7: NA | F7: 60.3 | G7: 60.4 | H7: 66 | I7: 73.1 | J7: 82.7 | K7: 91.2 | L7: 97.2 | M7: 101.7 | N7: 108.1 | O7: 110.4 | P7: 116 | Q7: 121.4 | R7: 127 | S7: 130 | Z7: NA | AA7: NA | AB7: NA | AC7: NA | AD7: NA | AE7: NA | AF7: NA | AG7: NA | AH7: NA | AI7: NA | AJ7: NA | AK7: NA | AL7: 73.1 | AM7: 101.7 | AN7: 121
A8: Y/Y % | J8: =+J7/F7-1 -> 0.37147595 | K8: =+K7/G7-1 -> 0.50993377 | L8: =+L7/H7-1 -> 0.47272727 | M8: =+M7/I7-1 -> 0.39124487 | N8: =+N7/J7-1 -> 0.30713422 | O8: =+O7/K7-1 -> 0.21052632 | P8: =+P7/L7-1 -> 0.19341564 | Q8: =+Q7/M7-1 -> 0.19370698 | ... S8: =+S7/O7-1 -> 0.17753623 | AM8: =+AM7/AL7-1 -> 0.39124487 | AN8: =+AN7/AM7-1 -> 0.18977384
A9: RDDT ARPU | B9: NA | C9: NA | D9: NA | E9: NA | F9: 2.72 | G9: 3.03 | H9: 3.14 | I9: 3.42 | J9: 2.94 | K9: 3.08 | L9: 3.58 | M9: 4.21 | N9: 3.63 | O9: 4.53 | P9: 5.04 | Q9: 5.98 | R9: 5.23 | S9: 6.18 | Z9: NA | AA9: NA | AB9: NA | AC9: NA | AD9: NA | AE9: NA | AF9: NA | AG9: NA | AH9: NA | AI9: NA | AJ9: NA | AK9: NA | AL9: 3.42 | AM9: 4.21 | AN9: 5.98
A10: Y/Y % | J10: =+J9/F9-1 -> 0.080882353 | K10: =+K9/G9-1 -> 0.01650165 | L10: =+L9/H9-1 -> 0.14012739 | M10: =+M9/I9-1 -> 0.23099415 | N10: =+N9/J9-1 -> 0.23469388 | O10: =+O9/K9-1 -> 0.47077922 | P10: =+P9/L9-1 -> 0.40782123 | Q10: =+Q9/M9-1 -> 0.42042755 | ... S10: =+S9/O9-1 -> 0.36423841 | AM10: =+AM9/AL9-1 -> 0.23099415 | AN10: =+AN9/AM9-1 -> 0.42042755
A11: PINS MAU | B11: 433 | C11: 433 | D11: 445 | E11: 450 | F11: 463 | G11: 465 | H11: 482 | I11: 498 | J11: 518 | K11: 522 | L11: 537 | M11: 553 | N11: 570 | O11: 578 | P11: 600 | Q11: 619 | R11: 631 | S11: 640 | Z11: NA | AA11: NA | AB11: NA | AC11: NA | AD11: NA | AE11: NA | AF11: NA | AG11: 265 | AH11: 335 | AI11: 459 | AJ11: 431 | AK11: 450 | AL11: 498 | AM11: 553 | AN11: 619
A12: Y/Y % | F12: =+F11/B11-1 -> 0.069284065 | G12: =+G11/C11-1 -> 0.073903002 | H12: =+H11/D11-1 -> 0.083146067 | I12: =+I11/E11-1 -> 0.10666667 | J12: =+J11/F11-1 -> 0.1187905 | K12: =+K11/G11-1 -> 0.12258065 | L12: =+L11/H11-1 -> 0.11410788 | M12: =+M11/I11-1 -> 0.11044177 | ... S12: =+S11/O11-1 -> 0.10726644 | AH12: =+AH11/AG11-1 -> 0.26415094 | AI12: =+AI11/AH11-1 -> 0.37014925 | AJ12: =+AJ11/AI11-1 -> -0.061002179 | AK12: =+AK11/AJ11-1 -> 0.044083527 | AL12: =+AL11/AK11-1 -> 0.10666667 | AM12: =+AM11/AL11-1 -> 0.11044177 | AN12: =+AN11/AM11-1 -> 0.11934901
A13: PINS ARPU | B13: 1.33 | C13: 1.54 | D13: 1.56 | E13: 1.96 | F13: 1.32 | G13: 1.53 | H13: 1.61 | I13: 2 | J13: 1.46 | K13: 1.64 | L13: 1.7 | M13: 2.12 | N13: 1.52 | O13: 1.74 | P13: 1.78 | Q13: 2.16 | R13: 1.61 | S13: 1.86 | Z13: NA | AA13: NA | AB13: NA | AC13: NA | AD13: NA | AE13: NA | AF13: NA | AG13: 1.06 | AH13: 1.22 | AI13: 1.57 | AJ13: 1.93 | AK13: 1.96 | AL13: 2 | AM13: 2.12 | AN13: 2.16
A14: Y/Y % | F14: =+F13/B13-1 -> -0.007518797 | G14: =+G13/C13-1 -> -0.0064935065 | H14: =+H13/D13-1 -> 0.032051282 | I14: =+I13/E13-1 -> 0.020408163 | J14: =+J13/F13-1 -> 0.10606061 | K14: =+K13/G13-1 -> 0.071895425 | L14: =+L13/H13-1 -> 0.055900621 | M14: =+M13/I13-1 -> 0.06 | ... S14: =+S13/O13-1 -> 0.068965517 | AH14: =+AH13/AG13-1 -> 0.1509434 | AI14: =+AI13/AH13-1 -> 0.28688525 | AJ14: =+AJ13/AI13-1 -> 0.22929936 | AK14: =+AK13/AJ13-1 -> 0.015544041 | AL14: =+AL13/AK13-1 -> 0.020408163 | AM14: =+AM13/AL13-1 -> 0.06 | AN14: =+AN13/AM13-1 -> 0.018867925
A16: DAU | B16: 2870 | C16: 2880 | D16: 2930 | E16: 2963 | F16: 3020 | G16: 3070 | H16: 3140 | I16: 3190 | J16: 3240 | K16: 3270 | L16: 3290 | M16: 3350 | N16: 3430 | O16: 3480 | P16: 3540 | Q16: 3580 | R16: 3560 | S16: 3600 | T16: =+S16*1.01 -> 3636 | U16: =+T16*1.01 -> 3672.36 | Z16: 483 | AA16: 618 | AB16: 757 | AC16: 890 | AD16: 1018 | AE16: 1227 | AF16: 1401 | AG16: 1523 | AH16: 1657 | AI16: 2540 | AJ16: 2820 | AK16: 2963 | AL16: 3190 | AM16: 3350 | AN16: 3580 | AO16: =+AN16*1.03 -> 3687.4 | AP16: =+AO16*1.04 -> 3834.896 | AQ16: =+AP16*1.04 -> 3988.2918 | AR16: =+AQ16*1.04 -> 4147.8235
A17: Y/Y % | B17: 0 | C17: 0 | D17: 0 | E17: 0 | F17: =+F16/B16-1 -> 0.052264808 | G17: =+G16/C16-1 -> 0.065972222 | H17: =+H16/D16-1 -> 0.071672355 | I17: =+I16/E16-1 -> 0.076611542 | J17: =+J16/F16-1 -> 0.072847682 | K17: =+K16/G16-1 -> 0.06514658 | L17: =+L16/H16-1 -> 0.047770701 | M17: =+M16/I16-1 -> 0.05015674 | ... U17: =+U16/Q16-1 -> 0.025798883 | AA17: =AA16/Z16-1 -> 0.27950311 | AB17: =AB16/AA16-1 -> 0.22491909 | AC17: =AC16/AB16-1 -> 0.17569353 | AD17: =AD16/AC16-1 -> 0.14382022 | AE17: =AE16/AD16-1 -> 0.20530452 | AF17: =AF16/AE16-1 -> 0.14180929 | AG17: =AG16/AF16-1 -> 0.087080657 | AH17: =AH16/AG16-1 -> 0.087984242 | ... AR17: =AR16/AQ16-1 -> 0.04
A18: q/q % | C18: =+C16/B16-1 -> 0.0034843206 | D18: =+D16/C16-1 -> 0.017361111 | E18: =+E16/D16-1 -> 0.011262799 | F18: =+F16/E16-1 -> 0.01923726 | G18: =+G16/F16-1 -> 0.016556291 | H18: =+H16/G16-1 -> 0.022801303 | I18: =+I16/H16-1 -> 0.015923567 | J18: =+J16/I16-1 -> 0.015673981 | ... U18: =+U16/T16-1 -> 0.01
A19: ARPU | B19: 9.57 | C19: 9.87 | D19: 9.44 | E19: 10.68 | F19: 9.47 | G19: 10.42 | H19: 10.93 | I19: 12.33 | J19: 11.2 | K19: 11.89 | L19: 12.29 | M19: 14.25 | N19: 12.36 | O19: 13.65 | P19: 14.46 | Q19: 16.56 | R19: 15.66 | S19: 16.86 | T19: =+P19*1.2 -> 17.352 | U19: =+Q19*1.2 -> 19.872 | Z19: =+AA19*0.94 -> 5.0008 | AA19: 5.32 | AB19: 6.81 | AC19: 9.45 | AD19: 11.96 | AE19: 15.98 | AF19: 20.21 | AG19: 24.96 | AH19: 29.25 | AI19: 27.51 | AJ19: 33.68 | AK19: 31.79 | AL19: 34.72 | AM19: 49.63 | AN19: 57.03 | AO19: =+AN19*1.2 -> 68.436 | AP19: =+AO19*1.1 -> 75.2796 | AQ19: =+AP19*1.1 -> 82.80756 | AR19: =+AQ19*1.1 -> 91.088316
A20: Y/Y % | B20: 0 | C20: 0 | D20: 0 | E20: 0 | F20: =+F19/B19-1 -> -0.010449321 | G20: =+G19/C19-1 -> 0.055724417 | H20: =+H19/D19-1 -> 0.15783898 | I20: =+I19/E19-1 -> 0.15449438 | J20: =+J19/F19-1 -> 0.18268215 | K20: =+K19/G19-1 -> 0.14107486 | L20: =+L19/H19-1 -> 0.12442818 | M20: =+M19/I19-1 -> 0.15571776 | ... U20: =+U19/Q19-1 -> 0.2 | AA20: =+AA19/Z19 -> 1.0638298 | AB20: =+AB19/AA19-1 -> 0.28007519 | AC20: =+AC19/AB19-1 -> 0.3876652 | AD20: =+AD19/AC19-1 -> 0.26560847 | AE20: =+AE19/AD19-1 -> 0.3361204 | AF20: =+AF19/AE19-1 -> 0.26470588 | AG20: =+AG19/AF19-1 -> 0.23503216 | AH20: =+AH19/AG19-1 -> 0.171875 | AI20: =+AI19/AH19-1 -> -0.059487179 | ... AR20: =+AR19/AQ19-1 -> 0.1
A21: DAU * ARPU | B21: =+B19*B16 -> 27465.9 | C21: =+C19*C16 -> 28425.6 | D21: =+D19*D16 -> 27659.2 | E21: =+E19*E16 -> 31644.84 | F21: =+F19*F16 -> 28599.4 | G21: =+G19*G16 -> 31989.4 | H21: =+H19*H16 -> 34320.2 | I21: =+I19*I16 -> 39332.7 | ... U21: =+U19*U16 -> 72977.138 | Z21: =+Z19*Z16 -> 2415.3864 | AA21: =+AA19*AA16 -> 3287.76 | AB21: =+AB19*AB16 -> 5155.17 | AC21: =+AC19*AC16 -> 8410.5 | AD21: =+AD19*AD16 -> 12175.28 | AE21: =+AE19*AE16 -> 19607.46 | AF21: =+AF19*AF16 -> 28314.21 | AG21: =+AG19*AG16 -> 38014.08 | ... AR21: =+AR19*AR16 -> 377818.26
B22: =+B21/B30 -> 0.98415866 | C22: =+C21/C30 -> 0.98624662 | D22: =+D21/D30 -> 0.99802266 | E22: =+E21/E30 -> 0.98382838 | F22: =+F21/F30 -> 0.9984081 | G22: =+G21/G30 -> 0.99969999 | H22: =+H21/H30 -> 1.0051016 | I22: =+I21/I30 -> 0.98059635 | ... U22: =+U21/U30 -> 0.95941618 | Z22: =+Z21/Z30 -> 0.65087211 | AA22: =+AA21/AA30 -> 0.64605227 | AB22: =+AB21/AB30 -> 0.65487424 | AC22: =+AC21/AC30 -> 0.67467512 | AD22: =+AD21/AD30 -> 0.67912093 | AE22: =+AE21/AE30 -> 0.70943845 | AF22: =+AF21/AF30 -> 0.69648513 | AG22: =+AG21/AG30 -> 0.68079229 | ... AR22: =+AR21/AR30 -> 0.93361205
A24: Advertising | B24: 26998 | C24: 28152 | D24: 27237 | E24: 31254 | F24: 28101 | G24: 31498 | H24: 33643 | I24: 38706 | J24: 35635 | K24: 38329 | L24: 39885 | M24: 46783 | N24: 41392 | O24: 46563 | P24: 50082 | Q24: 58137 | R24: 55024 | S24: 59363 | Z24: 3711 | AA24: 5089 | AB24: 6986 | AC24: 11492 | AD24: 17079 | AE24: 26885 | AF24: 39942 | AG24: 55013 | AH24: 69655 | AI24: 84169 | AJ24: 114934 | AK24: 113642 | AL24: 131948 | AM24: 160633 | AN24: 196175 | AO24: =+AO30-AO26 -> 253360.48 | AP24: =+AP30-AP26 -> 303838.78 | AQ24: =+AQ30-AQ26 -> 349414.59 | AR24: =+AR30-AR26 -> 398332.64 | AS24: =+AS30-AS26 -> 450115.88 | AT24: =+AT30-AT26 -> 504058.01
F25: =+F24/B24-1 -> 0.040854878 | G25: =+G24/C24-1 -> 0.11885479 | H25: =+H24/D24-1 -> 0.23519477 | I25: =+I24/E24-1 -> 0.23843348 | J25: =+J24/F24-1 -> 0.26810434 | K25: =+K24/G24-1 -> 0.21687091 | L25: =+L24/H24-1 -> 0.18553637 | M25: =+M24/I24-1 -> 0.20867566 | ... S25: =+S24/O24-1 -> 0.27489638 | AA25: =+AA24/Z24-1 -> 0.37132848 | AB25: =+AB24/AA24-1 -> 0.37276479 | AC25: =+AC24/AB24-1 -> 0.64500429 | AD25: =+AD24/AC24-1 -> 0.48616429 | AE25: =+AE24/AD24-1 -> 0.5741554 | AF25: =+AF24/AE24-1 -> 0.48566115 | AG25: =+AG24/AF24-1 -> 0.37732212 | AH25: =+AH24/AG24-1 -> 0.26615527 | ... AN25: =+AN24/AM24-1 -> 0.22126213 | AO25: =+AO24/AO$30 -> 0.98493215 | AP25: =+AP24/AP$30 -> 0.98430433 | AQ25: =+AQ24/AQ$30 -> 0.98430433 | AR25: =+AR24/AR$30 -> 0.98430433 | AS25: =+AS24/AS$30 -> 0.98430433 | AT25: =+AT24/AT$30 -> 0.98416419
A26: Other | B26: 215 | C26: 218 | D26: 192 | E26: 184 | F26: 205 | G26: 225 | H26: 293 | I26: 334 | J26: 380 | K26: 389 | L26: 434 | M26: 519 | N26: 510 | O26: 583 | P26: 690 | Q26: 801 | R26: 885 | S26: 1007 | Z26: 0 | AA26: 0 | AB26: 886 | AC26: 974 | AD26: 849 | AE26: 753 | AF26: 711 | AG26: 825 | AH26: 1042 | AI26: 657 | AJ26: 721 | AK26: 808 | AL26: 1058 | AM26: 1722 | AN26: 2584 | AO26: =+AN26*1.5 -> 3876 | AP26: =+AO26*1.25 -> 4845 | AQ26: =+AP26*1.15 -> 5571.75 | AR26: =+AQ26*1.14 -> 6351.795 | AS26: =+AR26*1.13 -> 7177.5283 | AT26: =+AS26*1.13 -> 8110.607
F27: =+F26/B26-1 -> -0.046511628 | G27: =+G26/C26-1 -> 0.032110092 | H27: =+H26/D26-1 -> 0.52604167 | I27: =+I26/E26-1 -> 0.81521739 | J27: =+J26/F26-1 -> 0.85365854 | K27: =+K26/G26-1 -> 0.72888889 | L27: =+L26/H26-1 -> 0.48122867 | M27: =+M26/I26-1 -> 0.55389222 | ... S27: =+S26/O26-1 -> 0.72727273 | AC27: =+AC26/AB26-1 -> 0.099322799 | AD27: =+AD26/AC26-1 -> -0.12833676 | AE27: =+AE26/AD26-1 -> -0.1130742 | AF27: =+AF26/AE26-1 -> -0.055776892 | AG27: =+AG26/AF26-1 -> 0.16033755 | AH27: =+AH26/AG26-1 -> 0.2630303 | AI27: =+AI26/AH26-1 -> -0.36948177 | AJ27: =+AJ26/AI26-1 -> 0.097412481 | ... AN27: =+AN26/AM26-1 -> 0.50058072 | AO27: =+AO26/AO$30 -> 0.015067847 | AP27: =+AP26/AP$30 -> 0.015695674 | AQ27: =+AQ26/AQ$30 -> 0.015695674 | AR27: =+AR26/AR$30 -> 0.015695674 | AS27: =+AS26/AS$30 -> 0.015695674 | AT27: =+AT26/AT$30 -> 0.015835814
A28: Reality Labs | B28: 695 | C28: 452 | D28: 285 | E28: 727 | F28: 339 | G28: 276 | H28: 210 | I28: 1071 | J28: 440 | K28: 353 | L28: 270 | M28: 1083 | N28: 412 | O28: 370 | P28: 470 | Q28: 955 | R28: 402 | S28: 431 | AI28: 1139 | AJ28: 2274 | AK28: 2159 | AL28: 1896 | AM28: 2146 | AN28: 2207
F29: =+F28/B28-1 -> -0.51223022 | G29: =+G28/C28-1 -> -0.38938053 | H29: =+H28/D28-1 -> -0.26315789 | I29: =+I28/E28-1 -> 0.47317744 | J29: =+J28/F28-1 -> 0.2979351 | K29: =+K28/G28-1 -> 0.27898551 | L29: =+L28/H28-1 -> 0.28571429 | M29: =+M28/I28-1 -> 0.011204482 | ... S29: =+S28/O28-1 -> 0.16486486 | AJ29: =+AJ28/AI28-1 -> 0.99648815 | AK29: =+AK28/AJ28-1 -> -0.05057168 | AL29: =+AL28/AK28-1 -> -0.12181566 | AM29: =+AM28/AL28-1 -> 0.13185654 | AN29: =+AN28/AM28-1 -> 0.028424977
A30: Revenues | B30: =+B24+B26+B28 -> 27908 | C30: =+C24+C26+C28 -> 28822 | D30: =+D24+D26+D28 -> 27714 | E30: =+E24+E26+E28 -> 32165 | F30: =+F24+F26+F28 -> 28645 | G30: =+G24+G26+G28 -> 31999 | H30: =+H24+H26+H28 -> 34146 | I30: =+I24+I26+I28 -> 40111 | ... Q30: =+Q24+Q26+Q28 -> 59893 | R30: 56311 | S30: 60801 | T30: =+P30*1.24 -> 63540.08 | U30: =+Q30*1.27 -> 76064.11 | Z30: =+Z24+Z26+Z28 -> 3711 | AA30: =+AA24+AA26+AA28 -> 5089 | AB30: =+AB24+AB26+AB28 -> 7872 | AC30: =+AC24+AC26+AC28 -> 12466 | AD30: =+AD24+AD26+AD28 -> 17928 | AE30: =+AE24+AE26+AE28 -> 27638 | AF30: =+AF24+AF26+AF28 -> 40653 | AG30: =+AG24+AG26+AG28 -> 55838 | ... AN30: =+AN24+AN26+AN28 -> 200966 | AO30: =+AN30*1.28 -> 257236.48 | AP30: =+AO30*1.2 -> 308683.78 | AQ30: =+AP30*1.15 -> 354986.34 | AR30: =+AQ30*1.14 -> 404684.43 | AS30: =+AR30*1.13 -> 457293.41 | AT30: =+AS30*1.12 -> 512168.62
F31: =+F30/B30-1 -> 0.026408198 | G31: =+G30/C30-1 -> 0.1102283 | H31: =+H30/D30-1 -> 0.23208487 | I31: =+I30/E30-1 -> 0.24703871 | J31: =+J30/F30-1 -> 0.27264793 | K31: =+K30/G30-1 -> 0.22100691 | L31: =+L30/H30-1 -> 0.18868974 | M31: =+M30/I30-1 -> 0.20627758 | ... U31: =+U30/Q30-1 -> 0.27 | AA31: =+AA30/Z30-1 -> 0.37132848 | AB31: =+AB30/AA30-1 -> 0.54686579 | AC31: =+AC30/AB30-1 -> 0.5835874 | AD31: =+AD30/AC30-1 -> 0.43815177 | AE31: =+AE30/AD30-1 -> 0.54161089 | AF31: =+AF30/AE30-1 -> 0.47090962 | AG31: =+AG30/AF30-1 -> 0.37352717 | AH31: =+AH30/AG30-1 -> 0.2661091 | ... AT31: =+AT30/AS30-1 -> 0.12 | AV31: =+(AT30/AO30)^(1/(AT2-AO2))-1 -> 0.14766749
A32: COGS | B32: 6005 | C32: 5192 | D32: 5716 | E32: 8336 | F32: 6108 | G32: 5945 | H32: 6210 | I32: 7695 | J32: 6640 | K32: 7308 | L32: 7375 | M32: 8839 | N32: 7572 | O32: 8491 | P32: 9206 | Q32: 10905 | R32: 10218 | S32: 11330 | T32: =+T30-T34 -> 11500.754 | U32: =+U30-U34 -> 13767.604 | Z32: 860 | AA32: 1364 | AB32: 1875 | AC32: 2153 | AD32: 2867 | AE32: 3789 | AF32: 5454 | AG32: 9355 | AH32: 12770 | AI32: 16692 | AJ32: 22649 | AK32: 25249 | AL32: 25959 | AM32: 30161 | AN32: 36175 | AO32: =+AO30-AO34 -> 46302.566 | AP32: =+AP30-AP34 -> 55563.08 | AQ32: =+AQ30-AQ34 -> 60347.678 | AR32: =+AR30-AR34 -> 68796.353 | AS32: =+AS30-AS34 -> 73166.945 | AT32: =+AT30-AT34 -> 81946.978
B33: =+B32/B$30 -> 0.21517128 | C33: =+C32/C$30 -> 0.18014017 | D33: =+D32/D$30 -> 0.20624955 | E33: =+E32/E$30 -> 0.25916369 | F33: =+F32/F$30 -> 0.21323093 | G33: =+G32/G$30 -> 0.18578706 | H33: =+H32/H$30 -> 0.1818661 | I33: =+I32/I$30 -> 0.19184264 | ... U33: =+U32/U$30 -> 0.181 | Z33: =+Z32/Z$30 -> 0.23174347 | AA33: =+AA32/AA$30 -> 0.26802908 | AB33: =+AB32/AB$30 -> 0.23818598 | AC33: =+AC32/AC$30 -> 0.17270977 | AD33: =+AD32/AD$30 -> 0.15991745 | AE33: =+AE32/AE$30 -> 0.13709386 | AF33: =+AF32/AF$30 -> 0.13415984 | AG33: =+AG32/AG$30 -> 0.16753824 | ... AT33: =+AT32/AT$30 -> 0.16
A34: Gross Profit | B34: =B30-B32 -> 21903 | C34: =C30-C32 -> 23630 | D34: =D30-D32 -> 21998 | E34: =E30-E32 -> 23829 | F34: =F30-F32 -> 22537 | G34: =G30-G32 -> 26054 | H34: =H30-H32 -> 27936 | I34: =I30-I32 -> 32416 | ... S34: =S30-S32 -> 49471 | T34: =+T30*0.819 -> 52039.326 | U34: =+U30*0.819 -> 62296.506 | Z34: =Z30-Z32 -> 2851 | AA34: =AA30-AA32 -> 3725 | AB34: =AB30-AB32 -> 5997 | AC34: =AC30-AC32 -> 10313 | AD34: =AD30-AD32 -> 15061 | AE34: =AE30-AE32 -> 23849 | AF34: =AF30-AF32 -> 35199 | AG34: =AG30-AG32 -> 46483 | ... AN34: =AN30-AN32 -> 164791 | AO34: =+AO30*0.82 -> 210933.91 | AP34: =+AP30*0.82 -> 253120.7 | AQ34: =+AQ30*0.83 -> 294638.66 | AR34: =+AR30*0.83 -> 335888.08 | AS34: =+AS30*0.84 -> 384126.46 | AT34: =+AT30*0.84 -> 430221.64
B35: =+B34/B$30 -> 0.78482872 | C35: =+C34/C$30 -> 0.81985983 | D35: =+D34/D$30 -> 0.79375045 | E35: =+E34/E$30 -> 0.74083631 | F35: =+F34/F$30 -> 0.78676907 | G35: =+G34/G$30 -> 0.81421294 | H35: =+H34/H$30 -> 0.8181339 | I35: =+I34/I$30 -> 0.80815736 | ... U35: =+U34/U$30 -> 0.819 | Z35: =+Z34/Z$30 -> 0.76825653 | AA35: =+AA34/AA$30 -> 0.73197092 | AB35: =+AB34/AB$30 -> 0.76181402 | AC35: =+AC34/AC$30 -> 0.82729023 | AD35: =+AD34/AD$30 -> 0.84008255 | AE35: =+AE34/AE$30 -> 0.86290614 | AF35: =+AF34/AF$30 -> 0.86584016 | AG35: =+AG34/AG$30 -> 0.83246176 | ... AT35: =+AT34/AT$30 -> 0.84
A36: R&D | B36: 7707 | C36: 8690 | D36: 9170 | E36: 9771 | F36: 9381 | G36: 9344 | H36: 9241 | I36: 10517 | J36: 9978 | K36: 10537 | L36: 11177 | M36: 12180 | N36: 12150 | O36: 12942 | P36: 15144 | Q36: 17136 | R36: 17699 | S36: 21656 | T36: =+P36*1.35 -> 20444.4 | U36: =+Q36*1.35 -> 23133.6 | Z36: 388 | AA36: 1399 | AB36: 1415 | AC36: 2666 | AD36: 4816 | AE36: 5919 | AF36: 7754 | AG36: 10273 | AH36: 13600 | AI36: 18447 | AJ36: 24655 | AK36: 35338 | AL36: 38483 | AM36: 43873 | AN36: 57372 | AO36: =+AO30*0.27 -> 69453.85 | AP36: =+AP30*0.27 -> 83344.62 | AQ36: =+AQ30*0.27 -> 95846.312 | AR36: =+AR30*0.27 -> 109264.8 | AS36: =+AS30*0.27 -> 123469.22 | AT36: =+AT30*0.25 -> 128042.15
B37: =+B36/B$30 -> 0.27615737 | C37: =+C36/C$30 -> 0.30150579 | D37: =+D36/D$30 -> 0.3308797 | E37: =+E36/E$30 -> 0.3037774 | F37: =+F36/F$30 -> 0.32749171 | G37: =+G36/G$30 -> 0.29200913 | H37: =+H36/H$30 -> 0.27063199 | I37: =+I36/I$30 -> 0.2621974 | ... U37: =+U36/U$30 -> 0.30413292 | Z37: =+Z36/Z$30 -> 0.10455403 | AA37: =+AA36/AA$30 -> 0.27490666 | AB37: =+AB36/AB$30 -> 0.17975102 | AC37: =+AC36/AC$30 -> 0.2138617 | AD37: =+AD36/AD$30 -> 0.26863008 | AE37: =+AE36/AE$30 -> 0.21416166 | AF37: =+AF36/AF$30 -> 0.19073623 | AG37: =+AG36/AG$30 -> 0.18397865 | ... AT37: =+AT36/AT$30 -> 0.25
A38: S&M | B38: 3312 | C38: 3595 | D38: 3780 | E38: 4574 | F38: 3044 | G38: 3154 | H38: 2877 | I38: 3226 | J38: 2564 | K38: 2721 | L38: 2822 | M38: 3240 | N38: 2757 | O38: 2979 | P38: 2845 | Q38: 3410 | R38: 2908 | S38: 3431 | T38: =+T30*0.055 -> 3494.7044 | U38: =+U30*0.055 -> 4183.5261 | Z38: 393 | AA38: 896 | AB38: 997 | AC38: 1680 | AD38: 2725 | AE38: 3772 | AF38: 4725 | AG38: 7846 | AH38: 9876 | AI38: 11591 | AJ38: 14043 | AK38: 15262 | AL38: 12301 | AM38: 11347 | AN38: 11991 | AO38: =+AO30*0.07 -> 18006.554 | AP38: =+AP30*0.07 -> 21607.864 | AQ38: =+AQ30*0.07 -> 24849.044 | AR38: =+AR30*0.07 -> 28327.91 | AS38: =+AS30*0.07 -> 32010.538 | AT38: =+AT30*0.05 -> 25608.431
B39: =+B38/B$30 -> 0.11867565 | C39: =+C38/C$30 -> 0.12473111 | D39: =+D38/D$30 -> 0.13639316 | E39: =+E38/E$30 -> 0.14220426 | F39: =+F38/F$30 -> 0.10626636 | G39: =+G38/G$30 -> 0.09856558 | H39: =+H38/H$30 -> 0.084255843 | I39: =+I38/I$30 -> 0.080426816 | ... U39: =+U38/U$30 -> 0.055 | Z39: =+Z38/Z$30 -> 0.10590137 | AA39: =+AA38/AA$30 -> 0.17606602 | AB39: =+AB38/AB$30 -> 0.12665142 | AC39: =+AC38/AC$30 -> 0.13476657 | AD39: =+AD38/AD$30 -> 0.15199688 | AE39: =+AE38/AE$30 -> 0.13647876 | AF39: =+AF38/AF$30 -> 0.11622758 | AG39: =+AG38/AG$30 -> 0.14051363 | ... AT39: =+AT38/AT$30 -> 0.05
A40: G&A | B40: 2360 | C40: 2987 | D40: 3384 | E40: 3085 | F40: 2885 | G40: 4164 | H40: 2070 | I40: 2289 | J40: 3455 | K40: 3658 | L40: 1865 | M40: 761 | N40: 2280 | O40: 2663 | P40: 3512 | Q40: 3697 | R40: 2614 | S40: 5609 | T40: =+T30*0.06 -> 3812.4048 | U40: =+U30*0.06 -> 4563.8466 | Z40: 314 | AA40: 892 | AB40: 781 | AC40: 973 | AD40: 1295 | AE40: 1731 | AF40: 2517 | AG40: 3451 | AH40: 10465 | AI40: 6564 | AJ40: 9829 | AK40: 11816 | AL40: 11408 | AM40: 9740 | AN40: 12152 | AO40: =+AO30*0.06 -> 15434.189 | AP40: =+AP30*0.06 -> 18521.027 | AQ40: =+AQ30*0.06 -> 21299.181 | AR40: =+AR30*0.06 -> 24281.066 | AS40: =+AS30*0.06 -> 27437.604 | AT40: =+AT30*0.06 -> 30730.117
B41: =+B40/B$30 -> 0.084563566 | C41: =+C40/C$30 -> 0.10363611 | D41: =+D40/D$30 -> 0.12210435 | E41: =+E40/E$30 -> 0.095911705 | F41: =+F40/F$30 -> 0.10071566 | G41: =+G40/G$30 -> 0.13012907 | H41: =+H40/H$30 -> 0.060622035 | I41: =+I40/I$30 -> 0.05706664 | ... U41: =+U40/U$30 -> 0.06 | Z41: =+Z40/Z$30 -> 0.084613312 | AA41: =+AA40/AA$30 -> 0.17528002 | AB41: =+AB40/AB$30 -> 0.099212398 | AC41: =+AC40/AC$30 -> 0.078052302 | AD41: =+AD40/AD$30 -> 0.072233378 | AE41: =+AE40/AE$30 -> 0.06263116 | AF41: =+AF40/AF$30 -> 0.06191425 | AG41: =+AG40/AG$30 -> 0.06180379 | ... AT41: =+AT40/AT$30 -> 0.06
A42: Op Ex | B42: =+B40+B38+B36 -> 13379 | C42: =+C40+C38+C36 -> 15272 | D42: =+D40+D38+D36 -> 16334 | E42: =+E40+E38+E36 -> 17430 | F42: =+F40+F38+F36 -> 15310 | G42: =+G40+G38+G36 -> 16662 | H42: =+H40+H38+H36 -> 14188 | I42: =+I40+I38+I36 -> 16032 | ... U42: =+U40+U38+U36 -> 31880.973 | Z42: =+Z40+Z38+Z36 -> 1095 | AA42: =+AA40+AA38+AA36 -> 3187 | AB42: =+AB40+AB38+AB36 -> 3193 | AC42: =+AC40+AC38+AC36 -> 5319 | AD42: =+AD40+AD38+AD36 -> 8836 | AE42: =+AE40+AE38+AE36 -> 11422 | AF42: =+AF40+AF38+AF36 -> 14996 | AG42: =+AG40+AG38+AG36 -> 21570 | ... AT42: =+AT40+AT38+AT36 -> 184380.7
B43: =+B42/B$30 -> 0.47939659 | C43: =+C42/C$30 -> 0.52987301 | D43: =+D42/D$30 -> 0.58937721 | E43: =+E42/E$30 -> 0.54189336 | F43: =+F42/F$30 -> 0.53447373 | G43: =+G42/G$30 -> 0.52070377 | H43: =+H42/H$30 -> 0.41550987 | I43: =+I42/I$30 -> 0.39969086 | ... U43: =+U42/U$30 -> 0.41913292 | Z43: =+Z42/Z$30 -> 0.29506871 | AA43: =+AA42/AA$30 -> 0.6262527 | AB43: =+AB42/AB$30 -> 0.40561484 | AC43: =+AC42/AC$30 -> 0.42668057 | AD43: =+AD42/AD$30 -> 0.49286033 | AE43: =+AE42/AE$30 -> 0.41327158 | AF43: =+AF42/AF$30 -> 0.36887807 | AG43: =+AG42/AG$30 -> 0.38629607 | ... AT43: =+AT42/AT$30 -> 0.36
A44: EBIT | B44: =B34-B42 -> 8524 | C44: =C34-C42 -> 8358 | D44: =D34-D42 -> 5664 | E44: =E34-E42 -> 6399 | F44: =F34-F42 -> 7227 | G44: =G34-G42 -> 9392 | H44: =H34-H42 -> 13748 | I44: =I34-I42 -> 16384 | ... U44: =U34-U42 -> 30415.533 | Z44: =Z34-Z42 -> 1756 | AA44: =AA34-AA42 -> 538 | AB44: =AB34-AB42 -> 2804 | AC44: =AC34-AC42 -> 4994 | AD44: =AD34-AD42 -> 6225 | AE44: =AE34-AE42 -> 12427 | AF44: =AF34-AF42 -> 20203 | AG44: =AG34-AG42 -> 24913 | ... AT44: =AT34-AT42 -> 245840.94
B45: =+B44/B$30 -> 0.30543213 | C45: =+C44/C$30 -> 0.28998682 | D45: =+D44/D$30 -> 0.20437324 | E45: =+E44/E$30 -> 0.19894295 | F45: =+F44/F$30 -> 0.25229534 | G45: =+G44/G$30 -> 0.29350917 | H45: =+H44/H$30 -> 0.40262403 | I45: =+I44/I$30 -> 0.40846651 | ... U45: =+U44/U$30 -> 0.39986708 | Z45: =+Z44/Z$30 -> 0.47318782 | AA45: =+AA44/AA$30 -> 0.10571822 | AB45: =+AB44/AB$30 -> 0.35619919 | AC45: =+AC44/AC$30 -> 0.40060966 | AD45: =+AD44/AD$30 -> 0.34722222 | AE45: =+AE44/AE$30 -> 0.44963456 | AF45: =+AF44/AF$30 -> 0.49696209 | AG45: =+AG44/AG$30 -> 0.44616569 | ... AT45: =+AT44/AT$30 -> 0.48
A46: Interest | B46: 384 | C46: -172 | D46: -88 | E46: -250 | F46: 80 | G46: -99 | H46: 272 | I46: 424 | J46: 365 | K46: 259 | L46: 472 | M46: 188 | N46: 827 | O46: =+93+343 -> 436 | P46: =+1128-954 -> 174 | Q46: 609 | R46: =-1120+1076 -> -44 | S46: -19 | T46: =-20-10000 -> -10020 | U46: -20 | Z46: -61 | AA46: -44 | AB46: -50 | AC46: -84 | AD46: -31 | AE46: 91 | AF46: 391 | AG46: 448 | AH46: 826 | AI46: 509 | AJ46: 531 | AK46: -125 | AL46: 677 | AM46: 1283 | AN46: 2656 | AO46: =+AN91*$AW$68-10000 -> -9543.04 | AP46: =+AO91*$AW$68 -> 2170.7953 | AQ46: =+AP91*$AW$68 -> 4464.4282 | AR46: =+AQ91*$AW$68 -> 7198.117 | AS46: =+AR91*$AW$68 -> 10351.213 | AT46: =+AS91*$AW$68 -> 14032.363
B47: =+B46/B$30 -> 0.013759495 | C47: =+C46/C$30 -> -0.0059676636 | D47: =+D46/D$30 -> -0.0031752905 | E47: =+E46/E$30 -> -0.0077724234 | F47: =+F46/F$30 -> 0.0027928085 | G47: =+G46/G$30 -> -0.0030938467 | H47: =+H46/H$30 -> 0.0079657939 | I47: =+I46/I$30 -> 0.010570666 | ... U47: =+U46/U$30 -> -0.00026293609 | Z47: =+Z46/Z$30 -> -0.016437618 | AA47: =+AA46/AA$30 -> -0.0086460994 | AB47: =+AB46/AB$30 -> -0.006351626 | AC47: =+AC46/AC$30 -> -0.0067383283 | AD47: =+AD46/AD$30 -> -0.0017291388 | AE47: =+AE46/AE$30 -> 0.0032925682 | AF47: =+AF46/AF$30 -> 0.0096179864 | AG47: =+AG46/AG$30 -> 0.00802321 | ... AT47: =+AT46/AT$30 -> 0.027397935
A48: Pretax / EBT | B48: =B44+B46 -> 8908 | C48: =C44+C46 -> 8186 | D48: =D44+D46 -> 5576 | E48: =E44+E46 -> 6149 | F48: =F44+F46 -> 7307 | G48: =G44+G46 -> 9293 | H48: =H44+H46 -> 14020 | I48: =I44+I46 -> 16808 | ... U48: =U44+U46 -> 30395.533 | Z48: =Z44+Z46 -> 1695 | AA48: =AA44+AA46 -> 494 | AB48: =AB44+AB46 -> 2754 | AC48: =AC44+AC46 -> 4910 | AD48: =AD44+AD46 -> 6194 | AE48: =AE44+AE46 -> 12518 | AF48: =AF44+AF46 -> 20594 | AG48: =AG44+AG46 -> 25361 | ... AT48: =AT44+AT46 -> 259873.3
B49: =+B48/B$30 -> 0.31919163 | C49: =+C48/C$30 -> 0.28401915 | D49: =+D48/D$30 -> 0.20119795 | E49: =+E48/E$30 -> 0.19117053 | F49: =+F48/F$30 -> 0.25508815 | G49: =+G48/G$30 -> 0.29041533 | H49: =+H48/H$30 -> 0.41058982 | I49: =+I48/I$30 -> 0.41903717 | ... U49: =+U48/U$30 -> 0.39960414 | Z49: =+Z48/Z$30 -> 0.4567502 | AA49: =+AA48/AA$30 -> 0.097072116 | AB49: =+AB48/AB$30 -> 0.34984756 | AC49: =+AC48/AC$30 -> 0.39387133 | AD49: =+AD48/AD$30 -> 0.34549308 | AE49: =+AE48/AE$30 -> 0.45292713 | AF49: =+AF48/AF$30 -> 0.50658008 | AG49: =+AG48/AG$30 -> 0.4541889 | ... AT49: =+AT48/AT$30 -> 0.50739794
A50: Taxes | B50: 1443 | C50: 1499 | D50: 1181 | E50: 1497 | F50: 1598 | G50: 1505 | H50: 2437 | I50: 2791 | J50: 1814 | K50: 1641 | L50: 2134 | M50: 2715 | N50: 1738 | O50: 2197 | P50: =+18954-15930 -> 3024 | Q50: 2586 | R50: -5021 | S50: 2908 | T50: =+T48*0.14 -> 1997.4943 | U50: =+U48*0.14 -> 4255.3747 | Z50: 695 | AA50: 441 | AB50: 1254 | AC50: 1970 | AD50: 2506 | AE50: 2301 | AF50: 4660 | AG50: 3249 | AH50: 6327 | AI50: 4034 | AJ50: 7914 | AK50: 5619 | AL50: 8330 | AM50: 8303 | AN50: 25474 | AO50: =+AO48*0.13 -> 12804.517 | AP50: =+AP48*0.13 -> 17136.338 | AQ50: =+AQ48*0.13 -> 20424.112 | AR50: =+AR48*0.13 -> 23557.615 | AS50: =+AS48*0.13 -> 27502.841 | AT50: =+AT48*0.13 -> 33783.529
B51: =+B50/B$30 -> 0.051705604 | C51: =+C50/C$30 -> 0.052008882 | D51: =+D50/D$30 -> 0.042613841 | E51: =+E50/E$30 -> 0.046541272 | F51: =+F50/F$30 -> 0.05578635 | G51: =+G50/G$30 -> 0.04703272 | H51: =+H50/H$30 -> 0.071369999 | I51: =+I50/I$30 -> 0.06958191 | ... U51: =+U50/U$30 -> 0.05594458 | Z51: =+Z50/Z$30 -> 0.18728106 | AA51: =+AA50/AA$30 -> 0.086657497 | AB51: =+AB50/AB$30 -> 0.15929878 | AC51: =+AC50/AC$30 -> 0.15802984 | AD51: =+AD50/AD$30 -> 0.13978135 | AE51: =+AE50/AE$30 -> 0.083254939 | AF51: =+AF50/AF$30 -> 0.11462869 | AG51: =+AG50/AG$30 -> 0.058186181 | ... AT51: =+AT50/AT$30 -> 0.065961732
A52: Net Inc | B52: =B48-B50 -> 7465 | C52: =C48-C50 -> 6687 | D52: =D48-D50 -> 4395 | E52: =E48-E50 -> 4652 | F52: =F48-F50 -> 5709 | G52: =G48-G50 -> 7788 | H52: =H48-H50 -> 11583 | I52: =I48-I50 -> 14017 | ... U52: =U48-U50 -> 26140.159 | Z52: =Z48-Z50 -> 1000 | AA52: =AA48-AA50 -> 53 | AB52: =AB48-AB50 -> 1500 | AC52: =AC48-AC50 -> 2940 | AD52: =AD48-AD50 -> 3688 | AE52: =AE48-AE50 -> 10217 | AF52: =AF48-AF50 -> 15934 | AG52: =AG48-AG50 -> 22112 | ... AT52: =AT48-AT50 -> 226089.77 | AU52: =+AT52*(1+$AW$66) -> 230611.56 | AV52: =+AU52*(1+$AW$66) -> 235223.8 | AW52: =+AV52*(1+$AW$66) -> 239928.27 | AX52: =+AW52*(1+$AW$66) -> 244726.84 | AY52: =+AX52*(1+$AW$66) -> 249621.37 | AZ52: =+AY52*(1+$AW$66) -> 254613.8 | BA52: =+AZ52*(1+$AW$66) -> 259706.08 | BB52: =+BA52*(1+$AW$66) -> 264900.2 | ... EK52: =+EJ52*(1+$AW$66) -> 1483533.1
B53: =+B52/B$30 -> 0.26748603 | C53: =+C52/C$30 -> 0.23201027 | D53: =+D52/D$30 -> 0.15858411 | E53: =+E52/E$30 -> 0.14462926 | F53: =+F52/F$30 -> 0.1993018 | G53: =+G52/G$30 -> 0.24338261 | H53: =+H52/H$30 -> 0.33921982 | I53: =+I52/I$30 -> 0.34945526 | ... U53: =+U52/U$30 -> 0.34365956 | Z53: =+Z52/Z$30 -> 0.26946915 | AA53: =+AA52/AA$30 -> 0.01041462 | AB53: =+AB52/AB$30 -> 0.19054878 | AC53: =+AC52/AC$30 -> 0.23584149 | AD53: =+AD52/AD$30 -> 0.20571174 | AE53: =+AE52/AE$30 -> 0.36967219 | AF53: =+AF52/AF$30 -> 0.39195139 | AG53: =+AG52/AG$30 -> 0.39600272 | ... AT53: =+AT52/AT$30 -> 0.4414362
A54: EPS | B54: =B52/B56 -> 2.7224654 | C54: =C52/C56 -> 2.4647991 | D54: =D52/D56 -> 1.6356531 | E54: =E52/E56 -> 1.7621212 | F54: =F52/F56 -> 2.1991525 | G54: =G52/G56 -> 2.9816233 | H54: =H52/H56 -> 4.3858387 | I54: =I52/I56 -> 5.3296578 | ... U54: =U52/U56 -> 10.294035 | Z54: =Z52/Z56 -> 0.66312997 | AA54: =AA52/AA56 -> 0.024469067 | AB54: =AB52/AB56 -> 0.59594756 | AC54: =AC52/AC56 -> 1.1036036 | AD54: =AD52/AD56 -> 1.2926744 | AE54: =AE52/AE56 -> 3.4929915 | AF54: =AF52/AF56 -> 5.3903924 | AG54: =AG52/AG56 -> 7.5700103 | ... AT54: =AT52/AT56 -> 93.295608
F55: =+F54/B54-1 -> -0.19222019 | G55: =+G54/C54-1 -> 0.20968206 | H55: =+H54/D54-1 -> 1.681399 | I55: =+I54/E54-1 -> 2.0245693 | J55: =+J54/F54-1 -> 1.1426435 | K55: =+K54/G54-1 -> 0.73026682 | L55: =+L54/H54-1 -> 0.37575651 | M55: =+M54/I54-1 -> 0.50435533 | ... U55: =+U54/Q54-1 -> 0.15970664 | AA55: =+AA54/Z54-1 -> -0.96310065 | AB55: =+AB54/AA54-1 -> 23.35514 | AC55: =+AC54/AB54-1 -> 0.85184685 | AD55: =+AD54/AC54-1 -> 0.17132127 | AE55: =+AE54/AD54-1 -> 1.7021433 | AF55: =+AF54/AE54-1 -> 0.54320229 | AG55: =+AG54/AF54-1 -> 0.40435235 | AH55: =+AH54/AG54-1 -> -0.15094836 | ... AT55: =+AT54/AS54-1 -> 0.2407728 | AV55: =+(AT54/AO54)^(1/(AT2-AO2))-1 -> 0.2264029
A56: Shares | B56: 2742 | C56: 2713 | D56: 2687 | E56: 2640 | F56: 2596 | G56: 2612 | H56: 2641 | I56: 2630 | J56: 2625 | K56: 2610 | L56: 2600 | M56: 2599 | N56: 2590 | O56: 2570 | P56: 2572 | Q56: 2565 | R56: 2564 | S56: 2566 | T56: =+P56*0.99 -> 2546.28 | U56: =+Q56*0.99 -> 2539.35 | Z56: 1508 | AA56: 2166 | AB56: 2517 | AC56: 2664 | AD56: 2853 | AE56: 2925 | AF56: 2956 | AG56: 2921 | AH56: 2876 | AI56: 2888 | AJ56: 2859 | AK56: 2702 | AL56: 2629 | AM56: 2614 | AN56: 2574 | AO56: =+AN56*0.99 -> 2548.26 | AP56: =+AO56*0.99 -> 2522.7774 | AQ56: =+AP56*0.99 -> 2497.5496 | AR56: =+AQ56*0.99 -> 2472.5741 | AS56: =+AR56*0.99 -> 2447.8484 | AT56: =+AS56*0.99 -> 2423.3699
C57: =+C56/B56-1 -> -0.010576222 | D57: =+D56/C56-1 -> -0.0095834869 | E57: =+E56/D56-1 -> -0.017491626 | F57: =+F56/E56-1 -> -0.016666667 | G57: =+G56/F56-1 -> 0.0061633282 | H57: =+H56/G56-1 -> 0.011102603 | I57: =+I56/H56-1 -> -0.004165089 | J57: =+J56/I56-1 -> -0.0019011407 | ... U57: =+U56/T56-1 -> -0.0027216174 | AA57: =+AA56/Z56-1 -> 0.43633952 | AB57: =+AB56/AA56-1 -> 0.16204986 | AC57: =+AC56/AB56-1 -> 0.058402861 | AD57: =+AD56/AC56-1 -> 0.070945946 | AE57: =+AE56/AD56-1 -> 0.025236593 | AF57: =+AF56/AE56-1 -> 0.010598291 | AG57: =+AG56/AF56-1 -> -0.011840325 | AH57: =+AH56/AG56-1 -> -0.015405683 | ... AT57: =+AT56/AS56-1 -> -0.01
A59: Dividends | J59: 0.5 | K59: 0.5 | L59: 0.5 | M59: 0.5 | N59: 0.525 | O59: 0.525 | P59: 0.525 | Q59: 0.525 | R59: 0.525 | S59: 0.525 | T59: 0.525 | AM59: =+SUM(J59:M59) -> 2 | AN59: =+SUM(N59:Q59) -> 2.1 | AO59: =+SUM(O59:R59) -> 2.1
AN60: =+AN59/AM59-1 -> 0.05 | AO60: =+AO59/AN59-1 -> 0
A62: ADV Impression Y/Y | I62: 0.21 | J62: 0.2 | K62: 0.1 | L62: 0.07 | M62: 0.06 | N62: 0.05 | O62: 0.11 | P62: 0.14 | Q62: 0.18 | R62: 0.19 | S62: 0.14 | AE62: 0.5 | AF62: 0.33 | AG62: 0.33 | AH62: 0.33 | AI62: 0.34 | AJ62: 0.1 | AK62: 0.18 | AL62: 0.28 | AM62: 0.11 | AN62: 0.12
A63: Price per Ad Y/Y | I63: 0.02 | J63: 0.06 | K63: 0.1 | L63: 0.11 | M63: 0.14 | N63: 0.1 | O63: 0.09 | P63: 0.1 | Q63: 0.06 | R63: 0.12 | S63: 0.12 | AE63: 0.05 | AF63: 0.14 | AG63: 0.13 | AH63: 0.05 | AI63: -0.05 | AJ63: 0.24 | AK63: -0.16 | AL63: -0.09 | AM63: 0.1 | AN63: 0.09
A64: Contractual Commitments | S64: 349310 | AN64: 131050
BA65: Gordon Growth Model
A66: Gross Margin | B66: =B34/B30 -> 0.78482872 | C66: =C34/C30 -> 0.81985983 | D66: =D34/D30 -> 0.79375045 | E66: =E34/E30 -> 0.74083631 | F66: =F34/F30 -> 0.78676907 | G66: =G34/G30 -> 0.81421294 | H66: =H34/H30 -> 0.8181339 | I66: =I34/I30 -> 0.80815736 | ... U66: =U34/U30 -> 0.819 | Z66: =Z34/Z30 -> 0.76825653 | AA66: =AA34/AA30 -> 0.73197092 | AB66: =AB34/AB30 -> 0.76181402 | AC66: =AC34/AC30 -> 0.82729023 | AD66: =AD34/AD30 -> 0.84008255 | AE66: =AE34/AE30 -> 0.86290614 | AF66: =AF34/AF30 -> 0.86584016 | AG66: =AG34/AG30 -> 0.83246176 | ... AT66: =AT34/AT30 -> 0.84 | AV66: Terminal | AW66: 0.02 | BA66: Sustained growth | BB66: =+(1-BB67)*AN80 -> 0.2253701 | BD66: EV | BE66: =+BB68 -> 1945094.4
A67: OP Margin | B67: =B44/B30 -> 0.30543213 | C67: =C44/C30 -> 0.28998682 | D67: =D44/D30 -> 0.20437324 | E67: =E44/E30 -> 0.19894295 | F67: =F44/F30 -> 0.25229534 | G67: =G44/G30 -> 0.29350917 | H67: =H44/H30 -> 0.40262403 | I67: =I44/I30 -> 0.40846651 | ... U67: =U44/U30 -> 0.39986708 | Z67: =Z44/Z30 -> 0.47318782 | AA67: =AA44/AA30 -> 0.10571822 | AB67: =AB44/AB30 -> 0.35619919 | AC67: =AC44/AC30 -> 0.40060966 | AD67: =AD44/AD30 -> 0.34722222 | AE67: =AE44/AE30 -> 0.44963456 | AF67: =AF44/AF30 -> 0.49696209 | AG67: =AG44/AG30 -> 0.44616569 | ... AT67: =AT44/AT30 -> 0.48 | AV67: Discount | AW67: =+Main!E12 -> 0.10915439 | BA67: Payout ratio | BB67: =+(SUM(T173:W173)+SUM(T174:W174))/SUM(P52:S52) -> 0.25468097 | BD67: Shares | BE67: =+SUM(Main!F1:F2) -> 2547.5062
A68: NI Margin | B68: =B52/B30 -> 0.26748603 | C68: =C52/C30 -> 0.23201027 | D68: =D52/D30 -> 0.15858411 | E68: =E52/E30 -> 0.14462926 | F68: =F52/F30 -> 0.1993018 | G68: =G52/G30 -> 0.24338261 | H68: =H52/H30 -> 0.33921982 | I68: =I52/I30 -> 0.34945526 | ... U68: =U52/U30 -> 0.34365956 | Z68: =Z52/Z30 -> 0.26946915 | AA68: =AA52/AA30 -> 0.01041462 | AB68: =AB52/AB30 -> 0.19054878 | AC68: =AC52/AC30 -> 0.23584149 | AD68: =AD52/AD30 -> 0.20571174 | AE68: =AE52/AE30 -> 0.36967219 | AF68: =AF52/AF30 -> 0.39195139 | AG68: =AG52/AG30 -> 0.39600272 | ... AT68: =AT52/AT30 -> 0.4414362 | AV68: ROIC | AW68: 0.02 | BA68: Equity Value | BB68: =+(SUM(T180:W180)*(1+0.1))/(Main!B17-0.1) -> 1945094.4 | BD68: Price | BE68: =+BE66/BE67 -> 763.52882
A69: Tax Rate | B69: =B50/B48 -> 0.16198922 | C69: =C50/C48 -> 0.18311752 | D69: =D50/D48 -> 0.21180057 | E69: =E50/E48 -> 0.24345422 | F69: =F50/F48 -> 0.2186944 | G69: =G50/G48 -> 0.16194985 | H69: =H50/H48 -> 0.17382311 | I69: =I50/I48 -> 0.16605188 | ... U69: =U50/U48 -> 0.14 | Z69: =Z50/Z48 -> 0.4100295 | AA69: =AA50/AA48 -> 0.89271255 | AB69: =AB50/AB48 -> 0.45533769 | AC69: =AC50/AC48 -> 0.401222 | AD69: =AD50/AD48 -> 0.40458508 | AE69: =AE50/AE48 -> 0.18381531 | AF69: =AF50/AF48 -> 0.2262795 | AG69: =AG50/AG48 -> 0.12811009 | ... AT69: =AT50/AT48 -> 0.13 | AV69: NPV | AW69: =NPV(AW67,AO52:EK52)+Main!F5-Main!F6 -> 2001276.3 | BA69: Just. P/E | BB69: =+(BB67*(1+0.1))/(Main!B17-0.1) -> 23.11461 | BE69: =+BE68/Main!F3-1 -> 0.18560376
A70: Rule of 40 | F70: =+F31+F67 -> 0.27870354 | G70: =+G31+G67 -> 0.40373747 | H70: =+H31+H67 -> 0.63470889 | I70: =+I31+I67 -> 0.65550521 | J70: =+J31+J67 -> 0.65169059 | K70: =+K31+K67 -> 0.60100742 | L70: =+L31+L67 -> 0.61614546 | M70: =+M31+M67 -> 0.68917517 | ... U70: =+U31+U67 -> 0.66986708 | Z70: =+Z31+Z67 -> 0.47318782 | AA70: =+AA31+AA67 -> 0.4770467 | AB70: =+AB31+AB67 -> 0.90306498 | AC70: =+AC31+AC67 -> 0.98419706 | AD70: =+AD31+AD67 -> 0.785374 | AE70: =+AE31+AE67 -> 0.99124545 | AF70: =+AF31+AF67 -> 0.96787171 | AG70: =+AG31+AG67 -> 0.81969286 | ... AT70: =+AT31+AT67 -> 0.6 | AV70: Share | AW70: =+AW69/Main!F1 -> 907.5554
A71: Inc. Margin | F71: =+(F44-B44)/(F30-B30) -> -1.7598372 | G71: =+(G44-C44)/(G30-C30) -> 0.32546427 | H71: =+(H44-D44)/(H30-D30) -> 1.2568408 | I71: =+(I44-E44)/(I30-E30) -> 1.2566071 | J71: =+(J44-F44)/(J30-F30) -> 0.84391805 | K71: =+(K44-G44)/(K30-G30) -> 0.77135181 | L71: =+(L44-H44)/(L30-H30) -> 0.55905634 | M71: =+(M44-I44)/(M30-I30) -> 0.84372734 | ... U71: =+(U44-Q44)/(U30-Q30) -> 0.35065827 | Z71: 0 | AA71: =+(AA44-Z44)/(AA30-Z30) -> -0.8838897 | AB71: =+(AB44-AA44)/(AB30-AA30) -> 0.81422925 | AC71: =+(AC44-AB44)/(AC30-AB30) -> 0.47670875 | AD71: =+(AD44-AC44)/(AD30-AC30) -> 0.22537532 | AE71: =+(AE44-AD44)/(AE30-AD30) -> 0.63872297 | AF71: =+(AF44-AE44)/(AF30-AE30) -> 0.59746446 | AG71: =+(AG44-AF44)/(AG30-AF30) -> 0.31017451 | AH71: =+(AH44-AG44)/(AH30-AG30) -> -0.062386432 | ... AT71: =+(AT44-AS44)/(AT30-AS30) -> 0.81333333 | AV71: Diff | AW71: =+AW70/Main!F3-1 -> 0.40924752 | BA71: Dividend Yield | BB71: =+SUM(P59:S59)/SUM(P54:S54) -> 0.064043761
AV72: EV | AW72: =+AW70*(Main!F1+Main!F2) -> 2312003 | BA72: Debt-to-EBITDA | BB72: =+(S116-S99)/SUM(P88:S88) -> 0.62196323
A74: Advertising % | B74: =+B24/B$30 -> 0.96739286 | C74: =+C24/C$30 -> 0.97675387 | D74: =+D24/D$30 -> 0.98278848 | E74: =+E24/E$30 -> 0.97167729 | F74: =+F24/F$30 -> 0.9810089 | G74: =+G24/G$30 -> 0.98434326 | H74: =+H24/H$30 -> 0.98526914 | I74: =+I24/I$30 -> 0.9649722 | ... S74: =+S24/S$30 -> 0.97634907 | Z74: =+Z24/Z$30 -> 1 | AA74: =+AA24/AA$30 -> 1 | AB74: =+AB24/AB$30 -> 0.88744919 | AC74: =+AC24/AC$30 -> 0.92186748 | AD74: =+AD24/AD$30 -> 0.95264391 | AE74: =+AE24/AE$30 -> 0.9727549 | AF74: =+AF24/AF$30 -> 0.98251052 | AG74: =+AG24/AG$30 -> 0.98522512 | ... AT74: =+AT24/AT$30 -> 0.98416419
A75: Reality Labs % | B75: =+B28/B$30 -> 0.024903254 | C75: =+C28/C$30 -> 0.015682465 | D75: =+D28/D$30 -> 0.010283611 | E75: =+E28/E$30 -> 0.022602207 | F75: =+F28/F$30 -> 0.011834526 | G75: =+G28/G$30 -> 0.0086252695 | H75: =+H28/H$30 -> 0.0061500615 | I75: =+I28/I$30 -> 0.026700905 | ... S75: =+S28/S$30 -> 0.0070886992 | Z75: =+Z28/Z$30 -> 0 | AA75: =+AA28/AA$30 -> 0 | AB75: =+AB28/AB$30 -> 0 | AC75: =+AC28/AC$30 -> 0 | AD75: =+AD28/AD$30 -> 0 | AE75: =+AE28/AE$30 -> 0 | AF75: =+AF28/AF$30 -> 0 | AG75: =+AG28/AG$30 -> 0 | ... AT75: =+AT28/AT$30 -> 0
A76: Other % | B76: =+B26/B$30 -> 0.0077038842 | C76: =+C26/C$30 -> 0.0075636666 | D76: =+D26/D$30 -> 0.0069279065 | E76: =+E26/E$30 -> 0.0057205037 | F76: =+F26/F$30 -> 0.0071565718 | G76: =+G26/G$30 -> 0.0070314697 | H76: =+H26/H$30 -> 0.0085808001 | I76: =+I26/I$30 -> 0.0083268929 | ... S76: =+S26/S$30 -> 0.016562228 | Z76: =+Z26/Z$30 -> 0 | AA76: =+AA26/AA$30 -> 0 | AB76: =+AB26/AB$30 -> 0.11255081 | AC76: =+AC26/AC$30 -> 0.07813252 | AD76: =+AD26/AD$30 -> 0.047356091 | AE76: =+AE26/AE$30 -> 0.027245097 | AF76: =+AF26/AF$30 -> 0.017489484 | AG76: =+AG26/AG$30 -> 0.014774884 | ... AT76: =+AT26/AT$30 -> 0.015835814
A78: Asset Turnover | C78: =+(C30*4)/AVERAGE(B109:C109) -> 0.69035293 | D78: =+(D30*4)/AVERAGE(C109:D109) -> 0.63587313 | E78: =+(E30*4)/AVERAGE(D109:E109) -> 0.7057184 | F78: =+(F30*4)/AVERAGE(E109:F109) -> 0.61898614 | G78: =+(G30*4)/AVERAGE(F109:G109) -> 0.65441099 | H78: =+(H30*4)/AVERAGE(G109:H109) -> 0.64584489 | I78: =+(I30*4)/AVERAGE(H109:I109) -> 0.71964566 | J78: =+(J30*4)/AVERAGE(I109:J109) -> 0.64455501 | ... S78: =+(S30*4)/AVERAGE(R109:S109) -> 0.57549019 | AA78: =+SUM(AA30)/AVERAGE(Z109:AA109) -> 0.4748501 | AB78: =+SUM(AB30)/AVERAGE(AA109:AB109) -> 0.47711764 | AC78: =+SUM(AC30)/AVERAGE(AB109:AC109) -> 0.43089399 | AD78: =+SUM(AD30)/AVERAGE(AC109:AD109) -> 0.40119464 | AE78: =+SUM(AE30)/AVERAGE(AD109:AE109) -> 0.48331671 | AF78: =+SUM(AF30)/AVERAGE(AE109:AF109) -> 0.5439072 | AG78: =+SUM(AG30)/AVERAGE(AF109:AG109) -> 0.61408332 | AH78: =+SUM(AH30)/AVERAGE(AG109:AH109) -> 0.61286448 | ... AN78: =+SUM(AN30)/AVERAGE(AM109:AN109) -> 0.62598911
A79: ROA | C79: =+(C52*4)/AVERAGE(B109:C109) -> 0.16016897 | D79: =+(D52*4)/AVERAGE(C109:D109) -> 0.10083937 | E79: =+(E52*4)/AVERAGE(D109:E109) -> 0.10206753 | F79: =+(F52*4)/AVERAGE(E109:F109) -> 0.12336505 | G79: =+(G52*4)/AVERAGE(F109:G109) -> 0.15927225 | H79: =+(H52*4)/AVERAGE(G109:H109) -> 0.21908339 | I79: =+(I52*4)/AVERAGE(H109:I109) -> 0.25148396 | J79: =+(J52*4)/AVERAGE(I109:J109) -> 0.21869431 | ... S79: =+(S52*4)/AVERAGE(R109:S109) -> 0.15000359 | AA79: =+SUM(AA52)/AVERAGE(Z109:AA109) -> 0.0049453832 | AB79: =+SUM(AB52)/AVERAGE(AA109:AB109) -> 0.090914185 | AC79: =+SUM(AC52)/AVERAGE(AB109:AC109) -> 0.10162268 | AD79: =+SUM(AD52)/AVERAGE(AC109:AD109) -> 0.082530446 | AE79: =+SUM(AE52)/AVERAGE(AD109:AE109) -> 0.17866875 | AF79: =+SUM(AF52)/AVERAGE(AE109:AF109) -> 0.21318518 | AG79: =+SUM(AG52)/AVERAGE(AF109:AG109) -> 0.24317867 | AH79: =+SUM(AH52)/AVERAGE(AG109:AH109) -> 0.16024442 | ... AN79: =+SUM(AN52)/AVERAGE(AM109:AN109) -> 0.18832066
A80: ROE | C80: =+C81*C78*C68 -> 0.21484769 | D80: =+D81*D78*D68 -> 0.14071824 | E80: =+E81*E78*E68 -> 0.14897901 | F80: =+F81*F78*F68 -> 0.18231753 | G80: =+G81*G78*G68 -> 0.24071584 | H80: =+H81*H78*H68 -> 0.33464064 | I80: =+I81*I78*I68 -> 0.37878537 | J80: =+J81*J78*J68 -> 0.32690116 | ... S80: =+S81*S78*S68 -> 0.25110616 | AA80: =+AA81*AA78*AA68 -> 0.0066088908 | AB80: =+AB81*AB78*AB68 -> 0.11019284 | AC80: =+AC81*AC78*AC68 -> 0.11402862 | AD80: =+AD81*AD78*AD68 -> 0.09183953 | AE80: =+AE81*AE78*AE68 -> 0.19759796 | AF80: =+AF81*AF78*AF68 -> 0.23863832 | AG80: =+AG81*AG78*AG68 -> 0.27906155 | AH80: =+AH81*AH78*AH68 -> 0.19964251 | ... AN80: =+AN81*AN78*AN68 -> 0.30238071
A81: Financial Leverage | C81: =+AVERAGE(B109:C109)/AVERAGE(B124:C124) -> 1.3413815 | D81: =+AVERAGE(C109:D109)/AVERAGE(C124:D124) -> 1.3954692 | E81: =+AVERAGE(D109:E109)/AVERAGE(D124:E124) -> 1.4596123 | F81: =+AVERAGE(E109:F109)/AVERAGE(E124:F124) -> 1.4778702 | G81: =+AVERAGE(F109:G109)/AVERAGE(F124:G124) -> 1.5113483 | H81: =+AVERAGE(G109:H109)/AVERAGE(G124:H124) -> 1.5274578 | I81: =+AVERAGE(H109:I109)/AVERAGE(H124:I124) -> 1.5062009 | J81: =+AVERAGE(I109:J109)/AVERAGE(I124:J124) -> 1.4947859 | ... S81: =+AVERAGE(R109:S109)/AVERAGE(R124:S124) -> 1.6740009 | AA81: =+AVERAGE(Z109:AA109)/AVERAGE(Z124:AA124) -> 1.3363759 | AB81: =+AVERAGE(AA109:AB109)/AVERAGE(AA124:AB124) -> 1.2120533 | AC81: =+AVERAGE(AB109:AC109)/AVERAGE(AB124:AC124) -> 1.1220785 | AD81: =+AVERAGE(AC109:AD109)/AVERAGE(AC124:AD124) -> 1.1127958 | AE81: =+AVERAGE(AD109:AE109)/AVERAGE(AD124:AE124) -> 1.1059458 | AF81: =+AVERAGE(AE109:AF109)/AVERAGE(AE124:AF124) -> 1.1193945 | AG81: =+AVERAGE(AF109:AG109)/AVERAGE(AF124:AG124) -> 1.1475577 | AH81: =+AVERAGE(AG109:AH109)/AVERAGE(AG124:AH124) -> 1.2458625 | ... AN81: =+AVERAGE(AM109:AN109)/AVERAGE(AM124:AN124) -> 1.6056694
A82: Financial Leverage % | C82: =+C80-C79 -> 0.054678719 | D82: =+D80-D79 -> 0.039878866 | E82: =+E80-E79 -> 0.046911486 | F82: =+F80-F79 -> 0.05895248 | G82: =+G80-G79 -> 0.081443591 | H82: =+H80-H79 -> 0.11555725 | I82: =+I80-I79 -> 0.12730141 | J82: =+J80-J79 -> 0.10820685 | ... S82: =+S80-S79 -> 0.10110256 | AA82: =+AA80-AA79 -> 0.0016635076 | AB82: =+AB80-AB79 -> 0.019278653 | AC82: =+AC80-AC79 -> 0.012405944 | AD82: =+AD80-AD79 -> 0.0093090836 | AE82: =+AE80-AE79 -> 0.018929211 | AF82: =+AF80-AF79 -> 0.025453137 | AG82: =+AG80-AG79 -> 0.035882882 | AH82: =+AH80-AH79 -> 0.039398089 | ... AN82: =+AN80-AN79 -> 0.11406006
A84: Book Value | B84: =+B124/B56 -> 44.940919 | C84: =+C124/C56 -> 46.357169 | D84: =+D124/D56 -> 46.183104 | E84: =+E124/E56 -> 47.618561 | F84: =+F124/F56 -> 48.072034 | G84: =+G124/G56 -> 51.314319 | H84: =+H124/H56 -> 54.098069 | I84: =+I124/I56 -> 58.238783 | ... S84: =+S124/S56 -> 101.80086 | Z84: =+Z124/Z56 -> 2.8408488 | AA84: =+AA124/AA56 -> 5.4270545 | AB84: =+AB124/AB56 -> 6.1462058 | AC84: =+AC124/AC56 -> 13.54955 | AD84: =+AD124/AD56 -> 15.498773 | AE84: =+AE124/AE56 -> 20.237265 | AF84: =+AF124/AF56 -> 25.151218 | AG84: =+AG124/AG56 -> 28.800753 | ... AN84: =+AN124/AN56 -> 84.39899
A85: R&D Productivity | C85: =+(C44-B44)/(C36-B36) -> -0.1688708 | D85: =+(D44-C44)/(D36-C36) -> -5.6125 | E85: =+(E44-D44)/(E36-D36) -> 1.2229617 | F85: =+(F44-E44)/(F36-E36) -> -2.1230769 | G85: =+(G44-F44)/(G36-F36) -> -58.513514 | H85: =+(H44-G44)/(H36-G36) -> -42.291262 | I85: =+(I44-H44)/(I36-H36) -> 2.0658307 | J85: =+(J44-I44)/(J36-I36) -> 4.7606679 | ... S85: =+(S44-R44)/(S36-R36) -> -1.0353803 | AA85: =+(AA44-Z44)/(AA36-Z36) -> -1.2047478 | AB85: =+(AB44-AA44)/(AB36-AA36) -> 141.625 | AC85: =+(AC44-AB44)/(AC36-AB36) -> 1.7505995 | AD85: =+(AD44-AC44)/(AD36-AC36) -> 0.57255814 | AE85: =+(AE44-AD44)/(AE36-AD36) -> 5.6228468 | AF85: =+(AF44-AE44)/(AF36-AE36) -> 4.2376022 | AG85: =+(AG44-AF44)/(AG36-AF36) -> 1.8697896 | AH85: =+(AH44-AG44)/(AH36-AG36) -> -0.2786294 | ... AN85: =+(AN44-AM44)/(AN36-AM36) -> 1.0294096
A86: PPE Productivity | C86: =+(C52-B52)/(C105-B105) -> -0.12953713 | D86: =+(D52-C52)/(D105-C105) -> -0.37268293 | E86: =+(E52-D52)/(E105-D105) -> 0.044463668 | F86: =+(F52-E52)/(F105-E105) -> 0.22789996 | G86: =+(G52-F52)/(G105-F105) -> 0.54811495 | H86: =+(H52-G52)/(H105-G105) -> 0.99267591 | I86: =+(I52-H52)/(I105-H105) -> 0.50550363 | J86: =+(J52-I52)/(J105-I105) -> -0.71003878 | ... S86: =+(S52-R52)/(S105-R105) -> -0.3877795 | AA86: =+(AA52-Z52)/(AA105-Z105) -> -1.0338428 | AB86: =+(AB52-AA52)/(AB105-AA105) -> 2.9470468 | AC86: =+(AC52-AB52)/(AC105-AB105) -> 1.3271889 | AD86: =+(AD52-AC52)/(AD105-AC105) -> 0.43488372 | AE86: =+(AE52-AD52)/(AE105-AD105) -> 2.2482782 | AF86: =+(AF52-AE52)/(AF105-AE105) -> 1.114425 | AG86: =+(AG52-AF52)/(AG105-AF105) -> 0.56358329 | AH86: =+(AH52-AG52)/(AH105-AG105) -> -0.34088346 | ... AN86: =+(AN52-AM52)/(AN105-AM105) -> -0.034547898
A88: EBITDA | B88: =+B44+B129 -> 10680 | C88: =+C44+C129 -> 10337 | D88: =+D44+D129 -> 7839 | E88: =+E44+E129 -> 8775 | F88: =+F44+F129 -> 9751 | G88: =+G44+G129 -> 12015 | H88: =+H44+H129 -> 16606 | I88: =+I44+I129 -> 19556 | ... S88: =+S44+S129 -> 25131 | Z88: =+Z44+Z129 -> 2079 | AA88: =+AA44+AA129 -> 1187 | AB88: =+AB44+AB129 -> 3815 | AC88: =+AC44+AC129 -> 6237 | AD88: =+AD44+AD129 -> 8170 | AE88: =+AE44+AE129 -> 14769 | AF88: =+AF44+AF129 -> 23228 | AG88: =+AG44+AG129 -> 29228 | ... AT88: =+AT44+AT129 -> 297057.8
F89: =+F88/B88-1 -> -0.086985019 | G89: =+G88/C88-1 -> 0.1623295 | H89: =+H88/D88-1 -> 1.1183824 | I89: =+I88/E88-1 -> 1.228604 | J89: =+J88/F88-1 -> 0.76310122 | K89: =+K88/G88-1 -> 0.53841032 | L89: =+L88/H88-1 -> 0.28730579 | M89: =+M88/I88-1 -> 0.42283698 | ... S89: =+S88/O88-1 -> 0.014041884 | AA89: =+AA88/Z88-1 -> -0.42905243 | AB89: =+AB88/AA88-1 -> 2.2139848 | AC89: =+AC88/AB88-1 -> 0.63486239 | AD89: =+AD88/AC88-1 -> 0.30992464 | AE89: =+AE88/AD88-1 -> 0.80771114 | AF89: =+AF88/AE88-1 -> 0.57275374 | AG89: =+AG88/AF88-1 -> 0.25830894 | AH89: =+AH88/AG88-1 -> 0.01707267 | ... AT89: =+AT88/AS88-1 -> 0.20296296
A90: Adj. EBITDA | B90: =+B44+B129+B132+B133+B134+B135 -> 9896 | C90: =+C44+C129+C132+C133+C134+C135 -> 10073 | D90: =+D44+D129+D132+D133+D134+D135 -> 7259 | E90: =+E44+E129+E132+E133+E134+E135 -> 11320 | F90: =+F44+F129+F132+F133+F134+F135 -> 9894 | G90: =+G44+G129+G132+G133+G134+G135 -> 11322 | H90: =+H44+H129+H132+H133+H134+H135 -> 20070 | I90: =+I44+I129+I132+I133+I134+I135 -> 19617 | ... S90: =+S44+S129+S132+S133+S134+S135 -> 26631 | Z90: =+Z44+Z129+Z132+Z133+Z134+Z135 -> 2053 | AA90: =+AA44+AA129+AA132+AA133+AA134+AA135 -> 1024 | AB90: =+AB44+AB129+AB132+AB133+AB134+AB135 -> 3944 | AC90: =+AC44+AC129+AC132+AC133+AC134+AC135 -> 5987 | AD90: =+AD44+AD129+AD132+AD133+AD134+AD135 -> 7392 | AE90: =+AE44+AE129+AE132+AE133+AE134+AE135 -> 14342 | AF90: =+AF44+AF129+AF132+AF133+AF134+AF135 -> 22875 | AG90: =+AG44+AG129+AG132+AG133+AG134+AG135 -> 29450 | ... AN90: =+AN44+AN129+AN132+AN133+AN134+AN135 -> 119076
A91: Net Cash | Z91: =+Z99+Z100-Z116 -> 3293 | AA91: =+AA99+AA100-AA116 -> 8126 | AB91: =+AB99+AB100-AB116 -> 11449 | AC91: =+AC99+AC100-AC116 -> 11199 | AD91: =+AD99+AD100-AD116 -> 18434 | AE91: =+AE99+AE100-AE116 -> 29449 | AF91: =+AF99+AF100-AF116 -> 41711 | AG91: =+AG99+AG100-AG116 -> 41114 | ... AN91: =+AN99+AN100-AN116 -> 22848 | AO91: =+AN91+AO52 -> 108539.76 | AP91: =+AO91+AP52 -> 223221.41 | AQ91: =+AP91+AQ52 -> 359905.85 | AR91: =+AQ91+AR52 -> 517560.66 | AS91: =+AR91+AS52 -> 701618.13 | AT91: =+AS91+AT52 -> 927707.9
BA92: EV | BB92: =+AW95 -> 1609695.4
A93: NOPAT | B93: =+B44*(1-B69) -> 7143.2039 | C93: =+C44*(1-C69) -> 6827.5038 | D93: =+D44*(1-D69) -> 4464.3615 | E93: =+E44*(1-E69) -> 4841.1364 | F93: =+F44*(1-F69) -> 5646.4956 | G93: =+G44*(1-G69) -> 7870.967 | H93: =+H44*(1-H69) -> 11358.28 | I93: =+I44*(1-I69) -> 13663.406 | ... S93: =+S44*(1-S69) -> 15864.054 | Z93: =+Z44*(1-Z69) -> 1035.9882 | AA93: =+AA44*(1-AA69) -> 57.720648 | AB93: =+AB44*(1-AB69) -> 1527.2331 | AC93: =+AC44*(1-AC69) -> 2990.2974 | AD93: =+AD44*(1-AD69) -> 3706.4579 | AE93: =+AE44*(1-AE69) -> 10142.727 | AF93: =+AF44*(1-AF69) -> 15631.475 | AG93: =+AG44*(1-AG69) -> 21721.393 | ... AT93: =+AT44*(1-AT69) -> 213881.61 | AV93: Terminal | AW93: 0.02 | BA93: Debt (-) | BB93: =+Main!F6 -> 83664
A94: NWC | B94: =+SUM(B100,B101,B102)-SUM(B111,B112,B114) -> 11854 | C94: =+SUM(C100,C101,C102)-SUM(C111,C112,C114) -> 7811 | D94: =+SUM(D100,D101,D102)-SUM(D111,D112,D114) -> 8122 | E94: =+SUM(E100,E101,E102)-SUM(E111,E112,E114) -> 3658 | F94: =+SUM(F100,F101,F102)-SUM(F111,F112,F114) -> 265 | G94: =+SUM(G100,G101,G102)-SUM(G111,G112,G114) -> -4814 | H94: =+SUM(H100,H101,H102)-SUM(H111,H112,H114) -> -4647 | I94: =+SUM(I100,I101,I102)-SUM(I111,I112,I114) -> -5683 | ... S94: =+SUM(S100,S101,S102)-SUM(S111,S112,S114) -> 27405 | Z94: =+SUM(Z100,Z101,Z102)-SUM(Z111,Z112,Z114) -> 2056 | AA94: =+SUM(AA100,AA101,AA102)-SUM(AA111,AA112,AA114) -> 7088 | AB94: =+SUM(AB100,AB101,AB102)-SUM(AB111,AB112,AB114) -> 8578 | AC94: =+SUM(AC100,AC101,AC102)-SUM(AC111,AC112,AC114) -> 7800 | AD94: =+SUM(AD100,AD101,AD102)-SUM(AD111,AD112,AD114) -> 14986 | AE94: =+SUM(AE100,AE101,AE102)-SUM(AE111,AE112,AE114) -> 22993 | AF94: =+SUM(AF100,AF101,AF102)-SUM(AF111,AF112,AF114) -> 37212 | AG94: =+SUM(AG100,AG101,AG102)-SUM(AG111,AG112,AG114) -> 34132 | ... AN94: =+SUM(AN100,AN101,AN102)-SUM(AN111,AN112,AN114) -> 8073 | AO94: =+SUM(AO101,AO102)-SUM(AO111,AO112,AO114) -> -42209.313 | AP94: =+SUM(AP101,AP102)-SUM(AP111,AP112,AP114) -> -51801.34 | AQ94: =+SUM(AQ101,AQ102)-SUM(AQ111,AQ112,AQ114) -> -59049.761 | AR94: =+SUM(AR101,AR102)-SUM(AR111,AR112,AR114) -> -68802.419 | AS94: =+SUM(AS101,AS102)-SUM(AS111,AS112,AS114) -> -76999.405 | AT94: =+SUM(AT101,AT102)-SUM(AT111,AT112,AT114) -> -88091.56 | AV94: Discount | AW94: =+Main!E12 -> 0.10915439 | BA94: Cash (+) | BB94: =+Main!F5 -> 90260
A95: UFCF | C95: =+C93+C129-C144-(C94-B94) -> 5277.5038 | D95: =+D93+D129-D144-(D94-C94) -> -3046.6385 | E95: =+E93+E129-E144-(E94-D94) -> 2638.1364 | F95: =+F93+F129-F144-(F94-E94) -> 4740.4956 | G95: =+G93+G129-G144-(G94-F94) -> 9438.967 | H95: =+H93+H129-H144-(H94-G94) -> 7553.2799 | I95: =+I93+I129-I144-(I94-H94) -> 10279.406 | J95: =+J93+J129-J144-(J94-I94) -> 5989.6834 | ... S95: =+S93+S129-S144-(S94-R94) -> -21321.946 | AA95: =+AA93+AA129-AA144-(AA94-Z94) -> -5560.2794 | AB95: =+AB93+AB129-AB144-(AB94-AA94) -> -313.76688 | AC95: =+AC93+AC129-AC144-(AC94-AB94) -> 3180.2974 | AD95: =+AD93+AD129-AD144-(AD94-AC94) -> -4057.5421 | AE95: =+AE93+AE129-AE144-(AE94-AD94) -> -13.272807 | AF95: =+AF93+AF129-AF144-(AF94-AE94) -> -2295.5247 | AG95: =+AG93+AG129-AG144-(AG94-AF94) -> 15201.393 | AH95: =+AH93+AH129-AH144-(AH94-AG94) -> 18916.628 | ... AT95: =+AT93+AT129-AT144-(AT94-AS94) -> 199365.34 | AV95: EV | AW95: =+NPV(AW94,AO95:AT95,AT95+AW96) -> 1609695.4 | BA95: Equity Value | BB95: =+BB92-BB93+BB94 -> 1616291.4
A96: ROIC | C96: =+(C93*4)/(AVERAGE(B116:C116)+AVERAGE(B124:C124)) -> 0.21936196 | D96: =+(D93*4)/(AVERAGE(C116:D116)+AVERAGE(C124:D124)) -> 0.13747971 | E96: =+(E93*4)/(AVERAGE(D116:E116)+AVERAGE(D124:E124)) -> 0.1436262 | F96: =+(F93*4)/(AVERAGE(E116:F116)+AVERAGE(E124:F124)) -> 0.16708327 | G96: =+(G93*4)/(AVERAGE(F116:G116)+AVERAGE(F124:G124)) -> 0.21929662 | H96: =+(H93*4)/(AVERAGE(G116:H116)+AVERAGE(G124:H124)) -> 0.28968645 | I96: =+(I93*4)/(AVERAGE(H116:I116)+AVERAGE(H124:I124)) -> 0.32843838 | J96: =+(J93*4)/(AVERAGE(I116:J116)+AVERAGE(I124:J124)) -> 0.28398901 | ... S96: =+(S93*4)/(AVERAGE(R116:S116)+AVERAGE(R124:S124)) -> 0.19606008 | AA96: =+AA93/(AVERAGE(Z116:AA116)+AVERAGE(Z124:AA124)) -> 0.0063590005 | AB96: =+AB93/(AVERAGE(AA116:AB116)+AVERAGE(AA124:AB124)) -> 0.10633477 | AC96: =+AC93/(AVERAGE(AB116:AC116)+AVERAGE(AB124:AC124)) -> 0.11597942 | AD96: =+AD93/(AVERAGE(AC116:AD116)+AVERAGE(AC124:AD124)) -> 0.092299172 | AE96: =+AE93/(AVERAGE(AD116:AE116)+AVERAGE(AD124:AE124)) -> 0.19616151 | AF96: =+AF93/(AVERAGE(AE116:AF116)+AVERAGE(AE124:AF124)) -> 0.23410751 | AG96: =+AG93/(AVERAGE(AF116:AG116)+AVERAGE(AF124:AG124)) -> 0.27413195 | AH96: =+AH93/(AVERAGE(AG116:AH116)+AVERAGE(AG124:AH124)) -> 0.19299634 | ... AN96: =+AN93/(AVERAGE(AM116:AN116)+AVERAGE(AM124:AN124)) -> 0.24039124 | AV96: TV | AW96: =+AT95*(1+AW93)/(AW94-AW93) -> 2280904.4 | AX96: =+AT88*23 -> 6832329.3 | AY96: Peers | BA96: Shares | BB96: =+SUM(Main!F1:F2) -> 2547.5062
AV97: Diff | AW97: =+AW95/Main!F7-1 -> -0.014873068 | AX97: =+AT88*29 -> 8614676.1 | AY97: Precedent M&A | BA97: Price | BB97: =+BB95/BB96 -> 634.46025
BB98: =+BB97/Main!F3-1 -> -0.014813271
A99: Cash | B99: 14886 | C99: 12681 | D99: 14308 | E99: 14681 | F99: 11551 | G99: 28785 | H99: 36890 | I99: 41862 | J99: 32307 | K99: 32045 | L99: 43852 | M99: 43889 | N99: 28750 | O99: 12005 | P99: 10187 | Q99: 35873 | R99: 23426 | S99: 15462 | Z99: 1512 | AA99: 2384 | AB99: 3323 | AC99: 4315 | AD99: 4907 | AE99: 8903 | AF99: 8079 | AG99: 10019 | AH99: 19079 | AI99: 17576 | AJ99: 16601 | AK99: 14681 | AL99: 41862 | AM99: 43889 | AN99: 35873
A100: Mkt. Sec | B100: 29004 | C100: 27808 | D100: 27468 | E100: 26057 | F100: 25888 | G100: 24661 | H100: 24233 | I100: 23541 | J100: 25813 | K100: 26035 | L100: 27048 | M100: 33296 | N100: 41480 | O100: 35066 | P100: 34261 | Q100: 45719 | R100: 57754 | S100: 74798 | Z100: 2396 | AA100: 7242 | AB100: 8126 | AC100: 6884 | AD100: 13527 | AE100: 20546 | AF100: 33632 | AG100: 31095 | AH100: 35776 | AI100: 44378 | AJ100: 31397 | AK100: 26057 | AL100: 23541 | AM100: 33926 | AN100: 45719
A101: A/R | B101: 11390 | C101: 11525 | D101: 11227 | E101: 13466 | F101: 11044 | G101: 12511 | H101: 12944 | I101: 16169 | J101: 13430 | K101: 14505 | L101: 14700 | M101: 16994 | N101: 14514 | O101: 16561 | P101: 17297 | Q101: 19769 | R101: 17470 | S101: 21752 | Z101: 547 | AA101: 719 | AB101: 1109 | AC101: 1678 | AD101: 2559 | AE101: 3993 | AF101: 5832 | AG101: 7587 | AH101: 9518 | AI101: 11335 | AJ101: 14039 | AK101: 13466 | AL101: 16169 | AM101: 16994 | AN101: 19769 | AO101: =+(AO161/365)*AO30 -> 23961.754 | AP101: =+(AP161/365)*AP30 -> 27908.396 | AQ101: =+(AQ161/365)*AQ30 -> 32094.656 | AR101: =+(AR161/365)*AR30 -> 35479.183 | AS101: =+(AS161/365)*AS30 -> 40091.477 | AT101: =+(AT161/365)*AT30 -> 43499.252
A102: Prepaid Exp | B102: 3985 | C102: 3973 | D102: 5312 | E102: 5345 | F102: 4000 | G102: 3603 | H102: 4311 | I102: 3793 | J102: 3780 | K102: 3846 | L102: 5467 | M102: 5236 | N102: 5483 | O102: 9981 | P102: 11373 | Q102: 7361 | R102: 11115 | S102: 13463 | Z102: 149 | AA102: 471 | AB102: 461 | AC102: 513 | AD102: 659 | AE102: 959 | AF102: 1020 | AG102: 1779 | AH102: 1852 | AI102: 2381 | AJ102: 4629 | AK102: 5345 | AL102: 3793 | AM102: 5236 | AN102: 7361 | AO102: =+AO30*0.035 -> 9003.2768 | AP102: =+AP30*0.035 -> 10803.932 | AQ102: =+AQ30*0.035 -> 12424.522 | AR102: =+AR30*0.035 -> 14163.955 | AS102: =+AS30*0.035 -> 16005.269 | AT102: =+AT30*0.035 -> 17925.902
B103: =+B102/B30 -> 0.1427906 | C103: =+C102/C30 -> 0.13784609 | D103: =+D102/D30 -> 0.19167208 | E103: =+E102/E30 -> 0.16617441 | F103: =+F102/F30 -> 0.13964043 | G103: =+G102/G30 -> 0.11259727 | H103: =+H102/H30 -> 0.12625198 | I103: =+I102/I30 -> 0.094562589 | ... S103: =+S102/S30 -> 0.22142728 | Z103: =+Z102/Z30 -> 0.040150903 | AA103: =+AA102/AA30 -> 0.092552564 | AB103: =+AB102/AB30 -> 0.058561992 | AC103: =+AC102/AC30 -> 0.041151933 | AD103: =+AD102/AD30 -> 0.036758144 | AE103: =+AE102/AE30 -> 0.034698603 | AF103: =+AF102/AF30 -> 0.025090399 | AG103: =+AG102/AG30 -> 0.031860024 | ... AT103: =+AT102/AT30 -> 0.035
A104: Non Mrk. Sec | B104: 6775 | C104: 6536 | D104: 6528 | E104: 6201 | F104: 6167 | G104: 6208 | H104: 6142 | I104: 6141 | J104: 6218 | K104: 6207 | L104: 6071 | M104: 6070 | N104: 6168 | O104: 21988 | P104: 25074 | Q104: 27524 | R104: 28410 | S104: 30157 | Z104: 0 | AA104: 0 | AB104: 0 | AC104: 0 | AD104: 0 | AE104: 0 | AF104: 0 | AG104: 0 | AH104: 0 | AI104: 6234 | AJ104: 6775 | AK104: 6201 | AL104: 6141 | AM104: 6070 | AN104: 27524
A105: PP&E | B105: 61582 | C105: 67588 | D105: 73738 | E105: 79518 | F105: 84156 | G105: 87949 | H105: 91772 | I105: 96587 | J105: 98908 | K105: 102959 | L105: 112162 | M105: 121346 | N105: 133567 | O105: 147039 | P105: 160270 | Q105: 176400 | R105: 194776 | S105: 225724 | Z105: 1475 | AA105: 2391 | AB105: 2882 | AC105: 3967 | AD105: 5687 | AE105: 8591 | AF105: 13721 | AG105: 24683 | AH105: 35323 | AI105: 45633 | AJ105: 57809 | AK105: 79518 | AL105: 96587 | AM105: 121346 | AN105: 176400
A106: Op Lease ROU | B106: 12241 | C106: 14130 | D106: 13641 | E106: 12673 | F106: 12899 | G106: 12955 | H106: 13033 | I106: 13294 | J106: 13555 | K106: 14058 | L106: 14812 | M106: 14922 | N106: 15505 | O106: 15662 | P106: 17372 | Q106: 20404 | R106: 23268 | S106: 23985 | AA106: 0 | AB106: 0 | AC106: 3929 | AD106: 3246 | AE106: 2535 | AF106: 1884 | AG106: 0 | AH106: 9460 | AI106: 9348 | AJ106: 12155 | AK106: 12673 | AL106: 13294 | AM106: 14922 | AN106: 20404
A107: Goodwill | B107: 19923 | C107: 20229 | D107: 20268 | E107: 20306 | F107: 20649 | G107: 20659 | H107: 20668 | I107: 20654 | J107: 20654 | K107: 20654 | L107: 20654 | M107: 20654 | N107: 20654 | O107: 20654 | P107: 21158 | Q107: 24534 | R107: 24748 | S107: 23406 | Z107: 162 | AA107: 1388 | AB107: 1722 | AC107: 17981 | AD107: 18026 | AE107: 18122 | AF107: 18221 | AG107: 18301 | AH107: 18715 | AI107: 19050 | AJ107: 19197 | AK107: 20306 | AL107: 20654 | AM107: 20654 | AN107: 24534
A108: Other | B108: =+910+3522 -> 4432 | C108: =+965+4344 -> 5309 | D108: =+875+5529 -> 6404 | E108: =+6583+897 -> 7480 | F108: =+7188+949 -> 8137 | G108: =+8501+856 -> 9357 | H108: =+5468+813 -> 6281 | I108: 7582 | J108: 8179 | K108: 9929 | L108: 11642 | M108: 13017 | N108: 14092 | O108: 15788 | P108: 6852 | Q108: 8437 | R108: 14283 | S108: 21209 | Z108: 90 | AA108: =+57+451 -> 508 | AB108: =+221+51 -> 272 | AC108: 699 | AD108: 796 | AE108: 1312 | AF108: 2135 | AG108: =+2576+1294 -> 3870 | AH108: =+894+2759 -> 3653 | AI108: =+2758+623 -> 3381 | AJ108: =+634+2751 -> 3385 | AK108: =+6583+897 -> 7480 | AL108: 7582 | AM108: 13017 | AN108: 8437
...

Sheet Bond
A1: Main
B3: isin | C3: coupon | D3: couponType | E3: maturityDate | F3: callable | G3: currency | H3: Next Call Date
B4: US30303M8B15 | C4: 3.5 | D4: Fixed Listing | E4: 15/08/2027 | F4: Y | G4: USD
B5: US30303M8G02 | C5: 3.5 | D5: Fixed Listing | E5: 15/08/2027 | F5: Y | G5: USD
B6: USU59197AB66 | C6: 3.5 | D6: Fixed Listing | E6: 15/08/2027 | F6: Y | G6: USD
B7: US30303M8L96 | C7: 4.6 | D7: Fixed Listing | E7: 15/05/2028 | F7: Y | G7: USD
B8: US30303M8S40 | C8: 4.3 | D8: Fixed Listing | E8: 15/08/2029 | F8: Y | G8: USD
B9: US30303M8M79 | C9: 4.8 | D9: Fixed Listing | E9: 15/05/2030 | F9: Y | G9: USD
B10: US30303MAB81 | C10: 4.2 | D10: Fixed Listing | E10: 15/11/2030 | F10: Y | G10: USD
B11: US30303M8T23 | C11: 4.55 | D11: Fixed Listing | E11: 15/08/2031 | F11: Y | G11: USD
B12: US30303M8D70 | C12: 3.85 | D12: Fixed Listing | E12: 15/08/2032 | F12: Y | G12: USD
B13: US30303M8H84 | C13: 3.85 | D13: Fixed Listing | E13: 15/08/2032 | F13: Y | G13: USD
B14: USU59197AD23 | C14: 3.85 | D14: Fixed Listing | E14: 15/08/2032 | F14: Y | G14: USD
B15: US30303MAC64 | C15: 4.6 | D15: Fixed Listing | E15: 15/11/2032 | F15: Y | G15: USD
... B30: US30303M8W51 | C30: 5.55 | D30: Fixed Listing | E30: 15/08/2064 | F30: Y | G30: USD
B31: US30303M8Y18 | C31: 5.75 | D31: Fixed Listing | E31: 15/11/2065 | F31: Y | G31: USD | H31: 60402
C32: =+AVERAGE(C4:C31) -> 4.6482143

Sheet Board
A1: Main
A2: Mark Zuckerberg | B2: META CEO | G2: auditors | H2: EY
A5: Robert M. Kimmitt | B5: MD Lehman Brothers, General Counsel and Deputy Secretary of Department of Treasury, Law Background
B6: -> | C6: Privacy and Product compliance
A8: Peggy Alford | B8: eBay Director of Accounting Policy, Cfo rent.com (eBay), Executive roles Paypal
A11: Marc L. Andreesen
A14: John Arnold | B14: Enron VP, Centaurus Enercy and Centaurus Capital CEO
B15: -> | C15: Risk Oversight
A17: Patrick Collison | B17: CEO Stripe
A20: John Elkann | B20: Exor CEO, Chairman Ferrari and Stellantins | E20: -> | F20: Powerful italian family
A23: Andrew W. Houston | B23: Dropbox CEO
A26: Nancy Killefer | B26: McKinsey and Department of Treasury
A29: Dina Powell McCormick | B29: US Department of State, Excecutive Office of the President, Goldman Sachs
A32: Charles Songhurst | B32: Microsoft General Manager
A35: Hock E. Tan | B35: Broadcom CEO, Commodore VP of Finance
A38: Tracey T. Travis | B38: ?
A41: Dana White | B41: UFC CEO
A44: Tony Xu | B44: DoorDash CEO
