Workbook

Sheet Main
A1: Microsoft Corporation | D1: Price | E1: 484
D2: Share | E2: 7425.5455 | F2: Q426
D3: MC | E3: =+E2*E1 -> 3593964
D4: Cash | E4: 113191 | F4: Q426
D5: Debt | E5: =+31067+9227 -> 40294 | F5: Q426
D6: EV | E6: =+E3-E4+E5 -> 3521067
D8: Foundation | E8: 1975
A11: CAPM | B11: =+0.04+1.11*(0.1-0.04) -> 0.1066 | D11: WACC | E11: =+(E3/(E3+E5))*B11+(E5/(E5+E3))*B12*(1-0.17) -> 0.10594584
A12: Cost of Debt | B12: =+0.0495 + (B18/100) -> 0.057347826
A13: P/FCF | B13: =+E3/SUM(Model!R122:U122) -> 53.651664
A14: P/E | B14: =+E1/SUM(Model!R41:U41) -> 22.894938
A15: EV/EBITDA | B15: =+E6/SUM(Model!R65:U65) -> 16.816474
A16: EV/FCF | B16: =+E6/SUM(Model!R122:U122) -> 52.563438
A17: Inc. Margin | B17: =+((Model!U31+Model!T31+Model!S31+Model!R31)-(Model!Q31+Model!P31+Model!O31+Model!N31))/((Model!U13+Model!T13+Model!S13+Model!R13)-(Model!Q13+Model!P13+Model!O13+Model!N13)) -> 0.53295421
A18: Cr. Spread | B18: =+'[1]Credit Spread US'!J6 -> 0.78478261
A19: Rating | B19: AAA | C19: Aaa
B20: S&P | C20: Moody’s
A23: Productivity and Business Process
B24: -> | C24: Microsoft 365 Commercial Products
C25: AI-powered business and productivity solutions
B26: -> | C26: Microsoft 365 Consumer Products
B27: -> | C27: Linkedin
C28: Premium subscriptions and monetized solutions
B29: -> | C29: Dynamics Products (Dynamics 365)
C30: Enterprise resource planning, customer relationship management and supply chain management
A32: Intelligent Cloud
B33: -> | C33: public and private server products, cloud and AI based services. GitHub cloud services, Windows Server, Visual Studio
C34: Azure
B35: -> | C35: Enterprice and partner services (Enterprise support services, Industry solutions, Microsoft Partner Network)
A37: More Personal Computing
B38: product and services
B39: -> | C39: Windows devices (including licences)
C40: Windows Licences, Surface (PC), PC accessories
B41: -> | C41: Gaming (Xbox hardware and software)
B42: -> | C42: Search and news advertising (Bing, Copilot, Microsoft News)

Sheet Model
A1: Main | F1: 09/22 | J1: 09/23 | K1: 12/23 | L1: 03/24 | M1: 06/24 | N1: 09/24 | O1: 12/24 | P1: 03/25 | Q1: 06/25 | R1: 09/25 | S1: 12/25 | T1: 03/26 | U1: 06/26
A2: in Millions | B2: Q122 | C2: Q222 | D2: Q322 | E2: Q422 | F2: Q123 | G2: Q223 | H2: Q323 | I2: Q423 | J2: Q124 | K2: Q224 | L2: Q324 | M2: Q424 | N2: Q125 | O2: Q225 | P2: Q325 | Q2: Q425 | R2: Q126 | S2: Q226 | T2: Q326 | U2: Q426 | V2: Q127 | W2: Q227 | AB2: =+AC2-1 -> 2010 | AC2: =+AD2-1 -> 2011 | AD2: =+AE2-1 -> 2012 | AE2: =+AF2-1 -> 2013 | AF2: =+AG2-1 -> 2014 | AG2: =+AH2-1 -> 2015 | AH2: =+AI2-1 -> 2016 | AI2: =+AJ2-1 -> 2017 | ... AK2: =+AL2-1 -> 2019 | AL2: 2020 | AM2: =+AL2+1 -> 2021 | AN2: =+AM2+1 -> 2022 | AO2: =+AN2+1 -> 2023 | AP2: =+AO2+1 -> 2024 | AQ2: =+AP2+1 -> 2025 | AR2: =+AQ2+1 -> 2026 | AS2: =+AR2+1 -> 2027 | AT2: =+AS2+1 -> 2028 | ... BB2: =+BA2+1 -> 2036
A3: Productivity | K3: 25854 | L3: 27113 | N3: 28317 | O3: 29437 | P3: 29944 | Q3: =+AQ3-P3-O3-N3 -> 33112 | R3: 33020 | S3: 34116 | T3: 35013 | U3: =+AR3-T3-S3-R3 -> 37847 | AG3: 26430 | AH3: 26467 | AI3: 30444 | AJ3: 35865 | AK3: 41160 | AL3: 46398 | AM3: 53915 | AN3: 63364 | AO3: 69274 | AP3: 106820 | AQ3: 120810 | AR3: 139996
O4: =+O3/K3-1 -> 0.13858591 | P4: =+P3/L3-1 -> 0.10441486 | Q4: =+Q3/M3-1 -> #DIV/0! | R4: =+R3/N3-1 -> 0.16608398 | S4: =+S3/O3-1 -> 0.15894962 | T4: =+T3/P3-1 -> 0.16928266 | U4: =+U3/Q3-1 -> 0.14299952 | AH4: =+AH3/AG3-1 -> 0.0013999243 | AI4: =+AI3/AH3-1 -> 0.15026259 | AJ4: =+AJ3/AI3-1 -> 0.17806464 | AK4: =+AK3/AJ3-1 -> 0.14763697 | AL4: =+AL3/AK3-1 -> 0.12725948 | AM4: =+AM3/AL3-1 -> 0.16201129 | AN4: =+AN3/AM3-1 -> 0.17525735 | AO4: =+AO3/AN3-1 -> 0.093270627 | ... AR4: =+AR3/AQ3-1 -> 0.15881136
A5: Intelligent Cloud | K5: 21525 | L5: 22141 | N5: 24092 | O5: 25544 | P5: 26751 | Q5: =+AQ5-P5-O5-N5 -> 29878 | R5: 30897 | S5: 32907 | T5: 34681 | U5: =+AR5-T5-S5-R5 -> 39306 | AG5: 23715 | AH5: 25042 | AI5: 27440 | AJ5: 32219 | AK5: 38985 | AL5: 48366 | AM5: 60080 | AN5: 74965 | AO5: 87907 | AP5: 87464 | AQ5: 106265 | AR5: 137791
O6: =+O5/K5-1 -> 0.18671312 | P6: =+P5/L5-1 -> 0.20821101 | Q6: =+Q5/M5-1 -> #DIV/0! | R6: =+R5/N5-1 -> 0.28245891 | S6: =+S5/O5-1 -> 0.28824773 | T6: =+T5/P5-1 -> 0.29643752 | U6: =+U5/Q5-1 -> 0.3155499 | AH6: =+AH5/AG5-1 -> 0.055956146 | AI6: =+AI5/AH5-1 -> 0.095759125 | AJ6: =+AJ5/AI5-1 -> 0.17416181 | AK6: =+AK5/AJ5-1 -> 0.21000031 | AL6: =+AL5/AK5-1 -> 0.24063101 | AM6: =+AM5/AL5-1 -> 0.24219493 | AN6: =+AN5/AM5-1 -> 0.247753 | AO6: =+AO5/AN5-1 -> 0.17264057 | ... AR6: =+AR5/AQ5-1 -> 0.29667341
A7: More PC | K7: 14641 | L7: 12604 | N7: 13176 | O7: 14651 | P7: 13371 | Q7: =+AQ7-P7-O7-N7 -> 13451 | R7: 13756 | S7: 14250 | T7: 13192 | U7: =+AR7-T7-S7-R7 -> 12854 | AG7: 43435 | AH7: =+40434-6643 -> 33791 | AI7: =+38773-6707 -> 32066 | AJ7: 42276 | AK7: 45698 | AL7: 48251 | AM7: 54093 | AN7: 59941 | AO7: 54734 | AP7: 50838 | AQ7: 54649 | AR7: 54052
O8: =+O7/K7-1 -> 0.00068301346 | P8: =+P7/L7-1 -> 0.060853697 | Q8: =+Q7/M7-1 -> #DIV/0! | R8: =+R7/N7-1 -> 0.044019429 | S8: =+S7/O7-1 -> -0.027370145 | T8: =+T7/P7-1 -> -0.013387181 | U8: =+U7/Q7-1 -> -0.044383317 | AH8: =+AH7/AG7-1 -> -0.22203292 | AI8: =+AI7/AH7-1 -> -0.051049096 | AJ8: =+AJ7/AI7-1 -> 0.31840579 | AK8: =+AK7/AJ7-1 -> 0.080944271 | AL8: =+AL7/AK7-1 -> 0.055866778 | AM8: =+AM7/AL7-1 -> 0.12107521 | AN8: =+AN7/AM7-1 -> 0.10811011 | AO8: =+AO7/AN7-1 -> -0.086868754 | ... AR8: =+AR7/AQ7-1 -> -0.010924262
A9: Product | D9: 17366 | E9: 17956 | F9: 15741 | H9: 15588 | I9: 16853 | J9: 15535 | K9: 18941 | L9: 17080 | M9: 13217 | N9: 15272 | O9: 16219 | P9: 15319 | Q9: 17136 | R9: 15922 | S9: 16451 | T9: 15089 | U9: 17234 | AF9: 72948 | AG9: 75956 | AH9: 61502 | AI9: 57190 | AJ9: 64497 | AK9: 66069 | AL9: 68041 | AM9: 71074 | AN9: 72732 | AO9: 64699 | AP9: 64773 | AQ9: 63946 | AR9: 64696
F10: =+F9/B9-1 -> #DIV/0! | G10: =+G9/C9-1 -> #DIV/0! | H10: =+H9/D9-1 -> -0.10238397 | I10: =+I9/E9-1 -> -0.061427935 | J10: =+J9/F9-1 -> -0.013086843 | K10: =+K9/G9-1 -> #DIV/0! | L10: =+L9/H9-1 -> 0.095714652 | M10: =+M9/I9-1 -> -0.21574794 | ... U10: =+U9/Q9-1 -> 0.0057189542 | AG10: =+AG9/AF9-1 -> 0.041234852 | AH10: =+AH9/AG9-1 -> -0.19029438 | AI10: =+AI9/AH9-1 -> -0.070111541 | AJ10: =+AJ9/AI9-1 -> 0.12776709 | AK10: =+AK9/AJ9-1 -> 0.024373227 | AL10: =+AL9/AK9-1 -> 0.029847584 | AM10: =+AM9/AL9-1 -> 0.044576064 | AN10: =+AN9/AM9-1 -> 0.023327799 | ... AR10: =+AR9/AQ9-1 -> 0.011728646
A11: Service and other | D11: 31994 | E11: 33909 | F11: 34381 | H11: 37269 | I11: 39336 | J11: 40982 | K11: 43079 | L11: 44778 | M11: 51510 | N11: 50313 | O11: 53413 | P11: 54747 | Q11: 59305 | R11: 61751 | S11: 64822 | T11: 67797 | U11: 72773 | AF11: 13885 | AG11: 17624 | AH11: 23818 | AI11: 32760 | AJ11: 45863 | AK11: 59774 | AL11: 74974 | AM11: 97014 | AN11: 125538 | AO11: 147216 | AP11: 180349 | AQ11: 217778 | AR11: 267143
F12: =+F11/B11-1 -> #DIV/0! | G12: =+G11/C11-1 -> #DIV/0! | H12: =+H11/D11-1 -> 0.16487466 | I12: =+I11/E11-1 -> 0.16004601 | J12: =+J11/F11-1 -> 0.19199558 | K12: =+K11/G11-1 -> #DIV/0! | L12: =+L11/H11-1 -> 0.20148112 | M12: =+M11/I11-1 -> 0.30948749 | ... U12: =+U11/Q11-1 -> 0.22709721 | AG12: =+AG11/AF11-1 -> 0.2692834 | AH12: =+AH11/AG11-1 -> 0.35145256 | AI12: =+AI11/AH11-1 -> 0.37543035 | AJ12: =+AJ11/AI11-1 -> 0.39996947 | AK12: =+AK11/AJ11-1 -> 0.3033164 | AL12: =+AL11/AK11-1 -> 0.25429116 | AM12: =+AM11/AL11-1 -> 0.29396858 | AN12: =+AN11/AM11-1 -> 0.29401942 | ... AR12: =+AR11/AQ11-1 -> 0.22667579
A13: Revenue | B13: =+B11+B9 -> 0 | C13: =+C11+C9 -> 0 | D13: =+D11+D9 -> 49360 | E13: =+E11+E9 -> 51865 | F13: =+F11+F9 -> 50122 | G13: =+G11+G9 -> 0 | H13: =+H11+H9 -> 52857 | I13: =+I11+I9 -> 56189 | ... W13: =+W11+W9 -> 0 | AB13: 62484 | AC13: 69943 | AD13: 73723 | AE13: 77849 | AF13: =+AF11+AF9 -> 86833 | AG13: =+AG11+AG9 -> 93580 | AH13: =+AH11+AH9 -> 85320 | AI13: =+AI11+AI9 -> 89950 | AJ13: =+AJ11+AJ9 -> 110360 | AK13: =+AK11+AK9 -> 125843 | AL13: =+AL11+AL9 -> 143015 | AM13: =+AM11+AM9 -> 168088 | ... AR13: =+AR11+AR9 -> 331839 | AS13: =+AR13*1.17 -> 388251.63 | AT13: =+AS13*1.16 -> 450371.89 | AU13: =+AT13*1.15 -> 517927.67 | AV13: =+AU13*1.14 -> 590437.55 | AW13: =+AV13*1.13 -> 667194.43 | AX13: =+AW13*1.12 -> 747257.76 | AY13: =+AX13*1.11 -> 829456.12 | AZ13: =+AY13*1.11 -> 920696.29 | BA13: =+AZ13*1.11 -> 1021972.9 | BB13: =+BA13*1.11 -> 1134389.9
F14: =+F13/B13-1 -> #DIV/0! | G14: =+G13/C13-1 -> #DIV/0! | H14: =+H13/D13-1 -> 0.07084684 | I14: =+I13/E13-1 -> 0.083370288 | J14: =+J13/F13-1 -> 0.12758868 | K14: =+K13/G13-1 -> #DIV/0! | L14: =+L13/H13-1 -> 0.17028965 | M14: =+M13/I13-1 -> 0.15195145 | ... U14: =+U13/Q13-1 -> 0.17747021 | AC14: =+AC13/AB13-1 -> 0.11937456 | AD14: =+AD13/AC13-1 -> 0.054044007 | AE14: =+AE13/AD13-1 -> 0.055966252 | AF14: =+AF13/AE13-1 -> 0.1154029 | AG14: =+AG13/AF13-1 -> 0.077700874 | AH14: =+AH13/AG13-1 -> -0.088266724 | AI14: =+AI13/AH13-1 -> 0.054266292 | AJ14: =+AJ13/AI13-1 -> 0.22690384 | ... BB14: =+BB13/BA13-1 -> 0.11
A15: Product | D15: 4584 | E15: 4357 | F15: 4302 | H15: 3941 | I15: 3871 | J15: 3531 | K15: 5964 | L15: 4339 | M15: 1438 | N15: 3294 | O15: 3856 | P15: 3037 | Q15: 3314 | R15: 2922 | S15: 3505 | T15: 2733 | U15: 2938 | AF15: 16681 | AG15: 21410 | AH15: 17880 | AI15: 15175 | AJ15: 15420 | AK15: 16273 | AL15: 16017 | AM15: 18219 | AN15: 19064 | AO15: 17804 | AP15: 15272 | AQ15: 13501 | AR15: 12098
D16: =+D15/D$13 -> 0.09286872 | E16: =+E15/E$13 -> 0.084006555 | F16: =+F15/F$13 -> 0.085830573 | G16: =+G15/G$13 -> #DIV/0! | H16: =+H15/H$13 -> 0.074559661 | I16: =+I15/I$13 -> 0.068892488 | J16: =+J15/J$13 -> 0.062476777 | K16: =+K15/K$13 -> 0.096162528 | ... W16: =+W15/W$13 -> #DIV/0! | AG16: =+AG15/AF15-1 -> 0.28349619 | AH16: =+AH15/AG15-1 -> -0.16487623 | AI16: =+AI15/AH15-1 -> -0.15128635 | AJ16: =+AJ15/AI15-1 -> 0.016144975 | AK16: =+AK15/AJ15-1 -> 0.055317769 | AL16: =+AL15/AK15-1 -> -0.01573158 | AM16: =+AM15/AL15-1 -> 0.13747893 | AN16: =+AN15/AM15-1 -> 0.046380153 | ... AR16: =+AR15/AQ15-1 -> -0.10391823
A17: Service and Other | D17: 11031 | E17: 12072 | F17: 11150 | H17: 12187 | I17: 12924 | J17: 12771 | K17: 13659 | L17: 14166 | M17: 18246 | N17: 16805 | O17: 17943 | P17: 18882 | Q17: 20700 | R17: 21121 | S17: 22473 | T17: 24095 | U17: 26587 | AF17: 10397 | AG17: 11628 | AH17: 14900 | AI17: 19086 | AJ17: 22933 | AK17: 26637 | AL17: 30061 | AM17: 34013 | AN17: 43586 | AO17: 48059 | AP17: 58842 | AQ17: 74330 | AR17: 94276
D18: =+D17/D$13 -> 0.22348055 | E18: =+E17/E$13 -> 0.23275812 | F18: =+F17/F$13 -> 0.2224572 | G18: =+G17/G$13 -> #DIV/0! | H18: =+H17/H$13 -> 0.23056549 | I18: =+I17/I$13 -> 0.23000943 | J18: =+J17/J$13 -> 0.22596741 | K18: =+K17/K$13 -> 0.22023541 | ... W18: =+W17/W$13 -> #DIV/0! | AG18: =+AG17/AF17-1 -> 0.11839954 | AH18: =+AH17/AG17-1 -> 0.28138975 | AI18: =+AI17/AH17-1 -> 0.2809396 | AJ18: =+AJ17/AI17-1 -> 0.20156135 | AK18: =+AK17/AJ17-1 -> 0.16151398 | AL18: =+AL17/AK17-1 -> 0.128543 | AM18: =+AM17/AL17-1 -> 0.13146602 | AN18: =+AN17/AM17-1 -> 0.28145121 | ... AR18: =+AR17/AQ17-1 -> 0.26834387
A19: COGS | B19: =+B17+B15 -> 0 | C19: =+C17+C15 -> 0 | D19: =+D17+D15 -> 15615 | E19: =+E17+E15 -> 16429 | F19: =+F17+F15 -> 15452 | G19: =+G17+G15 -> 0 | H19: =+H17+H15 -> 16128 | I19: =+I17+I15 -> 16795 | ... W19: =+W17+W15 -> 0 | AB19: 12395 | AC19: 15577 | AD19: 17530 | AE19: 20249 | AF19: =+AF17+AF15 -> 27078 | AG19: =+AG17+AG15 -> 33038 | AH19: =+AH17+AH15 -> 32780 | AI19: =+AI17+AI15 -> 34261 | AJ19: =+AJ17+AJ15 -> 38353 | AK19: =+AK17+AK15 -> 42910 | AL19: =+AL17+AL15 -> 46078 | AM19: =+AM17+AM15 -> 52232 | ... AR19: =+AR17+AR15 -> 106374 | AS19: =+AS13-AS21 -> 122299.26 | AT19: =+AT13-AT21 -> 137363.43 | AU19: =+AU13-AU21 -> 152788.66 | AV19: =+AV13-AV21 -> 171226.89 | AW19: =+AW13-AW21 -> 190150.41 | AX19: =+AX13-AX21 -> 209232.17 | AY19: =+AY13-AY21 -> 228100.43 | AZ19: =+AZ13-AZ21 -> 248588 | ... BB19: =+BB13-BB21 -> 294941.37
D20: =+D19/D$13 -> 0.31634927 | E20: =+E19/E$13 -> 0.31676468 | F20: =+F19/F$13 -> 0.30828778 | G20: =+G19/G$13 -> #DIV/0! | H20: =+H19/H$13 -> 0.30512515 | I20: =+I19/I$13 -> 0.29890192 | J20: =+J19/J$13 -> 0.28844418 | K20: =+K19/K$13 -> 0.31639794 | ... W20: =+W19/W$13 -> #DIV/0! | AB20: =+AB19/AB$13 -> 0.19837078 | AC20: =+AC19/AC$13 -> 0.22270992 | AD20: =+AD19/AD$13 -> 0.23778197 | AE20: =+AE19/AE$13 -> 0.2601061 | AF20: =+AF19/AF$13 -> 0.31183997 | AG20: =+AG19/AG$13 -> 0.35304552 | AH20: =+AH19/AH$13 -> 0.38420066 | AI20: =+AI19/AI$13 -> 0.38088938 | ... BB20: =+BB19/BB$13 -> 0.26
A21: Gross Margin | B21: =+B13-B19 -> 0 | C21: =+C13-C19 -> 0 | D21: =+D13-D19 -> 33745 | E21: =+E13-E19 -> 35436 | F21: =+F13-F19 -> 34670 | G21: =+G13-G19 -> 0 | H21: =+H13-H19 -> 36729 | I21: =+I13-I19 -> 39394 | ... W21: =+W13-W19 -> 0 | AB21: =+AB13-AB19 -> 50089 | AC21: =+AC13-AC19 -> 54366 | AD21: =+AD13-AD19 -> 56193 | AE21: =+AE13-AE19 -> 57600 | AF21: =+AF13-AF19 -> 59755 | AG21: =+AG13-AG19 -> 60542 | AH21: =+AH13-AH19 -> 52540 | AI21: =+AI13-AI19 -> 55689 | ... AR21: =+AR13-AR19 -> 225465 | AS21: =+AS13*0.685 -> 265952.37 | AT21: =+AT13*0.695 -> 313008.46 | AU21: =+AU13*0.705 -> 365139.01 | AV21: =+AV13*0.71 -> 419210.66 | AW21: =+AW13*0.715 -> 477044.02 | AX21: =+AX13*0.72 -> 538025.59 | AY21: =+AY13*0.725 -> 601355.68 | AZ21: =+AZ13*0.73 -> 672108.29 | BA21: =+BA13*0.735 -> 751150.07 | BB21: =+BB13*0.74 -> 839448.52
D22: =+D21/D$13 -> 0.68365073 | E22: =+E21/E$13 -> 0.68323532 | F22: =+F21/F$13 -> 0.69171222 | G22: =+G21/G$13 -> #DIV/0! | H22: =+H21/H$13 -> 0.69487485 | I22: =+I21/I$13 -> 0.70109808 | J22: =+J21/J$13 -> 0.71155582 | K22: =+K21/K$13 -> 0.68360206 | ... W22: =+W21/W$13 -> #DIV/0! | AB22: =+AB21/AB$13 -> 0.80162922 | AC22: =+AC21/AC$13 -> 0.77729008 | AD22: =+AD21/AD$13 -> 0.76221803 | AE22: =+AE21/AE$13 -> 0.7398939 | AF22: =+AF21/AF$13 -> 0.68816003 | AG22: =+AG21/AG$13 -> 0.64695448 | AH22: =+AH21/AH$13 -> 0.61579934 | AI22: =+AI21/AI$13 -> 0.61911062 | ... BB22: =+BB21/BB$13 -> 0.74
A23: R&D | D23: 6306 | E23: 6849 | F23: 6628 | H23: 6984 | I23: 6739 | J23: 6659 | K23: 7142 | L23: 7653 | M23: 8056 | N23: 7544 | O23: 7917 | P23: 8198 | Q23: 8829 | R23: 8146 | S23: 8504 | T23: 8915 | U23: 9997 | AB23: 8714 | AC23: 9043 | AD23: 9811 | AE23: 10411 | AF23: 11381 | AG23: 12046 | AH23: 11988 | AI23: 13037 | AJ23: 14726 | AK23: 16876 | AL23: 19269 | AM23: 20716 | AN23: 24512 | AO23: 27195 | AP23: 29510 | AQ23: 32488 | AR23: 35562 | AS23: =+AS13*0.105 -> 40766.421 | AT23: =+AT13*0.105 -> 47289.049 | AU23: =+AU13*0.105 -> 54382.406 | AV23: =+AV13*0.1 -> 59043.755 | AW23: =+AW13*0.1 -> 66719.443 | AX23: =+AX13*0.1 -> 74725.776 | AY23: =+AY13*0.095 -> 78798.331 | AZ23: =+AZ13*0.095 -> 87466.147 | BA23: =+BA13*0.095 -> 97087.424 | BB23: =+BB13*0.095 -> 107767.04
D24: =+D23/D$13 -> 0.12775527 | E24: =+E23/E$13 -> 0.13205437 | F24: =+F23/F$13 -> 0.13223734 | G24: =+G23/G$13 -> #DIV/0! | H24: =+H23/H$13 -> 0.13213009 | I24: =+I23/I$13 -> 0.11993451 | J24: =+J23/J$13 -> 0.11782296 | K24: =+K23/K$13 -> 0.1151564 | ... W24: =+W23/W$13 -> #DIV/0! | AB24: =+AB23/AB$13 -> 0.1394597 | AC24: =+AC23/AC$13 -> 0.12929099 | AD24: =+AD23/AD$13 -> 0.13307923 | AE24: =+AE23/AE$13 -> 0.13373325 | AF24: =+AF23/AF$13 -> 0.13106768 | AG24: =+AG23/AG$13 -> 0.12872409 | AH24: =+AH23/AH$13 -> 0.14050633 | AI24: =+AI23/AI$13 -> 0.14493608 | ... BB24: =+BB23/BB$13 -> 0.095
A25: S&M | D25: 5595 | E25: 6304 | F25: 5126 | H25: 5750 | I25: 6204 | J25: 5187 | K25: 6246 | L25: 6207 | M25: 6816 | N25: 5717 | O25: 6440 | P25: 6212 | Q25: 7285 | R25: 5717 | S25: 6584 | T25: 6814 | U25: 7595 | AB25: 13214 | AC25: 13940 | AD25: 13857 | AE25: 15276 | AF25: 15811 | AG25: 15713 | AH25: 14697 | AI25: 15539 | AJ25: 17469 | AK25: 18213 | AL25: 19598 | AM25: 20117 | AN25: 21825 | AO25: 22759 | AP25: 24456 | AQ25: 25654 | AR25: 26710 | AS25: =+AS13*0.09 -> 34942.647 | AT25: =+AT13*0.09 -> 40533.47 | AU25: =+AU13*0.09 -> 46613.491 | AV25: =+AV13*0.09 -> 53139.379 | AW25: =+AW13*0.09 -> 60047.499 | AX25: =+AX13*0.09 -> 67253.199 | AY25: =+AY13*0.09 -> 74651.05 | AZ25: =+AZ13*0.09 -> 82862.666 | ... BB25: =+BB13*0.09 -> 102095.09
D26: =+D25/D$13 -> 0.11335089 | E26: =+E25/E$13 -> 0.12154632 | F26: =+F25/F$13 -> 0.10227046 | G26: =+G25/G$13 -> #DIV/0! | H26: =+H25/H$13 -> 0.10878408 | I26: =+I25/I$13 -> 0.11041307 | J26: =+J25/J$13 -> 0.091777695 | K26: =+K25/K$13 -> 0.10070945 | ... W26: =+W25/W$13 -> #DIV/0! | AB26: =+AB25/AB$13 -> 0.21147814 | AC26: =+AC25/AC$13 -> 0.19930515 | AD26: =+AD25/AD$13 -> 0.18796034 | AE26: =+AE25/AE$13 -> 0.19622603 | AF26: =+AF25/AF$13 -> 0.18208515 | AG26: =+AG25/AG$13 -> 0.16790981 | AH26: =+AH25/AH$13 -> 0.17225738 | AI26: =+AI25/AI$13 -> 0.17275153 | ... BB26: =+BB25/BB$13 -> 0.09
A27: G&A | D27: 1480 | E27: 1749 | F27: 1398 | H27: 1643 | I27: 2197 | J27: 1474 | K27: 1977 | L27: 1912 | M27: 2246 | N27: 1673 | O27: 1823 | P27: 1737 | Q27: 1990 | R27: 1806 | S27: 1932 | T27: 1931 | U27: 2287 | AB27: 4063 | AC27: 4222 | AD27: =+4569+6193 -> 10762 | AE27: 5149 | AF27: =+4677+127 -> 4804 | AG27: =+4611+10011 -> 14622 | AH27: =+4563+1110 -> 5673 | AI27: =+4481+306 -> 4787 | AJ27: 4754 | AK27: 4885 | AL27: 5111 | AM27: 5107 | AN27: 5900 | AO27: 7575 | AP27: 7609 | AQ27: 7223 | AR27: 7956 | AS27: =+AS13*0.024 -> 9318.0391 | AT27: =+AT13*0.024 -> 10808.925 | AU27: =+AU13*0.024 -> 12430.264 | AV27: =+AV13*0.024 -> 14170.501 | AW27: =+AW13*0.024 -> 16012.666 | AX27: =+AX13*0.024 -> 17934.186 | AY27: =+AY13*0.024 -> 19906.947 | AZ27: =+AZ13*0.024 -> 22096.711 | ... BB27: =+BB13*0.024 -> 27225.358
D28: =+D27/D$13 -> 0.029983793 | E28: =+E27/E$13 -> 0.033722163 | F28: =+F27/F$13 -> 0.027891944 | G28: =+G27/G$13 -> #DIV/0! | H28: =+H27/H$13 -> 0.031083868 | I28: =+I27/I$13 -> 0.03910018 | J28: =+J27/J$13 -> 0.026080648 | K28: =+K27/K$13 -> 0.031876814 | ... W28: =+W27/W$13 -> #DIV/0! | AB28: =+AB27/AB$13 -> 0.065024646 | AC28: =+AC27/AC$13 -> 0.060363439 | AD28: =+AD27/AD$13 -> 0.14597887 | AE28: =+AE27/AE$13 -> 0.066140862 | AF28: =+AF27/AF$13 -> 0.055324589 | AG28: =+AG27/AG$13 -> 0.15625134 | AH28: =+AH27/AH$13 -> 0.066490858 | AI28: =+AI27/AI$13 -> 0.053218455 | ... BB28: =+BB27/BB$13 -> 0.024
A29: OP Exp. | B29: =+B27+B25+B23 -> 0 | C29: =+C27+C25+C23 -> 0 | D29: =+D27+D25+D23 -> 13381 | E29: =+E27+E25+E23 -> 14902 | F29: =+F27+F25+F23 -> 13152 | G29: =+G27+G25+G23 -> 0 | H29: =+H27+H25+H23 -> 14377 | I29: =+I27+I25+I23 -> 15140 | ... W29: =+W27+W25+W23 -> 0 | AB29: =+AB27+AB25+AB23 -> 25991 | AC29: =+AC27+AC25+AC23 -> 27205 | AD29: =+AD27+AD25+AD23 -> 34430 | AE29: =+AE27+AE25+AE23 -> 30836 | AF29: =+AF27+AF25+AF23 -> 31996 | AG29: =+AG27+AG25+AG23 -> 42381 | AH29: =+AH27+AH25+AH23 -> 32358 | AI29: =+AI27+AI25+AI23 -> 33363 | ... BB29: =+BB27+BB25+BB23 -> 237087.49
D30: =+D29/D$13 -> 0.27108995 | E30: =+E29/E$13 -> 0.28732286 | F30: =+F29/F$13 -> 0.26239974 | G30: =+G29/G$13 -> #DIV/0! | H30: =+H29/H$13 -> 0.27199803 | I30: =+I29/I$13 -> 0.26944776 | J30: =+J29/J$13 -> 0.2356813 | K30: =+K29/K$13 -> 0.24774266 | ... W30: =+W29/W$13 -> #DIV/0! | AB30: =+AB29/AB$13 -> 0.41596249 | AC30: =+AC29/AC$13 -> 0.38895958 | AD30: =+AD29/AD$13 -> 0.46701843 | AE30: =+AE29/AE$13 -> 0.39610014 | AF30: =+AF29/AF$13 -> 0.36847742 | AG30: =+AG29/AG$13 -> 0.45288523 | AH30: =+AH29/AH$13 -> 0.37925457 | AI30: =+AI29/AI$13 -> 0.37090606 | ... BB30: =+BB29/BB$13 -> 0.209
A31: EBIT | B31: =+B21-B29 -> 0 | C31: =+C21-C29 -> 0 | D31: =+D21-D29 -> 20364 | E31: =+E21-E29 -> 20534 | F31: =+F21-F29 -> 21518 | G31: =+G21-G29 -> 0 | H31: =+H21-H29 -> 22352 | I31: =+I21-I29 -> 24254 | ... W31: =+W21-W29 -> 0 | AB31: =+AB21-AB29 -> 24098 | AC31: =+AC21-AC29 -> 27161 | AD31: =+AD21-AD29 -> 21763 | AE31: =+AE21-AE29 -> 26764 | AF31: =+AF21-AF29 -> 27759 | AG31: =+AG21-AG29 -> 18161 | AH31: =+AH21-AH29 -> 20182 | AI31: =+AI21-AI29 -> 22326 | ... BB31: =+BB21-BB29 -> 602361.04
D32: =+D31/D$13 -> 0.41256078 | E32: =+E31/E$13 -> 0.39591247 | F32: =+F31/F$13 -> 0.42931248 | G32: =+G31/G$13 -> #DIV/0! | H32: =+H31/H$13 -> 0.42287682 | I32: =+I31/I$13 -> 0.43165032 | J32: =+J31/J$13 -> 0.47587452 | K32: =+K31/K$13 -> 0.4358594 | ... W32: =+W31/W$13 -> #DIV/0! | AB32: =+AB31/AB$13 -> 0.38566673 | AC32: =+AC31/AC$13 -> 0.3883305 | AD32: =+AD31/AD$13 -> 0.2951996 | AE32: =+AE31/AE$13 -> 0.34379375 | AF32: =+AF31/AF$13 -> 0.31968261 | AG32: =+AG31/AG$13 -> 0.19406925 | AH32: =+AH31/AH$13 -> 0.23654477 | AI32: =+AI31/AI$13 -> 0.24820456 | ... BB32: =+BB31/BB$13 -> 0.531
A33: Other Income | D33: -174 | E33: -47 | F33: 54 | H33: 321 | I33: 473 | J33: 389 | K33: -506 | L33: -854 | M33: -675 | N33: -283 | O33: -2288 | P33: -623 | Q33: -1707 | R33: -3660 | S33: 9971 | T33: 942 | U33: 3444 | AB33: 915 | AC33: 910 | AD33: 504 | AE33: 288 | AF33: 61 | AG33: 346 | AH33: -431 | AI33: 823 | AJ33: 1416 | AK33: 729 | AL33: 77 | AM33: 1186 | AN33: 333 | AO33: 788 | AP33: -1646 | AQ33: -4901 | AR33: 10697 | AS33: =+AR66*$BE$48 -> 1851.63 | AT33: =+AS66*$BE$48 -> 3313.8451 | AU33: =+AT66*$BE$48 -> 5055.372 | AV33: =+AU66*$BE$48 -> 7058.1642 | AW33: =+AV66*$BE$48 -> 9397.5026 | AX33: =+AW66*$BE$48 -> 12078.066 | AY33: =+AX66*$BE$48 -> 14809.399 | AZ33: =+AY66*$BE$48 -> 17909.06 | ... BB33: =+BA66*$BE$48 -> 25304.853
D34: =+D33/D$13 -> -0.0035251216 | E34: =+E33/E$13 -> -0.00090619879 | F34: =+F33/F$13 -> 0.0010773712 | G34: =+G33/G$13 -> #DIV/0! | H34: =+H33/H$13 -> 0.0060729894 | I34: =+I33/I$13 -> 0.0084180178 | J34: =+J33/J$13 -> 0.0068828848 | K34: =+K33/K$13 -> -0.0081586585 | ... W34: =+W33/W$13 -> #DIV/0! | AB34: =+AB33/AB$13 -> 0.014643749 | AC34: =+AC33/AC$13 -> 0.013010594 | AD34: =+AD33/AD$13 -> 0.0068364011 | AE34: =+AE33/AE$13 -> 0.0036994695 | AF34: =+AF33/AF$13 -> 0.0007024979 | AG34: =+AG33/AG$13 -> 0.0036973712 | AH34: =+AH33/AH$13 -> -0.0050515706 | AI34: =+AI33/AI$13 -> 0.0091495275 | ... BB34: =+BB33/BB$13 -> 0.022307015
A35: EBT | B35: =+B31+B33 -> 0 | C35: =+C31+C33 -> 0 | D35: =+D31+D33 -> 20190 | E35: =+E31+E33 -> 20487 | F35: =+F31+F33 -> 21572 | G35: =+G31+G33 -> 0 | H35: =+H31+H33 -> 22673 | I35: =+I31+I33 -> 24727 | ... W35: =+W31+W33 -> 0 | AB35: =+AB31+AB33 -> 25013 | AC35: =+AC31+AC33 -> 28071 | AD35: =+AD31+AD33 -> 22267 | AE35: =+AE31+AE33 -> 27052 | AF35: =+AF31+AF33 -> 27820 | AG35: =+AG31+AG33 -> 18507 | AH35: =+AH31+AH33 -> 19751 | AI35: =+AI31+AI33 -> 23149 | ... BB35: =+BB31+BB33 -> 627665.89
D36: =+D35/D$13 -> 0.40903566 | E36: =+E35/E$13 -> 0.39500627 | F36: =+F35/F$13 -> 0.43038985 | G36: =+G35/G$13 -> #DIV/0! | H36: =+H35/H$13 -> 0.42894981 | I36: =+I35/I$13 -> 0.44006834 | J36: =+J35/J$13 -> 0.4827574 | K36: =+K35/K$13 -> 0.42770074 | ... W36: =+W35/W$13 -> #DIV/0! | AB36: =+AB35/AB$13 -> 0.40031048 | AC36: =+AC35/AC$13 -> 0.40134109 | AD36: =+AD35/AD$13 -> 0.302036 | AE36: =+AE35/AE$13 -> 0.34749322 | AF36: =+AF35/AF$13 -> 0.32038511 | AG36: =+AG35/AG$13 -> 0.19776662 | AH36: =+AH35/AH$13 -> 0.2314932 | AI36: =+AI35/AI$13 -> 0.25735409 | ... BB36: =+BB35/BB$13 -> 0.55330702
A37: Taxes | D37: 3462 | E37: 3747 | F37: 4016 | H37: 4374 | I37: 4646 | J37: 4993 | K37: 4656 | L37: 4788 | M37: 5214 | N37: 5602 | O37: 5257 | P37: 5553 | Q37: 5383 | R37: 6554 | S37: 9788 | T37: 7562 | U37: 8281 | AB37: 6253 | AC37: 4921 | AD37: 5289 | AE37: 5189 | AF37: 5746 | AG37: 6314 | AH37: 2953 | AI37: 1945 | AJ37: 19903 | AK37: 4448 | AL37: 8755 | AM37: 9831 | AN37: 10978 | AO37: 16950 | AP37: 19651 | AQ37: 21795 | AR37: 32185 | AS37: =+AS35*0.2 -> 36555.378 | AT37: =+AT35*0.2 -> 43538.173 | AU37: =+AU35*0.22 -> 56489.009 | AV37: =+AV35*0.22 -> 65981.341 | AW37: =+AW35*0.22 -> 75605.621 | AX37: =+AX35*0.3 -> 117057.15 | AY37: =+AY35*0.3 -> 132842.63 | AZ37: =+AZ35*0.3 -> 149277.55 | BA37: =+BA35*0.3 -> 167684.98 | BB37: =+BB35*0.3 -> 188299.77
D38: =+D37/D$13 -> 0.070137763 | E38: =+E37/E$13 -> 0.072245252 | F38: =+F37/F$13 -> 0.080124496 | G38: =+G37/G$13 -> #DIV/0! | H38: =+H37/H$13 -> 0.082751575 | I38: =+I37/I$13 -> 0.082685223 | J38: =+J37/J$13 -> 0.0883451 | K38: =+K37/K$13 -> 0.075072557 | ... W38: =+W37/W$13 -> #DIV/0! | AB38: =+AB37/AB$13 -> 0.10007362 | AC38: =+AC37/AC$13 -> 0.070357291 | AD38: =+AD37/AD$13 -> 0.071741519 | AE38: =+AE37/AE$13 -> 0.066654678 | AF38: =+AF37/AF$13 -> 0.066172999 | AG38: =+AG37/AG$13 -> 0.067471682 | AH38: =+AH37/AH$13 -> 0.034610877 | AI38: =+AI37/AI$13 -> 0.021623124 | ... BB38: =+BB37/BB$13 -> 0.1659921
A39: Net Income | B39: =+B35-B37 -> 0 | C39: =+C35-C37 -> 0 | D39: =+D35-D37 -> 16728 | E39: =+E35-E37 -> 16740 | F39: =+F35-F37 -> 17556 | G39: =+G35-G37 -> 0 | H39: =+H35-H37 -> 18299 | I39: =+I35-I37 -> 20081 | ... W39: =+W35-W37 -> 0 | AB39: =+AB35-AB37 -> 18760 | AC39: =+AC35-AC37 -> 23150 | AD39: =+AD35-AD37 -> 16978 | AE39: =+AE35-AE37 -> 21863 | AF39: =+AF35-AF37 -> 22074 | AG39: =+AG35-AG37 -> 12193 | AH39: =+AH35-AH37 -> 16798 | AI39: =+AI35-AI37 -> 21204 | ... BB39: =+BB35-BB37 -> 439366.12 | BC39: =+BB39*(1+$BE$46) -> 448153.44 | BD39: =+BC39*(1+$BE$46) -> 457116.51 | BE39: =+BD39*(1+$BE$46) -> 466258.84 | BF39: =+BE39*(1+$BE$46) -> 475584.02 | BG39: =+BF39*(1+$BE$46) -> 485095.7 | BH39: =+BG39*(1+$BE$46) -> 494797.61 | BI39: =+BH39*(1+$BE$46) -> 504693.57 | BJ39: =+BI39*(1+$BE$46) -> 514787.44 | ... DX39: =+DW39*(1+$BE$46) -> 1902126
D40: =+D39/D$13 -> 0.33889789 | E40: =+E39/E$13 -> 0.32276101 | F40: =+F39/F$13 -> 0.35026535 | G40: =+G39/G$13 -> #DIV/0! | H40: =+H39/H$13 -> 0.34619823 | I40: =+I39/I$13 -> 0.35738312 | J40: =+J39/J$13 -> 0.3944123 | K40: =+K39/K$13 -> 0.35262818 | ... W40: =+W39/W$13 -> #DIV/0! | AB40: =+AB39/AB$13 -> 0.30023686 | AC40: =+AC39/AC$13 -> 0.3309838 | AD40: =+AD39/AD$13 -> 0.23029448 | AE40: =+AE39/AE$13 -> 0.28083855 | AF40: =+AF39/AF$13 -> 0.25421211 | AG40: =+AG39/AG$13 -> 0.13029493 | AH40: =+AH39/AH$13 -> 0.19688233 | AI40: =+AI39/AI$13 -> 0.23573096 | ... BB40: =+BB39/BB$13 -> 0.38731491
A41: EPS | B41: =+B39/B43 -> #DIV/0! | C41: =+C39/C43 -> #DIV/0! | D41: =+D39/D43 -> 2.2203345 | E41: =+E39/E43 -> 2.2302158 | F41: =+F39/F43 -> 2.345491 | G41: =+G39/G43 -> #DIV/0! | H41: =+H39/H43 -> 2.4516345 | I41: =+I39/I43 -> 2.6892996 | ... T41: =+T39/T43 -> 4.268368 | U41: 8 | V41: =+V39/V43 -> #DIV/0! | W41: =+W39/W43 -> #DIV/0! | AB41: =+AB39/AB43 -> 2.1014899 | AC41: =+AC39/AC43 -> 2.6940533 | AD41: =+AD39/AD43 -> 1.9960028 | AE41: =+AE39/AE43 -> 2.5812279 | AF41: =+AF39/AF43 -> 2.62817 | AG41: =+AG39/AG43 -> 1.4772232 | AH41: =+AH39/AH43 -> 2.0963434 | AI41: =+AI39/AI43 -> 2.7073544 | ... BB41: =+BB39/BB43 -> 61.981865
F42: =+F41/B41-1 -> #DIV/0! | G42: =+G41/C41-1 -> #DIV/0! | H42: =+H41/D41-1 -> 0.10417351 | I42: =+I41/E41-1 -> 0.20584723 | J42: =+J41/F41-1 -> 0.27362196 | K42: =+K41/G41-1 -> #DIV/0! | L42: =+L41/H41-1 -> 0.19763434 | M42: =+M41/I41-1 -> 0.096621397 | ... U42: =+U41/Q41-1 -> 1.1917527 | AC42: =+AC41/AB41-1 -> 0.28197302 | AD42: =+AD41/AC41-1 -> -0.25910789 | AE42: =+AE41/AD41-1 -> 0.2931985 | AF42: =+AF41/AE41-1 -> 0.01818598 | AG42: =+AG41/AF41-1 -> -0.43792709 | AH42: =+AH41/AG41-1 -> 0.41911086 | AI42: =+AI41/AH41-1 -> 0.29146512 | AJ42: =+AJ41/AI41-1 -> -0.21468625 | ... BB42: =+BB41/BA41-1 -> 0.12858048
A43: Shares | D43: 7534 | E43: 7506 | F43: 7485 | H43: 7464 | I43: 7467 | J43: 7462 | K43: 7468 | L43: 7472 | M43: 7472 | N43: 7470 | O43: 7468 | P43: 7461 | Q43: 7461 | R43: 7466 | S43: 7460 | T43: 7445 | U43: 7443 | AB43: 8927 | AC43: 8593 | AD43: 8506 | AE43: 8470 | AF43: 8399 | AG43: 8254 | AH43: 8013 | AI43: 7832 | AJ43: 7794 | AK43: 7753 | AL43: 7683 | AM43: 7608 | AN43: 7540 | AO43: 7472 | AP43: 7469 | AQ43: 7465 | AR43: 7453 | AS43: =+AR43*0.995 -> 7415.735 | AT43: =+AS43*0.995 -> 7378.6563 | AU43: =+AT43*0.995 -> 7341.763 | AV43: =+AU43*0.995 -> 7305.0542 | AW43: =+AV43*0.995 -> 7268.529 | AX43: =+AW43*0.995 -> 7232.1863 | AY43: =+AX43*0.995 -> 7196.0254 | AZ43: =+AY43*0.995 -> 7160.0453 | ... BB43: =+BA43*0.995 -> 7088.6238
E44: =+E43/D43-1 -> -0.0037164853 | F44: =+F43/E43-1 -> -0.0027977618 | G44: =+G43/F43-1 -> -1 | H44: =+H43/G43-1 -> #DIV/0! | I44: =+I43/H43-1 -> 0.00040192926 | J44: =+J43/I43-1 -> -0.00066961296 | K44: =+K43/J43-1 -> 0.00080407397 | L44: =+L43/K43-1 -> 0.00053561864 | ... U44: =+U43/T43-1 -> -0.00026863667 | AC44: =+AC43/AB43-1 -> -0.037414585 | AD44: =+AD43/AC43-1 -> -0.01012452 | AE44: =+AE43/AD43-1 -> -0.0042323066 | AF44: =+AF43/AE43-1 -> -0.0083825266 | AG44: =+AG43/AF43-1 -> -0.01726396 | AH44: =+AH43/AG43-1 -> -0.029197965 | AI44: =+AI43/AH43-1 -> -0.022588294 | AJ44: =+AJ43/AI43-1 -> -0.0048518897 | ... BB44: =+BB43/BA43-1 -> -0.005
BG45: Gordon Growth Model
A46: Gross Margin | B46: =+B21/B13 -> #DIV/0! | C46: =+C21/C13 -> #DIV/0! | D46: =+D21/D13 -> 0.68365073 | E46: =+E21/E13 -> 0.68323532 | F46: =+F21/F13 -> 0.69171222 | G46: =+G21/G13 -> #DIV/0! | H46: =+H21/H13 -> 0.69487485 | I46: =+I21/I13 -> 0.70109808 | ... U46: =+U21/U13 -> 0.67196996 | AB46: =+AB21/AB13 -> 0.80162922 | AC46: =+AC21/AC13 -> 0.77729008 | AD46: =+AD21/AD13 -> 0.76221803 | AE46: =+AE21/AE13 -> 0.7398939 | AF46: =+AF21/AF13 -> 0.68816003 | AG46: =+AG21/AG13 -> 0.64695448 | AH46: =+AH21/AH13 -> 0.61579934 | AI46: =+AI21/AI13 -> 0.61911062 | ... BB46: =+BB21/BB13 -> 0.74 | BD46: Terminal | BE46: 0.02 | BG46: Payout Ratio | BH46: =+SUM(R174:U174)/SUM(R39:U39) -> 0.34921383
A47: OP Margin | B47: =+B31/B13 -> #DIV/0! | C47: =+C31/C13 -> #DIV/0! | D47: =+D31/D13 -> 0.41256078 | E47: =+E31/E13 -> 0.39591247 | F47: =+F31/F13 -> 0.42931248 | G47: =+G31/G13 -> #DIV/0! | H47: =+H31/H13 -> 0.42287682 | I47: =+I31/I13 -> 0.43165032 | ... U47: =+U31/U13 -> 0.45110936 | AB47: =+AB31/AB13 -> 0.38566673 | AC47: =+AC31/AC13 -> 0.3883305 | AD47: =+AD31/AD13 -> 0.2951996 | AE47: =+AE31/AE13 -> 0.34379375 | AF47: =+AF31/AF13 -> 0.31968261 | AG47: =+AG31/AG13 -> 0.19406925 | AH47: =+AH31/AH13 -> 0.23654477 | AI47: =+AI31/AI13 -> 0.24820456 | ... BB47: =+BB31/BB13 -> 0.531 | BD47: Discount | BE47: =+Main!E11 -> 0.10594584 | BG47: Sustained Growth | BH47: =+(1-BH46)*U54 -> 0.21734372
A48: NI Margin | B48: =+B39/B13 -> #DIV/0! | C48: =+C39/C13 -> #DIV/0! | D48: =+D39/D13 -> 0.33889789 | E48: =+E39/E13 -> 0.32276101 | F48: =+F39/F13 -> 0.35026535 | G48: =+G39/G13 -> #DIV/0! | H48: =+H39/H13 -> 0.34619823 | I48: =+I39/I13 -> 0.35738312 | ... U48: =+U39/U13 -> 0.39736909 | AB48: =+AB39/AB13 -> 0.30023686 | AC48: =+AC39/AC13 -> 0.3309838 | AD48: =+AD39/AD13 -> 0.23029448 | AE48: =+AE39/AE13 -> 0.28083855 | AF48: =+AF39/AF13 -> 0.25421211 | AG48: =+AG39/AG13 -> 0.13029493 | AH48: =+AH39/AH13 -> 0.19688233 | AI48: =+AI39/AI13 -> 0.23573096 | ... BB48: =+BB39/BB13 -> 0.38731491 | BD48: ROIC | BE48: 0.01 | BG48: Equity Value | BH48: =+SUM(AO174:AR174)/(Main!E11-0.06) -> 3577146.7 | BJ48: Diff | BK48: =+BH48/Main!E6-1 -> 0.015926914
A49: Tax Rate | B49: =+B37/B35 -> #DIV/0! | C49: =+C37/C35 -> #DIV/0! | D49: =+D37/D35 -> 0.17147103 | E49: =+E37/E35 -> 0.18289647 | F49: =+F37/F35 -> 0.18616725 | G49: =+G37/G35 -> #DIV/0! | H49: =+H37/H35 -> 0.19291669 | I49: =+I37/I35 -> 0.18789178 | ... U49: =+U37/U35 -> 0.18800372 | AB49: =+AB37/AB35 -> 0.24999001 | AC49: =+AC37/AC35 -> 0.17530548 | AD49: =+AD37/AD35 -> 0.23752638 | AE49: =+AE37/AE35 -> 0.19181576 | AF49: =+AF37/AF35 -> 0.20654206 | AG49: =+AG37/AG35 -> 0.34116821 | AH49: =+AH37/AH35 -> 0.14951142 | AI49: =+AI37/AI35 -> 0.084020908 | ... BB49: =+BB37/BB35 -> 0.3 | BD49: NPV | BE49: =+NPV(BE47,AR39:DX39)+Main!E4-Main!E5 -> 3284196 | BG49: Just. P/E | BH49: =+BH46*(1+0.06)/(Main!B11-0.06) -> 7.9434905
A50: CapEx Margin | B50: =+B120/B39 -> #DIV/0! | C50: =+C120/C39 -> #DIV/0! | D50: =+D120/D39 -> 0.31922525 | E50: =+E120/E39 -> 0.410454 | F50: =+F120/F39 -> 0.35788334 | G50: =+G120/G39 -> #DIV/0! | H50: =+H120/H39 -> 0.36105798 | I50: =+I120/I39 -> 0.44534635 | ... U50: =+U120/U39 -> 1.0010065 | AB50: =+AB120/AB39 -> 0.1053838 | AC50: =+AC120/AC39 -> 0.10172786 | AD50: =+AD120/AD39 -> 0.13576393 | AE50: =+AE120/AE39 -> 0.19471253 | AF50: =+AF120/AF39 -> 0.24848238 | AG50: =+AG120/AG39 -> 0.48749282 | AH50: =+AH120/AH39 -> 0.49666627 | AI50: =+AI120/AI39 -> 0.38337106 | ... BB50: =+BB120/BB39 -> 0.25818784 | BD50: Shares | BE50: =+BE49/Main!E2 -> 442.28347
BD51: Diff | BE51: =+BE50/Main!E1-1 -> -0.086191179 | BG51: Dividend yield | BH51: =+SUM(R170:U170)/SUM(R39:U39) -> 0.1977211
BG52: Debt-to-EBITDA | BH52: =+(-U68+U81)/SUM(R65:U65) -> 0.092457804
A53: ROA | D53: =+(D39*4)/AVERAGE(C78:D78) -> #DIV/0! | E53: =+(E39*4)/AVERAGE(D78:E78) -> 0.36706501 | F53: =+(F39*4)/AVERAGE(E78:F78) -> 0.38495779 | G53: =+(G39*4)/AVERAGE(F78:G78) -> #DIV/0! | H53: =+(H39*4)/AVERAGE(G78:H78) -> 0.38515291 | I53: =+(I39*4)/AVERAGE(H78:I78) -> 0.20282199 | J53: =+(J39*4)/AVERAGE(I78:J78) -> 0.2078994 | K53: =+(K39*4)/AVERAGE(J78:K78) -> 0.39247619 | ... U53: =+(U39*4)/AVERAGE(T78:U78) -> 0.19697591 | AC53: =+SUM(AC39)/AVERAGE(AB78:AC78) -> 0.23765893 | AD53: =+SUM(AD39)/AVERAGE(AC78:AD78) -> 0.14765083 | AE53: =+SUM(AE39)/AVERAGE(AD78:AE78) -> 0.16581596 | AF53: =+SUM(AF39)/AVERAGE(AE78:AF78) -> 0.14023474 | AG53: =+SUM(AG39)/AVERAGE(AF78:AG78) -> 0.070305833 | AH53: =+SUM(AH39)/AVERAGE(AG78:AH78) -> 0.091308365 | AI53: =+SUM(AI39)/AVERAGE(AH78:AI78) -> 0.095560863 | AJ53: =+SUM(AJ39)/AVERAGE(AI78:AJ78) -> 0.065091523 | ... AR53: =+SUM(AR39)/AVERAGE(AQ78:AR78) -> 0.19420798
A54: ROE | J54: =+J55*J56*J48 -> 0.4176916 | K54: =+K55*K56*K48 -> 0.79270006 | L54: =+L55*L56*L48 -> #DIV/0! | M54: =+M55*M56*M48 -> 0.65662235 | N54: =+N55*N56*N48 -> 0.35479324 | O54: =+O55*O56*O48 -> 0.32665671 | P54: =+P55*P56*P48 -> 0.3307663 | Q54: =+Q55*Q56*Q48 -> 0.32743286 | ... U54: =+U55*U56*U48 -> 0.33397102 | AC54: =+AC55*AC56*AC48 -> 0.44839141 | AD54: =+AD55*AD56*AD48 -> 0.27506764 | AE54: =+AE55*AE56*AE48 -> 0.3009215 | AF54: =+AF55*AF56*AF48 -> 0.26165189 | AG54: =+AG55*AG56*AG48 -> 0.14355937 | AH54: =+AH55*AH56*AH48 -> 0.22091005 | AI54: =+AI55*AI56*AI48 -> 0.2655346 | AJ54: =+AJ55*AJ56*AJ48 -> 0.19446221 | ... AR54: =+AR55*AR56*AR48 -> 0.34038627
A55: Asset Turnover | D55: =+(D13*4)/AVERAGE(C78:D78) -> #DIV/0! | E55: =+(E13*4)/AVERAGE(D78:E78) -> 1.1372657 | F55: =+(F13*4)/AVERAGE(E78:F78) -> 1.0990462 | G55: =+(G13*4)/AVERAGE(F78:G78) -> #DIV/0! | H55: =+(H13*4)/AVERAGE(G78:H78) -> 1.1125213 | I55: =+(I13*4)/AVERAGE(H78:I78) -> 0.5675198 | J55: =+(J13*4)/AVERAGE(I78:J78) -> 0.52711186 | K55: =+(K13*4)/AVERAGE(J78:K78) -> 1.1130029 | ... U55: =+(U13*4)/AVERAGE(T78:U78) -> 0.49570014 | AC55: =+SUM(AC13)/AVERAGE(AB78:AC78) -> 0.71803795 | AD55: =+SUM(AD13)/AVERAGE(AC78:AD78) -> 0.64113925 | AE55: =+SUM(AE13)/AVERAGE(AD78:AE78) -> 0.59043162 | AF55: =+SUM(AF13)/AVERAGE(AE78:AF78) -> 0.55164462 | AG55: =+SUM(AG13)/AVERAGE(AF78:AG78) -> 0.53958992 | AH55: =+SUM(AH13)/AVERAGE(AG78:AH78) -> 0.46377127 | AI55: =+SUM(AI13)/AVERAGE(AH78:AI78) -> 0.40538104 | AJ55: =+SUM(AJ13)/AVERAGE(AI78:AJ78) -> 0.43349831 | ... AR55: =+SUM(AR13)/AVERAGE(AQ78:AR78) -> 0.48184124
A56: Financial Leverage | D56: =+AVERAGE(C78:D78)/AVERAGE(C99:D99) -> #DIV/0! | E56: =+AVERAGE(D78:E78)/AVERAGE(D99:E99) -> 2.1906786 | F56: =+AVERAGE(E78:F78)/AVERAGE(E99:F99) -> 2.1906786 | G56: =+AVERAGE(F78:G78)/AVERAGE(F99:G99) -> #DIV/0! | H56: =+AVERAGE(G78:H78)/AVERAGE(G99:H99) -> 1.952343 | I56: =+AVERAGE(H78:I78)/AVERAGE(H99:I99) -> 1.9756851 | J56: =+AVERAGE(I78:J78)/AVERAGE(I99:J99) -> 2.0091044 | K56: =+AVERAGE(J78:K78)/AVERAGE(J99:K99) -> 2.0197405 | ... U56: =+AVERAGE(T78:U78)/AVERAGE(T99:U99) -> 1.6954917 | AC56: =+AVERAGE(AB78:AC78)/AVERAGE(AB99:AC99) -> 1.8867013 | AD56: =+AVERAGE(AC78:AD78)/AVERAGE(AC99:AD99) -> 1.8629603 | AE56: =+AVERAGE(AD78:AE78)/AVERAGE(AD99:AE99) -> 1.8147921 | AF56: =+AVERAGE(AE78:AF78)/AVERAGE(AE99:AF99) -> 1.8658136 | AG56: =+AVERAGE(AF78:AG78)/AVERAGE(AF99:AG99) -> 2.0419269 | AH56: =+AVERAGE(AG78:AH78)/AVERAGE(AG99:AH99) -> 2.4193845 | AI56: =+AVERAGE(AH78:AI78)/AVERAGE(AH99:AI99) -> 2.7786961 | AJ56: =+AVERAGE(AI78:AJ78)/AVERAGE(AI99:AJ99) -> 2.9875197 | ... AR56: =+AVERAGE(AQ78:AR78)/AVERAGE(AQ99:AR99) -> 1.7526894
A57: Financial Leverage % | J57: =+J54-J53 -> 0.2097922 | K57: =+K54-K53 -> 0.40022386 | L57: =+L54-L53 -> #DIV/0! | M57: =+M54-M53 -> 0.31241944 | N57: =+N54-N53 -> 0.16416285 | O57: =+O54-O53 -> 0.14417777 | P57: =+P54-P53 -> 0.14235968 | Q57: =+Q54-Q53 -> 0.14305657 | ... U57: =+U54-U53 -> 0.1369951 | AC57: =+AC54-AC53 -> 0.21073248 | AD57: =+AD54-AD53 -> 0.12741681 | AE57: =+AE54-AE53 -> 0.13510554 | AF57: =+AF54-AF53 -> 0.12141715 | AG57: =+AG54-AG53 -> 0.07325354 | AH57: =+AH54-AH53 -> 0.12960168 | AI57: =+AI54-AI53 -> 0.16997374 | AJ57: =+AJ54-AJ53 -> 0.12937069 | ... AR57: =+AR54-AR53 -> 0.14617829
BD58: Terminal | BE58: 0.02
BD59: Discount | BE59: =+Main!E11 -> 0.10594584
A60: NOPAT | AB60: =+AB31*(1-AB49) -> 18073.741 | AC60: =+AC31*(1-AC49) -> 22399.528 | AD60: =+AD31*(1-AD49) -> 16593.713 | AE60: =+AE31*(1-AE49) -> 21630.243 | AF60: =+AF31*(1-AF49) -> 22025.599 | AG60: =+AG31*(1-AG49) -> 11965.044 | AH60: =+AH31*(1-AH49) -> 17164.561 | AI60: =+AI31*(1-AI49) -> 20450.149 | ... BB60: =+BB31*(1-BB49) -> 421652.72 | BD60: EV | BE60: =+NPV(BE59,AS62:BA62,BB62+BE61) -> 3550536.5
A61: NWC | AB61: =+SUM(AB70,AB71)-SUM(AB80,AB82,AB84,AB87,AB92) -> -11211 | AC61: =+SUM(AC70,AC71)-SUM(AC80,AC82,AC84,AC87,AC92) -> -11207 | AD61: =+SUM(AD70,AD71)-SUM(AD80,AD82,AD84,AD87,AD92) -> -13726 | AE61: =+SUM(AE70,AE71)-SUM(AE80,AE82,AE84,AE87,AE92) -> -14349 | AF61: =+SUM(AF70,AF71)-SUM(AF80,AF82,AF84,AF87,AF92) -> -20863 | AG61: =+SUM(AG70,AG71)-SUM(AG80,AG82,AG84,AG87,AG92) -> -21261 | AH61: =+SUM(AH70,AH71)-SUM(AH80,AH82,AH84,AH87,AH92) -> -25631 | AI61: =+SUM(AI70,AI71)-SUM(AI80,AI82,AI84,AI87,AI92) -> -21012 | ... BB61: =+SUM(BB70,BB71)-SUM(BB80,BB82,BB84,BB87,BB92) -> -261137.66 | BD61: TV | BE61: =+BB62*(1+BE58)/(BE59-BE58) -> 5610323.2
A62: UFCF | AC62: =+AC60+AC104-AC120-(AC61-AB61) -> 22806.528 | AD62: =+AD60+AD104-AD120-(AD61-AC61) -> 25967.713 | AE62: =+AE60+AE104-AE120-(AE61-AD61) -> 21751.243 | AF62: =+AF60+AF104-AF120-(AF61-AE61) -> 28266.599 | AG62: =+AG60+AG104-AG120-(AG61-AF61) -> 12376.044 | AH62: =+AH60+AH104-AH120-(AH61-AG61) -> 19813.561 | AI62: =+AI60+AI104-AI120-(AI61-AH61) -> 16480.149 | AJ62: =+AJ60+AJ104-AJ120-(AJ61-AI61) -> 18891.678 | ... BB62: =+BB60+BB104-BB120-(BB61-BA61) -> 472729.33 | BD62: Diff | BE62: =+BE60/Main!E6-1 -> 0.0083694779
A65: EBITDA | B65: =+B35+B104 -> 0 | C65: =+C35+C104 -> 0 | D65: =+D35+D104 -> 23963 | E65: =+E35+E104 -> 24466 | F65: =+F35+F104 -> 24362 | G65: =+G35+G104 -> 0 | H65: =+H35+H104 -> 26222 | I65: =+I35+I104 -> 28601 | ... U65: =+U35+U104 -> 55069 | AB65: =+AB35+AB104 -> 27686 | AC65: =+AC35+AC104 -> 30837 | AD65: =+AD35+AD104 -> 31427 | AE65: =+AE35+AE104 -> 30807 | AF65: =+AF35+AF104 -> 33032 | AG65: =+AG35+AG104 -> 24464 | AH65: =+AH35+AH104 -> 26373 | AI65: =+AI35+AI104 -> 31927 | ... BB65: =+BB35+BB104 -> 775136.57
A66: Net Cash | AB66: =+AB68+31283-AB81 -> 30849 | AC66: =+AC68+43162-AC81 -> 40851 | AD66: =+AD68+56102-AD81 -> 51096 | AE66: =+AE68+73218-AE81 -> 61422 | AF66: =+AF68+77040-AF81 -> 63064 | AG66: =+AG68+90931-AG81 -> 61234 | AH66: =+AH68+106730-AH81 -> 59779 | AI66: =+AI68+125318-AI81 -> 46787 | AJ66: =+AJ68+121822-AJ81 -> 57528 | AK66: =+AK68+122463-AK81 -> 61641 | AL66: =+AL68+122951-AL81 -> 73200 | AM66: =+AM68+116110-AM81 -> 72188 | AN66: =+AN68+90826-AN81 -> 54976 | AO66: =+AO68+76558-AO81 -> 64025 | AP66: =+AP68+57228-AP81 -> 23913 | AQ66: =+AQ68+64323-AQ81 -> 51414 | AR66: =+AQ66+AR39 -> 185163 | AS66: =+AR66+AS39 -> 331384.51 | AT66: =+AS66+AT39 -> 505537.2 | AU66: =+AT66+AU39 -> 705816.42 | AV66: =+AU66+AV39 -> 939750.26 | AW66: =+AV66+AW39 -> 1207806.6 | AX66: =+AW66+AX39 -> 1480939.9 | AY66: =+AX66+AY39 -> 1790906 | ... BB66: =+BA66+BB39 -> 2969851.4
A68: Cash | E68: 13931 | H68: 26562 | I68: 34704 | J68: 80452 | M68: 18315 | N68: 20840 | O68: 17482 | P68: 28828 | Q68: 30242 | R68: 28849 | S68: 24296 | T68: 32105 | U68: 20935 | AB68: 5505 | AC68: 9610 | AD68: 6938 | AE68: 3804 | AF68: 8669 | AG68: 5595 | AH68: 6510 | AI68: 7663 | AJ68: 11946 | AK68: 11356 | AL68: 13576 | AM68: 14224 | AN68: 13931 | AO68: 34704 | AP68: 18315 | AQ68: 30242 | AR68: 20935
A69: Investments | E69: =+90826+6891 -> 97717 | H69: =+77865+9415 -> 87280 | I69: =+76558+9879 -> 86437 | J69: =+63499+11423 -> 74922 | M69: =+14600+57228 -> 71828 | N69: =+57588+15778 -> 73366 | O69: =+54073+15581 -> 69654 | P69: =+50790+16035 -> 66825 | Q69: =+15405+64323 -> 79728 | R69: =+73163+11465 -> 84628 | S69: =+65166+21202 -> 86368 | T69: =+46167+33683 -> 79850 | U69: =+36348+55908 -> 92256 | AB69: =+31283+7754 -> 39037 | AC69: =+43162+10865 -> 54027 | AD69: =+56102+9776 -> 65878 | AE69: =+73218+10844 -> 84062 | AF69: =+77040+14597 -> 91637 | AG69: =+90931+12053 -> 102984 | AH69: =+106730+10431 -> 117161 | AI69: =+125318+6023 -> 131341 | AJ69: =+121822+1862 -> 123684 | AK69: =+122463+2649 -> 125112 | AL69: =+122951+2965 -> 125916 | AM69: =+116110+5984 -> 122094 | AN69: =+90826+6891 -> 97717 | AO69: =+76558+9879 -> 86437 | AP69: =+14600+57228 -> 71828 | AQ69: =+15405+64323 -> 79728 | AR69: =+36348+55908 -> 92256
A70: A/R | E70: 44261 | H70: 37420 | I70: 48688 | J70: 36953 | M70: 56924 | N70: 44148 | O70: 48188 | P70: 51700 | Q70: 69905 | R70: 52894 | S70: 56535 | T70: 60041 | U70: 80876 | AB70: 13014 | AC70: 14987 | AD70: 15780 | AE70: 17486 | AF70: 19544 | AG70: 17908 | AH70: 18277 | AI70: 22431 | AJ70: 26481 | AK70: 29524 | AL70: 32011 | AM70: 38043 | AN70: 44261 | AO70: 48688 | AP70: 56924 | AQ70: 69905 | AR70: 80876 | AS70: =+(AS157/365)*AS13 -> 86159.951 | AT70: =+(AT157/365)*AT13 -> 98711.647 | AU70: =+(AU157/365)*AU13 -> 113518.39 | AV70: =+(AV157/365)*AV13 -> 127793.33 | AW70: =+(AW157/365)*AW13 -> 144406.47 | AX70: =+(AX157/365)*AX13 -> 159687.96 | AY70: =+(AY157/365)*AY13 -> 177253.64 | AZ70: =+(AZ157/365)*AZ13 -> 194229.08 | ... BB70: =+(BB157/365)*BB13 -> 236201.73
A71: Inventories | E71: 3742 | H71: 2877 | I71: 2500 | J71: 3000 | M71: 1246 | N71: 1626 | O71: 909 | P71: 848 | Q71: 938 | R71: 1130 | S71: 1059 | T71: 1219 | U71: 1397 | AB71: 740 | AC71: 1372 | AD71: 1137 | AE71: 1938 | AF71: 2660 | AG71: 2902 | AH71: 2251 | AI71: 2181 | AJ71: 2662 | AK71: 2063 | AL71: 1895 | AM71: 2636 | AN71: 3742 | AO71: 2500 | AP71: 1246 | AQ71: 938 | AR71: 1397 | AS71: =+(AS158/365)*AS19 -> 1675.3324 | AT71: =+(AT158/365)*AT19 -> 1881.6908 | AU71: =+(AU158/365)*AU19 -> 2092.9954 | AV71: =+(AV158/365)*AV19 -> 2345.5738 | AW71: =+(AW158/365)*AW19 -> 2604.8002 | AX71: =+(AX158/365)*AX19 -> 2866.1942 | AY71: =+(AY158/365)*AY19 -> 3124.6634 | AZ71: =+(AZ158/365)*AZ19 -> 3405.315 | ... BB71: =+(BB158/365)*BB19 -> 4040.2928
A72: PP&E | E72: 74398 | H72: 88132 | I72: 95641 | J72: 102502 | M72: 135591 | N72: 152863 | O72: 166902 | P72: 183939 | Q72: 204966 | R72: 230861 | S72: 261126 | T72: 283228 | U72: 313076 | AB72: 7630 | AC72: 8162 | AD72: 8269 | AE72: 9991 | AF72: 13011 | AG72: 14731 | AH72: 18356 | AI72: 23734 | AJ72: 29460 | AK72: 36477 | AL72: 44151 | AM72: 59715 | AN72: 74398 | AO72: 95641 | AP72: 135591 | AQ72: 204966 | AR72: 313076
A73: Op Lease ROU | E73: 13148 | H73: 13879 | I73: 14346 | J73: 15435 | M73: 18961 | N73: 20528 | O73: 22816 | P73: 24475 | Q73: 24823 | R73: 24791 | S73: 25103 | T73: 24403 | U73: 24177 | AB73: 0 | AC73: 0 | AD73: 0 | AE73: 0 | AF73: 0 | AG73: 0 | AH73: 0 | AI73: 6555 | AJ73: 6686 | AK73: 7379 | AL73: 8753 | AM73: 11088 | AN73: 13148 | AO73: 14346 | AP73: 18961 | AQ73: 24823 | AR73: 24177
A74: Goodwill | E74: 67524 | H74: 67940 | I74: 67886 | J74: 67790 | M74: 119220 | N74: 119374 | O74: 119191 | P74: 119329 | Q74: 119509 | R74: 119497 | S74: 119622 | T74: 119661 | U74: 119651 | AB74: 12394 | AC74: 12581 | AD74: 13452 | AE74: 14655 | AF74: 20127 | AG74: 16939 | AH74: 17872 | AI74: 35122 | AJ74: 35683 | AK74: 42026 | AL74: 43351 | AM74: 49711 | AN74: 67524 | AO74: 67886 | AP74: 119220 | AQ74: 119509 | AR74: 119651
A75: Intangible | E75: 11298 | H75: 9879 | I75: 9366 | J75: 8895 | M75: 27597 | N75: 26751 | O75: 25385 | P75: 23968 | Q75: 22604 | R75: 21236 | S75: 20289 | T75: 19325 | U75: 18609 | AB75: 1158 | AC75: 744 | AD75: 3170 | AE75: 3083 | AF75: 6981 | AG75: 4835 | AH75: 3733 | AI75: 10106 | AJ75: 8053 | AK75: 7750 | AL75: 7038 | AM75: 7800 | AN75: 11298 | AO75: 9366 | AP75: 27597 | AQ75: 22604 | AR75: 18609
A76: Other Current | E76: 16924 | H76: 19165 | I76: 21807 | J76: 23682 | M76: 26021 | N76: 25724 | O76: 26428 | P76: 24478 | Q76: 25723 | R76: 33030 | S76: 33134 | T76: 35797 | U76: 48594 | AB76: 2950 | AC76: 3320 | AD76: 3092 | AE76: 3388 | AF76: 4392 | AG76: 5461 | AH76: 5892 | AI76: 5103 | AJ76: 6751 | AK76: 10146 | AL76: 11482 | AM76: 13393 | AN76: 16924 | AO76: 21807 | AP76: 26021 | AQ76: 25723 | AR76: 48594
A77: Other Non Current | E77: =+21897 -> 21897 | H77: =+26954 -> 26954 | I77: =+30601 -> 30601 | J77: =+32154 -> 32154 | M77: =+36460 -> 36460 | N77: =+37793 -> 37793 | O77: =+36943 -> 36943 | P77: =+38234 -> 38234 | Q77: =+40565 -> 40565 | R77: =+39435 -> 39435 | S77: =+37770 -> 37770 | T77: =+38599 -> 38599 | U77: 38805 | AB77: =+1501+2184 -> 3685 | AC77: =+1434+2467 -> 3901 | AD77: =+2035+1520 -> 3555 | AE77: =+2392+1632 -> 4024 | AF77: =+3422+1941 -> 5363 | AG77: 3117 | AH77: 3416 | AI77: 6076 | AJ77: =+7442 -> 7442 | AK77: =+14723 -> 14723 | AL77: =+13138 -> 13138 | AM77: =+15075 -> 15075 | AN77: =+21897 -> 21897 | AO77: =+30601 -> 30601 | AP77: =+36460 -> 36460 | AQ77: =+40565 -> 40565 | AR77: 38805
A78: A | B78: =+SUM(B68:B77) -> 0 | C78: =+SUM(C68:C77) -> 0 | D78: =+SUM(D68:D77) -> 0 | E78: =+SUM(E68:E77) -> 364840 | F78: =+SUM(F68:F77) -> 0 | G78: =+SUM(G68:G77) -> 0 | H78: =+SUM(H68:H77) -> 380088 | I78: =+SUM(I68:I77) -> 411976 | ... U78: =+SUM(U68:U77) -> 758376 | AB78: =+SUM(AB68:AB77) -> 86113 | AC78: =+SUM(AC68:AC77) -> 108704 | AD78: =+SUM(AD68:AD77) -> 121271 | AE78: =+SUM(AE68:AE77) -> 142431 | AF78: =+SUM(AF68:AF77) -> 172384 | AG78: =+SUM(AG68:AG77) -> 174472 | AH78: =+SUM(AH68:AH77) -> 193468 | AI78: =+SUM(AI68:AI77) -> 250312 | ... AR78: =+SUM(AR68:AR77) -> 758376
A80: A/P | E80: 19000 | H80: 15305 | I80: 18095 | J80: 19307 | M80: 21996 | N80: 22768 | O80: 22608 | P80: 26250 | Q80: 27724 | R80: 32580 | S80: 37328 | T80: 37513 | U80: 42416 | AB80: 4025 | AC80: 4197 | AD80: 4175 | AE80: 4828 | AF80: 7432 | AG80: 6591 | AH80: 6898 | AI80: 7390 | AJ80: 8617 | AK80: 9382 | AL80: 12530 | AM80: 15163 | AN80: 19000 | AO80: 18095 | AP80: 21996 | AQ80: 27724 | AR80: 42416 | AS80: =+(AS159/365)*AS19 -> 34846.913 | AT80: =+(AT159/365)*AT19 -> 39515.506 | AU80: =+(AU159/365)*AU19 -> 43952.903 | AV80: =+(AV159/365)*AV19 -> 49726.165 | AW80: =+(AW159/365)*AW19 -> 55221.764 | AX80: =+(AX159/365)*AX19 -> 61336.555 | AY80: =+(AY159/365)*AY19 -> 66867.798 | AZ80: =+(AZ159/365)*AZ19 -> 73554.805 | ... BB80: =+(BB159/365)*BB19 -> 88886.441
A81: Debt | E81: =+2749+47032 -> 49781 | H81: =+6245+41965 -> 48210 | I81: =+5247+41990 -> 47237 | J81: =+25808+3748+41946 -> 71502 | M81: =+6693+2249+42688 -> 51630 | N81: =+0+2249+42868 -> 45117 | O81: =+0+5248+39722 -> 44970 | P81: =+0+39882+2999 -> 42881 | Q81: =+0+40152+2999 -> 43151 | R81: =+7832+35376 -> 43208 | S81: =+10103+35425 -> 45528 | T81: =+8839+31423 -> 40262 | U81: =+31067+9227 -> 40294 | AB81: =+1000+4939 -> 5939 | AC81: =+0+11921 -> 11921 | AD81: =+1231+10713 -> 11944 | AE81: =+2999+12601 -> 15600 | AF81: =+2000+20645 -> 22645 | AG81: =+4985+2499+27808 -> 35292 | AH81: =+12904+0+40557 -> 53461 | AI81: =+9072+1049+76073 -> 86194 | AJ81: =+3998+72242 -> 76240 | AK81: =+5516+66662 -> 72178 | AL81: =+3749+59578 -> 63327 | AM81: =+8072+50074 -> 58146 | AN81: =+2749+47032 -> 49781 | AO81: =+5247+41990 -> 47237 | AP81: =+6693+2249+42688 -> 51630 | AQ81: =+0+40152+2999 -> 43151 | AR81: =+31067+9227 -> 40294
A82: Accr. Compensation | E82: 10661 | H82: 10411 | I82: 11009 | J82: 6990 | M82: 12564 | N82: 8326 | O82: 9176 | P82: 10579 | Q82: 13709 | R82: =+9201 -> 9201 | S82: 10103 | T82: 11270 | U82: 14945 | AB82: 3283 | AC82: 3575 | AD82: 3875 | AE82: 4117 | AF82: 4797 | AG82: 5096 | AH82: 5264 | AI82: 5819 | AJ82: 6103 | AK82: 6830 | AL82: 7874 | AM82: 10057 | AN82: 10661 | AO82: 11009 | AP82: 12564 | AQ82: 13709 | AR82: 14945 | AS82: =+AR82*1.1 -> 16439.5 | AT82: =+AS82*1.1 -> 18083.45 | AU82: =+AT82*1.1 -> 19891.795 | AV82: =+AU82*1.1 -> 21880.975 | AW82: =+AV82*1.1 -> 24069.072 | AX82: =+AW82*1.05 -> 25272.526 | AY82: =+AX82*1.05 -> 26536.152 | AZ82: =+AY82*1.05 -> 27862.959 | BA82: =+AZ82*1.05 -> 29256.107 | BB82: =+BA82*1.05 -> 30718.913
AB83: =+AB82/AB$13 -> 0.052541451 | AC83: =+AC82/AC$13 -> 0.051113049 | AD83: =+AD82/AD$13 -> 0.052561616 | AE83: =+AE82/AE$13 -> 0.05288443 | AF83: =+AF82/AF$13 -> 0.055243974 | AG83: =+AG82/AG$13 -> 0.05445608 | AH83: =+AH82/AH$13 -> 0.06169714 | AI83: =+AI82/AI$13 -> 0.064691495 | ... BB83: =+BB82/BB$13 -> 0.027079678
A84: Income Taxes Curr. | E84: =+4067+26069 -> 30136 | H84: =+4163+25000 -> 29163 | I84: =+4152+25560 -> 29712 | J84: =+8035+22983 -> 31018 | M84: =+5017+27931 -> 32948 | N84: =+9717+24452 -> 34169 | O84: =+6056+24389 -> 30445 | P84: =+6805+25061 -> 31866 | Q84: =+7211+25986 -> 33197 | R84: =+3655+26569 -> 30224 | S84: =+2050+27256 -> 29306 | T84: =+3563+27941 -> 31504 | U84: =+2534+28647 -> 31181 | AB84: 1074 | AC84: 580 | AD84: 789 | AE84: 592 | AF84: 782 | AG84: 606 | AH84: 580 | AI84: 718 | AJ84: =+2121 -> 2121 | AK84: =+5665 -> 5665 | AL84: =+2130 -> 2130 | AM84: =+2174 -> 2174 | AN84: =+4067 -> 4067 | AO84: =+4152 -> 4152 | AP84: =+5017 -> 5017 | AQ84: =+7211 -> 7211 | AR84: =+2534+28647 -> 31181 | AS84: =+AR84*1.3 -> 40535.3 | AT84: =+AS84*1.2 -> 48642.36 | AU84: =+AT84*1.2 -> 58370.832 | AV84: =+AU84*1.2 -> 70044.998 | AW84: =+AV84*1.15 -> 80551.748 | AX84: =+AW84*1.15 -> 92634.51 | AY84: =+AX84*1.15 -> 106529.69 | AZ84: =+AY84*1.15 -> 122509.14 | BA84: =+AZ84*1.1 -> 134760.05 | BB84: =+BA84*1.1 -> 148236.06
AB85: =+AB84/AB$13 -> 0.0171884 | AC85: =+AC84/AC$13 -> 0.0082924667 | AD85: =+AD84/AD$13 -> 0.010702223 | AE85: =+AE84/AE$13 -> 0.0076044651 | AF85: =+AF84/AF$13 -> 0.0090057927 | AG85: =+AG84/AG$13 -> 0.0064757427 | AH85: =+AH84/AH$13 -> 0.0067979372 | AI85: =+AI84/AI$13 -> 0.0079822123 | ... BB85: =+BB84/BB$13 -> 0.1306747
A86: Income Taxes Non Current | AB86: 0 | AC86: 0 | AD86: 0 | AE86: 0 | AF86: 0 | AG86: 0 | AH86: 0 | AI86: 13485 | AJ86: 30265 | AK86: 29612 | AL86: 29432 | AM86: 27190 | AN86: 26069 | AO86: 25560 | AP86: 27931 | AQ86: 25986
A87: U/R Curr | E87: =+2870+45538 -> 48408 | H87: =+2698+36903 -> 39601 | I87: =+50901+2912 -> 53813 | J87: =+46429+2759 -> 49188 | M87: =+57582+2602 -> 60184 | N87: =+53026+2663 -> 55689 | O87: =+45508+2537 -> 48045 | P87: =+44636+2840 -> 47476 | Q87: =+2710+64555 -> 67265 | R87: =+58987+2546 -> 61533 | S87: =+51376+2668 -> 54044 | T87: =+50924+2753 -> 53677 | U87: =+72965 -> 72965 | AB87: =+13652 -> 13652 | AC87: =+15722 -> 15722 | AD87: =+18653 -> 18653 | AE87: =+20639 -> 20639 | AF87: =+23150 -> 23150 | AG87: =+23223 -> 23223 | AH87: =+27468 -> 27468 | AI87: 24013 | AJ87: =+28905 -> 28905 | AK87: =+32676 -> 32676 | AL87: =+36000 -> 36000 | AM87: =+41525 -> 41525 | AN87: =+45538 -> 45538 | AO87: =+50901 -> 50901 | AP87: =+57582 -> 57582 | AQ87: =+64555 -> 64555 | AR87: =+72965 -> 72965 | AS87: =+AR87*1.1 -> 80261.5 | AT87: =+AS87*1.1 -> 88287.65 | AU87: =+AT87*1.1 -> 97116.415 | AV87: =+AU87*1.1 -> 106828.06 | AW87: =+AV87*1.05 -> 112169.46 | AX87: =+AW87*1.05 -> 117777.93 | AY87: =+AX87*1.05 -> 123666.83 | AZ87: =+AY87*1.05 -> 129850.17 | BA87: =+AZ87*1.05 -> 136342.68 | BB87: =+BA87*1.05 -> 143159.81
AB88: =+AB87/AB$13 -> 0.21848793 | AC88: =+AC87/AC$13 -> 0.22478304 | AD88: =+AD87/AD$13 -> 0.25301466 | AE88: =+AE87/AE$13 -> 0.2651158 | AF88: =+AF87/AF$13 -> 0.26660371 | AG88: =+AG87/AG$13 -> 0.248162 | AH88: =+AH87/AH$13 -> 0.32194093 | AI88: =+AI87/AI$13 -> 0.26695942 | ... BB88: =+BB87/BB$13 -> 0.12619983
A89: U/R Non Curr | U89: 2747 | AB89: 1178 | AC89: 1398 | AD89: 1406 | AE89: 1760 | AF89: 2008 | AG89: 2095 | AH89: 6441 | AI89: 2643 | AJ89: 3815 | AK89: 4530 | AL89: 3180 | AM89: 2616 | AN89: 2870 | AO89: 2912 | AP89: 2602 | AQ89: 2710 | AR89: 2747
A90: D/T Curr. | E90: 230 | H90: 302 | I90: 433 | J90: 470 | M90: 2618 | N90: 2581 | O90: 2513 | P90: 2522 | Q90: 2835 | R90: 2852 | S90: 2876 | T90: 2899 | U90: 3054 | AB90: 229 | AC90: 1456 | AD90: 1893 | AE90: 1709 | AF90: 2728 | AG90: =+1295 -> 1295 | AH90: 1476 | AI90: 5734 | AJ90: 541 | AK90: 233 | AL90: 204 | AM90: 198 | AN90: 230 | AO90: 433 | AP90: 2618 | AQ90: 2835 | AR90: 3054
A91: Op Lease Liab. | E91: 11489 | H91: 12312 | I91: 12728 | J91: 13487 | M91: 15497 | N91: 16361 | O91: 17254 | P91: 17686 | Q91: 17437 | R91: 17348 | S91: 17345 | T91: 16703 | U91: 16532 | AB91: 0 | AC91: 0 | AD91: 0 | AE91: 0 | AF91: 0 | AG91: 0 | AH91: 0 | AI91: 5372 | AJ91: 5568 | AK91: 6188 | AL91: 7671 | AM91: 9629 | AN91: 11489 | AO91: 12728 | AP91: 15497 | AQ91: 17437 | AR91: 16532
A92: Other Liab. Curr | U92: 26738 | AB92: 2931 | AC92: 3492 | AD92: 3151 | AE92: 3597 | AF92: 6906 | AG92: 6555 | AH92: 5949 | AI92: 7684 | AJ92: =+8744 -> 8744 | AK92: 7581 | AL92: 10027 | AM92: 11666 | AN92: 13067 | AO92: 14745 | AP92: 19185 | AQ92: 25020 | AR92: 26738 | AS92: =+AR92*1.2 -> 32085.6 | AT92: =+AS92*1.15 -> 36898.44 | AU92: =+AT92*1.15 -> 42433.206 | AV92: =+AU92*1.15 -> 48798.187 | AW92: =+AV92*1.15 -> 56117.915 | AX92: =+AW92*1.1 -> 61729.706 | AY92: =+AX92*1.1 -> 67902.677 | AZ92: =+AY92*1.1 -> 74692.945 | BA92: =+AZ92*1.1 -> 82162.239 | BB92: =+BA92*1.1 -> 90378.463
AB93: =+AB92/AB$13 -> 0.046908008 | AC93: =+AC92/AC$13 -> 0.049926369 | AD93: =+AD92/AD$13 -> 0.042741071 | AE93: =+AE92/AE$13 -> 0.046204832 | AF93: =+AF92/AF$13 -> 0.079531975 | AG93: =+AG92/AG$13 -> 0.070047019 | AH93: =+AH92/AH$13 -> 0.069725738 | AI93: =+AI92/AI$13 -> 0.085425236 | ... BB93: =+BB92/BB$13 -> 0.079671428
A94: Other Liab. Non Curr | E94: =+13067+15526 -> 28593 | H94: =+17437+12664 -> 30101 | I94: =+17981+14745 -> 32726 | J94: =+18634+14475 -> 33109 | M94: =+27064+19185 -> 46249 | N94: =+31165+19114 -> 50279 | O94: =+35906+20286 -> 56192 | P94: =+38536+22937 -> 61473 | Q94: =+25020+45186 -> 70206 | R94: =+53588+22741 -> 76329 | S94: =+58852+24311 -> 83163 | T94: =+24552+61481 -> 86033 | U94: 65117 | AB94: =+7445+182 -> 7627 | AC94: =+1208+8072 -> 9280 | AD94: =+8208+814 -> 9022 | AE94: =+10000+645 -> 10645 | AF94: =+11594+558 -> 12152 | AG94: =+13544+92 -> 13636 | AH94: =+13640+294 -> 13934 | AI94: 3549 | AJ94: 5211 | AK94: =+9351 -> 9351 | AL94: =+10632 -> 10632 | AM94: =+13427 -> 13427 | AN94: =+15526 -> 15526 | AO94: =+17981 -> 17981 | AP94: =+27064 -> 27064 | AQ94: =+45186 -> 45186 | AR94: 65117
A95: L | B95: =+SUM(B80:B94)-B93-B88-B85-B83 -> 0 | C95: =+SUM(C80:C94)-C93-C88-C85-C83 -> 0 | D95: =+SUM(D80:D94)-D93-D88-D85-D83 -> 0 | E95: =+SUM(E80:E94)-E93-E88-E85-E83 -> 198298 | F95: =+SUM(F80:F94)-F93-F88-F85-F83 -> 0 | G95: =+SUM(G80:G94)-G93-G88-G85-G83 -> 0 | H95: =+SUM(H80:H94)-H93-H88-H85-H83 -> 185405 | I95: =+SUM(I80:I94)-I93-I88-I85-I83 -> 205753 | ... U95: =+SUM(U80:U94)-U93-U88-U85-U83 -> 315989 | AB95: =+SUM(AB80:AB94)-AB93-AB88-AB85-AB83 -> 39938 | AC95: =+SUM(AC80:AC94)-AC93-AC88-AC85-AC83 -> 51621 | AD95: =+SUM(AD80:AD94)-AD93-AD88-AD85-AD83 -> 54908 | AE95: =+SUM(AE80:AE94)-AE93-AE88-AE85-AE83 -> 63487 | AF95: =+SUM(AF80:AF94)-AF93-AF88-AF85-AF83 -> 82600 | AG95: =+SUM(AG80:AG94)-AG93-AG88-AG85-AG83 -> 94389 | AH95: =+SUM(AH80:AH94)-AH93-AH88-AH85-AH83 -> 121471 | AI95: =+SUM(AI80:AI94)-AI93-AI88-AI85-AI83 -> 162601 | ... AR95: =+SUM(AR80:AR94)-AR93-AR88-AR85-AR83 -> 315989
A96: Stocks | E96: 86939 | H96: 92093 | I96: 93718 | J96: 95508 | M96: 100923 | N96: 102976 | O96: 104829 | P96: 106965 | Q96: 109095 | R96: 110964 | S96: 112788 | T96: 115060 | U96: 117406 | AB96: 62856 | AC96: 63415 | AD96: 65797 | AE96: 67306 | AF96: 68366 | AG96: 68465 | AH96: 68178 | AI96: 69315 | AJ96: 71223 | AK96: 78520 | AL96: 80552 | AM96: 83111 | AN96: 86939 | AO96: 93718 | AP96: 100923 | AQ96: 109095 | AR96: 117406
A97: Retain. Earnings | E97: 84281 | H97: 108234 | I97: 118848 | J97: 132143 | M97: 173144 | N97: 188929 | O97: 203482 | P97: 219759 | Q97: 237731 | R97: 254873 | S97: 280789 | T97: 302526 | U97: 328265 | AB97: -16681 | AC97: -6332 | AD97: 566 | AE97: 9895 | AF97: 17710 | AG97: 9096 | AH97: 2282 | AI97: 17769 | AJ97: 13682 | AK97: 24150 | AL97: 34566 | AM97: 57055 | AN97: 84281 | AO97: 118848 | AP97: 173144 | AQ97: 237731 | AR97: 328265
A98: Acc. Comprehensive loss | E98: -4678 | H98: -5644 | I98: -6343 | J98: -6937 | M98: -5590 | N98: -4182 | O98: -5616 | P98: -4833 | Q98: -3347 | R98: -2761 | S98: -2702 | T98: -3228 | U98: -3284 | AB98: 0 | AC98: 0 | AD98: 0 | AE98: 1743 | AF98: 3708 | AG98: 2522 | AH98: 1537 | AI98: 627 | AJ98: -2187 | AK98: -340 | AL98: 3186 | AM98: 1822 | AN98: -4678 | AO98: -6343 | AP98: -5590 | AQ98: -3347 | AR98: -3284
A99: SE | B99: =+SUM(B96:B98) -> 0 | C99: =+SUM(C96:C98) -> 0 | D99: =+SUM(D96:D98) -> 0 | E99: =+SUM(E96:E98) -> 166542 | F99: =+SUM(F96:F98) -> 0 | G99: =+SUM(G96:G98) -> 0 | H99: =+SUM(H96:H98) -> 194683 | I99: =+SUM(I96:I98) -> 206223 | ... U99: =+SUM(U96:U98) -> 442387 | AB99: =+SUM(AB96:AB98) -> 46175 | AC99: =+SUM(AC96:AC98) -> 57083 | AD99: =+SUM(AD96:AD98) -> 66363 | AE99: =+SUM(AE96:AE98) -> 78944 | AF99: =+SUM(AF96:AF98) -> 89784 | AG99: =+SUM(AG96:AG98) -> 80083 | AH99: =+SUM(AH96:AH98) -> 71997 | AI99: =+SUM(AI96:AI98) -> 87711 | ... AR99: =+SUM(AR96:AR98) -> 442387
A100: L+SE | B100: =+B99+B95 -> 0 | C100: =+C99+C95 -> 0 | D100: =+D99+D95 -> 0 | E100: =+E99+E95 -> 364840 | F100: =+F99+F95 -> 0 | G100: =+G99+G95 -> 0 | H100: =+H99+H95 -> 380088 | I100: =+I99+I95 -> 411976 | ... U100: =+U99+U95 -> 758376 | AB100: =+AB99+AB95 -> 86113 | AC100: =+AC99+AC95 -> 108704 | AD100: =+AD99+AD95 -> 121271 | AE100: =+AE99+AE95 -> 142431 | AF100: =+AF99+AF95 -> 172384 | AG100: =+AG99+AG95 -> 174472 | AH100: =+AH99+AH95 -> 193468 | AI100: =+AI99+AI95 -> 250312 | ... AR100: =+AR99+AR95 -> 758376
A102: Model NI | B102: =+B39 -> 0 | C102: =+C39 -> 0 | D102: =+D39 -> 16728 | E102: =+E39 -> 16740 | F102: =+F39 -> 17556 | G102: =+G39 -> 0 | H102: =+H39 -> 18299 | I102: =+I39 -> 20081 | ... U102: =+U39 -> 35766 | AB102: =+AB39 -> 18760 | AC102: =+AC39 -> 23150 | AD102: =+AD39 -> 16978 | AE102: =+AE39 -> 21863 | AF102: =+AF39 -> 22074 | AG102: =+AG39 -> 12193 | AH102: =+AH39 -> 16798 | AI102: =+AI39 -> 21204 | ... BB102: =+BB39 -> 439366.12
A103: Net Income | D103: 16728 | E103: 16740 | F103: 17556 | H103: 18299 | I103: 20081 | J103: 22291 | K103: 21870 | L103: 21939 | M103: 22036 | N103: 24667 | O103: 24108 | P103: 25824 | Q103: 27233 | R103: 27747 | S103: 38458 | T103: 31778 | U103: 35766 | AB103: 18760 | AC103: 23150 | AD103: 16978 | AE103: 21863 | AF103: 22074 | AG103: 12193 | AH103: 16798 | AI103: 21204 | AJ103: 16571 | AK103: 39240 | AL103: 44281 | AM103: 61271 | AN103: 72738 | AO103: 72361 | AP103: 88136 | AQ103: 101832 | AR103: 133749
A104: D&A | D104: 3773 | E104: 3979 | F104: 2790 | H104: 3549 | I104: 3874 | J104: 3921 | K104: 5959 | L104: 6027 | M104: 6380 | N104: 7383 | O104: 5667 | P104: 8740 | Q104: 11203 | R104: 13061 | S104: 9198 | T104: 10167 | U104: 11022 | AB104: 2673 | AC104: 2766 | AD104: =+2967+6193 -> 9160 | AE104: 3755 | AF104: 5212 | AG104: 5957 | AH104: 6622 | AI104: 8778 | AJ104: 10261 | AK104: 11682 | AL104: 12796 | AM104: 11686 | AN104: 14460 | AO104: 13861 | AP104: 22287 | AQ104: 34153 | AR104: 38534 | AS104: =+AS13*0.2 -> 77650.326 | AT104: =+AT13*0.2 -> 90074.378 | AU104: =+AU13*0.2 -> 103585.53 | AV104: =+AV13*0.2 -> 118087.51 | AW104: =+AW13*0.2 -> 133438.89 | AX104: =+AX13*0.13 -> 97143.509 | AY104: =+AY13*0.13 -> 107829.3 | AZ104: =+AZ13*0.13 -> 119690.52 | BA104: =+BA13*0.13 -> 132856.47 | BB104: =+BB13*0.13 -> 147470.69
F105: =+F104/B104-1 -> #DIV/0! | G105: =+G104/C104-1 -> #DIV/0! | H105: =+H104/D104-1 -> -0.059369202 | I105: =+I104/E104-1 -> -0.02638854 | J105: =+J104/F104-1 -> 0.40537634 | K105: =+K104/G104-1 -> #DIV/0! | L105: =+L104/H104-1 -> 0.69822485 | M105: =+M104/I104-1 -> 0.64687661 | ... U105: =+U104/Q104-1 -> -0.016156387 | AB105: =+AB104/AB$13 -> 0.042778951 | AC105: =+AC104/AC$13 -> 0.039546488 | AD105: =+AD104/AD$13 -> 0.12424888 | AE105: =+AE104/AE$13 -> 0.048234402 | AF105: =+AF104/AF$13 -> 0.060023263 | AG105: =+AG104/AG$13 -> 0.063656764 | AH105: =+AH104/AH$13 -> 0.07761369 | AI105: =+AI104/AI$13 -> 0.097587549 | ... BB105: =+BB104/BB$13 -> 0.13
...

Sheet Bond
A1: Main
B3: isin | C3: bondType | D3: immediateIssuer | E3: coupon | F3: couponType | G3: maturityDate | H3: callable | I3: currency | J3: seniorityLevel | K3: liquidityScore
B4: US594918BR43 | C4: — | D4: Microsoft Corporation | E4: 2400 | F4: Fixed Listing | G4: 08/08/2026 | H4: Y | I4: USD | J4: Senior | K4: —
B5: US00507VAK52 | C5: — | D5: Activision Blizzard, Inc. | E5: 3400 | F5: Fixed Listing | G5: 15/09/2026 | H5: Y | I5: USD | J5: Senior | K5: —
B6: US594918CG78 | C6: — | D6: Microsoft Corporation | E6: 3400 | F6: Fixed Listing | G6: 15/09/2026 | H6: Y | I6: USD | J6: Senior | K6: —
B7: US594918CM47 | C7: — | D7: Microsoft Corporation | E7: 3400 | F7: Fixed Listing | G7: 15/09/2026 | H7: Y | I7: USD | J7: Senior | K7: —
B8: US594918CN20 | C8: — | D8: Microsoft Corporation | E8: 3400 | F8: Fixed Listing | G8: 15/09/2026 | H8: Y | I8: USD | J8: Senior | K8: —
B9: USU59340AH90 | C9: — | D9: Microsoft Corporation | E9: 3400 | F9: Fixed Listing | G9: 15/09/2026 | H9: Y | I9: USD | J9: Senior | K9: —
B10: US594918BY93 | C10: — | D10: Microsoft Corporation | E10: 3300 | F10: Fixed Listing | G10: 06/02/2027 | H10: Y | I10: USD | J10: Senior | K10: —
B11: US00507VAM19 | C11: — | D11: Activision Blizzard, Inc. | E11: 3400 | F11: Fixed Listing | G11: 15/06/2027 | H11: Y | I11: USD | J11: Senior | K11: — | M11: MSFT acquired Blizzard in 2013
B12: US594918CH51 | C12: — | D12: Microsoft Corporation | E12: 3400 | F12: Fixed Listing | G12: 15/06/2027 | H12: Y | I12: USD | J12: Senior | K12: —
B13: US594918CP77 | C13: — | D13: Microsoft Corporation | E13: 3400 | F13: Fixed Listing | G13: 15/06/2027 | H13: Y | I13: USD | J13: Senior | K13: —
B14: US594918CQ50 | C14: — | D14: Microsoft Corporation | E14: 3400 | F14: Fixed Listing | G14: 15/06/2027 | H14: Y | I14: USD | J14: Senior | K14: —
B15: USU59340AJ56 | C15: — | D15: Microsoft Corporation | E15: 3400 | F15: Fixed Listing | G15: 15/06/2027 | H15: Y | I15: USD | J15: Senior | K15: —
B16: XS1001749289 | C16: — | D16: Microsoft Corporation | E16: 3125 | F16: Fixed Listing | G16: 06/12/2028 | H16: Y | I16: EUR | J16: Senior | K16: —
B17: US00507VAP40 | C17: — | D17: Activision Blizzard, Inc. | E17: 1350 | F17: Fixed Listing | G17: 15/09/2030 | H17: Y | I17: USD | J17: Senior | K17: —
B18: US594918CJ18 | C18: — | D18: Microsoft Corporation | E18: 1350 | F18: Fixed Listing | G18: 15/09/2030 | H18: Y | I18: USD | J18: Senior | K18: —
B19: US594918CR34 | C19: — | D19: Microsoft Corporation | E19: 1350 | F19: Fixed Listing | G19: 15/09/2030 | H19: Y | I19: USD | J19: Senior | K19: —
B20: US594918CS17 | C20: — | D20: Microsoft Corporation | E20: 1350 | F20: Fixed Listing | G20: 15/09/2030 | H20: Y | I20: USD | J20: Senior | K20: —
B21: USU59340AK20 | C21: — | D21: Microsoft Corporation | E21: 1350 | F21: Fixed Listing | G21: 15/09/2030 | H21: Y | I21: USD | J21: Senior | K21: —
B22: XS0922885362 | C22: — | D22: Microsoft Corporation | E22: 2625 | F22: Fixed Listing | G22: 02/05/2033 | H22: Y | I22: EUR | J22: Senior | K22: —
B23: US594918BC73 | C23: — | D23: Microsoft Corporation | E23: 3500 | F23: Fixed Listing | G23: 12/02/2035 | H23: Y | I23: USD | J23: Senior | K23: —
... B54: US594918CF95 | C54: — | D54: Microsoft Corporation | E54: 3041 | F54: Fixed Listing | G54: 17/03/2062 | H54: Y | I54: USD | J54: Senior | K54: —
E55: =+AVERAGE(E4:E54) -> 3413.4706

Sheet Board
A1: Main
