Workbook

Sheet Main
A1: Netflix | F1: price | G1: 78
A2: The 4th quarter is the most sub grower | F2: shares | G2: 4163.9397 | H2: Q226
A3: Asian users watch ½ to 2/3 the amount of TV as US consumers | F3: MC | G3: =G2*G1 -> 324787.29 | O3: -> | P3: After the NFLX – WBD acquisition, the management proved to be long term viewer and willing to maximize the shareholder value
F4: cash | G4: 9128 | H4: Q226 | O4: -> | P4: Acquired InterPositive AI film making studio
F5: debt | G5: 14309 | H5: Q226 | O5: -> | P5: NFLX to increase subscription prices.
F6: EV | G6: =G3-G4+G5 -> 329968.29 | P6: 8.99$ (from 7.99$) for AD supported tier, 19.99$ (from 17.99), adding a user in ad free account is not 6.99$ (from 7.99)
G7: =G6/(SUM(Model!W40:Z40)) -> 24.667473 | P7: and adding from an ad free account is 9.99$ (from 8.99). Ad free passes at 26.99$ (from 24.99)
O8: -> | P8: 275 M&A cost (not just for WBD)
A9: BETA | B9: 1.49 | D9: WACC | E9: =+(G3/(G3+G5))*B10+(G5/(G3+G5))*B11*(1-Model!AN52) -> 0.12117122
A10: CAPM | B10: =+0.05 + B9*(0.1 - 0.05) -> 0.1245
A11: Cost of Debt | B11: =+0.045 + (B17/100) -> 0.052847826 | C11: 0.0472 | D11: EV/Subs | E11: =+G6/Model!AN11 -> 1015.2871
A12: P/E | B12: =+G1/Model!AN42 -> 30.856029
A13: P/FCF | B13: =+G3/SUM(Model!X135:AA135) -> 29.125108 | H13: P/B | I13: =G3/Model!Z113 -> 10.434464
A14: EV/EBITDA | B14: =+G6/SUM(Model!X58:AA58) -> 22.404283 | H14: D/E | I14: =Model!Z97/Model!Z113 -> 0.42926042
A15: EV/FCF | B15: =+G6/SUM(Model!X135:AA135) -> 29.589711
A16: Inc Margin | B16: =+((Model!AA30+Model!Z30+Model!Y30+Model!X30)-(Model!W30+Model!V30+Model!U30+Model!T30))/((Model!AA16+Model!Z16+Model!Y16+Model!X16)-(Model!W16+Model!V16+Model!U16+Model!T16)) -> 0.29969701
A17: Cr. Spread | B17: =+'[1]Credit Spread US'!J6 -> 0.78478261
A18: Rating | B18: A- | C18: A3
B19: S&P | C19: Moody’s
A22: IR | F22: CEO | G22: Ted Sarandos
A23: ir@netflix.com | F23: Founded | G23: 1997
F24: Streaming | G24: 2007
A26: UCAN | B26: 2020 | C26: =B26+1 -> 2021 | D26: =C26+1 -> 2022 | E26: =D26+1 -> 2023 | F26: =E26+1 -> 2024 | G26: =F26+1 -> 2025 | I26: Arm | J26: =(Model!AN16/(F28+F33+F38+F43))/12 -> 12.487273
A27: Streaming Revenues | D27: 14084 | E27: 14873 | F27: 17359
A28: Memberships | D28: 74 | E28: 80.1 | F28: 89.625
A29: ARM | B29: =(B27/B28)/12 -> #DIV/0! | C29: =(C27/C28)/12 -> #DIV/0! | D29: =(D27/D28)/12 -> 15.86036 | E29: =(E27/E28)/12 -> 15.473367 | F29: =(F27/F28)/12 -> 16.1404 | G29: =(G27/G28)/12 -> #DIV/0!
A31: EMEA
A32: Streaming Revenues | D32: 9745 | E32: 10556.4 | F32: 12387
A33: Memberships | D33: 76.7 | E33: 88.8 | F33: 101.1
A34: ARM | B34: =(B32/B33)/12 -> #DIV/0! | C34: =(C32/C33)/12 -> #DIV/0! | D34: =(D32/D33)/12 -> 10.587788 | E34: =(E32/E33)/12 -> 9.9065315 | F34: =(F32/F33)/12 -> 10.210188 | G34: =(G32/G33)/12 -> #DIV/0!
A36: LATAM
A37: Streaming Revenues | D37: 4069.9 | E37: 4446.4 | F37: 4839.8
A38: Memberships | D38: 41.6 | E38: 45.9 | F38: 53.3
A39: ARM | B39: =(B37/B38)/12 -> #DIV/0! | C39: =(C37/C38)/12 -> #DIV/0! | D39: =(D37/D38)/12 -> 8.1528446 | E39: =(E37/E38)/12 -> 8.0726216 | F39: =(F37/F38)/12 -> 7.5669168 | G39: =(G37/G38)/12 -> #DIV/0!
A41: APAC
A42: Streaming Revenues | D42: 3570.2 | E42: 3763.7 | F42: 4414.7
A43: Memberships | D43: 38 | E43: 45.3 | F43: 57.5
A44: ARM | B44: =(B42/B43)/12 -> #DIV/0! | C44: =(C42/C43)/12 -> #DIV/0! | D44: =(D42/D43)/12 -> 7.829386 | E44: =(E42/E43)/12 -> 6.9236571 | F44: =(F42/F43)/12 -> 6.3981159 | G44: =(G42/G43)/12 -> #DIV/0!

Sheet Model
A1: Main
A2: in Millions | B2: Q120 | C2: Q220 | D2: Q320 | E2: Q420 | F2: Q121 | G2: Q221 | H2: Q321 | I2: Q421 | J2: Q122 | K2: Q222 | L2: Q322 | M2: Q422 | N2: Q123 | O2: Q223 | P2: Q323 | Q2: Q423 | R2: Q124 | S2: Q224 | T2: Q324 | U2: Q424 | V2: Q125 | W2: Q225 | X2: Q325 | Y2: Q425 | Z2: Q126 | AA2: Q226 | AB2: Q326 | AC2: Q426 | AI2: 2020 | AJ2: 2021 | AK2: 2022 | AL2: =AK2+1 -> 2023 | AM2: =AL2+1 -> 2024 | AN2: =AM2+1 -> 2025 | AO2: =AN2+1 -> 2026 | AP2: =AO2+1 -> 2027 | AQ2: =AP2+1 -> 2028 | AR2: =AQ2+1 -> 2029 | AS2: =AR2+1 -> 2030
A3: Disney + Subs | AK3: 102.9 | AL3: 112.6 | AM3: 125.3 | AN3: 131.6
AL4: =+AL3/AK3-1 -> 0.094266278 | AM4: =+AM3/AL3-1 -> 0.11278863 | AN4: =+AN3/AM3-1 -> 0.05027933
A5: Disney+ ARPU | AK5: 6.22 | AL5: 6.39 | AM5: 7.04 | AN5: 7.81
AL6: =+AL5/AK5-1 -> 0.02733119 | AM6: =+AM5/AL5-1 -> 0.10172144 | AN6: =+AN5/AM5-1 -> 0.109375
A7: Hulu Subs | AK7: 47.2 | AL7: 48.5 | AM7: 52 | AN7: 64.1
AL8: =+AL7/AK7-1 -> 0.027542373 | AM8: =+AM7/AL7-1 -> 0.072164948 | AN8: =+AN7/AM7-1 -> 0.23269231
A11: Subscriptions | B11: 182.8 | C11: 192.9 | D11: 195.1 | E11: 203.6 | F11: 107.6 | G11: 109.1 | H11: 213.56 | I11: 221.84 | J11: 221.64 | K11: 220.6 | L11: 223.09 | M11: 230.7 | N11: 232.5 | O11: 238.3 | P11: 247.15 | Q11: 260.2 | R11: 269.6 | S11: 277.6 | T11: 282.7 | U11: 301 | V11: - | W11: - | X11: - | Y11: 325 | Z11: 0 | AA11: =Z11*1.05 -> 0 | AB11: =AA11*1.05 -> 0 | AC11: =AB11*1.05 -> 0 | AI11: =E11 -> 203.6 | AJ11: =I11 -> 221.84 | AK11: =M11 -> 230.7 | AL11: =Q11 -> 260.2 | AM11: =U11 -> 301 | AN11: 325 | AO11: =AN11*1.07 -> 347.75 | AP11: =AO11*1.07 -> 372.0925 | AQ11: =AP11*1.07 -> 398.13898 | AR11: =AQ11*1.07 -> 426.0087 | AS11: =AR11*1.07 -> 455.82931
F12: =+F11/B11-1 -> -0.41137856 | G12: =+G11/C11-1 -> -0.43442198 | H12: =+H11/D11-1 -> 0.094618145 | I12: =+I11/E11-1 -> 0.089587426 | J12: =+J11/F11-1 -> 1.0598513 | K12: =+K11/G11-1 -> 1.0219982 | L12: =+L11/H11-1 -> 0.044624462 | M12: =+M11/I11-1 -> 0.039938695 | ... U12: =+U11/Q11-1 -> 0.15680246 | V12: N.M. | W12: N.M. | X12: N.M. | Y12: =+Y11/U11-1 -> 0.079734219 | Z12: N.M. | AJ12: =+AJ11/AI11-1 -> 0.089587426 | AK12: =+AK11/AJ11-1 -> 0.039938695 | AL12: =+AL11/AK11-1 -> 0.12787169 | AM12: =+AM11/AL11-1 -> 0.15680246 | AN12: =+AN11/AM11-1 -> 0.079734219 | AO12: =+AO11/AN11-1 -> 0.07 | AP12: =+AP11/AO11-1 -> 0.07 | AQ12: =+AQ11/AP11-1 -> 0.07 | ... AS12: =+AS11/AR11-1 -> 0.07
A13: ARM | B13: =+B16/B11 -> 31.551422 | C13: =+C16/C11 -> 31.872473 | D13: =+D16/D11 -> 32.986161 | E13: =+E16/E11 -> 32.634578 | F13: =+F16/F11 -> 66.572491 | G13: =+G16/G11 -> 67.294015 | H13: =+H16/H11 -> 35.041206 | I13: =+I16/I11 -> 34.751623 | ... U13: =+U16/U11 -> 34.043189 | V13: 0 | W13: 0 | X13: 0 | Y13: =+Y16/Y11 -> 37.079077 | AI13: =+AI16/AI11 -> 122.77041 | AJ13: =+AJ16/AJ11 -> 133.87056 | AK13: =+AK16/AK11 -> 137.04183 | AL13: =+AL16/AL11 -> 129.60529 | AM13: =+AM16/AM11 -> 129.57142 | AN13: =+AN16/AN11 -> 139.02369 | AO13: =+AO16/AO11 -> 147.72891 | AP13: =+AP16/AP11 -> 156.97923 | ... AS13: =+AS16/AS11 -> 183.25919
F14: =+F13/B13-1 -> 1.109968 | G14: =+G13/C13-1 -> 1.1113522 | H14: =+H13/D13-1 -> 0.062300226 | I14: =+I13/E13-1 -> 0.06487123 | J14: =+J13/F13-1 -> -0.46678195 | K14: =+K13/G13-1 -> -0.46312105 | L14: =+L13/H13-1 -> 0.013771598 | M14: =+M13/I13-1 -> -0.020605622 | ... U14: =+U13/Q13-1 -> 0.0029481288 | V14: N.M. | W14: N.M. | X14: N.M. | Y14: =+Y13/U13-1 -> 0.08917753 | Z14: N.M. | AJ14: =+AJ13/AI13-1 -> 0.090413826 | AK14: =+AK13/AJ13-1 -> 0.023689107 | AL14: =+AL13/AK13-1 -> -0.054264725 | AM14: =+AM13/AL13-1 -> -0.00026138439 | AN14: =+AN13/AM13-1 -> 0.072950326 | AO14: =+AO13/AN13-1 -> 0.062616822 | AP14: =+AP13/AO13-1 -> 0.062616822 | AQ14: =+AQ13/AP13-1 -> 0.056074766 | ... AS14: =+AS13/AR13-1 -> 0.046728972
A16: Revenues | B16: 5767.6 | C16: 6148.2 | D16: 6435.6 | E16: 6644.4 | F16: 7163.2 | G16: 7341.777 | H16: 7483.4 | I16: 7709.3 | J16: 7867.7 | K16: 7970 | L16: 7925 | M16: 7852 | N16: 8161.5 | O16: 8187 | P16: 8542 | Q16: 8832 | R16: 9370 | S16: 9559 | T16: 9824 | U16: 10247 | V16: 10543 | W16: 11079 | X16: 11510 | Y16: 12050.7 | Z16: 12249.757 | AA16: 12559.938 | AB16: =X16*1.155 -> 13294.05 | AC16: =Y16*1.155 -> 13918.558 | AI16: 24996.056 | AJ16: 29697.844 | AK16: 31615.55 | AL16: 33723.297 | AM16: 39000.996 | AN16: =SUM(V16:Y16) -> 45182.7 | AO16: =AN16*1.137 -> 51372.73 | AP16: =AO16*1.137 -> 58410.794 | AQ16: =AP16*1.13 -> 66004.197 | AR16: =AQ16*1.13 -> 74584.743 | AS16: =AR16*1.12 -> 83534.912
F17: =+F16/B16-1 -> 0.2419724 | G17: =+G16/C16-1 -> 0.19413438 | H17: =+H16/D16-1 -> 0.1628131 | I17: =+I16/E16-1 -> 0.1602703 | J17: =+J16/F16-1 -> 0.098349899 | K17: =+K16/G16-1 -> 0.085568249 | L17: =+L16/H16-1 -> 0.05901061 | M17: =+M16/I16-1 -> 0.018510111 | ... AC17: =+AC16/Y16-1 -> 0.155 | AJ17: =+AJ16/AI16-1 -> 0.18810119 | AK17: =+AK16/AJ16-1 -> 0.064573913 | AL17: =+AL16/AK16-1 -> 0.066668048 | AM17: =+AM16/AL16-1 -> 0.15650009 | AN17: =+AN16/AM16-1 -> 0.15850118 | AO17: =+AO16/AN16-1 -> 0.137 | AP17: =+AP16/AO16-1 -> 0.137 | AQ17: =+AQ16/AP16-1 -> 0.13 | ... AS17: =+AS16/AR16-1 -> 0.12
A18: COGS | B18: 3599.7 | C18: 3643.7 | D18: 3867.7 | E18: 4165.1 | F18: 3868.5 | G18: 4018 | H18: 4206.5 | I18: 5239.5 | J18: 4284.7 | K18: 4690.7 | L18: 4788 | M18: 5404 | N18: 4803 | O18: 4673 | P18: 4930 | Q18: 5307 | R18: 4977 | S18: 5174 | T18: 5119 | U18: 5767 | V18: 5263 | W18: 5325 | X18: 6164 | Y18: 6522.621 | Z18: 5888.238 | AA18: 6036.965 | AB18: =AB16-AB20 -> 6514.0845 | AC18: =AC16-AC20 -> 6820.0937 | AI18: 15276.319 | AJ18: 17332.683 | AK18: 19168.285 | AL18: 19715.368 | AM18: 21038.464 | AN18: 23275.329 | AO18: =AO16-AO20 -> 25686.365 | AP18: =AP16-AP20 -> 28329.235 | AQ18: =AQ16-AQ20 -> 31682.015 | AR18: =AR16-AR20 -> 35427.753 | AS18: =AS16-AS20 -> 39261.409
B19: =+B18/B$16 -> 0.62412442 | C19: =+C18/C$16 -> 0.592645 | D19: =+D18/D$16 -> 0.60098515 | E19: =+E18/E$16 -> 0.62685871 | F19: =+F18/F$16 -> 0.54005193 | G19: =+G18/G$16 -> 0.54727895 | H19: =+H18/H$16 -> 0.56211081 | I19: =+I18/I$16 -> 0.67963369 | ... AC19: =+AC18/AC$16 -> 0.49 | AI19: =+AI18/AI$16 -> 0.61114917 | AJ19: =+AJ18/AJ$16 -> 0.58363439 | AK19: =+AK18/AK$16 -> 0.60629295 | AL19: =+AL18/AL$16 -> 0.5846216 | AM19: =+AM18/AM$16 -> 0.53943402 | AN19: =+AN18/AN$16 -> 0.51513807 | AO19: =+AO18/AO$16 -> 0.5 | AP19: =+AP18/AP$16 -> 0.485 | ... AS19: =+AS18/AS$16 -> 0.47
A20: Gross Profit | B20: =B16-B18 -> 2167.9 | C20: =C16-C18 -> 2504.5 | D20: =D16-D18 -> 2567.9 | E20: =E16-E18 -> 2479.3 | F20: =F16-F18 -> 3294.7 | G20: =G16-G18 -> 3323.777 | H20: =H16-H18 -> 3276.9 | I20: =I16-I18 -> 2469.8 | ... AA20: =AA16-AA18 -> 6522.973 | AB20: =AB16*0.51 -> 6779.9655 | AC20: =AC16*0.51 -> 7098.4648 | AI20: =AI16-AI18 -> 9719.737 | AJ20: =AJ16-AJ18 -> 12365.161 | AK20: =AK16-AK18 -> 12447.265 | AL20: =AL16-AL18 -> 14007.929 | AM20: =AM16-AM18 -> 17962.532 | AN20: =AN16-AN18 -> 21907.371 | AO20: =AO16*0.5 -> 25686.365 | AP20: =AP16*0.515 -> 30081.559 | AQ20: =AQ16*0.52 -> 34322.182 | AR20: =AR16*0.525 -> 39156.99 | AS20: =AS16*0.53 -> 44273.503
B21: =+B20/B$16 -> 0.37587558 | C21: =+C20/C$16 -> 0.407355 | D21: =+D20/D$16 -> 0.39901485 | E21: =+E20/E$16 -> 0.37314129 | F21: =+F20/F$16 -> 0.45994807 | G21: =+G20/G$16 -> 0.45272105 | H21: =+H20/H$16 -> 0.43788919 | I21: =+I20/I$16 -> 0.32036631 | ... AC21: =+AC20/AC$16 -> 0.51 | AI21: =+AI20/AI$16 -> 0.38885083 | AJ21: =+AJ20/AJ$16 -> 0.41636561 | AK21: =+AK20/AK$16 -> 0.39370705 | AL21: =+AL20/AL$16 -> 0.4153784 | AM21: =+AM20/AM$16 -> 0.46056598 | AN21: =+AN20/AN$16 -> 0.48486193 | AO21: =+AO20/AO$16 -> 0.5 | AP21: =+AP20/AP$16 -> 0.515 | ... AS21: =+AS20/AS$16 -> 0.53
A22: T&D | B22: 453.8 | C22: 435 | D22: 453.8 | E22: 486.9 | F22: 525.2 | G22: 537.3 | H22: 563.8 | I22: 647 | J22: 657.5 | K22: 716.8 | L22: 662.7 | M22: 673.9 | N22: 687.2 | O22: 657 | P22: 657 | Q22: 673 | R22: 702 | S22: 711 | T22: 735 | U22: 776 | V22: 822 | W22: 824 | X22: 853 | Y22: 890.3 | Z22: 959.696 | AA22: 1007.675 | AB22: =X22*1.13 -> 963.89 | AC22: =Y22*1.13 -> 1006.039 | AI22: 1829.6 | AJ22: 2273.885 | AK22: 2711.041 | AL22: 2675.758 | AM22: 2925.295 | AN22: 3391.39 | AO22: =+AO16*0.073 -> 3750.2093 | AP22: =+AP16*0.073 -> 4263.988 | AQ22: =+AQ16*0.073 -> 4818.3064 | AR22: =+AR16*0.073 -> 5444.6862 | AS22: =+AS16*0.07 -> 5847.4438
B23: =+B22/B$16 -> 0.078680907 | C23: =+C22/C$16 -> 0.070752415 | D23: =+D22/D$16 -> 0.070514016 | E23: =+E22/E$16 -> 0.073279754 | F23: =+F22/F$16 -> 0.073319187 | G23: =+G22/G$16 -> 0.073183917 | H23: =+H22/H$16 -> 0.075340086 | I23: =+I22/I$16 -> 0.083924611 | ... AC23: =+AC22/AC$16 -> 0.072280402 | AI23: =+AI22/AI$16 -> 0.073195547 | AJ23: =+AJ22/AJ$16 -> 0.076567343 | AK23: =+AK22/AK$16 -> 0.08575024 | AL23: =+AL22/AL$16 -> 0.079344496 | AM23: =+AM22/AM$16 -> 0.075005649 | AN23: =+AN22/AN$16 -> 0.075059481 | AO23: =+AO22/AO$16 -> 0.073 | AP23: =+AP22/AP$16 -> 0.073 | ... AS23: =+AS22/AS$16 -> 0.07
A24: S&M | B24: 503.8 | C24: 434.3 | D24: 527.5 | E24: 762.5 | F24: 512.5 | G24: 603.9 | H24: 635.9 | I24: 792 | J24: 555.9 | K24: 574.9 | L24: 567.9 | M24: 831.6 | N24: 555.3 | O24: 627 | P24: 558 | Q24: 916 | R24: 654 | S24: 688 | T24: 642 | U24: 976 | V24: 644 | W24: 713 | X24: 786 | Y24: 1113.376 | Z24: 842.217 | AA24: 823.838 | AB24: =X24*1.13 -> 888.18 | AC24: =Y24*1.13 -> 1258.1149 | AI24: 2228.362 | AJ24: 2545.146 | AK24: 2530.502 | AL24: 2657.883 | AM24: 2917.554 | AN24: 3301.306 | AO24: =+AO16*0.07 -> 3596.0911 | AP24: =+AP16*0.07 -> 4088.7556 | AQ24: =+AQ16*0.067 -> 4422.2812 | AR24: =+AR16*0.067 -> 4997.1778 | AS24: =+AS16*0.065 -> 5429.7693
B25: =+B24/B$16 -> 0.087350024 | C25: =+C24/C$16 -> 0.070638561 | D25: =+D24/D$16 -> 0.081965939 | E25: =+E24/E$16 -> 0.11475829 | F25: =+F24/F$16 -> 0.071546236 | G25: =+G24/G$16 -> 0.082255291 | H25: =+H24/H$16 -> 0.084974744 | I25: =+I24/I$16 -> 0.10273306 | ... AC25: =+AC24/AC$16 -> 0.090391177 | AI25: =+AI24/AI$16 -> 0.089148544 | AJ25: =+AJ24/AJ$16 -> 0.085701373 | AK25: =+AK24/AK$16 -> 0.080039791 | AL25: =+AL24/AL$16 -> 0.078814447 | AM25: =+AM24/AM$16 -> 0.074807166 | AN25: =+AN24/AN$16 -> 0.073065709 | AO25: =+AO24/AO$16 -> 0.07 | AP25: =+AP24/AP$16 -> 0.07 | ... AS25: =+AS24/AS$16 -> 0.065
A26: G&A | B26: 252 | C26: 277.2 | D26: 271.6 | E26: 275.5 | F26: 297.1 | G26: 334.8 | H26: 321.7 | I26: 397.7 | J26: 397.9 | K26: 409.2 | L26: 373 | M26: 392.4 | N26: 400.9 | O26: 401 | P26: 478 | Q26: 429 | R26: 404 | S26: 426 | T26: 417 | U26: 453 | V26: 421 | W26: 441 | X26: 457 | Y26: 567.802 | Z26: 602.609 | AA26: 498.85 | AB26: =X26*1.13 -> 516.41 | AC26: =Y26*1.13 -> 641.61626 | AI26: 1076.486 | AJ26: 1351.621 | AK26: 1572.891 | AL26: 1720.285 | AM26: 1702.039 | AN26: 1888.408 | AO26: =+AO16*0.042 -> 2157.6547 | AP26: =+AP16*0.042 -> 2453.2533 | AQ26: =+AQ16*0.04 -> 2640.1679 | AR26: =+AR16*0.04 -> 2983.3897 | AS26: =+AS16*0.04 -> 3341.3965
B27: =+B26/B$16 -> 0.04369235 | C27: =+C26/C$16 -> 0.045086367 | D27: =+D26/D$16 -> 0.042202747 | E27: =+E26/E$16 -> 0.041463488 | F27: =+F26/F$16 -> 0.041475877 | G27: =+G26/G$16 -> 0.045602039 | H27: =+H26/H$16 -> 0.042988481 | I27: =+I26/I$16 -> 0.051587044 | ... AC27: =+AC26/AC$16 -> 0.046097896 | AI27: =+AI26/AI$16 -> 0.043066234 | AJ27: =+AJ26/AJ$16 -> 0.045512428 | AK27: =+AK26/AK$16 -> 0.04975055 | AL27: =+AL26/AL$16 -> 0.051011768 | AM27: =+AM26/AM$16 -> 0.043640911 | AN27: =+AN26/AN$16 -> 0.041794935 | AO27: =+AO26/AO$16 -> 0.042 | AP27: =+AP26/AP$16 -> 0.042 | ... AS27: =+AS26/AS$16 -> 0.04
A28: OpEx | B28: =SUM(B22:B26) -> 1209.766 | C28: =SUM(C22:C26) -> 1146.6414 | D28: =SUM(D22:D26) -> 1253.0525 | E28: =SUM(E22:E26) -> 1525.088 | F28: =SUM(F22:F26) -> 1334.9449 | G28: =SUM(G22:G26) -> 1476.1554 | H28: =SUM(H22:H26) -> 1521.5603 | I28: =SUM(I22:I26) -> 1836.8867 | ... AC28: =SUM(AC22:AC26) -> 2905.9328 | AI28: =SUM(AI22:AI26) -> 5134.6103 | AJ28: =SUM(AJ22:AJ26) -> 6170.8143 | AK28: =SUM(AK22:AK26) -> 6814.5998 | AL28: =SUM(AL22:AL26) -> 7054.0842 | AM28: =SUM(AM22:AM26) -> 7545.0378 | AN28: =SUM(AN22:AN26) -> 8581.2521 | AO28: =SUM(AO22:AO26) -> 9504.098 | AP28: =SUM(AP22:AP26) -> 10806.14 | ... AS28: =SUM(AS22:AS26) -> 14618.745
B29: =+B28/B$16 -> 0.20975207 | C29: =+C28/C$16 -> 0.18650034 | D29: =+D28/D$16 -> 0.1947064 | E29: =+E28/E$16 -> 0.22952984 | F29: =+F28/F$16 -> 0.18636152 | G29: =+G28/G$16 -> 0.20106242 | H29: =+H28/H$16 -> 0.20332473 | I29: =+I28/I$16 -> 0.23826893 | ... AC29: =+AC28/AC$16 -> 0.20878116 | AI29: =+AI28/AI$16 -> 0.20541682 | AJ29: =+AJ28/AJ$16 -> 0.20778661 | AK29: =+AK28/AK$16 -> 0.21554582 | AL29: =+AL28/AL$16 -> 0.2091754 | AM29: =+AM28/AM$16 -> 0.19345757 | AN29: =+AN28/AN$16 -> 0.1899234 | AO29: =+AO28/AO$16 -> 0.18500278 | AP29: =+AP28/AP$16 -> 0.18500245 | ... AS29: =+AS28/AS$16 -> 0.17500162
A30: EBIT | B30: =B20-B28 -> 958.13397 | C30: =C20-C28 -> 1357.8586 | D30: =D20-D28 -> 1314.8475 | E30: =E20-E28 -> 954.21196 | F30: =F20-F28 -> 1959.7551 | G30: =G20-G28 -> 1847.6216 | H30: =H20-H28 -> 1755.3397 | I30: =I20-I28 -> 632.91334 | ... AC30: =AC20-AC28 -> 4192.532 | AI30: =AI20-AI28 -> 4585.1267 | AJ30: =AJ20-AJ28 -> 6194.3467 | AK30: =AK20-AK28 -> 5632.6652 | AL30: =AL20-AL28 -> 6953.8448 | AM30: =AM20-AM28 -> 10417.494 | AN30: =AN20-AN28 -> 13326.119 | AO30: =AO20-AO28 -> 16182.267 | AP30: =AP20-AP28 -> 19275.419 | ... AS30: =AS20-AS28 -> 29654.759
B31: =+B30/B$16 -> 0.16612351 | C31: =+C30/C$16 -> 0.22085466 | D31: =+D30/D$16 -> 0.20430846 | E31: =+E30/E$16 -> 0.14361146 | F31: =+F30/F$16 -> 0.27358654 | G31: =+G30/G$16 -> 0.25165863 | H31: =+H30/H$16 -> 0.23456446 | I31: =+I30/I$16 -> 0.082097381 | ... AC31: =+AC30/AC$16 -> 0.30121884 | AI31: =+AI30/AI$16 -> 0.183434 | AJ31: =+AJ30/AJ$16 -> 0.208579 | AK31: =+AK30/AK$16 -> 0.17816123 | AL31: =+AL30/AL$16 -> 0.20620299 | AM31: =+AM30/AM$16 -> 0.26710841 | AN31: =+AN30/AN$16 -> 0.29493852 | AO31: =+AO30/AO$16 -> 0.31499722 | AP31: =+AP30/AP$16 -> 0.32999755 | ... AS31: =+AS30/AS$16 -> 0.35499838
A32: Interest Exp | B32: -184 | C32: -189.1 | D32: -197 | E32: -197.1 | F32: -194.4 | G32: -191.3 | H32: -190 | I32: -189.4 | J32: -187.5 | K32: -175.4 | L32: -187.5 | M32: -170.6 | N32: -174.2 | O32: -174.8 | P32: -175.5 | Q32: -175.2 | R32: -173.3 | S32: -167.9 | T32: -184.8 | U32: -192.6 | V32: -184.1 | W32: -182.6 | X32: -175 | Y32: -234.395 | Z32: -262.077 | AA32: -175.685 | AB32: -175 | AC32: -234.3 | AI32: -767.499 | AJ32: -765.62 | AK32: -706.212 | AL32: -699.826 | AM32: -718.733 | AN32: -776.51 | AO32: =SUM(Z32:AC32) -> -847.062 | AP32: =AO32*1.02 -> -864.00324 | AQ32: =AP32*1.02 -> -881.2833 | AR32: =AQ32*1.02 -> -898.90897 | AS32: =AR32*1.02 -> -916.88715
B33: =+B32/B$16 -> -0.031902351 | C33: =+C32/C$16 -> -0.03075697 | D33: =+D32/D$16 -> -0.030610976 | E33: =+E32/E$16 -> -0.029664078 | F33: =+F32/F$16 -> -0.027138709 | G33: =+G32/G$16 -> -0.026056362 | H33: =+H32/H$16 -> -0.025389529 | I33: =+I32/I$16 -> -0.02456773 | ... AC33: =+AC32/AC$16 -> -0.01683364 | AI33: =+AI32/AI$16 -> -0.030704804 | AJ33: =+AJ32/AJ$16 -> -0.025780323 | AK33: =+AK32/AK$16 -> -0.022337489 | AL33: =+AL32/AL$16 -> -0.020752004 | AM33: =+AM32/AM$16 -> -0.018428581 | AN33: =+AN32/AN$16 -> -0.017186003 | AO33: =+AO32/AO$16 -> -0.016488553 | AP33: =+AP32/AP$16 -> -0.014791842 | ... AS33: =+AS32/AS$16 -> -0.010976095
A34: Other Income | B34: 21.6 | C34: -133.1 | D34: -256.3 | E34: -250.6 | F34: 269 | G34: -62.5 | H34: 96.1 | I34: 108.5 | J34: 195.6 | K34: 220.2 | L34: 195 | M34: -339.9 | N34: -71 | O34: 26.9 | P34: 168.2 | Q34: -172.7 | R34: 155.3 | S34: 79 | T34: -21.6 | U34: 54.1 | V34: 50 | W34: 39.6 | X34: 36.4 | Y34: 45.473 | Z34: 2852.166 | AA34: 51.661 | AB34: =AA34 -> 51.661 | AC34: =AB34 -> 51.661 | AI34: -618.441 | AJ34: 411.214 | AK34: 337.31 | AL34: -48.772 | AM34: 266.776 | AN34: 172.459 | AO34: =+AO16*0.003 -> 154.11819 | AP34: =+AP16*0.003 -> 175.23238 | AQ34: =+AQ16*0.003 -> 198.01259 | AR34: =+AR16*0.003 -> 223.75423 | AS34: =+AS16*0.003 -> 250.60474
B35: =+B34/B$16 -> 0.0037450586 | C35: =+C34/C$16 -> -0.021648613 | D35: =+D34/D$16 -> -0.039825347 | E35: =+E34/E$16 -> -0.037715971 | F35: =+F34/F$16 -> 0.037553049 | G35: =+G34/G$16 -> -0.0085129254 | H35: =+H34/H$16 -> 0.012841756 | I35: =+I34/I$16 -> 0.014073911 | ... AC35: =+AC34/AC$16 -> 0.0037116631 | AI35: =+AI34/AI$16 -> -0.024741543 | AJ35: =+AJ34/AJ$16 -> 0.013846594 | AK35: =+AK34/AK$16 -> 0.010669117 | AL35: =+AL34/AL$16 -> -0.0014462406 | AM35: =+AM34/AM$16 -> 0.0068402356 | AN35: =+AN34/AN$16 -> 0.0038169255 | AO35: =+AO34/AO$16 -> 0.003 | AP35: =+AP34/AP$16 -> 0.003 | ... AS35: =+AS34/AS$16 -> 0.003
A36: EBT | B36: =B30+B32+B34 -> 795.73397 | C36: =C30+C32+C34 -> 1035.6586 | D36: =D30+D32+D34 -> 861.54752 | E36: =E30+E32+E34 -> 506.51196 | F36: =F30+F32+F34 -> 2034.3551 | G36: =G30+G32+G34 -> 1593.8216 | H36: =H30+H32+H34 -> 1661.4397 | I36: =I30+I32+I34 -> 552.01334 | ... AC36: =AC30+AC32+AC34 -> 4009.893 | AI36: =AI30+AI32+AI34 -> 3199.1867 | AJ36: =AJ30+AJ32+AJ34 -> 5839.9407 | AK36: =AK30+AK32+AK34 -> 5263.7632 | AL36: =AL30+AL32+AL34 -> 6205.2468 | AM36: =AM30+AM32+AM34 -> 9965.5372 | AN36: =AN30+AN32+AN34 -> 12722.068 | AO36: =AO30+AO32+AO34 -> 15489.323 | AP36: =AP30+AP32+AP34 -> 18586.648 | ... AS36: =AS30+AS32+AS34 -> 28988.476
B37: =+B36/B$16 -> 0.13796622 | C37: =+C36/C$16 -> 0.16844908 | D37: =+D36/D$16 -> 0.13387214 | E37: =+E36/E$16 -> 0.076231407 | F37: =+F36/F$16 -> 0.28400088 | G37: =+G36/G$16 -> 0.21708935 | H37: =+H36/H$16 -> 0.22201669 | I37: =+I36/I$16 -> 0.071603562 | ... AC37: =+AC36/AC$16 -> 0.28809686 | AI37: =+AI36/AI$16 -> 0.12798766 | AJ37: =+AJ36/AJ$16 -> 0.19664528 | AK37: =+AK36/AK$16 -> 0.16649286 | AL37: =+AL36/AL$16 -> 0.18400475 | AM37: =+AM36/AM$16 -> 0.25552007 | AN37: =+AN36/AN$16 -> 0.28156945 | AO37: =+AO36/AO$16 -> 0.30150866 | AP37: =+AP36/AP$16 -> 0.31820571 | ... AS37: =+AS36/AS$16 -> 0.34702229
A38: Taxes | B38: 86.8 | C38: 315.4 | D38: 71.4 | E38: -35.7 | F38: 327.7 | G38: 240.7 | H38: 211.8 | I38: -56.5 | J38: 382.2 | K38: 182.1 | L38: 223.6 | M38: -15.9 | N38: 163.7 | O38: 191.7 | P38: 191.7 | Q38: 210.3 | R38: 282 | S38: 323 | T38: 339 | U38: 265.6 | V38: 366 | W38: 506 | X38: 562.4 | Y38: 349.22 | Z38: 1264.295 | AA38: 667.172 | AB38: =AB36*X52 -> 775.11269 | AC38: =AC36*Y52 -> 505.99039 | AI38: 437.954 | AJ38: 723.875 | AK38: 772.005 | AL38: 797.415 | AM38: 1254.026 | AN38: 1741.351 | AO38: =AO36*0.15 -> 2323.3985 | AP38: =AP36*0.15 -> 2787.9972 | AQ38: =AQ36*0.15 -> 3263.7024 | AR38: =AR36*0.15 -> 3758.4662 | AS38: =AS36*0.15 -> 4348.2714
B39: =+B38/B$16 -> 0.015049587 | C39: =+C38/C$16 -> 0.051299567 | D39: =+D38/D$16 -> 0.011094537 | E39: =+E38/E$16 -> -0.0053729456 | F39: =+F38/F$16 -> 0.045747711 | G39: =+G38/G$16 -> 0.032784978 | H39: =+H38/H$16 -> 0.028302643 | I39: =+I38/I$16 -> -0.0073288107 | ... AC39: =+AC38/AC$16 -> 0.036353649 | AI39: =+AI38/AI$16 -> 0.017520924 | AJ39: =+AJ38/AJ$16 -> 0.024374665 | AK39: =+AK38/AK$16 -> 0.024418522 | AL39: =+AL38/AL$16 -> 0.02364582 | AM39: =+AM38/AM$16 -> 0.032153692 | AN39: =+AN38/AN$16 -> 0.038540216 | AO39: =+AO38/AO$16 -> 0.045226299 | AP39: =+AP38/AP$16 -> 0.047730856 | ... AS39: =+AS38/AS$16 -> 0.052053343
A40: Net Inc | B40: =B36-B38 -> 708.93397 | C40: =C36-C38 -> 720.25861 | D40: =D36-D38 -> 790.14752 | E40: =E36-E38 -> 542.21196 | F40: =F36-F38 -> 1706.6551 | G40: =G36-G38 -> 1353.1216 | H40: =H36-H38 -> 1449.6397 | I40: =I36-I38 -> 608.51334 | ... AC40: =AC36-AC38 -> 3503.9026 | AI40: =AI36-AI38 -> 2761.2327 | AJ40: =AJ36-AJ38 -> 5116.0657 | AK40: =AK36-AK38 -> 4491.7582 | AL40: =AL36-AL38 -> 5407.8318 | AM40: =AM36-AM38 -> 8711.5112 | AN40: =AN36-AN38 -> 10980.717 | AO40: =AO36-AO38 -> 13165.925 | AP40: =AP36-AP38 -> 15798.651 | ... AS40: =AS36-AS38 -> 24640.205 | AT40: =AS40*(1+$AX$49) -> 25133.009 | AU40: =AT40*(1+$AX$49) -> 25635.669 | AV40: =AU40*(1+$AX$49) -> 26148.383 | AW40: =AV40*(1+$AX$49) -> 26671.35 | AX40: =AW40*(1+$AX$49) -> 27204.777 | AY40: =AX40*(1+$AX$49) -> 27748.873 | AZ40: =AY40*(1+$AX$49) -> 28303.85 | BA40: =AZ40*(1+$AX$49) -> 28869.927 | ... DH40: =DG40*(1+$AX$49) -> 92865.804
B41: =+B40/B$16 -> 0.12291663 | C41: =+C40/C$16 -> 0.11714951 | D41: =+D40/D$16 -> 0.1227776 | E41: =+E40/E$16 -> 0.081604353 | F41: =+F40/F$16 -> 0.23825317 | G41: =+G40/G$16 -> 0.18430437 | H41: =+H40/H$16 -> 0.19371405 | I41: =+I40/I$16 -> 0.078932373 | ... AC41: =+AC40/AC$16 -> 0.25174321 | AI41: =+AI40/AI$16 -> 0.11046673 | AJ41: =+AJ40/AJ$16 -> 0.17227061 | AK41: =+AK40/AK$16 -> 0.14207433 | AL41: =+AL40/AL$16 -> 0.16035893 | AM41: =+AM40/AM$16 -> 0.22336638 | AN41: =+AN40/AN$16 -> 0.24302923 | AO41: =+AO40/AO$16 -> 0.25628236 | AP41: =+AP40/AP$16 -> 0.27047485 | ... AS41: =+AS40/AS$16 -> 0.29496895
A42: EPS | B42: =B40/B44 -> 1.5670512 | C42: =C40/C44 -> 1.5868222 | D42: =D40/D44 -> 1.736588 | E42: =E40/E44 -> 1.1916746 | F42: =F40/F44 -> 3.7459507 | G42: =G40/G44 -> 2.9732401 | H42: =H40/H44 -> 3.1867217 | I42: =I40/I44 -> 1.3353376 | ... AC42: =AC40/AC44 -> 0.83895667 | AI42: =AI40/AI44 -> 6.0792251 | AJ42: =AJ40/AJ44 -> 11.234915 | AK42: =AK40/AK44 -> 9.9531525 | AL42: =AL40/AL44 -> 12.030825 | AM42: =AM40/AM44 -> 1.9832207 | AN42: =AN40/AN44 -> 2.5278691 | AO42: =AO40/AO44 -> 3.0615408 | AP42: =AP40/AP44 -> 3.7108508 | ... AS42: =AS40/AS44 -> 5.9647497
F43: =+F42/B42-1 -> 1.3904456 | G43: =+G42/C42-1 -> 0.8737071 | H43: =+H42/D42-1 -> 0.83504766 | I43: =+I42/E42-1 -> 0.12055552 | J43: =+J42/F42-1 -> -0.058410194 | K43: =+K42/G42-1 -> 0.076728682 | L43: =+L42/H42-1 -> -0.082116812 | M43: =+M42/I42-1 -> -0.90828402 | ... AC43: =+AC42/Y42-1 -> 0.49769289 | AJ43: =+AJ42/AI42-1 -> 0.84808342 | AK43: =+AK42/AJ42-1 -> -0.11408742 | AL43: =+AL42/AK42-1 -> 0.20874518 | AM43: =+AM42/AL42-1 -> -0.83515505 | AN43: =+AN42/AM42-1 -> 0.2746282 | AO43: =+AO42/AN42-1 -> 0.21111526 | AP43: =+AP42/AO42-1 -> 0.21208602 | AQ43: =+AQ42/AP42-1 -> 0.18245065 | ... AS43: =+AS42/AR42-1 -> 0.16861324
A44: Shares | B44: 452.4 | C44: 453.9 | D44: 455 | E44: 455 | F44: 455.6 | G44: 455.1 | H44: 454.9 | I44: 455.7 | J44: 452.9 | K44: 450.1 | L44: 450.3 | M44: 451.6 | N44: 452.4 | O44: 451.5 | P44: 450 | Q44: 444.2 | R44: 441.6 | S44: 439.7 | T44: 437.9 | U44: 437.8 | V44: 436.9 | W44: 434.9 | X44: 434 | Y44: =4317.1 -> 4317.1 | Z44: 4298.437 | AA44: 4261.3 | AB44: =+AA44*0.99 -> 4218.687 | AC44: =+AB44*0.99 -> 4176.5001 | AI44: 454.208 | AJ44: 455.372 | AK44: 451.29 | AL44: 449.498 | AM44: 4392.608 | AN44: 4343.863 | AO44: =+AN44*0.99 -> 4300.4244 | AP44: =+AO44*0.99 -> 4257.4201 | AQ44: =+AP44*0.99 -> 4214.8459 | AR44: =+AQ44*0.99 -> 4172.6975 | AS44: =+AR44*0.99 -> 4130.9705
F45: =+F44/E44-1 -> 0.0013186813 | G45: =+G44/F44-1 -> -0.0010974539 | H45: =+H44/G44-1 -> -0.00043946385 | I45: =+I44/H44-1 -> 0.0017586283 | J45: =+J44/I44-1 -> -0.0061443932 | K45: =+K44/J44-1 -> -0.0061823802 | L45: =+L44/K44-1 -> 0.0004443457 | M45: =+M44/L44-1 -> 0.0028869642 | ... AC45: =+AC44/AB44-1 -> -0.01 | AJ45: =+AJ44/AI44-1 -> 0.0025627026 | AK45: =+AK44/AJ44-1 -> -0.0089640997 | AL45: =+AL44/AK44-1 -> -0.0039708391 | AM45: =+AM44/AL44-1 -> 8.7722526 | AN45: =+AN44/AM44-1 -> -0.011097052 | AO45: =+AO44/AN44-1 -> -0.01 | AP45: =+AP44/AO44-1 -> -0.01 | AQ45: =+AQ44/AP44-1 -> -0.01 | ... AS45: =+AS44/AR44-1 -> -0.01
BC47: Gordon Growth Model
A48: Gross Margin | B48: =+B20/B16 -> 0.37587558 | C48: =+C20/C16 -> 0.407355 | D48: =+D20/D16 -> 0.39901485 | E48: =+E20/E16 -> 0.37314129 | F48: =+F20/F16 -> 0.45994807 | G48: =+G20/G16 -> 0.45272105 | H48: =+H20/H16 -> 0.43788919 | I48: =+I20/I16 -> 0.32036631 | ... AC48: =+AC20/AC16 -> 0.51 | AI48: =+AI20/AI16 -> 0.38885083 | AJ48: =+AJ20/AJ16 -> 0.41636561 | AK48: =+AK20/AK16 -> 0.39370705 | AL48: =+AL20/AL16 -> 0.4153784 | AM48: =+AM20/AM16 -> 0.46056598 | AN48: =+AN20/AN16 -> 0.48486193 | AO48: =+AO20/AO16 -> 0.5 | AP48: =+AP20/AP16 -> 0.515 | ... AS48: =+AS20/AS16 -> 0.53 | AW48: ROIC | AX48: 0.02 | AZ48: EV | BA48: =Main!G6 -> 329968.29 | BC48: Payout Ratio | BD48: =+(SUM(X156:AA156)-SUM(X153:AA153))/SUM(X40:AA40) -> 0.70806562 | BF48: Ev | BG48: =+BD50 -> 394524.41
A49: OP Margin | B49: =+B30/B16 -> 0.16612351 | C49: =+C30/C16 -> 0.22085466 | D49: =+D30/D16 -> 0.20430846 | E49: =+E30/E16 -> 0.14361146 | F49: =+F30/F16 -> 0.27358654 | G49: =+G30/G16 -> 0.25165863 | H49: =+H30/H16 -> 0.23456446 | I49: =+I30/I16 -> 0.082097381 | ... AC49: =+AC30/AC16 -> 0.30121884 | AI49: =+AI30/AI16 -> 0.183434 | AJ49: =+AJ30/AJ16 -> 0.208579 | AK49: =+AK30/AK16 -> 0.17816123 | AL49: =+AL30/AL16 -> 0.20620299 | AM49: =+AM30/AM16 -> 0.26710841 | AN49: =+AN30/AN16 -> 0.29493852 | AO49: =+AO30/AO16 -> 0.31499722 | AP49: =+AP30/AP16 -> 0.32999755 | ... AS49: =+AS30/AS16 -> 0.35499838 | AW49: Terminal | AX49: 0.02 | AZ49: 2026 E | BA49: =AO40 -> 13165.925 | BC49: Sustained Growth | BD49: =+(1-BD48)*AN63 -> 0.1248327 | BF49: Share | BG49: =+Main!G2 -> 4163.9397
A50: NI Margin | B50: =+B40/B16 -> 0.12291663 | C50: =+C40/C16 -> 0.11714951 | D50: =+D40/D16 -> 0.1227776 | E50: =+E40/E16 -> 0.081604353 | F50: =+F40/F16 -> 0.23825317 | G50: =+G40/G16 -> 0.18430437 | H50: =+H40/H16 -> 0.19371405 | I50: =+I40/I16 -> 0.078932373 | ... AC50: =+AC40/AC16 -> 0.25174321 | AI50: =+AI40/AI16 -> 0.11046673 | AJ50: =+AJ40/AJ16 -> 0.17227061 | AK50: =+AK40/AK16 -> 0.14207433 | AL50: =+AL40/AL16 -> 0.16035893 | AM50: =+AM40/AM16 -> 0.22336638 | AN50: =+AN40/AN16 -> 0.24302923 | AO50: =+AO40/AO16 -> 0.25628236 | AP50: =+AP40/AP16 -> 0.27047485 | ... AS50: =+AS40/AS16 -> 0.29496895 | AW50: Discount | AX50: =+Main!E9 -> 0.12117122 | AZ50: EV/E | BA50: =BA48/BA49 -> 25.062296 | BC50: Equity Value | BD50: =+SUM(X160:AA160)/(Main!B10-0.1) -> 394524.41 | BF50: Price | BG50: =+BG48/BG49 -> 94.747868
A51: Rule of 40 | F51: =+F49+F17 -> 0.51555894 | G51: =+G49+G17 -> 0.44579301 | H51: =+H49+H17 -> 0.39737756 | I51: =+I49+I17 -> 0.24236768 | J51: =+J49+J17 -> 0.34893721 | K51: =+K49+K17 -> 0.28359057 | L51: =+L49+L17 -> 0.25247998 | M51: =+M49+M17 -> 0.088544276 | ... AC51: =+AC49+AC17 -> 0.45621884 | AJ51: =+AJ49+AJ17 -> 0.3966802 | AK51: =+AK49+AK17 -> 0.24273514 | AL51: =+AL49+AL17 -> 0.27287104 | AM51: =+AM49+AM17 -> 0.4236085 | AN51: =+AN49+AN17 -> 0.45343971 | AO51: =+AO49+AO17 -> 0.45199722 | AP51: =+AP49+AP17 -> 0.46699755 | AQ51: =+AQ49+AQ17 -> 0.46999788 | ... AS51: =+AS49+AS17 -> 0.47499838 | AW51: NPV | AX51: =NPV(AX50,AO40:DH40)+(Main!G4)-(Main!G5) -> 199617.82 | BC51: Just P/E | BD51: =+BD48*(1+0.1)/(Main!B10-0.1) -> 31.790701 | BG51: =+BG50/Main!G1-1 -> 0.21471626
A52: Tax Rate | B52: =+B38/B36 -> 0.10908168 | C52: =+C38/C36 -> 0.30454051 | D52: =+D38/D36 -> 0.082874129 | E52: =+E38/E36 -> -0.070482047 | F52: =+F38/F36 -> 0.16108299 | G52: =+G38/G36 -> 0.15102067 | H52: =+H38/H36 -> 0.1274798 | I52: =+I38/I36 -> -0.1023526 | ... AC52: =+AC38/AC36 -> 0.12618551 | AI52: =+AI38/AI36 -> 0.13689542 | AJ52: =+AJ38/AJ36 -> 0.12395246 | AK52: =+AK38/AK36 -> 0.14666408 | AL52: =+AL38/AL36 -> 0.12850657 | AM52: =+AM38/AM36 -> 0.12583627 | AN52: =+AN38/AN36 -> 0.13687641 | AO52: =+AO38/AO36 -> 0.15 | AP52: =+AP38/AP36 -> 0.15 | ... AS52: =+AS38/AS36 -> 0.15 | AW52: Share | AX52: =AX51/Main!G2 -> 47.939653
AW53: Diff | AX53: =AX52/Main!G1-1 -> -0.38538907 | AZ53: yield | BA53: =BA49/BA48 -> 0.039900575 | BC53: Debt-to-EBITDA | BD53: =+(-AA80-AA81+AA96+AA97)/SUM(X58:AA58) -> 0.35180793
AZ54: AVG bond yield | BA54: 0.04722 | BC54: Dividend Yield | BD54: 0
A55: New Gross Margin | Z55: =+Z48*(Z16-Y16) -> 103.37388
Z56: =+Y24/(Z55*12) -> 0.89753171
A58: EBITDA | B58: =+B30+B120 -> 986.63397 | C58: =+C30+C120 -> 1384.4586 | D58: =+D30+D120 -> 1343.3475 | E58: =+E30+E120 -> 986.11196 | F58: =+F30+F120 -> 1995.4551 | G58: =+G30+G120 -> 1886.0216 | H58: =+H30+H120 -> 1825.5397 | I58: =+I30+I120 -> 696.81334 | ... AC58: =+AC30+AC120 -> 4282.727 | AI58: =AI30+AI120 -> 4700.6267 | AJ58: =AJ30+AJ120 -> 6402.5467 | AK58: =AK30+AK120 -> 5969.1652 | AL58: =AL30+AL120 -> 7310.5448 | AM58: =AM30+AM120 -> 10745.394 | AN58: =AN30+AN120 -> 13659.319 | AO58: =AO30+AO120 -> 20035.222 | AP58: =AP30+AP120 -> 23656.229 | ... AS58: =AS30+AS120 -> 35919.877
F59: =+F58/B58-1 -> 1.0224878 | G59: =+G58/C58-1 -> 0.36228093 | H59: =+H58/D58-1 -> 0.35894819 | I59: =+I58/E58-1 -> -0.29337299 | J59: =+J58/F58-1 -> 0.025403047 | K59: =+K58/G58-1 -> -0.11891891 | L59: =+L58/H58-1 -> -0.11349792 | M59: =+M58/I58-1 -> -0.07692889 | ... AC59: =+AC58/Y58-1 -> 0.40771066 | AJ59: =+AJ58/AI58-1 -> 0.36206238 | AK59: =+AK58/AJ58-1 -> -0.067688927 | AL59: =+AL58/AK58-1 -> 0.22471813 | AM59: =+AM58/AL58-1 -> 0.46984861 | AN59: =+AN58/AM58-1 -> 0.27117895 | AO59: =+AO58/AN58-1 -> 0.46678043 | AP59: =+AP58/AO58-1 -> 0.18073206 | AQ59: =+AQ58/AP58-1 -> 0.15790232 | ... AS59: =+AS58/AR58-1 -> 0.14666748
A60: Incremental Margin Y/Y | F60: =(F30-B30)/(F16-B16) -> 0.71769932 | G60: =(G30-C30)/(G16-C16) -> 0.4103321 | H60: =(H30-D30)/(H16-D16) -> 0.42039718 | I60: =(I30-E30)/(I16-E16) -> -0.30171717 | J60: =(J30-F30)/(J16-F16) -> 0.016736182 | K60: =(K30-G30)/(K16-G16) -> -0.42880256 | L60: =(L30-H30)/(L16-H16) -> -0.50293244 | M60: =(M30-I30)/(M16-I16) -> -0.58167538 | ... AA60: =(AA30-W30)/(AA16-W16) -> 0.28131016 | AJ60: =(AJ30-AI30)/(AJ16-AI16) -> 0.34225705 | AK60: =(AK30-AJ30)/(AK16-AJ16) -> -0.2928924 | AL60: =(AL30-AK30)/(AL16-AK16) -> 0.62682079 | AM60: =(AM30-AL30)/(AM16-AL16) -> 0.6562802 | AN60: =(AN30-AM30)/(AN16-AM16) -> 0.47052151 | AO60: =(AO30-AN30)/(AO16-AN16) -> 0.46141103 | AP60: =(AP30-AO30)/(AP16-AO16) -> 0.43948905 | AQ60: =(AQ30-AP30)/(AQ16-AP16) -> 0.41692347 | ... AS60: =(AS30-AR30)/(AS16-AR16) -> 0.43833389
A62: ROA | C62: =+SUM(C40)/AVERAGE(B87:C87) -> 0.020269362 | D62: =+SUM(D40)/AVERAGE(C87:D87) -> 0.020848962 | E62: =+SUM(E40)/AVERAGE(D87:E87) -> 0.013920289 | F62: =+SUM(F40)/AVERAGE(E87:F87) -> 0.042987224 | G62: =+SUM(G40)/AVERAGE(F87:G87) -> 0.033371846 | H62: =+SUM(H40)/AVERAGE(G87:H87) -> 0.034634596 | I62: =+SUM(I40)/AVERAGE(H87:I87) -> 0.013936878 | J62: =+SUM(J40)/AVERAGE(I87:J87) -> 0.035532274 | ... AA62: =+SUM(AA40)/AVERAGE(Z87:AA87) -> 0.056941022 | AJ62: =+SUM(AJ40)/AVERAGE(AI87:AJ87) -> 0.12200775 | AK62: =+SUM(AK40)/AVERAGE(AJ87:AK87) -> 0.096411385 | AL62: =+SUM(AL40)/AVERAGE(AK87:AL87) -> 0.11112813 | AM62: =+SUM(AM40)/AVERAGE(AL87:AM87) -> 0.1702113 | AN62: =+SUM(AN40)/AVERAGE(AM87:AN87) -> 0.20106333
A63: ROE | C63: =+C64*C65*C50 -> 0.081182884 | D63: =+D64*D65*D50 -> 0.085319431 | E63: =+E64*E65*E50 -> 0.053545717 | F63: =+F64*F65*F50 -> 0.14252532 | G63: =+G64*G65*G50 -> 0.10118007 | H63: =+H64*H65*H50 -> 0.099366616 | I63: =+I64*I65*I50 -> 0.039052451 | J63: =+J64*J65*J50 -> 0.095674341 | ... AA63: =+AA64*AA65*AA50 -> 0.11101025 | AJ63: =+AJ64*AJ65*AJ50 -> 0.38017453 | AK63: =+AK64*AK65*AK50 -> 0.24527234 | AL63: =+AL64*AL65*AL50 -> 0.26146517 | AM63: =+AM64*AM65*AM50 -> 0.38434522 | AN63: =+AN64*AN65*AN50 -> 0.42760535
A64: A. Turnover | C64: =+SUM(C16)/AVERAGE(B87:C87) -> 0.17302132 | D64: =+SUM(D16)/AVERAGE(C87:D87) -> 0.1698108 | E64: =+SUM(E16)/AVERAGE(D87:E87) -> 0.17058268 | F64: =+SUM(F16)/AVERAGE(E87:F87) -> 0.18042666 | G64: =+SUM(G16)/AVERAGE(F87:G87) -> 0.18106921 | H64: =+SUM(H16)/AVERAGE(G87:H87) -> 0.17879239 | I64: =+SUM(I16)/AVERAGE(H87:I87) -> 0.17656732 | J64: =+SUM(J16)/AVERAGE(I87:J87) -> 0.17500267 | ... AA64: =+SUM(AA16)/AVERAGE(Z87:AA87) -> 0.21026737 | AJ64: =+SUM(AJ16)/AVERAGE(AI87:AJ87) -> 0.70823313 | AK64: =+SUM(AK16)/AVERAGE(AJ87:AK87) -> 0.67859818 | AL64: =+SUM(AL16)/AVERAGE(AK87:AL87) -> 0.69299617 | AM64: =+SUM(AM16)/AVERAGE(AL87:AM87) -> 0.76202739 | AN64: =+SUM(AN16)/AVERAGE(AM87:AN87) -> 0.82732159
A65: Financial Leverage | C65: =+AVERAGE(B87:C87)/AVERAGE(B105:C105) -> 4.0052017 | D65: =+AVERAGE(C87:D87)/AVERAGE(C105:D105) -> 4.0922628 | E65: =+AVERAGE(D87:E87)/AVERAGE(D105:E105) -> 3.8465952 | F65: =+AVERAGE(E87:F87)/AVERAGE(E105:F105) -> 3.3155273 | G65: =+AVERAGE(F87:G87)/AVERAGE(F105:G105) -> 3.0318991 | H65: =+AVERAGE(G87:H87)/AVERAGE(G105:H105) -> 2.8689988 | I65: =+AVERAGE(H87:I87)/AVERAGE(H105:I105) -> 2.8020947 | J65: =+AVERAGE(I87:J87)/AVERAGE(I105:J105) -> 2.6926039 | ... AA65: =+AVERAGE(Z87:AA87)/AVERAGE(Z105:AA105) -> 1.9495655 | AJ65: =+AVERAGE(AI87:AJ87)/AVERAGE(AI105:AJ105) -> 3.1159867 | AK65: =+AVERAGE(AJ87:AK87)/AVERAGE(AJ105:AK105) -> 2.5440184 | AL65: =+AVERAGE(AK87:AL87)/AVERAGE(AK105:AL105) -> 2.3528263 | AM65: =+AVERAGE(AL87:AM87)/AVERAGE(AL105:AM105) -> 2.2580477 | AN65: =+AVERAGE(AM87:AN87)/AVERAGE(AM105:AN105) -> 2.1267197
A66: Financial Leverage % | C66: =+C63-C62 -> 0.060913522 | D66: =+D63-D62 -> 0.064470469 | E66: =+E63-E62 -> 0.039625428 | F66: =+F63-F62 -> 0.099538091 | G66: =+G63-G62 -> 0.067808225 | H66: =+H63-H62 -> 0.06473202 | I66: =+I63-I62 -> 0.025115574 | J66: =+J63-J62 -> 0.060142067 | ... AA66: =+AA63-AA62 -> 0.054069231 | AJ66: =+AJ63-AJ62 -> 0.25816678 | AK66: =+AK63-AK62 -> 0.14886096 | AL66: =+AL63-AL62 -> 0.15033705 | AM66: =+AM63-AM62 -> 0.21413393 | AN66: =+AN63-AN62 -> 0.22654202
AZ68: Ev | BA68: =+AX71 -> 258419.47
A69: NOPAT | B69: =B30*(1-B52) -> 853.6191 | C69: =C30*(1-C52) -> 944.33566 | D69: =D30*(1-D52) -> 1205.8807 | E69: =E30*(1-E52) -> 1021.4668 | F69: =F30*(1-F52) -> 1644.0719 | G69: =G30*(1-G52) -> 1568.5925 | H69: =H30*(1-H52) -> 1531.5693 | I69: =I30*(1-I52) -> 697.69367 | ... AC69: =AC30*(1-AC52) -> 3663.4952 | AI69: =AI30*(1-AI52) -> 3957.4438 | AJ69: =AJ30*(1-AJ52) -> 5426.5422 | AK69: =AK30*(1-AK52) -> 4806.5555 | AL69: =AL30*(1-AL52) -> 6060.2301 | AM69: =AM30*(1-AM52) -> 9106.5956 | AN69: =AN30*(1-AN52) -> 11502.088 | AO69: =AO30*(1-AO52) -> 13754.927 | AP69: =AP30*(1-AP52) -> 16384.106 | ... AS69: =AS30*(1-AS52) -> 25206.545 | AW69: Terminal | AX69: 0.02 | AZ69: Debt (-) | BA69: =+Main!G5 -> 14309
A70: Invested Capital | AI70: =(AI87-AI80)-(AI100-0) -> 2859.934 | AJ70: =(AJ87-AJ80)-(AJ100-0) -> 9821.4659 | AK70: =(AK87-AK80)-(AK100-0) -> 15630.17 | AL70: =(AL87-AL80)-(AL100-0) -> 13471.141 | AM70: =(AM87-AM80)-(AM100-0) -> 16938.163 | AN70: =(AN87-AN80)-(AN100-0) -> 17581.899 | AW70: Discount | AX70: =+Main!E9 -> 0.12117122 | AZ70: Cash (+) | BA70: =+Main!G4 -> 9128
A71: ROIC | AI71: =AI69/AI70 -> 1.3837536 | AJ71: =AJ69/AJ70 -> 0.55251856 | AK71: =AK69/AK70 -> 0.3075178 | AL71: =AL69/AL70 -> 0.44986761 | AM71: =AM69/AM70 -> 0.53763773 | AN71: =AN69/AN70 -> 0.65420052 | AW71: EV | AX71: =+NPV(AX70,AO74:AS74,AS74+AX72) -> 258419.47 | AZ71: Equity Value | BA71: =+BA68-BA69+BA70 -> 253238.47
A72: A/L | B72: =B87/B100 -> 1.2717475 | C72: =C87/C100 -> 1.3352568 | D72: =D87/D100 -> 1.3652293 | E72: =E87/E100 -> 1.3921511 | F72: =F87/F100 -> 1.4729672 | G72: =G87/G100 -> 1.5114201 | H72: =H87/H100 -> 1.5584043 | I72: =I87/I100 -> 1.551526 | ... AA72: =AA87/AA100 -> 2.0654528 | AI72: =AI87/AI100 -> 1.3921873 | AJ72: =AJ87/AJ100 -> 1.5515621 | AK72: =AK87/AK100 -> 1.7469209 | AL72: =AL87/AL100 -> 1.7315373 | AM72: =AM87/AM100 -> 1.8565484 | AN72: =AN87/AN100 -> 1.9183707 | AW72: TV | AX72: =+AS74*(1+AX69)/(AX70-AX69) -> 316493.76 | AZ72: Share | BA72: =+Main!G2 -> 4163.9397
A73: NWC | B73: =+SUM(B84)-SUM(B89,B91,B92,B94) -> -7224.6 | C73: =+SUM(C84)-SUM(C89,C91,C92,C94) -> -5716.2 | D73: =+SUM(D84)-SUM(D89,D91,D92,D94) -> -6006.1 | E73: =+SUM(E84)-SUM(E89,E91,E92,E94) -> -5749.6 | F73: =+SUM(F84)-SUM(F89,F91,F92,F94) -> -5559 | G73: =+SUM(G84)-SUM(G89,G91,G92,G94) -> -5306.8 | H73: =+SUM(H84)-SUM(H89,H91,H92,H94) -> -5460.5 | I73: =+SUM(I84)-SUM(I89,I91,I92,I94) -> -5746.9 | ... AA73: =+SUM(AA84)-SUM(AA89,AA91,AA92,AA94) -> -4925.747 | AI73: =+SUM(AI84)-SUM(AI89,AI91,AI92,AI94) -> -5749.6 | AJ73: =+SUM(AJ84)-SUM(AJ89,AJ91,AJ92,AJ94) -> -5746.9 | AK73: =+SUM(AK84)-SUM(AK89,AK91,AK92,AK94) -> -4722.8 | AL73: =+SUM(AL84)-SUM(AL89,AL91,AL92,AL94) -> -5680.6 | AM73: =+SUM(AM84)-SUM(AM89,AM91,AM92,AM94) -> -5454.8 | AN73: =+SUM(AN84)-SUM(AN89,AN91,AN92,AN94) -> -6023.9 | AO73: =+SUM(AO84)-SUM(AO89,AO91,AO92,AO94) -> -5652.2372 | AP73: =+SUM(AP84)-SUM(AP89,AP91,AP92,AP94) -> -6430.3123 | ... AS73: =+SUM(AS84)-SUM(AS89,AS91,AS92,AS94) -> -9305.6201 | AW73: Diff | AX73: =+AX71/Main!G6-1 -> -0.21683545 | AZ73: Price | BA73: =+BA71/BA72 -> 60.817037
A74: UFCF | AJ74: =+AJ69+AJ120-AJ133-(AJ73-AI73) -> 5107.6422 | AK74: =+AK69+AK120-AK133-(AK73-AJ73) -> 3554.4555 | AL74: =+AL69+AL120-AL133-(AL73-AK73) -> 7026.3301 | AM74: =+AM69+AM120-AM133-(AM73-AL73) -> 8769.3956 | AN74: =+AN69+AN120-AN133-(AN73-AM73) -> 11716.388 | AO74: =+AO69+AO120-AO133-(AO73-AN73) -> 16479.419 | AP74: =+AP69+AP120-AP133-(AP73-AO73) -> 20710.511 | AQ74: =+AQ69+AQ120-AQ133-(AQ73-AP73) -> 23975.353 | ... AS74: =+AS69+AS120-AS133-(AS73-AR73) -> 31392.216 | BA74: =+BA73/Main!G1-1 -> -0.2202944
A78: Net Cash | B78: =B80+B81-B97 -> -9018.8 | C78: =C80+C81-C97 -> -8141.7 | D78: =D80+D81-D97 -> -7155.3 | E78: =E80+E81-E97 -> -7603.5 | F78: =F80+F81-F97 -> -6456.8 | G78: =G80+G81-G97 -> -7149.3 | H78: =H80+H81-H97 -> -7267 | I78: =I80+I81-I97 -> -8665.2 | ... AC78: =AC80+AC81-AC97 -> -13361.331 | AI78: =AI80+AI81-AI97 -> -7603.5 | AJ78: =AJ80+AJ81-AJ97 -> -8665.2 | AK78: =AK80+AK81-AK97 -> -8294.7 | AL78: =AL80+AL81-AL97 -> -7005.53 | AM78: =AM80+AM81-AM97 -> -4214.6 | AN78: =AN80+AN81-AN97 -> -4401.62 | AO78: =AN78+AO40 -> 8764.3046 | AP78: =AO78+AP40 -> 24562.956 | AQ78: =AP78+AQ40 -> 43057.269 | AR78: =AQ78+AR40 -> 64355.245 | AS78: =AR78+AS40 -> 88995.45
A80: Cash | B80: 5151.8 | C80: 7153.2 | D80: 8392.3 | E80: 8205.5 | F80: 8403.7 | G80: 7777.5 | H80: 7526.6 | I80: 6027.8 | J80: =6008.9 -> 6008.9 | K80: =5819.4 -> 5819.4 | L80: 6113.7 | M80: =5147.1 -> 5147.1 | N80: =6714.5 -> 6714.5 | O80: =7662.7 -> 7662.7 | P80: =7353.2 -> 7353.2 | Q80: =7116.9 -> 7116.9 | R80: =7024.7 -> 7024.7 | S80: =6624.9 -> 6624.9 | T80: =7457 -> 7457 | U80: =7804.7 -> 7804.7 | V80: =7199.8 -> 7199.8 | W80: =8177.4 -> 8177.4 | X80: =9287 -> 9287 | Y80: =9033.68 -> 9033.68 | Z80: 12259.772 | AA80: 9099.232 | AI80: 8205.5 | AJ80: 6027.8 | AK80: =5147.1 -> 5147.1 | AL80: =7116.9 -> 7116.9 | AM80: =7804.7 -> 7804.7 | AN80: =9033.68 -> 9033.68
A81: Short Investments | B81: 0 | C81: 0 | D81: 0 | E81: 0 | F81: 0 | G81: 0 | H81: 0 | I81: 0 | J81: 0 | K81: 0 | L81: 0 | M81: 911.2 | N81: 1112.9 | O81: 914.2 | P81: 514.2 | Q81: 20.97 | R81: 20.9 | S81: 30.9 | T81: 1766.9 | U81: 1779 | V81: 1171.1 | W81: 213 | X81: 37 | Y81: 28.6 | Z81: 28.678 | AA81: 28.678 | AI81: 0 | AJ81: 0 | AK81: 911.2 | AL81: 20.97 | AM81: 1779 | AN81: 28.6
A82: Content Asset | B82: 25266.8 | C82: 25155.1 | D82: 25067.6 | E82: 25383.9 | F82: 26043.9 | G82: 27291.6 | H82: 28974 | I82: 30919.5 | J82: 31191.9 | K82: 32533.1 | L82: 32777.3 | M82: 32736.7 | N82: 32349.1 | O82: 32520.7 | P82: 31749.8 | Q82: 31658 | R82: 31662.1 | S82: 31927.3 | T82: 32175.3 | U82: 32452.4 | V82: 32040.8 | W82: 32089.3 | X82: 32639 | Y82: 32778.3 | Z82: 33376.295 | AA82: 33837.573 | AI82: 25383.9 | AJ82: 30919.5 | AK82: 32736.7 | AL82: 31658 | AM82: 32452.4 | AN82: 32778.3
A83: PP&E | B83: 650.4 | C83: 751.9 | D83: 828.1 | E83: 960.1 | F83: 1015.4 | G83: 1107.4 | H83: 1220.1 | I83: 1323.4 | J83: 1383.7 | K83: 1361.9 | L83: 1372.7 | M83: 1398.2 | N83: 1413 | O83: 1471.9 | P83: 1498.3 | Q83: 1491.4 | R83: 1501.1 | S83: 1510.9 | T83: 1568.2 | U83: 1593.7 | V83: 1644.3 | W83: 1743.5 | X83: 1837.8 | Y83: 2004.3 | Z83: 2147.829 | AA83: 2398.848 | AI83: 960.1 | AJ83: 1323.4 | AK83: 1398.2 | AL83: 1491.4 | AM83: 1593.7 | AN83: 2004.3
A84: Other, Curr | B84: 130 | C84: 1410.8 | D84: 1434 | E84: 1556 | F84: 1703.8 | G84: 1826.7 | H84: 1889.1 | I84: 2042 | J84: =+2089 -> 2089 | K84: 2021 | L84: 2703 | M84: 3208 | N84: 2655 | O84: 2929 | P84: 2912 | Q84: 2780 | R84: 2876 | S84: 2960 | T84: 2905 | U84: 3516 | V84: 3327 | W84: 3603 | X84: 3638 | Y84: 3958 | Z84: 4782.532 | AA84: 4725.393 | AI84: 1556 | AJ84: 2042 | AK84: 3208 | AL84: 2780 | AM84: 3516 | AN84: 3958 | AO84: =+AO16*0.085 -> 4366.682 | AP84: =+AP16*0.085 -> 4964.9175 | AQ84: =+AQ16*0.085 -> 5610.3568 | AR84: =+AR16*0.085 -> 6339.7031 | AS84: =+AS16*0.085 -> 7100.4675
B85: =+B84/B$16 -> 0.022539705 | C85: =+C84/C$16 -> 0.22946553 | D85: =+D84/D$16 -> 0.22282305 | E85: =+E84/E$16 -> 0.23418217 | F85: =+F84/F$16 -> 0.23785459 | G85: =+G84/G$16 -> 0.24880897 | H85: =+H84/H$16 -> 0.25243873 | I85: =+I84/I$16 -> 0.26487489 | ... AC85: =+AC84/AC$16 -> 0 | AI85: =+AI84/AI$16 -> 0.062249821 | AJ85: =+AJ84/AJ$16 -> 0.0687592 | AK85: =+AK84/AK$16 -> 0.10146906 | AL85: =+AL84/AL$16 -> 0.082435593 | AM85: =+AM84/AM$16 -> 0.090151544 | AN85: =+AN84/AN$16 -> 0.0875999 | AO85: =+AO84/AO$16 -> 0.085 | AP85: =+AP84/AP$16 -> 0.085 | ... AS85: =+AS84/AS$16 -> 0.085
A86: Other, Non Curr | B86: =+2694.7 -> 2694.7 | C86: =+2704 -> 2704 | D86: =+2900.3 -> 2900.3 | E86: =+3174.6 -> 3174.6 | F86: =+2956 -> 2956 | G86: =+2967.6 -> 2967.6 | H86: 3129.9 | I86: =+4271.8 -> 4271.8 | J86: 4657.2 | K86: =++4615 -> 4615 | L86: =++4595.1 -> 4595.1 | M86: =++5193.3 -> 5193.3 | N86: =++5245.4 -> 5245.4 | O86: =++5318.3 -> 5318.3 | P86: =++5474 -> 5474 | Q86: =++5664.3 -> 5664.3 | R86: =+5743.1 -> 5743.1 | S86: =+6045 -> 6045 | T86: =+6409.1 -> 6409.1 | U86: =+6483.77 -> 6483.77 | V86: =+6704.8 -> 6704.8 | W86: =+7273.5 -> 7273.5 | X86: =+7494.1 -> 7494.1 | Y86: =+7794 -> 7794 | Z86: =+8420.808 -> 8420.808 | AA86: 8360.717 | AI86: =+3174.6 -> 3174.6 | AJ86: =++4271.8 -> 4271.8 | AK86: =++5193.3 -> 5193.3 | AL86: =++5664.3 -> 5664.3 | AM86: =++6483.77 -> 6483.77 | AN86: =++7794 -> 7794
A87: A | B87: =SUM(B80:B86)-B85 -> 33893.7 | C87: =SUM(C80:C86)-C85 -> 37175 | D87: =SUM(D80:D86)-D85 -> 38622.3 | E87: =SUM(E80:E86)-E85 -> 39280.1 | F87: =SUM(F80:F86)-F85 -> 40122.8 | G87: =SUM(G80:G86)-G85 -> 40970.8 | H87: =SUM(H80:H86)-H85 -> 42739.7 | I87: =SUM(I80:I86)-I85 -> 44584.5 | ... AC87: =SUM(AC80:AC86)-AC85 -> 0 | AI87: =SUM(AI80:AI86)-AI85 -> 39280.1 | AJ87: =SUM(AJ80:AJ86)-AJ85 -> 44584.5 | AK87: =SUM(AK80:AK86)-AK85 -> 48594.5 | AL87: =SUM(AL80:AL86)-AL85 -> 48731.57 | AM87: =SUM(AM80:AM86)-AM85 -> 53629.57 | AN87: =SUM(AN80:AN86)-AN85 -> 55596.88
A89: Current content Liabilities | B89: 4761.5 | C89: 4664.7 | D89: 4599.6 | E89: 4429.5 | F89: 4297.9 | G89: 4197.8 | H89: 4110.9 | I89: 4292.9 | J89: 4066.2 | K89: 4174.96 | L89: 4225.8 | M89: 4480.1 | N89: 4344.5 | O89: 4440.4 | P89: 4259.5 | Q89: 4466.4 | R89: 4436 | S89: 4391.4 | T89: 4489.9 | U89: 4393.6 | V89: 4128.9 | W89: 4091.7 | X89: 4102.6 | Y89: 4084.8 | Z89: 4052.278 | AA89: 3866.522 | AI89: 4429.5 | AJ89: 4292.9 | AK89: 4480.1 | AL89: 4466.4 | AM89: 4393.6 | AN89: 4084.8 | AO89: =+AO16*0.095 -> 4880.4093 | AP89: =+AP16*0.095 -> 5549.0254 | AQ89: =+AQ16*0.095 -> 6270.3987 | AR89: =+AR16*0.095 -> 7085.5506 | AS89: =+AS16*0.095 -> 7935.8166
B90: =+B89/B$16 -> 0.82556002 | C90: =+C89/C$16 -> 0.75870987 | D90: =+D89/D$16 -> 0.71471191 | E90: =+E89/E$16 -> 0.66665162 | F90: =+F89/F$16 -> 0.59999721 | G90: =+G89/G$16 -> 0.57176893 | H90: =+H89/H$16 -> 0.54933586 | I90: =+I89/I$16 -> 0.55684693 | ... AC90: =+AC89/AC$16 -> 0 | AI90: =+AI89/AI$16 -> 0.17720796 | AJ90: =+AJ89/AJ$16 -> 0.14455258 | AK90: =+AK89/AK$16 -> 0.14170558 | AL90: =+AL89/AL$16 -> 0.13244257 | AM90: =+AM89/AM$16 -> 0.11265353 | AN90: =+AN89/AN$16 -> 0.090406284 | AO90: =+AO89/AO$16 -> 0.095 | AP90: =+AP89/AP$16 -> 0.095 | ... AS90: =+AS89/AS$16 -> 0.095
A91: A/P | B91: 545.4 | C91: 446.6 | D91: 541.2 | E91: 656.1 | F91: 532.9 | G91: 622.9 | H91: 643 | I91: 837.4 | J91: 617.2 | K91: 504.2 | L91: 560.1 | M91: 671.5 | N91: 591.9 | O91: 615.3 | P91: 534.4 | Q91: 747.4 | R91: 607 | S91: 598.5 | T91: 641.9 | U91: 899.9 | V91: 614.4 | W91: 632.7 | X91: 793.2 | Y91: 900.6 | Z91: 894.681 | AA91: 814.551 | AI91: 656.1 | AJ91: 837.4 | AK91: 671.5 | AL91: 747.4 | AM91: 899.9 | AN91: 900.6 | AO91: =+AO149*AO18/365 -> 1028.6916 | AP91: =+AP149*AP18/365 -> 1173.3408 | AQ91: =+AQ149*AQ18/365 -> 1355.6063 | AR91: =+AR149*AR18/365 -> 1564.4097 | AS91: =+AS149*AS18/365 -> 1787.478
A92: Accrued Exp | B92: 1061 | C92: 986.5 | D92: 1259.1 | E92: 1102.1 | F92: 1291.8 | G92: 1125.5 | H92: 1413.1 | I92: 1449.3 | J92: 1817.1 | K92: 1596 | L92: 1803.5 | M92: 1514.6 | N92: 1718 | O92: 1908.7 | P92: 1838.9 | Q92: 1803.9 | R92: 1977.4 | S92: 1876.2 | T92: 2241.7 | U92: 2156.5 | V92: 2359.5 | W92: 2489.4 | X92: 3111.3 | Y92: 3220.8 | Z92: 4441.986 | AA92: 3172.611 | AI92: 1102.1 | AJ92: 1449.3 | AK92: 1514.6 | AL92: 1803.9 | AM92: 2156.5 | AN92: 3220.8 | AO92: =+AO16*0.05 -> 2568.6365 | AP92: =+AP16*0.05 -> 2920.5397 | AQ92: =+AQ16*0.05 -> 3300.2099 | AR92: =+AR16*0.05 -> 3729.2371 | AS92: =+AS16*0.05 -> 4176.7456
B93: =+B92/B$16 -> 0.18395867 | C93: =+C92/C$16 -> 0.16045347 | D93: =+D92/D$16 -> 0.19564609 | E93: =+E92/E$16 -> 0.165869 | F93: =+F92/F$16 -> 0.1803384 | G93: =+G92/G$16 -> 0.15330076 | H93: =+H92/H$16 -> 0.18883128 | I93: =+I92/I$16 -> 0.18799372 | ... AC93: =+AC92/AC$16 -> 0 | AI93: =+AI92/AI$16 -> 0.044090956 | AJ93: =+AJ92/AJ$16 -> 0.048801522 | AK93: =+AK92/AK$16 -> 0.047906805 | AL93: =+AL92/AL$16 -> 0.053491211 | AM93: =+AM92/AM$16 -> 0.05529346 | AN93: =+AN92/AN$16 -> 0.071283921 | AO93: =+AO92/AO$16 -> 0.05 | AP93: =+AP92/AP$16 -> 0.05 | ... AS93: =+AS92/AS$16 -> 0.05
A94: D/R | B94: 986.7 | C94: 1029.2 | D94: 1040.2 | E94: 1117.9 | F94: 1140.2 | G94: 1187.3 | H94: 1182.6 | I94: 1209.3 | J94: 1239 | K94: 1224.7 | L94: 1176.3 | M94: 1264.6 | N94: 1262.2 | O94: 1311.9 | P94: 1306.1 | Q94: 1442.9 | R94: 1469.4 | S94: 1476.2 | T94: 1513 | U94: 1520.8 | V94: 1609.7 | W94: 1728.3 | X94: 1724.6 | Y94: 1775.7 | Z94: 1743.448 | AA94: 1797.456 | AI94: 1117.9 | AJ94: 1209.3 | AK94: 1264.6 | AL94: 1442.9 | AM94: 1520.8 | AN94: 1775.7 | AO94: =+AO16*0.03 -> 1541.1819 | AP94: =+AP16*0.03 -> 1752.3238 | AQ94: =+AQ16*0.03 -> 1980.1259 | AR94: =+AR16*0.03 -> 2237.5423 | AS94: =+AS16*0.03 -> 2506.0474
B95: =+B94/B$16 -> 0.17107636 | C95: =+C94/C$16 -> 0.16739859 | D95: =+D94/D$16 -> 0.16163217 | E95: =+E94/E$16 -> 0.16824694 | F95: =+F94/F$16 -> 0.15917467 | G95: =+G94/G$16 -> 0.16171834 | H95: =+H94/H$16 -> 0.15802977 | I95: =+I94/I$16 -> 0.15686249 | ... AC95: =+AC94/AC$16 -> 0 | AI95: =+AI94/AI$16 -> 0.044723056 | AJ95: =+AJ94/AJ$16 -> 0.040720128 | AK95: =+AK94/AK$16 -> 0.039999304 | AL95: =+AL94/AL$16 -> 0.042786445 | AM95: =+AM94/AM$16 -> 0.038993876 | AN95: =+AN94/AN$16 -> 0.03930044 | AO95: =+AO94/AO$16 -> 0.03 | AP95: =+AP94/AP$16 -> 0.03 | ... AS95: =+AS94/AS$16 -> 0.03
A96: Short debt | B96: 498.8 | C96: 499.1 | D96: 499.5 | E96: 499.8 | F96: 698.7 | G96: 699.1 | H96: 699 | I96: 699.8 | J96: 0 | K96: 0 | L96: 0 | M96: 0 | N96: 399.1 | O96: 399.3 | P96: 399.6 | Q96: 399.8 | R96: 798.9 | S96: 1800 | T96: 1820.3 | U96: 1784.4 | V96: 1005.8 | W96: 0 | X96: 0 | Y96: 998.8 | Z96: 999.185 | AA96: 2483.758 | AB96: 999.185 | AC96: 999.185 | AI96: 499.8 | AJ96: 699.8 | AK96: 0 | AL96: 399.8 | AM96: 1784.4 | AN96: 998.8
A97: Long Debt | B97: =++14170.6 -> 14170.6 | C97: =++15294.9 -> 15294.9 | D97: =++15547.6 -> 15547.6 | E97: =++15809 -> 15809 | F97: =++14860.5 -> 14860.5 | G97: =+14926.8 -> 14926.8 | H97: =++14793.6 -> 14793.6 | I97: =++14693 -> 14693 | J97: =0+14534.5 -> 14534.5 | K97: =0+14223.3 -> 14223.3 | L97: =0+13888.1 -> 13888.1 | M97: =0+14353 -> 14353 | N97: =+14037 -> 14037 | O97: =+14070.1 -> 14070.1 | P97: =+13900.7 -> 13900.7 | Q97: =+14143.4 -> 14143.4 | R97: =+13217 -> 13217 | S97: =+12180 -> 12180 | T97: =+14160.9 -> 14160.9 | U97: 13798.3 | V97: =+14011 -> 14011 | W97: =0+14453.2 -> 14453.2 | X97: =0+14463 -> 14463 | Y97: =+13463.9 -> 13463.9 | Z97: =+13361.331 -> 13361.331 | AA97: 11825.548 | AB97: =+13361.331 -> 13361.331 | AC97: =+13361.331 -> 13361.331 | AI97: =+15809 -> 15809 | AJ97: =+14693 -> 14693 | AK97: =14353 -> 14353 | AL97: =+14143.4 -> 14143.4 | AM97: =+13798.3 -> 13798.3 | AN97: =+13463.9 -> 13463.9
A98: NCCL | B98: 3206 | C98: 3208.1 | D98: 2926.5 | E98: 2618 | F98: 2465.6 | G98: 2265.2 | H98: 2301 | I98: 3094.2 | J98: 2945.2 | K98: 2989.9 | L98: 2955.3 | M98: 3081.2 | N98: 2908 | O98: 2849.3 | P98: 2668.4 | Q98: 2578.1 | R98: 2370.6 | S98: 2028.7 | T98: 1918.08 | U98: 1780.8 | V98: 1696.6 | W98: 1606.4 | X98: 1591.9 | Y98: 1579.4 | Z98: 1626.498 | AA98: 1625.6 | AI98: 2618 | AJ98: 3094.2 | AK98: 3081.2 | AL98: 2578.1 | AM98: 1780.8 | AN98: 1579.4
A99: Other NCL | B99: 1420.1 | C99: 1710.9 | D99: 1875.2 | E99: 1982 | F99: 1950.9 | G99: 2082 | H99: 2281.2 | I99: 2459.1 | J99: 2567.4 | K99: 2551.6 | L99: 2424.6 | M99: 2452 | N99: 2400 | O99: 2389.9 | P99: 2486.2 | Q99: 2561.4 | R99: 2585.3 | S99: 2637.3 | T99: 2774.9 | U99: 2552.2 | V99: 2633.3 | W99: 3145.8 | X99: 3193.9 | Y99: 2957.1 | Z99: 2770.108 | AA99: 2712.343 | AI99: 1982 | AJ99: 2459.1 | AK99: 2452 | AL99: 2561.4 | AM99: 2552.2 | AN99: 2957.1
A100: L | B100: =SUM(B89:B99) -> 26651.281 | C100: =SUM(C89:C99) -> 27841.087 | D100: =SUM(D89:D99) -> 28289.972 | E100: =SUM(E89:E99) -> 28215.401 | F100: =SUM(F89:F99) -> 27239.44 | G100: =SUM(G89:G99) -> 27107.487 | H100: =SUM(H89:H99) -> 27425.296 | I100: =SUM(I89:I99) -> 28735.902 | ... AC100: =SUM(AC89:AC99) -> 14360.516 | AI100: =SUM(AI89:AI99) -> 28214.666 | AJ100: =SUM(AJ89:AJ99) -> 28735.234 | AK100: =SUM(AK89:AK99) -> 27817.23 | AL100: =SUM(AL89:AL99) -> 28143.529 | AM100: =SUM(AM89:AM99) -> 28886.707 | AN100: =SUM(AN89:AN99) -> 28981.301
A101: Stocks | B101: 2935.5 | C101: 3127.8 | D101: 3303.4 | E101: 3447.6 | F101: 3600 | G101: 3721.2 | H101: 3852.5 | I101: 4024.5 | J101: 4155.5 | K101: 4316.8 | L101: 4473.9 | M101: 4637.6 | N101: 4762.3 | O101: 4874.2 | P101: 5011.427 | Q101: 5145.1 | R101: 5489.8 | S101: 5680 | T101: 5887.9 | U101: 6252.1 | V101: 6677.4 | W101: 6932.8 | X101: 7080 | Y101: 7286.4 | Z101: 7478.495 | AA101: 7670.503 | AI101: 3447.6 | AJ101: 4024.5 | AK101: 4637.6 | AL101: 5145.1 | AM101: 6252.1 | AN101: 7286.4
A102: Treasury stock | B102: 0 | C102: 0 | D102: 0 | E102: 0 | F102: 0 | G102: -500 | H102: -600 | I102: -824.1 | J102: -824.1 | K102: -824.1 | L102: -824.1 | M102: -824.1 | N102: -1228.9 | O102: -1876.7 | P102: -4399.6 | Q102: -6922.2 | R102: -8934 | S102: -10547 | T102: -12254.85 | U102: -13171.6 | V102: -16754.9 | W102: -18392.9 | X102: -20270.6 | Y102: -22372.6 | Z102: -23681.974 | AA102: -28387.657 | AI102: 0 | AJ102: -824.1 | AK102: -824.1 | AL102: -6922.2 | AM102: -13171.6 | AN102: -22372.6
A103: Accumulated income or loss | B103: -47 | C103: -34 | D103: -1147 | E103: 44.3 | F103: 4 | G103: 9 | H103: -19.8 | I103: -40.4 | J103: -74.1 | K103: -144.4 | L103: -247.6 | M103: -217.3 | N103: -191.6 | O103: -139.2 | P103: -155.5 | Q103: -223.9 | R103: -111.8 | S103: -89.1 | T103: -344.6 | U103: 362.1 | V103: -85.7 | W103: -904.6 | X103: -719.2 | Y103: -580.3 | Z103: -235.031 | AA103: -97.117 | AI103: 44.3 | AJ103: -40.4 | AK103: -217.3 | AL103: -223.9 | AM103: 362.1 | AN103: -580.3
A104: Retained Earning | B104: 5520.8 | C104: 6241 | D104: 7030.9 | E104: 7573.1 | F104: 9279.8 | G104: 10632.8 | H104: 12081.9 | I104: 12689.3 | J104: 14286.8 | K104: 15727.7 | L104: 17126 | M104: 17181.2 | N104: 18486.4 | O104: 19974 | P104: 21651.4 | Q104: 22589.2 | R104: 24921.4 | S104: 27068.8 | T104: 29432.3 | U104: 31300.9 | V104: 34191.2 | W104: 37316.6 | X104: 39863.59 | Y104: 42282.118 | Z104: 47564.909 | AA104: 50966.323 | AI104: 7573.1 | AJ104: 12689.3 | AK104: 17181.2 | AL104: 22589.2 | AM104: 31300.9 | AN104: 42282.118
A105: SE | B105: =SUM(B101:B104) -> 8409.3 | C105: =SUM(C101:C104) -> 9334.8 | D105: =SUM(D101:D104) -> 9187.3 | E105: =SUM(E101:E104) -> 11065 | F105: =SUM(F101:F104) -> 12883.8 | G105: =SUM(G101:G104) -> 13863 | H105: =SUM(H101:H104) -> 15314.6 | I105: =SUM(I101:I104) -> 15849.3 | ... AB105: =SUM(AB101:AB104) -> 0 | AI105: =SUM(AI101:AI104) -> 11065 | AJ105: =SUM(AJ101:AJ104) -> 15849.3 | AK105: =SUM(AK101:AK104) -> 20777.4 | AL105: =SUM(AL101:AL104) -> 20588.2 | AM105: =SUM(AM101:AM104) -> 24743.5 | AN105: =SUM(AN101:AN104) -> 26615.618
A106: L+SE | B106: =B100+B105 -> 35060.581 | C106: =C100+C105 -> 37175.887 | D106: =D100+D105 -> 37477.272 | E106: =E100+E105 -> 39280.401 | F106: =F100+F105 -> 40123.24 | G106: =G100+G105 -> 40970.487 | H106: =H100+H105 -> 42739.896 | I106: =I100+I105 -> 44585.202 | ... V106: =V100+V105 -> 52087.968 | W106: =W105+W100 -> 53100.15 | X106: =X105+X100 -> 54935.067 | Y106: =Y100+Y105 -> 55597.472 | Z106: =Z100+Z105 -> 61016.75 | AA106: =AA100+AA105 -> 58451.145 | AB106: =AB100+AB105 -> 14360.516 | AC106: =AC100+AC105 -> 14360.516 | AI106: =AI100+AI105 -> 39279.666 | AJ106: =AJ100+AJ105 -> 44584.534 | AK106: =AK100+AK105 -> 48594.63 | AL106: =AL100+AL105 -> 48731.729 | AM106: =AM100+AM105 -> 53630.207 | AN106: =AN100+AN105 -> 55596.919
A108: Content Obligations | B108: - | C108: - | D108: - | E108: 19218.8 | F108: 20725.1 | G108: 21863.1 | H108: 22465 | I108: 23161.3 | J108: 22365.5 | K108: 22769.6 | L108: 21572 | M108: 21831.9 | N108: 21525.8 | O108: 20900.2 | P108: 19650 | Q108: 21713.3 | R108: 24195 | S108: 23309.6 | T108: 22698.8 | U108: 23248.9 | V108: 21790.6 | W108: 20967.2 | X108: 20940.9 | Y108: 24039.2 | Z108: 24139.431 | AA108: 25106.705 | AI108: 19218.8 | AJ108: 23161.3 | AK108: 21831.9 | AL108: 21713.3 | AM108: 23248.9 | AN108: 24039.2
I109: =+I108/E108-1 -> 0.20513768 | J109: =+J108/F108-1 -> 0.079150402 | K109: =+K108/G108-1 -> 0.041462556 | L109: =+L108/H108-1 -> -0.039750723 | M109: =+M108/I108-1 -> -0.057397469 | N109: =+N108/J108-1 -> -0.037544432 | O109: =+O108/K108-1 -> -0.082100696 | P109: =+P108/L108-1 -> -0.089096978 | ... AA109: =+AA108/W108-1 -> 0.19742765 | AJ109: =+AJ108/AI108-1 -> 0.20513768 | AK109: =+AK108/AJ108-1 -> -0.057397469 | AL109: =+AL108/AK108-1 -> -0.0054324177 | AM109: =+AM108/AL108-1 -> 0.070721631 | AN109: =+AN108/AM108-1 -> 0.033993006
A111: ROCE | AI111: =AI30/(AI113+(AI97-AI80)) -> 0.24560766 | AJ111: =AJ30/(AJ113+(AJ97-AJ80)) -> 0.25268093 | AK111: =AK30/(AK113+(AK97-AK80)) -> 0.18786008 | AL111: =AL30/(AL113+(AL97-AL80)) -> 0.25181678 | AM111: =AM30/(AM113+(AM97-AM80)) -> 0.33892248 | AN111: =AN30/(AN113+(AN97-AN80)) -> 0.42924011
A112: Cap. Employed | AI112: =AI30+(AI97-AI80) -> 12188.627 | AJ112: =AJ30+(AJ97-AJ80) -> 14859.547 | AK112: =AK30+(AK97-AK80) -> 14838.565 | AL112: =AL30+(AL97-AL80) -> 13980.345 | AM112: =AM30+(AM97-AM80) -> 16411.094 | AN112: =AN30+(AN97-AN80) -> 17756.339
A113: Book Value | B113: =B105 -> 8409.3 | C113: =C105 -> 9334.8 | D113: =D105 -> 9187.3 | E113: =E105 -> 11065 | F113: =F105 -> 12883.8 | G113: =G105 -> 13863 | H113: =H105 -> 15314.6 | I113: =I105 -> 15849.3 | ... AA113: =AA105 -> 30152.052 | AI113: =AI105 -> 11065 | AJ113: =AJ105 -> 15849.3 | AK113: =AK105 -> 20777.4 | AL113: =AL105 -> 20588.2 | AM113: =AM105 -> 24743.5 | AN113: =AN105 -> 26615.618
A115: Model NI | B115: =B40 -> 708.93397 | C115: =C40 -> 720.25861 | D115: =D40 -> 790.14752 | E115: =E40 -> 542.21196 | F115: =F40 -> 1706.6551 | G115: =G40 -> 1353.1216 | H115: =H40 -> 1449.6397 | I115: =I40 -> 608.51334 | ... AC115: =AC40 -> 3503.9026 | AI115: =AI40 -> 2761.2327 | AJ115: =AJ40 -> 5116.0657 | AK115: =AK40 -> 4491.7582 | AL115: =AL40 -> 5407.8318 | AM115: =AM40 -> 8711.5112 | AN115: =AN40 -> 10980.717 | AO115: =AO40 -> 13165.925 | AP115: =AP40 -> 15798.651 | ... AS115: =AS40 -> 24640.205
...

Sheet Bonds
A1: Main
B3: yield
A4: US64110LAN64 | B4: 4375 | C4: Fixed Listing | D4: 15/11/2026 | E4: 1 | F4: USD | G4: Senior
A5: XS1821883102 | B5: 3625 | C5: Fixed Listing | D5: 15/05/2027 | E5: 1 | F5: EUR | G5: Senior
A6: US64110LAS51 | B6: 4875 | C6: Fixed Listing | D6: 15/04/2028 | E6: 1 | F6: USD | G6: Senior
A7: US64110LAT35 | B7: 5875 | C7: Fixed Listing | D7: 15/11/2028 | E7: 1 | F7: USD | G7: Senior
A8: US64110LAX47 | B8: 6375 | C8: Fixed Listing | D8: 15/05/2029 | E8: 1 | F8: USD | G8: Senior
A9: XS2076099865 | B9: 4625 | C9: Fixed Listing | D9: 15/05/2029 | E9: 1 | F9: EUR | G9: Senior
A10: US64110LAU08 | B10: 5375 | C10: Fixed Listing | D10: 15/11/2029 | E10: 1 | F10: USD | G10: Senior
A11: USU74079AN15 | B11: 5375 | C11: Fixed Listing | D11: 15/11/2029 | E11: 1 | F11: USD | G11: Senior
A12: XS1989380172 | B12: 3875 | C12: Fixed Listing | D12: 15/11/2029 | E12: 1 | F12: EUR | G12: Senior
A13: XS1989380503 | B13: 3875 | C13: Fixed Listing | D13: 15/11/2029 | E13: 1 | F13: EUR | G13: Senior
A14: US64110LAV80 | B14: 4875 | C14: Fixed Listing | D14: 15/06/2030 | E14: 1 | F14: USD | G14: Senior
A15: USU74079AQ46 | B15: 4875 | C15: Fixed Listing | D15: 15/06/2030 | E15: 1 | F15: USD | G15: Senior
... A19: US64110LBA35 | B19: 5400 | C19: Fixed Listing | D19: 15/08/2054 | E19: 1 | F19: USD | G19: Senior
A22: average yield | B22: =AVERAGE(B4:B19) -> 4721.875
