Workbook

Sheet Main
A1: Nvidia Corp | E1: Price | F1: 219
E2: Share | F2: 24100 | G2: Q227 | I2: -> | J2: Increasing strategic partenrship with UBER in order to inprove Drive and Alpamayo in real world scenarios
E3: MC | F3: =+F1*F2 -> 5277900 | J3: Exploiting UBER’s network effect in order to engage more users and deploy L4 AV in 28 cities by 2028
E4: Cash | F4: 99369 | G4: Q227 | J4: -> | K4: Nvidia’s Level 4 AV are developed altogether with Mercedes Benz, Stellantis and Lucid
E5: Debt | F5: =+1000+32366 -> 33366 | G5: Q227
E6: EV | F6: =+F3-F4+F5 -> 5211897
A10: P/FCF | B10: =+F3/SUM(Model!L131:O131) -> 41.556286 | D10: BETA | E10: 2.21 | G10: WACC | H10: =+(F3/(F3+F5))*E11+(F5/(F3+F5))*E12*(1-Model!N64) -> 0.15870008
A11: EV/EBITDA | B11: =+F6/SUM(Model!L73:O73) -> 25.82026 | D11: CAPM | E11: =+'[1]Zero-rate curve US'!J3+E10*(0.1-'[1]Zero-rate curve US'!J3) -> 0.15939289
A12: EV/FCF | B12: =+F6/SUM(Model!L131:O131) -> 41.036602 | D12: Cost of Debt | E12: =+'[1]Zero-rate curve US'!J3+(E13/100) -> 0.058862796
A13: Inc. Margin | B13: =+((Model!O31+Model!N31+Model!M31+Model!L31)-(Model!K31+Model!J31+Model!I31+Model!H31))/((Model!O19+Model!N19+Model!M19+Model!L19)-(Model!K19+Model!J19+Model!I19+Model!H19)) -> 0.72775945 | D13: Cr. Spread | E13: =+'[1]Credit Spread US'!J6 -> 0.79478261
A14: P/E | B14: =+F1/SUM(Model!L45:O45) -> 27.683985 | D14: Rating | E14: AA | F14: Aa2
E15: S&P | F15: Moody’s

Sheet Model
A1: Main | B1: 45042 | C1: 45133 | D1: 45224 | E1: 45348 | F1: 45408 | G1: 45499 | H1: 45589 | I1: 45683 | J1: 45773 | K1: 45864 | L1: 45955 | M1: 46079 | N1: 46138 | O1: 46229 | P1: 46320 | Q1: 46444
A2: in Millions | B2: Q124 | C2: Q224 | D2: Q324 | E2: Q424 | F2: Q125 | G2: Q225 | H2: Q325 | I2: Q425 | J2: Q126 | K2: Q226 | L2: Q326 | M2: Q426 | N2: Q127 | O2: Q227 | P2: Q327 | Q2: Q427 | V2: =+W2-1 -> 2011 | W2: =+X2-1 -> 2012 | X2: =+Y2-1 -> 2013 | Y2: =+Z2-1 -> 2014 | Z2: =+AA2-1 -> 2015 | AA2: =+AB2-1 -> 2016 | AB2: =+AC2-1 -> 2017 | AC2: =+AD2-1 -> 2018 | AD2: =+AE2-1 -> 2019 | AE2: 2020 | AF2: =+AE2+1 -> 2021 | AG2: =+AF2+1 -> 2022 | AH2: =+AG2+1 -> 2023 | AI2: =+AH2+1 -> 2024 | AJ2: =+AI2+1 -> 2025 | AK2: =+AJ2+1 -> 2026 | AL2: =+AK2+1 -> 2027 | AM2: =+AL2+1 -> 2028 | ... AP2: =+AO2+1 -> 2031
A3: Data Center | B3: =SUM(B5:B6) -> 4284 | C3: =SUM(C5:C6) -> 10323 | D3: =SUM(D5:D6) -> 14514 | E3: =SUM(E5:E6) -> 18404 | F3: =SUM(F5:F6) -> 22563 | G3: =SUM(G5:G6) -> 26272 | H3: =SUM(H5:H6) -> 30771 | I3: =SUM(I5:I6) -> 35580 | ... O3: =SUM(O5:O6) -> 89023 | Y3: 199 | Z3: 317 | AA3: 339 | AB3: 830 | AC3: 1932 | AD3: 2932 | AE3: 2983 | AF3: 6696 | AG3: 10613 | AH3: 15005 | AI3: =SUM(AI5:AI6) -> 47525 | AJ3: =SUM(AJ5:AJ6) -> 115186 | AK3: 193737
F4: =+F3/B3-1 -> 4.2668067 | G4: =+G3/C3-1 -> 1.5449966 | H4: =+H3/D3-1 -> 1.1200909 | I4: =+I3/E3-1 -> 0.93327537 | J4: =+J3/F3-1 -> 0.95284315 | K4: =+K3/G3-1 -> 0.56425091 | L4: =+L3/H3-1 -> 0.6643918 | M4: =+M3/I3-1 -> 0.75137718 | ... O4: =+O3/K3-1 -> 1.1662206
A5: Compute | B5: 3357 | C5: 8612 | D5: 11908 | E5: 15073 | F5: 19392 | G5: 22604 | H5: 27644 | I5: 32556 | J5: 39112 | K5: 33844 | L5: 43028 | M5: 51334 | N5: 60400 | O5: 48710 | AI5: =SUM(B5:E5) -> 38950 | AJ5: =SUM(F5:I5) -> 102196 | AK5: 162361
A6: Networking | B6: 927 | C6: 1711 | D6: 2606 | E6: 3331 | F6: 3171 | G6: 3668 | H6: 3127 | I6: 3024 | J6: 4950 | K6: 7252 | L6: 8187 | M6: 10980 | N6: 14800 | O6: 40313 | AI6: =SUM(B6:E6) -> 8575 | AJ6: =SUM(F6:I6) -> 12990 | AK6: =SUM(J6:M6) -> 31369
A7: % | F7: =+F6/B6-1 -> 2.420712 | G7: =+G6/C6-1 -> 1.1437756 | H7: =+H6/D6-1 -> 0.19992325 | I7: =+I6/E6-1 -> -0.092164515 | J7: =+J6/F6-1 -> 0.56102176 | K7: =+K6/G6-1 -> 0.97709924 | L7: =+L6/H6-1 -> 1.6181644 | M7: =+M6/I6-1 -> 2.6309524 | ... O7: =+O6/K6-1 -> 4.5588803 | Y7: =Y3/Y$19 -> 0.048184019 | Z7: =Z3/Z$19 -> 0.067706109 | AA7: =AA3/AA$19 -> 0.067664671 | AB7: =AB3/AB$19 -> 0.12011577 | AC7: =AC3/AC$19 -> 0.1988882 | AD7: =AD3/AD$19 -> 0.25025606 | AE7: =AE3/AE$19 -> 0.27321854 | AF7: =AF3/AF$19 -> 0.40155922 | ... AK7: =AK3/AK$19 -> 0.89718808
A8: Gaming | B8: 2240 | C8: 2486 | D8: 2856 | E8: 2865 | F8: 2647 | G8: 2880 | H8: 3279 | I8: 2544 | J8: 3763 | K8: 4287 | L8: 4265 | M8: 3727 | Y8: 1511 | Z8: 2058 | AA8: 2818 | AB8: 4060 | AC8: 5513 | AD8: 6246 | AE8: 5518 | AF8: 7759 | AG8: 12462 | AH8: 9067 | AI8: =SUM(B8:E8) -> 10447 | AJ8: =SUM(F8:I8) -> 11350 | AK8: =SUM(J8:M8) -> 16042
A9: % | F9: =+F8/B8-1 -> 0.18169643 | G9: =+G8/C8-1 -> 0.15848753 | H9: =+H8/D8-1 -> 0.14810924 | I9: =+I8/E8-1 -> -0.11204188 | J9: =+J8/F8-1 -> 0.42160937 | K9: =+K8/G8-1 -> 0.48854167 | L9: =+L8/H8-1 -> 0.30070143 | M9: =+M8/I8-1 -> 0.46501572 | Y9: =Y8/Y$19 -> 0.36585956 | Z9: =Z8/Z$19 -> 0.43955575 | AA9: =AA8/AA$19 -> 0.56247505 | AB9: =AB8/AB$19 -> 0.58755427 | AC9: =AC8/AC$19 -> 0.5675314 | AD9: =AD8/AD$19 -> 0.5331171 | AE9: =AE8/AE$19 -> 0.50540392 | AF9: =AF8/AF$19 -> 0.46530735 | ... AK9: =AK8/AK$19 -> 0.074289842
A10: Professional Vis | B10: 295 | C10: 379 | D10: 416 | E10: 463 | F10: 427 | G10: 454 | H10: 489 | I10: 511 | J10: 509 | K10: 601 | L10: 760 | M10: 1321 | Y10: 789 | Z10: 795 | AA10: 750 | AB10: 835 | AC10: 934 | AD10: 1130 | AE10: 1212 | AF10: 1053 | AG10: 2111 | AH10: 1544 | AI10: =SUM(B10:E10) -> 1553 | AJ10: 1878 | AK10: =SUM(J10:M10) -> 3191
A11: % | F11: =+F10/B10-1 -> 0.44745763 | G11: =+G10/C10-1 -> 0.19788918 | H11: =+H10/D10-1 -> 0.17548077 | I11: =+I10/E10-1 -> 0.10367171 | J11: =+J10/F10-1 -> 0.19203747 | K11: =+K10/G10-1 -> 0.32378855 | L11: =+L10/H10-1 -> 0.55419223 | M11: =+M10/I10-1 -> 1.5851272 | Y11: =Y10/Y$19 -> 0.19104116 | Z11: =Z10/Z$19 -> 0.16979923 | AA11: =AA10/AA$19 -> 0.1497006 | AB11: =AB10/AB$19 -> 0.12083936 | AC11: =AC10/AC$19 -> 0.096149887 | AD11: =AD10/AD$19 -> 0.0964493 | AE11: =AE10/AE$19 -> 0.11100934 | AF11: =AF10/AF$19 -> 0.063148426 | ... AK11: =AK10/AK$19 -> 0.01477739
A12: Auto | B12: 296 | C12: 253 | D12: 261 | E12: 281 | F12: 329 | G12: 346 | H12: 449 | I12: 570 | J12: 567 | K12: 586 | L12: 592 | M12: 604 | Y12: 99 | Z12: 183 | AA12: 320 | AB12: 487 | AC12: 558 | AD12: 641 | AE12: 700 | AF12: 536 | AG12: 566 | AH12: 903 | AI12: =SUM(B12:E12) -> 1091 | AJ12: =SUM(F12:I12) -> 1694 | AK12: =SUM(J12:M12) -> 2349
A13: % | F13: =+F12/B12-1 -> 0.11148649 | G13: =+G12/C12-1 -> 0.36758893 | H13: =+H12/D12-1 -> 0.72030651 | I13: =+I12/E12-1 -> 1.0284698 | J13: =+J12/F12-1 -> 0.72340426 | K13: =+K12/G12-1 -> 0.69364162 | L13: =+L12/H12-1 -> 0.31848552 | M13: =+M12/I12-1 -> 0.059649123 | Y13: =Y12/Y$19 -> 0.023970944 | Z13: =Z12/Z$19 -> 0.039085861 | AA13: =AA12/AA$19 -> 0.063872255 | AB13: =AB12/AB$19 -> 0.070477569 | AC13: =AC12/AC$19 -> 0.057442866 | AD13: =AD12/AD$19 -> 0.054711506 | AE13: =AE12/AE$19 -> 0.064114307 | AF13: =AF12/AF$19 -> 0.032143928 | ... AK13: =AK12/AK$19 -> 0.010878122
A14: OEM & Other | B14: 77 | C14: 66 | D14: 73 | E14: 90 | F14: 78 | G14: 88 | H14: 97 | I14: 126 | J14: 111 | K14: 173 | L14: 174 | M14: 161 | Y14: 1532 | Z14: 1329 | AA14: 783 | AB14: 698 | AC14: 777 | AD14: 767 | AE14: 505 | AF14: 631 | AG14: 1162 | AH14: 455 | AI14: =SUM(B14:E14) -> 306 | AJ14: =SUM(F14:I14) -> 389 | AK14: =SUM(J14:M14) -> 619
A15: % | F15: =+F14/B14-1 -> 0.012987013 | G15: =+G14/C14-1 -> 0.33333333 | H15: =+H14/D14-1 -> 0.32876712 | I15: =+I14/E14-1 -> 0.4 | J15: =+J14/F14-1 -> 0.42307692 | K15: =+K14/G14-1 -> 0.96590909 | L15: =+L14/H14-1 -> 0.79381443 | M15: =+M14/I14-1 -> 0.27777778 | Y15: =Y14/Y$19 -> 0.37094431 | Z15: =Z14/Z$19 -> 0.28385305 | AA15: =AA14/AA$19 -> 0.15628743 | AB15: =AB14/AB$19 -> 0.10101302 | AC15: =AC14/AC$19 -> 0.079987647 | AD15: =AD14/AD$19 -> 0.065466029 | AE15: =AE14/AE$19 -> 0.046253893 | AF15: =AF14/AF$19 -> 0.037841079 | ... AK15: =AK14/AK$19 -> 0.0028665636
A16: Edge Computing | K16: =+K14+K12+K10+K8 -> 5647 | L16: =+L14+L12+L10+L8 -> 5791 | M16: =+M14+M12+M10+M8 -> 5813 | N16: 6369 | O16: 7198
O17: =+O16/K16-1 -> 0.27465911
A19: Revenue | B19: =+B14+B12+B10+B8+B3 -> 7192 | C19: =+C14+C12+C10+C8+C3 -> 13507 | D19: =+D14+D12+D10+D8+D3 -> 18120 | E19: =+E14+E12+E10+E8+E3 -> 22103 | F19: =+F14+F12+F10+F8+F3 -> 26044 | G19: =+G14+G12+G10+G8+G3 -> 30040 | H19: =+H14+H12+H10+H8+H3 -> 35085 | I19: =+I14+I12+I10+I8+I3 -> 39331 | ... M19: =+M14+M12+M10+M8+M3 -> 68127 | N19: 81615 | O19: =+O16+O3 -> 96221 | P19: =+L19*1.9 -> 108311.4 | Q19: =+M19*1.9 -> 129441.3 | V19: 3543.309 | W19: 3997.93 | X19: 4280.159 | Y19: =+Y14+Y12+Y10+Y8+Y3 -> 4130 | Z19: =+Z14+Z12+Z10+Z8+Z3 -> 4682 | AA19: =+AA14+AA12+AA10+AA8+AA3 -> 5010 | AB19: =+AB14+AB12+AB10+AB8+AB3 -> 6910 | AC19: =+AC14+AC12+AC10+AC8+AC3 -> 9714 | AD19: =+AD14+AD12+AD10+AD8+AD3 -> 11716 | AE19: =+AE14+AE12+AE10+AE8+AE3 -> 10918 | AF19: =+AF14+AF12+AF10+AF8+AF3 -> 16675 | ... AJ19: =+AJ14+AJ12+AJ10+AJ8+AJ3 -> 130497 | AK19: 215938 | AL19: =+AK19*1.9 -> 410282.2 | AM19: =+AL19*1.8 -> 738507.96 | AN19: =+AM19*1.4 -> 1033911.1 | AO19: =+AN19*1.2 -> 1240693.4 | AP19: =+AO19*1.2 -> 1488832
F20: =+F19/B19-1 -> 2.6212458 | G20: =+G19/C19-1 -> 1.224032 | H20: =+H19/D19-1 -> 0.93625828 | I20: =+I19/E19-1 -> 0.7794417 | J20: =+J19/F19-1 -> 0.88189218 | K20: =+K19/G19-1 -> 0.5560253 | L20: =+L19/H19-1 -> 0.62479692 | M20: =+M19/I19-1 -> 0.73214513 | ... Q20: =+Q19/M19-1 -> 0.9
A21: COGS | B21: 2544 | C21: 4045 | D21: 4720 | E21: 5312 | F21: 5638 | G21: 7466 | H21: 8926 | I21: 10608 | J21: 17394 | K21: 12890 | L21: 15157 | M21: 17034 | N21: 20458 | O21: 24079 | P21: =+P19*0.25 -> 27077.85 | Q21: =+Q19*0.25 -> 32360.325 | V21: 2134.219 | W21: 1941.413 | X21: 2053.816 | Y21: 1862 | Z21: 2083 | AA21: 2199 | AB21: 2847 | AC21: 3892 | AD21: 4545 | AE21: 4150 | AF21: 6279 | AG21: 9439 | AH21: 11618 | AI21: =SUM(B21:E21) -> 16621 | AJ21: =SUM(F21:I21) -> 32638 | AK21: =SUM(J21:M21) -> 62475 | AL21: =+AL19-AL23 -> 114879.02 | AM21: =+AM19-AM23 -> 203089.69 | AN21: =+AN19-AN23 -> 279156.01 | AO21: =+AO19-AO23 -> 328783.74 | AP21: =+AP19-AP23 -> 387096.33
B22: =+B21/B$19 -> 0.35372636 | C22: =+C21/C$19 -> 0.29947435 | D22: =+D21/D$19 -> 0.26048565 | E22: =+E21/E$19 -> 0.24032937 | F22: =+F21/F$19 -> 0.2164798 | G22: =+G21/G$19 -> 0.24853529 | H22: =+H21/H$19 -> 0.25441072 | I22: =+I21/I$19 -> 0.26971092 | ... Q22: =+Q21/Q$19 -> 0.25 | V22: =+V21/V$19 -> 0.6023237 | W22: =+W21/W$19 -> 0.48560455 | X22: =+X21/X$19 -> 0.47984573 | Y22: =+Y21/Y$19 -> 0.45084746 | Z22: =+Z21/Z$19 -> 0.44489534 | AA22: =+AA21/AA$19 -> 0.43892216 | AB22: =+AB21/AB$19 -> 0.41201158 | AC22: =+AC21/AC$19 -> 0.40065884 | ... AP22: =+AP21/AP$19 -> 0.26
A23: Gross Profit | B23: =B19-B21 -> 4648 | C23: =C19-C21 -> 9462 | D23: =D19-D21 -> 13400 | E23: =E19-E21 -> 16791 | F23: =F19-F21 -> 20406 | G23: =G19-G21 -> 22574 | H23: =H19-H21 -> 26159 | I23: =I19-I21 -> 28723 | ... Q23: =Q19-Q21 -> 97080.975 | V23: =V19-V21 -> 1409.09 | W23: =W19-W21 -> 2056.517 | X23: =X19-X21 -> 2226.343 | Y23: =Y19-Y21 -> 2268 | Z23: =Z19-Z21 -> 2599 | AA23: =AA19-AA21 -> 2811 | AB23: =AB19-AB21 -> 4063 | AC23: =AC19-AC21 -> 5822 | ... AK23: =AK19-AK21 -> 153463 | AL23: =+AL19*0.72 -> 295403.18 | AM23: =+AM19*0.725 -> 535418.27 | AN23: =+AN19*0.73 -> 754755.14 | AO23: =+AO19*0.735 -> 911909.63 | AP23: =+AP19*0.74 -> 1101735.7
B24: =+B23/B$19 -> 0.64627364 | C24: =+C23/C$19 -> 0.70052565 | D24: =+D23/D$19 -> 0.73951435 | E24: =+E23/E$19 -> 0.75967063 | F24: =+F23/F$19 -> 0.7835202 | G24: =+G23/G$19 -> 0.75146471 | H24: =+H23/H$19 -> 0.74558928 | I24: =+I23/I$19 -> 0.73028908 | ... Q24: =+Q23/Q$19 -> 0.75 | V24: =+V23/V$19 -> 0.3976763 | W24: =+W23/W$19 -> 0.51439545 | X24: =+X23/X$19 -> 0.52015427 | Y24: =+Y23/Y$19 -> 0.54915254 | Z24: =+Z23/Z$19 -> 0.55510466 | AA24: =+AA23/AA$19 -> 0.56107784 | AB24: =+AB23/AB$19 -> 0.58798842 | AC24: =+AC23/AC$19 -> 0.59934116 | ... AP24: =+AP23/AP$19 -> 0.74
A25: R&D | B25: 1875 | C25: 2040 | D25: 2294 | E25: 2465 | F25: 2720 | G25: 3090 | H25: 3390 | I25: 3714 | J25: 3989 | K25: 4291 | L25: 4705 | M25: 5512 | N25: 6321 | O25: 7054 | P25: =+P19*0.07 -> 7581.798 | Q25: =+Q19*0.07 -> 9060.891 | V25: 848.83 | W25: 1002.605 | X25: 1147.282 | Y25: 1336 | Z25: 1360 | AA25: 1331 | AB25: 1463 | AC25: 1797 | AD25: 2376 | AE25: 2829 | AF25: 3924 | AG25: 5268 | AH25: 7339 | AI25: =SUM(B25:E25) -> 8674 | AJ25: =SUM(F25:I25) -> 12914 | AK25: =SUM(J25:M25) -> 18497 | AL25: =+AL19*0.1 -> 41028.22 | AM25: =+AM19*0.1 -> 73850.796 | AN25: =+AN19*0.1 -> 103391.11 | AO25: =+AO19*0.1 -> 124069.34 | AP25: =+AP19*0.1 -> 148883.2
B26: =+B25/B$19 -> 0.26070634 | C26: =+C25/C$19 -> 0.1510328 | D26: =+D25/D$19 -> 0.12660044 | E26: =+E25/E$19 -> 0.11152332 | F26: =+F25/F$19 -> 0.10443864 | G26: =+G25/G$19 -> 0.10286285 | H26: =+H25/H$19 -> 0.096622488 | I26: =+I25/I$19 -> 0.094429331 | ... Q26: =+Q25/Q$19 -> 0.07 | V26: =+V25/V$19 -> 0.23955856 | W26: =+W25/W$19 -> 0.25078103 | X26: =+X25/X$19 -> 0.26804658 | Y26: =+Y25/Y$19 -> 0.32348668 | Z26: =+Z25/Z$19 -> 0.29047416 | AA26: =+AA25/AA$19 -> 0.26566866 | AB26: =+AB25/AB$19 -> 0.21172214 | AC26: =+AC25/AC$19 -> 0.18499074 | ... AP26: =+AP25/AP$19 -> 0.1
A27: SG&A | B27: 633 | C27: 622 | D27: 689 | E27: 711 | F27: 777 | G27: 842 | H27: 897 | I27: 975 | J27: 1041 | K27: 1122 | L27: 1134 | M27: 1282 | N27: 1300 | O27: 1354 | P27: =+P19*0.015 -> 1624.671 | Q27: =+Q19*0.015 -> 1941.6195 | V27: =+361.513-57 -> 304.513 | W27: 405.613 | X27: 430.822 | Y27: 436 | Z27: 480 | AA27: =+602+131 -> 733 | AB27: =+663+3 -> 666 | AC27: 815 | AD27: 991 | AE27: 1093 | AF27: 1940 | AG27: 2166 | AH27: =+2440+1353 -> 3793 | AI27: =SUM(B27:E27) -> 2655 | AJ27: =SUM(F27:I27) -> 3491 | AK27: =SUM(J27:M27) -> 4579 | AL27: =+AL19*0.02 -> 8205.644 | AM27: =+AM19*0.02 -> 14770.159 | AN27: =+AN19*0.02 -> 20678.223 | AO27: =+AO19*0.02 -> 24813.867 | AP27: =+AP19*0.02 -> 29776.641
B28: =+B27/B$19 -> 0.088014461 | C28: =+C27/C$19 -> 0.046050196 | D28: =+D27/D$19 -> 0.038024283 | E28: =+E27/E$19 -> 0.032167579 | F28: =+F27/F$19 -> 0.029834127 | G28: =+G27/G$19 -> 0.028029294 | H28: =+H27/H$19 -> 0.025566481 | I28: =+I27/I$19 -> 0.024789606 | ... Q28: =+Q27/Q$19 -> 0.015 | V28: =+V27/V$19 -> 0.085940289 | W28: =+W27/W$19 -> 0.10145575 | X28: =+X27/X$19 -> 0.10065561 | Y28: =+Y27/Y$19 -> 0.10556901 | Z28: =+Z27/Z$19 -> 0.10252029 | AA28: =+AA27/AA$19 -> 0.14630739 | AB28: =+AB27/AB$19 -> 0.096382055 | AC28: =+AC27/AC$19 -> 0.083899526 | ... AP28: =+AP27/AP$19 -> 0.02
A29: Op Exp | B29: =+B27+B25 -> 2508 | C29: =+C27+C25 -> 2662 | D29: =+D27+D25 -> 2983 | E29: =+E27+E25 -> 3176 | F29: =+F27+F25 -> 3497 | G29: =+G27+G25 -> 3932 | H29: =+H27+H25 -> 4287 | I29: =+I27+I25 -> 4689 | ... Q29: =+Q27+Q25 -> 11002.511 | V29: =+V27+V25 -> 1153.343 | W29: =+W27+W25 -> 1408.218 | X29: =+X27+X25 -> 1578.104 | Y29: =+Y27+Y25 -> 1772 | Z29: =+Z27+Z25 -> 1840 | AA29: =+AA27+AA25 -> 2064 | AB29: =+AB27+AB25 -> 2129 | AC29: =+AC27+AC25 -> 2612 | ... AP29: =+AP27+AP25 -> 178659.85
B30: =+B29/B$19 -> 0.3487208 | C30: =+C29/C$19 -> 0.19708299 | D30: =+D29/D$19 -> 0.16462472 | E30: =+E29/E$19 -> 0.1436909 | F30: =+F29/F$19 -> 0.13427277 | G30: =+G29/G$19 -> 0.13089214 | H30: =+H29/H$19 -> 0.12218897 | I30: =+I29/I$19 -> 0.11921894 | ... Q30: =+Q29/Q$19 -> 0.085 | V30: =+V29/V$19 -> 0.32549885 | W30: =+W29/W$19 -> 0.35223678 | X30: =+X29/X$19 -> 0.36870219 | Y30: =+Y29/Y$19 -> 0.42905569 | Z30: =+Z29/Z$19 -> 0.39299445 | AA30: =+AA29/AA$19 -> 0.41197605 | AB30: =+AB29/AB$19 -> 0.3081042 | AC30: =+AC29/AC$19 -> 0.26889026 | ... AP30: =+AP29/AP$19 -> 0.12
A31: Op Inc | B31: =B23-B29 -> 2140 | C31: =C23-C29 -> 6800 | D31: =D23-D29 -> 10417 | E31: =E23-E29 -> 13615 | F31: =F23-F29 -> 16909 | G31: =G23-G29 -> 18642 | H31: =H23-H29 -> 21872 | I31: =I23-I29 -> 24034 | ... Q31: =Q23-Q29 -> 86078.465 | V31: =V23-V29 -> 255.747 | W31: =W23-W29 -> 648.299 | X31: =X23-X29 -> 648.239 | Y31: =Y23-Y29 -> 496 | Z31: =Z23-Z29 -> 759 | AA31: =AA23-AA29 -> 747 | AB31: =AB23-AB29 -> 1934 | AC31: =AC23-AC29 -> 3210 | ... AP31: =AP23-AP29 -> 923075.87
B32: =+B31/B$19 -> 0.29755284 | C32: =+C31/C$19 -> 0.50344266 | D32: =+D31/D$19 -> 0.57488962 | E32: =+E31/E$19 -> 0.61597973 | F32: =+F31/F$19 -> 0.64924743 | G32: =+G31/G$19 -> 0.62057257 | H32: =+H31/H$19 -> 0.62340031 | I32: =+I31/I$19 -> 0.61107015 | ... Q32: =+Q31/Q$19 -> 0.665 | V32: =+V31/V$19 -> 0.072177448 | W32: =+W31/W$19 -> 0.16215867 | X32: =+X31/X$19 -> 0.15145208 | Y32: =+Y31/Y$19 -> 0.12009685 | Z32: =+Z31/Z$19 -> 0.16211021 | AA32: =+AA31/AA$19 -> 0.1491018 | AB32: =+AB31/AB$19 -> 0.27988423 | AC32: =+AC31/AC$19 -> 0.3304509 | ... AP32: =+AP31/AP$19 -> 0.62
A33: Int Income | B33: 150 | C33: 187 | D33: 234 | E33: 294 | F33: 359 | G33: 444 | H33: 472 | I33: 511 | J33: 515 | K33: 592 | L33: 624 | M33: 568 | N33: 540 | V33: 19.057 | W33: 19.149 | X33: 19.908 | Y33: 17 | Z33: 28 | AA33: 39 | AB33: 54 | AC33: 69 | AD33: 136 | AE33: 178 | AF33: 57 | AG33: 29 | AH33: 267 | AI33: =SUM(B33:E33) -> 865 | AJ33: =SUM(F33:I33) -> 1786 | AK33: =SUM(J33:M33) -> 2299 | AL33: =+AL19*0.01 -> 4102.822 | AM33: =+AM19*0.01 -> 7385.0796 | AN33: =+AN19*0.01 -> 10339.111 | AO33: =+AO19*0.01 -> 12406.934 | AP33: =+AP19*0.01 -> 14888.32
B34: =+B33/B$19 -> 0.020856507 | C34: =+C33/C$19 -> 0.013844673 | D34: =+D33/D$19 -> 0.012913907 | E34: =+E33/E$19 -> 0.013301362 | F34: =+F33/F$19 -> 0.013784365 | G34: =+G33/G$19 -> 0.014780293 | H34: =+H33/H$19 -> 0.013453043 | I34: =+I33/I$19 -> 0.012992296 | ... N34: =+N33/N$19 -> 0.0066164308 | V34: =+V33/V$19 -> 0.005378306 | W34: =+W33/W$19 -> 0.0047897287 | X34: =+X33/X$19 -> 0.0046512291 | Y34: =+Y33/Y$19 -> 0.0041162228 | Z34: =+Z33/Z$19 -> 0.0059803503 | AA34: =+AA33/AA$19 -> 0.0077844311 | AB34: =+AB33/AB$19 -> 0.0078147612 | AC34: =+AC33/AC$19 -> 0.0071031501 | ... AP34: =+AP33/AP$19 -> 0.01
A35: Int Exp | B35: -66 | C35: -65 | D35: -63 | E35: -63 | F35: -64 | G35: -61 | H35: -61 | I35: -61 | J35: -63 | K35: -62 | L35: -61 | M35: -74 | N35: -102 | V35: -3.127 | W35: -3.089 | X35: -3.294 | Y35: -10 | Z35: -46 | AA35: -47 | AB35: -58 | AC35: -61 | AD35: -58 | AE35: -52 | AF35: -184 | AG35: -236 | AH35: -262 | AI35: =SUM(B35:E35) -> -257 | AJ35: =SUM(F35:I35) -> -247 | AK35: =SUM(J35:M35) -> -260 | AL35: -300 | AM35: -300 | AN35: -300 | AO35: -300 | AP35: -300
B36: =+B35/B$19 -> -0.0091768632 | C36: =+C35/C$19 -> -0.0048123195 | D36: =+D35/D$19 -> -0.0034768212 | E36: =+E35/E$19 -> -0.0028502918 | F36: =+F35/F$19 -> -0.0024573798 | G36: =+G35/G$19 -> -0.0020306258 | H36: =+H35/H$19 -> -0.0017386347 | I36: =+I35/I$19 -> -0.0015509395 | ... N36: =+N35/N$19 -> -0.0012497703 | V36: =+V35/V$19 -> -0.00088250841 | W36: =+W35/W$19 -> -0.00077264985 | X36: =+X35/X$19 -> -0.00076959758 | Y36: =+Y35/Y$19 -> -0.0024213075 | Z36: =+Z35/Z$19 -> -0.0098248612 | AA36: =+AA35/AA$19 -> -0.0093812375 | AB36: =+AB35/AB$19 -> -0.0083936324 | AC36: =+AC35/AC$19 -> -0.0062795965 | ... AP36: =+AP35/AP$19 -> -0.00020150023
A37: Other Income | B37: -15 | C37: 59 | D37: -66 | E37: 260 | F37: 75 | G37: 189 | H37: 36 | I37: 733 | J37: -180 | K37: 2236 | L37: 1363 | M37: 5604 | N37: 15929 | O37: 7773 | P37: =+P19*0.08 -> 8664.912 | Q37: =+Q19*0.08 -> 10355.304 | V37: -0.508 | W37: -0.963 | X37: -2.814 | Y37: 7 | Z37: 14 | AA37: 4 | AB37: -25 | AC37: -22 | AD37: 14 | AE37: -2 | AF37: 4 | AG37: 107 | AH37: -48 | AI37: =SUM(B37:E37) -> 238 | AJ37: =SUM(F37:I37) -> 1033 | AK37: =SUM(J37:M37) -> 9023 | AL37: 30000 | AM37: =+AM19*0.01 -> 7385.0796 | AN37: =+AN19*0.01 -> 10339.111 | AO37: =+AO19*0.01 -> 12406.934 | AP37: =+AP19*0.01 -> 14888.32
B38: =+B37/B$19 -> -0.0020856507 | C38: =+C37/C$19 -> 0.0043681054 | D38: =+D37/D$19 -> -0.0036423841 | E38: =+E37/E$19 -> 0.011763109 | F38: =+F37/F$19 -> 0.002879742 | G38: =+G37/G$19 -> 0.0062916112 | H38: =+H37/H$19 -> 0.0010260795 | I38: =+I37/I$19 -> 0.018636699 | ... Q38: =+Q37/Q$19 -> 0.08 | V38: =+V37/V$19 -> -0.00014336881 | W38: =+W37/W$19 -> -0.00024087465 | X38: =+X37/X$19 -> -0.00065745221 | Y38: =+Y37/Y$19 -> 0.0016949153 | Z38: =+Z37/Z$19 -> 0.0029901751 | AA38: =+AA37/AA$19 -> 0.00079840319 | AB38: =+AB37/AB$19 -> -0.003617945 | AC38: =+AC37/AC$19 -> -0.0022647725 | ... AP38: =+AP37/AP$19 -> 0.01
A39: Pretax | B39: =SUM(B31:B37) -> 2209.3092 | C39: =SUM(C31:C37) -> 6981.5125 | D39: =SUM(D31:D37) -> 10522.584 | E39: =SUM(E31:E37) -> 14106.626 | F39: =SUM(F31:F37) -> 17279.661 | G39: =SUM(G31:G37) -> 19214.633 | H39: =SUM(H31:H37) -> 22319.635 | I39: =SUM(I31:I37) -> 25217.623 | ... Q39: =SUM(Q31:Q37) -> 96434.433 | V39: =SUM(V31:V37)-V32-V34-V36 -> 271.169 | W39: =SUM(W31:W37)-W32-W34-W36 -> 663.396 | X39: =SUM(X31:X37)-X32-X34-X36 -> 662.039 | Y39: =SUM(Y31:Y37)-Y32-Y34-Y36 -> 510 | Z39: =SUM(Z31:Z37)-Z32-Z34-Z36 -> 755 | AA39: =SUM(AA31:AA37)-AA32-AA34-AA36 -> 743 | AB39: =SUM(AB31:AB37)-AB32-AB34-AB36 -> 1905 | AC39: =SUM(AC31:AC37)-AC32-AC34-AC36 -> 3196 | ... AP39: =SUM(AP31:AP37)-AP32-AP34-AP36 -> 952552.51
B40: =+B39/B$19 -> 0.30718983 | C40: =+C39/C$19 -> 0.51688106 | D40: =+D39/D$19 -> 0.58071657 | E40: =+E39/E$19 -> 0.63822225 | F40: =+F39/F$19 -> 0.66347952 | G40: =+G39/G$19 -> 0.63963493 | H40: =+H39/H$19 -> 0.6361589 | I40: =+I39/I$19 -> 0.64116403 | ... Q40: =+Q39/Q$19 -> 0.74500514 | V40: =+V39/V$19 -> 0.076529876 | W40: =+W39/W$19 -> 0.16593487 | X40: =+X39/X$19 -> 0.15467626 | Y40: =+Y39/Y$19 -> 0.12348668 | Z40: =+Z39/Z$19 -> 0.16125587 | AA40: =+AA39/AA$19 -> 0.14830339 | AB40: =+AB39/AB$19 -> 0.27568741 | AC40: =+AC39/AC$19 -> 0.32900968 | ... AP40: =+AP39/AP$19 -> 0.6397985
A41: Tax | B41: 166 | C41: 793 | D41: 1279 | E41: 1821 | F41: 2398 | G41: 2615 | H41: 3007 | I41: 3126 | J41: 3135 | K41: 4784 | L41: 6026 | M41: 7437 | N41: 11582 | O41: 11819 | V41: 18.023 | W41: 82.306 | X41: 99.503 | Y41: 70 | Z41: 124 | AA41: 129 | AB41: 239 | AC41: 149 | AD41: -245 | AE41: 174 | AF41: 77 | AG41: 189 | AH41: -187 | AI41: =SUM(B41:E41) -> 4059 | AJ41: =SUM(F41:I41) -> 11146 | AK41: =SUM(J41:M41) -> 21382 | AL41: =+AL39*0.13 -> 36396.378 | AM41: =+AM39*0.13 -> 59964.772 | AN41: =+AN39*0.13 -> 84638.323 | AO41: =+AO39*0.13 -> 102380.24 | AP41: =+AP39*0.13 -> 123831.83
B42: =+B41/B$19 -> 0.023081201 | C42: =+C41/C$19 -> 0.058710298 | D42: =+D41/D$19 -> 0.070584989 | E42: =+E41/E$19 -> 0.082387006 | F42: =+F41/F$19 -> 0.09207495 | G42: =+G41/G$19 -> 0.087050599 | H42: =+H41/H$19 -> 0.085706142 | I42: =+I41/I$19 -> 0.079479291 | ... Q42: =+Q41/Q$19 -> 0 | V42: =+V41/V$19 -> 0.0050864884 | W42: =+W41/W$19 -> 0.020587154 | X42: =+X41/X$19 -> 0.023247501 | Y42: =+Y41/Y$19 -> 0.016949153 | Z42: =+Z41/Z$19 -> 0.026484408 | AA42: =+AA41/AA$19 -> 0.025748503 | AB42: =+AB41/AB$19 -> 0.034587554 | AC42: =+AC41/AC$19 -> 0.015338686 | ... AP42: =+AP41/AP$19 -> 0.083173805
A43: Net Inc | B43: =B39-B41 -> 2043.3092 | C43: =C39-C41 -> 6188.5125 | D43: =D39-D41 -> 9243.5843 | E43: =E39-E41 -> 12285.626 | F43: =F39-F41 -> 14881.661 | G43: =G39-G41 -> 16599.633 | H43: =H39-H41 -> 19312.635 | I43: =I39-I41 -> 22091.623 | ... Q43: =Q39-Q41 -> 96434.433 | V43: =V39-V41 -> 253.146 | W43: =W39-W41 -> 581.09 | X43: =X39-X41 -> 562.536 | Y43: =Y39-Y41 -> 440 | Z43: =Z39-Z41 -> 631 | AA43: =AA39-AA41 -> 614 | AB43: =AB39-AB41 -> 1666 | AC43: =AC39-AC41 -> 3047 | ... AP43: =AP39-AP41 -> 828720.68 | AQ43: =+AP43*(1+AT52) -> 853582.3 | AR43: =+AQ43*(1+$AT$52) -> 879189.77 | AS43: =+AR43*(1+$AT$52) -> 905565.47 | AT43: =+AS43*(1+$AT$52) -> 932732.43 | AU43: =+AT43*(1+$AT$52) -> 960714.4 | AV43: =+AU43*(1+$AT$52) -> 989535.84 | AW43: =+AV43*(1+$AT$52) -> 1019221.9 | AX43: =+AW43*(1+$AT$52) -> 1049798.6 | AY43: =+AX43*(1+$AT$52) -> 1081292.5 | ... DJ43: =+DI43*(1+$AT$52) -> 6961268.1
B44: =+B43/B$19 -> 0.28410863 | C44: =+C43/C$19 -> 0.45817076 | D44: =+D43/D$19 -> 0.51013159 | E44: =+E43/E$19 -> 0.55583525 | F44: =+F43/F$19 -> 0.57140457 | G44: =+G43/G$19 -> 0.55258433 | H44: =+H43/H$19 -> 0.55045276 | I44: =+I43/I$19 -> 0.56168474 | ... Q44: =+Q43/Q$19 -> 0.74500514 | V44: =+V43/V$19 -> 0.071443388 | W44: =+W43/W$19 -> 0.14534772 | X44: =+X43/X$19 -> 0.13142876 | Y44: =+Y43/Y$19 -> 0.10653753 | Z44: =+Z43/Z$19 -> 0.13477147 | AA44: =+AA43/AA$19 -> 0.12255489 | AB44: =+AB43/AB$19 -> 0.24109986 | AC44: =+AC43/AC$19 -> 0.31367099 | ... AP44: =+AP43/AP$19 -> 0.55662469
A45: EPS | B45: =B43/B47 -> 0.82060612 | C45: =C43/C47 -> 0.24759992 | D45: =D43/D47 -> 0.37063289 | E45: =E43/E47 -> 0.49339865 | F45: =F43/F47 -> 0.59789717 | G45: =G43/G47 -> 0.66804706 | H45: =H43/H47 -> 0.77955256 | I45: =I43/I47 -> 0.89418046 | ... Q45: =Q43/Q47 -> 3.9709464 | V45: =V43/V47 -> 0.43002018 | W45: =W43/W47 -> 0.94276012 | X45: =X43/X47 -> 0.90011953 | Y45: =Y43/Y47 -> 0.7394958 | Z45: =Z43/Z47 -> 1.1207815 | AA45: =AA43/AA47 -> 1.0790861 | AB45: =AB43/AB47 -> 2.5670262 | AC45: =AC43/AC47 -> 4.8212025 | ... AP45: =AP43/AP47 -> 76.71252
F46: =+F45/B45-1 -> -0.27139567 | G46: =+G45/C45-1 -> 1.6980907 | H46: =+H45/D45-1 -> 1.1033011 | I46: =+I45/E45-1 -> 0.81228801 | J46: =+J45/F45-1 -> 0.6123546 | K46: =+K45/G45-1 -> 0.61226291 | L46: =+L45/H45-1 -> 0.67195853 | M46: =+M45/I45-1 -> 0.96646727 | ... Q46: =+Q45/M45-1 -> 1.2583026
A47: Shares | B47: 2490 | C47: 24994 | D47: 24940 | E47: 24900 | F47: 24890 | G47: 24848 | H47: 24774 | I47: 24706 | J47: 24611 | K47: 24532 | L47: 24483 | M47: 24432 | N47: 24391 | O47: 24285 | P47: 24285 | Q47: 24285 | V47: 588.684 | W47: 616.371 | X47: 624.957 | Y47: 595 | Z47: 563 | AA47: 569 | AB47: 649 | AC47: 632 | AD47: 625 | AE47: 618 | AF47: 628 | AG47: 2535 | AH47: 2507 | AI47: 24940 | AJ47: =AVERAGE(F47:I47) -> 24804.5 | AK47: =AVERAGE(J47:M47) -> 24514.5 | AL47: =+AK47*(1-$AK$64) -> 20808.79 | AM47: =+AL47*(1-$AK$64) -> 17663.249 | AN47: =+AM47*(1-$AK$64) -> 14993.201 | AO47: =+AN47*(1-$AK$64) -> 12726.769 | AP47: =+AO47*(1-$AK$64) -> 10802.939
C48: =+C47/B47-1 -> 9.037751 | D48: =+D47/C47-1 -> -0.0021605185 | E48: =+E47/D47-1 -> -0.0016038492 | F48: =+F47/E47-1 -> -0.00040160643 | G48: =+G47/F47-1 -> -0.0016874247 | H48: =+H47/G47-1 -> -0.0029781069 | I48: =+I47/H47-1 -> -0.0027448131 | J48: =+J47/I47-1 -> -0.0038452198 | ... Q48: =+Q47/P47-1 -> 0
A50: Revenue Y/Y | B50: 0 | C50: 0 | D50: 0 | E50: 0 | F50: =F19/B19-1 -> 2.6212458 | G50: =G19/C19-1 -> 1.224032 | H50: =H19/D19-1 -> 0.93625828 | I50: =I19/E19-1 -> 0.7794417 | J50: =J19/F19-1 -> 0.88189218 | K50: =K19/G19-1 -> 0.5560253 | L50: =L19/H19-1 -> 0.62479692 | M50: =M19/I19-1 -> 0.73214513 | ... Q50: =Q19/M19-1 -> 0.9 | W50: =W19/V19-1 -> 0.12830408 | X50: =X19/W19-1 -> 0.070593782 | Y50: =Y19/X19-1 -> -0.035082575 | Z50: =Z19/Y19-1 -> 0.13365617 | AA50: =AA19/Z19-1 -> 0.070055532 | AB50: =AB19/AA19-1 -> 0.37924152 | AC50: =AC19/AB19-1 -> 0.40578871 | AD50: =AD19/AC19-1 -> 0.2060943 | ... AP50: =AP19/AO19-1 -> 0.2
A51: Revenue q/q | B51: 0 | C51: =C19/B19-1 -> 0.87805895 | D51: =D19/C19-1 -> 0.34152662 | E51: =E19/D19-1 -> 0.21981236 | F51: =F19/E19-1 -> 0.17830159 | G51: =G19/F19-1 -> 0.15343265 | H51: =H19/G19-1 -> 0.16794274 | I51: =I19/H19-1 -> 0.12102038 | J51: =J19/I19-1 -> 0.24614172 | ... Q51: =Q19/P19-1 -> 0.19508473 | W51: 0 | X51: 0 | Y51: 0 | Z51: 0 | AA51: 0 | AB51: 0 | AC51: 0 | AD51: 0 | AE51: 0 | AF51: 0 | AG51: 0 | AH51: 0 | AI51: 0 | AJ51: 0 | AK51: 0
A52: Revenue h/h | B52: 0 | C52: 0 | D52: 0 | E52: =((E43+D43)/(C43+B43))-1 -> 1.6153641 | F52: =((F43+E43)/(D43+C43))-1 -> 0.76044042 | G52: =((G43+F43)/(E43+D43))-1 -> 0.46225954 | H52: =((H43+G43)/(F43+E43))-1 -> 0.32189381 | I52: =((I43+H43)/(G43+F43))-1 -> 0.3152019 | J52: =((J43+I43)/(H43+G43))-1 -> 0.27580841 | K52: =((K43+J43)/(I43+H43))-1 -> 0.21118393 | L52: =((L43+K43)/(J43+I43))-1 -> 0.27317458 | ... Q52: =((Q43+P43)/(O43+N43))-1 -> 0.50094573 | W52: 0 | X52: 0 | Y52: 0 | Z52: 0 | AA52: 0 | AB52: 0 | AC52: 0 | AD52: 0 | AE52: 0 | AF52: 0 | AG52: 0 | AH52: 0 | AI52: 0 | AJ52: 0 | AK52: 0 | AS52: Terminal | AT52: 0.03
A53: Data Center Y/Y | B53: 0 | C53: 0 | D53: 0 | E53: 0 | F53: =F3/B3-1 -> 4.2668067 | G53: =G3/C3-1 -> 1.5449966 | H53: =H3/D3-1 -> 1.1200909 | I53: =I3/E3-1 -> 0.93327537 | J53: =J3/F3-1 -> 0.95284315 | K53: =K3/G3-1 -> 0.56425091 | L53: =L3/H3-1 -> 0.6643918 | M53: =M3/I3-1 -> 0.75137718 | N53: =N3/J3-1 -> 0.70668603 | Z53: =Z3/Y3-1 -> 0.59296482 | AA53: =AA3/Z3-1 -> 0.069400631 | AB53: =AB3/AA3-1 -> 1.4483776 | AC53: =AC3/AB3-1 -> 1.3277108 | AD53: =AD3/AC3-1 -> 0.51759834 | AE53: =AE3/AD3-1 -> 0.01739427 | AF53: =AF3/AE3-1 -> 1.2447201 | AG53: =AG3/AF3-1 -> 0.58497611 | ... AK53: =AK3/AJ3-1 -> 0.6819492 | AS53: Discount | AT53: 0.16
A54: Gaming Y/Y | B54: 0 | C54: 0 | D54: 0 | E54: 0 | F54: =F8/B8-1 -> 0.18169643 | G54: =G8/C8-1 -> 0.15848753 | H54: =H8/D8-1 -> 0.14810924 | I54: =I8/E8-1 -> -0.11204188 | J54: =J8/F8-1 -> 0.42160937 | K54: =K8/G8-1 -> 0.48854167 | L54: =L8/H8-1 -> 0.30070143 | M54: =M8/I8-1 -> 0.46501572 | Z54: =Z8/Y8-1 -> 0.36201191 | AA54: =AA8/Z8-1 -> 0.36929057 | AB54: =AB8/AA8-1 -> 0.44073811 | AC54: =AC8/AB8-1 -> 0.35788177 | AD54: =AD8/AC8-1 -> 0.13295846 | AE54: =AE8/AD8-1 -> -0.11655459 | AF54: =AF8/AE8-1 -> 0.40612541 | AG54: =AG8/AF8-1 -> 0.60613481 | ... AK54: =AK8/AJ8-1 -> 0.41339207 | AS54: ROIC | AT54: 0.02
A55: P.V. Y/Y | B55: 0 | C55: 0 | D55: 0 | E55: 0 | F55: =F10/B10-1 -> 0.44745763 | G55: =G10/C10-1 -> 0.19788918 | H55: =H10/D10-1 -> 0.17548077 | I55: =I10/E10-1 -> 0.10367171 | J55: =J10/F10-1 -> 0.19203747 | K55: =K10/G10-1 -> 0.32378855 | L55: =L10/H10-1 -> 0.55419223 | M55: =M10/I10-1 -> 1.5851272 | Z55: =Z10/Y10-1 -> 0.0076045627 | AA55: =AA10/Z10-1 -> -0.056603774 | AB55: =AB10/AA10-1 -> 0.11333333 | AC55: =AC10/AB10-1 -> 0.11856287 | AD55: =AD10/AC10-1 -> 0.20985011 | AE55: =AE10/AD10-1 -> 0.072566372 | AF55: =AF10/AE10-1 -> -0.13118812 | AG55: =AG10/AF10-1 -> 1.0047483 | ... AK55: =AK10/AJ10-1 -> 0.69914803 | AS55: NPV | AT55: =+NPV(AT53,AL43:DJ43) -> 4769636.1
A56: Auto Y/Y | B56: 0 | C56: 0 | D56: 0 | E56: 0 | F56: =F12/B12-1 -> 0.11148649 | G56: =G12/C12-1 -> 0.36758893 | H56: =H12/D12-1 -> 0.72030651 | I56: =I12/E12-1 -> 1.0284698 | J56: =J12/F12-1 -> 0.72340426 | K56: =K12/G12-1 -> 0.69364162 | L56: =L12/H12-1 -> 0.31848552 | M56: =M12/I12-1 -> 0.059649123 | Z56: =Z12/Y12-1 -> 0.84848485 | AA56: =AA12/Z12-1 -> 0.74863388 | AB56: =AB12/AA12-1 -> 0.521875 | AC56: =AC12/AB12-1 -> 0.14579055 | AD56: =AD12/AC12-1 -> 0.14874552 | AE56: =AE12/AD12-1 -> 0.092043682 | AF56: =AF12/AE12-1 -> -0.23428571 | AG56: =AG12/AF12-1 -> 0.055970149 | ... AK56: =AK12/AJ12-1 -> 0.3866588 | AS56: Share | AT56: =+AT55/Main!F2 -> 197.91021
A57: OEM & Other Y/Y | B57: 0 | C57: 0 | D57: 0 | E57: 0 | F57: =F14/B14-1 -> 0.012987013 | G57: =G14/C14-1 -> 0.33333333 | H57: =H14/D14-1 -> 0.32876712 | I57: =I14/E14-1 -> 0.4 | J57: =J14/F14-1 -> 0.42307692 | K57: =K14/G14-1 -> 0.96590909 | L57: =L14/H14-1 -> 0.79381443 | M57: =M14/I14-1 -> 0.27777778 | Z57: =Z14/Y14-1 -> -0.13250653 | AA57: =AA14/Z14-1 -> -0.41083521 | AB57: =AB14/AA14-1 -> -0.10855683 | AC57: =AC14/AB14-1 -> 0.11318052 | AD57: =AD14/AC14-1 -> -0.012870013 | AE57: =AE14/AD14-1 -> -0.34159061 | AF57: =AF14/AE14-1 -> 0.24950495 | AG57: =AG14/AF14-1 -> 0.84152139 | ... AK57: =AK14/AJ14-1 -> 0.59125964 | AS57: Diff | AT57: =+AT56/Main!F1-1 -> -0.096300398
A58: Inc. Margin | J58: =+((SUM(G31:J31)-SUM(C31:F31))/((SUM(G19:J19)-SUM(C19:F19)))) -> 0.58885391 | K58: =+((SUM(H31:K31)-SUM(D31:G31))/((SUM(H19:K19)-SUM(D19:G19)))) -> 0.55982617 | L58: =+((SUM(I31:L31)-SUM(E31:H31))/((SUM(I19:L19)-SUM(E19:H19)))) -> 0.55866531 | M58: =+((SUM(J31:M31)-SUM(F31:I31))/((SUM(J19:M19)-SUM(F19:I19)))) -> 0.59609683 | N58: =+((SUM(K31:N31)-SUM(G31:J31))/((SUM(K19:N19)-SUM(G19:J19)))) -> 0.71132639 | O58: =+((SUM(L31:O31)-SUM(H31:K31))/((SUM(L19:O19)-SUM(H19:K19)))) -> 0.72775945 | P58: =+((SUM(M31:P31)-SUM(I31:L31))/((SUM(M19:P19)-SUM(I19:L19)))) -> 0.73080729 | Q58: =+((SUM(N31:Q31)-SUM(J31:M31))/((SUM(N19:Q19)-SUM(J19:M19)))) -> 0.71925034
A61: Gross Margin | B61: =B23/B19 -> 0.64627364 | C61: =C23/C19 -> 0.70052565 | D61: =D23/D19 -> 0.73951435 | E61: =E23/E19 -> 0.75967063 | F61: =F23/F19 -> 0.7835202 | G61: =G23/G19 -> 0.75146471 | H61: =H23/H19 -> 0.74558928 | I61: =I23/I19 -> 0.73028908 | ... Q61: =Q23/Q19 -> 0.75 | V61: =V23/V19 -> 0.3976763 | W61: =W23/W19 -> 0.51439545 | X61: =X23/X19 -> 0.52015427 | Y61: =Y23/Y19 -> 0.54915254 | Z61: =Z23/Z19 -> 0.55510466 | AA61: =AA23/AA19 -> 0.56107784 | AB61: =AB23/AB19 -> 0.58798842 | AC61: =AC23/AC19 -> 0.59934116 | ... AP61: =AP23/AP19 -> 0.74
A62: OP Margin | B62: =B31/B19 -> 0.29755284 | C62: =C31/C19 -> 0.50344266 | D62: =D31/D19 -> 0.57488962 | E62: =E31/E19 -> 0.61597973 | F62: =F31/F19 -> 0.64924743 | G62: =G31/G19 -> 0.62057257 | H62: =H31/H19 -> 0.62340031 | I62: =I31/I19 -> 0.61107015 | ... Q62: =Q31/Q19 -> 0.665 | V62: =V31/V19 -> 0.072177448 | W62: =W31/W19 -> 0.16215867 | X62: =X31/X19 -> 0.15145208 | Y62: =Y31/Y19 -> 0.12009685 | Z62: =Z31/Z19 -> 0.16211021 | AA62: =AA31/AA19 -> 0.1491018 | AB62: =AB31/AB19 -> 0.27988423 | AC62: =AC31/AC19 -> 0.3304509 | ... AP62: =AP31/AP19 -> 0.62
A63: NI Margin | B63: =+B43/B19 -> 0.28410863 | C63: =+C43/C19 -> 0.45817076 | D63: =+D43/D19 -> 0.51013159 | E63: =+E43/E19 -> 0.55583525 | F63: =+F43/F19 -> 0.57140457 | G63: =+G43/G19 -> 0.55258433 | H63: =+H43/H19 -> 0.55045276 | I63: =+I43/I19 -> 0.56168474 | ... Q63: =+Q43/Q19 -> 0.74500514 | V63: =V43/V19 -> 0.071443388 | W63: =W43/W19 -> 0.14534772 | X63: =X43/X19 -> 0.13142876 | Y63: =Y43/Y19 -> 0.10653753 | Z63: =Z43/Z19 -> 0.13477147 | AA63: =AA43/AA19 -> 0.12255489 | AB63: =AB43/AB19 -> 0.24109986 | AC63: =AC43/AC19 -> 0.31367099 | ... AP63: =AP43/AP19 -> 0.55662469
A64: Tax Rate | B64: =B41/B39 -> 0.075136607 | C64: =C41/C39 -> 0.1135857 | D64: =D41/D39 -> 0.12154809 | E64: =E41/E39 -> 0.12908827 | F64: =F41/F39 -> 0.13877587 | G64: =G41/G39 -> 0.13609419 | H64: =H41/H39 -> 0.13472442 | I64: =I41/I39 -> 0.12396093 | ... Q64: =Q41/Q39 -> 0 | V64: =V41/V39 -> 0.066464087 | W64: =W41/W39 -> 0.12406768 | X64: =X41/X39 -> 0.15029779 | Y64: =Y41/Y39 -> 0.1372549 | Z64: =Z41/Z39 -> 0.16423841 | AA64: =AA41/AA39 -> 0.17362046 | AB64: =AB41/AB39 -> 0.12545932 | AC64: =AC41/AC39 -> 0.046620776 | ... AP64: =AP41/AP39 -> 0.13
A66: ROA | F66: =+SUM(C43:F43)/AVERAGE(C93:F93) -> 0.69125948 | G66: =+SUM(D43:G43)/AVERAGE(D93:G93) -> 0.75145572 | H66: =+SUM(E43:H43)/AVERAGE(E93:H93) -> 0.77866381 | I66: =+SUM(F43:I43)/AVERAGE(F93:I93) -> 0.78813723 | J66: =+SUM(G43:J43)/AVERAGE(G93:J93) -> 0.78192222 | K66: =+SUM(H43:K43)/AVERAGE(H93:K93) -> 0.77323381 | L66: =+SUM(I43:L43)/AVERAGE(I93:L93) -> 0.77328474 | M66: =+SUM(J43:M43)/AVERAGE(J93:M93) -> 0.78883481 | ... O66: =+SUM(L43:O43)/AVERAGE(L93:O93) -> 0.81410671 | W66: =+SUM(W43)/AVERAGE(V93:W93) -> 0.11566057 | X66: =+SUM(X43)/AVERAGE(W93:X93) -> 0.094028633 | Y66: =+SUM(Y43)/AVERAGE(X93:Y93) -> 0.06440669 | Z66: =+SUM(Z43)/AVERAGE(Y93:Z93) -> 0.087324001 | AA66: =+SUM(AA43)/AVERAGE(Z93:AA93) -> 0.084276795 | AB66: =+SUM(AB43)/AVERAGE(AA93:AB93) -> 0.19359672 | AC66: =+SUM(AC43)/AVERAGE(AB93:AC93) -> 0.2890614 | AD66: =+SUM(AD43)/AVERAGE(AC93:AD93) -> 0.33758583 | ... AK66: =+SUM(AK43)/AVERAGE(AJ93:AK93) -> 0.75418012
A67: ROE | F67: =+F68*F69*F63 -> 1.192607 | G67: =+G68*G69*G63 -> 1.1597943 | H67: =+H68*H69*H63 -> 1.153706 | I67: =+I68*I69*I63 -> 1.1610709 | J67: =+J68*J69*J63 -> 1.0345893 | K67: =+K68*K69*K63 -> 1.1688129 | L67: =+L68*L69*L63 -> 1.1253713 | M67: =+M68*M69*M63 -> 1.2107885 | ... O67: =+O68*O69*O63 -> 1.0729474 | W67: =+W68*W69*W63 -> 0.15861205 | X67: =+X68*X69*X63 -> 0.12537851 | Y67: =+Y68*Y69*Y63 -> 0.094785699 | Z67: =+Z68*Z69*Z63 -> 0.14220683 | AA67: =+AA68*AA69*AA63 -> 0.13683976 | AB67: =+AB68*AB69*AB63 -> 0.32196347 | AC67: =+AC68*AC69*AC63 -> 0.45943908 | AD67: =+AD68*AD69*AD63 -> 0.49259502 | ... AK67: =+AK68*AK69*AK63 -> 1.0148508
A68: A. Turnover | F68: =+SUM(C19:F19)/AVERAGE(C93:F93) -> 1.2944913 | G68: =+SUM(D19:G19)/AVERAGE(D93:G93) -> 1.3652095 | H68: =+SUM(E19:H19)/AVERAGE(E93:H93) -> 1.3982471 | I68: =+SUM(F19:I19)/AVERAGE(F93:I93) -> 1.4111426 | J68: =+SUM(G19:J19)/AVERAGE(G93:J93) -> 1.4682596 | K68: =+SUM(H19:K19)/AVERAGE(H93:K93) -> 1.4372308 | L68: =+SUM(I19:L19)/AVERAGE(I93:L93) -> 1.4262236 | M68: =+SUM(J19:M19)/AVERAGE(J93:M93) -> 1.393736 | ... O68: =+SUM(L19:O19)/AVERAGE(L93:O93) -> 1.2787589 | W68: =+SUM(W19)/AVERAGE(V93:W93) -> 0.79575083 | X68: =+SUM(X19)/AVERAGE(W93:X93) -> 0.71543422 | Y68: =+SUM(Y19)/AVERAGE(X93:Y93) -> 0.60454461 | Z68: =+SUM(Z19)/AVERAGE(Y93:Z93) -> 0.64794132 | AA68: =+SUM(AA19)/AVERAGE(Z93:AA93) -> 0.6876657 | AB68: =+SUM(AB19)/AVERAGE(AA93:AB93) -> 0.80297318 | AC68: =+SUM(AC19)/AVERAGE(AB93:AC93) -> 0.92154331 | AD68: =+SUM(AD19)/AVERAGE(AC93:AD93) -> 0.95512088 | ... AK68: =+SUM(AK19)/AVERAGE(AJ93:AK93) -> 1.3563772
A69: Financial Leverage | F69: =+AVERAGE(C93:F93)/AVERAGE(C109:F109) -> 1.6123321 | G69: =+AVERAGE(D93:G93)/AVERAGE(D109:G109) -> 1.5373865 | H69: =+AVERAGE(E93:H93)/AVERAGE(E109:H109) -> 1.4989638 | I69: =+AVERAGE(F93:I93)/AVERAGE(F109:I109) -> 1.4648569 | J69: =+AVERAGE(G93:J93)/AVERAGE(G109:J109) -> 1.4556308 | K69: =+AVERAGE(H93:K93)/AVERAGE(H109:K109) -> 1.4386634 | L69: =+AVERAGE(I93:L93)/AVERAGE(I109:L109) -> 1.4095914 | M69: =+AVERAGE(J93:M93)/AVERAGE(J109:M109) -> 1.3776412 | ... O69: =+AVERAGE(L93:O93)/AVERAGE(L109:O109) -> 1.3525949 | W69: =+AVERAGE(V93:W93)/AVERAGE(V109:W109) -> 1.3713581 | X69: =+AVERAGE(W93:X93)/AVERAGE(W109:X109) -> 1.3334077 | Y69: =+AVERAGE(X93:Y93)/AVERAGE(X109:Y109) -> 1.4716747 | Z69: =+AVERAGE(Y93:Z93)/AVERAGE(Y109:Z109) -> 1.6284965 | AA69: =+AVERAGE(Z93:AA93)/AVERAGE(Z109:AA109) -> 1.6236944 | AB69: =+AVERAGE(AA93:AB93)/AVERAGE(AA109:AB109) -> 1.6630627 | AC69: =+AVERAGE(AB93:AC93)/AVERAGE(AB109:AC109) -> 1.5894169 | AD69: =+AVERAGE(AC93:AD93)/AVERAGE(AC109:AD109) -> 1.4591697 | ... AK69: =+AVERAGE(AJ93:AK93)/AVERAGE(AJ109:AK109) -> 1.3456345
A70: Financial Leverage % | F70: =+F67-F66 -> 0.50134751 | G70: =+G67-G66 -> 0.40833853 | H70: =+H67-H66 -> 0.37504215 | I70: =+I67-I66 -> 0.37293369 | J70: =+J67-J66 -> 0.25266705 | K70: =+K67-K66 -> 0.39557913 | L70: =+L67-L66 -> 0.35208654 | M70: =+M67-M66 -> 0.42195372 | ... O70: =+O67-O66 -> 0.25884065 | W70: =+W67-W66 -> 0.042951484 | X70: =+X67-X66 -> 0.031349874 | Y70: =+Y67-Y66 -> 0.030379009 | Z70: =+Z67-Z66 -> 0.054882828 | AA70: =+AA67-AA66 -> 0.052562965 | AB70: =+AB67-AB66 -> 0.12836676 | AC70: =+AC67-AC66 -> 0.17037768 | AD70: =+AD67-AD66 -> 0.15500919 | ... AK70: =+AK67-AK66 -> 0.2606707
A73: EBITDA | B73: =+B31+B116 -> 2524 | C73: =+C31+C116 -> 7165 | D73: =+D31+D116 -> 10789 | E73: =+E31+E116 -> 14002 | F73: =+F31+F116 -> 17319 | G73: =+G31+G116 -> 19075 | H73: =+H31+H116 -> 22350 | I73: =+I31+I116 -> 24577 | ... Q73: =+Q31+Q116 -> 86078.465 | V73: =+V31+V116 -> 356.1 | W73: =+W31+W116 -> 784.653 | X73: =+X31+X116 -> 784.901 | Y73: =+Y31+Y116 -> 632 | Z73: =+Z31+Z116 -> 917 | AA73: =+AA31+AA116 -> 944 | AB73: =+AB31+AB116 -> 2121 | AC73: =+AC31+AC116 -> 3409 | ... AP73: =+AP31+AP116 -> 942430.69
A74: Net Cash | B74: =+B81-B98 -> 4366 | C74: =+C81-C98 -> 6318 | D74: =+D81-D98 -> 8575 | E74: =+E81-E98 -> 16275 | F74: =+F81-F98 -> 21728 | G74: =+G81-G98 -> 26339 | H74: =+H81-H98 -> 30025 | I74: =+I81-I98 -> 34747 | ... O74: =+O81-O98 -> 23220 | V74: =+V81-V98 -> 2490.563 | W74: =+W81-W98 -> 3129.576 | X74: =+X81-X98 -> 3727.886 | Y74: =+Y81-Y98 -> 3315.435 | Z74: =+Z81-Z98 -> 3239 | AA74: =+AA81-AA98 -> 3624 | AB74: =+AB81-AB98 -> 4019 | AC74: =+AC81-AC98 -> 5108 | ... AK74: =+AK81-AK98 -> 54088 | AL74: =+AK74+AL43 -> 297663.76 | AM74: =+AL74+AM43 -> 698966.47 | AN74: =+AM74+AN43 -> 1265392.2 | AO74: =+AN74+AO43 -> 1950552.2 | AP74: =+AO74+AP43 -> 2779272.9
AS75: Terminal | AT75: 0.03 | AW75: EV | AX75: =+AT77 -> 8296414.9
A76: NOPAT | B76: =+B31*(1-B64) -> 1979.2077 | C76: =+C31*(1-C64) -> 6027.6172 | D76: =+D31*(1-D64) -> 9150.8336 | E76: =+E31*(1-E64) -> 11857.463 | F76: =+F31*(1-F64) -> 14562.439 | G76: =+G31*(1-G64) -> 16104.932 | H76: =+H31*(1-H64) -> 18925.307 | I76: =+I31*(1-I64) -> 21054.723 | ... Q76: =+Q31*(1-Q64) -> 86078.465 | V76: =+V31*(1-V64) -> 238.74901 | W76: =+W31*(1-W64) -> 567.86605 | X76: =+X31*(1-X64) -> 550.81011 | Y76: =+Y31*(1-Y64) -> 427.92157 | Z76: =+Z31*(1-Z64) -> 634.34305 | AA76: =+AA31*(1-AA64) -> 617.30552 | AB76: =+AB31*(1-AB64) -> 1691.3617 | AC76: =+AC31*(1-AC64) -> 3060.3473 | ... AP76: =+AP31*(1-AP64) -> 803076.01 | AS76: Discount | AT76: =+Main!H10 -> 0.15870008 | AW76: Debt | AX76: =+Main!F5 -> 33366
A77: NWC | B77: =+B83+B84+B85-B95-B96 -> 3553 | C77: =+C83+C84+C85-C95-C96 -> 3689 | D77: =+D83+D84+D85-D95-D96 -> 6525 | E77: =+E83+E84+E85-E95-E96 -> 8980 | F77: =+F83+F84+F85-F95-F96 -> 8318 | G77: =+G83+G84+G85-G95-G96 -> 10864 | H77: =+H83+H84+H85-H95-H96 -> 12674 | I77: =+I83+I84+I85-I95-I96 -> 18869 | ... O77: =+O83+O84+O85-O95-O96 -> 56024 | V77: =+V83+V84+V85-V95-V96 -> -215.751 | W77: =+W83+W84+W85-W95-W96 -> -204.107 | X77: =+X83+X84+X85-X95-X96 -> -32.584 | Y77: =+Y83+Y84+Y85-Y95-Y96 -> -61.089 | Z77: =+Z83+Z84+Z85-Z95-Z96 -> 131 | AA77: =+AA83+AA84+AA85-AA95-AA96 -> 78 | AB77: =+AB83+AB84+AB85-AB95-AB96 -> 746 | AC77: =+AC83+AC84+AC85-AC95-AC96 -> 1009 | ... AP77: =+AP83+AP84+AP85-AP95-AP96 -> 102156.98 | AS77: EV | AT77: =+NPV(AT76,AL78:AO78,AP78+AU78) -> 8296414.9 | AW77: Cash | AX77: =+Main!F4 -> 99369
A78: UFCF | W78: =+W76+W116-W129-(W77-V77) -> 553.84105 | X78: =+X76+X116-X129-(X77-W77) -> 332.64011 | Y78: =+Y76+Y116-Y129-(Y77-X77) -> 337.42657 | Z78: =+Z76+Z116-Z129-(Z77-Y77) -> 478.25405 | AA78: =+AA76+AA116-AA129-(AA77-Z77) -> 781.30552 | AB78: =+AB76+AB116-AB129-(AB77-AA77) -> 1034.3617 | AC78: =+AC76+AC116-AC129-(AC77-AB77) -> 2403.3473 | AD78: =+AD76+AD116-AD129-(AD77-AC77) -> 2908.2146 | ... AP78: =+AP76+AP116-AP129-(AP77-AO77) -> 788865.57 | AS78: TV | AT78: =+AP78*(1+AT75)/(AT76-AT75) -> 6313372.6 | AU78: =+AP73*15 -> 14136460 | AW78: Equity Value | AX78: =+AX75-AX76+AX77 -> 8362417.9
AS79: Diff | AT79: =+AT77/Main!F6-1 -> 0.59182249 | AW79: Shares | AX79: =+Main!F2 -> 24100
AW80: Price | AX80: =+AX78/AX79 -> 346.98829
A81: Cash | B81: 15320 | C81: 16023 | D81: 18281 | E81: 25984 | F81: 31438 | G81: 34800 | H81: 38487 | I81: 43210 | J81: 53691 | K81: 56791 | L81: 60608 | M81: =+10605+39065 -> 49670 | N81: =+13237+37098 -> 50335 | O81: =+22443+34143 -> 56586 | V81: =+665.361+1825.202 -> 2490.563 | W81: =+667.876+2461.7 -> 3129.576 | X81: =+732.789+2995.097 -> 3727.886 | Y81: =+1151.587+3520.223 -> 4671.81 | Z81: =+497+4126 -> 4623 | AA81: =+4441+596 -> 5037 | AB81: =+1766+5032 -> 6798 | AC81: =+4002+3106 -> 7108 | AD81: =+782+6640 -> 7422 | AE81: =+10896+1 -> 10897 | AF81: =+847+10714 -> 11561 | AG81: =+1990+19218 -> 21208 | AH81: =+3389+9907 -> 13296 | AI81: =+7280+18704 -> 25984 | AJ81: 43210 | AK81: 62556 | AX81: =+AX80/Main!F1-1 -> 0.58442143
A82: Mrk. Securities | M82: 12886 | N82: 30237 | O82: 42783
A83: A/R | B83: 4080 | C83: 7066 | D83: 8309 | E83: 9999 | F83: 12365 | G83: 14132 | H83: 17693 | I83: 23065 | J83: 22132 | K83: 27808 | L83: 33391 | M83: 38466 | N83: 40710 | O83: 63059 | V83: 348.77 | W83: 336.143 | X83: 454.252 | Y83: 426.357 | Z83: 474 | AA83: 505 | AB83: 826 | AC83: 1265 | AD83: 1424 | AE83: 1657 | AF83: 2429 | AG83: 4650 | AH83: 3827 | AI83: 9999 | AJ83: 23065 | AK83: 38466 | AL83: =+AL137*AL19/365 -> 57330.389 | AM83: =+AM137*AM19/365 -> 101171.39 | AN83: =+AN137*AN19/365 -> 138807.31 | AO83: =+AO137*AO19/365 -> 163169.62 | AP83: =+AP137*AP19/365 -> 191724.55
A84: Inventories | B84: 4611 | C84: 4319 | D84: 4779 | E84: 5282 | F84: 5864 | G84: 6675 | H84: 7654 | I84: 10080 | J84: 11333 | K84: 14962 | L84: 19784 | M84: 21403 | N84: 25797 | O84: 31575 | V84: 345.525 | W84: 340.297 | X84: 412.467 | Y84: 387.765 | Z84: 483 | AA84: 418 | AB84: 794 | AC84: 796 | AD84: 1575 | AE84: 979 | AF84: 1826 | AG84: 2605 | AH84: 5159 | AI84: 5282 | AJ84: 10080 | AK84: 21403 | AL84: =+AL138*AL21/365 -> 28630.73 | AM84: =+AM138*AM21/365 -> 50058.63 | AN84: =+AN138*AN21/365 -> 68043.051 | AO84: =+AO138*AO21/365 -> 79238.816 | AP84: =+AP138*AP21/365 -> 92231.955
A85: Prepaid Exp | B85: 872 | C85: 1389 | D85: 1289 | E85: 3080 | F85: 4062 | G85: 4026 | H85: 3806 | I85: 3771 | J85: 2779 | K85: 2658 | L85: 2709 | M85: 3180 | N85: 3916 | O85: 3409 | V85: 32.636 | W85: 49.411 | X85: 76.92 | Y85: 70.285 | Z85: 70 | AA85: 93 | AB85: 118 | AC85: 86 | AD85: 136 | AE85: 157 | AF85: 239 | AG85: 366 | AH85: 791 | AI85: 3080 | AJ85: 3771 | AK85: 3180 | AL85: =+AL19*0.015 -> 6154.233 | AM85: =+AM19*0.015 -> 11077.619 | AN85: =+AN19*0.015 -> 15508.667 | AO85: =+AO19*0.015 -> 18610.401 | AP85: =+AP19*0.015 -> 22332.481
V86: =+V85/V$19 -> 0.0092105995 | W86: =+W85/W$19 -> 0.012359146 | X86: =+X85/X$19 -> 0.017971295 | Y86: =+Y85/Y$19 -> 0.01701816 | Z86: =+Z85/Z$19 -> 0.014950876 | AA86: =+AA85/AA$19 -> 0.018562874 | AB86: =+AB85/AB$19 -> 0.0170767 | AC86: =+AC85/AC$19 -> 0.0088532016 | ... AP86: =+AP85/AP$19 -> 0.015
A87: PP&E | B87: 3740 | C87: 3799 | D87: 3844 | E87: 3914 | F87: 4006 | G87: 4885 | H87: 5343 | I87: 6283 | J87: 7136 | K87: 9141 | L87: 9780 | M87: 10383 | N87: 12403 | O87: 14285 | V87: 568.857 | W87: 560.072 | X87: 576.144 | Y87: 582.74 | Z87: 557 | AA87: 466 | AB87: 521 | AC87: 997 | AD87: 1404 | AE87: 1674 | AF87: 2149 | AG87: 2778 | AH87: 3807 | AI87: 3914 | AJ87: 6283 | AK87: 10383
A88: Op Lease | B88: 1094 | C88: 1235 | D88: 1316 | E88: 1346 | F88: 1532 | G88: 1556 | H88: 1755 | I88: 1793 | J88: 1810 | K88: 2084 | L88: 2281 | M88: 2867 | N88: 4258 | O88: 5390 | V88: 0 | W88: 0 | X88: 0 | Y88: 0 | Z88: 0 | AA88: 0 | AB88: 0 | AC88: 0 | AD88: 0 | AE88: 618 | AF88: 707 | AG88: 829 | AH88: 1038 | AI88: 1346 | AJ88: 1793 | AK88: 2867
A89: Goodwill | B89: 4430 | C89: 4430 | D89: 4430 | E89: 4430 | F89: 4453 | G89: 4622 | H89: 4724 | I89: 5188 | J89: 5498 | K89: 5755 | L89: 6261 | M89: 20832 | N89: 20894 | O89: 21125 | V89: 369.844 | W89: 641.03 | X89: 641.03 | Y89: 643.179 | Z89: 618 | AA89: 618 | AB89: 618 | AC89: 618 | AD89: 618 | AE89: 618 | AF89: 4193 | AG89: 4349 | AH89: 4372 | AI89: 4430 | AJ89: 5188 | AK89: 20832
A90: Intangible | B90: 1541 | C90: 1395 | D90: 1251 | E90: 1112 | F90: 986 | G90: 952 | H90: 838 | I90: 807 | J90: 769 | K90: 755 | L90: 936 | M90: 3306 | N90: 3120 | O90: 2998 | V90: 288.745 | W90: 326.136 | X90: 312.332 | Y90: 296.012 | Z90: 222 | AA90: 166 | AB90: 104 | AC90: 52 | AD90: 45 | AE90: 49 | AF90: 2737 | AG90: 2339 | AH90: 1676 | AI90: 1112 | AJ90: 807 | AK90: 13258
A91: D/T | B91: 4568 | C91: 5398 | D91: 5982 | E91: 6081 | F91: 7798 | G91: 9578 | H91: 10276 | I91: 10979 | J91: 13318 | K91: 13570 | L91: 13674 | M91: 13258 | N91: 11707 | O91: 12159 | V91: 9.456 | W91: 49.931 | X91: 103.736 | Y91: 68.494 | Z91: 63 | AA91: 0 | AB91: 0 | AC91: 0 | AD91: 560 | AE91: 548 | AF91: 806 | AG91: 1222 | AH91: 3396 | AI91: 6081 | AJ91: 10979 | AK91: 22251
A92: Other Asset | B92: 4204 | C92: 4501 | D92: 4667 | E92: 4500 | F92: 4568 | G92: 4001 | H92: 5437 | I92: 6425 | J92: 6788 | K92: 7216 | L92: 11724 | M92: =+22251+8301 -> 30552 | N92: =+43364+12733 -> 56097 | O92: =+51157+15746 -> 66903 | V92: 40.85 | W92: 120.332 | X92: 107.481 | Y92: 104.252 | Z92: 91 | AA92: 67 | AB92: 62 | AC92: 319 | AD92: 108 | AE92: 118 | AF92: 2144 | AG92: 3841 | AH92: 3820 | AI92: 4500 | AJ92: 6425 | AK92: =+3306+8301 -> 11607
A93: A | B93: =SUM(B81:B92) -> 44460 | C93: =SUM(C81:C92) -> 49555 | D93: =SUM(D81:D92) -> 54148 | E93: =SUM(E81:E92) -> 65728 | F93: =SUM(F81:F92) -> 77072 | G93: =SUM(G81:G92) -> 85227 | H93: =SUM(H81:H92) -> 96013 | I93: =SUM(I81:I92) -> 111601 | ... O93: =SUM(O81:O92) -> 320272 | V93: =SUM(V81:V92) -> 4495.2552 | W93: =SUM(W81:W92) -> 5552.9404 | X93: =SUM(X81:X92) -> 6412.266 | Y93: =SUM(Y81:Y92) -> 7250.911 | Z93: =SUM(Z81:Z92) -> 7201.015 | AA93: =SUM(AA81:AA92) -> 7370.0186 | AB93: =SUM(AB81:AB92) -> 9841.0171 | AC93: =SUM(AC81:AC92) -> 11241.009 | ... AK93: =SUM(AK81:AK92) -> 206803.01
A95: A/P | B95: 1141 | C95: 1929 | D95: 2380 | E95: 2699 | F95: 2715 | G95: 3680 | H95: 5353 | I95: 6310 | J95: 7331 | K95: 9064 | L95: 8624 | M95: 9812 | N95: 13097 | O95: 15059 | V95: 286.138 | W95: 335.072 | X95: 356.428 | Y95: 324.391 | Z95: 293 | AA95: 296 | AB95: 485 | AC95: 596 | AD95: 511 | AE95: 687 | AF95: 1149 | AG95: 1783 | AH95: 1193 | AI95: 2699 | AJ95: 6310 | AK95: 9812 | AL95: =+AL139*AL21/365 -> 15137.302 | AM95: =+AM139*AM21/365 -> 27316.998 | AN95: =+AN139*AN21/365 -> 38313.266 | AO95: =+AO139*AO21/365 -> 46025.291 | AP95: =+AP139*AP21/365 -> 55248.804
A96: Accr Liab. | B96: 4869 | C96: 7156 | D96: 5472 | E96: 6682 | F96: 11258 | G96: 10289 | H96: 11126 | I96: 11737 | J96: 19211 | K96: 15193 | L96: 16452 | M96: 21352 | N96: 29787 | O96: 26960 | V96: 656.544 | W96: 594.886 | X96: 619.795 | Y96: 621.105 | Z96: 603 | AA96: 642 | AB96: 507 | AC96: 542 | AD96: 818 | AE96: 1097 | AF96: 1777 | AG96: 2552 | AH96: 4120 | AI96: 6682 | AJ96: 11737 | AK96: 21352 | AL96: =+AL19*0.1 -> 41028.22 | AM96: =+AM19*0.1 -> 73850.796 | AN96: =+AN19*0.1 -> 103391.11 | AO96: =+AO19*0.1 -> 124069.34 | AP96: =+AP19*0.1 -> 148883.2
B97: =+B96/B$19 -> 0.67700222 | C97: =+C96/C$19 -> 0.52979936 | D97: =+D96/D$19 -> 0.30198675 | E97: =+E96/E$19 -> 0.3023119 | F97: =+F96/F$19 -> 0.43226847 | G97: =+G96/G$19 -> 0.34250999 | H97: =+H96/H$19 -> 0.31711558 | I97: =+I96/I$19 -> 0.29841601 | ... O97: =+O96/O$19 -> 0.28018832 | V97: =+V96/V$19 -> 0.18529121 | W97: =+W96/W$19 -> 0.1487985 | X97: =+X96/X$19 -> 0.14480654 | Y97: =+Y96/Y$19 -> 0.15038862 | Z97: =+Z96/Z$19 -> 0.12879111 | AA97: =+AA96/AA$19 -> 0.12814371 | AB97: =+AB96/AB$19 -> 0.073371925 | AC97: =+AC96/AC$19 -> 0.055795759 | ... AP97: =+AP96/AP$19 -> 0.1
A98: Debt | B98: =+1250+9704 -> 10954 | C98: =+1249+8456 -> 9705 | D98: =+1249+8457 -> 9706 | E98: =+1250+8459 -> 9709 | F98: =+1250+8460 -> 9710 | G98: 8461 | H98: 8462 | I98: 8463 | J98: 8464 | K98: 8466 | L98: =+7468+999 -> 8467 | M98: =+999+7469 -> 8468 | N98: =+1000+7470 -> 8470 | O98: =+1000+32366 -> 33366 | V98: 0 | W98: 0 | X98: 0 | Y98: 1356.375 | Z98: =+0+1384 -> 1384 | AA98: =+1413+0 -> 1413 | AB98: =+796+1983 -> 2779 | AC98: =+15+1985 -> 2000 | AD98: 1988 | AE98: =+0+1991 -> 1991 | AF98: =+999+5964 -> 6963 | AG98: =+0+10946 -> 10946 | AH98: =+1250+9703 -> 10953 | AI98: =+1250+8459 -> 9709 | AJ98: 8463 | AK98: =+999+7469 -> 8468
A99: Op Lease | B99: 939 | C99: 1041 | D99: 1091 | E99: 1119 | F99: 1281 | G99: 1304 | H99: 1490 | I99: 1519 | J99: 1521 | K99: 1831 | L99: 2014 | M99: 2572 | N99: 3878 | O99: 4985 | V99: 23.389 | W99: 21.439 | X99: 18.998 | Y99: 17.5 | Z99: 489 | AA99: 453 | AB99: 0 | AC99: 0 | AD99: 0 | AE99: 561 | AF99: 634 | AG99: 741 | AH99: 902 | AI99: 1119 | AJ99: 1519 | AK99: 2572
A100: Other Liabilities | B100: 2037 | C100: 2223 | D100: 2234 | E100: 2541 | F100: 2966 | G100: 3336 | H100: 3683 | I100: 4245 | J100: 4884 | K100: 6055 | L100: 6694 | M100: 7306 | N100: 8768 | O100: 10918 | V100: 347.713 | W100: 455.807 | X100: 589.321 | Y100: 475.125 | Z100: 14 | AA100: 10 | AB100: 277 | AC100: 632 | AD100: 633 | AE100: 775 | AF100: 1375 | AG100: 1553 | AH100: 1913 | AI100: 2541 | AJ100: 4245 | AK100: 7306
A101: L | B101: =SUM(B95:B100)-B97 -> 19940 | C101: =SUM(C95:C100)-C97 -> 22054 | D101: =SUM(D95:D100)-D97 -> 20883 | E101: =SUM(E95:E100)-E97 -> 22750 | F101: =SUM(F95:F100)-F97 -> 27930 | G101: =SUM(G95:G100)-G97 -> 27070 | H101: =SUM(H95:H100)-H97 -> 30114 | I101: =SUM(I95:I100)-I97 -> 32274 | ... O101: =SUM(O95:O100)-O97 -> 91288 | V101: =SUM(V95:V100)-V97 -> 1313.784 | W101: =SUM(W95:W100)-W97 -> 1407.204 | X101: =SUM(X95:X100)-X97 -> 1584.542 | Y101: =SUM(Y95:Y100)-Y97 -> 2794.496 | Z101: =SUM(Z95:Z100)-Z97 -> 2783 | AA101: =SUM(AA95:AA100)-AA97 -> 2814 | AB101: =SUM(AB95:AB100)-AB97 -> 4048 | AC101: =SUM(AC95:AC100)-AC97 -> 3770 | ... AK101: =SUM(AK95:AK100)-AK97 -> 49510
A102: Commitments and Contingencies | M102: 0 | N102: 0 | O102: 0 | V102: 0 | W102: 0 | X102: 0 | Y102: 0 | Z102: 0 | AA102: 87 | AB102: 31 | AC102: 0 | AD102: 0 | AE102: 0 | AF102: 0 | AG102: 0 | AH102: 0 | AI102: 0 | AJ102: 0 | AK102: 0
A103: Preferred Stocks | M103: 0 | N103: 0 | O103: 0 | V103: 0 | W103: 0 | X103: 0 | Y103: 0 | Z103: 0 | AA103: 0 | AB103: 0 | AC103: 0 | AD103: 0 | AE103: 0 | AF103: 0 | AG103: 0 | AH103: 0 | AI103: 0 | AJ103: 0 | AK103: 0
A104: Shares | M104: 24 | N104: 24 | O104: 24 | V104: 0.7 | W104: 0.677 | X104: 0.72 | Y104: 0.732 | Z104: 1 | AA104: 1 | AB104: 1 | AC104: 1 | AD104: 1 | AE104: 1 | AF104: 3 | AG104: 3 | AH104: 2 | AI104: 2 | AJ104: 24 | AK104: 24
A105: APIC | M105: 10118 | N105: 10275 | O105: 9828 | V105: 2500.577 | W105: 2900.896 | X105: 3193.623 | Y105: 3483.342 | Z105: 3855 | AA105: 4170 | AB105: 4708 | AC105: 5351 | AD105: 6051 | AE105: 7045 | AF105: 8719 | AG105: 10385 | AH105: 11971 | AI105: 13132 | AJ105: 11237 | AK105: 10118
A106: Treasury Stocks | M106: 178 | N106: 137 | O106: -25 | V106: -1479.392 | W106: -1496.904 | X106: -1622.709 | Y106: -2537.295 | Z106: -3395 | AA106: -4048 | AB106: -5039 | AC106: -6650 | AD106: -9263 | AE106: -9814 | AF106: -10756 | AG106: 0 | AH106: 0 | AI106: 0 | AJ106: 0 | AK106: 0
A107: Acc. Loss | M107: 0 | N107: 0 | O107: 0 | V107: 10.272 | W107: 10.614 | X107: 9.981 | Y107: 4.877 | Z107: 8 | AA107: -4 | AB107: -16 | AC107: -18 | AD107: -12 | AE107: 1 | AF107: 19 | AG107: -11 | AH107: -43 | AI107: 27 | AJ107: 28 | AK107: 178
A108: Retained Earnings | M108: 146976 | N108: 185038 | O108: 219157 | V108: 2149.328 | W108: 2730.418 | X108: 3246.088 | Y108: 3504.742 | Z108: 3949 | AA108: 4350 | AB108: 6108 | AC108: 8787 | AD108: 12565 | AE108: 14971 | AF108: 18908 | AG108: 16235 | AH108: 10171 | AI108: 29817 | AJ108: 68038 | AK108: 146973
...

Sheet Bond
A1: Main
B4: isin | C4: immediateIssuer | D4: coupon | E4: couponType | F4: maturityDate | G4: callable | H4: currency
B5: US67066GAE44 | C5: NVIDIA Corporation | D5: 3200 | E5: Fixed Listing | F5: 16/09/2026 | G5: Y | H5: USD
B6: US67066GAM69 | C6: NVIDIA Corporation | D6: 1550 | E6: Fixed Listing | F6: 15/06/2028 | G6: Y | H6: USD
B7: US67066GAF19 | C7: NVIDIA Corporation | D7: 2850 | E7: Fixed Listing | F7: 01/04/2030 | G7: Y | H7: USD
B8: US67066GAN43 | C8: NVIDIA Corporation | D8: 2000 | E8: Fixed Listing | F8: 15/06/2031 | G8: Y | H8: USD
B9: US67066GAG91 | C9: NVIDIA Corporation | D9: 3500 | E9: Fixed Listing | F9: 01/04/2040 | G9: Y | H9: USD
B10: US67066GAH74 | C10: NVIDIA Corporation | D10: 3500 | E10: Fixed Listing | F10: 01/04/2050 | G10: Y | H10: USD
B11: US67066GAJ31 | C11: NVIDIA Corporation | D11: 3700 | E11: Fixed Listing | F11: 01/04/2060 | G11: Y | H11: USD
D12: =AVERAGE(D5:D11) -> 2900

Sheet Board
A1: Main
