Workbook

Sheet Main
A1: Spotify Technologies S.A. | E1: Price | F1: 485
E2: Share | F2: 209.28045 | G2: Q425
E3: MC | F3: =F1*F2 -> 101501.02
B4: Beta | C4: 1.02 | E4: Cash | F4: =+5314+3491 -> 8805 | G4: Q126
E5: Debt | F5: 414 | G5: Q126
E6: EV | F6: =F3-F4+F5 -> 93110.018
F7: =F6/17186 -> 5.4177829
A9: CAPM | B9: =0.04+(C4*(0.1-0.04)) -> 0.1012 | D9: WACC | E9: =+(F3/(F3+F5))*B9+(F5/(F5+F3))*B10*(1-Model!R68) -> 0.1009541
A10: Cost of Debt | B10: =+0.045 + (B17/100) -> 0.052847826
A11: Incremental Margin TTM | B11: =((Model!S46+Model!R46+Model!Q46+Model!P46)-(Model!O46+Model!N46+Model!M46+Model!L46))/((Model!S28+Model!R28+Model!Q28+Model!P28)-(Model!O28+Model!N28+Model!M28+Model!L28)) -> 0.5378799
A12: Leverage | B12: =(F5-F4)/Model!S70 -> -12.267544
A13: EV/FCF (TTM) | B13: =+F6/SUM(Model!P144:S144) -> 28.552597
A14: EV/FCF (FFCF) | B14: =$F$6/(SUM(Model!Q144:T144)) -> 27.207649
A15: P/FCF | B15: =+F3/SUM(Model!Q144:T144) -> 29.659581
A16: EV/EBITDA | B16: =+F6/SUM(Model!P70:S70) -> 33.768888
A17: Cr. Spread | B17: =+'[1]Credit Spread US'!J6 -> 0.78478261
A18: Rating | B18: N.A. | C18: N.A.
B19: S&P | C19: Moody’s
A21: ir@spotify.com
A22: Founder and CEO | B22: Daniel Ek | C22: Holds 13 % | J22: Management
A23: Tencent holds 8 % | K23: -> | L23: Approached AI in 2021
B25: -> | C25: ChatGPT integration
C26: Use of AI for algorithm and playlist → increase engagement?
C27: -> | D27: Prompted end of year wrapped (boosted Q4 2025 subs and earnings)
A30: Sector | B30: “Audio Streaming”
A37: Plans | B37: Ad-Supported | C37: Music and Audiobook with Ad break
B38: Basic | C38: Ad Supported account with certain Premium features ???
B39: Audiobook Access | C39: Only with Audiobooks without ads, music with ads
B40: Premium | C40: Audiobook and Music without ad break | G40: -> | H40: Mainly sold to end users and businesses that sell the service in bundle with their own service
B41: Standard
B42: Family
B43: Duo
B44: Student
A46: Seasonality | B46: There is no clear seasonality for the Premium revenues
B47: There is seasonality in the Ad-Supported accounts since in the 4th quarter there is a higher demand for advertisement due to the holiday season.
B48: During the 1st quarter there is a lower demand for ADV
B49: In 4th quarter there is also the Spotify Wrapper (which has a big social appeal). On top of that, there are also Christmas Gifts
A54: Revenues | B54: 88% of revenues is dependant on Premium subscriptions
B55: -> | C55: which is a fixed income for the firm
B56: -> | C56: every month has 281 people paying on avg $4.53
B60: -> | C60: Price increasing in 2026
B61: -> | C61: Want to enter the physical book market integrated in the audiobook ecosystem

Sheet Model
A1: Main
A2: in Millions | B2: Q122 | C2: Q222 | D2: Q322 | E2: Q422 | F2: Q123 | G2: Q223 | H2: Q323 | I2: Q423 | J2: Q124 | K2: Q224 | L2: Q324 | M2: Q424 | N2: Q125 | O2: Q225 | P2: Q325 | Q2: Q425 | R2: Q126 | S2: Q226 | T2: Q326 | U2: Q426 | AA2: 2019 | AB2: 2020 | AC2: =AB2+1 -> 2021 | AD2: =AC2+1 -> 2022 | AE2: =AD2+1 -> 2023 | AF2: =AE2+1 -> 2024 | AG2: =AF2+1 -> 2025 | AH2: =AG2+1 -> 2026 | AI2: =AH2+1 -> 2027 | AJ2: =AI2+1 -> 2028 | ... AQ2: =AP2+1 -> 2035
A3: Streamed Hours | AE3: =AF3*0.85 -> 161500 | AF3: 190000
AF4: =+AF3/AE3-1 -> 0.17647059
A6: MAU | B6: 422 | C6: 433 | D6: 456 | E6: 489 | F6: 515 | G6: 551 | H6: 574 | I6: 602 | J6: 615 | K6: 626 | L6: 640 | M6: 675 | N6: 678 | O6: 696 | P6: 713 | Q6: 751 | R6: 761 | S6: 777 | AA6: 271 | AB6: 345 | AC6: 406 | AD6: 489 | AE6: 602 | AF6: 675 | AG6: 751 | AH6: 759
F7: =+F6/B6-1 -> 0.22037915 | G7: =+G6/C6-1 -> 0.27251732 | H7: =+H6/D6-1 -> 0.25877193 | I7: =+I6/E6-1 -> 0.23108384 | J7: =+J6/F6-1 -> 0.19417476 | K7: =+K6/G6-1 -> 0.13611615 | L7: =+L6/H6-1 -> 0.11498258 | M7: =+M6/I6-1 -> 0.12126246 | ... S7: =+S6/O6-1 -> 0.11637931 | AB7: =+AB6/AA6-1 -> 0.27306273 | AC7: =+AC6/AB6-1 -> 0.17681159 | AD7: =+AD6/AC6-1 -> 0.2044335 | AE7: =+AE6/AD6-1 -> 0.23108384 | AF7: =+AF6/AE6-1 -> 0.12126246 | AG7: =+AG6/AF6-1 -> 0.11259259 | AH7: =+AH6/AG6-1 -> 0.010652463
A8: Premium Subs | B8: 182 | C8: 188 | D8: 195 | E8: 205 | F8: 210 | G8: 220 | H8: 226 | I8: 236 | J8: 239 | K8: 246 | L8: 252 | M8: 263 | N8: 268 | O8: 276 | P8: 281 | Q8: 290 | R8: 293 | S8: 300 | AA8: 124 | AB8: 155 | AC8: 180 | AD8: 205 | AE8: 236 | AF8: 263 | AG8: =Q8 -> 290 | AH8: =+AG8+3 -> 293
F9: =+F8/B8-1 -> 0.15384615 | G9: =+G8/C8-1 -> 0.17021277 | H9: =+H8/D8-1 -> 0.15897436 | I9: =+I8/E8-1 -> 0.15121951 | J9: =+J8/F8-1 -> 0.13809524 | K9: =+K8/G8-1 -> 0.11818182 | L9: =+L8/H8-1 -> 0.11504425 | M9: =+M8/I8-1 -> 0.11440678 | ... S9: =+S8/O8-1 -> 0.086956522 | AB9: =+AB8/AA8-1 -> 0.25 | AC9: =+AC8/AB8-1 -> 0.16129032 | AD9: =+AD8/AC8-1 -> 0.13888889 | AE9: =+AE8/AD8-1 -> 0.15121951 | AF9: =+AF8/AE8-1 -> 0.11440678 | AG9: =+AG8/AF8-1 -> 0.1026616 | AH9: =+AH8/AG8-1 -> 0.010344828
A10: Premium ARPU | B10: 4.38 | C10: 4.54 | D10: 4.63 | E10: 4.55 | F10: 4.32 | G10: 4.27 | H10: 4.34 | I10: 4.6 | J10: 4.55 | K10: 4.62 | L10: 4.71 | M10: 4.85 | N10: 4.73 | O10: 4.57 | P10: 4.53 | Q10: 4.7 | R10: 4.76 | S10: 4.89 | AA10: 4.72 | AB10: 4.31 | AC10: 4.29 | AD10: 4.52 | AE10: 4.39 | AF10: 4.69 | AG10: =Q10 -> 4.7 | AH10: =+AG10*1.06 -> 4.982
F11: =+F10/B10-1 -> -0.01369863 | G11: =+G10/C10-1 -> -0.059471366 | H11: =+H10/D10-1 -> -0.062634989 | I11: =+I10/E10-1 -> 0.010989011 | J11: =+J10/F10-1 -> 0.053240741 | K11: =+K10/G10-1 -> 0.081967213 | L11: =+L10/H10-1 -> 0.085253456 | M11: =+M10/I10-1 -> 0.054347826 | ... S11: =+S10/O10-1 -> 0.070021882 | AB11: =+AB10/AA10-1 -> -0.086864407 | AC11: =+AC10/AB10-1 -> -0.0046403712 | AD11: =+AD10/AC10-1 -> 0.053613054 | AE11: =+AE10/AD10-1 -> -0.028761062 | AF11: =+AF10/AE10-1 -> 0.06833713 | AG11: =+AG10/AF10-1 -> 0.0021321962 | AH11: =+AH10/AG10-1 -> 0.06
A12: Ad-Sup MAU | B12: 252 | C12: 256 | D12: 273 | E12: 295 | F12: 317 | G12: 343 | H12: 361 | I12: 379 | J12: 388 | K12: 393 | L12: 402 | M12: 425 | N12: 423 | O12: 433 | P12: 446 | Q12: 476 | R12: 483 | S12: 494 | AA12: 153 | AB12: 199 | AC12: 236 | AD12: 295 | AE12: 379 | AF12: 425 | AG12: =Q12 -> 476
F13: =+F12/B12-1 -> 0.25793651 | G13: =+G12/C12-1 -> 0.33984375 | H13: =+H12/D12-1 -> 0.32234432 | I13: =+I12/E12-1 -> 0.28474576 | J13: =+J12/F12-1 -> 0.22397476 | K13: =+K12/G12-1 -> 0.14577259 | L13: =+L12/H12-1 -> 0.11357341 | M13: =+M12/I12-1 -> 0.12137203 | ... S13: =+S12/O12-1 -> 0.1408776 | AB13: =+AB12/AA12-1 -> 0.30065359 | AC13: =+AC12/AB12-1 -> 0.18592965 | AD13: =+AD12/AC12-1 -> 0.25 | AE13: =+AE12/AD12-1 -> 0.28474576 | AF13: =+AF12/AE12-1 -> 0.12137203 | AG13: =+AG12/AF12-1 -> 0.12
A15: Premium % | B15: =B8/B6 -> 0.43127962 | C15: =C8/C6 -> 0.43418014 | D15: =D8/D6 -> 0.42763158 | E15: =E8/E6 -> 0.4192229 | F15: =F8/F6 -> 0.40776699 | G15: =G8/G6 -> 0.39927405 | H15: =H8/H6 -> 0.39372822 | I15: =I8/I6 -> 0.39202658 | ... S15: =S8/S6 -> 0.38610039 | AA15: =AA8/AA6 -> 0.45756458 | AB15: =AB8/AB6 -> 0.44927536 | AC15: =AC8/AC6 -> 0.44334975 | AD15: =AD8/AD6 -> 0.4192229 | AE15: =AE8/AE6 -> 0.39202658 | AF15: =AF8/AF6 -> 0.38962963 | AG15: =AG8/AG6 -> 0.3861518
F16: =+F15/B15-1 -> -0.054518297 | G16: =+G15/C15-1 -> -0.080395413 | H16: =+H15/D15-1 -> -0.079281694 | I16: =+I15/E15-1 -> -0.064873187 | J16: =+J15/F15-1 -> -0.046960898 | K16: =+K15/G15-1 -> -0.015785652 | L16: =+L15/H15-1 -> 5.5309735e-05 | M16: =+M15/I15-1 -> -0.0061142498 | ... S16: =+S15/O15-1 -> -0.026355548 | AB16: =+AB15/AA15-1 -> -0.018115942 | AC16: =+AC15/AB15-1 -> -0.013189258 | AD16: =+AD15/AC15-1 -> -0.05441945 | AE16: =+AE15/AD15-1 -> -0.064873187 | AF16: =+AF15/AE15-1 -> -0.0061142498 | AG16: =+AG15/AF15-1 -> -0.0089259947
A17: ARPU | B17: =B28/B6 -> 6.3056872 | C17: =C28/C6 -> 6.6143187 | D17: =D28/D6 -> 6.6578947 | E17: =E28/E6 -> 6.4744376 | F17: =F28/F6 -> 5.9070687 | G17: =G28/G6 -> 5.7660752 | H17: =H28/H6 -> 5.8486023 | I17: =I28/I6 -> 6.0982836 | ... S17: =S28/S6 -> 6.1480051 | AA17: =AA28/AA6 -> 24.95941 | AB17: =AB28/AB6 -> 22.841079 | AC17: =AC28/AC6 -> 23.813265 | AD17: =AD28/AD6 -> 23.982028 | AE17: =AE28/AE6 -> 22.005196 | AF17: =AF28/AF6 -> 23.219548 | AG17: =AG28/AG6 -> 22.884306
F18: =+F17/B17-1 -> -0.063215707 | G18: =+G17/C17-1 -> -0.12824352 | H18: =+H17/D17-1 -> -0.12155381 | I18: =+I17/E17-1 -> -0.058098332 | J18: =+J17/F17-1 -> 0.00092202118 | K18: =+K17/G17-1 -> 0.054756038 | L18: =+L17/H17-1 -> 0.065481137 | M18: =+M17/I17-1 -> 0.03056776 | ... S18: =+S17/O17-1 -> 0.02048394 | AB18: =+AB17/AA17-1 -> -0.084871009 | AC18: =+AC17/AB17-1 -> 0.042563049 | AD18: =+AD17/AC17-1 -> 0.0070869214 | AE18: =+AE17/AD17-1 -> -0.082429707 | AF18: =+AF17/AE17-1 -> 0.055184755 | AG18: =+AG17/AF17-1 -> -0.014437917
A19: CPU | B19: =B34/B6 -> 4.7156398 | C19: =C34/C6 -> 4.9884527 | D19: =D34/D6 -> 5.0131579 | E19: =E34/E6 -> 4.8364008 | F19: =F34/F6 -> 4.4194175 | G19: =G34/G6 -> 4.3756806 | H19: =H34/H6 -> 4.3066202 | I19: =I34/I6 -> 4.4700997 | ... S19: =S34/S6 -> 4.0939511 | AA19: =AA34/AA6 -> 18.605166 | AB19: =AB34/AB6 -> 17 | AC19: =AC34/AC6 -> 17.431034 | AD19: =AD34/AD6 -> 17.997955 | AE19: =AE34/AE6 -> 16.362126 | AF19: =AF34/AF6 -> 16.220741 | AG19: =AG34/AG6 -> 15.565912
F20: =+F19/B19-1 -> -0.062816998 | G20: =+G19/C19-1 -> -0.12283811 | H20: =+H19/D19-1 -> -0.14093665 | I20: =+I19/E19-1 -> -0.075738377 | J20: =+J19/F19-1 -> -0.031620158 | K20: =+K19/G19-1 -> -0.016127493 | L20: =+L19/H19-1 -> -0.0029884709 | M20: =+M19/I19-1 -> -0.047498245 | ... S20: =+S19/O19-1 -> -0.0082179041 | AB20: =+AB19/AA19-1 -> -0.086275288 | AC20: =+AC19/AB19-1 -> 0.02535497 | AD20: =+AD19/AC19-1 -> 0.032523631 | AE20: =+AE19/AD19-1 -> -0.090889702 | AF20: =+AF19/AE19-1 -> -0.0086410227 | AG20: =+AG19/AF19-1 -> -0.040369835
A21: PPU | B21: =B17-B19 -> 1.5900474 | C21: =C17-C19 -> 1.6258661 | D21: =D17-D19 -> 1.6447368 | E21: =E17-E19 -> 1.6380368 | F21: =F17-F19 -> 1.4876513 | G21: =G17-G19 -> 1.3903946 | H21: =H17-H19 -> 1.5419821 | I21: =I17-I19 -> 1.6281839 | ... S21: =S17-S19 -> 2.0540541 | AA21: =AA17-AA19 -> 6.3542435 | AB21: =AB17-AB19 -> 5.8410793 | AC21: =AC17-AC19 -> 6.3822308 | AD21: =AD17-AD19 -> 5.984073 | AE21: =AE17-AE19 -> 5.6430702 | AF21: =AF17-AF19 -> 6.9988071 | AG21: =AG17-AG19 -> 7.3183938
F22: =+F21/B21-1 -> -0.064398169 | G22: =+G21/C21-1 -> -0.14482832 | H22: =+H21/D21-1 -> -0.062474911 | I22: =+I21/E21-1 -> -0.0060150518 | J22: =+J21/F21-1 -> 0.097596208 | K22: =+K21/G21-1 -> 0.27783205 | L22: =+L21/H21-1 -> 0.25671073 | M22: =+M21/I21-1 -> 0.24489418 | ... S22: =+S21/O21-1 -> 0.082948263 | AB22: =+AB21/AA21-1 -> -0.080759295 | AC22: =+AC21/AB21-1 -> 0.092645804 | AD22: =+AD21/AC21-1 -> -0.062385363 | AE22: =+AE21/AD21-1 -> -0.056985063 | AF22: =+AF21/AE21-1 -> 0.24024809 | AG22: =+AG21/AF21-1 -> 0.045663026
A24: Premium | B24: 2379 | C24: 2504 | D24: 2651 | E24: =AD24-D24-C24-B24 -> 2717 | F24: 2713 | G24: 2773 | H24: 2910 | I24: 3170 | J24: 3247 | K24: 3351 | L24: 3516 | M24: 3705 | N24: 3783 | O24: 3753 | P24: 3835 | Q24: 4020 | R24: 4148 | AA24: 6086 | AB24: 7135 | AC24: 8460 | AD24: 10251 | AE24: 11566 | AF24: 13819 | AG24: =SUM(N24:Q24) -> 15391
F25: =+F24/B24-1 -> 0.14039512 | G25: =+G24/C24-1 -> 0.10742812 | H25: =+H24/D24-1 -> 0.097698982 | I25: =+I24/E24-1 -> 0.16672801 | J25: =+J24/F24-1 -> 0.19683008 | K25: =+K24/G24-1 -> 0.20843851 | L25: =+L24/H24-1 -> 0.20824742 | M25: =+M24/I24-1 -> 0.16876972 | ... S25: =+S24/O24-1 -> -1 | AB25: =+AB24/AA24-1 -> 0.1723628 | AC25: =+AC24/AB24-1 -> 0.18570427 | AD25: =+AD24/AC24-1 -> 0.21170213 | AE25: =+AE24/AD24-1 -> 0.12828017 | AF25: =+AF24/AE24-1 -> 0.19479509 | AG25: =+AG24/AF24-1 -> 0.11375642
A26: Ad-Sup | B26: 282 | C26: 360 | D26: 385 | E26: =AD26-D26-C26-B26 -> 449 | F26: 329 | G26: 404 | H26: 447 | I26: 501 | J26: 389 | K26: 456 | L26: 472 | M26: 537 | N26: 407 | O26: 440 | P26: 437 | Q26: 511 | R26: 385 | AA26: 678 | AB26: 745 | AC26: 1208 | AD26: 1476 | AE26: 1681 | AF26: 1854 | AG26: =SUM(N26:Q26) -> 1795
F27: =+F26/B26-1 -> 0.16666667 | G27: =+G26/C26-1 -> 0.12222222 | H27: =+H26/D26-1 -> 0.16103896 | I27: =+I26/E26-1 -> 0.11581292 | J27: =+J26/F26-1 -> 0.18237082 | K27: =+K26/G26-1 -> 0.12871287 | L27: =+L26/H26-1 -> 0.055928412 | M27: =+M26/I26-1 -> 0.071856287 | ... S27: =+S26/O26-1 -> -1 | AB27: =+AB26/AA26-1 -> 0.098820059 | AC27: =+AC26/AB26-1 -> 0.62147651 | AD27: =+AD26/AC26-1 -> 0.2218543 | AE27: =+AE26/AD26-1 -> 0.13888889 | AF27: =+AF26/AE26-1 -> 0.10291493 | AG27: =+AG26/AF26-1 -> -0.031823085
A28: Revenue | B28: =SUM(B24:B26) -> 2661 | C28: =SUM(C24:C26) -> 2864 | D28: =SUM(D24:D26) -> 3036 | E28: 3166 | F28: =SUM(F24:F26) -> 3042.1404 | G28: =SUM(G24:G26) -> 3177.1074 | H28: =SUM(H24:H26) -> 3357.0977 | I28: =SUM(I24:I26) -> 3671.1667 | J28: =SUM(J24:J26) -> 3636.1968 | K28: =SUM(K24:K26) -> 3807.2084 | L28: =SUM(L24:L26) -> 3988.2082 | M28: =SUM(M24:M26) -> 4242.1688 | ... R28: =SUM(R24:R26) -> 4533.0965 | S28: 4777 | T28: =+P28*1.145 -> 4891.5439 | U28: =+Q28*1.145 -> 5188.0923 | AA28: =SUM(AA24:AA26) -> 6764 | AB28: =SUM(AB24:AB26) -> 7880.1724 | AC28: =SUM(AC24:AC26) -> 9668.1857 | AD28: =SUM(AD24:AD26) -> 11727.212 | AE28: =SUM(AE24:AE26) -> 13247.128 | AF28: =SUM(AF24:AF26) -> 15673.195 | AG28: =SUM(AG24:AG26) -> 17186.114 | AH28: =AG28*1.15 -> 19764.031 | AI28: =AH28*1.15 -> 22728.635 | AJ28: =AI28*1.15 -> 26137.931 | AK28: =AJ28*1.15 -> 30058.62 | AL28: =AK28*1.15 -> 34567.413 | AM28: =AL28*1.15 -> 39752.525 | AN28: =AM28*1.15 -> 45715.404 | AO28: =AN28*1.15 -> 52572.715 | ... AQ28: =AP28*1.15 -> 69527.415
F29: =+F28/B28-1 -> 0.14323202 | G29: =+G28/C28-1 -> 0.10932522 | H29: =+H28/D28-1 -> 0.10576341 | I29: =+I28/E28-1 -> 0.15955993 | J29: =+J28/F28-1 -> 0.19527581 | K29: =+K28/G28-1 -> 0.19832537 | L29: =+L28/H28-1 -> 0.1879929 | M29: =+M28/I28-1 -> 0.15553694 | ... U29: =+U28/Q28-1 -> 0.145 | AB29: =+AB28/AA28-1 -> 0.16501661 | AC29: =+AC28/AB28-1 -> 0.22690028 | AD29: =+AD28/AC28-1 -> 0.21296922 | AE29: =+AE28/AD28-1 -> 0.12960596 | AF29: =+AF28/AE28-1 -> 0.18313905 | AG29: =+AG28/AF28-1 -> 0.096529073 | AH29: =+AH28/AG28-1 -> 0.15 | AI29: =+AI28/AH28-1 -> 0.15 | ... AQ29: =+AQ28/AP28-1 -> 0.15
A30: Premium COGS | B30: 1704 | C30: 1804 | D30: 1908 | E30: =AD30-D30-C30-B30 -> 1939 | F30: 1937 | G30: 1984 | H30: 2062 | I30: =AE30-H30-G30-F30 -> 2248 | J30: 2268 | K30: 2300 | L30: 2338 | M30: 2425 | N30: 2514 | O30: 2509 | P30: 2561 | Q30: 2623 | R30: 2703 | AA30: 4443 | AB30: 5126 | AC30: 5986 | AD30: 7355 | AE30: 8231 | AF30: 9324 | AG30: =SUM(N30:Q30) -> 10207
B31: =+B30/B$28 -> 0.64036077 | C31: =+C30/C$28 -> 0.62988827 | D31: =+D30/D$28 -> 0.6284585 | E31: =+E30/E$28 -> 0.61244473 | F31: =+F30/F$28 -> 0.63672275 | G31: =+G30/G$28 -> 0.6244674 | H31: =+H30/H$28 -> 0.61422103 | I31: =+I30/I$28 -> 0.61233939 | ... U31: =+U30/U$28 -> 0 | AB31: =+AB30/AA30-1 -> 0.15372496 | AC31: =+AC30/AB30-1 -> 0.16777214 | AD31: =+AD30/AC30-1 -> 0.2287003 | AE31: =+AE30/AD30-1 -> 0.11910265 | AF31: =+AF30/AE30-1 -> 0.13279067 | AG31: =+AG30/AF30-1 -> 0.094701845
A32: Ad-Sup COGS | B32: 286 | C32: 356 | D32: 378 | E32: =AD32-D32-C32-B32 -> 426 | F32: 339 | G32: 427 | H32: 410 | I32: =AE32-H32-G32-F32 -> 443 | J32: 364 | K32: 395 | L32: 410 | M32: 449 | N32: 350 | O32: 364 | P32: 360 | Q32: 409 | R32: 335 | AA32: 599 | AB32: 739 | AC32: 1091 | AD32: 1446 | AE32: 1619 | AF32: 1625 | AG32: =SUM(N32:Q32) -> 1483
B33: =+B32/B$28 -> 0.10747839 | C33: =+C32/C$28 -> 0.12430168 | D33: =+D32/D$28 -> 0.12450593 | E33: =+E32/E$28 -> 0.13455464 | F33: =+F32/F$28 -> 0.1114347 | G33: =+G32/G$28 -> 0.13439898 | H33: =+H32/H$28 -> 0.1221293 | I33: =+I32/I$28 -> 0.12067008 | ... U33: =+U32/U$28 -> 0 | AB33: =+AB32/AA32-1 -> 0.23372287 | AC33: =+AC32/AB32-1 -> 0.47631935 | AD33: =+AD32/AC32-1 -> 0.32538955 | AE33: =+AE32/AD32-1 -> 0.11964039 | AF33: =+AF32/AE32-1 -> 0.0037059914 | AG33: =+AG32/AF32-1 -> -0.087384615
A34: COGS | B34: =SUM(B30:B32)-B31 -> 1990 | C34: =SUM(C30:C32)-C31 -> 2160 | D34: =SUM(D30:D32)-D31 -> 2286 | E34: =SUM(E30:E32)-E31 -> 2365 | F34: =SUM(F30:F32)-F31 -> 2276 | G34: =SUM(G30:G32)-G31 -> 2411 | H34: =SUM(H30:H32)-H31 -> 2472 | I34: =SUM(I30:I32)-I31 -> 2691 | ... R34: =SUM(R30:R32)-R31 -> 3038 | S34: 3181 | T34: =+T28-T36 -> 3277.3344 | U34: =+U28-U36 -> 3476.0219 | AA34: =SUM(AA30:AA32)-AA31 -> 5042 | AB34: =SUM(AB30:AB32)-AB31 -> 5865 | AC34: =SUM(AC30:AC32)-AC31 -> 7077 | AD34: =SUM(AD30:AD32)-AD31 -> 8801 | AE34: =SUM(AE30:AE32)-AE31 -> 9850 | AF34: =SUM(AF30:AF32)-AF31 -> 10949 | AG34: =SUM(AG30:AG32)-AG31 -> 11690 | AH34: =AH28-AH36 -> 13439.541 | AI34: =AI28-AI36 -> 15341.829 | AJ34: =AJ28-AJ36 -> 17512.414 | AK34: =AK28-AK36 -> 19988.983 | AL34: =AL28-AL36 -> 22814.493 | AM34: =AM28-AM36 -> 26037.904 | AN34: =AN28-AN36 -> 29715.013 | AO34: =AO28-AO36 -> 33909.401 | ... AQ34: =AQ28-AQ36 -> 44149.909
B35: =+B34/B$28 -> 0.74783916 | C35: =+C34/C$28 -> 0.75418994 | D35: =+D34/D$28 -> 0.75296443 | E35: =+E34/E$28 -> 0.74699937 | F35: =+F34/F$28 -> 0.74815745 | G35: =+G34/G$28 -> 0.75886638 | H35: =+H34/H$28 -> 0.73635033 | I35: =+I34/I$28 -> 0.73300948 | ... U35: =+U34/U$28 -> 0.67 | AA35: =+AA34/AA$28 -> 0.74541691 | AB35: =+AB34/AB$28 -> 0.74427306 | AC35: =+AC34/AC$28 -> 0.73198842 | AD35: =+AD34/AD$28 -> 0.75047677 | AE35: =+AE34/AE$28 -> 0.74355738 | AF35: =+AF34/AF$28 -> 0.69858125 | AG35: =+AG34/AG$28 -> 0.68020032 | AH35: =+AH34/AH$28 -> 0.68 | ... AQ35: =+AQ34/AQ$28 -> 0.635
A36: Gross Profit | B36: =B28-B34 -> 671 | C36: =C28-C34 -> 704 | D36: =D28-D34 -> 750 | E36: =E28-E34 -> 801 | F36: =F28-F34 -> 766.1404 | G36: =G28-G34 -> 766.10743 | H36: =H28-H34 -> 885.0977 | I36: =I28-I34 -> 980.16673 | ... S36: =S28-S34 -> 1596 | T36: =+T28*0.33 -> 1614.2095 | U36: =+U28*0.33 -> 1712.0705 | AA36: =AA28-AA34 -> 1722 | AB36: =AB28-AB34 -> 2015.1724 | AC36: =AC28-AC34 -> 2591.1857 | AD36: =AD28-AD34 -> 2926.2117 | AE36: =AE28-AE34 -> 3397.1283 | AF36: =AF28-AF34 -> 4724.1948 | AG36: =AG28-AG34 -> 5496.1138 | AH36: =AH28*0.32 -> 6324.4899 | AI36: =AI28*0.325 -> 7386.8065 | AJ36: =AJ28*0.33 -> 8625.5172 | AK36: =AK28*0.335 -> 10069.638 | AL36: =AL28*0.34 -> 11752.921 | AM36: =AM28*0.345 -> 13714.621 | AN36: =AN28*0.35 -> 16000.391 | AO36: =AO28*0.355 -> 18663.314 | AP36: =AP28*0.36 -> 21765.104 | AQ36: =AQ28*0.365 -> 25377.507
B37: =+B36/B$28 -> 0.25216084 | C37: =+C36/C$28 -> 0.24581006 | D37: =+D36/D$28 -> 0.24703557 | E37: =+E36/E$28 -> 0.25300063 | F37: =+F36/F$28 -> 0.25184255 | G37: =+G36/G$28 -> 0.24113362 | H37: =+H36/H$28 -> 0.26364967 | I37: =+I36/I$28 -> 0.26699052 | ... U37: =+U36/U$28 -> 0.33 | AA37: =+AA36/AA$28 -> 0.25458309 | AB37: =+AB36/AB$28 -> 0.25572694 | AC37: =+AC36/AC$28 -> 0.26801158 | AD37: =+AD36/AD$28 -> 0.24952323 | AE37: =+AE36/AE$28 -> 0.25644262 | AF37: =+AF36/AF$28 -> 0.30141875 | AG37: =+AG36/AG$28 -> 0.31979968 | AH37: =+AH36/AH$28 -> 0.32 | ... AQ37: =+AQ36/AQ$28 -> 0.365
A38: R&D | B38: 250 | C38: 336 | D38: 386 | E38: 415 | F38: 435 | G38: 453 | H38: 369 | I38: 468 | J38: 389 | K38: 379 | L38: 342 | M38: 376 | N38: 379 | O38: 415 | P38: 309 | Q38: 290 | R38: 331 | S38: 403 | T38: =+P38*0.9 -> 278.1 | U38: =+Q38*0.9 -> 261 | AA38: 615 | AB38: 837 | AC38: 912 | AD38: 1387 | AE38: 1725 | AF38: 1486 | AG38: =SUM(N38:Q38) -> 1393 | AH38: =AG38*1.1 -> 1532.3 | AI38: =AH38*1.1 -> 1685.53 | AJ38: =AI38*1.1 -> 1854.083 | AK38: =AJ38*1.1 -> 2039.4913 | AL38: =AK38*1.1 -> 2243.4404 | AM38: =AL38*1.1 -> 2467.7845 | AN38: =AM38*1.1 -> 2714.5629 | AO38: =AN38*1.1 -> 2986.0192 | ... AQ38: =AP38*1.1 -> 3613.0832
B39: =+B38/B$28 -> 0.093949643 | C39: =+C38/C$28 -> 0.11731844 | D39: =+D38/D$28 -> 0.12714097 | E39: =+E38/E$28 -> 0.13108023 | F39: =+F38/F$28 -> 0.14299143 | G39: =+G38/G$28 -> 0.14258253 | H39: =+H38/H$28 -> 0.10991637 | I39: =+I38/I$28 -> 0.12747991 | ... U39: =+U38/U$28 -> 0.050307509 | AA39: =+AA38/AA$28 -> 0.090922531 | AB39: =+AB38/AB$28 -> 0.10621595 | AC39: =+AC38/AC$28 -> 0.094330004 | AD39: =+AD38/AD$28 -> 0.11827193 | AE39: =+AE38/AE$28 -> 0.1302169 | AF39: =+AF38/AF$28 -> 0.094811557 | AG39: =+AG38/AG$28 -> 0.08105381 | AH39: =+AH38/AH$28 -> 0.077529731 | ... AQ39: =+AQ38/AQ$28 -> 0.05196631
A40: S&M | B40: 296 | C40: 391 | D40: 432 | E40: 453 | F40: 347 | G40: 399 | H40: 355 | I40: 432 | J40: 324 | K40: 343 | L40: 332 | M40: 393 | N40: 314 | O40: 364 | P40: 349 | Q40: 399 | R40: 342 | S40: 390 | T40: =+P40*1.01 -> 352.49 | U40: =+Q40*1.01 -> 402.99 | AA40: 826 | AB40: 1029 | AC40: 1135 | AD40: 1572 | AE40: 1533 | AF40: 1392 | AG40: =SUM(N40:Q40) -> 1426 | AH40: =AG40*1.08 -> 1540.08 | AI40: =AH40*1.08 -> 1663.2864 | AJ40: =AI40*1.08 -> 1796.3493 | AK40: =AJ40*1.08 -> 1940.0573 | AL40: =AK40*1.08 -> 2095.2618 | AM40: =AL40*1.08 -> 2262.8828 | AN40: =AM40*1.08 -> 2443.9134 | AO40: =AN40*1.08 -> 2639.4265 | ... AQ40: =AP40*1.08 -> 3078.627
B41: =+B40/B$28 -> 0.11123638 | C41: =+C40/C$28 -> 0.13652235 | D41: =+D40/D$28 -> 0.14229249 | E41: =+E40/E$28 -> 0.14308275 | F41: =+F40/F$28 -> 0.11406443 | G41: =+G40/G$28 -> 0.12558593 | H41: =+H40/H$28 -> 0.1057461 | I41: =+I40/I$28 -> 0.11767376 | ... U41: =+U40/U$28 -> 0.07767595 | AA41: =+AA40/AA$28 -> 0.12211709 | AB41: =+AB40/AB$28 -> 0.1305809 | AC41: =+AC40/AC$28 -> 0.11739535 | AD41: =+AD40/AD$28 -> 0.13404721 | AE41: =+AE40/AE$28 -> 0.11572319 | AF41: =+AF40/AF$28 -> 0.088814056 | AG41: =+AG40/AG$28 -> 0.082973965 | AH41: =+AH40/AH$28 -> 0.077923376 | ... AQ41: =+AQ40/AQ$28 -> 0.044279325
A42: G&A | B42: 131 | C42: 171 | D42: 160 | E42: 164 | F42: 140 | G42: 161 | H42: 129 | I42: 155 | J42: 123 | K42: 124 | L42: 112 | M42: 122 | N42: 124 | O42: 135 | P42: 111 | Q42: 109 | R42: 107 | S42: 148 | T42: =+P42*0.9 -> 99.9 | U42: =+Q42*0.9 -> 98.1 | AA42: 354 | AB42: 442 | AC42: 450 | AD42: 626 | AE42: 585 | AF42: 481 | AG42: =SUM(N42:Q42) -> 479 | AH42: =AG42*1.05 -> 502.95 | AI42: =AH42*1.05 -> 528.0975 | AJ42: =AI42*1.05 -> 554.50238 | AK42: =AJ42*1.05 -> 582.22749 | AL42: =AK42*1.05 -> 611.33887 | AM42: =AL42*1.05 -> 641.90581 | AN42: =AM42*1.05 -> 674.0011 | AO42: =AN42*1.05 -> 707.70116 | ... AQ42: =AP42*1.05 -> 780.24053
B43: =+B42/B$28 -> 0.049229613 | C43: =+C42/C$28 -> 0.059706704 | D43: =+D42/D$28 -> 0.052700922 | E43: =+E42/E$28 -> 0.051800379 | F43: =+F42/F$28 -> 0.04602023 | G43: =+G42/G$28 -> 0.050675026 | H43: =+H42/H$28 -> 0.038426049 | I43: =+I42/I$28 -> 0.04222091 | ... U43: =+U42/U$28 -> 0.018908684 | AA43: =+AA42/AA$28 -> 0.052335896 | AB43: =+AB42/AB$28 -> 0.056090144 | AC43: =+AC42/AC$28 -> 0.04654441 | AD43: =+AD42/AD$28 -> 0.053380123 | AE43: =+AE42/AE$28 -> 0.044160514 | AF43: =+AF42/AF$28 -> 0.03068934 | AG43: =+AG42/AG$28 -> 0.027871339 | AH43: =+AH42/AH$28 -> 0.025447744 | ... AQ43: =+AQ42/AQ$28 -> 0.011222056
A44: OpEx | B44: =SUM(B38:B42)-B41-B39 -> 677 | C44: =SUM(C38:C42)-C41-C39 -> 898 | D44: =SUM(D38:D42)-D41-D39 -> 978 | E44: =SUM(E38:E42)-E41-E39 -> 1032 | F44: =SUM(F38:F42)-F41-F39 -> 922 | G44: =SUM(G38:G42)-G41-G39 -> 1013 | H44: =SUM(H38:H42)-H41-H39 -> 853 | I44: =SUM(I38:I42)-I41-I39 -> 1055 | ... S44: =SUM(S38:S42)-S41-S39 -> 941 | T44: =SUM(T38:T42) -> 730.61891 | U44: =SUM(U38:U42) -> 762.21798 | AA44: =SUM(AA38:AA42)-AA41-AA39 -> 1795 | AB44: =SUM(AB38:AB42)-AB41-AB39 -> 2308 | AC44: =SUM(AC38:AC42)-AC41-AC39 -> 2497 | AD44: =SUM(AD38:AD42)-AD41-AD39 -> 3585 | AE44: =SUM(AE38:AE42)-AE41-AE39 -> 3843 | AF44: =SUM(AF38:AF42)-AF41-AF39 -> 3359 | AG44: =SUM(AG38:AG42)-AG41-AG39 -> 3298 | AH44: =SUM(AH38:AH42)-AH41-AH39 -> 3575.33 | ... AQ44: =SUM(AQ38:AQ42)-AQ41-AQ39 -> 7471.9508
B45: =+B44/B$28 -> 0.25441563 | C45: =+C44/C$28 -> 0.31354749 | D45: =+D44/D$28 -> 0.32213439 | E45: =+E44/E$28 -> 0.32596336 | F45: =+F44/F$28 -> 0.30307608 | G45: =+G44/G$28 -> 0.31884348 | H45: =+H44/H$28 -> 0.25408852 | I45: =+I44/I$28 -> 0.28737458 | ... U45: =+U44/U$28 -> 0.14691681 | AA45: =+AA44/AA$28 -> 0.26537552 | AB45: =+AB44/AB$28 -> 0.29288699 | AC45: =+AC44/AC$28 -> 0.25826976 | AD45: =+AD44/AD$28 -> 0.30569927 | AE45: =+AE44/AE$28 -> 0.29010061 | AF45: =+AF44/AF$28 -> 0.21431495 | AG45: =+AG44/AG$28 -> 0.19189911 | AH45: =+AH44/AH$28 -> 0.18090085 | ... AQ45: =+AQ44/AQ$28 -> 0.10746769
A46: OpInc / EBIT | B46: =B36-B44 -> -6 | C46: =C36-C44 -> -194 | D46: =D36-D44 -> -228 | E46: =E36-E44 -> -231 | F46: =F36-F44 -> -155.8596 | G46: =G36-G44 -> -246.89257 | H46: =H36-H44 -> 32.097699 | I46: =I36-I44 -> -74.833272 | ... U46: =U36-U44 -> 949.85249 | AA46: =AA36-AA44 -> -73 | AB46: =AB36-AB44 -> -292.82764 | AC46: =AC36-AC44 -> 94.185704 | AD46: =AD36-AD44 -> -658.7883 | AE46: =AE36-AE44 -> -445.87172 | AF46: =AF36-AF44 -> 1365.1948 | AG46: =AG36-AG44 -> 2198.1138 | AH46: =AG46+((AG28-AF28)*0.1) -> 2349.4057 | AI46: =AH46+((AH28-AG28)*0.1) -> 2607.1974 | AJ46: =AI46+((AI28-AH28)*0.1) -> 2903.6578 | AK46: =AJ46+((AJ28-AI28)*0.1) -> 3244.5874 | AL46: =AK46+((AK28-AJ28)*0.1) -> 3636.6563 | AM46: =AL46+((AL28-AK28)*0.1) -> 4087.5356 | AN46: =AM46+((AM28-AL28)*0.1) -> 4606.0468 | AO46: =AN46+((AN28-AM28)*0.1) -> 5202.3347 | ... AQ46: =AP46+((AP28-AO28)*0.1) -> 6676.6565
B47: =+B46/B$28 -> -0.0022547914 | C47: =+C46/C$28 -> -0.06773743 | D47: =+D46/D$28 -> -0.075098814 | E47: =+E46/E$28 -> -0.072962729 | F47: =+F46/F$28 -> -0.051233534 | G47: =+G46/G$28 -> -0.07770986 | H47: =+H46/H$28 -> 0.0095611453 | I47: =+I46/I$28 -> -0.020384057 | ... U47: =+U46/U$28 -> 0.18308319 | AA47: =+AA46/AA$28 -> -0.010792431 | AB47: =+AB46/AB$28 -> -0.037160055 | AC47: =+AC46/AC$28 -> 0.0097418179 | AD47: =+AD46/AD$28 -> -0.056176039 | AE47: =+AE46/AE$28 -> -0.033657991 | AF47: =+AF46/AF$28 -> 0.087103798 | AG47: =+AG46/AG$28 -> 0.12790057 | AH47: =+AH46/AH$28 -> 0.1188728 | ... AQ47: =+AQ46/AQ$28 -> 0.09602912
A48: Finance Inc | B48: 175 | C48: 118 | D48: 102 | E48: 26 | F48: 27 | G48: 33 | H48: 55 | I48: 46 | J48: 59 | K48: 76 | L48: =-M48-K48-J48+AF48 -> 66 | M48: 127 | N48: 71 | O48: 89 | P48: 262 | Q48: 349 | R48: 248 | S48: 86 | T48: =+P48*1.5 -> 393 | U48: =+Q48*1.5 -> 523.5 | AA48: 275 | AB48: 94 | AC48: 246 | AD48: 421 | AE48: 161 | AF48: 328 | AG48: 292 | AH48: =AG48*(1+$AV$66) -> 297.84 | AI48: =AH48*(1+$AV$66) -> 303.7968 | AJ48: =AI48*(1+$AV$66) -> 309.87274 | AK48: =AJ48*(1+$AV$66) -> 316.07019 | AL48: =AK48*(1+$AV$66) -> 322.39159 | AM48: =AL48*(1+$AV$66) -> 328.83943 | AN48: =AM48*(1+$AV$66) -> 335.41621 | AO48: =AN48*(1+$AV$66) -> 342.12454 | ... AQ48: =AP48*(1+$AV$66) -> 355.94637
B49: =+B48/B$28 -> 0.06576475 | C49: =+C48/C$28 -> 0.041201117 | D49: =+D48/D$28 -> 0.033596838 | E49: =+E48/E$28 -> 0.0082122552 | F49: =+F48/F$28 -> 0.00887533 | G49: =+G48/G$28 -> 0.010386806 | H49: =+H48/H$28 -> 0.016383199 | I49: =+I48/I$28 -> 0.012530077 | ... U49: =+U48/U$28 -> 0.10090414 | AA49: =+AA48/AA$28 -> 0.040656416 | AB49: =+AB48/AB$28 -> 0.011928673 | AC49: =+AC48/AC$28 -> 0.025444278 | AD49: =+AD48/AD$28 -> 0.035899412 | AE49: =+AE48/AE$28 -> 0.012153577 | AF49: =+AF48/AF$28 -> 0.02092745 | AG49: =+AG48/AG$28 -> 0.016990461 | AH49: =+AH48/AH$28 -> 0.0150698 | ... AQ49: =+AQ48/AQ$28 -> 0.005119511
A50: Finance exp | B50: -14 | C50: -14 | D50: -18 | E50: -86 | F50: -77 | G50: -27 | H50: -14 | I50: -102 | J50: -53 | K50: -72 | L50: =-M50-K50-J50+AF50 -> -122 | M50: -105 | N50: -252 | O50: -447 | P50: -17 | Q50: -29 | R50: -26 | S50: -21 | T50: 20 | U50: 20 | AA50: -333 | AB50: -510 | AC50: -91 | AD50: -132 | AE50: -220 | AF50: -352 | AG50: -266 | AH50: =AG50*(1+$AV$66) -> -271.32 | AI50: =AH50*(1+$AV$66) -> -276.7464 | AJ50: =AI50*(1+$AV$66) -> -282.28133 | AK50: =AJ50*(1+$AV$66) -> -287.92695 | AL50: =AK50*(1+$AV$66) -> -293.68549 | AM50: =AL50*(1+$AV$66) -> -299.5592 | AN50: =AM50*(1+$AV$66) -> -305.55039 | AO50: =AN50*(1+$AV$66) -> -311.6614 | ... AQ50: =AP50*(1+$AV$66) -> -324.25252
B51: =+B50/B$28 -> -0.00526118 | C51: =+C50/C$28 -> -0.0048882682 | D51: =+D50/D$28 -> -0.0059288538 | E51: =+E50/E$28 -> -0.027163613 | F51: =+F50/F$28 -> -0.025311126 | G51: =+G50/G$28 -> -0.0084982962 | H51: =+H50/H$28 -> -0.0041702689 | I51: =+I50/I$28 -> -0.027784083 | ... U51: =+U50/U$28 -> 0.0038549815 | AA51: =+AA50/AA$28 -> -0.049231224 | AB51: =+AB50/AB$28 -> -0.064719397 | AC51: =+AC50/AC$28 -> -0.009412314 | AD51: =+AD50/AD$28 -> -0.011255873 | AE51: =+AE50/AE$28 -> -0.016607373 | AF51: =+AF50/AF$28 -> -0.022458727 | AG51: =+AG50/AG$28 -> -0.015477612 | AH51: =+AH50/AH$28 -> -0.013727969 | ... AQ51: =+AQ50/AQ$28 -> -0.0046636642
A52: EBT | B52: =SUM(B46:B50)-B49-B47 -> 155 | C52: =SUM(C46:C50)-C49-C47 -> -90 | D52: =SUM(D46:D50)-D49-D47 -> -144 | E52: =SUM(E46:E50)-E49-E47 -> -291 | F52: =SUM(F46:F50)-F49-F47 -> -205.8596 | G52: =SUM(G46:G50)-G49-G47 -> -240.89257 | H52: =SUM(H46:H50)-H49-H47 -> 73.097699 | I52: =SUM(I46:I50)-I49-I47 -> -130.83327 | ... U52: =SUM(U46:U50)-U49-U47 -> 1493.3525 | AA52: =SUM(AA46:AA50)-AA49-AA47 -> -131 | AB52: =SUM(AB46:AB50)-AB49-AB47 -> -708.82764 | AC52: =SUM(AC46:AC50)-AC49 -> 249.19545 | AD52: =SUM(AD46:AD50)-AD49-AD47 -> -369.7883 | AE52: =SUM(AE46:AE50)-AE49-AE47 -> -504.87172 | AF52: =SUM(AF46:AF50)-AF49 -> 1341.2819 | AG52: =SUM(AG46:AG50)-AG49-AG47 -> 2224.1138 | AH52: =SUM(AH46:AH50)-AH49-AH47 -> 2375.9257 | AI52: =SUM(AI46:AI50)-AI49-AI47 -> 2634.2478 | AJ52: =SUM(AJ46:AJ50)-AJ49-AJ47 -> 2931.2492 | AK52: =SUM(AK46:AK50)-AK49-AK47 -> 3272.7306 | AL52: =SUM(AL46:AL50)-AL49-AL47 -> 3665.3624 | AM52: =SUM(AM46:AM50)-AM49-AM47 -> 4116.8158 | AN52: =SUM(AN46:AN50)-AN49-AN47 -> 4635.9126 | ... AQ52: =SUM(AQ46:AQ50)-AQ49-AQ47 -> 6708.3503
B53: =+B52/B$28 -> 0.058248779 | C53: =+C52/C$28 -> -0.031424581 | D53: =+D52/D$28 -> -0.04743083 | E53: =+E52/E$28 -> -0.091914087 | F53: =+F52/F$28 -> -0.067669331 | G53: =+G52/G$28 -> -0.075821349 | H53: =+H52/H$28 -> 0.021774076 | I53: =+I52/I$28 -> -0.035638063 | ... U53: =+U52/U$28 -> 0.28784231 | AA53: =+AA52/AA$28 -> -0.019367238 | AB53: =+AB52/AB$28 -> -0.089950778 | AC53: =+AC52/AC$28 -> 0.025774789 | AD53: =+AD52/AD$28 -> -0.0315325 | AE53: =+AE52/AE$28 -> -0.038111786 | AF53: =+AF52/AF$28 -> 0.085578079 | AG53: =+AG52/AG$28 -> 0.12941342 | AH53: =+AH52/AH$28 -> 0.12021463 | ... AQ53: =+AQ52/AQ$28 -> 0.096484966
A54: Taxes | B54: 24 | C54: 35 | D54: 22 | E54: -21 | F54: 19 | G54: 61 | H54: 8 | I54: -61 | J54: -23 | K54: -4 | L54: 98 | M54: 132 | N54: 103 | O54: 134 | P54: -72 | Q54: -153 | R54: 216 | S54: 175 | T54: =+T52*0.05 -> 64.829528 | U54: =+U52*0.05 -> 74.667625 | AA54: 55 | AB54: -128 | AC54: 283 | AD54: 60 | AE54: 27 | AF54: 203 | AG54: =SUM(N54:Q54) -> 12 | AH54: =AH52*0.05 -> 118.79628 | AI54: =AI52*0.05 -> 131.71239 | AJ54: =AJ52*0.05 -> 146.56246 | AK54: =AK52*0.05 -> 163.63653 | AL54: =AL52*0.12 -> 439.84349 | AM54: =AM52*0.12 -> 494.0179 | AN54: =AN52*0.12 -> 556.30952 | AO54: =AO52*0.22 -> 1151.2155 | AP54: =AP52*0.22 -> 1302.2104 | AQ54: =AQ52*0.22 -> 1475.8371
B55: =+B54/B$28 -> 0.0090191657 | C55: =+C54/C$28 -> 0.01222067 | D55: =+D54/D$28 -> 0.0072463768 | E55: =+E54/E$28 -> -0.0066329754 | F55: =+F54/F$28 -> 0.0062456026 | G55: =+G54/G$28 -> 0.019199854 | H55: =+H54/H$28 -> 0.0023830108 | I55: =+I54/I$28 -> -0.016615971 | ... U55: =+U54/U$28 -> 0.014392116 | AA55: =+AA54/AA$28 -> 0.0081312833 | AB55: =+AB54/AB$28 -> -0.0162433 | AC55: =+AC54/AC$28 -> 0.029271262 | AD55: =+AD54/AD$28 -> 0.0051163057 | AE55: =+AE54/AE$28 -> 0.0020381776 | AF55: =+AF54/AF$28 -> 0.01295205 | AG55: =+AG54/AG$28 -> 0.00069823813 | AH55: =+AH54/AH$28 -> 0.0060107315 | ... AQ55: =+AQ54/AQ$28 -> 0.021226693
A56: Net Inc | B56: =B52-B54 -> 131 | C56: =C52-C54 -> -125 | D56: =D52-D54 -> -166 | E56: =E52-E54 -> -270 | F56: =F52-F54 -> -224.8596 | G56: =G52-G54 -> -301.89257 | H56: =H52-H54 -> 65.097699 | I56: =I52-I54 -> -69.833272 | ... U56: =U52-U54 -> 1418.6849 | AA56: =AA52-AA54 -> -186 | AB56: =AB52-AB54 -> -580.82764 | AC56: =AC52-AC54 -> -33.804554 | AD56: =AD52-AD54 -> -429.7883 | AE56: =AE52-AE54 -> -531.87172 | AF56: =AF52-AF54 -> 1138.2819 | AG56: =AG52-AG54 -> 2212.1138 | AH56: =AH52-AH54 -> 2257.1294 | ... AQ56: =AQ52-AQ54 -> 5232.5133 | AR56: =AQ56*(1+$AV$64) -> 5337.1635 | AS56: =AR56*(1+$AV$64) -> 5443.9068 | AT56: =AS56*(1+$AV$64) -> 5552.7849 | AU56: =AT56*(1+$AV$64) -> 5663.8406 | AV56: =AU56*(1+$AV$64) -> 5777.1175 | AW56: =AV56*(1+$AV$64) -> 5892.6598 | AX56: =AW56*(1+$AV$64) -> 6010.513 | AY56: =AX56*(1+$AV$64) -> 6130.7233 | ... DG56: =DF56*(1+$AV$64) -> 20115.092
B57: =+B56/B$28 -> 0.049229613 | C57: =+C56/C$28 -> -0.043645251 | D57: =+D56/D$28 -> -0.054677207 | E57: =+E56/E$28 -> -0.085281112 | F57: =+F56/F$28 -> -0.073914933 | G57: =+G56/G$28 -> -0.095021204 | H57: =+H56/H$28 -> 0.019391065 | I57: =+I56/I$28 -> -0.019022092 | ... U57: =+U56/U$28 -> 0.2734502 | AA57: =+AA56/AA$28 -> -0.027498522 | AB57: =+AB56/AB$28 -> -0.073707479 | AC57: =+AC56/AC$28 -> -0.0034964734 | AD57: =+AD56/AD$28 -> -0.036648805 | AE57: =+AE56/AE$28 -> -0.040149964 | AF57: =+AF56/AF$28 -> 0.072626029 | AG57: =+AG56/AG$28 -> 0.12871518 | AH57: =+AH56/AH$28 -> 0.1142039 | ... AQ57: =+AQ56/AQ$28 -> 0.075258274
A58: EPS | B58: =B56/B60 -> 0.66471481 | C58: -0.85 | D58: -0.99 | E58: =E56/E60 -> -1.397313 | F58: =F56/F60 -> -1.1616929 | G58: =G56/G60 -> -1.5527856 | H58: =H56/H60 -> 0.32875633 | I58: =I56/I60 -> -0.35622677 | J58: =J56/J60 -> 0.96772796 | K58: =K56/K60 -> 1.3303404 | L58: 1.45 | M58: =M56/M60 -> 1.7566875 | N58: =N56/N60 -> 1.0709754 | O58: =O56/O60 -> -0.41805623 | P58: 3.28 | Q58: 4.43 | R58: =+R56/R60 -> 3.4455989 | S58: =+S56/S60 -> 2.6094226 | T58: =+T56/T60 -> 5.9571588 | U58: =+U56/U60 -> 6.9304823 | AA58: -1.03 | AB58: =AB56/AB60 -> -3.0963767 | AC58: -1.03 | AD58: -2.93 | AE58: =AE56/AE60 -> -2.7313011 | AF58: =AF56/AF60 -> 5.499212 | AG58: 10.51 | AH58: =AH56/AH60 -> 10.414005 | AI58: =AI56/AI60 -> 11.319869 | AJ58: =AJ56/AJ60 -> 12.349158 | AK58: =AK56/AK60 -> 13.517447 | AL58: =AL56/AL60 -> 14.165282 | AM58: =AM56/AM60 -> 16.070691 | AN58: =AN56/AN60 -> 18.279872 | AO58: =AO56/AO60 -> 18.473475 | ... AQ58: =AQ56/AQ60 -> 24.163508
F59: =+F58/B58-1 -> -2.7476561 | G59: =+G58/C58-1 -> 0.82680656 | H59: =+H58/D58-1 -> -1.3320771 | I59: =+I58/E58-1 -> -0.74506301 | J59: =+J58/F58-1 -> -1.8330325 | K59: =+K58/G58-1 -> -1.8567445 | L59: =+L58/H58-1 -> 3.4105614 | M59: =+M58/I58-1 -> -5.9313742 | ... U59: =+U58/Q58-1 -> 0.56444296 | AB59: =+AB58/AA58-1 -> 2.006191 | AC59: =+AC58/AB58-1 -> -0.66735314 | AD59: =+AD58/AC58-1 -> 1.8446602 | AE59: =+AE58/AD58-1 -> -0.067815335 | AF59: =+AF58/AE58-1 -> -3.0134038 | AG59: =+AG58/AF58-1 -> 0.9111829 | AH59: =+AH58/AG58-1 -> -0.0091336782 | AI59: =+AI58/AH58-1 -> 0.086985125 | ... AQ59: =+AQ58/AP58-1 -> 0.14478008
A60: Shares | B60: 197.077 | C60: 195.859 | D60: 195.988 | E60: 193.228 | F60: 193.562 | G60: 194.42 | H60: 198.012 | I60: 196.036 | J60: 203.773 | K60: 206.119 | L60: 207.3995 | M60: 209.012 | N60: 210.243 | O60: 205.427 | P60: 213.789 | Q60: 212.49 | R60: 209.28045 | S60: 208.85847 | T60: =+S60*0.99 -> 206.76988 | U60: =+T60*0.99 -> 204.70218 | AA60: 187.583 | AB60: 187.583 | AC60: 193.943 | AD60: 195.846 | AE60: 194.732 | AF60: 206.99 | AG60: =Q60 -> 212.49 | AH60: =+AG60*1.02 -> 216.7398 | AI60: =+AH60*1.02 -> 221.0746 | AJ60: =+AI60*1.02 -> 225.49609 | AK60: =+AJ60*1.02 -> 230.00601 | AL60: =+AK60*0.99 -> 227.70595 | AM60: =+AL60*0.99 -> 225.42889 | AN60: =+AM60*0.99 -> 223.1746 | AO60: =+AN60*0.99 -> 220.94286 | AP60: =+AO60*0.99 -> 218.73343 | AQ60: =+AP60*0.99 -> 216.54609
C61: =+C60/B60-1 -> -0.0061803255 | D61: =+D60/C60-1 -> 0.00065863708 | E61: =+E60/D60-1 -> -0.014082495 | F61: =+F60/E60-1 -> 0.001728528 | G61: =+G60/F60-1 -> 0.0044326882 | H61: =+H60/G60-1 -> 0.018475465 | I61: =+I60/H60-1 -> -0.0099791932 | J61: =+J60/I60-1 -> 0.039467241 | ... U61: =+U60/T60-1 -> -0.01 | AB61: =+AB60/AA60-1 -> 0 | AC61: =+AC60/AB60-1 -> 0.033904991 | AD61: =+AD60/AC60-1 -> 0.0098121613 | AE61: =+AE60/AD60-1 -> -0.0056881427 | AF61: =+AF60/AE60-1 -> 0.062948052 | AG61: =+AG60/AF60-1 -> 0.026571332 | AH61: =+AH60/AG60-1 -> 0.02 | AI61: =+AI60/AH60-1 -> 0.02 | ... AQ61: =+AQ60/AP60-1 -> -0.01
BA63: Gordon Growth Model
A64: Gross Margin | B64: =B36/B28 -> 0.25216084 | C64: =C36/C28 -> 0.24581006 | D64: =D36/D28 -> 0.24703557 | E64: =E36/E28 -> 0.25300063 | F64: =F36/F28 -> 0.25184255 | G64: =G36/G28 -> 0.24113362 | H64: =H36/H28 -> 0.26364967 | I64: =I36/I28 -> 0.26699052 | ... U64: =U36/U28 -> 0.33 | AA64: =AA36/AA28 -> 0.25458309 | AB64: =AB36/AB28 -> 0.25572694 | AC64: =AC36/AC28 -> 0.26801158 | AD64: =AD36/AD28 -> 0.24952323 | AE64: =AE36/AE28 -> 0.25644262 | AF64: =AF36/AF28 -> 0.30141875 | AG64: =AG36/AG28 -> 0.31979968 | AH64: =AH36/AH28 -> 0.32 | ... AQ64: =AQ36/AQ28 -> 0.365 | AU64: Terminal | AV64: 0.02 | AX64: EV | AY64: =Main!F6 -> 93110.018 | BA64: Payout Ratio | BB64: =+SUM(P167:S167)/SUM(P56:S56) -> 0.23148757 | BD64: Equity Value | BE64: =+BB66 -> 29193.736
A65: Op Margin | B65: =B46/B28 -> -0.0022547914 | C65: =C46/C28 -> -0.06773743 | D65: =D46/D28 -> -0.075098814 | E65: =E46/E28 -> -0.072962729 | F65: =F46/F28 -> -0.051233534 | G65: =G46/G28 -> -0.07770986 | H65: =H46/H28 -> 0.0095611453 | I65: =I46/I28 -> -0.020384057 | ... U65: =U46/U28 -> 0.18308319 | AA65: =AA46/AA28 -> -0.010792431 | AB65: =AB46/AB28 -> -0.037160055 | AC65: =AC46/AC28 -> 0.0097418179 | AD65: =AD46/AD28 -> -0.056176039 | AE65: =AE46/AE28 -> -0.033657991 | AF65: =AF46/AF28 -> 0.087103798 | AG65: =AG46/AG28 -> 0.12790057 | AH65: =AH46/AH28 -> 0.1188728 | ... AQ65: =AQ46/AQ28 -> 0.09602912 | AU65: Discount | AV65: =+Main!E9 -> 0.1009541 | AX65: 2026 E | AY65: =AH28 -> 19764.031 | BA65: Sustainable Growth | BB65: =+(1-BB64)*AG78 -> 0.072794251 | BD65: Shares | BE65: =+Main!F2 -> 209.28045
A66: NI Margin | B66: =B56/B28 -> 0.049229613 | C66: =C56/C28 -> -0.043645251 | D66: =D56/D28 -> -0.054677207 | E66: =E56/E28 -> -0.085281112 | F66: =F56/F28 -> -0.073914933 | G66: =G56/G28 -> -0.095021204 | H66: =H56/H28 -> 0.019391065 | I66: =I56/I28 -> -0.019022092 | ... U66: =U56/U28 -> 0.2734502 | AA66: =AA56/AA28 -> -0.027498522 | AB66: =AB56/AB28 -> -0.073707479 | AC66: =AC56/AC28 -> -0.0034964734 | AD66: =AD56/AD28 -> -0.036648805 | AE66: =AE56/AE28 -> -0.040149964 | AF66: =AF56/AF28 -> 0.072626029 | AG66: =AG56/AG28 -> 0.12871518 | AH66: =AH56/AH28 -> 0.1142039 | ... AQ66: =AQ56/AQ28 -> 0.075258274 | AU66: ROIC | AV66: 0.02 | AX66: EV/E | AY66: =AY64/AY65 -> 4.7110844 | BA66: Equity Value | BB66: =+(SUM(P167:S167)*(1+BB65))/(Main!B9-BB65) -> 29193.736 | BD66: Price | BE66: =+BE64/BE65 -> 139.49576
A67: Rule of 40 | F67: =+F65+F29 -> 0.091998482 | G67: =+G65+G29 -> 0.03161536 | H67: =+H65+H29 -> 0.11532455 | I67: =+I65+I29 -> 0.13917587 | J67: =+J65+J29 -> 0.24153206 | K67: =+K65+K29 -> 0.26824758 | L67: =+L65+L29 -> 0.3018807 | M67: =+M65+M29 -> 0.26801921 | ... U67: =+U65+U29 -> 0.32808319 | AB67: =+AB65+AB29 -> 0.12785656 | AC67: =+AC65+AC29 -> 0.2366421 | AD67: =+AD65+AD29 -> 0.15679318 | AE67: =+AE65+AE29 -> 0.095947973 | AF67: =+AF65+AF29 -> 0.27024285 | AG67: =+AG65+AG29 -> 0.22442964 | AH67: =+AH65+AH29 -> 0.2688728 | AI67: =+AI65+AI29 -> 0.26470981 | ... AQ67: =+AQ65+AQ29 -> 0.24602912 | AU67: NPV | AV67: =NPV(AV65,AH56:DG56) -> 45319.58 | BA67: Just P/E | BE67: =+BE66/Main!F1-1 -> -0.71237987
A68: Tax Rate | B68: =+B54/B52 -> 0.15483871 | C68: =+C54/C52 -> -0.38888889 | D68: =+D54/D52 -> -0.15277778 | E68: =+E54/E52 -> 0.072164948 | F68: =+F54/F52 -> -0.092295912 | G68: =+G54/G52 -> -0.25322491 | H68: =+H54/H52 -> 0.10944257 | I68: =+I54/I52 -> 0.46624226 | ... U68: =+U54/U52 -> 0.05 | AA68: =+AA54/AA52 -> -0.41984733 | AB68: =+AB54/AB52 -> 0.18057987 | AC68: =+AC54/AC52 -> 1.1356548 | AD68: =+AD54/AD52 -> -0.162255 | AE68: =+AE54/AE52 -> -0.053478931 | AF68: =+AF54/AF52 -> 0.15134775 | AG68: =+AG54/AG52 -> 0.0053954075 | AH68: =+AH54/AH52 -> 0.05 | ... AQ68: =+AQ54/AQ52 -> 0.22 | AU68: Share | AV68: =AV67/(Main!F2) -> 216.54952
AU69: Diff | AV69: =AV68/Main!F1-1 -> -0.55350615 | AX69: yield | AY69: =AY65/AY64 -> 0.21226535 | BA69: Useless for this Company at this stage
A70: EBITDA | B70: =B46+B128 -> 31 | C70: =C46+C128 -> -154 | D70: =D46+D128 -> -184 | E70: =E46+E128 -> -181 | F70: =F46+F128 -> -111.8596 | G70: =G46+G128 -> -202.89257 | H70: =H46+H128 -> 68.097699 | I70: =I46+I128 -> -40.833272 | ... S70: =S46+S128 -> 684 | AA70: =AA46+AA128 -> 14 | AB70: =AB46+AB128 -> -181.82764 | AC70: =AC46+AC128 -> 221.1857 | AD70: =AD46+AD128 -> -487.7883 | AE70: =AE46+AE128 -> -287.87172 | AF70: =AF46+AF128 -> 1486.1948 | AG70: =AG46+AG128 -> 2300.1138 | AH70: =AH46+AH128 -> 2487.7539 | ... AQ70: =AQ46+AQ128 -> 7163.3484
A71: Inc. Margin | F71: =+(F46-B46)/(F28-B28) -> -0.39318741 | G71: =+(G46-C46)/(G28-C28) -> -0.16892787 | H71: =+(H46-D46)/(H28-D28) -> 0.81002667 | I71: =+(I46-E46)/(I28-E28) -> 0.30913898 | J71: =+(J46-F46)/(J28-F28) -> 0.54549773 | K71: =+(K46-G46)/(K28-G28) -> 0.81431549 | L71: =+(L46-H46)/(L28-H28) -> 0.66883773 | M71: =+(M46-I46)/(M28-I28) -> 0.96672516 | ... S71: =+(S46-O46)/(S28-O28) -> 0.426252 | AB71: =+(AB46-AA46)/(AB28-AA28) -> -0.19694775 | AC71: =+(AC46-AB46)/(AC28-AB28) -> 0.2164488 | AD71: =+(AD46-AC46)/(AD28-AC28) -> -0.36569427 | AE71: =+(AE46-AD46)/(AE28-AD28) -> 0.14008438 | AF71: =+(AF46-AE46)/(AF28-AE28) -> 0.74650324 | AG71: =+(AG46-AF46)/(AG28-AF28) -> 0.55053772
A74: Premium Reve | B74: =B24/B28 -> 0.8940248 | C74: =C24/C28 -> 0.87430168 | D74: =D24/D28 -> 0.87318841 | E74: =E24/E28 -> 0.85818067 | F74: =F24/F28 -> 0.89180631 | G74: =G24/G28 -> 0.8728065 | H74: =H24/H28 -> 0.86682017 | I74: =I24/I28 -> 0.86348571 | ... S74: =S24/S28 -> 0 | AA74: =AA24/AA28 -> 0.89976345 | AB74: =AB24/AB28 -> 0.90543705 | AC74: =AC24/AC28 -> 0.87503491 | AD74: =AD24/AD28 -> 0.87412083 | AE74: =AE24/AE28 -> 0.87309489 | AF74: =AF24/AF28 -> 0.88169644 | AG74: =AG24/AG28 -> 0.89554859
A75: Book Value | B75: =B103-B116 -> 2147 | C75: =C103-C116 -> 2301 | D75: =D103-D116 -> 2233 | E75: =E103-E116 -> 2401 | F75: =F103-F116 -> 2342 | G75: =G103-G116 -> 2054 | H75: =H103-H116 -> 2139 | I75: =I103-I116 -> 2523 | ... S75: =S103-S116 -> 8385 | AA75: =AA103-AA116 -> 0 | AB75: =AB103-AB116 -> 2805 | AC75: =AC103-AC116 -> 2119 | AD75: =AD103-AD116 -> 9082 | AE75: =AE103-AE116 -> 9058 | AF75: =AF103-AF116 -> 17726 | AG75: =AG103-AG116 -> 28985
A77: ROA | F77: =+SUM(C56:F56)/AVERAGE(C103:F103) -> -0.10413909 | G77: =+SUM(D56:G56)/AVERAGE(D103:G103) -> -0.12790225 | H77: =+SUM(E56:H56)/AVERAGE(E103:H103) -> -0.097330071 | I77: =+SUM(F56:I56)/AVERAGE(F103:I103) -> -0.069071477 | J77: =+SUM(G56:J56)/AVERAGE(G103:J103) -> -0.013541385 | K77: =+SUM(H56:K56)/AVERAGE(H103:K103) -> 0.053092488 | L77: =+SUM(I56:L56)/AVERAGE(I103:L103) -> 0.07363906 | M77: =+SUM(J56:M56)/AVERAGE(J103:M103) -> 0.10902916 | ... S77: =+SUM(P56:S56)/AVERAGE(P103:S103) -> 0.23607439 | AB77: =+SUM(AB56)/AVERAGE(AA103:AB103) -> -0.18363188 | AC77: =+SUM(AC56)/AVERAGE(AB103:AC103) -> -0.0050095664 | AD77: =+SUM(AD56)/AVERAGE(AC103:AD103) -> -0.023316875 | AE77: =+SUM(AE56)/AVERAGE(AD103:AE103) -> -0.017590096 | AF77: =+SUM(AF56)/AVERAGE(AE103:AF103) -> 0.031375779 | AG77: =+SUM(AG56)/AVERAGE(AF103:AG103) -> 0.04531395
A78: ROE | F78: =+F79*F80*F66 -> -0.38588871 | G78: =+G79*G80*G66 -> -0.52282699 | H78: =+H79*H80*H66 -> 0.11060324 | I78: =+I79*I80*I66 -> -0.11128081 | J78: =+J79*J80*J66 -> 0.29951148 | K78: =+K79*K80*K66 -> 0.34089948 | L78: =+L79*L80*L66 -> 0.30884166 | M78: =+M79*M80*M66 -> 0.30612645 | ... S78: =+S79*S80*S66 -> 0.25431661 | AB78: =+AB79*AB80*AB66 -> -0.41413735 | AC78: =+AC79*AC80*AC66 -> -0.013730526 | AD78: =+AD79*AD80*AD66 -> -0.076741058 | AE78: =+AE79*AE80*AE66 -> -0.058640763 | AF78: =+AF79*AF80*AF66 -> 0.084997155 | AG78: =+AG79*AG80*AG66 -> 0.09472098
A79: A Turnover | F79: =+SUM(C28:F28)/AVERAGE(C103:F103) -> 1.6045242 | G79: =+SUM(D28:G28)/AVERAGE(D103:G103) -> 1.6501708 | H79: =+SUM(E28:H28)/AVERAGE(E103:H103) -> 1.6950807 | I79: =+SUM(F28:I28)/AVERAGE(F103:I103) -> 1.72163 | J79: =+SUM(G28:J28)/AVERAGE(G103:J103) -> 1.7128005 | K79: =+SUM(H28:K28)/AVERAGE(H103:K103) -> 1.6464256 | L79: =+SUM(I28:L28)/AVERAGE(I103:L103) -> 1.5847618 | M79: =+SUM(J28:M28)/AVERAGE(J103:M103) -> 1.5006374 | ... S79: =+SUM(P28:S28)/AVERAGE(P103:S103) -> 1.2805424 | AB79: =+SUM(AB28)/AVERAGE(AA103:AB103) -> 2.4913602 | AC79: =+SUM(AC28)/AVERAGE(AB103:AC103) -> 1.4327483 | AD79: =+SUM(AD28)/AVERAGE(AC103:AD103) -> 0.6362247 | AE79: =+SUM(AE28)/AVERAGE(AD103:AE103) -> 0.43810987 | AF79: =+SUM(AF28)/AVERAGE(AE103:AF103) -> 0.43201838 | AG79: =+SUM(AG28)/AVERAGE(AF103:AG103) -> 0.35204822
A80: Financial Leverage | F80: =+AVERAGE(C103:F103)/AVERAGE(C122:F122) -> 3.2537458 | G80: =+AVERAGE(D103:G103)/AVERAGE(D122:G122) -> 3.33433 | H80: =+AVERAGE(E103:H103)/AVERAGE(E122:H122) -> 3.3649284 | I80: =+AVERAGE(F103:I103)/AVERAGE(F122:I122) -> 3.3979907 | J80: =+AVERAGE(G103:J103)/AVERAGE(G122:J122) -> 3.2244389 | K80: =+AVERAGE(H103:K103)/AVERAGE(H122:K122) -> 2.874816 | L80: =+AVERAGE(I103:L103)/AVERAGE(I122:L122) -> 2.5889704 | M80: =+AVERAGE(J103:M103)/AVERAGE(J122:M122) -> 2.3569333 | ... S80: =+AVERAGE(P103:S103)/AVERAGE(P122:S122) -> 1.7407624 | AB80: =+AVERAGE(AA103:AB103)/AVERAGE(AA122:AB122) -> 2.2552585 | AC80: =+AVERAGE(AB103:AC103)/AVERAGE(AB122:AC122) -> 2.7408611 | AD80: =+AVERAGE(AC103:AD103)/AVERAGE(AC122:AD122) -> 3.291224 | AE80: =+AVERAGE(AD103:AE103)/AVERAGE(AD122:AE122) -> 3.3337376 | AF80: =+AVERAGE(AE103:AF103)/AVERAGE(AE122:AF122) -> 2.7090054 | AG80: =+AVERAGE(AF103:AG103)/AVERAGE(AF122:AG122) -> 2.0903271
A81: Financial Leverage % | F81: =+F78-F77 -> -0.28174962 | G81: =+G78-G77 -> -0.39492474 | H81: =+H78-H77 -> 0.20793332 | I81: =+I78-I77 -> -0.042209335 | J81: =+J78-J77 -> 0.31305286 | K81: =+K78-K77 -> 0.28780699 | L81: =+L78-L77 -> 0.2352026 | M81: =+M78-M77 -> 0.19709729 | ... S81: =+S78-S77 -> 0.018242217 | AB81: =+AB78-AB77 -> -0.23050547 | AC81: =+AC78-AC77 -> -0.0087209592 | AD81: =+AD78-AD77 -> -0.053424183 | AE81: =+AE78-AE77 -> -0.041050667 | AF81: =+AF78-AF77 -> 0.053621376 | AG81: =+AG78-AG77 -> 0.04940703 | AX81: EV | AY81: =+AV84 -> 100724.81
AU82: Terminal | AV82: 0.02 | AX82: Debt (-) | AY82: =+Main!F5 -> 414
A83: NWC | B83: =+B94+B92+B95-(B105+B107+B109) -> -2245 | C83: =+C94+C92+C95-(C105+C107+C109) -> -2340 | D83: =+D94+D92+D95-(D105+D107+D109) -> -2527 | E83: =+E94+E92+E95-(E105+E107+E109) -> -2484 | F83: =+F94+F92+F95-(F105+F107+F109) -> -2561 | G83: =+G94+G92+G95-(G105+G107+G109) -> -2583 | H83: =+H94+H92+H95-(H105+H107+H109) -> -2686 | I83: =+I94+I92+I95-(I105+I107+I109) -> -3020 | ... S83: =+S94+S92+S95-(S105+S107+S109) -> -3688 | AB83: =+AB94+AB92+AB95-(AB105+AB107+AB109) -> -2189 | AC83: =+AC94+AC92+AC95-(AC105+AC107+AC109) -> -2257 | AD83: =+AD94+AD92+AD95-(AD105+AD107+AD109) -> -9596 | AE83: =+AE94+AE92+AE95-(AE105+AE107+AE109) -> -10850 | AF83: =+AF94+AF92+AF95-(AF105+AF107+AF109) -> -12557 | AG83: =+AG94+AG92+AG95-(AG105+AG107+AG109) -> -13477 | AH83: =+AH94+AH92+AH95-(AH105+AH107+AH109) -> -13578.137 | AI83: =+AI94+AI92+AI95-(AI105+AI107+AI109) -> -15715.914 | ... AQ83: =+AQ94+AQ92+AQ95-(AQ105+AQ107+AQ109) -> -50411.279 | AU83: Discount | AV83: =+Main!E9 -> 0.1009541 | AX83: Cash (+) | AY83: =+Main!F4 -> 8805
A84: NOPAT | B84: =+B46*(1-B68) -> -5.0709677 | C84: =+C46*(1-C68) -> -269.44444 | D84: =+D46*(1-D68) -> -262.83333 | E84: =+E46*(1-E68) -> -214.3299 | F84: =+F46*(1-F68) -> -170.24481 | G84: =+G46*(1-G68) -> -309.41192 | H84: =+H46*(1-H68) -> 28.584844 | I84: =+I46*(1-I68) -> -39.942838 | ... S84: =+S46*(1-S68) -> 495.79861 | AB84: =+AB46*(1-AB68) -> -239.94886 | AC84: =+AC46*(1-AC68) -> -12.776741 | AD84: =+AD46*(1-AD68) -> -765.67999 | AE84: =+AE46*(1-AE68) -> -469.71646 | AF84: =+AF46*(1-AF68) -> 1158.5756 | AG84: =+AG46*(1-AG68) -> 2186.254 | AH84: =+AH46*(1-AH68) -> 2231.9354 | AI84: =+AI46*(1-AI68) -> 2476.8375 | ... AQ84: =+AQ46*(1-AQ68) -> 5207.7921 | AU84: EV | AV84: =+NPV(AV83,AH85:AP85,AQ85+AV85) -> 100724.81 | AX84: Equity Value | AY84: =+AY81-AY82+AY83 -> 109115.81
A85: UFCF | AC85: =+AC84+AC128-AC142-(AC83-AB83) -> 97.223259 | AD85: =+AD84+AD128-AD142-(AD83-AC83) -> 6719.32 | AE85: =+AE84+AE128-AE142-(AE83-AD83) -> 936.28354 | AF85: =+AF84+AF128-AF142-(AF83-AE83) -> 2969.5756 | AG85: =+AG84+AG128-AG142-(AG83-AF83) -> 3149.254 | AH85: =+AH84+AH128-AH142-(AH83-AG83) -> 2418.3204 | AI85: =+AI84+AI128-AI142-(AI83-AH83) -> 4725.9256 | AJ85: =+AJ84+AJ128-AJ142-(AJ83-AI83) -> 5370.6001 | ... AQ85: =+AQ84+AQ128-AQ142-(AQ83-AP83) -> 12425.489 | AU85: TV | AV85: =+AQ85*(1+AV82)/(AV83-AV82) -> 156557.84 | AX85: Shares | AY85: =+Main!F2 -> 209.28045
AU86: Diff | AV86: =+AV84/Main!F6-1 -> 0.081782701 | AX86: Price | AY86: =+AY84/AY85 -> 521.38557
A87: A/L | B87: =B103/B116 -> 1.4388798 | C87: =C103/C116 -> 1.4523295 | D87: =D103/D116 -> 1.4135951 | E87: =E103/E116 -> 1.4586437 | F87: =F103/F116 -> 1.4515134 | G87: =G103/G116 -> 1.3906428 | H87: =H103/H116 -> 1.3922611 | I87: =I103/I116 -> 1.4332818 | ... S87: =S103/S116 -> 2.5634906 | AA87: =AA103/AA116 -> #DIV/0! | AB87: =AB103/AB116 -> 1.7966487 | AC87: =AC103/AC116 -> 1.4195209 | AD87: =AD103/AD116 -> 1.4405957 | AE87: =AE103/AE116 -> 1.4170158 | AF87: =AF103/AF116 -> 1.7369559 | AG87: =AG103/AG116 -> 2.0786722 | AY87: =+AY86/Main!F1-1 -> 0.075021797
A90: Cash | B90: =+2721+82 -> 2803 | C90: =+2786+84 -> 2870 | D90: =+2851+86 -> 2937 | E90: =+78+2483 -> 2561 | F90: =+2443+77 -> 2520 | G90: =+2550+76 -> 2626 | H90: =+2618+75 -> 2693 | I90: =+3114+75 -> 3189 | J90: =+3451+72 -> 3523 | K90: =+70+4054 -> 4124 | L90: =+72+4688 -> 4760 | M90: =+4781+68 -> 4849 | N90: =+65+5019 -> 5084 | O90: =+59+5161 -> 5220 | P90: =+5456+61 -> 5517 | Q90: =+5258+61 -> 5319 | R90: =+59+5255 -> 5314 | S90: =+5938+56 -> 5994 | AB90: =+1151+78 -> 1229 | AC90: =+2744+77 -> 2821 | AD90: =SUM(B90:E90) -> 11171 | AE90: =SUM(F90:I90) -> 11028 | AF90: =SUM(J90:M90) -> 17256 | AG90: =SUM(N90:Q90) -> 21140
A91: Investments | B91: =+816+682 -> 1498 | C91: =+782+720 -> 1502 | D91: =+630+815 -> 1445 | E91: =+867+1138 -> 2005 | F91: =+1134+995 -> 2129 | G91: =+1015+866 -> 1881 | H91: =+903+1097 -> 2000 | I91: =+1215+1100 -> 2315 | J91: =+1220+1534 -> 2754 | K91: =+1344+1931 -> 3275 | L91: =+1392+1604 -> 2996 | M91: =+1635+2667 -> 4302 | N91: =+1958+2894 -> 4852 | O91: =+2417+3183 -> 5600 | P91: =+3606+2888 -> 6494 | Q91: =+2181+4209 -> 6390 | R91: =+3491+1194 -> 4685 | S91: =+3450+1118 -> 4568 | AB91: =+596+2277 -> 2873 | AC91: =+756+916 -> 1672 | AD91: =SUM(B91:E91) -> 6450 | AE91: =SUM(F91:I91) -> 8325 | AF91: =SUM(J91:M91) -> 13327 | AG91: =SUM(N91:Q91) -> 23336
A92: Income tax receivables | B92: 5 | C92: 4 | D92: 2 | E92: 5 | F92: 5 | G92: 8 | H92: 8 | I92: 20 | J92: 21 | K92: 35 | L92: 27 | M92: 28 | N92: 46 | O92: 83 | P92: 117 | Q92: 116 | R92: 94 | S92: 92 | AB92: 4 | AC92: 5 | AD92: =SUM(B92:E92) -> 16 | AE92: =SUM(F92:I92) -> 41 | AF92: =SUM(J92:M92) -> 111 | AG92: =SUM(N92:Q92) -> 362 | AH92: =+AH28*0.02 -> 395.28062 | AI92: =+AI28*0.02 -> 454.57271 | AJ92: =+AJ28*0.02 -> 522.75862 | AK92: =+AK28*0.02 -> 601.17241 | AL92: =+AL28*0.02 -> 691.34827 | AM92: =+AM28*0.02 -> 795.05051 | AN92: =+AN28*0.02 -> 914.30809 | AO92: =+AO28*0.02 -> 1051.4543 | ... AQ92: =+AQ28*0.02 -> 1390.5483
F93: =+F92/B92-1 -> 0 | G93: =+G92/C92-1 -> 1 | H93: =+H92/D92-1 -> 3 | I93: =+I92/E92-1 -> 3 | J93: =+J92/F92-1 -> 3.2 | K93: =+K92/G92-1 -> 3.375 | L93: =+L92/H92-1 -> 2.375 | M93: =+M92/I92-1 -> 0.4 | ... S93: =+S92/O92-1 -> 0.10843373 | AB93: =+AB92/AB$28 -> 0.00050760311 | AC93: =+AC92/AC$28 -> 0.00051716011 | AD93: =+AD92/AD$28 -> 0.0013643482 | AE93: =+AE92/AE$28 -> 0.0030950104 | AF93: =+AF92/AF$28 -> 0.0070821553 | AG93: =+AG92/AG$28 -> 0.021063517 | AH93: =+AH92/AH$28 -> 0.02 | AI93: =+AI92/AI$28 -> 0.02 | ... AQ93: =+AQ92/AQ$28 -> 0.02
A94: A/R | B94: 556 | C94: 613 | D94: 648 | E94: 690 | F94: 555 | G94: 632 | H94: 747 | I94: 858 | J94: 777 | K94: 753 | L94: 749 | M94: 771 | N94: 749 | O94: 736 | P94: 735 | Q94: 802 | R94: 683 | S94: 780 | AB94: 464 | AC94: 621 | AD94: =SUM(B94:E94) -> 2507 | AE94: =SUM(F94:I94) -> 2792 | AF94: =SUM(J94:M94) -> 3050 | AG94: =SUM(N94:Q94) -> 3022 | AH94: =+AH156*AH28/365 -> 3437.252 | AI94: =+AI156*AI28/365 -> 3890.5695 | AJ94: =+AJ156*AJ28/365 -> 4402.5442 | AK94: =+AK156*AK28/365 -> 4980.5734 | AL94: =+AL156*AL28/365 -> 5632.9542 | AM94: =+AM156*AM28/365 -> 6368.9863 | AN94: =+AN156*AN28/365 -> 7199.0866 | AO94: =+AO156*AO28/365 -> 8134.9147 | ... AQ94: =+AQ156*AQ28/365 -> 10377.453
A95: Other | B95: 270 | C95: 337 | D95: 343 | E95: 307 | F95: 295 | G95: 273 | H95: 225 | I95: 168 | J95: 175 | K95: 158 | L95: 147 | M95: 132 | N95: 146 | O95: 136 | P95: 143 | Q95: 111 | R95: 136 | S95: 116 | AB95: 151 | AC95: 246 | AD95: =SUM(B95:E95) -> 1257 | AE95: =SUM(F95:I95) -> 961 | AF95: =SUM(J95:M95) -> 612 | AG95: =SUM(N95:Q95) -> 536 | AH95: =+AH28*0.03 -> 592.92092 | AI95: =+AI28*0.03 -> 681.85906 | AJ95: =+AJ28*0.03 -> 784.13792 | AK95: =+AK28*0.03 -> 901.75861 | AL95: =+AL28*0.03 -> 1037.0224 | AM95: =+AM28*0.03 -> 1192.5758 | AN95: =+AN28*0.03 -> 1371.4621 | AO95: =+AO28*0.03 -> 1577.1814 | ... AQ95: =+AQ28*0.03 -> 2085.8225
F96: =+F95/B95-1 -> 0.092592593 | G96: =+G95/C95-1 -> -0.18991098 | H96: =+H95/D95-1 -> -0.34402332 | I96: =+I95/E95-1 -> -0.45276873 | J96: =+J95/F95-1 -> -0.40677966 | K96: =+K95/G95-1 -> -0.42124542 | L96: =+L95/H95-1 -> -0.34666667 | M96: =+M95/I95-1 -> -0.21428571 | ... S96: =+S95/O95-1 -> -0.14705882 | AB96: =+AB95/AB$28 -> 0.019162017 | AC96: =+AC95/AC$28 -> 0.025444278 | AD96: =+AD95/AD$28 -> 0.1071866 | AE96: =+AE95/AE$28 -> 0.072544025 | AF96: =+AF95/AF$28 -> 0.039047559 | AG96: =+AG95/AG$28 -> 0.03118797 | AH96: =+AH95/AH$28 -> 0.03 | AI96: =+AI95/AI$28 -> 0.03 | ... AQ96: =+AQ95/AQ$28 -> 0.03
A97: Lease ROU | B97: 443 | C97: 445 | D97: 453 | E97: 417 | F97: 413 | G97: 344 | H97: 343 | I97: 300 | J97: 274 | K97: 254 | L97: 235 | M97: 226 | N97: 223 | O97: 256 | P97: 242 | Q97: 234 | R97: 227 | S97: 225 | AB97: 444 | AC97: 437 | AD97: =SUM(B97:E97) -> 1758 | AE97: =SUM(F97:I97) -> 1400 | AF97: =SUM(J97:M97) -> 989 | AG97: =SUM(N97:Q97) -> 955
A98: PP&E | B98: 369 | C98: 373 | D98: 382 | E98: 348 | F98: 331 | G98: 280 | H98: 275 | I98: 247 | J98: 224 | K98: 211 | L98: 195 | M98: 188 | N98: 178 | O98: 161 | P98: 174 | Q98: 188 | R98: 182 | S98: 193 | AB98: 313 | AC98: 372 | AD98: =SUM(B98:E98) -> 1472 | AE98: =SUM(F98:I98) -> 1133 | AF98: =SUM(J98:M98) -> 818 | AG98: =SUM(N98:Q98) -> 701
A99: Goodwill | B99: 978 | C99: 1111 | D99: 1261 | E99: 1168 | F99: 1155 | G99: 1148 | H99: 1180 | I99: 1137 | J99: 1159 | K99: 1167 | L99: 1128 | M99: 1201 | N99: 1156 | O99: 1074 | P99: 1078 | Q99: 1083 | R99: 1099 | S99: 1110 | AB99: 736 | AC99: 894 | AD99: =SUM(B99:E99) -> 4518 | AE99: =SUM(F99:I99) -> 4620 | AF99: =SUM(J99:M99) -> 4655 | AG99: =SUM(N99:Q99) -> 4391
A100: Intangible | B100: 109 | C100: 126 | D100: 153 | E100: 127 | F100: 115 | G100: 105 | H100: 98 | I100: 84 | J100: 76 | K100: 68 | L100: 58 | M100: 48 | N100: 43 | O100: 37 | P100: 33 | Q100: 41 | R100: 41 | S100: 36 | AB100: 97 | AC100: 89 | AD100: =SUM(B100:E100) -> 515 | AE100: =SUM(F100:I100) -> 402 | AF100: =SUM(J100:M100) -> 250 | AG100: =SUM(N100:Q100) -> 154
A101: Finance recevables | B101: 0 | C101: 0 | D101: 0 | E101: 0 | F101: 0 | G101: 0 | H101: 0 | I101: 0 | J101: 51 | K101: 52 | L101: 64 | M101: 74 | N101: 74 | O101: 68 | P101: 69 | Q101: 69 | R101: 71 | S101: 71 | AB101: 0 | AC101: 0 | AD101: =SUM(B101:E101) -> 0 | AE101: =SUM(F101:I101) -> 0 | AF101: =SUM(J101:M101) -> 241 | AG101: =SUM(N101:Q101) -> 280
A102: D/T | B102: 8 | C102: 7 | D102: 8 | E102: 8 | F102: 11 | G102: 15 | H102: 23 | I102: 28 | J102: 41 | K102: 49 | L102: 194 | M102: 186 | N102: 136 | O102: 94 | P102: 87 | Q102: 662 | R102: 596 | S102: 563 | AB102: 15 | AC102: 13 | AD102: =SUM(B102:E102) -> 31 | AE102: =SUM(F102:I102) -> 77 | AF102: =SUM(J102:M102) -> 470 | AG102: =SUM(N102:Q102) -> 979
A103: A | B103: =SUM(B90:B102)-B96-B93 -> 7039 | C103: =SUM(C90:C102)-C96-C93 -> 7388 | D103: =SUM(D90:D102)-D96-D93 -> 7632 | E103: =SUM(E90:E102)-E96-E93 -> 7636 | F103: =SUM(F90:F102)-F96-F93 -> 7529 | G103: =SUM(G90:G102)-G96-G93 -> 7312 | H103: =SUM(H90:H102)-H96-H93 -> 7592 | I103: =SUM(I90:I102)-I96-I93 -> 8346 | ... S103: =SUM(S90:S102)-S96-S93 -> 13748 | AA103: =SUM(AA90:AA102)-AA96-AA93 -> 0 | AB103: =SUM(AB90:AB102)-AB96-AB93 -> 6326 | AC103: =SUM(AC90:AC102)-AC96-AC93 -> 7170 | AD103: =SUM(AD90:AD102)-AD96-AD93 -> 29695 | AE103: =SUM(AE90:AE102)-AE96-AE93 -> 30779 | AF103: =SUM(AF90:AF102)-AF96-AF93 -> 41779 | AG103: =SUM(AG90:AG102)-AG96-AG93 -> 55856
A105: A/P | B105: 695 | C105: 825 | D105: 947 | E105: 845 | F105: 850 | G105: 893 | H105: 945 | I105: 978 | J105: 1048 | K105: 1091 | L105: 1084 | M105: 1342 | N105: 1064 | O105: 1171 | P105: 1193 | Q105: 1194 | R105: 1250 | S105: 1325 | AB105: 638 | AC105: 793 | AD105: =SUM(B105:E105) -> 3312 | AE105: =SUM(F105:I105) -> 3666 | AF105: =SUM(J105:M105) -> 4565 | AG105: =SUM(N105:Q105) -> 4622 | AH105: =+AH157*AH34/365 -> 5354.6106 | AI105: =+AI157*AI34/365 -> 6196.5891 | AJ105: =+AJ157*AJ34/365 -> 7169.2501 | AK105: =+AK157*AK34/365 -> 8292.6392 | AL105: =+AL157*AL34/365 -> 9589.8427 | AM105: =+AM157*AM34/365 -> 11087.445 | AN105: =+AN157*AN34/365 -> 12816.051 | AO105: =+AO157*AO34/365 -> 14810.891 | ... AQ105: =+AQ157*AQ34/365 -> 19767.557
A106: Income tax payables | B106: 13 | C106: 7 | D106: 16 | E106: 11 | F106: 9 | G106: 11 | H106: 8 | I106: 12 | J106: 14 | K106: 17 | L106: 21 | M106: 33 | N106: 40 | O106: 42 | P106: 31 | Q106: 72 | R106: 150 | S106: 171 | AB106: 9 | AC106: 23 | AD106: =SUM(B106:E106) -> 47 | AE106: =SUM(F106:I106) -> 40 | AF106: =SUM(J106:M106) -> 85 | AG106: =SUM(N106:Q106) -> 185
A107: D/R | B107: 469 | C107: 489 | D107: 522 | E107: 520 | F107: 524 | G107: 536 | H107: 599 | I107: 622 | J107: 634 | K107: 657 | L107: 680 | M107: 683 | N107: 675 | O107: 665 | P107: 692 | Q107: 711 | R107: 750 | S107: 778 | AB107: 380 | AC107: 458 | AD107: =SUM(B107:E107) -> 2000 | AE107: =SUM(F107:I107) -> 2281 | AF107: =SUM(J107:M107) -> 2654 | AG107: =SUM(N107:Q107) -> 2743 | AH107: =+AH28*0.14 -> 2766.9643 | AI107: =+AI28*0.14 -> 3182.009 | AJ107: =+AJ28*0.14 -> 3659.3103 | AK107: =+AK28*0.14 -> 4208.2069 | AL107: =+AL28*0.14 -> 4839.4379 | AM107: =+AM28*0.14 -> 5565.3536 | AN107: =+AN28*0.14 -> 6400.1566 | AO107: =+AO28*0.14 -> 7360.1801 | ... AQ107: =+AQ28*0.14 -> 9733.8382
F108: =+F107/B107-1 -> 0.11727079 | G108: =+G107/C107-1 -> 0.096114519 | H108: =+H107/D107-1 -> 0.14750958 | I108: =+I107/E107-1 -> 0.19615385 | J108: =+J107/F107-1 -> 0.20992366 | K108: =+K107/G107-1 -> 0.22574627 | L108: =+L107/H107-1 -> 0.13522538 | M108: =+M107/I107-1 -> 0.09807074 | ... S108: =+S107/O107-1 -> 0.16992481 | AB108: =+AB107/AB$28 -> 0.048222295 | AC108: =+AC107/AC$28 -> 0.047371866 | AD108: =+AD107/AD$28 -> 0.17054352 | AE108: =+AE107/AE$28 -> 0.17218826 | AF108: =+AF107/AF$28 -> 0.1693337 | AG108: =+AG107/AG$28 -> 0.1596056 | AH108: =+AH107/AH$28 -> 0.14 | AI108: =+AI107/AI$28 -> 0.14 | ... AQ108: =+AQ107/AQ$28 -> 0.14
A109: Accr exp | B109: =+1882+30 -> 1912 | C109: =+1951+29 -> 1980 | D109: =+2020+31 -> 2051 | E109: =+2093+28 -> 2121 | F109: =+2025+17 -> 2042 | G109: =+2053+14 -> 2067 | H109: =+2108+14 -> 2122 | I109: =+2440+26 -> 2466 | J109: =+2228+17 -> 2245 | K109: =+2223+11 -> 2234 | L109: =+2275+5 -> 2280 | M109: =+2347+5 -> 2352 | N109: =+4+2471 -> 2475 | O109: =+2442+4 -> 2446 | P109: =+2519+1 -> 2520 | Q109: =+2589+2 -> 2591 | R109: =+2+2471 -> 2473 | S109: 2573 | AB109: =+42+1748 -> 1790 | AC109: =+1841+37 -> 1878 | AD109: =SUM(B109:E109) -> 8064 | AE109: =SUM(F109:I109) -> 8697 | AF109: =SUM(J109:M109) -> 9111 | AG109: =SUM(N109:Q109) -> 10032 | AH109: =+AH28*0.5 -> 9882.0154 | AI109: =+AI28*0.5 -> 11364.318 | AJ109: =+AJ28*0.5 -> 13068.965 | AK109: =+AK28*0.5 -> 15029.31 | AL109: =+AL28*0.5 -> 17283.707 | AM109: =+AM28*0.5 -> 19876.263 | AN109: =+AN28*0.5 -> 22857.702 | AO109: =+AO28*0.5 -> 26286.357 | ... AQ109: =+AQ28*0.5 -> 34763.708
F110: =+F109/B109-1 -> 0.067991632 | G110: =+G109/C109-1 -> 0.043939394 | H110: =+H109/D109-1 -> 0.03461726 | I110: =+I109/E109-1 -> 0.16265912 | J110: =+J109/F109-1 -> 0.099412341 | K110: =+K109/G109-1 -> 0.08079342 | L110: =+L109/H109-1 -> 0.074458058 | M110: =+M109/I109-1 -> -0.04622871 | ... S110: =+S109/O109-1 -> 0.051921504 | AB110: =+AB109/AB$28 -> 0.22715239 | AC110: =+AC109/AC$28 -> 0.19424534 | AD110: =+AD109/AD$28 -> 0.68763149 | AE110: =+AE109/AE$28 -> 0.65651965 | AF110: =+AF109/AF$28 -> 0.58131097 | AG110: =+AG109/AG$28 -> 0.58372708 | AH110: =+AH109/AH$28 -> 0.5 | AI110: =+AI109/AI$28 -> 0.5 | ... AQ110: =+AQ109/AQ$28 -> 0.5
...
