Workbook

Sheet Main
A1: UBER | D1: Price | E1: 75 | L1: -> | M1: Waabi (ai company that builds AV)
D2: Share | E2: 2035.599 | F2: Q126 | L2: -> | M2: Wayve (british based ai company that builds AV)
D3: MC | E3: =E1*E2 -> 152669.93 | L3: -> | M3: Airport to increase pick-up fees (LAX)
D4: Cash | E4: 8911 | F4: Q126 | L4: -> | M4: Online Food Delivery marlket projected to expand by 9.7% CAGR up to 2032
D5: Debt | E5: 10514 | F5: Q126 | L5: -> | M5: Zoox strategic partnership (AMZN)
D6: EV | E6: =E3-E4+E5 -> 154272.93 | L6: -> | M6: Robotaxi collaboration with Wayve and Nissan in Tokyo powered by Nissan LEAF with Wayve AI
L7: -> | M7: Robotaxi collaboration with Motional (Hyunday Motor Group) in Las Vegas
A8: BETA | B8: 1.2 | D8: EV / Rev | E8: =+E6/(SUM(Model!O68:R68)) -> 24.640606 | M8: one of the first SAE Level 4 AV
L9: -> | M9: Increasing the strategic partnership with Nvidia in order to deploy their L4 (high automation) driverless vehicle in 28 cities by 2028
M10: Using UBER’s network effect to test and improve Nvidia’s DRIVE AGX and Ampamayo
L11: -> | M11: Partnership with Rivianto help them deploy 50,000 R2 robotaxies
A12: CAPM / Cost of Equity | B12: =0.045+B8*(0.1-0.0495) -> 0.1056 | D12: Cr. Spread | E12: =+'[1]Credit Spread US'!J6 -> 0.78043478 | M12: - currently still a L3 automation but this partnership sould help them develop at least an L4 automation
A13: Cost Debt | B13: =+0.0495+(E12/10) -> 0.12754348 | M13: - the full deployment should happen in 2031 with a total investment of 1.25$ B into the company given certain milestones
A14: Incremental Margin TTM | B14: =((Model!S68+Model!R68+Model!Q68+Model!P68)-(Model!O68+Model!N68+Model!M68+Model!L68))/((Model!S52+Model!R52+Model!Q52+Model!P52)-(Model!O52+Model!N52+Model!M52+Model!L52)) -> 0.27737452 | D14: WACC | E14: =+(E4/(E4+E5))*B12+(E5/(E4+E5)*B13*(1-0.22)) -> 0.1022896 | L14: -> | M14: Multi – year partnership with Ibotta to use Ibotta’s discounts over CPG (consumer Packed Goods) into Uber Eat.
A15: Leverage | B15: =(E5-E4)/Model!S111 -> 0.56864136 | M15: -> | N15: Ibotta will reach a bigger audience while UBER Eat ueasers (and UBER One) will have a better experience with the product (higher conversion rate?)
A16: EV/FCF (TTM) | B16: =+E6/SUM(Model!P175:S175) -> 15.304769 | L16: -> | M16: UBER to inctease not temporaly the prices for ridesharing services in order to bear oil price hikes
A17: EV/EBITDA | B17: =E6/(SUM(Model!O111:R111)) -> 16.51214 | M17: the change won’t be temporaly
A18: P/E | B18: =+E1/SUM(Model!P86:S86) -> 16.466975 | L18: -> | M18: UBER to parner with Pony.ai and Verne to deploy the first robotaxies in europe (Zagreb)
A19: P/FCF (TTM) | B19: =E3/SUM(Model!P175:S175) -> 15.145742 | M19: Following this strategic partnership, UBER will invest in Verne
A20: Rating | B20: BBB+ | C20: Baa1 | M20: Pony.ai will bring the Gen-7 autonomous vehicles, Verne will be the owner of the fleet while UBER will provide the networking (the demand)
B21: S&P | C21: Moody’s | M21: Still waiting for EU approval
L22: -> | M22: UBER to acquire Blacklane to improve it’s luxury and executive driving. UBER Elite
M23: Blacklane already operates in over 500 cities.
D24: Founded | E24: 2009 | F24: Delaware | M24: waiting for antitrust approval
D25: UBERCAB | E25: 2010 | L25: -> | M25: UBER to deploy fully driverless (Level 4) robotaxies in Dubai together with WeRide and Tawasul.
D26: UBER | E26: 2011 | M26: Tawasul will be the fleet operator. WeRide committed to deploy at least 1,200 Robotaxis in the ME (WeRide has been the first company to receive a national licence for self driving vehicles in the UAE).
D27: IPO | E27: May 9th 2019 | M27: UBER owns 5.82% of WeRide Class A shares
C28: Sector | D28: Technology Platform | L28: -> | M28: MOIA America will test its AV in LA through Uber in late 2026
C29: CEO | D29: Dara Khosrowshahi | M29: This partnership has been going on since 2025 and aims to deploy thousands of AV. MOIA (and theparent VolksWagen) are advancing AV testing in Hamburg, Oslo, Berlin, Munich.
C30: Founder | D30: Travis Kalanick | L30: -> | M30: UBER to add Cash App Pay (Block inc. XYZ) into the app to reach the over 59 million transaction done mainly from Millenials and Gen Zs
A31: investor@uber.com | L31: -> | M31: UBER to launch a robotaxi program in Munich together with NVDA Hyperion
L32: -> | M32: UBER together with AVOMO and WERIDE to launch the first robotaxi fleet in Madrid aiming to deploy hudreds of robotaxies in the region in the foreseeable future as certain milestones are met
M33: This partnerships have already been tested in the US (AVOMO) and in the ME (WERIDE) and show positive sign as of relationship and clear path
A34: Segments | M34: Still 11 cities do expand the partnership with WeRide before 2030. Next sure is Riyadh.
A35: Delivery (UberEats) | L35: -> | M35: UBER expands further the shops where consumers can buy through UBER Eats beyond the food segment.
A36: Mobility (Uber, Lime, carsharing, taxi, …) | M36: Consumers are using delivery apps not anymore just for food delivery, but they want a wider range of goods to choose from. UBER is targeting this niche
A37: Freight (on demand platform to automate logistics transactions) UBER freight | L37: -> | M37: UBER to expand their commercial robotaxies to Zurich with WeRide. Ryderra will manage day-to-day fleet operations
A38: Nissan, Kellog, CL, … | G38: -> | H38: Prashanth Mahendra-Rajan in US gov? | L38: -> | M38: UBER to deploy in mid-2027 Robotaxies in Houston with Nuro (Level 4 AV) and Lucid
G39: -> | H39: Reserve increased Uber’s reliability | M39: Nuro aims to deploy over 35,000 AVs globally
L40: -> | M40: UBER to acquire Delibvery Hero for 14.8B$ to be approved around Q2 27. It is expected to create synergies for at least 1.2B$
A41: Advertising (opened in 2022) Uber Journey Ads | I41: Lime ? | M41: this merge will increase the servidces provided in Uber One and reach newer markets where Uber Eats failed (i.e. Italy) or has never penetrated
B42: -> | C42: surpassed the 2 B$ | I42: Freight growth ? | M42: UBER is currently 1st in the Japan delivery market, therefore will use the same approach also for the newer asian markets
I43: Adv data ? | M43: this merge will also create a newer “quick commerce” segment into Uber Eats to expand its business (which is already Adj. EBITDA profitable for Delivery Hero)
M44: Delivery Hero is also more efficient in the Advertisement management (3% of revenues) therefore Uber can use their know how to increas the Advertisement impact
B45: MAPC | C45: Unique consumers that have completed a Mobility ride or a Delivery order once in a given month | M45: -> | N45: Uber to acquire Baedal Minjok (SK), Glovo, Foodora(HU), Foodpanda, Hungerstation (SA), PedidosYa, Talabat
B46: Gross Booking | C46: Total value of all UBER’s activities (including taxes, …) | M46: -> | N46: If it fails for regulatory reasons Uber pays Delivery Hero 700M$
B47: Trips | C47: Each completed event on Uber’s platform (ridesharing or delivery especially) | M47: -> | N47: Delivery Hero has to pay Uber 200M$ if it accepts another competing offer
L48: -> | M48: GameStop to deliver games and consoles through Uber Eats
B51: Mobility | C51: Connect consumers with drivers. It also contains ADV and financial partnership products.
B52: Delivery | C52: (Grocery and Retail) Food delivery form local restaurants. It also contains ADV.
B53: Freight | C53: Connects carriers with shippers, Freight financing program
A59: Seasonality | B59: Mobility has a higher Gross booking in Q4 and a slower demand in Q1 mainly
B60: due to business demand and Holiday demand
B61: Delivery has a higher Gropss booking in Q4
A64: UBER Freight | B64: Despite general increase in cargo theft and frauds (18%) and increase in the total-average amount, UberFreightNetwork is decreasing the amount of frauds (20%)
B65: -> | C65: Truckload conditions are getting tighter, therefore more expensive. This is leading to a shift towards intermodal may be a suitable solution
A66: Transplace Holdings Inc. | B66: Q126 | C66: Decreasing FTA (First Tender Acceptance) 92% → 85% due to higher shipping costs
A67: Transplace Mexico | B67: Q126 | C67: on top of that Class 8 tractors’ demand is st ATH but supply is not enough (no short term relief)
A68: Leancore Supply Chain Group | B68: Q126 | C68: LTL (Less Than truckLoad – nonfull trucks) is more expensive than ever (up 5.2% YoY)
A75: Aleka Insurance / Raise LLC | B75: -> | C75: Ad hoc insurance built by Uber, through Raise LLC (Uber’s arm for insurances)
B76: -> | C76: In 2021 James River made a LPT (JR paid Aleka a premium in order to take Uber’s insurance risk)
C77: -> | D77: When a drive crashes, he asks Raise for the money to pay the damages, Raise asks to
D78: JR, which asks to Aleka to pay. Aleka is payd by JR to bear the risk.
A82: News | B82: -> | C82: Baidu collaboration to deploy AV in Dubai through their subsidiary Apollo Go
C83: -> | D83: This follows a prevoious agreement to serve the Apollo Go’s AV through the Uber App
A88: ! REMARK | B88: -> | C88: If jurisdictions claim that UBER’s drivers should be considered
C89: as UBER employees and not independent contractors
B90: -> | C90: To remain relevant they can lower fees or increase Driver incentives
B91: -> | C91: High part of the stock is a bet in their R&D for AV.
C92: They have to create the biggest synergies to speed the AV R&D.
L94: -> | M94: Many governments are hostile against UBER and LYFT and whant to calssify
B95: -> | C95: Some AV companies may need UBER’s help in order to reach the broader audience (Apollo GO) | M95: Drivers as employees (Switzerland). Others rely heavely on taxi drivers (Italy)
C96: UBER’s main strength is it’s network effect. The more people use it, the more drivers | M96: -> | N96: This is a huge risk factor. With high probability there will be more lawsuits
C97: The best is the experience of the service | N97: And in more states UBER will have to employ its drivers
C98: -> | D98: Partnership with Nvidia for the AV race | M98: -> | N98: https://www.dir.ca.gov/dlse/Lawsuits-Uber-Lyft.html
N99: The California litigation is mainly about the Proposition 22 which classifies
B100: -> | C100: They also hold stakes in strategic firms in order to hold a position in the sector even in countries | N100: drivers as indipendent drivers but they have some benefits as 120% of base wage
C101: where UBER is not known or can’t operate. | O101: -> | P101: Proposition 22 states that drivers should use platforms as UBER for independent work
C102: -> | D102: Careem (Dubai where UBER owns only the ridesharing section. Everything else is owned by Emirates) | O102: -> | P102: The ABC case has been dissolved (no longer subject of that order) but now the trial is open for the pre Proposition 22 rule in California.
C103: -> | D103: Delivery Hero (Taiwan with objective to buy Foodpanda – blocked by antitrust) | M103: -> | N103: Other similar litigations ended with a settlement of a few M$
D104: -> | E104: Grab to acquire Delivery Hero | N104: (Massacchussets 148 M$, New York 328M$, California 8M$, New Jersey 100M$)
C105: -> | D105: MLU B.V. (Russia) → Sold in 2023 | N105: or get dismissed (Philadelphia)
C106: -> | D106: Treydon GO (Turkey version for UberEats) | M106: -> | N106: Also in France, after many disputes, the drivers were considered as Independent Workers
D107: -> | E107: put/call option that can be exercised in 2013 Q1, it is currently recorded as RNCI
C108: -> | D108: Getir (acquired its delivery division for the turkish market) – Mubadala Investment Company (UAE sovreign wealth fund) | L108: -> | M108: UBER is currently facing +3,000 alligations for sexual violence from its drivers (1 every 8 minutes for the last 5 years)
D109: -> | E109: Now Getir customers can use Getir’s “super app” (?) to order and benefit of | M109: -> | N109: BUILD america 250, no ride-hailing company shall be liable for any harm caused by vehicles or people from the app
E110: all the Treydon GO restaurants (435 M$) | N110: This applies unless wrongdoping or company’s conduct rose gross negligence
C111: -> | D111: Lime (Neutron Technologies) ??
B112: -> | C112: UBER Elite, executive focused service where for an additional fee, the customer can request a newer car to be driven with (<= 3 y.o.)
C113: In-vehicle amenities (chargers, bottled water, towels) and 24/7 support with the cheuffer
C114: -> | D114: Blacklane to be acquired to improve the increasing demand for luxury hauls (550 M$)
B115: -> | C115: SpotHero, digital parking aggregator (600M$)
B120: -> | C120: Can Issue up to 5 Billion more shares
C121: -> | D121: And up to 10 M preferred shares (currently 0)
B122: -> | C122: As of 2024 they still have to repurchase $5.8B in shares. In jan 25 they stareted ASR
C123: Accelerated Share Repurchase
B125: -> | C125: In Feb26 expires a 213M loan to Moove
B128: -> | C128: Currrently developing UBER AI Solution also to increase driver engagement and retention
C129: and using genAI in order to personalise interactions and the UBER experience
C130: -> | D130: Mighty AI Gmbh
...

Sheet Model
A1: Main | B1: 03/22 | C1: 06/22 | D1: 09/22 | E1: 12/22 | F1: 03/23 | G1: 06/23 | H1: 09/23 | I1: 12/23 | J1: 03/24 | K1: 06/24 | L1: 09/24 | M1: 12/24 | N1: 03/25 | O1: 06/25 | P1: 09/25 | Q1: 12/25 | R1: 03/26 | S1: 06/26 | T1: 09/26 | U1: 12/26 | Y1: 12/19 | Z1: 12/20 | AA1: 12/21 | AB1: 12/22 | AC1: 12/23 | AD1: 12/24 | AE1: 12/25 | AF1: 12/26 | AG1: 12/27 | AH1: 12/28 | AI1: 12/29 | AJ1: 12/30 | AK1: 12/31 | AL1: 12/32 | AM1: 12/33 | AN1: 12/34 | AO1: 12/35
A2: in Millions | B2: Q122 | C2: Q222 | D2: Q322 | E2: Q422 | F2: Q123 | G2: Q223 | H2: Q323 | I2: Q423 | J2: Q124 | K2: Q224 | L2: Q324 | M2: Q424 | N2: Q125 | O2: Q225 | P2: Q325 | Q2: Q425 | R2: Q126 | S2: Q226 | T2: Q326 | U2: Q426 | Y2: 2019 | Z2: 2020 | AA2: =Z2+1 -> 2021 | AB2: =AA2+1 -> 2022 | AC2: =AB2+1 -> 2023 | AD2: =AC2+1 -> 2024 | AE2: =AD2+1 -> 2025 | AF2: =AE2+1 -> 2026 | AG2: =AF2+1 -> 2027 | AH2: =AG2+1 -> 2028 | ... AO2: =AN2+1 -> 2035
A3: GRAB Group MTUs | B3: 30.9 | C3: 32.6 | D3: 33.5 | E3: 33.6 | F3: 33.3 | G3: 34.9 | H3: 36 | I3: 37.7 | J3: 38.5 | K3: 40.9 | L3: 41.9 | M3: 43.9 | N3: 44.5 | O3: 46.2 | P3: 47.7 | Q3: 50.5 | R3: 51.6 | Z3: 27.7 | AA3: 28.1 | AB3: 32.7 | AC3: 35.5 | AD3: 41.3 | AE3: 50.5
A4: % | F4: =F3/B3-1 -> 0.077669903 | G4: =G3/C3-1 -> 0.070552147 | H4: =H3/D3-1 -> 0.074626866 | I4: =I3/E3-1 -> 0.12202381 | J4: =J3/F3-1 -> 0.15615616 | K4: =K3/G3-1 -> 0.17191977 | L4: =L3/H3-1 -> 0.16388889 | M4: =M3/I3-1 -> 0.16445623 | ... R4: =R3/N3-1 -> 0.15955056 | AA4: =+AA3/Z3-1 -> 0.014440433 | AB4: =+AB3/AA3-1 -> 0.16370107 | AC4: =+AC3/AB3-1 -> 0.085626911 | AD4: =+AD3/AC3-1 -> 0.16338028 | AE4: =+AE3/AD3-1 -> 0.22276029
A5: GRAB GMV | B5: - | C5: - | D5: - | E5: 0 | F5: 3600 | G5: 3939 | H5: 4063 | I5: =+AC5-F5-G5-H5 -> 4183 | J5: 4242 | K5: 4434 | L5: 4659 | M5: 5028 | N5: 4932 | O5: 5354 | P5: 5774 | Q5: 6077 | R5: 6131 | Y5: - | Z5: - | AA5: - | AB5: 15592 | AC5: 15785 | AD5: 18364 | AE5: 22138
A6: % | J6: =J5/F5-1 -> 0.17833333 | K6: =K5/G5-1 -> 0.12566641 | L6: =L5/H5-1 -> 0.14668964 | M6: =M5/I5-1 -> 0.20200813 | N6: =N5/J5-1 -> 0.16265912 | O6: =O5/K5-1 -> 0.2074876 | P6: =P5/L5-1 -> 0.23932174 | Q6: =Q5/M5-1 -> 0.20863166 | R6: =R5/N5-1 -> 0.24310624 | AC6: =+AC5/AB5-1 -> 0.012378143 | AD6: =+AD5/AC5-1 -> 0.16338296 | AE6: =+AE5/AD5-1 -> 0.20551078
A8: DASH Orders | B8: 404 | C8: 426 | D8: 439 | E8: 467 | F8: 512 | G8: 532 | H8: 543 | I8: 574 | J8: 620 | K8: 635 | L8: 643 | M8: 685 | N8: 732 | O8: 761 | P8: 776 | Q8: 903 | R8: 933 | Y8: 263 | Z8: 816 | AA8: 1390 | AB8: 1736 | AC8: 2161 | AD8: 2583 | AE8: 3172
A9: % | F9: =F8/B8-1 -> 0.26732673 | G9: =G8/C8-1 -> 0.24882629 | H9: =H8/D8-1 -> 0.23690205 | I9: =I8/E8-1 -> 0.22912206 | J9: =J8/F8-1 -> 0.2109375 | K9: =K8/G8-1 -> 0.19360902 | L9: =L8/H8-1 -> 0.18416206 | M9: =M8/I8-1 -> 0.19337979 | ... R9: =R8/N8-1 -> 0.27459016 | Z9: =+Z8/Y8-1 -> 2.1026616 | AA9: =+AA8/Z8-1 -> 0.70343137 | AB9: =+AB8/AA8-1 -> 0.24892086 | AC9: =+AC8/AB8-1 -> 0.24481567 | AD9: =+AD8/AC8-1 -> 0.19527996 | AE9: =+AE8/AD8-1 -> 0.22802942
A10: ZOOX Trips (‘000)
A11: Waymo Trips (‘000) | P11: 3500 | Q11: 5300 | R11: 6200 | AC11: 0.8 | AD11: 4 | AE11: 15
A12: Apollo Go (‘000) | F12: 660 | G12: 714 | H12: 821 | I12: 839 | J12: 826 | K12: 899 | L12: 988 | M12: 1100 | N12: 1400 | O12: 2200 | P12: 3100 | Q12: 3400 | R12: 3200 | AB12: 1.5 | AC12: 3.03 | AD12: 3.813 | AE12: 10.1
J13: =J12/F12-1 -> 0.25151515 | K13: =K12/G12-1 -> 0.25910364 | L13: =L12/H12-1 -> 0.20341048 | M13: =M12/I12-1 -> 0.31108462 | N13: =N12/J12-1 -> 0.69491525 | O13: =O12/K12-1 -> 1.4471635 | P13: =P12/L12-1 -> 2.1376518 | Q13: =Q12/M12-1 -> 2.0909091 | R13: =R12/N12-1 -> 1.2857143 | AC13: =AC12/AB12-1 -> 1.02 | AD13: =AD12/AC12-1 -> 0.25841584 | AE13: =AE12/AD12-1 -> 1.6488329
A14: Tesla Robotaxi
A15: Texla FSD (miles) | S15: 10000
A18: LYFT Trips | B18: 139.5 | C18: 152.1 | D18: 155.8 | E18: 151.1 | F18: 153 | G18: 177.9 | H18: 187.4 | I18: 190.8 | J18: 187.7 | K18: 205.3 | L18: 216.7 | M18: 218.5 | N18: 218.4 | O18: 234.8 | P18: 248.8 | Q18: 243.5 | R18: 236.9 | Y18: - | Z18: - | AA18: - | AB18: 598.5 | AC18: =SUM(F18:I18) -> 709.1 | AD18: =SUM(J18:M18) -> 828.2 | AE18: =SUM(N18:Q18) -> 945.5
A19: % | F19: =F18/B18-1 -> 0.096774194 | G19: =G18/C18-1 -> 0.16962525 | H19: =H18/D18-1 -> 0.20282413 | I19: =I18/E18-1 -> 0.26273991 | J19: =J18/F18-1 -> 0.22679739 | K19: =K18/G18-1 -> 0.15401911 | L19: =L18/H18-1 -> 0.15635005 | M19: =M18/I18-1 -> 0.1451782 | ... R19: =R18/N18-1 -> 0.08470696 | AC19: =AC18/AB18-1 -> 0.18479532 | AD19: =AD18/AC18-1 -> 0.16795939 | AE19: =AE18/AD18-1 -> 0.14163246
A20: LYFT Gross Book | B20: 2694 | C20: 3093 | D20: 3079 | E20: 3191 | F20: 3051 | G20: 3446 | H20: 3554 | I20: 3724 | J20: 3693 | K20: 4019 | L20: 4108 | M20: 4279 | N20: 4162 | O20: 4490 | P20: 4780 | Q20: 5074 | R20: 4946 | Y20: - | Z20: - | AA20: - | AB20: 12057 | AC20: =SUM(F20:I20) -> 13775 | AD20: =SUM(J20:M20) -> 16099 | AE20: =SUM(N20:Q20) -> 18506
A21: % | F21: =F20/B20-1 -> 0.1325167 | G21: =G20/C20-1 -> 0.11412868 | H21: =H20/D20-1 -> 0.15427087 | I21: =I20/E20-1 -> 0.16703228 | J21: =J20/F20-1 -> 0.21042281 | K21: =K20/G20-1 -> 0.16627974 | L21: =L20/H20-1 -> 0.1558807 | M21: =M20/I20-1 -> 0.1490333 | ... R21: =R20/N20-1 -> 0.18837098 | AC21: =AC20/AB20-1 -> 0.14248984 | AD21: =AD20/AC20-1 -> 0.16871143 | AE21: =AE20/AD20-1 -> 0.14951239
A24: MAD | B24: 4.4 | E24: 5.4 | F24: 5.7 | G24: 6 | H24: 6.5 | I24: 6.8 | J24: 7.1 | K24: 7.4 | L24: 7.8 | M24: 8.15 | N24: 8.5 | O24: 8.8 | P24: 9.4 | Q24: 9.7 | R24: 9.9 | Y24: - | Z24: 3.4 | AA24: 4.4 | AB24: 5.4 | AC24: 6.8 | AD24: 8.2 | AE24: 9.7 | AF24: =+AE24*1.17 -> 11.349
A25: % | F25: =F24/B24-1 -> 0.29545455 | G25: =G24/C24-1 -> #DIV/0! | H25: =H24/D24-1 -> #DIV/0! | I25: =I24/E24-1 -> 0.25925926 | J25: =J24/F24-1 -> 0.24561404 | K25: =K24/G24-1 -> 0.23333333 | L25: =L24/H24-1 -> 0.2 | M25: =M24/I24-1 -> 0.19852941 | ... S25: =S24/O24-1 -> -1 | AA25: =AA24/Z24-1 -> 0.29411765 | AB25: =AB24/AA24-1 -> 0.22727273 | AC25: =AC24/AB24-1 -> 0.25925926 | AD25: =AD24/AC24-1 -> 0.20588235 | AE25: =AE24/AD24-1 -> 0.18292683
A26: MAPC | B26: 115 | C26: 122 | D26: 124 | E26: 131 | F26: 130 | G26: 137 | H26: 142 | I26: 150 | J26: 149 | K26: 156 | L26: 161 | M26: 171 | N26: 170 | O26: 180 | P26: 189 | Q26: 202 | R26: 199 | S26: 208 | Y26: 111 | Z26: 93 | AA26: 118 | AB26: 131 | AC26: 150 | AD26: 171 | AE26: 202
A27: % | F27: =F26/B26-1 -> 0.13043478 | G27: =G26/C26-1 -> 0.12295082 | H27: =H26/D26-1 -> 0.14516129 | I27: =I26/E26-1 -> 0.14503817 | J27: =J26/F26-1 -> 0.14615385 | K27: =K26/G26-1 -> 0.13868613 | L27: =L26/H26-1 -> 0.13380282 | M27: =M26/I26-1 -> 0.14 | ... S27: =S26/O26-1 -> 0.15555556 | Z27: =Z26/Y26-1 -> -0.16216216 | AA27: =AA26/Z26-1 -> 0.2688172 | AB27: =AB26/AA26-1 -> 0.11016949 | AC27: =AC26/AB26-1 -> 0.14503817 | AD27: =AD26/AC26-1 -> 0.14 | AE27: =AE26/AD26-1 -> 0.18128655
A28: Trips | B28: 1713 | C28: 1872 | D28: 1953 | E28: 2104 | F28: 2124 | G28: 2282 | H28: 2441 | I28: 2601 | J28: 2572 | K28: 2765 | L28: 2868 | M28: 3068 | N28: 3036 | O28: 3268 | P28: 3512 | Q28: 3751 | R28: 3643 | S28: 3867 | Y28: =+1550+1677+1770+1907 -> 6904 | Z28: =+1661+737+1184+1443 -> 5025 | AA28: 6368 | AB28: 7642 | AC28: =SUM(F28:I28) -> 9448 | AD28: =SUM(J28:M28) -> 11273 | AE28: =SUM(N28:Q28) -> 13567
A29: % | F29: =F28/B28-1 -> 0.23992995 | G29: =G28/C28-1 -> 0.21901709 | H29: =H28/D28-1 -> 0.24987199 | I29: =I28/E28-1 -> 0.23621673 | J29: =J28/F28-1 -> 0.21092279 | K29: =K28/G28-1 -> 0.21165644 | L29: =L28/H28-1 -> 0.17492831 | M29: =M28/I28-1 -> 0.17954633 | ... S29: =S28/O28-1 -> 0.18329253 | Z29: =Z28/Y28-1 -> -0.27216107 | AA29: =AA28/Z28-1 -> 0.26726368 | AB29: =AB28/AA28-1 -> 0.20006281 | AC29: =AC28/AB28-1 -> 0.23632557 | AD29: =AD28/AC28-1 -> 0.19316257 | AE29: =AE28/AD28-1 -> 0.20349508
A31: Mobility GB | B31: 10723 | C31: 13364 | D31: 13684 | E31: 14894 | F31: 14981 | G31: 16728 | H31: 17903 | I31: 19285 | J31: 18670 | K31: 20554 | L31: 21002 | M31: 22798 | N31: 21182 | O31: 23762 | P31: 25111 | Q31: 27442 | R31: 26394 | S31: 28988
F32: =F31/B31-1 -> 0.39709037 | G32: =G31/C31-1 -> 0.25172104 | H32: =H31/D31-1 -> 0.30831628 | I32: =I31/E31-1 -> 0.2948167 | J32: =J31/F31-1 -> 0.24624524 | K32: =K31/G31-1 -> 0.22871832 | L32: =L31/H31-1 -> 0.17309948 | M32: =M31/I31-1 -> 0.1821623 | ... S32: =S31/O31-1 -> 0.21993098
A33: Delivery GB | B33: 13903 | C33: 13876 | D33: 13684 | E33: 14315 | F33: 15026 | G33: 15595 | H33: 16094 | I33: 17011 | J33: 17699 | K33: 18126 | L33: 18663 | M33: 20126 | N33: 20377 | O33: 21734 | P33: 23322 | Q33: 25431 | R33: 25992 | S33: 27463
F34: =F33/B33-1 -> 0.080773934 | G34: =G33/C33-1 -> 0.12388296 | H34: =H33/D33-1 -> 0.17611809 | I34: =I33/E33-1 -> 0.18833392 | J34: =J33/F33-1 -> 0.17789165 | K34: =K33/G33-1 -> 0.16229561 | L34: =L33/H33-1 -> 0.1596247 | M34: =M33/I33-1 -> 0.18311681 | ... S34: =S33/O33-1 -> 0.26359621
A35: Freight GB | B35: 1823 | C35: 1838 | D35: 1751 | E35: 1540 | F35: 1401 | G35: 1278 | H35: 1284 | I35: 1279 | J35: 1282 | K35: 1272 | L35: 1308 | M35: 1273 | N35: 1259 | O35: 1260 | P35: 1307 | Q35: 1267 | R35: 1334 | S35: 1571
F36: =F35/B35-1 -> -0.23148656 | G36: =G35/C35-1 -> -0.304679 | H36: =H35/D35-1 -> -0.26670474 | I36: =I35/E35-1 -> -0.16948052 | J36: =J35/F35-1 -> -0.084939329 | K36: =K35/G35-1 -> -0.0046948357 | L36: =L35/H35-1 -> 0.018691589 | M36: =M35/I35-1 -> -0.004691165 | ... S36: =S35/O35-1 -> 0.2468254
A37: Gross Booking | B37: =+B35+B33+B31 -> 26449 | C37: =+C35+C33+C31 -> 29078 | D37: =+D35+D33+D31 -> 29119 | E37: =+E35+E33+E31 -> 30749 | F37: =+F35+F33+F31 -> 31408 | G37: =+G35+G33+G31 -> 33601 | H37: =+H35+H33+H31 -> 35281 | I37: =+I35+I33+I31 -> 37575 | ... S37: =+S35+S33+S31 -> 58022 | T37: =+P37*1.18 -> 58693.2 | Y37: 65001 | Z37: 57897 | AA37: 90415 | AB37: 115395 | AC37: =SUM(F37:I37) -> 137865 | AD37: =SUM(J37:M37) -> 162773 | AE37: =SUM(N37:Q37) -> 193454 | AF37: =+AE37*1.2 -> 232144.8 | AG37: =+AF37*1.2 -> 278573.76 | AH37: =+AG37*1.2 -> 334288.51 | AI37: =+AH37*1.2 -> 401146.21 | AJ37: =+AI37*1.2 -> 481375.46 | AK37: =+AJ37*1.2 -> 577650.55 | AL37: =+AK37*1.2 -> 693180.66 | AM37: =+AL37*1.2 -> 831816.79 | ... AO37: =+AN37*1.2 -> 1197816.2
A38: % | F38: =F37/B37-1 -> 0.18749291 | G38: =G37/C37-1 -> 0.15554715 | H38: =H37/D37-1 -> 0.21161441 | I38: =I37/E37-1 -> 0.22199096 | J38: =J37/F37-1 -> 0.19877101 | K38: =K37/G37-1 -> 0.18901223 | L38: =L37/H37-1 -> 0.1613333 | M38: =M37/I37-1 -> 0.1762342 | ... T38: =T37/P37-1 -> 0.18 | Z38: =Z37/Y37-1 -> -0.10929063 | AA38: =AA37/Z37-1 -> 0.56165259 | AB38: =AB37/AA37-1 -> 0.27628159 | AC38: =AC37/AB37-1 -> 0.19472247 | AD38: =AD37/AC37-1 -> 0.1806695 | AE38: =AE37/AD37-1 -> 0.18848949 | AF38: =AF37/AE37-1 -> 0.2 | AG38: =AG37/AF37-1 -> 0.2 | ... AO38: =AO37/AN37-1 -> 0.2
A39: Uber One | H39: 15 | I39: 19 | L39: 25 | M39: 30 | Q39: 46 | R39: 50 | AC39: 19 | AD39: 30 | AE39: 46
A40: % | I40: =+I39/H39-1 -> 0.26666667 | M40: =+M39/L39-1 -> 0.2 | R40: =+R39/Q39-1 -> 0.086956522 | AD40: =AD39/AC39-1 -> 0.57894737 | AE40: =AE39/AD39-1 -> 0.53333333
A41: Take Rate | B41: =+B52/B37 -> 0.25914023 | C41: =+C52/C37 -> 0.27763257 | D41: =+D52/D37 -> 0.28651396 | E41: =+E52/E37 -> 0.27991154 | F41: =+F52/F37 -> 0.28094597 | G41: =+G52/G37 -> 0.27470952 | H41: =+H52/H37 -> 0.26338217 | I41: =+I52/I37 -> 0.26444186 | ... S41: =+S52/S37 -> 0.24457964 | Y41: =+Y52/Y37 -> 0.21764281 | Z41: =+Z52/Z37 -> 0.19240211 | AA41: =+AA52/AA37 -> 0.19308071 | AB41: =+AB52/AB37 -> 0.27627349 | AC41: =+AC52/AC37 -> 0.2704188 | AD41: =+AD52/AD37 -> 0.27018223 | AE41: =+AE52/AE37 -> 0.26888784 | AF41: =+AF52/AF37 -> 0.25096199 | ... AO41: =+AO52/AO37 -> 0.15247736
A42: % | F42: =F41/B41-1 -> 0.084146464 | G42: =G41/C41-1 -> -0.010528486 | H42: =H41/D41-1 -> -0.080735296 | I42: =I41/E41-1 -> -0.055266325 | J42: =J41/F41-1 -> -0.042216005 | K42: =K41/G41-1 -> -0.02504414 | L42: =L41/H41-1 -> 0.036777681 | M42: =M41/I41-1 -> 0.023265891 | ... S42: =S41/O41-1 -> -0.096105159 | Z42: =Z41/Y41-1 -> -0.11597302 | AA42: =AA41/Z41-1 -> 0.0035269882 | AB42: =AB41/AA41-1 -> 0.43087049 | AC42: =AC41/AB41-1 -> -0.02119165 | AD42: =AD41/AC41-1 -> -0.00087484337 | AE42: =AE41/AD41-1 -> -0.0047907832 | AF42: =AF41/AE41-1 -> -0.066666667 | AG42: =AG41/AF41-1 -> -0.041666667 | ... AO42: =AO41/AN41-1 -> -0.083333333
A44: Mobility | B44: 2518 | C44: 3553 | D44: 3822 | E44: 4136 | F44: 4330 | G44: 4894 | H44: 5071 | I44: 5537 | J44: 5633 | K44: 6134 | L44: 6409 | M44: 6911 | N44: 6496 | O44: 7288 | P44: 7682 | Q44: 8204 | R44: 6798 | S44: 7363 | Y44: 10745 | Z44: 6089 | AA44: 6953 | AB44: 14029 | AC44: 19832 | AD44: 25087 | AE44: =SUM(N44:Q44) -> 29670
A45: % | F45: =+F44/B44-1 -> 0.71961875 | G45: =+G44/C44-1 -> 0.37742753 | H45: =+H44/D44-1 -> 0.32679226 | I45: =+I44/E44-1 -> 0.33873308 | J45: =+J44/F44-1 -> 0.30092379 | K45: =+K44/G44-1 -> 0.25337148 | L45: =+L44/H44-1 -> 0.26385328 | M45: =+M44/I44-1 -> 0.24814882 | ... S45: =+S44/O44-1 -> 0.010290889 | Z45: =+Z44/Y44-1 -> -0.43331782 | AA45: =+AA44/Z44-1 -> 0.14189522 | AB45: =+AB44/AA44-1 -> 1.0176902 | AC45: =+AC44/AB44-1 -> 0.41364317 | AD45: =+AD44/AC44-1 -> 0.2649758 | AE45: =+AE44/AD44-1 -> 0.18268426
A46: Delivery | B46: 2512 | C46: 2688 | D46: 2770 | E46: 2931 | F46: 3093 | G46: 3057 | H46: 2935 | I46: 3119 | J46: 3214 | K46: 3293 | L46: 3470 | M46: 3773 | N46: 3777 | O46: 4102 | P46: 4477 | Q46: 4892 | R46: 5068 | S46: 5245 | Y46: 2510 | Z46: 3904 | AA46: 8362 | AB46: 10901 | AC46: 12204 | AD46: 13750 | AE46: =SUM(N46:Q46) -> 17248
A47: % | F47: =+F46/B46-1 -> 0.23128981 | G47: =+G46/C46-1 -> 0.13727679 | H47: =+H46/D46-1 -> 0.059566787 | I47: =+I46/E46-1 -> 0.064141931 | J47: =+J46/F46-1 -> 0.039120595 | K47: =+K46/G46-1 -> 0.077199869 | L47: =+L46/H46-1 -> 0.18228279 | M47: =+M46/I46-1 -> 0.20968259 | ... S47: =+S46/O46-1 -> 0.27864456 | Z47: =+Z46/Y46-1 -> 0.55537849 | AA47: =+AA46/Z46-1 -> 1.1419057 | AB47: =+AB46/AA46-1 -> 0.30363549 | AC47: =+AC46/AB46-1 -> 0.11953032 | AD47: =+AD46/AC46-1 -> 0.12667978 | AE47: =+AE46/AD46-1 -> 0.2544
A48: Freight | B48: 1824 | C48: 1832 | D48: 1751 | E48: 1540 | F48: 1400 | G48: 1279 | H48: 1286 | I48: 1280 | J48: 1284 | K48: 1273 | L48: 1309 | M48: 1275 | N48: 1260 | O48: 1261 | P48: 1308 | Q48: 1270 | R48: 1337 | S48: 1583 | Y48: 731 | Z48: 1011 | AA48: 2132 | AB48: 6947 | AC48: 5245 | AD48: 5141 | AE48: =SUM(N48:Q48) -> 5099
A49: % | F49: =+F48/B48-1 -> -0.23245614 | G49: =+G48/C48-1 -> -0.3018559 | H49: =+H48/D48-1 -> -0.26556254 | I49: =+I48/E48-1 -> -0.16883117 | J49: =+J48/F48-1 -> -0.082857143 | K49: =+K48/G48-1 -> -0.004691165 | L49: =+L48/H48-1 -> 0.017884914 | M49: =+M48/I48-1 -> -0.00390625 | ... S49: =+S48/O48-1 -> 0.25535289 | Z49: =+Z48/Y48-1 -> 0.38303694 | AA49: =+AA48/Z48-1 -> 1.1088032 | AB49: =+AB48/AA48-1 -> 2.2584428 | AC49: =+AC48/AB48-1 -> -0.24499784 | AD49: =+AD48/AC48-1 -> -0.019828408 | AE49: =+AE48/AD48-1 -> -0.0081696168
A50: Other | B50: 0 | C50: 0 | D50: 0 | E50: 0 | F50: 0 | G50: 0 | H50: 0 | I50: 0 | J50: 0 | K50: 0 | L50: 0 | M50: 0 | N50: 0 | O50: 0 | P50: 0 | Q50: 0 | R50: 0 | S50: 0 | Y50: =+119+42 -> 161 | Z50: 135 | AA50: 8 | AB50: 0 | AC50: 0 | AD50: 0 | AE50: =SUM(N50:Q50) -> 0
A51: % | F51: N.M. | G51: N.M. | H51: N.M. | I51: N.M. | J51: N.M. | K51: N.M. | L51: N.M. | M51: N.M. | N51: N.M. | O51: N.M. | P51: N.M. | Q51: N.M. | R51: N.M. | S51: N.M. | Z51: =+Z50/Y50-1 -> -0.16149068 | AA51: =+AA50/Z50-1 -> -0.94074074 | AB51: N.M. | AC51: N.M. | AD51: N.M. | AE51: N.M.
A52: Revenue | B52: =SUM(B44:B48) -> 6854 | C52: =SUM(C44:C48) -> 8073 | D52: =SUM(D44:D48) -> 8343 | E52: =SUM(E44:E48) -> 8607 | F52: =SUM(F44:F48) -> 8823.9509 | G52: =SUM(G44:G48) -> 9230.5147 | H52: =SUM(H44:H48) -> 9292.3864 | I52: =SUM(I44:I48) -> 9936.4029 | ... P52: =SUM(P44:P48) -> 13467.489 | Q52: =SUM(Q44:Q48)-Q47-Q45 -> 14366 | R52: =SUM(R44:R48)-R47-R45 -> 13203 | S52: =SUM(S44:S48)-S47-S45 -> 14191 | T52: =+P52*1.1 -> 14814.238 | U52: =+Q52*1.1 -> 15802.6 | Y52: =SUM(Y44:Y50) -> 14147 | Z52: =SUM(Z44:Z50) -> 11139.505 | AA52: =SUM(AA44:AA50) -> 17457.393 | AB52: =SUM(AB44:AB50) -> 31880.58 | AC52: =SUM(AC44:AC50) -> 37281.288 | AD52: =SUM(AD44:AD50) -> 43978.372 | AE52: =SUM(AE44:AE50) -> 52017.429 | AF52: =AE52*1.12 -> 58259.52 | AG52: =AF52*1.15 -> 66998.448 | AH52: =AG52*1.16 -> 77718.2 | AI52: =AH52*1.16 -> 90153.112 | AJ52: =AI52*1.15 -> 103676.08 | AK52: =AJ52*1.14 -> 118190.73 | AL52: =AK52*1.13 -> 133555.53 | AM52: =AL52*1.12 -> 149582.19 | AN52: =AM52*1.11 -> 166036.23 | AO52: =AN52*1.1 -> 182639.85
A53: % | F53: =+F52/B52-1 -> 0.28741624 | G53: =+G52/C52-1 -> 0.14338099 | H53: =+H52/D52-1 -> 0.11379436 | I53: =+I52/E52-1 -> 0.15445601 | J53: =+J52/F52-1 -> 0.14816369 | K53: =+K52/G52-1 -> 0.15923444 | L53: =+L52/H52-1 -> 0.20404444 | M53: =+M52/I52-1 -> 0.20360034 | ... S53: =+S52/O52-1 -> 0.12169104 | Z53: =+Z52/Y52-1 -> -0.21258888 | AA53: =+AA52/Z52-1 -> 0.56716052 | AB53: =+AB52/AA52-1 -> 0.82619366 | AC53: =+AC52/AB52-1 -> 0.16940433 | AD53: =+AD52/AC52-1 -> 0.17963659 | AE53: =+AE52/AD52-1 -> 0.1827957 | AF53: =+AF52/AE52-1 -> 0.12 | AG53: =+AG52/AF52-1 -> 0.15 | ... AO53: =+AO52/AN52-1 -> 0.1
A54: COGS | B54: =+4026+254 -> 4280 | C54: =+5153+243 -> 5396 | D54: =+5173+227 -> 5400 | E54: =+5307+223 -> 5530 | F54: =+207+5259 -> 5466 | G54: =+208+5515 -> 5723 | H54: =+205+5626 -> 5831 | I54: =+203+6057 -> 6260 | J54: =+190+6168 -> 6358 | K54: =+173+6488 -> 6661 | L54: =+179+6761 -> 6940 | M54: =+169+7234 -> 7403 | N54: =+171+6937 -> 7108 | O54: =+175+7611 -> 7786 | P54: =+188+8109 -> 8297 | Q54: =+185+8681 -> 8866 | R54: =+7258+184 -> 7442 | S54: =+7815+188 -> 8003 | T54: =+T52-T56 -> 8444.1155 | U54: =+U52-U56 -> 9007.482 | Y54: =+7208+472 -> 7680 | Z54: =+575+5154 -> 5729 | AA54: =+902+9351 -> 10253 | AB54: =+947+19659 -> 20606 | AC54: =+823+22457 -> 23280 | AD54: =+711+26651 -> 27362 | AE54: =SUM(N54:Q54) -> 32057 | AF54: =AF52-AF56 -> 34955.712 | AG54: =AG52-AG56 -> 39864.077 | AH54: =AH52-AH56 -> 45853.738 | AI54: =AI52-AI56 -> 52739.571 | AJ54: =AJ52-AJ56 -> 60132.126 | AK54: =AK52-AK56 -> 66777.763 | AL54: =AL52-AL56 -> 76126.649 | AM54: =AM52-AM56 -> 84513.936 | ... AO54: =AO52-AO56 -> 101365.12
A55: % | B55: =+B54/B$52 -> 0.62445287 | C55: =+C54/C$52 -> 0.66840084 | D55: =+D54/D$52 -> 0.64724919 | E55: =+E54/E$52 -> 0.64250029 | F55: =+F54/F$52 -> 0.61945041 | G55: =+G54/G$52 -> 0.62000876 | H55: =+H54/H$52 -> 0.62750297 | I55: =+I54/I$52 -> 0.63000666 | ... S55: =+S54/S$52 -> 0.56394898 | Y55: =+Y54/Y$52 -> 0.54287128 | Z55: =+Z54/Z$52 -> 0.51429574 | AA55: =+AA54/AA$52 -> 0.58731566 | AB55: =+AB54/AB$52 -> 0.6463496 | AC55: =+AC54/AC$52 -> 0.62444194 | AD55: =+AD54/AD$52 -> 0.62216946 | AE55: =+AE54/AE$52 -> 0.61627421 | AF55: =+AF54/AF$52 -> 0.6 | ... AO55: =+AO54/AO$52 -> 0.555
A56: Gross Profit | B56: =B52-B54 -> 2574 | C56: =C52-C54 -> 2677 | D56: =D52-D54 -> 2943 | E56: =E52-E54 -> 3077 | F56: =F52-F54 -> 3357.9509 | G56: =G52-G54 -> 3507.5147 | H56: =H52-H54 -> 3461.3864 | I56: =I52-I54 -> 3676.4029 | ... S56: =S52-S54 -> 6188 | T56: =+T52*0.43 -> 6370.1222 | U56: =+U52*0.43 -> 6795.118 | Y56: =Y52-Y54 -> 6467 | Z56: =Z52-Z54 -> 5410.5051 | AA56: =AA52-AA54 -> 7204.3926 | AB56: =AB52-AB54 -> 11274.58 | AC56: =AC52-AC54 -> 14001.288 | AD56: =AD52-AD54 -> 16616.372 | AE56: =AE52-AE54 -> 19960.429 | AF56: =+AF52*0.4 -> 23303.808 | AG56: =+AG52*0.405 -> 27134.372 | AH56: =+AH52*0.41 -> 31864.462 | AI56: =+AI52*0.415 -> 37413.542 | AJ56: =+AJ52*0.42 -> 43543.953 | AK56: =+AK52*0.435 -> 51412.968 | AL56: =+AL52*0.43 -> 57428.876 | AM56: =+AM52*0.435 -> 65068.252 | AN56: =+AN52*0.44 -> 73055.941 | AO56: =+AO52*0.445 -> 81274.734
A57: % | B57: =+B56/B$52 -> 0.37554713 | C57: =+C56/C$52 -> 0.33159916 | D57: =+D56/D$52 -> 0.35275081 | E57: =+E56/E$52 -> 0.35749971 | F57: =+F56/F$52 -> 0.38054959 | G57: =+G56/G$52 -> 0.37999124 | H57: =+H56/H$52 -> 0.37249703 | I57: =+I56/I$52 -> 0.36999334 | ... U57: =+U56/U$52 -> 0.43 | Y57: =+Y56/Y$52 -> 0.45712872 | Z57: =+Z56/Z$52 -> 0.48570426 | AA57: =+AA56/AA$52 -> 0.41268434 | AB57: =+AB56/AB$52 -> 0.3536504 | AC57: =+AC56/AC$52 -> 0.37555806 | AD57: =+AD56/AD$52 -> 0.37783054 | AE57: =+AE56/AE$52 -> 0.38372579 | AF57: =+AF56/AF$52 -> 0.4 | ... AO57: =+AO56/AO$52 -> 0.445
A58: O&S | B58: 574 | C58: 617 | D58: 617 | E58: 605 | F58: 640 | G58: 664 | H58: 683 | I58: 702 | J58: 685 | K58: 682 | L58: 687 | M58: 678 | N58: 668 | O58: 696 | P58: 735 | Q58: 755 | R58: 763 | S58: 805 | T58: =+S58*1.1 -> 885.5 | U58: =+T58*1.1 -> 974.05 | Y58: 2302 | Z58: 1819 | AA58: 1877 | AB58: 2413 | AC58: 2689 | AD58: 2732 | AE58: =SUM(N58:Q58) -> 2854 | AF58: =+AF52*0.05 -> 2912.976 | AG58: =+AG52*0.05 -> 3349.9224 | AH58: =+AH52*0.05 -> 3885.91 | AI58: =+AI52*0.05 -> 4507.6556 | AJ58: =+AJ52*0.05 -> 5183.804 | AK58: =+AK52*0.05 -> 5909.5365 | AL58: =+AL52*0.05 -> 6677.7763 | AM58: =+AM52*0.05 -> 7479.1094 | ... AO58: =+AO52*0.05 -> 9131.9926
A59: % | B59: =+B58/B$52 -> 0.083746717 | C59: =+C58/C$52 -> 0.076427598 | D59: =+D58/D$52 -> 0.073954213 | E59: =+E58/E$52 -> 0.070291623 | F59: =+F58/F$52 -> 0.072529869 | G59: =+G58/G$52 -> 0.071935317 | H59: =+H58/H$52 -> 0.073501033 | I59: =+I58/I$52 -> 0.070649309 | ... S59: =+S58/S$52 -> 0.056726094 | Y59: =+Y58/Y$52 -> 0.16272001 | Z59: =+Z58/Z$52 -> 0.16329271 | AA59: =+AA58/AA$52 -> 0.10751892 | AB59: =+AB58/AB$52 -> 0.075688711 | AC59: =+AC58/AC$52 -> 0.072127336 | AD59: =+AD58/AD$52 -> 0.062121445 | AE59: =+AE58/AE$52 -> 0.054866226 | AF59: =+AF58/AF$52 -> 0.05 | ... AO59: =+AO58/AO$52 -> 0.05
A60: S&M | B60: 1263 | C60: 1218 | D60: 1153 | E60: 1122 | F60: 1262 | G60: 1218 | H60: 941 | I60: 935 | J60: 917 | K60: 1115 | L60: 1096 | M60: 1209 | N60: 1057 | O60: 1210 | P60: 1277 | Q60: 1354 | R60: 1326 | S60: 1515 | T60: =+S60*1.1 -> 1666.5 | U60: =+T60*1.1 -> 1833.15 | Y60: 4626 | Z60: 3583 | AA60: 4789 | AB60: 4756 | AC60: 4356 | AD60: 4337 | AE60: =SUM(N60:Q60) -> 4898 | AF60: =+AF52*0.09 -> 5243.3568 | AG60: =+AG52*0.09 -> 6029.8604 | AH60: =+AH52*0.08 -> 6217.456 | AI60: =+AI52*0.08 -> 7212.249 | AJ60: =+AJ52*0.08 -> 8294.0863 | AK60: =+AK52*0.08 -> 9455.2584 | AL60: =+AL52*0.07 -> 9348.8868 | AM60: =+AM52*0.07 -> 10470.753 | AN60: =+AN52*0.07 -> 11622.536 | AO60: =+AO52*0.07 -> 12784.79
A61: % | B61: =+B60/B$52 -> 0.18427196 | C61: =+C60/C$52 -> 0.15087328 | D61: =+D60/D$52 -> 0.13819969 | E61: =+E60/E$52 -> 0.13035901 | F61: =+F60/F$52 -> 0.14301983 | G61: =+G60/G$52 -> 0.13195364 | H61: =+H60/H$52 -> 0.1012657 | I61: =+I60/I$52 -> 0.094098439 | ... S61: =+S60/S$52 -> 0.1067578 | Y61: =+Y60/Y$52 -> 0.32699512 | Z61: =+Z60/Z$52 -> 0.32164804 | AA61: =+AA60/AA$52 -> 0.27432504 | AB61: =+AB60/AB$52 -> 0.14918173 | AC61: =+AC60/AC$52 -> 0.11684146 | AD61: =+AD60/AD$52 -> 0.098616657 | AE61: =+AE60/AE$52 -> 0.094160748 | AF61: =+AF60/AF$52 -> 0.09 | ... AO61: =+AO60/AO$52 -> 0.07
A62: R&D | B62: 587 | C62: 704 | D62: 760 | E62: 747 | F62: 775 | G62: 808 | H62: 797 | I62: 784 | J62: 790 | K62: 760 | L62: 774 | M62: 785 | N62: 815 | O62: 840 | P62: 862 | Q62: 885 | R62: 951 | S62: 1043 | T62: =+S62*1.1 -> 1147.3 | U62: =+T62*1.1 -> 1262.03 | Y62: 4836 | Z62: 2205 | AA62: 2054 | AB62: 2798 | AC62: 3164 | AD62: 3109 | AE62: =SUM(N62:Q62) -> 3402 | AF62: =+AF52*0.07 -> 4078.1664 | AG62: =+AG52*0.07 -> 4689.8914 | AH62: =+AH52*0.07 -> 5440.274 | AI62: =+AI52*0.07 -> 6310.7179 | AJ62: =+AJ52*0.06 -> 6220.5647 | AK62: =+AK52*0.06 -> 7091.4438 | AL62: =+AL52*0.06 -> 8013.3315 | AM62: =+AM52*0.06 -> 8974.9313 | AN62: =+AN52*0.06 -> 9962.1737 | AO62: =+AO52*0.06 -> 10958.391
A63: % | B63: =+B62/B$52 -> 0.08564342 | C63: =+C62/C$52 -> 0.087204261 | D63: =+D62/D$52 -> 0.091094331 | E63: =+E62/E$52 -> 0.086789822 | F63: =+F62/F$52 -> 0.087829138 | G63: =+G62/G$52 -> 0.087535747 | H63: =+H62/H$52 -> 0.085769141 | I63: =+I62/I$52 -> 0.078901793 | ... S63: =+S62/S$52 -> 0.073497287 | Y63: =+Y62/Y$52 -> 0.34183926 | Z63: =+Z62/Z$52 -> 0.19794416 | AA63: =+AA62/AA$52 -> 0.11765789 | AB63: =+AB62/AB$52 -> 0.087765029 | AC63: =+AC62/AC$52 -> 0.084868312 | AD63: =+AD62/AD$52 -> 0.07069384 | AE63: =+AE62/AE$52 -> 0.065401156 | AF63: =+AF62/AF$52 -> 0.07 | ... AO63: =+AO62/AO$52 -> 0.06
A64: G&A | B64: 632 | C64: 851 | D64: 908 | E64: 745 | F64: 942 | G64: 491 | H64: 646 | I64: 603 | J64: 1209 | K64: 686 | L64: 630 | M64: 1114 | N64: 657 | O64: 669 | P64: 1183 | Q64: 732 | R64: 798 | S64: 935 | T64: =+S64*1.1 -> 1028.5 | U64: =+T64*1.1 -> 1131.35 | Y64: 3299 | Z64: 2666 | AA64: 2316 | AB64: 3136 | AC64: 2682 | AD64: 3639 | AE64: =SUM(N64:Q64) -> 3241 | AF64: =+AF52*0.06 -> 3495.5712 | AG64: =+AG52*0.06 -> 4019.9069 | AH64: =+AH52*0.06 -> 4663.092 | AI64: =+AI52*0.05 -> 4507.6556 | AJ64: =+AJ52*0.05 -> 5183.804 | AK64: =+AK52*0.05 -> 5909.5365 | AL64: =+AL52*0.05 -> 6677.7763 | AM64: =+AM52*0.05 -> 7479.1094 | AN64: =+AN52*0.05 -> 8301.8114 | AO64: =+AO52*0.05 -> 9131.9926
A65: % | B65: =+B64/B$52 -> 0.092208929 | C65: =+C64/C$52 -> 0.10541311 | D65: =+D64/D$52 -> 0.10883375 | E65: =+E64/E$52 -> 0.086557453 | F65: =+F64/F$52 -> 0.1067549 | G65: =+G64/G$52 -> 0.053193133 | H65: =+H64/H$52 -> 0.069519279 | I65: =+I64/I$52 -> 0.060685945 | ... S65: =+S64/S$52 -> 0.06588683 | Y65: =+Y64/Y$52 -> 0.23319432 | Z65: =+Z64/Z$52 -> 0.23932841 | AA65: =+AA64/AA$52 -> 0.13266586 | AB65: =+AB64/AB$52 -> 0.098367094 | AC65: =+AC64/AC$52 -> 0.071939574 | AD65: =+AD64/AD$52 -> 0.082745219 | AE65: =+AE64/AE$52 -> 0.06230604 | AF65: =+AF64/AF$52 -> 0.06 | ... AO65: =+AO64/AO$52 -> 0.05
A66: OpEx | B66: =SUM(B58:B64)-B63-B61-B59 -> 3056 | C66: =SUM(C58:C64)-C63-C61-C59 -> 3390 | D66: =SUM(D58:D64)-D63-D61-D59 -> 3438 | E66: =SUM(E58:E64)-E63-E61-E59 -> 3219 | F66: =SUM(F58:F64)-F63-F61-F59 -> 3619 | G66: =SUM(G58:G64)-G63-G61-G59 -> 3181 | H66: =SUM(H58:H64)-H63-H61-H59 -> 3067 | I66: =SUM(I58:I64)-I63-I61-I59 -> 3024 | ... S66: =SUM(S58:S64)-S63-S61-S59 -> 4298 | T66: =SUM(T58:T64) -> 4727.8 | U66: =SUM(U58:U64) -> 5200.58 | Y66: =+Y64+Y62+Y60+Y58 -> 15063 | Z66: =+Z64+Z62+Z60+Z58 -> 10273 | AA66: =+AA64+AA62+AA60+AA58 -> 11036 | AB66: =+AB64+AB62+AB60+AB58 -> 13103 | AC66: =+AC64+AC62+AC60+AC58 -> 12891 | AD66: =+AD64+AD62+AD60+AD58 -> 13817 | AE66: =+AE64+AE62+AE60+AE58 -> 14395 | AF66: =+AF64+AF62+AF60+AF58 -> 15730.071 | ... AO66: =+AO64+AO62+AO60+AO58 -> 42007.166
A67: % | B67: =+B66/B$52 -> 0.44587102 | C67: =+C66/C$52 -> 0.41991825 | D67: =+D66/D$52 -> 0.41208198 | E67: =+E66/E$52 -> 0.37399791 | F67: =+F66/F$52 -> 0.41013374 | G67: =+G66/G$52 -> 0.34461784 | H67: =+H66/H$52 -> 0.33005515 | I67: =+I66/I$52 -> 0.30433549 | ... U67: =+U66/U$52 -> 0.32909648 | Y67: =+Y66/Y$52 -> 1.0647487 | Z67: =+Z66/Z$52 -> 0.92221332 | AA67: =+AA66/AA$52 -> 0.63216772 | AB67: =+AB66/AB$52 -> 0.41100256 | AC67: =+AC66/AC$52 -> 0.34577668 | AD67: =+AD66/AD$52 -> 0.31417716 | AE67: =+AE66/AE$52 -> 0.27673417 | AF67: =+AF66/AF$52 -> 0.27 | ... AO67: =+AO66/AO$52 -> 0.23
A68: OpInc / EBIT | B68: =B56-B66 -> -482 | C68: =C56-C66 -> -713 | D68: =D56-D66 -> -495 | E68: =E56-E66 -> -142 | F68: =F56-F66 -> -261.04909 | G68: =G56-G66 -> 326.5147 | H68: =H56-H66 -> 394.38636 | I68: =I56-I66 -> 652.40288 | ... U68: =U56-U66 -> 1594.538 | Y68: =Y56-Y66 -> -8596 | Z68: =Z56-Z66 -> -4862.4949 | AA68: =AA56-AA66 -> -3831.6074 | AB68: =AB56-AB66 -> -1828.4202 | AC68: =AC56-AC66 -> 1110.2882 | AD68: =AD56-AD66 -> 2799.3718 | AE68: =AE56-AE66 -> 5565.4289 | AF68: =AF56-AF66 -> 7573.7376 | ... AO68: =AO56-AO66 -> 39267.568
A69: % | B69: =+B68/B$52 -> -0.070323898 | C69: =+C68/C$52 -> -0.088319088 | D69: =+D68/D$52 -> -0.059331176 | E69: =+E68/E$52 -> -0.016498199 | F69: =+F68/F$52 -> -0.02958415 | G69: =+G68/G$52 -> 0.035373402 | H69: =+H68/H$52 -> 0.042441881 | I69: =+I68/I$52 -> 0.065657853 | ... U69: =+U68/U$52 -> 0.10090352 | Y69: =+Y68/Y$52 -> -0.60761999 | Z69: =+Z68/Z$52 -> -0.43650906 | AA69: =+AA68/AA$52 -> -0.21948337 | AB69: =+AB68/AB$52 -> -0.057352164 | AC69: =+AC68/AC$52 -> 0.029781379 | AD69: =+AD68/AD$52 -> 0.063653376 | AE69: =+AE68/AE$52 -> 0.10699162 | AF69: =+AF68/AF$52 -> 0.13 | ... AO69: =+AO68/AO$52 -> 0.215
A70: Interest Exp | B70: -129 | C70: -139 | D70: -146 | E70: -151 | F70: -168 | G70: -144 | H70: -166 | I70: -155 | J70: -124 | K70: -139 | L70: -143 | M70: -117 | N70: -105 | O70: -108 | P70: -112 | Q70: -115 | R70: =-108+175 -> 67 | S70: =-127+172 -> 45 | T70: -100 | U70: -100 | Y70: -559 | Z70: -458 | AA70: -483 | AB70: -565 | AC70: -633 | AD70: -523 | AE70: =SUM(N70:Q70) -> -440 | AF70: =AE120*$AS$100 -> -17.48 | AG70: =AF120*$AS$100 -> 185.87018 | AH70: =AG120*$AS$100 -> 378.25274 | AI70: =AH120*$AS$100 -> 610.90043 | AJ70: =AI120*$AS$100 -> 908.65138 | AK70: =AJ120*$AS$100 -> 1267.5754 | AL70: =AK120*$AS$100 -> 1709.0524 | AM70: =AL120*$AS$100 -> 2221.9631 | ... AO70: =AN120*$AS$100 -> 3384.2681
A71: % | B71: =+B70/B$52 -> -0.018821126 | C71: =+C70/C$52 -> -0.017217887 | D71: =+D70/D$52 -> -0.0174997 | E71: =+E70/E$52 -> -0.01754386 | F71: =+F70/F$52 -> -0.019039091 | G71: =+G70/G$52 -> -0.01560043 | H71: =+H70/H$52 -> -0.017864087 | I71: =+I70/I$52 -> -0.015599206 | ... U71: =+U70/U$52 -> -0.0063280726 | Y71: =+Y70/Y$52 -> -0.039513678 | Z71: =+Z70/Z$52 -> -0.041114932 | AA71: =+AA70/AA$52 -> -0.027667362 | AB71: =+AB70/AB$52 -> -0.017722388 | AC71: =+AC70/AC$52 -> -0.016979027 | AD71: =+AD70/AD$52 -> -0.011892209 | AE71: =+AE70/AE$52 -> -0.0084587033 | AF71: =+AF70/AF$52 -> -0.0003000368 | ... AO71: =+AO70/AO$52 -> 0.018529735
A72: Other | B72: -5557 | C72: -1704 | D72: -535 | E72: 767 | F72: 292 | G72: 273 | H72: -52 | I72: 1331 | J72: -678 | K72: 420 | L72: 1851 | M72: 256 | N72: 262 | O72: 162 | P72: 1619 | Q72: -1368 | R72: -1494 | S72: 1342 | T72: 1000 | U72: 1000 | Y72: 722 | Z72: -1625 | AA72: 3292 | AB72: -7029 | AC72: 1844 | AD72: 1849 | AE72: =SUM(N72:Q72) -> 675 | AF72: 1000 | AG72: 1000 | AH72: 1000 | AI72: 1000 | AJ72: 1000 | AK72: 1000 | AL72: 1000 | AM72: 1000 | AN72: 1000 | AO72: 1000
A73: % | B73: =+B72/B$52 -> -0.81076744 | C73: =+C72/C$52 -> -0.21107395 | D73: =+D72/D$52 -> -0.064125614 | E73: =+E72/E$52 -> 0.089113512 | F73: =+F72/F$52 -> 0.033091753 | G73: =+G72/G$52 -> 0.029575816 | H73: =+H72/H$52 -> -0.0055959791 | I73: =+I72/I$52 -> 0.1339519 | ... U73: =+U72/U$52 -> 0.063280726 | Y73: =+Y72/Y$52 -> 0.051035555 | Z73: =+Z72/Z$52 -> -0.14587722 | AA73: =+AA72/AA$52 -> 0.18857341 | AB73: =+AB72/AB$52 -> -0.22047905 | AC73: =+AC72/AC$52 -> 0.04946181 | AD73: =+AD72/AD$52 -> 0.042043394 | AE73: =+AE72/AE$52 -> 0.01297642 | AF73: =+AF72/AF$52 -> 0.017164577 | ... AO73: =+AO72/AO$52 -> 0.0054752563
A74: Pretax | B74: =SUM(B68:B72)-B71-B69 -> -6168 | C74: =SUM(C68:C72)-C71-C69 -> -2556 | D74: =SUM(D68:D72)-D71-D69 -> -1176 | E74: =SUM(E68:E72)-E71-E69 -> 474 | F74: =SUM(F68:F72)-F71-F69 -> -137.04909 | G74: =SUM(G68:G72)-G71-G69 -> 455.5147 | H74: =SUM(H68:H72)-H71-H69 -> 176.38636 | I74: =SUM(I68:I72)-I71-I69 -> 1828.4029 | ... S74: =SUM(S68:S72)-S71-S69 -> 3277 | T74: =SUM(T68:T72) -> 2542.4263 | U74: =SUM(U68:U72) -> 2494.6326 | Y74: =+Y72+Y70+Y68 -> -8433 | Z74: =+Z72+Z70+Z68 -> -6945.4949 | AA74: =+AA72+AA70+AA68 -> -1022.6074 | AB74: =+AB72+AB70+AB68 -> -9422.4202 | AC74: =+AC72+AC70+AC68 -> 2321.2882 | AD74: =+AD72+AD70+AD68 -> 4125.3718 | AE74: =+AE72+AE70+AE68 -> 5800.4289 | AF74: =+AF72+AF70+AF68 -> 8556.2576 | ... AO74: =+AO72+AO70+AO68 -> 43651.836
A75: % | B75: =+B74/B$52 -> -0.89991246 | C75: =+C74/C$52 -> -0.31661093 | D75: =+D74/D$52 -> -0.14095649 | E75: =+E74/E$52 -> 0.055071453 | F75: =+F74/F$52 -> -0.015531488 | G75: =+G74/G$52 -> 0.049348787 | H75: =+H74/H$52 -> 0.018981815 | I75: =+I74/I$52 -> 0.18401054 | ... U75: =+U74/U$52 -> 0.15786216 | Y75: =+Y74/Y$52 -> -0.59609811 | Z75: =+Z74/Z$52 -> -0.62350121 | AA75: =+AA74/AA$52 -> -0.058577327 | AB75: =+AB74/AB$52 -> -0.2955536 | AC75: =+AC74/AC$52 -> 0.062264162 | AD75: =+AD74/AD$52 -> 0.09380456 | AE75: =+AE74/AE$52 -> 0.11150934 | AF75: =+AF74/AF$52 -> 0.14686454 | ... AO75: =+AO74/AO$52 -> 0.23900499
A76: Taxes | B76: -232 | C76: 77 | D76: 58 | E76: -84 | F76: 55 | G76: 65 | H76: -40 | I76: 133 | J76: 29 | K76: 57 | L76: 158 | M76: -6002 | N76: -402 | O76: 142 | P76: -4046 | Q76: -40 | R76: 194 | S76: 840 | T76: =+T74*(-0.1) -> -254.24263 | U76: =+U74*(-0.1) -> -249.46326 | Y76: 45 | Z76: -192 | AA76: -492 | AB76: -181 | AC76: 213 | AD76: -5758 | AE76: =SUM(N76:Q76) -> -4346 | AF76: =AF74*-0.2 -> -1711.2515 | AG76: =AG74*0.05 -> 511.53304 | AH76: =AH74*0.1 -> 1303.5983 | AI76: =AI74*0.1 -> 1648.6164 | AJ76: =AJ74*0.13 -> 2674.1449 | AK76: =AK74*0.13 -> 3290.9198 | AL76: =AL74*0.13 -> 3824.6205 | AM76: =AM74*0.2 -> 6777.2623 | AN76: =AN74*0.2 -> 7726.5504 | AO76: =AO74*0.2 -> 8730.3672
A77: % | B77: =+B76/B$52 -> -0.033848847 | C77: =+C76/C$52 -> 0.0095379661 | D77: =+D76/D$52 -> 0.0069519358 | E77: =+E76/E$52 -> -0.0097594981 | F77: =+F76/F$52 -> 0.0062330356 | G77: =+G76/G$52 -> 0.0070418608 | H77: =+H76/H$52 -> -0.0043045993 | I77: =+I76/I$52 -> 0.013385126 | ... U77: =+U76/U$52 -> -0.015786216 | Y77: =+Y76/Y$52 -> 0.0031808864 | Z77: =+Z76/Z$52 -> -0.017235954 | AA77: =+AA76/AA$52 -> -0.028182903 | AB77: =+AB76/AB$52 -> -0.0056774375 | AC77: =+AC76/AC$52 -> 0.0057133219 | AD77: =+AD76/AD$52 -> -0.13092799 | AE77: =+AE76/AE$52 -> -0.08354892 | AF77: =+AF76/AF$52 -> -0.029372908 | ... AO77: =+AO76/AO$52 -> 0.047800998
A78: Loss from invest | B78: 18 | C78: 17 | D78: 30 | E78: 42 | F78: 36 | G78: 4 | H78: 3 | I78: 5 | J78: -4 | K78: -12 | L78: -12 | M78: -10 | N78: -13 | O78: -12 | P78: -14 | Q78: -14 | R78: -20 | S78: -21 | T78: -10 | U78: -10 | Y78: -34 | Z78: -34 | AA78: -37 | AB78: 107 | AC78: 48 | AD78: -38 | AE78: =SUM(N78:Q78) -> -53 | AF78: -50 | AG78: -50 | AH78: -50 | AI78: 100 | AJ78: 100 | AK78: 100 | AL78: 100 | AM78: 100 | AN78: 100 | AO78: 100
A79: % | B79: =+B78/B$52 -> 0.0026262037 | C79: =+C78/C$52 -> 0.0021057847 | D79: =+D78/D$52 -> 0.0035958288 | E79: =+E78/E$52 -> 0.004879749 | F79: =+F78/F$52 -> 0.0040798051 | G79: =+G78/G$52 -> 0.00043334528 | H79: =+H78/H$52 -> 0.00032284495 | I79: =+I78/I$52 -> 0.00050320021 | ... U79: =+U78/U$52 -> -0.00063280726 | Y79: =+Y78/Y$52 -> -0.0024033364 | Z79: =+Z78/Z$52 -> -0.0030522002 | AA79: =+AA78/AA$52 -> -0.0021194459 | AB79: =+AB78/AB$52 -> 0.0033562752 | AC79: =+AC78/AC$52 -> 0.0012875092 | AD79: =+AD78/AD$52 -> -0.00086406109 | AE79: =+AE78/AE$52 -> -0.0010188893 | AF79: =+AF78/AF$52 -> -0.00085822883 | ... AO79: =+AO78/AO$52 -> 0.00054752563
A80: Pre NCI | B80: =B74-B76+B78 -> -5918 | C80: =C74-C76+C78 -> -2616 | D80: =D74-D76+D78 -> -1204 | E80: =E74-E76+E78 -> 600 | F80: =F74-F76+F78 -> -156.04909 | G80: =G74-G76+G78 -> 394.5147 | H80: =H74-H76+H78 -> 219.38636 | I80: =I74-I76+I78 -> 1700.4029 | ... U80: =U74-U76+U78 -> 2734.0958 | Y80: =Y74-Y76+Y78 -> -8512 | Z80: =Z74-Z76+Z78 -> -6787.4949 | AA80: =AA74-AA76+AA78 -> -567.6074 | AB80: =AB74-AB76+AB78 -> -9134.4202 | AC80: =AC74-AC76+AC78 -> 2156.2882 | AD80: =AD74-AD76+AD78 -> 9845.3718 | AE80: =AE74-AE76+AE78 -> 10093.429 | AF80: =AF74-AF76+AF78 -> 10217.509 | ... AO80: =AO74-AO76+AO78 -> 35021.469
A81: % | B81: =+B80/B$52 -> -0.86343741 | C81: =+C80/C$52 -> -0.32404311 | D81: =+D80/D$52 -> -0.1443126 | E81: =+E80/E$52 -> 0.069710701 | F81: =+F80/F$52 -> -0.017684719 | G81: =+G80/G$52 -> 0.042740271 | H81: =+H80/H$52 -> 0.023609259 | I81: =+I80/I$52 -> 0.17112862 | ... U81: =+U80/U$52 -> 0.17301557 | Y81: =+Y80/Y$52 -> -0.60168234 | Z81: =+Z80/Z$52 -> -0.60931746 | AA81: =+AA80/AA$52 -> -0.03251387 | AB81: =+AB80/AB$52 -> -0.28651989 | AC81: =+AC80/AC$52 -> 0.05783835 | AD81: =+AD80/AD$52 -> 0.22386849 | AE81: =+AE80/AE$52 -> 0.19403937 | AF81: =+AF80/AF$52 -> 0.17537922 | ... AO81: =+AO80/AO$52 -> 0.19175152
A82: NCI | B82: 12 | C82: -15 | D82: 2 | E82: 5 | F82: 0 | G82: 0 | H82: -2 | I82: 271 | J82: -9 | K82: -7 | L82: -13 | M82: 18 | N82: -2 | O82: -5 | P82: 26 | Q82: 21 | R82: 19 | S82: 22 | T82: 30 | U82: 30 | Y82: -6 | Z82: -20 | AA82: -74 | AB82: 3 | AC82: 269 | AD82: -11 | AE82: =SUM(N82:Q82) -> 40 | AF82: 50 | AG82: 50 | AH82: 50 | AI82: 50 | AJ82: 50 | AK82: 50 | AL82: 50 | AM82: 50 | AN82: 50 | AO82: 50
A83: % | B83: =+B82/B$52 -> 0.0017508025 | C83: =+C82/C$52 -> -0.0018580453 | D83: =+D82/D$52 -> 0.00023972192 | E83: =+E82/E$52 -> 0.0005809225 | F83: =+F82/F$52 -> 0 | G83: =+G82/G$52 -> 0 | H83: =+H82/H$52 -> -0.00021522997 | I83: =+I82/I$52 -> 0.027273451 | ... U83: =+U82/U$52 -> 0.0018984218 | Y83: =+Y82/Y$52 -> -0.00042411819 | Z83: =+Z82/Z$52 -> -0.0017954119 | AA83: =+AA82/AA$52 -> -0.0042388919 | AB83: =+AB82/AB$52 -> 9.4101175e-05 | AC83: =+AC82/AC$52 -> 0.0072154159 | AD83: =+AD82/AD$52 -> -0.00025012295 | AE83: =+AE82/AE$52 -> 0.00076897303 | AF83: =+AF82/AF$52 -> 0.00085822883 | ... AO83: =+AO82/AO$52 -> 0.00027376282
A84: Net Inc | B84: =B80-B82 -> -5930 | C84: =C80-C82 -> -2601 | D84: =D80-D82 -> -1206 | E84: =E80-E82 -> 595 | F84: =F80-F82 -> -156.04909 | G84: =G80-G82 -> 394.5147 | H84: =H80-H82 -> 221.38636 | I84: =I80-I82 -> 1429.4029 | ... U84: =U80-U82 -> 2704.0958 | Y84: =Y80-Y82 -> -8506 | Z84: =Z80-Z82 -> -6767.4949 | AA84: =AA80-AA82 -> -493.6074 | AB84: =AB80-AB82 -> -9137.4202 | AC84: =AC80-AC82 -> 1887.2882 | AD84: =AD80-AD82 -> 9856.3718 | AE84: =AE80-AE82 -> 10053.429 | AF84: =AF80-AF82 -> 10167.509 | ... AO84: =AO80-AO82 -> 34971.469 | AP84: =AO84*(1+$AS$98) -> 34621.754 | AQ84: =AP84*(1+$AS$98) -> 34275.537 | AR84: =AQ84*(1+$AS$98) -> 33932.781 | AS84: =AR84*(1+$AS$98) -> 33593.454 | AT84: =AS84*(1+$AS$98) -> 33257.519 | AU84: =AT84*(1+$AS$98) -> 32924.944 | AV84: =AU84*(1+$AS$98) -> 32595.694 | AW84: =AV84*(1+$AS$98) -> 32269.737 | ... EG84: =EF84*(1+$AS$98) -> 13325.777
A85: % | B85: =+B84/B$52 -> -0.86518821 | C85: =+C84/C$52 -> -0.32218506 | D85: =+D84/D$52 -> -0.14455232 | E85: =+E84/E$52 -> 0.069129778 | F85: =+F84/F$52 -> -0.017684719 | G85: =+G84/G$52 -> 0.042740271 | H85: =+H84/H$52 -> 0.023824489 | I85: =+I84/I$52 -> 0.14385516 | ... U85: =+U84/U$52 -> 0.17111715 | Y85: =+Y84/Y$52 -> -0.60125822 | Z85: =+Z84/Z$52 -> -0.60752204 | AA85: =+AA84/AA$52 -> -0.028274978 | AB85: =+AB84/AB$52 -> -0.28661399 | AC85: =+AC84/AC$52 -> 0.050622934 | AD85: =+AD84/AD$52 -> 0.22411862 | AE85: =+AE84/AE$52 -> 0.19327039 | AF85: =+AF84/AF$52 -> 0.17452099 | ... AO85: =+AO84/AO$52 -> 0.19147776
A86: EPS | B86: =B84/B88 -> -3.0290168 | C86: =C84/C88 -> -1.3210543 | D86: =D84/D88 -> -0.60939869 | E86: =E84/E88 -> 0.28875435 | F86: =F84/F88 -> -0.077655681 | G86: =G84/G88 -> 0.18974351 | H86: =H84/H88 -> 0.10500207 | I86: =I84/I88 -> 0.6736429 | ... U86: =U84/U88 -> 1.2839961 | Y86: =Y84/Y88 -> -6.8137778 | Z86: =Z84/Z88 -> -3.8607421 | AA86: =AA84/AA88 -> -0.26041013 | AB86: =AB84/AB88 -> -4.6267762 | AC86: =AC84/AC88 -> 0.90227479 | AD86: =AD84/AD88 -> 4.5832931 | AE86: =AE84/AE88 -> 4.765608 | AF86: =AF84/AF88 -> 4.9180462 | ... AO86: =AO84/AO88 -> 20.28884
A87: % | F87: =+F86/B86-1 -> -0.97436274 | G87: =+G86/C86-1 -> -1.1436304 | H87: =+H86/D86-1 -> -1.1723044 | I87: =+I86/E86-1 -> 1.3329273 | J87: =+J86/F86-1 -> 3.0466387 | K87: =+K86/G86-1 -> 1.4888692 | L87: =+L86/H86-1 -> 10.548114 | M87: =+M86/I86-1 -> 3.7717658 | ... S87: =+S86/O86-1 -> 0.79652671 | Z87: =+Z86/Y86-1 -> -0.43339184 | AA87: =+AA86/Z86-1 -> -0.9325492 | AB87: =+AB86/AA86-1 -> 16.767267 | AC87: =+AC86/AB86-1 -> -1.1950115 | AD87: =+AD86/AC86-1 -> 4.0797087 | AE87: =+AE86/AD86-1 -> 0.039778141 | AF87: =+AF86/AE86-1 -> 0.031987141 | AG87: =+AG86/AF86-1 -> -0.034627238 | ... AO87: =+AO86/AN86-1 -> 0.15276327
A88: Shares | B88: 1957.731 | C88: 1968.882 | D88: 1979 | E88: 2060.575 | F88: 2009.5 | G88: 2079.2 | H88: 2108.4 | I88: 2121.9 | J88: 2080.1 | K88: 2150 | L88: 2154.46 | M88: 2141.4 | N88: 2122.618 | O88: 2085.4 | P88: 2124.3 | Q88: 2106 | R88: 2071.391 | S88: 2050.225 | T88: 2106 | U88: 2106 | Y88: 1248.353 | Z88: 1752.9 | AA88: 1895.5 | AB88: 1974.9 | AC88: 2091.7 | AD88: 2150.5 | AE88: =AVERAGE(N88:Q88) -> 2109.5795 | AF88: =+AE88*0.98 -> 2067.3879 | AG88: =+AF88*0.98 -> 2026.0402 | AH88: =+AG88*0.98 -> 1985.5193 | AI88: =+AH88*0.98 -> 1945.809 | AJ88: =+AI88*0.98 -> 1906.8928 | AK88: =+AJ88*0.98 -> 1868.7549 | AL88: =+AK88*0.98 -> 1831.3798 | AM88: =+AL88*0.98 -> 1794.7522 | ... AO88: =+AN88*0.98 -> 1723.68
A89: % | C89: =+C88/B88-1 -> 0.0056958796 | D89: =+D88/C88-1 -> 0.005138957 | E89: =+E88/D88-1 -> 0.041220313 | F89: =+F88/E88-1 -> -0.024786771 | G89: =+G88/F88-1 -> 0.034685245 | H89: =+H88/G88-1 -> 0.014043863 | I89: =+I88/H88-1 -> 0.0064029596 | J89: =+J88/I88-1 -> -0.019699326 | ... S89: =+S88/R88-1 -> -0.010218254 | Z89: =+Z88/Y88-1 -> 0.40417013 | AA89: =+AA88/Z88-1 -> 0.081350904 | AB89: =+AB88/AA88-1 -> 0.041888684 | AC89: =+AC88/AB88-1 -> 0.059142235 | AD89: =+AD88/AC88-1 -> 0.028111106 | AE89: =+AE88/AD88-1 -> -0.019028365 | AF89: =+AF88/AE88-1 -> -0.02 | AG89: =+AG88/AF88-1 -> -0.02 | ... AO89: =+AO88/AN88-1 -> -0.02
A94: Gross Margin | B94: =B56/B52 -> 0.37554713 | C94: =C56/C52 -> 0.33159916 | D94: =D56/D52 -> 0.35275081 | E94: =E56/E52 -> 0.35749971 | F94: =F56/F52 -> 0.38054959 | G94: =G56/G52 -> 0.37999124 | H94: =H56/H52 -> 0.37249703 | I94: =I56/I52 -> 0.36999334 | ... U94: =U56/U52 -> 0.43 | Y94: =Y56/Y52 -> 0.45712872 | Z94: =Z56/Z52 -> 0.48570426 | AA94: =AA56/AA52 -> 0.41268434 | AB94: =AB56/AB52 -> 0.3536504 | AC94: =AC56/AC52 -> 0.37555806 | AD94: =AD56/AD52 -> 0.37783054 | AE94: =AE56/AE52 -> 0.38372579 | AF94: =AF56/AF52 -> 0.4 | ... AO94: =AO56/AO52 -> 0.445
A95: Op Margin | B95: =B68/B52 -> -0.070323898 | C95: =C68/C52 -> -0.088319088 | D95: =D68/D52 -> -0.059331176 | E95: =E68/E52 -> -0.016498199 | F95: =F68/F52 -> -0.02958415 | G95: =G68/G52 -> 0.035373402 | H95: =H68/H52 -> 0.042441881 | I95: =I68/I52 -> 0.065657853 | ... U95: =U68/U52 -> 0.10090352 | Y95: =Y68/Y52 -> -0.60761999 | Z95: =Z68/Z52 -> -0.43650906 | AA95: =AA68/AA52 -> -0.21948337 | AB95: =AB68/AB52 -> -0.057352164 | AC95: =AC68/AC52 -> 0.029781379 | AD95: =AD68/AD52 -> 0.063653376 | AE95: =AE68/AE52 -> 0.10699162 | AF95: =AF68/AF52 -> 0.13 | ... AO95: =AO68/AO52 -> 0.215
A96: NI Margin | B96: =+B84/B52 -> -0.86518821 | C96: =+C84/C52 -> -0.32218506 | D96: =+D84/D52 -> -0.14455232 | E96: =+E84/E52 -> 0.069129778 | F96: =+F84/F52 -> -0.017684719 | G96: =+G84/G52 -> 0.042740271 | H96: =+H84/H52 -> 0.023824489 | I96: =+I84/I52 -> 0.14385516 | ... U96: =+U84/U52 -> 0.17111715 | Y96: =+Y84/Y52 -> -0.60125822 | Z96: =+Z84/Z52 -> -0.60752204 | AA96: =+AA84/AA52 -> -0.028274978 | AB96: =+AB84/AB52 -> -0.28661399 | AC96: =+AC84/AC52 -> 0.050622934 | AD96: =+AD84/AD52 -> 0.22411862 | AE96: =+AE84/AE52 -> 0.19327039 | AF96: =+AF84/AF52 -> 0.17452099 | ... AO96: =+AO84/AO52 -> 0.19147776
A97: Tax Rate | B97: =B76/B74 -> 0.037613489 | C97: =C76/C74 -> -0.030125196 | D97: =D76/D74 -> -0.049319728 | E97: =E76/E74 -> -0.17721519 | F97: =F76/F74 -> -0.40131605 | G97: =G76/G74 -> 0.14269572 | H97: =H76/H74 -> -0.22677491 | I97: =I76/I74 -> 0.07274108 | ... S97: =S76/S74 -> 0.25633201 | Y97: =Y76/Y74 -> -0.0053361793 | Z97: =Z76/Z74 -> 0.027643818 | AA97: =AA76/AA74 -> 0.48112306 | AB97: =AB76/AB74 -> 0.019209502 | AC97: =AC76/AC74 -> 0.091759396 | AD97: =AD76/AD74 -> -1.395753 | AE97: =AE76/AE74 -> -0.74925494 | AF97: =AF76/AF74 -> -0.2 | ... AO97: =AO76/AO74 -> 0.2
A98: Incremental Margin | F98: =(F68-B68)/(F52-B52) -> 0.11216062 | G98: =(G68-C68)/(G52-C52) -> 0.89805745 | H98: =(H68-D68)/(H52-D52) -> 0.93680128 | I98: =(I68-E68)/(I52-E52) -> 0.59756368 | J98: =(J68-F68)/(J52-F52) -> 0.33149207 | K98: =(K68-G68)/(K52-G52) -> 0.31964267 | L98: =(L68-H68)/(L52-H52) -> 0.35181368 | M98: =(M68-I68)/(M52-I52) -> 0.058354795 | ... S98: =(S68-O68)/(S52-O52) -> 0.28551302 | Z98: =(Z68-Y68)/(Z52-Y52) -> -1.2414003 | AA98: =(AA68-Z68)/(AA52-Z52) -> 0.16316965 | AB98: =(AB68-AA68)/(AB52-AA52) -> 0.13888658 | AC98: =(AC68-AB68)/(AC52-AB52) -> 0.54413388 | AD98: =(AD68-AC68)/(AD52-AC52) -> 0.25221182 | AE98: =(AE68-AD68)/(AE52-AD52) -> 0.3440773 | AF98: =(AF68-AE68)/(AF52-AE52) -> 0.32173651 | AG98: =(AG68-AF68)/(AG52-AF52) -> 0.16833333 | ... AO98: =(AO68-AN68)/(AO52-AN52) -> 0.265 | AR98: Terminal | AS98: -0.01
AR99: Discount | AS99: 0.1012
AR100: ROIC | AS100: 0.02
A101: NWC | B101: =+B125-B136 -> 1614 | C101: =+C125-C136 -> 1649 | D101: =+D125-D136 -> 1694 | E101: =+E125-E136 -> 2051 | F101: =+F125-F136 -> 1859 | G101: =+G125-G136 -> 1882 | H101: =+H125-H136 -> 2201 | I101: =+I125-I136 -> 2614 | ... S101: =+S125-S136 -> 2932 | Y101: =+Y125+Y126-Y136-Y138+Y124 -> 1560 | Z101: =+Z125+Z126-Z136-Z138+Z124 -> 1990 | AA101: =+AA125+AA126-AA136-AA138+AA124 -> 1591 | AB101: =+AB125+AB126-AB136-AB138+AB124 -> 1941 | AC101: =+AC125+AC126-AC136-AC138+AC124 -> 2945 | AD101: =+AD125+AD126-AD136-AD138+AD124 -> 2195 | AE101: =+AE125+AE126-AE136-AE138+AE124 -> 1857 | AF101: =+AF125+AF126-AF136-AF138-AF141 -> -7418.1129 | AG101: =+AG125+AG126-AG136-AG138-AG141 -> -8595.0749 | AH101: =+AH125+AH126-AH136-AH138-AH141 -> -10172.567 | AI101: =+AI125+AI126-AI136-AI138-AI141 -> -11584.057 | AJ101: =+AJ125+AJ126-AJ136-AJ138-AJ141 -> -13426.762 | AK101: =+AK125+AK126-AK136-AK138-AK141 -> -15262.795 | AL101: =+AL125+AL126-AL136-AL138-AL141 -> -17263.424 | AM101: =+AM125+AM126-AM136-AM138-AM141 -> -19316.593 | ... AO101: =+AO125+AO126-AO136-AO138-AO141 -> -23540.526 | AR101: NPV | AS101: =NPV(AS99,AF84:EG84)+Main!E4-Main!E5 -> 228547.85
A102: ROA | C102: =+SUM(C84)/AVERAGE(B134:C134) -> -0.081502836 | D102: =+SUM(D84)/AVERAGE(C134:D134) -> -0.038824325 | E102: =+SUM(E84)/AVERAGE(D134:E134) -> 0.018822859 | F102: =+SUM(F84)/AVERAGE(E134:F134) -> -0.0048342346 | G102: =+SUM(G84)/AVERAGE(F134:G134) -> 0.011861715 | H102: =+SUM(H84)/AVERAGE(G134:H134) -> 0.0063237888 | I102: =+SUM(I84)/AVERAGE(H134:I134) -> 0.038297151 | J102: =+SUM(J84)/AVERAGE(I134:J134) -> -0.016696722 | ... S102: =+SUM(S84)/AVERAGE(R134:S134) -> 0.038094935 | Z102: =+SUM(Z84)/AVERAGE(Y134:Z134) -> -0.20818833 | AA102: =+SUM(AA84)/AVERAGE(Z134:AA134) -> -0.01370633 | AB102: =+SUM(AB84)/AVERAGE(AA134:AB134) -> -0.2578165 | AC102: =+SUM(AC84)/AVERAGE(AB134:AC134) -> 0.053307133 | AD102: =+SUM(AD84)/AVERAGE(AC134:AD134) -> 0.21916911 | AE102: =+SUM(AE84)/AVERAGE(AD134:AE134) -> 0.17786428 | AR102: Price | AS102: =AS101/Main!E2 -> 112.27548
A103: ROE | C103: =+C104*C105*C96 -> -0.30632434 | D103: =+D104*D105*D96 -> -0.17172149 | E103: =+E104*E105*E96 -> 0.080672497 | F103: =+F104*F105*F96 -> -0.019115464 | G103: =+G104*G105*G96 -> 0.044646037 | H103: =+H104*H105*H96 -> 0.022654015 | I103: =+I104*I105*I96 -> 0.12904824 | J103: =+J104*J105*J96 -> -0.054754562 | ... S103: =+S104*S105*S96 -> 0.090106705 | Z103: =+Z104*Z105*Z96 -> -0.46773991 | AA103: =+AA104*AA105*AA96 -> -0.03392141 | AB103: =+AB104*AB105*AB96 -> -0.76614432 | AC103: =+AC104*AC105*AC96 -> 0.18383871 | AD103: =+AD104*AD105*AD96 -> 0.57286169 | AE103: =+AE104*AE105*AE96 -> 0.39973078 | AR103: Diff | AS103: =+AS102/Main!E1-1 -> 0.49700636
A104: A. Turnover | C104: =+SUM(C52)/AVERAGE(B134:C134) -> 0.25296901 | D104: =+SUM(D52)/AVERAGE(C134:D134) -> 0.2685832 | E104: =+SUM(E52)/AVERAGE(D134:E134) -> 0.27228294 | F104: =+SUM(F52)/AVERAGE(E134:F134) -> 0.2733566 | G104: =+SUM(G52)/AVERAGE(F134:G134) -> 0.27753017 | H104: =+SUM(H52)/AVERAGE(G134:H134) -> 0.26543229 | I104: =+SUM(I52)/AVERAGE(H134:I134) -> 0.2662202 | J104: =+SUM(J52)/AVERAGE(I134:J134) -> 0.25878924 | ... S104: =+SUM(S52)/AVERAGE(R134:S134) -> 0.22581672 | Z104: =+SUM(Z52)/AVERAGE(Y134:Z134) -> 0.34268441 | AA104: =+SUM(AA52)/AVERAGE(Z134:AA134) -> 0.48475123 | AB104: =+SUM(AB52)/AVERAGE(AA134:AB134) -> 0.89952517 | AC104: =+SUM(AC52)/AVERAGE(AB134:AC134) -> 1.0530234 | AD104: =+SUM(AD52)/AVERAGE(AC134:AD134) -> 0.97791566 | AE104: =+SUM(AE52)/AVERAGE(AD134:AE134) -> 0.92028727
A105: Financial Leverage | C105: =+AVERAGE(B134:C134)/AVERAGE(B151:C151) -> 3.7584501 | D105: =+AVERAGE(C134:D134)/AVERAGE(C151:D151) -> 4.4230386 | E105: =+AVERAGE(D134:E134)/AVERAGE(D151:E151) -> 4.2858789 | F105: =+AVERAGE(E134:F134)/AVERAGE(E151:F151) -> 3.9541863 | G105: =+AVERAGE(F134:G134)/AVERAGE(F151:G151) -> 3.7638771 | H105: =+AVERAGE(G134:H134)/AVERAGE(G151:H151) -> 3.5823484 | I105: =+AVERAGE(H134:I134)/AVERAGE(H151:I151) -> 3.3696565 | J105: =+AVERAGE(I134:J134)/AVERAGE(I151:J151) -> 3.27936 | ... S105: =+AVERAGE(R134:S134)/AVERAGE(R151:S151) -> 2.3653198 | Z105: =+AVERAGE(Y134:Z134)/AVERAGE(Y151:Z151) -> 2.2467153 | AA105: =+AVERAGE(Z134:AA134)/AVERAGE(Z151:AA151) -> 2.4748717 | AB105: =+AVERAGE(AA134:AB134)/AVERAGE(AA151:AB151) -> 2.9716652 | AC105: =+AVERAGE(AB134:AC134)/AVERAGE(AB151:AC151) -> 3.44867 | AD105: =+AVERAGE(AC134:AD134)/AVERAGE(AC151:AD151) -> 2.6137885 | AE105: =+AVERAGE(AD134:AE134)/AVERAGE(AD151:AE151) -> 2.2473921
A106: Financial Leverage % | C106: =+C103-C102 -> -0.22482151 | D106: =+D103-D102 -> -0.13289716 | E106: =+E103-E102 -> 0.061849637 | F106: =+F103-F102 -> -0.01428123 | G106: =+G103-G102 -> 0.032784322 | H106: =+H103-H102 -> 0.016330226 | I106: =+I103-I102 -> 0.090751093 | J106: =+J103-J102 -> -0.03805784 | ... S106: =+S103-S102 -> 0.05201177 | Z106: =+Z103-Z102 -> -0.25955158 | AA106: =+AA103-AA102 -> -0.020215079 | AB106: =+AB103-AB102 -> -0.50832782 | AC106: =+AC103-AC102 -> 0.13053157 | AD106: =+AD103-AD102 -> 0.35369259 | AE106: =+AE103-AE102 -> 0.22186649
AU108: EV | AV108: =+AS111 -> 214646
A109: NOPAT | B109: =+B68*(1-B97) -> -463.8703 | C109: =+C68*(1-C97) -> -734.47926 | D109: =+D68*(1-D97) -> -519.41327 | E109: =+E68*(1-E97) -> -167.16456 | F109: =+F68*(1-F97) -> -365.81228 | G109: =+G68*(1-G97) -> 279.92245 | H109: =+H68*(1-H97) -> 483.82329 | I109: =+I68*(1-I97) -> 604.94639 | ... S109: =+S68*(1-S97) -> 1405.5325 | Y109: =+Y68*(1-Y97) -> -8641.8698 | Z109: =+Z68*(1-Z97) -> -4728.077 | AA109: =+AA68*(1-AA97) -> -1988.1327 | AB109: =+AB68*(1-AB97) -> -1793.2972 | AC109: =+AC68*(1-AC97) -> 1008.4088 | AD109: =+AD68*(1-AD97) -> 6706.6034 | AE109: =+AE68*(1-AE97) -> 9735.354 | AF109: =+AF68*(1-AF97) -> 9088.4852 | ... AO109: =+AO68*(1-AO97) -> 31414.054 | AR109: Terminal | AS109: -0.01 | AU109: Debt (-) | AV109: =+Main!E5 -> 10514
A110: EBITDA | B110: =B68+B157 -> -228 | C110: =C68+C157 -> -470 | D110: =D68+D157 -> -268 | E110: =E68+E157 -> 81 | F110: =F68+F157 -> -54.049091 | G110: =G68+G157 -> 534.5147 | H110: =H68+H157 -> 599.38636 | I110: =I68+I157 -> 855.40288 | ... L110: =L68+L157 -> 1247.4461 | M110: =M68+L157 -> 956.45783 | N110: =N68+N157 -> 1406.3284 | O110: =O68+O157 -> 1631.4338 | P110: =P68+P157 -> 1308.4888 | Q110: =Q68+Q157 -> 1967 | R110: =R68+R157 -> 2114 | S110: =S68+S157 -> 2085 | Y110: =Y68+Y157 -> -8124 | Z110: =Z68+Z157 -> -4287.4949 | AA110: =AA68+AA157 -> -2929.6074 | AB110: =AB68+AB157 -> -881.42023 | AC110: =AC68+AC157 -> 1933.2882 | AD110: =AD68+AD157 -> 3536.3718 | AE110: =AE68+AE157 -> 6312.4289 | AR110: Discount | AS110: =+Main!E14 -> 0.1022896 | AU110: Cash (+) | AV110: =+Main!E4 -> 8911
A111: Adj. EBITDA | B111: 168 | C111: 364 | D111: 516 | E111: 665 | F111: 761 | G111: 916 | H111: 1092 | I111: 1283 | J111: 1382 | K111: 1570 | L111: 1690 | M111: 1842 | N111: 1868 | O111: 2119 | P111: 2256 | Q111: 2487 | R111: 2481 | S111: 2819 | Y111: -2725 | Z111: -2528 | AA111: -774 | AB111: 1713 | AC111: 4052 | AD111: 6484 | AE111: 8730 | AR111: EV | AS111: =+NPV(AS110,AF113:AN113,AO113+AS112) -> 214646 | AU111: Equity Value | AV111: =+AV108-AV109+AV110 -> 213043
A112: Book Value | B112: =B134-B144-B150 -> 9613 | C112: =C134-C144-C150 -> 7369 | D112: =D134-D144-D150 -> 6677 | E112: =E134-E144-E150 -> 8074 | F112: =F134-F144-F150 -> 8253 | G112: =G134-G144-G150 -> 9420 | H112: =H134-H144-H150 -> 10125 | I112: =I134-I144-I150 -> 12028 | ... S112: =S134-S144-S150 -> 27496 | Y112: =Y134-Y144-Y150 -> 14871.626 | Z112: =Z134-Z144-Z150 -> 12966.412 | AA112: =AA134-AA144-AA150 -> 15144.573 | AB112: =AB134-AB144-AB150 -> 8073.7732 | AC112: =AC134-AC144-AC150 -> 12027.8 | AD112: =AD134-AD144-AD150 -> 22382.784 | AE112: =AE134-AE144-AE150 -> 27917.815 | AR112: TV | AS112: =+AO113*(1+AS109)/(AS110-AS109) -> 300479.62 | AU112: Shares | AV112: =+Main!E2 -> 2035.599
...

Sheet Bond
A1: Main
B4: isin | C4: bondType | D4: immediateIssuer | E4: coupon | F4: couponType | G4: maturityDate | H4: callable | I4: currency | J4: seniorityLevel | K4: liquidityScore
B5: US90353TAR14 | C5: — | D5: Uber Technologies, Inc. | E5: 0 | F5: Non-Interest-Bearing | G5: 15/05/2028 | H5: N | I5: USD | J5: Senior | K5: — | M5: Zero-coupon bond backed by Aurora stocks priced at 8.50$ a share
B6: US90353TAM27 | C6: — | D6: Uber Technologies, Inc. | E6: 875 | F6: Fixed Listing | G6: 01/12/2028 | H6: N | I6: USD | J6: Senior | K6: — | M6: convertible bond with a conversion price of 72.54$. If the stock trades at 94.30$ for 20 trading days it can be redeemed.
B7: US90353TAK60 | C7: — | D7: Uber Technologies, Inc. | E7: 4500 | F7: Fixed Listing | G7: 15/08/2029 | H7: Y | I7: USD | J7: Senior | K7: —
B8: USU9029YAG53 | C8: — | D8: Uber Technologies, Inc. | E8: 4500 | F8: Fixed Listing | G8: 15/08/2029 | H8: Y | I8: USD | J8: Senior | K8: —
B9: US90353TAN00 | C9: — | D9: Uber Technologies, Inc. | E9: 4300 | F9: Fixed Listing | G9: 15/01/2030 | H9: Y | I9: USD | J9: Senior | K9: —
B10: US90353TAT79 | C10: — | D10: Uber Technologies, Inc. | E10: 4150 | F10: Fixed Listing | G10: 15/01/2031 | H10: Y | I10: USD | J10: Senior | K10: —
B11: US90353TAP57 | C11: — | D11: Uber Technologies, Inc. | E11: 4800 | F11: Fixed Listing | G11: 15/09/2034 | H11: Y | I11: USD | J11: Senior | K11: —
B12: US90353TAU43 | C12: — | D12: Uber Technologies, Inc. | E12: 4800 | F12: Fixed Listing | G12: 15/09/2035 | H12: Y | I12: USD | J12: Senior | K12: —
B13: US90353TAQ31 | C13: — | D13: Uber Technologies, Inc. | E13: 5350 | F13: Fixed Listing | G13: 15/09/2054 | H13: Y | I13: USD | J13: Senior | K13: —
E14: =+AVERAGE(E5:E13) -> 3697.2222

Sheet Board 
A1: Main | G1: auditor | H1: PwC
A2: 2026
A3: -> | B3: EPS instead of adj. EBITDA and adj. EBITDA less SBC
A4: -> | B4: EPS will account for 60% of compensation bonus, Gross Booking 30%
A5: -> | B5: shifting to a 3 years NON-GAAP bonus compensation instead of annual adj. EBITDA margin
B6: -> | C6: 90% of SBC will be based on financial performance, therefore they consider this the main long-term driver
A7: -> | B7: SBC liked to increase in safety in their departments (Delivery, Mobility, Freight) – 10% compensation
B10: Cybersecurity
B11: -> | C11: Nikesh Arora (Palo Alto Networks CEO) expertise in AI cybersecurity
B13: AV Transparency
B14: -> | C14: More transparency in the Autonomous, Mobility and Delivery safety guidelines (AM&D)
C15: AM&D safety program to govern partner deployment for future AV
B17: Electrification Strategy
B18: -> | C18: publishing the Electrification Update in order to focus more on EV and less on “Green Vehicles”
C19: 2040 net-zero goal
B22: The Board is aiming to partner with the highest amount of AV companies possible (and often investing in them) in order to have a competitive advantage as soon as someone reahces a level 5 automation.
A25: 6% of UBER is owned by the Public Investment Fund (Saudi’s investment fund)
