Workbook

Sheet Main
A1: Waste Management Inc. | E1: Price | F1: 225
E2: Share | F2: 399.71518 | G2: Q226
E3: MC | F3: =+F1*F2 -> 89935.916
E4: Cash | F4: 557 | G4: Q226
E5: Debt | F5: =+22281+1075 -> 23356 | G5: Q226
E6: EV | F6: =+F3-F4+F5 -> 112734.92
A9: CAPM | B9: =+0.0495+B10*(0.1-0.0495) -> 0.07172 | D9: WACC | E9: =+(F3/(F3+F5))*B9+(F5/(F3+F5))*B11*(1-Model!V70) -> 0.066275701
A10: BETA | B10: 0.44 | D10: PEG
A11: Cost of Debt | B11: =+0.0495+(B17/100) -> 0.057304348 | D11: FPE
D13: P/B | E13: =+F1/Model!K75 -> 9.1224181
A17: Cr Spread | B17: =+'[1]Credit Spread US'!J6 -> 0.78043478
A18: Cr Rating | B18: A- | C18: A3
B19: S&P | C19: Moody’s
A32: Solid Waste Business, managed locally
A34: WM Renewable Energy, operated through landfills gas-to-energy to produce RNG (Renewable Natural Gas)
A36: Following 2024 Sterilcycle they have been developing also Heathcare waste solutions.

Sheet Model
A1: Main
A2: in Million | B2: Q124 | C2: Q224 | D2: Q324 | E2: Q424 | F2: Q125 | G2: Q225 | H2: Q325 | I2: Q425 | J2: Q126 | K2: Q226 | L2: Q326 | M2: Q426 | Q2: 2020 | R2: =+Q2+1 -> 2021 | S2: =+R2+1 -> 2022 | T2: =+S2+1 -> 2023 | U2: =+T2+1 -> 2024 | V2: =+U2+1 -> 2025 | W2: =+V2+1 -> 2026 | X2: =+W2+1 -> 2027 | Y2: =+X2+1 -> 2028 | ... AG2: =+AF2+1 -> 2036
A4: Commercial | B4: 1316 | C4: 1330 | D4: 1359 | E4: 1366 | F4: 1380 | G4: 1398 | H4: 1419 | I4: 1433 | J4: 1429 | K4: 1485 | Q4: 4102 | R4: 4760 | S4: 4860 | T4: 5109 | U4: 5371 | V4: 5630
A5: Y/Y | F5: =+F4/B4-1 -> 0.048632219 | G5: =+G4/C4-1 -> 0.05112782 | H5: =+H4/D4-1 -> 0.04415011 | I5: =+I4/E4-1 -> 0.049048316 | J5: =+J4/F4-1 -> 0.035507246 | K5: =+K4/G4-1 -> 0.06223176 | R5: =+R4/Q4-1 -> 0.16040956 | T5: =+T4/S4-1 -> 0.051234568 | U5: =+U4/T4-1 -> 0.051282051 | V5: =+V4/U4-1 -> 0.048221933
A6: Industrial | B6: 747 | C6: 779 | D6: 797 | E6: 766 | F6: 741 | G6: 790 | H6: 808 | I6: 767 | J6: 758 | K6: 820 | Q6: 2716 | R6: 3210 | S6: 3025 | T6: 3083 | U6: 3089 | V6: 3106
A7: Y/Y | F7: =+F6/B6-1 -> -0.0080321285 | G7: =+G6/C6-1 -> 0.014120668 | H7: =+H6/D6-1 -> 0.013801757 | I7: =+I6/E6-1 -> 0.001305483 | J7: =+J6/F6-1 -> 0.02294197 | K7: =+K6/G6-1 -> 0.037974684 | R7: =+R6/Q6-1 -> 0.18188513 | T7: =+T6/S6-1 -> 0.019173554 | U7: =+U6/T6-1 -> 0.0019461563 | V7: =+V6/U6-1 -> 0.0055033992
A8: Residential | B8: 854 | C8: 863 | D8: 875 | E8: 874 | F8: 872 | G8: 872 | H8: 884 | I8: 882 | J8: 888 | K8: 911 | Q8: 2770 | R8: 3172 | S8: 3264 | T8: 3378 | U8: 3466 | V8: 3510
A9: Y/Y | F9: =+F8/B8-1 -> 0.021077283 | G9: =+G8/C8-1 -> 0.010428737 | H9: =+H8/D8-1 -> 0.010285714 | I9: =+I8/E8-1 -> 0.0091533181 | J9: =+J8/F8-1 -> 0.018348624 | K9: =+K8/G8-1 -> 0.044724771 | R9: =+R8/Q8-1 -> 0.14512635 | T9: =+T8/S8-1 -> 0.034926471 | U9: =+U8/T8-1 -> 0.026050918 | V9: =+V8/U8-1 -> 0.012694749
A10: Other Collection | B10: 698 | C10: 729 | D10: 765 | E10: 772 | F10: 753 | G10: 796 | H10: 819 | I10: 807 | J10: 794 | K10: 849 | Q10: 465 | R10: 533 | S10: 2466 | T10: 2786 | U10: 2964 | V10: 3175
A11: Y/Y | F11: =+F10/B10-1 -> 0.078796562 | G11: =+G10/C10-1 -> 0.091906722 | H11: =+H10/D10-1 -> 0.070588235 | I11: =+I10/E10-1 -> 0.045336788 | J11: =+J10/F10-1 -> 0.054448871 | K11: =+K10/G10-1 -> 0.066582915 | R11: =+R10/Q10-1 -> 0.14623656 | T11: =+T10/S10-1 -> 0.1297648 | U11: =+U10/T10-1 -> 0.063890883 | V11: =+V10/U10-1 -> 0.071187584
A12: Total Collection | B12: =+B10+B8+B6+B4 -> 3615 | C12: =+C10+C8+C6+C4 -> 3701 | D12: =+D10+D8+D6+D4 -> 3796 | E12: =+E10+E8+E6+E4 -> 3778 | F12: =+F10+F8+F6+F4 -> 3746 | G12: =+G10+G8+G6+G4 -> 3856 | H12: =+H10+H8+H6+H4 -> 3930 | I12: =+I10+I8+I6+I4 -> 3889 | ... K12: =+K10+K8+K6+K4 -> 4065 | Q12: =+Q10+Q8+Q6+Q4 -> 10053 | R12: =+R10+R8+R6+R4 -> 11675 | S12: =+S10+S8+S6+S4 -> 13615 | T12: =+T10+T8+T6+T4 -> 14356 | U12: =+U10+U8+U6+U4 -> 14890 | V12: =+V10+V8+V6+V4 -> 15421
A13: Y/Y | F13: =+F12/B12-1 -> 0.036237898 | G13: =+G12/C12-1 -> 0.041880573 | H13: =+H12/D12-1 -> 0.035300316 | I13: =+I12/E12-1 -> 0.029380625 | J13: =+J12/F12-1 -> 0.032835024 | K13: =+K12/G12-1 -> 0.054201245 | R13: =+R12/Q12-1 -> 0.16134487 | T13: =+T12/S12-1 -> 0.054425266 | U13: =+U12/T12-1 -> 0.037196991 | V13: =+V12/U12-1 -> 0.035661518
A14: Landfill | B14: 792 | C14: 873 | D14: 923 | E14: 857 | F14: 840 | G14: 1036 | H14: 995 | I14: 910 | J14: 864 | K14: 1004 | Q14: 3667 | R14: 4153 | S14: 3062 | T14: 3252 | U14: 3445 | V14: 3781
A15: Y/Y | F15: =+F14/B14-1 -> 0.060606061 | G15: =+G14/C14-1 -> 0.18671249 | H15: =+H14/D14-1 -> 0.078006501 | I15: =+I14/E14-1 -> 0.061843641 | J15: =+J14/F14-1 -> 0.028571429 | K15: =+K14/G14-1 -> -0.030888031 | R15: =+R14/Q14-1 -> 0.13253341 | T15: =+T14/S14-1 -> 0.062050947 | U15: =+U14/T14-1 -> 0.059348093 | V15: =+V14/U14-1 -> 0.097532656
A16: Transfer | B16: 309 | C16: 348 | D16: 365 | E16: 359 | F16: 336 | G16: 389 | H16: 396 | I16: 381 | J16: 348 | K16: 410 | Q16: 1855 | R16: 2072 | S16: 1166 | T16: 1257 | U16: 1381 | V16: 1502
A17: Y/Y | F17: =+F16/B16-1 -> 0.087378641 | G17: =+G16/C16-1 -> 0.11781609 | H17: =+H16/D16-1 -> 0.084931507 | I17: =+I16/E16-1 -> 0.061281337 | J17: =+J16/F16-1 -> 0.035714286 | K17: =+K16/G16-1 -> 0.053984576 | R17: =+R16/Q16-1 -> 0.11698113 | T17: =+T16/S16-1 -> 0.078044597 | U17: =+U16/T16-1 -> 0.098647574 | V17: =+V16/U16-1 -> 0.087617668
A18: Total Collection and Disposal | B18: =+B16+B14+B12 -> 4716 | C18: =+C16+C14+C12 -> 4922 | D18: =+D16+D14+D12 -> 5084 | E18: =+E16+E14+E12 -> 4994 | F18: =+F16+F14+F12 -> 4922 | G18: =+G16+G14+G12 -> 5281 | H18: =+H16+H14+H12 -> 5321 | I18: =+I16+I14+I12 -> 5180 | ... K18: =+K16+K14+K12 -> 5479 | Q18: =+Q16+Q14+Q12 -> 15575 | R18: =+R16+R14+R12 -> 17900 | S18: =+S16+S14+S12 -> 17843 | T18: =+T16+T14+T12 -> 18865 | U18: =+U16+U14+U12 -> 19716 | V18: =+V16+V14+V12 -> 20704
A19: Y/Y | F19: =+F18/B18-1 -> 0.043681086 | G19: =+G18/C18-1 -> 0.07293783 | H19: =+H18/D18-1 -> 0.046616837 | I19: =+I18/E18-1 -> 0.037244694 | J19: =+J18/F18-1 -> 0.032303941 | K19: =+K18/G18-1 -> 0.037492899 | R19: =+R18/Q18-1 -> 0.14927769 | T19: =+T18/S18-1 -> 0.057277364 | U19: =+U18/T18-1 -> 0.045109992 | V19: =+V18/U18-1 -> 0.050111584
A20: Recycling Processing | B20: 368 | C20: 405 | D20: 432 | E20: 398 | F20: 384 | G20: 381 | H20: 372 | I20: 355 | J20: 368 | K20: 403 | Q20: 1127 | R20: 1681 | S20: 1516 | T20: 1264 | U20: 1603 | V20: 1492
A21: Y/Y | F21: =+F20/B20-1 -> 0.043478261 | G21: =+G20/C20-1 -> -0.059259259 | H21: =+H20/D20-1 -> -0.13888889 | I21: =+I20/E20-1 -> -0.1080402 | J21: =+J20/F20-1 -> -0.041666667 | K21: =+K20/G20-1 -> 0.057742782 | R21: =+R20/Q20-1 -> 0.49157054 | T21: =+T20/S20-1 -> -0.16622691 | U21: =+U20/T20-1 -> 0.2681962 | V21: =+V20/U20-1 -> -0.069245165
A22: Renewable Energy | B22: 69 | C22: 69 | D22: 87 | E22: 93 | F22: 91 | G22: 115 | H22: 115 | I22: 157 | J22: 159 | K22: 157 | Q22: 1776 | R22: 2112 | S22: 312 | T22: 273 | U22: 318 | V22: 478
A23: Y/Y | F23: =+F22/B22-1 -> 0.31884058 | G23: =+G22/C22-1 -> 0.66666667 | H23: =+H22/D22-1 -> 0.32183908 | I23: =+I22/E22-1 -> 0.68817204 | J23: =+J22/F22-1 -> 0.74725275 | K23: =+K22/G22-1 -> 0.36521739 | R23: =+R22/Q22-1 -> 0.18918919 | T23: =+T22/S22-1 -> -0.125 | U23: =+U22/T22-1 -> 0.16483516 | V23: =+V22/U22-1 -> 0.50314465
A24: WM Business | B24: =+B22+B20+B18 -> 5153 | C24: =+C22+C20+C18 -> 5396 | D24: =+D22+D20+D18 -> 5603 | E24: =+E22+E20+E18 -> 5485 | F24: =+F22+F20+F18 -> 5397 | G24: =+G22+G20+G18 -> 5777 | H24: =+H22+H20+H18 -> 5808 | I24: =+I22+I20+I18 -> 5692 | ... K24: =+K22+K20+K18 -> 6039 | S24: =+S22+S20+S18 -> 19671 | T24: =+T22+T20+T18 -> 20402 | U24: =+U22+U20+U18 -> 21637 | V24: =+V22+V20+V18 -> 22674
A25: Y/Y | F25: =+F24/B24-1 -> 0.047351058 | G25: =+G24/C24-1 -> 0.070607858 | H25: =+H24/D24-1 -> 0.036587542 | I25: =+I24/E24-1 -> 0.037739289 | J25: =+J24/F24-1 -> 0.039095794 | K25: =+K24/G24-1 -> 0.045352259 | T25: =+T24/S24-1 -> 0.037161303 | U25: =+U24/T24-1 -> 0.060533281 | V25: =+V24/U24-1 -> 0.047927162
A26: WM Healthcare | B26: 0 | C26: 0 | D26: 0 | E26: 403 | F26: 619 | G26: 646 | H26: 628 | I26: 616 | J26: 614 | K26: 638 | S26: 0 | T26: 0 | U26: 403 | V26: 2508
A27: Y/Y | F27: =+F26/B26-1 -> #DIV/0! | G27: =+G26/C26-1 -> #DIV/0! | H27: =+H26/D26-1 -> #DIV/0! | I27: =+I26/E26-1 -> 0.52853598 | J27: =+J26/F26-1 -> -0.0080775444 | K27: =+K26/G26-1 -> -0.012383901 | T27: =+T26/S26-1 -> #DIV/0! | U27: =+U26/T26-1 -> #DIV/0! | V27: =+V26/U26-1 -> 5.2233251
A28: Corporate and Other | B28: 6 | C28: 6 | D28: 6 | E28: 5 | F28: 2 | G28: 7 | H28: 7 | I28: 6 | J28: 5 | K28: 7 | Q28: -3260 | R28: -3762 | S28: 27 | T28: 24 | U28: 23 | V28: 22
A29: Y/Y | F29: =+F28/B28-1 -> -0.66666667 | G29: =+G28/C28-1 -> 0.16666667 | H29: =+H28/D28-1 -> 0.16666667 | I29: =+I28/E28-1 -> 0.2 | J29: =+J28/F28-1 -> 1.5 | K29: =+K28/G28-1 -> 0 | R29: =+R28/Q28-1 -> 0.15398773 | T29: =+T28/S28-1 -> -0.11111111 | U29: =+U28/T28-1 -> -0.041666667 | V29: =+V28/U28-1 -> -0.043478261
A30: Revenues | B30: =+B28+B26+B24 -> 5159 | C30: =+C28+C26+C24 -> 5402 | D30: =+D28+D26+D24 -> 5609 | E30: =+E28+E26+E24 -> 5893 | F30: =+F28+F26+F24 -> 6018 | G30: =+G28+G26+G24 -> 6430 | H30: =+H28+H26+H24 -> 6443 | I30: =+I28+I26+I24 -> 6314 | ... K30: =+K28+K26+K24 -> 6684 | Q30: =+Q18+Q20+Q22+Q28 -> 15218 | R30: =+R18+R20+R22+R28 -> 17931 | S30: =+S28+S26+S24 -> 19698 | T30: =+T28+T26+T24 -> 20426 | U30: =+U28+U26+U24 -> 22063 | V30: =+V28+V26+V24 -> 25204 | W30: =+V30*1.05 -> 26464.2 | X30: =+W30*1.12 -> 29639.904 | Y30: =+X30*1.11 -> 32900.293 | Z30: =+Y30*1.1 -> 36190.323 | AA30: =+Z30*1.09 -> 39447.452 | AB30: =+AA30*1.08 -> 42603.248 | AC30: =+AB30*1.07 -> 45585.475 | AD30: =+AC30*1.07 -> 48776.459 | AE30: =+AD30*1.07 -> 52190.811 | AF30: =+AE30*1.07 -> 55844.167 | AG30: =+AF30*1.07 -> 59753.259
A31: Y/Y | F31: =+F30/B30-1 -> 0.16650514 | G31: =+G30/C30-1 -> 0.19029989 | H31: =+H30/D30-1 -> 0.14868961 | I31: =+I30/E30-1 -> 0.071440692 | J31: =+J30/F30-1 -> 0.034729146 | K31: =+K30/G30-1 -> 0.039502333 | R31: =+R30/Q30-1 -> 0.17827573 | S31: =+S30/R30-1 -> 0.09854442 | T31: =+T30/S30-1 -> 0.036958067 | U31: =+U30/T30-1 -> 0.080142955 | V31: =+V30/U30-1 -> 0.14236505 | W31: =+W30/V30-1 -> 0.05 | X31: =+X30/W30-1 -> 0.12 | Y31: =+Y30/X30-1 -> 0.11 | ... AG31: =+AG30/AF30-1 -> 0.07
A32: COGS | B32: 3140 | C32: 3291 | D32: 3399 | E32: 3553 | F32: 3612 | G32: 3803 | H32: 3833 | I32: 3693 | J32: 3694 | K32: 3955 | Q32: 9341 | R32: 11111 | S32: 12294 | T32: 12606 | U32: 13383 | V32: 15012 | W32: =+W30-W34 -> 15746.199 | X32: =+X30-X34 -> 17487.543 | Y32: =+Y30-Y34 -> 19246.672 | Z32: =+Z30-Z34 -> 20990.387 | AA32: =+AA30-AA34 -> 22682.285 | AB32: =+AB30-AB34 -> 24283.851 | AC32: =+AC30-AC34 -> 25755.794 | AD32: =+AD30-AD34 -> 27314.817 | ... AG32: =+AG30-AG34 -> 32565.526
B33: =+B32/B$30 -> 0.60864509 | C33: =+C32/C$30 -> 0.60921881 | D33: =+D32/D$30 -> 0.60599037 | E33: =+E32/E$30 -> 0.60291872 | F33: =+F32/F$30 -> 0.6001994 | G33: =+G32/G$30 -> 0.59144635 | H33: =+H32/H$30 -> 0.5949092 | I33: =+I32/I$30 -> 0.58489072 | ... K33: =+K32/K$30 -> 0.59171155 | Q33: =+Q32/Q$30 -> 0.61381259 | R33: =+R32/R$30 -> 0.61965311 | S33: =+S32/S$30 -> 0.62412428 | T33: =+T32/T$30 -> 0.61715461 | U33: =+U32/U$30 -> 0.60658115 | V33: =+V32/V$30 -> 0.59561974 | W33: =+W32/W$30 -> 0.595 | X33: =+X32/X$30 -> 0.59 | ... AG33: =+AG32/AG$30 -> 0.545
A34: Gross Profit | B34: =+B30-B32 -> 2019 | C34: =+C30-C32 -> 2111 | D34: =+D30-D32 -> 2210 | E34: =+E30-E32 -> 2340 | F34: =+F30-F32 -> 2406 | G34: =+G30-G32 -> 2627 | H34: =+H30-H32 -> 2610 | I34: =+I30-I32 -> 2621 | ... K34: =+K30-K32 -> 2729 | Q34: =+Q30-Q32 -> 5877 | R34: =+R30-R32 -> 6820 | S34: =+S30-S32 -> 7404 | T34: =+T30-T32 -> 7820 | U34: =+U30-U32 -> 8680 | V34: =+V30-V32 -> 10192 | W34: =+W30*0.405 -> 10718.001 | X34: =+X30*0.41 -> 12152.361 | Y34: =+Y30*0.415 -> 13653.622 | Z34: =+Z30*0.42 -> 15199.936 | AA34: =+AA30*0.425 -> 16765.167 | AB34: =+AB30*0.43 -> 18319.397 | AC34: =+AC30*0.435 -> 19829.682 | AD34: =+AD30*0.44 -> 21461.642 | AE34: =+AE30*0.445 -> 23224.911 | AF34: =+AF30*0.45 -> 25129.875 | AG34: =+AG30*0.455 -> 27187.733
B35: =+B34/B$30 -> 0.39135491 | C35: =+C34/C$30 -> 0.39078119 | D35: =+D34/D$30 -> 0.39400963 | E35: =+E34/E$30 -> 0.39708128 | F35: =+F34/F$30 -> 0.3998006 | G35: =+G34/G$30 -> 0.40855365 | H35: =+H34/H$30 -> 0.4050908 | I35: =+I34/I$30 -> 0.41510928 | ... K35: =+K34/K$30 -> 0.40828845 | Q35: =+Q34/Q$30 -> 0.38618741 | R35: =+R34/R$30 -> 0.38034689 | S35: =+S34/S$30 -> 0.37587572 | T35: =+T34/T$30 -> 0.38284539 | U35: =+U34/U$30 -> 0.39341885 | V35: =+V34/V$30 -> 0.40438026 | W35: =+W34/W$30 -> 0.405 | X35: =+X34/X$30 -> 0.41 | ... AG35: =+AG34/AG$30 -> 0.455
A36: SG&A | B36: 491 | C36: 501 | D36: 525 | E36: 747 | F36: 687 | G36: 696 | H36: 665 | I36: 674 | J36: 707 | K36: 683 | Q36: 1728 | R36: 1864 | S36: 1938 | T36: 1926 | U36: 2264 | V36: 2722 | W36: =+V36*1.15 -> 3130.3 | X36: =+W36*1.15 -> 3599.845 | Y36: =+X36*1.15 -> 4139.8218 | Z36: =+Y36*1.1 -> 4553.8039 | AA36: =+Z36*1.1 -> 5009.1843 | AB36: =+AA36*1.1 -> 5510.1027 | AC36: =+AB36*1.1 -> 6061.113 | AD36: =+AC36*1.1 -> 6667.2243 | AE36: =+AD36*1.05 -> 7000.5855 | AF36: =+AE36*1.05 -> 7350.6148 | AG36: =+AF36*1.05 -> 7718.1456
B37: =+B36/B$30 -> 0.095173483 | C37: =+C36/C$30 -> 0.092743428 | D37: =+D36/D$30 -> 0.093599572 | E37: =+E36/E$30 -> 0.12676056 | F37: =+F36/F$30 -> 0.11415753 | G37: =+G36/G$30 -> 0.10824261 | H37: =+H36/H$30 -> 0.10321279 | I37: =+I36/I$30 -> 0.10674691 | ... K37: =+K36/K$30 -> 0.10218432 | Q37: =+Q36/Q$30 -> 0.11354974 | R37: =+R36/R$30 -> 0.10395405 | S37: =+S36/S$30 -> 0.098385623 | T37: =+T36/T$30 -> 0.094291589 | U37: =+U36/U$30 -> 0.10261524 | V37: =+V36/V$30 -> 0.10799873 | W37: =+W36/W$30 -> 0.11828432 | X37: =+X36/X$30 -> 0.12145265 | ... AG37: =+AG36/AG$30 -> 0.12916694
A38: D&A | B38: 514 | C38: 543 | D38: 558 | E38: 652 | F38: 691 | G38: 744 | H38: 729 | I38: 770 | J38: 735 | K38: 777 | Q38: 1671 | R38: 1999 | S38: 2038 | T38: 2071 | U38: 2267 | V38: 2863 | W38: =+V38*1.15 -> 3292.45 | X38: =+W38*1.15 -> 3786.3175 | Y38: =+X38*1.15 -> 4354.2651 | Z38: =+Y38*1.1 -> 4789.6916 | AA38: =+Z38*1.1 -> 5268.6608 | AB38: =+AA38*1.1 -> 5795.5269 | AC38: =+AB38*1.1 -> 6375.0796 | AD38: =+AC38*1.1 -> 7012.5875 | AE38: =+AD38*1.05 -> 7363.2169 | AF38: =+AE38*1.05 -> 7731.3777 | AG38: =+AF38*1.05 -> 8117.9466
B39: =+B38/B$30 -> 0.099631712 | C39: =+C38/C$30 -> 0.10051833 | D39: =+D38/D$30 -> 0.099482974 | E39: =+E38/E$30 -> 0.11063974 | F39: =+F38/F$30 -> 0.1148222 | G39: =+G38/G$30 -> 0.11570762 | H39: =+H38/H$30 -> 0.11314605 | I39: =+I38/I$30 -> 0.12195122 | ... K39: =+K38/K$30 -> 0.11624776 | Q39: =+Q38/Q$30 -> 0.10980418 | R39: =+R38/R$30 -> 0.11148291 | S39: =+S38/S$30 -> 0.10346228 | T39: =+T38/T$30 -> 0.10139038 | U39: =+U38/U$30 -> 0.10275121 | V39: =+V38/V$30 -> 0.11359308 | W39: =+W38/W$30 -> 0.12441147 | X39: =+X38/X$30 -> 0.12774392 | ... AG39: =+AG38/AG$30 -> 0.13585781
A40: Restructuring | B40: 0 | C40: 0 | D40: 2 | E40: 2 | F40: 13 | G40: 12 | H40: 14 | I40: 12 | J40: 4 | K40: 6 | Q40: 9 | R40: 8 | S40: 1 | T40: 5 | U40: 4 | V40: 51 | W40: 20 | X40: 20 | Y40: 20 | Z40: 20 | AA40: 20 | AB40: 20 | AC40: 20 | AD40: 20 | AE40: 20 | AF40: 20 | AG40: 20
B41: =+B40/B$30 -> 0 | C41: =+C40/C$30 -> 0 | D41: =+D40/D$30 -> 0.0003565698 | E41: =+E40/E$30 -> 0.00033938571 | F41: =+F40/F$30 -> 0.0021601861 | G41: =+G40/G$30 -> 0.0018662519 | H41: =+H40/H$30 -> 0.0021729008 | I41: =+I40/I$30 -> 0.0019005385 | ... K41: =+K40/K$30 -> 0.00089766607 | Q41: =+Q40/Q$30 -> 0.00059140492 | R41: =+R40/R$30 -> 0.0004461547 | S41: =+S40/S$30 -> 5.0766575e-05 | T41: =+T40/T$30 -> 0.00024478606 | U41: =+U40/U$30 -> 0.00018129901 | V41: =+V40/V$30 -> 0.0020234883 | W41: =+W40/W$30 -> 0.00075573794 | X41: =+X40/X$30 -> 0.00067476602 | ... AG41: =+AG40/AG$30 -> 0.00033470978
A42: Loss from divesture | B42: -2 | C42: 58 | D42: 6 | E42: 20 | F42: 2 | G42: 24 | H42: 213 | I42: 9 | J42: -26 | K42: 10 | Q42: 35 | R42: -16 | S42: 62 | T42: 243 | U42: 82 | V42: 248 | W42: 50 | X42: 50 | Y42: 50 | Z42: 50 | AA42: 50 | AB42: 50 | AC42: 50 | AD42: 50 | AE42: 50 | AF42: 50 | AG42: 50
B43: =+B42/B$30 -> -0.00038767203 | C43: =+C42/C$30 -> 0.010736764 | D43: =+D42/D$30 -> 0.0010697094 | E43: =+E42/E$30 -> 0.0033938571 | F43: =+F42/F$30 -> 0.00033233632 | G43: =+G42/G$30 -> 0.0037325039 | H43: =+H42/H$30 -> 0.033059134 | I43: =+I42/I$30 -> 0.0014254039 | ... K43: =+K42/K$30 -> 0.0014961101 | Q43: =+Q42/Q$30 -> 0.002299908 | R43: =+R42/R$30 -> -0.00089230941 | S43: =+S42/S$30 -> 0.0031475277 | T43: =+T42/T$30 -> 0.011896602 | U43: =+U42/U$30 -> 0.0037166297 | V43: =+V42/V$30 -> 0.009839708 | W43: =+W42/W$30 -> 0.0018893449 | X43: =+X42/X$30 -> 0.001686915 | ... AG43: =+AG42/AG$30 -> 0.00083677444
A44: OP Exp | B44: =+B42+B40+B38+B36 -> 1003 | C44: =+C42+C40+C38+C36 -> 1102 | D44: =+D42+D40+D38+D36 -> 1091 | E44: =+E42+E40+E38+E36 -> 1421 | F44: =+F42+F40+F38+F36 -> 1393 | G44: =+G42+G40+G38+G36 -> 1476 | H44: =+H42+H40+H38+H36 -> 1621 | I44: =+I42+I40+I38+I36 -> 1465 | ... K44: =+K42+K40+K38+K36 -> 1476 | Q44: =+Q42+Q40+Q38+Q36 -> 3443 | R44: =+R42+R40+R38+R36 -> 3855 | S44: =+S42+S40+S38+S36 -> 4039 | T44: =+T42+T40+T38+T36 -> 4245 | U44: =+U42+U40+U38+U36 -> 4617 | V44: =+V42+V40+V38+V36 -> 5884 | W44: =+W42+W40+W38+W36 -> 6492.75 | X44: =+X42+X40+X38+X36 -> 7456.1625 | ... AG44: =+AG42+AG40+AG38+AG36 -> 15906.092
B45: =+B44/B$30 -> 0.19441752 | C45: =+C44/C$30 -> 0.20399852 | D45: =+D44/D$30 -> 0.19450883 | E45: =+E44/E$30 -> 0.24113355 | F45: =+F44/F$30 -> 0.23147225 | G45: =+G44/G$30 -> 0.22954899 | H45: =+H44/H$30 -> 0.25159087 | I45: =+I44/I$30 -> 0.23202407 | ... K45: =+K44/K$30 -> 0.22082585 | Q45: =+Q44/Q$30 -> 0.22624524 | R45: =+R44/R$30 -> 0.2149908 | S45: =+S44/S$30 -> 0.2050462 | T45: =+T44/T$30 -> 0.20782336 | U45: =+U44/U$30 -> 0.20926438 | V45: =+V44/V$30 -> 0.23345501 | W45: =+W44/W$30 -> 0.24534088 | X45: =+X44/X$30 -> 0.25155825 | ... AG45: =+AG44/AG$30 -> 0.26619623
A46: EBIT | B46: =+B34-B44 -> 1016 | C46: =+C34-C44 -> 1009 | D46: =+D34-D44 -> 1119 | E46: =+E34-E44 -> 919 | F46: =+F34-F44 -> 1013 | G46: =+G34-G44 -> 1151 | H46: =+H34-H44 -> 989 | I46: =+I34-I44 -> 1156 | ... K46: =+K34-K44 -> 1253 | Q46: =+Q34-Q44 -> 2434 | R46: =+R34-R44 -> 2965 | S46: =+S34-S44 -> 3365 | T46: =+T34-T44 -> 3575 | U46: =+U34-U44 -> 4063 | V46: =+V34-V44 -> 4308 | W46: =+W34-W44 -> 4225.251 | X46: =+X34-X44 -> 4696.1981 | ... AG46: =+AG34-AG44 -> 11281.641
B47: =+B46/B$30 -> 0.19693739 | C47: =+C46/C$30 -> 0.18678267 | D47: =+D46/D$30 -> 0.1995008 | E47: =+E46/E$30 -> 0.15594773 | F47: =+F46/F$30 -> 0.16832835 | G47: =+G46/G$30 -> 0.17900467 | H47: =+H46/H$30 -> 0.15349992 | I47: =+I46/I$30 -> 0.18308521 | ... K47: =+K46/K$30 -> 0.1874626 | Q47: =+Q46/Q$30 -> 0.15994217 | R47: =+R46/R$30 -> 0.16535609 | S47: =+S46/S$30 -> 0.17082953 | T47: =+T46/T$30 -> 0.17502203 | U47: =+U46/U$30 -> 0.18415447 | V47: =+V46/V$30 -> 0.17092525 | W47: =+W46/W$30 -> 0.15965912 | X47: =+X46/X$30 -> 0.15844175 | ... AG47: =+AG46/AG$30 -> 0.18880377
A48: Interest Exp | B48: -130 | C48: -136 | D48: -131 | E48: -201 | F48: -232 | G48: -232 | H48: -225 | I48: -223 | J48: -225 | K48: -233 | Q48: -425 | R48: -365 | S48: -378 | T48: -500 | U48: -598 | V48: -912 | W48: =+V95*$AJ$69 -> -454.12 | X48: =+W95*$AJ$69 -> -393.4819 | Y48: =+X95*$AJ$69 -> -324.33844 | Z48: =+Y95*$AJ$69 -> -247.7953 | AA48: =+Z95*$AJ$69 -> -158.87699 | AB48: =+AA95*$AJ$69 -> -58.441867 | AC48: =+AB95*$AJ$69 -> 52.023335 | AD48: =+AC95*$AJ$69 -> 170.33154 | ... AG48: =+AF95*$AJ$69 -> 609.47714
B49: =+B48/B$30 -> -0.025198682 | C49: =+C48/C$30 -> -0.025175861 | D49: =+D48/D$30 -> -0.023355322 | E49: =+E48/E$30 -> -0.034108264 | F49: =+F48/F$30 -> -0.038551014 | G49: =+G48/G$30 -> -0.036080871 | H49: =+H48/H$30 -> -0.03492162 | I49: =+I48/I$30 -> -0.03531834 | ... K49: =+K48/K$30 -> -0.034859366 | Q49: =+Q48/Q$30 -> -0.027927454 | R49: =+R48/R$30 -> -0.020355808 | S49: =+S48/S$30 -> -0.019189765 | T49: =+T48/T$30 -> -0.024478606 | U49: =+U48/U$30 -> -0.027104202 | V49: =+V48/V$30 -> -0.036184733 | W49: =+W48/W$30 -> -0.017159786 | X49: =+X48/X$30 -> -0.013275411 | ... AG49: =+AG48/AG$30 -> 0.010199898
A50: Other | B50: =-19+2 -> -17 | C50: =+22-1 -> 21 | D50: =+1+6 -> 7 | E50: -18 | F50: 7 | G50: 9 | H50: =+4+7 -> 11 | I50: =-1+4 -> 3 | J50: 3 | K50: 4 | Q50: =-53-68+5 -> -116 | R50: =-220-36+5 -> -251 | S50: =-67-2 -> -69 | T50: =-60+6 -> -54 | U50: =+4-11 -> -7 | V50: =+10+20 -> 30 | W50: 20 | X50: 20 | Y50: 20 | Z50: 20 | AA50: 20 | AB50: 20 | AC50: 20 | AD50: 20 | AE50: 20 | AF50: 20 | AG50: 20
B51: =+B50/B$30 -> -0.0032952123 | C51: =+C50/C$30 -> 0.0038874491 | D51: =+D50/D$30 -> 0.0012479943 | E51: =+E50/E$30 -> -0.0030544714 | F51: =+F50/F$30 -> 0.0011631771 | G51: =+G50/G$30 -> 0.001399689 | H51: =+H50/H$30 -> 0.0017072792 | I51: =+I50/I$30 -> 0.00047513462 | ... K51: =+K50/K$30 -> 0.00059844405 | Q51: =+Q50/Q$30 -> -0.0076225522 | R51: =+R50/R$30 -> -0.013998104 | S51: =+S50/S$30 -> -0.0035028937 | T51: =+T50/T$30 -> -0.0026436894 | U51: =+U50/U$30 -> -0.00031727326 | V51: =+V50/V$30 -> 0.0011902873 | W51: =+W50/W$30 -> 0.00075573794 | X51: =+X50/X$30 -> 0.00067476602 | ... AG51: =+AG50/AG$30 -> 0.00033470978
A52: EBT | B52: =+B46+B48+B50 -> 869 | C52: =+C46+C48+C50 -> 894 | D52: =+D46+D48+D50 -> 995 | E52: =+E46+E48+E50 -> 700 | F52: =+F46+F48+F50 -> 788 | G52: =+G46+G48+G50 -> 928 | H52: =+H46+H48+H50 -> 775 | I52: =+I46+I48+I50 -> 936 | ... K52: =+K46+K48+K50 -> 1024 | Q52: =+Q46+Q48+Q50 -> 1893 | R52: =+R46+R48+R50 -> 2349 | S52: =+S46+S48+S50 -> 2918 | T52: =+T46+T48+T50 -> 3021 | U52: =+U46+U48+U50 -> 3458 | V52: =+V46+V48+V50 -> 3426 | W52: =+W46+W48+W50 -> 3791.131 | X52: =+X46+X48+X50 -> 4322.7162 | ... AG52: =+AG46+AG48+AG50 -> 11911.118
B53: =+B52/B$30 -> 0.1684435 | C53: =+C52/C$30 -> 0.16549426 | D53: =+D52/D$30 -> 0.17739347 | E53: =+E52/E$30 -> 0.118785 | F53: =+F52/F$30 -> 0.13094051 | G53: =+G52/G$30 -> 0.14432348 | H53: =+H52/H$30 -> 0.12028558 | I53: =+I52/I$30 -> 0.148242 | ... K53: =+K52/K$30 -> 0.15320168 | Q53: =+Q52/Q$30 -> 0.12439217 | R53: =+R52/R$30 -> 0.13100218 | S53: =+S52/S$30 -> 0.14813687 | T53: =+T52/T$30 -> 0.14789974 | U53: =+U52/U$30 -> 0.15673299 | V53: =+V52/V$30 -> 0.1359308 | W53: =+W52/W$30 -> 0.14325508 | X53: =+X52/X$30 -> 0.1458411 | ... AG53: =+AG52/AG$30 -> 0.19933838
A54: Taxes | B54: 162 | C54: 214 | D54: 235 | E54: 102 | F54: 151 | G54: 201 | H54: 172 | I54: 193 | J54: 168 | K54: 238 | Q54: 397 | R54: 532 | S54: 678 | T54: 745 | U54: 713 | V54: 717 | W54: =+W52*0.2 -> 758.2262 | X54: =+X52*0.2 -> 864.54325 | Y54: =+Y52*0.2 -> 957.03929 | Z54: =+Z52*0.2 -> 1111.7289 | AA54: =+AA52*0.2 -> 1255.689 | AB54: =+AB52*0.2 -> 1381.065 | AC54: =+AC52*0.2 -> 1479.1025 | AD54: =+AD52*0.2 -> 1580.4323 | ... AG54: =+AG52*0.2 -> 2382.2236
B55: =+B54/B$30 -> 0.031401434 | C55: =+C54/C$30 -> 0.039614957 | D55: =+D54/D$30 -> 0.041896951 | E55: =+E54/E$30 -> 0.017308671 | F55: =+F54/F$30 -> 0.025091392 | G55: =+G54/G$30 -> 0.03125972 | H55: =+H54/H$30 -> 0.026695639 | I55: =+I54/I$30 -> 0.030566994 | ... K55: =+K54/K$30 -> 0.035607421 | Q55: =+Q54/Q$30 -> 0.026087528 | R55: =+R54/R$30 -> 0.029669288 | S55: =+S54/S$30 -> 0.034419738 | T55: =+T54/T$30 -> 0.036473122 | U55: =+U54/U$30 -> 0.032316548 | V55: =+V54/V$30 -> 0.028447865 | W55: =+W54/W$30 -> 0.028651015 | X55: =+X54/X$30 -> 0.02916822 | ... AG55: =+AG54/AG$30 -> 0.039867676
A56: Net Income | B56: =+B52-B54 -> 707 | C56: =+C52-C54 -> 680 | D56: =+D52-D54 -> 760 | E56: =+E52-E54 -> 598 | F56: =+F52-F54 -> 637 | G56: =+G52-G54 -> 727 | H56: =+H52-H54 -> 603 | I56: =+I52-I54 -> 743 | ... K56: =+K52-K54 -> 786 | Q56: =+Q52-Q54 -> 1496 | R56: =+R52-R54 -> 1817 | S56: =+S52-S54 -> 2240 | T56: =+T52-T54 -> 2276 | U56: =+U52-U54 -> 2745 | V56: =+V52-V54 -> 2709 | W56: =+W52-W54 -> 3032.9048 | X56: =+X52-X54 -> 3458.173 | ... AG56: =+AG52-AG54 -> 9528.8943
B57: =+B56/B$30 -> 0.13704206 | C57: =+C56/C$30 -> 0.1258793 | D57: =+D56/D$30 -> 0.13549652 | E57: =+E56/E$30 -> 0.10147633 | F57: =+F56/F$30 -> 0.10584912 | G57: =+G56/G$30 -> 0.11306376 | H57: =+H56/H$30 -> 0.093589943 | I57: =+I56/I$30 -> 0.11767501 | ... K57: =+K56/K$30 -> 0.11759425 | Q57: =+Q56/Q$30 -> 0.098304639 | R57: =+R56/R$30 -> 0.10133289 | S57: =+S56/S$30 -> 0.11371713 | T57: =+T56/T$30 -> 0.11142661 | U57: =+U56/U$30 -> 0.12441644 | V57: =+V56/V$30 -> 0.10748294 | W57: =+W56/W$30 -> 0.11460406 | X57: =+X56/X$30 -> 0.11667288 | ... AG57: =+AG56/AG$30 -> 0.1594707
A58: NCI | B58: -1 | C58: 0 | D58: 0 | E58: 0 | F58: 0 | G58: 1 | H58: 0 | I58: 0 | J58: 0 | K58: 1 | Q58: 0 | R58: 1 | S58: 2 | T58: -28 | U58: -1 | V58: 1 | W58: 1 | X58: 1 | Y58: 1 | Z58: 1 | AA58: 1 | AB58: 1 | AC58: 1 | AD58: 1 | AE58: 1 | AF58: 1 | AG58: 1
B59: =+B58/B$30 -> -0.00019383601 | C59: =+C58/C$30 -> 0 | D59: =+D58/D$30 -> 0 | E59: =+E58/E$30 -> 0 | F59: =+F58/F$30 -> 0 | G59: =+G58/G$30 -> 0.000155521 | H59: =+H58/H$30 -> 0 | I59: =+I58/I$30 -> 0 | ... K59: =+K58/K$30 -> 0.00014961101 | Q59: =+Q58/Q$30 -> 0 | R59: =+R58/R$30 -> 5.5769338e-05 | S59: =+S58/S$30 -> 0.00010153315 | T59: =+T58/T$30 -> -0.0013708019 | U59: =+U58/U$30 -> -4.5324752e-05 | V59: =+V58/V$30 -> 3.9676242e-05 | W59: =+W58/W$30 -> 3.7786897e-05 | X59: =+X58/X$30 -> 3.3738301e-05 | ... AG59: =+AG58/AG$30 -> 1.6735489e-05
A60: Net Income WM | B60: =+B56-B58 -> 708 | C60: =+C56-C58 -> 680 | D60: =+D56-D58 -> 760 | E60: =+E56-E58 -> 598 | F60: =+F56-F58 -> 637 | G60: =+G56-G58 -> 726 | H60: =+H56-H58 -> 603 | I60: =+I56-I58 -> 743 | ... K60: =+K56-K58 -> 785 | Q60: =+Q56-Q58 -> 1496 | R60: =+R56-R58 -> 1816 | S60: =+S56-S58 -> 2238 | T60: =+T56-T58 -> 2304 | U60: =+U56-U58 -> 2746 | V60: =+V56-V58 -> 2708 | W60: =+W56-W58 -> 3031.9048 | X60: =+X56-X58 -> 3457.173 | ... AG60: =+AG56-AG58 -> 9527.8943 | AH60: =+AG60*(1+$AJ$67) -> 9718.4522 | AI60: =+AH60*(1+$AJ$67) -> 9912.8212 | AJ60: =+AI60*(1+$AJ$67) -> 10111.078 | AK60: =+AJ60*(1+$AJ$67) -> 10313.299 | AL60: =+AK60*(1+$AJ$67) -> 10519.565 | AM60: =+AL60*(1+$AJ$67) -> 10729.956 | AN60: =+AM60*(1+$AJ$67) -> 10944.556 | AO60: =+AN60*(1+$AJ$67) -> 11163.447 | ... CU60: =+CT60*(1+$AJ$67) -> 35205.318
B61: =+B60/B$30 -> 0.1372359 | C61: =+C60/C$30 -> 0.1258793 | D61: =+D60/D$30 -> 0.13549652 | E61: =+E60/E$30 -> 0.10147633 | F61: =+F60/F$30 -> 0.10584912 | G61: =+G60/G$30 -> 0.11290824 | H61: =+H60/H$30 -> 0.093589943 | I61: =+I60/I$30 -> 0.11767501 | ... K61: =+K60/K$30 -> 0.11744464 | Q61: =+Q60/Q$30 -> 0.098304639 | R61: =+R60/R$30 -> 0.10127712 | S61: =+S60/S$30 -> 0.1136156 | T61: =+T60/T$30 -> 0.11279742 | U61: =+U60/U$30 -> 0.12446177 | V61: =+V60/V$30 -> 0.10744326 | W61: =+W60/W$30 -> 0.11456627 | X61: =+X60/X$30 -> 0.11663914 | ... AG61: =+AG60/AG$30 -> 0.15945397
A62: EPS | B62: =+B60/B64 -> 1.7529091 | C62: =+C60/C64 -> 1.6865079 | D62: =+D60/D64 -> 1.8849206 | E62: =+E60/E64 -> 1.481665 | F62: =+F60/F64 -> 1.5771231 | G62: =+G60/G64 -> 1.7956963 | H62: =+H60/H64 -> 1.4914667 | I62: =+I60/I64 -> 1.8368356 | ... K62: =+K60/K64 -> 1.9507952 | Q62: =+Q60/Q64 -> 3.519172 | R62: =+R60/R64 -> 4.2941594 | S62: =+S60/S64 -> 5.3927711 | T62: =+T60/T64 -> 5.6623249 | U62: =+U60/U64 -> 6.8054523 | V62: =+V60/V64 -> 6.6996536 | W62: =+W60/W64 -> 7.5767692 | X62: =+X60/X64 -> 8.7267877 | ... AG62: =+AG60/AG64 -> 26.327734
F63: =+F62/B62-1 -> -0.10028249 | G63: =+G62/C62-1 -> 0.064742256 | H63: =+H62/D62-1 -> -0.20873765 | I63: =+I62/E62-1 -> 0.23971045 | J63: =+J62/F62-1 -> 0.13360453 | K63: =+K62/G62-1 -> 0.086372605 | R63: =+R62/Q62-1 -> 0.22021868 | S63: =+S62/R62-1 -> 0.2558386 | T63: =+T62/S62-1 -> 0.049984286 | U63: =+U62/T62-1 -> 0.20188305 | V63: =+V62/U62-1 -> -0.015546161 | W63: =+W62/V62-1 -> 0.13091954 | X63: =+X62/W62-1 -> 0.15178218 | Y63: =+Y62/X62-1 -> 0.1182013 | ... AG63: =+AG62/AF62-1 -> 0.15241614
A64: Shares | B64: 403.9 | C64: 403.2 | D64: 403.2 | E64: 403.6 | F64: 403.9 | G64: 404.3 | H64: 404.3 | I64: 404.5 | J64: 404.4 | K64: 402.4 | Q64: 425.1 | R64: 422.9 | S64: 415 | T64: 406.9 | U64: 403.5 | V64: 404.2 | W64: =+V64*0.99 -> 400.158 | X64: =+W64*0.99 -> 396.15642 | Y64: =+X64*0.99 -> 392.19486 | Z64: =+Y64*0.99 -> 388.27291 | AA64: =+Z64*0.99 -> 384.39018 | AB64: =+AA64*0.99 -> 380.54628 | AC64: =+AB64*0.99 -> 376.74081 | AD64: =+AC64*0.99 -> 372.97341 | ... AG64: =+AF64*0.99 -> 361.89572
C65: =+C64/B64-1 -> -0.0017331023 | D65: =+D64/C64-1 -> 0 | E65: =+E64/D64-1 -> 0.00099206349 | F65: =+F64/E64-1 -> 0.00074331021 | G65: =+G64/F64-1 -> 0.00099034414 | H65: =+H64/G64-1 -> 0 | I65: =+I64/H64-1 -> 0.00049468217 | J65: =+J64/I64-1 -> -0.00024721879 | K65: =+K64/J64-1 -> -0.0049455984 | R65: =+R64/Q64-1 -> -0.0051752529 | S65: =+S64/R64-1 -> -0.018680539 | T65: =+T64/S64-1 -> -0.019518072 | U65: =+U64/T64-1 -> -0.0083558614 | V65: =+V64/U64-1 -> 0.0017348203 | W65: =+W64/V64-1 -> -0.01 | X65: =+X64/W64-1 -> -0.01 | Y65: =+Y64/X64-1 -> -0.01 | ... AG65: =+AG64/AF64-1 -> -0.01
AL66: Gordon Growth Model
A67: Gross Margin | B67: =+B34/B30 -> 0.39135491 | C67: =+C34/C30 -> 0.39078119 | D67: =+D34/D30 -> 0.39400963 | E67: =+E34/E30 -> 0.39708128 | F67: =+F34/F30 -> 0.3998006 | G67: =+G34/G30 -> 0.40855365 | H67: =+H34/H30 -> 0.4050908 | I67: =+I34/I30 -> 0.41510928 | ... K67: =+K34/K30 -> 0.40828845 | Q67: =+Q34/Q30 -> 0.38618741 | R67: =+R34/R30 -> 0.38034689 | S67: =+S34/S30 -> 0.37587572 | T67: =+T34/T30 -> 0.38284539 | U67: =+U34/U30 -> 0.39341885 | V67: =+V34/V30 -> 0.40438026 | W67: =+W34/W30 -> 0.405 | X67: =+X34/X30 -> 0.41 | ... AG67: =+AG34/AG30 -> 0.455 | AI67: Terminal | AJ67: 0.02 | AL67: Sustained growth | AM67: =+(1-AM68)*V81 -> 0.048373241 | AO67: EV | AP67: =+AM69 -> 107276.72
A68: OP Margin | B68: =+B46/B30 -> 0.19693739 | C68: =+C46/C30 -> 0.18678267 | D68: =+D46/D30 -> 0.1995008 | E68: =+E46/E30 -> 0.15594773 | F68: =+F46/F30 -> 0.16832835 | G68: =+G46/G30 -> 0.17900467 | H68: =+H46/H30 -> 0.15349992 | I68: =+I46/I30 -> 0.18308521 | ... K68: =+K46/K30 -> 0.1874626 | Q68: =+Q46/Q30 -> 0.15994217 | R68: =+R46/R30 -> 0.16535609 | S68: =+S46/S30 -> 0.17082953 | T68: =+T46/T30 -> 0.17502203 | U68: =+U46/U30 -> 0.18415447 | V68: =+V46/V30 -> 0.17092525 | W68: =+W46/W30 -> 0.15965912 | X68: =+X46/X30 -> 0.15844175 | ... AG68: =+AG46/AG30 -> 0.18880377 | AI68: Discount | AJ68: =+Main!E9 -> 0.066275701 | AL68: Payout ratio | AM68: =+(SUM(H163:K163)+SUM(H165:K165)-SUM(H161:K161))/SUM(H60:K60) -> 0.83707078 | AO68: Shares | AP68: =+Main!F2 -> 399.71518
A69: NI Margin | B69: =+B60/B30 -> 0.1372359 | C69: =+C60/C30 -> 0.1258793 | D69: =+D60/D30 -> 0.13549652 | E69: =+E60/E30 -> 0.10147633 | F69: =+F60/F30 -> 0.10584912 | G69: =+G60/G30 -> 0.11290824 | H69: =+H60/H30 -> 0.093589943 | I69: =+I60/I30 -> 0.11767501 | ... K69: =+K60/K30 -> 0.11744464 | Q69: =+Q60/Q30 -> 0.098304639 | R69: =+R60/R30 -> 0.10127712 | S69: =+S60/S30 -> 0.1136156 | T69: =+T60/T30 -> 0.11279742 | U69: =+U60/U30 -> 0.12446177 | V69: =+V60/V30 -> 0.10744326 | W69: =+W60/W30 -> 0.11456627 | X69: =+X60/X30 -> 0.11663914 | ... AG69: =+AG60/AG30 -> 0.15945397 | AI69: ROIC | AJ69: 0.02 | AL69: Equity Value | AM69: =+(SUM(H168:K168)*(1+AM67))/(Main!B9-AM67) -> 107276.72 | AO69: Price | AP69: =+AP67/AP68 -> 268.3829
A70: Tax Rate | B70: =+B54/B52 -> 0.18642117 | C70: =+C54/C52 -> 0.2393736 | D70: =+D54/D52 -> 0.2361809 | E70: =+E54/E52 -> 0.14571429 | F70: =+F54/F52 -> 0.19162437 | G70: =+G54/G52 -> 0.21659483 | H70: =+H54/H52 -> 0.22193548 | I70: =+I54/I52 -> 0.20619658 | ... K70: =+K54/K52 -> 0.23242188 | Q70: =+Q54/Q52 -> 0.20972002 | R70: =+R54/R52 -> 0.22647935 | S70: =+S54/S52 -> 0.23235093 | T70: =+T54/T52 -> 0.24660708 | U70: =+U54/U52 -> 0.20618855 | V70: =+V54/V52 -> 0.20928196 | W70: =+W54/W52 -> 0.2 | X70: =+X54/X52 -> 0.2 | ... AG70: =+AG54/AG52 -> 0.2 | AI70: NPV | AJ70: =+NPV(AJ68,W60:CU60) -> 138759.71 | AL70: Just. P/E | AM70: =+AM68*(1+AM67)/(Main!B9-AM67) -> 37.588199 | AP70: =+AP69/Main!F1-1 -> 0.19281287
A71: Inc Margin | R71: =+(R46-Q46)/(R30-Q30) -> 0.19572429 | S71: =+(S46-R46)/(S30-R30) -> 0.22637238 | T71: =+(T46-S46)/(T30-S30) -> 0.28846154 | U71: =+(U46-T46)/(U30-T30) -> 0.29810629 | V71: =+(V46-U46)/(V30-U30) -> 0.078000637 | W71: =+(W46-V46)/(W30-V30) -> -0.065663387 | X71: =+(X46-W46)/(X30-W30) -> 0.14829693 | Y71: =+(Y46-X46)/(Y30-X30) -> 0.12064104 | ... AG71: =+(AG46-AF46)/(AG30-AF30) -> 0.3335194 | AI71: Share | AJ71: =+AJ70/Main!F2 -> 347.14645
AI72: Diff | AJ72: =+AJ71/Main!F1-1 -> 0.54287311 | AL72: Dividend Yield | AM72: =+SUM(H76:K76)/SUM(H65:K65) -> 0
A73: Dividends | B73: 0.75 | C73: 0.75 | D73: 0.75 | E73: 0.75 | F73: 0.825 | G73: 0.825 | H73: 0.825 | I73: 0.825 | J73: 0.945 | K73: 0.945 | L73: 0.945 | M73: 0.945 | R73: =+0.575*4 -> 2.3 | S73: =+0.65*4 -> 2.6 | T73: =+0.7*4 -> 2.8 | U73: =+SUM(B73:E73) -> 3 | V73: =+SUM(F73:I73) -> 3.3 | W73: =+SUM(J73:M73) -> 3.78 | AL73: Debt-to-EBITDA | AM73: =+(K117-K97)/SUM(H94:K94) -> 3.0598577
S74: =+S73/R73-1 -> 0.13043478 | T74: =+T73/S73-1 -> 0.076923077 | U74: =+U73/T73-1 -> 0.071428571 | V74: =+V73/U73-1 -> 0.1 | W74: =+W73/V73-1 -> 0.14545455
A75: BVPS | B75: =+B128/B64 -> 17.534043 | C75: =+C128/C64 -> 18.494544 | D75: =+D128/D64 -> 19.789187 | E75: =+E128/E64 -> 20.445986 | F75: =+F128/F64 -> 21.416192 | G75: =+G128/G64 -> 22.757853 | H75: =+H128/H64 -> 23.544398 | I75: =+I128/I64 -> 24.697157 | ... K75: =+K128/K64 -> 24.664513 | Q75: =+Q128/Q64 -> 17.529993 | R75: =+R128/R64 -> 16.84559 | S75: =+S128/S64 -> 16.503614 | T75: =+T128/T64 -> 16.964856 | U75: =+U128/U64 -> 20.451053 | V75: =+V128/V64 -> 24.715487
A78: Net Income / PPE | B78: =+(B60*4)/B105 -> 0.16615818 | C78: =+(C60*4)/C105 -> 0.15614237 | D78: =+(D60*4)/D105 -> 0.16953879 | E78: =+(E60*4)/E105 -> 0.12368149 | F78: =+(F60*4)/F105 -> 0.13031248 | G78: =+(G60*4)/G105 -> 0.14546912 | H78: =+(H60*4)/H105 -> 0.12018536 | I78: =+(I60*4)/I105 -> 0.14584356 | ... K78: =+(K60*4)/K105 -> 0.15362035 | Q78: =+(Q60)/Q105 -> 0.10573933 | R78: =+(R60)/R105 -> 0.12594493 | S78: =+(S60)/S105 -> 0.14237547 | T78: =+(T60)/T105 -> 0.13578501 | U78: =+(U60)/U105 -> 0.14198552 | V78: =+(V60)/V105 -> 0.13288841
F79: =+(F78-B78)*100 -> -3.5845695 | G79: =+(G78-C78)*100 -> -1.0673247 | H79: =+(H78-D78)*100 -> -4.9353427 | I79: =+(I78-E78)*100 -> 2.2162068 | J79: =+(J78-F78)*100 -> 1.1905367 | K79: =+(K78-G78)*100 -> 0.81512344 | R79: =+(R78-Q78)*100 -> 2.0205607 | S79: =+(S78-R78)*100 -> 1.6430535 | T79: =+(T78-S78)*100 -> -0.65904621 | U79: =+(U78-T78)*100 -> 0.62005152 | V79: =+(V78-U78)*100 -> -0.90971132
A81: ROE | C81: =+(C60*4)/AVERAGE(B128:C128) -> 0.37416604 | D81: =+(D60*4)/AVERAGE(C128:D128) -> 0.39388443 | E81: =+(E60*4)/AVERAGE(D128:E128) -> 0.29474462 | F81: =+(F60*4)/AVERAGE(E128:F128) -> 0.30150278 | G81: =+(G60*4)/AVERAGE(F128:G128) -> 0.32535992 | H81: =+(H60*4)/AVERAGE(G128:H128) -> 0.25769231 | I81: =+(I60*4)/AVERAGE(H128:I128) -> 0.30467989 | J81: =+(J60*4)/AVERAGE(I128:J128) -> 0.28904103 | K81: =+(K60*4)/AVERAGE(J128:K128) -> 0.3148501 | R81: =+R60/AVERAGE(Q128:R128) -> 0.24917673 | S81: =+S60/AVERAGE(R128:S128) -> 0.32033207 | T81: =+T60/AVERAGE(S128:T128) -> 0.33507853 | U81: =+U60/AVERAGE(T128:U128) -> 0.36238865 | V81: =+V60/AVERAGE(U128:V128) -> 0.29689727
A82: ROA | C82: =+(C60*4)/AVERAGE(B111:C111) -> 0.08160204 | D82: =+(D60*4)/AVERAGE(C111:D111) -> 0.088463385 | E82: =+(E60*4)/AVERAGE(D111:E111) -> 0.060330151 | F82: =+(F60*4)/AVERAGE(E111:F111) -> 0.05722435 | G82: =+(G60*4)/AVERAGE(F111:G111) -> 0.065106268 | H82: =+(H60*4)/AVERAGE(G111:H111) -> 0.054062535 | I82: =+(I60*4)/AVERAGE(H111:I111) -> 0.065793697 | J82: =+(J60*4)/AVERAGE(I111:J111) -> 0.063188944 | K82: =+(K60*4)/AVERAGE(J111:K111) -> 0.068156412 | R82: =+R60/AVERAGE(Q111:R111) -> 0.062146984 | S82: =+S60/AVERAGE(R111:S111) -> 0.074027429 | T82: =+T60/AVERAGE(S111:T111) -> 0.071786802 | U82: =+U60/AVERAGE(T111:U111) -> 0.070965164 | V82: =+V60/AVERAGE(U111:V111) -> 0.059910113
A83: Asset Turnover | C83: =+(C30*4)/AVERAGE(B111:C111) -> 0.64825621 | D83: =+(D30*4)/AVERAGE(C111:D111) -> 0.65288306 | E83: =+(E30*4)/AVERAGE(D111:E111) -> 0.59452438 | F83: =+(F30*4)/AVERAGE(E111:F111) -> 0.54062188 | G83: =+(G30*4)/AVERAGE(F111:G111) -> 0.5766299 | H83: =+(H30*4)/AVERAGE(G111:H111) -> 0.57765326 | I83: =+(I30*4)/AVERAGE(H111:I111) -> 0.5591136 | J83: =+(J30*4)/AVERAGE(I111:J111) -> 0.54422898 | K83: =+(K30*4)/AVERAGE(J111:K111) -> 0.58032798 | R83: =+R30/AVERAGE(Q111:R111) -> 0.61363302 | S83: =+S30/AVERAGE(R111:S111) -> 0.65156045 | T83: =+T30/AVERAGE(S111:T111) -> 0.6364224 | U83: =+U30/AVERAGE(T111:U111) -> 0.5701764 | V83: =+V30/AVERAGE(U111:V111) -> 0.55759767
A84: Financial Leverage | C84: =+AVERAGE(B111:C111)/AVERAGE(B128:C128) -> 4.5852535 | D84: =+AVERAGE(C111:D111)/AVERAGE(C128:D128) -> 4.4525136 | E84: =+AVERAGE(D111:E111)/AVERAGE(D128:E128) -> 4.8855277 | F84: =+AVERAGE(E111:F111)/AVERAGE(E128:F128) -> 5.2687848 | G84: =+AVERAGE(F111:G111)/AVERAGE(F128:G128) -> 4.9973671 | H84: =+AVERAGE(G111:H111)/AVERAGE(G128:H128) -> 4.7665598 | I84: =+AVERAGE(H111:I111)/AVERAGE(H128:I128) -> 4.630837 | J84: =+AVERAGE(I111:J111)/AVERAGE(I128:J128) -> 4.5742342 | K84: =+AVERAGE(J111:K111)/AVERAGE(J128:K128) -> 4.6195227 | R84: =+AVERAGE(Q111:R111)/AVERAGE(Q128:R128) -> 4.0094742 | S84: =+AVERAGE(R111:S111)/AVERAGE(R128:S128) -> 4.3272078 | T84: =+AVERAGE(S111:T111)/AVERAGE(S128:T128) -> 4.66769 | U84: =+AVERAGE(T111:U111)/AVERAGE(T128:U128) -> 5.106571 | V84: =+AVERAGE(U111:V111)/AVERAGE(U128:V128) -> 4.9557121
A85: Financial Leverage % | C85: =+C81-C82 -> 0.292564 | D85: =+D81-D82 -> 0.30542104 | E85: =+E81-E82 -> 0.23441447 | F85: =+F81-F82 -> 0.24427843 | G85: =+G81-G82 -> 0.26025366 | H85: =+H81-H82 -> 0.20362977 | I85: =+I81-I82 -> 0.23888619 | J85: =+J81-J82 -> 0.22585208 | K85: =+K81-K82 -> 0.24669368 | R85: =+R81-R82 -> 0.18702974 | S85: =+S81-S82 -> 0.24630464 | T85: =+T81-T82 -> 0.26329173 | U85: =+U81-U82 -> 0.29142349 | V85: =+V81-V82 -> 0.23698716
AL88: Ev | AM88: =+AJ91 -> 132146.46
AI89: Terminal | AJ89: 0.02 | AL89: Debt (-) | AM89: =+Main!F5 -> 23356
A90: NWC | Q90: =+SUM(Q98,Q99,Q101,Q103)-SUM(Q113,Q114) -> 524 | R90: =+SUM(R98,R99,R101,R103)-SUM(R113,R114) -> 148 | S90: =+SUM(S98,S99,S101,S103)-SUM(S113,S114) -> -191 | T90: =+SUM(T98,T99,T101,T103)-SUM(T113,T114) -> 32 | U90: =+SUM(U98,U99,U101,U103)-SUM(U113,U114) -> 134 | V90: =+SUM(V98,V99,V101,V103)-SUM(V113,V114) -> 631 | W90: =+SUM(W98,W99,W101,W103)-SUM(W113,W114) -> 304.56273 | X90: =+SUM(X98,X99,X101,X103)-SUM(X113,X114) -> 272.3173 | ... AG90: =+SUM(AG98,AG99,AG101,AG103)-SUM(AG113,AG114) -> -625.51007 | AI90: Discount | AJ90: =+Main!E9 -> 0.066275701 | AL90: Cash (+) | AM90: =+Main!F4 -> 557
A91: NOPAT | Q91: =+Q46*(1-Q70) -> 1923.5415 | R91: =+R46*(1-R70) -> 2293.4887 | S91: =+S46*(1-S70) -> 2583.1391 | T91: =+T46*(1-T70) -> 2693.3797 | U91: =+U46*(1-U70) -> 3225.2559 | V91: =+V46*(1-V70) -> 3406.4133 | W91: =+W46*(1-W70) -> 3380.2008 | X91: =+X46*(1-X70) -> 3756.9585 | ... AG91: =+AG46*(1-AG70) -> 9025.3126 | AI91: EV | AJ91: =+NPV(AJ90,W92:AF92,AG92+AJ92) -> 132146.46 | AL91: Equity Value | AM91: =+AM88-AM89+AM90 -> 109347.46
A92: UFCF | R92: =+R91+R134-R150-(R90-Q90) -> 2764.4887 | S92: =+S91+S134-S150-(S90-R90) -> 2373.1391 | T92: =+T91+T134-T150-(T90-S90) -> 1646.3797 | U92: =+U91+U134-U150-(U90-T90) -> 2159.2559 | V92: =+V91+V134-V150-(V90-U90) -> 2545.4133 | W92: =+W91+W134-W150-(W90-V90) -> 3441.9961 | X92: =+X91+X134-X150-(X90-W90) -> 3492.8049 | Y92: =+Y91+Y134-Y150-(Y90-X90) -> 3788.1289 | ... AG92: =+AG91+AG134-AG150-(AG90-AF90) -> 8584.5434 | AI92: TV | AJ92: =+AG92*(1+AJ89)/(AJ90-AJ89) -> 189218.83 | AL92: Shares | AM92: =+Main!F2 -> 399.71518
AI93: Diff | AJ93: =+AJ91/Main!F6-1 -> 0.17218751 | AL93: Price | AM93: =+AM91/AM92 -> 273.56344
A94: EBITDA | B94: =+B46+B134 -> 1530 | C94: =+C46+C134 -> 1552 | D94: =+D46+D134 -> 1677 | E94: =+E46+E134 -> 1571 | F94: =+F46+F134 -> 1704 | G94: =+G46+G134 -> 1895 | H94: =+H46+H134 -> 1647 | I94: =+I46+I134 -> 1926 | ... K94: =+K46+K134 -> 2030 | Q94: =+Q46+Q134 -> 4105 | R94: =+R46+R134 -> 4964 | S94: =+S46+S134 -> 5403 | T94: =+T46+T134 -> 5646 | U94: =+U46+U134 -> 6330 | V94: =+V46+V134 -> 7171 | AM94: =+AM93/Main!F1-1 -> 0.21583751
A95: Net Cash | B95: =+B97-B117 -> -15776 | C95: =+C97-C117 -> -16571 | D95: =+D97-D117 -> -16039 | E95: =+E97-E117 -> -23486 | F95: =+F97-F117 -> -23621 | G95: =+G97-G117 -> -23580 | H95: =+H97-H117 -> -23187 | I95: =+I97-I117 -> -22706 | ... K95: =+K97-K117 -> -22799 | Q95: =+Q97-Q117 -> -13257 | R95: =+R97-R117 -> -13287 | S95: =+S97-S117 -> -14633 | T95: =+T97-T117 -> -15771 | U95: =+U97-U117 -> -23486 | V95: =+V97-V117 -> -22706 | W95: =+V95+W60 -> -19674.095 | X95: =+W95+X60 -> -16216.922 | Y95: =+X95+Y60 -> -12389.765 | Z95: =+Y95+Z60 -> -7943.8493 | AA95: =+Z95+AA60 -> -2922.0933 | AB95: =+AA95+AB60 -> 2601.1668 | AC95: =+AB95+AC60 -> 8516.5768 | AD95: =+AC95+AD60 -> 14837.306 | ... AG95: =+AF95+AG60 -> 40001.751
A97: Cash | B97: 322 | C97: 172 | D97: 614 | E97: 414 | F97: 216 | G97: 440 | H97: 175 | I97: 201 | J97: 158 | K97: 557 | Q97: 553 | R97: 118 | S97: 351 | T97: 458 | U97: 414 | V97: 201
A98: A/R | B98: 2530 | C98: 2728 | D98: 2841 | E98: 3272 | F98: 3260 | G98: 2407 | H98: 2297 | I98: 3435 | J98: 3372 | K98: 3495 | Q98: 2097 | R98: 2278 | S98: 2461 | T98: 2633 | U98: 3272 | V98: 3435 | W98: =+W156/365*W30 -> 3484.9227 | X98: =+X156/365*X30 -> 3862.5108 | Y98: =+Y156/365*Y30 -> 4242.3181 | Z98: =+Z156/365*Z30 -> 4616.9741 | AA98: =+AA156/365*AA30 -> 4978.4642 | AB98: =+AB156/365*AB30 -> 5318.3807 | AC98: =+AC156/365*AC30 -> 5628.2215 | AD98: =+AD156/365*AD30 -> 5955.3799 | ... AG98: =+AG156/365*AG30 -> 7050.0351
A99: Other Receivables | B99: 155 | C99: 252 | D99: 284 | E99: 415 | F99: 328 | G99: 524 | H99: 620 | I99: 620 | J99: 592 | K99: 711 | Q99: 527 | R99: 268 | S99: 291 | T99: 237 | U99: 415 | V99: 620 | W99: =+W30*0.02 -> 529.284 | X99: =+X30*0.02 -> 592.79808 | Y99: =+Y30*0.02 -> 658.00587 | Z99: =+Z30*0.02 -> 723.80646 | AA99: =+AA30*0.02 -> 788.94904 | AB99: =+AB30*0.02 -> 852.06496 | AC99: =+AC30*0.02 -> 911.70951 | AD99: =+AD30*0.02 -> 975.52917 | ... AG99: =+AG30*0.02 -> 1195.0652
Q100: =+Q99/Q$30 -> 0.034630043 | R100: =+R99/R$30 -> 0.014946183 | S100: =+S99/S$30 -> 0.014773073 | T100: =+T99/T$30 -> 0.011602859 | U100: =+U99/U$30 -> 0.018809772 | V100: =+V99/V$30 -> 0.02459927 | W100: =+W99/W$30 -> 0.02 | X100: =+X99/X$30 -> 0.02 | ... AG100: =+AG99/AG$30 -> 0.02
A101: Parts and Supplies | B101: 189 | C101: 183 | D101: 184 | E101: 206 | F101: 218 | G101: 224 | H101: 223 | I101: 225 | J101: 235 | K101: 232 | Q101: 124 | R101: 135 | S101: 164 | T101: 173 | U101: 206 | V101: 225 | W101: =+W30*0.009 -> 238.1778 | X101: =+X30*0.009 -> 266.75914 | Y101: =+Y30*0.009 -> 296.10264 | Z101: =+Z30*0.009 -> 325.71291 | AA101: =+AA30*0.009 -> 355.02707 | AB101: =+AB30*0.009 -> 383.42923 | AC101: =+AC30*0.009 -> 410.26928 | AD101: =+AD30*0.009 -> 438.98813 | ... AG101: =+AG30*0.009 -> 537.77933
Q102: =+Q101/Q$30 -> 0.0081482455 | R102: =+R101/R$30 -> 0.0075288606 | S102: =+S101/S$30 -> 0.0083257183 | T102: =+T101/T$30 -> 0.0084695976 | U102: =+U101/U$30 -> 0.0093368989 | V102: =+V101/V$30 -> 0.0089271544 | W102: =+W101/W$30 -> 0.009 | X102: =+X101/X$30 -> 0.009 | ... AG102: =+AG101/AG$30 -> 0.009
A103: Other, curr | B103: 333 | C103: 1104 | D103: 336 | E103: 467 | F103: 433 | G103: 389 | H103: 424 | I103: 429 | J103: 451 | K103: 402 | Q103: 239 | R103: 270 | S103: 284 | T103: 303 | U103: 467 | V103: 429 | W103: =+W30*0.02 -> 529.284 | X103: =+X30*0.02 -> 592.79808 | Y103: =+Y30*0.02 -> 658.00587 | Z103: =+Z30*0.02 -> 723.80646 | AA103: =+AA30*0.02 -> 788.94904 | AB103: =+AB30*0.02 -> 852.06496 | AC103: =+AC30*0.02 -> 911.70951 | AD103: =+AD30*0.02 -> 975.52917 | ... AG103: =+AG30*0.02 -> 1195.0652
Q104: =+Q103/Q$30 -> 0.015705086 | R104: =+R103/R$30 -> 0.015057721 | S104: =+S103/S$30 -> 0.014417707 | T104: =+T103/T$30 -> 0.014834035 | U104: =+U103/U$30 -> 0.021166659 | V104: =+V103/V$30 -> 0.017021108 | W104: =+W103/W$30 -> 0.02 | X104: =+X103/X$30 -> 0.02 | ... AG104: =+AG103/AG$30 -> 0.02
A105: PP&E | B105: 17044 | C105: 17420 | D105: 17931 | E105: 19340 | F105: 19553 | G105: 19963 | H105: 20069 | I105: 20378 | J105: 20335 | K105: 20440 | Q105: 14148 | R105: 14419 | S105: 15719 | T105: 16968 | U105: 19340 | V105: 20378
A106: Goodwill | B106: 9246 | C106: 9363 | D106: 9822 | E106: 13438 | F106: 13529 | G106: 13886 | H106: 13894 | I106: 13880 | J106: 13873 | K106: 14001 | Q106: 8994 | R106: 9028 | S106: 9323 | T106: 9254 | U106: 13438 | V106: 13880
A107: Intangible | B107: 728 | C107: 753 | D107: 742 | E107: 4188 | F107: 4015 | G107: 3964 | H107: 3873 | I107: 3767 | J107: 3664 | K107: 3641 | Q107: 1024 | R107: 898 | S107: 827 | T107: 759 | U107: 4188 | V107: 3767
...

Sheet Bond
A1: Main
B3: ISIN | C3: Bond Type | D3: Immediate Issuer | E3: Coupon (%) | F3: Maturity Date | G3: Callable | H3: Currency | I3: Seniority Level | J3: Yield To Worst
B4: US94106LBX64 | C4: - | D4: Waste Management, Inc. | E4: 4.95 | F4: 46571 | G4: Yes | H4: USD | I4: Senior | J4: 4.294
B5: US94106LBE83 | C5: - | D5: Waste Management, Inc. | E5: 3.15 | F5: 46706 | G5: Yes | H5: USD | I5: Senior | J5: 4.335
B6: US94106LBN82 | C6: - | D6: Waste Management, Inc. | E6: 1.15 | F6: 46827 | G6: Yes | H6: USD | I6: Senior | J6: 4.358
B7: US94106LCB36 | C7: - | D7: Waste Management, Inc. | E7: 4.5 | F7: 46827 | G7: Yes | H7: USD | I7: Senior | J7: 4.438
B8: US902917AH67 | C8: - | D8: Waste Management, Inc. | E8: 7 | F8: 46949 | G8: Yes | H8: USD | I8: Senior | J8: 4.544
B9: US858912AC34 | C9: - | D9: Stericycle, Inc. | E9: 3.875 | F9: 47133 | G9: Yes | H9: USD | I9: Senior | J9: 4.485
B10: US94106LBZ13 | C10: - | D10: Waste Management, Inc. | E10: 3.875 | F10: 47133 | G10: Yes | H10: USD | I10: Senior | J10: 4.485
B11: US94106LCA52 | C11: - | D11: Waste Management, Inc. | E11: 3.875 | F11: 47133 | G11: Yes | H11: USD | I11: Senior | J11: 4.485
B12: USU85881AC12 | C12: - | D12: Stericycle, Inc. | E12: 3.875 | F12: 47133 | G12: Yes | H12: USD | I12: Senior | J12: 4.485
B13: USU94106AK47 | C13: - | D13: Waste Management, Inc. | E13: 3.875 | F13: 47133 | G13: Yes | H13: USD | I13: Senior | J13: 4.485
B14: US94106LBV09 | C14: - | D14: Waste Management, Inc. | E14: 4.875 | F14: 47164 | G14: Yes | H14: USD | I14: Senior | J14: 4.533
B15: US94106LAG41 | C15: - | D15: Waste Management, Inc. | E15: 7.375 | F15: 47253 | G15: Yes | H15: USD | I15: Senior | J15: 5.06
... B34: US94106LCF40 | C34: - | D34: Waste Management, Inc. | E34: 5.35 | F34: 56537 | G34: Yes | H34: USD | I34: Senior | J34: 5.852
B35: US89351YAA70 | C35: - | D35: TransAmerican Waste Industries, I... | E35: 10 | F35: - | G35: -- | H35: USD | I35: - | J35: -
E37: =+AVERAGE(E4:E35) -> 4.5084063
